Workbook
Name AvgHomePrice: [3]Residential!$H$52
Name bondcapacity: #REF!
Name CFDCity: 'Land Use'!#REF!
Name CFDName: '[4]Land Use'!$D$5
Name CFDName: 'Land Use'!#REF!
Name CommunityList: #REF!
Name CommunityListCity: #REF!
Name CommunityListTax: '[4]Taxes Comps'!#REF!
Name CommunityListTax: #REF!
Name CompTaxes: #REF!
Name Construction: #REF!
Name Developer: '[4]Land Use'!$D$4
Name Developer: 'Land Use'!#REF!
Name ExhibitList: #REF!
Name k: '[2]Land Use'!$D$5
Name LandUseCopy: 'Land Use'!$F$9:$K$23
Name OandM: #REF!
Name Phase: #REF!
Name PhaseAll: #REF!
Name Project: 'Land Use'!#REF!
Name Providers: #REF!
Name SortStart: #REF!
Name Taxes: #REF!
Name Total_DU: [1]SA!$D$14

Sheet Source Use
D2: The Villages of Tortolita Community Facilities District
D3: Sources and Uses of Funds
D4: Public Infrastructure Construction
E7: Totals | F7: =AV!E7 -> 2020 | G7: =AV!F7 -> 2021 | H7: =AV!G7 -> 2022 | I7: =AV!H7 -> 2023 | J7: =AV!I7 -> 2024 | K7: =AV!J7 -> 2025 | L7: =AV!K7 -> 2026 | M7: =AV!L7 -> 2027 | ... V7: =AV!U7 -> 2036
D9: Sources of Funds
D10: Equity / Cash Flow / Loans (1) | E10: =SUM(F10:V10) -> 28209554 | F10: =F18-SUM(F11:F12) -> 19405022 | G10: =G18-SUM(G11:G12) -> -255962.69 | H10: =H18-SUM(H11:H12) -> 953001.72 | I10: =I18-SUM(I11:I12) -> -258688.66 | J10: =J18-SUM(J11:J12) -> 2296574.7 | K10: =K18-SUM(K11:K12) -> 1554908.3 | L10: =L18-SUM(L11:L12) -> 604352.38 | M10: =M18-SUM(M11:M12) -> 2938316.2 | ... V10: =V18-SUM(V11:V12) -> 0
D11: CFD Funds SA (Net) (2) | E11: =SUM(F11:V11) -> 4694300 | F11: =$C$58*$F$34*H40 -> 2143050 | G11: =$C$58*$F$34*I40 -> 0 | H11: =$C$58*$F$34*J40 -> 0 | I11: =$C$58*$F$34*K40 -> 1377675 | J11: =$C$58*$F$34*L40 -> 0 | K11: =$C$58*$F$34*M40 -> 1173575 | L11: =$C$58*$F$34*N40 -> 0 | M11: =$C$58*$F$34*O40 -> 0 | ... V11: =$C$58*$F$34*X40 -> 0
D12: CFD Funds GO (Net) (3) | E12: =SUM(F12:V12) -> 9687862.1 | F12: =AV!E$84 -> 0 | G12: =AV!F$84 -> 463540.43 | H12: =AV!G$84 -> 1328477.9 | I12: =AV!H$84 -> 1469791.1 | J12: =AV!I$84 -> 1187493 | K12: =AV!J$84 -> 1338135.5 | L12: =AV!K$84 -> 1488993.5 | M12: =AV!L$84 -> 1248375.5 | ... V12: =AV!U$84 -> 0
D13: Total Sources | E13: =SUM(F13:V13) -> 42591717 | F13: =SUM(F10:F12) -> 21548072 | G13: =SUM(G10:G12) -> 207577.74 | H13: =SUM(H10:H12) -> 2281479.6 | I13: =SUM(I10:I12) -> 2588777.5 | J13: =SUM(J10:J12) -> 3484067.7 | K13: =SUM(K10:K12) -> 4066618.8 | L13: =SUM(L10:L12) -> 2093345.8 | M13: =SUM(M10:M12) -> 4186691.7 | ... V13: =SUM(V10:V12) -> 0
D15: Uses of Funds
D16: Public Improvements | E16: =SUM(F16:V16) -> 31730299 | F16: =H71 -> 21141033 | G16: =I71 -> 0 | H16: =J71 -> 2281479.6 | I16: =K71 -> 2327109.2 | J16: =L71 -> 2960731.2 | K16: =M71 -> 3019945.8 | L16: =N71 -> 0 | M16: =O71 -> 0 | ... V16: =X71 -> 0
D17: Assessment Bond Debt Service (4) | E17: =SUM(F17:V17) -> 10861418 | F17: =H44 -> 407039.47 | G17: =I44 -> 207577.74 | H17: =J44 -> 0 | I17: =K44 -> 261668.23 | J17: =L44 -> 523336.46 | K17: =M44 -> 1046672.9 | L17: =N44 -> 2093345.8 | M17: =O44 -> 4186691.7 | ... V17: =X44 -> 0
D18: Total Uses | E18: =SUM(F18:V18) -> 42591717 | F18: =SUM(F16:F17) -> 21548072 | G18: =SUM(G16:G17) -> 207577.74 | H18: =SUM(H16:H17) -> 2281479.6 | I18: =SUM(I16:I17) -> 2588777.5 | J18: =SUM(J16:J17) -> 3484067.7 | K18: =SUM(K16:K17) -> 4066618.8 | L18: =SUM(L16:L17) -> 2093345.8 | M18: =SUM(M16:M17) -> 4186691.7 | ... V18: =SUM(V16:V17) -> 0
D20: Net Cash Flow | E20: =ROUND(E13-E18,-1) -> 0 | F20: =ROUND(F13-F18,-1) -> 0 | G20: =ROUND(G13-G18,-1) -> 0 | H20: =ROUND(H13-H18,-1) -> 0 | I20: =ROUND(I13-I18,-1) -> 0 | J20: =ROUND(J13-J18,-1) -> 0 | K20: =ROUND(K13-K18,-1) -> 0 | L20: =ROUND(L13-L18,-1) -> 0 | ... V20: =ROUND(V13-V18,-1) -> 0
F22: =(C22+F20) -> 0 | G22: =(F22+G20) -> 0 | H22: =(G22+H20) -> 0 | I22: =(H22+I20) -> 0 | P22: =(E20) -> 0
D23: Source: Applicant
D24: Footnotes
C25: 1 | D25: All improvements will be funded with internal funds, project cash flow and/or third party and/or related party loans.
C26: 2 | D26: ="Represent the net construction proceeds assuming an average "&TEXT($F$34,"$0,0")&" special assessment lien per lot." -> Represent the net construction proceeds assuming an average $6,500 special assessment lien per lot.
D27: Assessment bonds are anticipated to be issued in conjunction with the construction of a phase.
C28: 3 | D28: Represents the net construction proceeds related to the issuance of general obligation bonds. It is anticipated
D29: that general obligation bonds will be issued over time as the secondary assessed valuation of the district increases
D30: with the construction of homes and commercial buildings.
C31: 4 | D31: Assuming 12 months of capitalized interest.
D34: SA Amount | F34: 6500
D35: SA Interest | F35: 0.055
D36: Capitalized Interest | F36: 1
D37: SA Terms | F37: 25 | H37: =F7 -> 2020 | I37: =H37+1 -> 2021 | J37: =I37+1 -> 2022 | K37: =J37+1 -> 2023 | L37: =K37+1 -> 2024 | M37: =L37+1 -> 2025 | N37: =M37+1 -> 2026 | O37: =N37+1 -> 2027 | P37: =O37+1 -> 2028 | ... X37: =W37+1 -> 2036
D38: Lot Sales | F38: 0 | I38: 420 | J38: 0 | L38: 0 | M38: 230 | N38: 0 | O38: 0 | P38: 270 | Q38: =AV!N34 -> 0 | R38: =AV!O34 -> 0 | S38: =AV!P34 -> 0 | T38: =AV!Q34 -> 0 | U38: =AV!R34 -> 0 | V38: =AV!S34 -> 0 | W38: =AV!T34 -> 0 | X38: =AV!U34 -> 0
D39: Cumulative | F39: 0 | H39: =F$39+H$38 -> 0 | I39: =H$39+I$38 -> 420 | J39: =I$39+J$38 -> 420 | K39: =J$39+K$38 -> 420 | L39: =K$39+L$38 -> 420 | M39: =L$39+M$38 -> 650 | N39: =M$39+N$38 -> 650 | O39: =N$39+O$38 -> 650 | P39: =O$39+P$38 -> 920 | ... X39: =W$39+X$38 -> 920
D40: SA Issue | F40: 0 | H40: 420 | I40: 0 | J40: 0 | K40: 270 | L40: 0 | M40: 230 | N40: 0 | O40: 0 | P40: 0 | Q40: 0 | R40: 0 | S40: 0 | T40: 0 | U40: 0 | V40: 0 | W40: 0 | X40: 0
D41: Cumulative SA Issue | F41: =F40 -> 0 | H41: =F41+H40 -> 420 | I41: =H41+I40 -> 420 | J41: =I41+J40 -> 420 | K41: =J41+K40 -> 690 | L41: =K41+L40 -> 690 | M41: =L41+M40 -> 920 | N41: =M41+N40 -> 920 | O41: =N41+O40 -> 920 | P41: =O41+P40 -> 920 | ... X41: =W41+X40 -> 920
D42: Issues | F42: =F40*$F$34 -> 0 | H42: =H40*$F$34 -> 2730000 | I42: =I40*$F$34 -> 0 | J42: =J40*$F$34 -> 0 | K42: =K40*$F$34 -> 1755000 | L42: =L40*$F$34 -> 0 | M42: =M40*$F$34 -> 1495000 | N42: =N40*$F$34 -> 0 | O42: =O40*$F$34 -> 0 | ... X42: =X40*$F$34 -> 0
D43: Principal Beg Balance | H43: =(IF(H41=0,0,IF(H39>H41,0,IF(AND(H38>0,H40>0),SUM(G43,(H42-H42*(H38/H40))),IF(H38>0,MAX($G$43:G43,SUM(G$42:$H42))-MAX($G$43:G43,SUM(G$42:$H42))*(H39/H41),SUM(G43,H42))))))+(IF(H41=0,0,IF(H39>H41,0,IF(AND(H38>0,H40>0),SUM(G43,(H42-H42*(H38/H40))),IF(H38>0,MAX($G$43:G43,SUM(G$42:$H42))-MAX($G$43:G43,SUM(G$42:$H42))*(H39/H41),SUM(G43,H42)))))) -> 5460000 | I43: =(IF(I41=0,0,IF(I39>I41,0,IF(AND(I38>0,I40>0),SUM(H43,(I42-I42*(I38/I40))),IF(I38>0,MAX($G$43:H43,SUM(H$42:$H42))-MAX($G$43:H43,SUM(H$42:$H42))*(I39/I41),SUM(H43,I42))))))+(IF(I41=0,0,IF(I39>I41,0,IF(AND(I38>0,I40>0),SUM(H43,(I42-I42*(I38/I40))),IF(I38>0,MAX($G$43:H43,SUM(H$42:$H42))-MAX($G$43:H43,SUM(H$42:$H42))*(I39/I41),SUM(H43,I42)))))) -> 0 | J43: =(IF(J41=0,0,IF(J39>J41,0,IF(AND(J38>0,J40>0),SUM(I43,(J42-J42*(J38/J40))),IF(J38>0,MAX($G$43:I43,SUM($H$42:I42))-MAX($G$43:I43,SUM($H$42:I42))*(J39/J41),SUM(I43,J42))))))+(IF(J41=0,0,IF(J39>J41,0,IF(AND(J38>0,J40>0),SUM(I43,(J42-J42*(J38/J40))),IF(J38>0,MAX($G$43:I43,SUM($H$42:I42))-MAX($G$43:I43,SUM($H$42:I42))*(J39/J41),SUM(I43,J42)))))) -> 0 | K43: =(IF(K41=0,0,IF(K39>K41,0,IF(AND(K38>0,K40>0),SUM(J43,(K42-K42*(K38/K40))),IF(K38>0,MAX($G$43:J43,SUM($H$42:J42))-MAX($G$43:J43,SUM($H$42:J42))*(K39/K41),SUM(J43,K42))))))+(IF(K41=0,0,IF(K39>K41,0,IF(AND(K38>0,K40>0),SUM(J43,(K42-K42*(K38/K40))),IF(K38>0,MAX($G$43:J43,SUM($H$42:J42))-MAX($G$43:J43,SUM($H$42:J42))*(K39/K41),SUM(J43,K42)))))) -> 3510000 | L43: =(IF(L41=0,0,IF(L39>L41,0,IF(AND(L38>0,L40>0),SUM(K43,(L42-L42*(L38/L40))),IF(L38>0,MAX($G$43:K43,SUM($H$42:K42))-MAX($G$43:K43,SUM($H$42:K42))*(L39/L41),SUM(K43,L42))))))+(IF(L41=0,0,IF(L39>L41,0,IF(AND(L38>0,L40>0),SUM(K43,(L42-L42*(L38/L40))),IF(L38>0,MAX($G$43:K43,SUM($H$42:K42))-MAX($G$43:K43,SUM($H$42:K42))*(L39/L41),SUM(K43,L42)))))) -> 7020000 | M43: =(IF(M41=0,0,IF(M39>M41,0,IF(AND(M38>0,M40>0),SUM(L43,(M42-M42*(M38/M40))),IF(M38>0,MAX($G$43:L43,SUM($H$42:L42))-MAX($G$43:L43,SUM($H$42:L42))*(M39/M41),SUM(L43,M42))))))+(IF(M41=0,0,IF(M39>M41,0,IF(AND(M38>0,M40>0),SUM(L43,(M42-M42*(M38/M40))),IF(M38>0,MAX($G$43:L43,SUM($H$42:L42))-MAX($G$43:L43,SUM($H$42:L42))*(M39/M41),SUM(L43,M42)))))) -> 14040000 | N43: =(IF(N41=0,0,IF(N39>N41,0,IF(AND(N38>0,N40>0),SUM(M43,(N42-N42*(N38/N40))),IF(N38>0,MAX($G$43:M43,SUM($H$42:M42))-MAX($G$43:M43,SUM($H$42:M42))*(N39/N41),SUM(M43,N42))))))+(IF(N41=0,0,IF(N39>N41,0,IF(AND(N38>0,N40>0),SUM(M43,(N42-N42*(N38/N40))),IF(N38>0,MAX($G$43:M43,SUM($H$42:M42))-MAX($G$43:M43,SUM($H$42:M42))*(N39/N41),SUM(M43,N42)))))) -> 28080000 | O43: =(IF(O41=0,0,IF(O39>O41,0,IF(AND(O38>0,O40>0),SUM(N43,(O42-O42*(O38/O40))),IF(O38>0,MAX($G$43:N43,SUM($H$42:N42))-MAX($G$43:N43,SUM($H$42:N42))*(O39/O41),SUM(N43,O42))))))+(IF(O41=0,0,IF(O39>O41,0,IF(AND(O38>0,O40>0),SUM(N43,(O42-O42*(O38/O40))),IF(O38>0,MAX($G$43:N43,SUM($H$42:N42))-MAX($G$43:N43,SUM($H$42:N42))*(O39/O41),SUM(N43,O42)))))) -> 56160000 | P43: =(IF(P41=0,0,IF(P39>P41,0,IF(AND(P38>0,P40>0),SUM(O43,(P42-P42*(P38/P40))),IF(P38>0,MAX($G$43:O43,SUM($H$42:O42))-MAX($G$43:O43,SUM($H$42:O42))*(P39/P41),SUM(O43,P42))))))+(IF(P41=0,0,IF(P39>P41,0,IF(AND(P38>0,P40>0),SUM(O43,(P42-P42*(P38/P40))),IF(P38>0,MAX($G$43:O43,SUM($H$42:O42))-MAX($G$43:O43,SUM($H$42:O42))*(P39/P41),SUM(O43,P42)))))) -> 0 | Q43: =(IF(Q41=0,0,IF(Q39>Q41,0,IF(AND(Q38>0,Q40>0),SUM(P43,(Q42-Q42*(Q38/Q40))),IF(Q38>0,MAX($G$43:P43,SUM($H$42:P42))-MAX($G$43:P43,SUM($H$42:P42))*(Q39/Q41),SUM(P43,Q42))))))+(IF(Q41=0,0,IF(Q39>Q41,0,IF(AND(Q38>0,Q40>0),SUM(P43,(Q42-Q42*(Q38/Q40))),IF(Q38>0,MAX($G$43:P43,SUM($H$42:P42))-MAX($G$43:P43,SUM($H$42:P42))*(Q39/Q41),SUM(P43,Q42)))))) -> 0 | ... X43: =(IF(X41=0,0,IF(X39>X41,0,IF(AND(X38>0,X40>0),SUM(W43,(X42-X42*(X38/X40))),IF(X38>0,MAX($G$43:W43,SUM($H$42:W42))-MAX($G$43:W43,SUM($H$42:W42))*(X39/X41),SUM(W43,X42))))))+(IF(X41=0,0,IF(X39>X41,0,IF(AND(X38>0,X40>0),SUM(W43,(X42-X42*(X38/X40))),IF(X38>0,MAX($G$43:W43,SUM($H$42:W42))-MAX($G$43:W43,SUM($H$42:W42))*(X39/X41),SUM(W43,X42)))))) -> 0
D44: Debt Service | F44: =PMT($F$35,$F$37,-F42) -> 0 | H44: =IF(H43=0,PMT($F$35,$F$37,-G43)*50%,PMT($F$35,$F$37,-H43)) -> 407039.47 | I44: =IF(I43=0,PMT($F$35,$F$37-$F$36,-H43)*50%,PMT($F$35,$F$37,-I43)) -> 207577.74 | J44: =IF(J43=0,PMT($F$35,$F$37-$F$36,-I43)*50%,PMT($F$35,$F$37,-J43)) -> 0 | K44: =IF(K43=0,PMT($F$35,$F$37-$F$36,-J43)*50%,PMT($F$35,$F$37,-K43)) -> 261668.23 | L44: =IF(L43=0,PMT($F$35,$F$37-$F$36,-K43)*50%,PMT($F$35,$F$37,-L43)) -> 523336.46 | M44: =IF(M43=0,PMT($F$35,$F$37-$F$36,-L43)*50%,PMT($F$35,$F$37,-M43)) -> 1046672.9 | N44: =IF(N43=0,PMT($F$35,$F$37-$F$36,-M43)*50%,PMT($F$35,$F$37,-N43)) -> 2093345.8 | O44: =IF(O43=0,PMT($F$35,$F$37-$F$36,-N43)*50%,PMT($F$35,$F$37,-O43)) -> 4186691.7 | P44: =IF(P43=0,PMT($F$35,$F$37-$F$36,-O43)*50%,PMT($F$35,$F$37,-P43)) -> 2135085.4 | ... X44: =IF(X43=0,PMT($F$35,$F$37-$F$36,-W43)*50%,PMT($F$35,$F$37,-X43)) -> 0
C47: GO COI Breakdown
C48: 0.02 | D48: Underwriters Fee
C49: 0.04 | D49: Cost of Issuance
C50: 0 | D50: Capialized Interest (% int rate * years)
C51: 0 | D51: Reserve Fund
C52: =1-SUM(C48:C51) -> 0.94 | D52: Available Proceeds
C53: SA COI Breakdown
C54: 0.02 | D54: Underwriters Fee
C55: 0.04 | D55: Cost of Issuance
C56: =F36*F35 -> 0.055 | D56: Capialized Interest (% int rate * years)
C57: 0.1 | D57: Reserve Fund
C58: =1-SUM(C54:C57) -> 0.785 | D58: Available Proceeds
B61: The Villages of Tortolita Community Facilities District
B62: Estimated Public Infrastructure Phasing Timetable
F64: Uninflated | H64: 0 | I64: =H64+1 -> 1 | J64: =I64+1 -> 2 | K64: =J64+1 -> 3 | L64: =K64+1 -> 4 | M64: =L64+1 -> 5 | N64: =M64+1 -> 6 | O64: =N64+1 -> 7 | P64: =O64+1 -> 8 | ... X64: =W64+1 -> 16
B65: Description | D65: Acres | E65: Units (1) | F65: Costs | G65: TOTAL | H65: =H37 -> 2020 | I65: =H65+1 -> 2021 | J65: =I65+1 -> 2022 | K65: =J65+1 -> 2023 | L65: =K65+1 -> 2024 | M65: =L65+1 -> 2025 | N65: =M65+1 -> 2026 | O65: =N65+1 -> 2027 | P65: =O65+1 -> 2028 | ... X65: =W65+1 -> 2036
B66: Sale 1 | E66: 420 | F66: 21141033 | G66: =SUM(H66:Y66) -> 21141033 | H66: =IF(AND($H80<=H$65,$I80>=H$65),$K80*(1+AV!$D$101)^'Source Use'!H$64,0) -> 21141033 | I66: =IF(AND($H80<=I$65,$I80>=I$65),$K80*(1+AV!$D$101)^'Source Use'!I$64,0) -> 0 | J66: =IF(AND($H80<=J$65,$I80>=J$65),$K80*(1+AV!$D$101)^'Source Use'!J$64,0) -> 0 | K66: =IF(AND($H80<=K$65,$I80>=K$65),$K80*(1+AV!$D$101)^'Source Use'!K$64,0) -> 0 | L66: =IF(AND($H80<=L$65,$I80>=L$65),$K80*(1+AV!$D$101)^'Source Use'!L$64,0) -> 0 | M66: =IF(AND($H80<=M$65,$I80>=M$65),$K80*(1+AV!$D$101)^'Source Use'!M$64,0) -> 0 | N66: =IF(AND($H80<=N$65,$I80>=N$65),$K80*(1+AV!$D$101)^'Source Use'!N$64,0) -> 0 | O66: =IF(AND($H80<=O$65,$I80>=O$65),$K80*(1+AV!$D$101)^'Source Use'!O$64,0) -> 0 | ... X66: =IF(AND($H80<=X$65,$I80>=X$65),$K80*(1+AV!$D$101)^'Source Use'!X$64,0) -> 0
B67: Sale 2 | D67: 0 | E67: 270 | F67: 4385774 | G67: =SUM(H67:Y67) -> 4608588.9 | H67: =IF(AND($H81<=H$65,$I81>=H$65),$K81*(1+AV!$D$101)^'Source Use'!H$64,0) -> 0 | I67: =IF(AND($H81<=I$65,$I81>=I$65),$K81*(1+AV!$D$101)^'Source Use'!I$64,0) -> 0 | J67: =IF(AND($H81<=J$65,$I81>=J$65),$K81*(1+AV!$D$101)^'Source Use'!J$64,0) -> 2281479.6 | K67: =IF(AND($H81<=K$65,$I81>=K$65),$K81*(1+AV!$D$101)^'Source Use'!K$64,0) -> 2327109.2 | L67: =IF(AND($H81<=L$65,$I81>=L$65),$K81*(1+AV!$D$101)^'Source Use'!L$64,0) -> 0 | M67: =IF(AND($H81<=M$65,$I81>=M$65),$K81*(1+AV!$D$101)^'Source Use'!M$64,0) -> 0 | N67: =IF(AND($H81<=N$65,$I81>=N$65),$K81*(1+AV!$D$101)^'Source Use'!N$64,0) -> 0 | O67: =IF(AND($H81<=O$65,$I81>=O$65),$K81*(1+AV!$D$101)^'Source Use'!O$64,0) -> 0 | ... X67: =IF(AND($H81<=X$65,$I81>=X$65),$K81*(1+AV!$D$101)^'Source Use'!X$64,0) -> 0
B68: Sale 3 | D68: 0 | E68: 230 | F68: 5470516 | G68: =SUM(H68:Y68) -> 5980677.1 | H68: =IF(AND($H82<=H$65,$I82>=H$65),$K82*(1+AV!$D$101)^'Source Use'!H$64,0) -> 0 | I68: =IF(AND($H82<=I$65,$I82>=I$65),$K82*(1+AV!$D$101)^'Source Use'!I$64,0) -> 0 | J68: =IF(AND($H82<=J$65,$I82>=J$65),$K82*(1+AV!$D$101)^'Source Use'!J$64,0) -> 0 | K68: =IF(AND($H82<=K$65,$I82>=K$65),$K82*(1+AV!$D$101)^'Source Use'!K$64,0) -> 0 | L68: =IF(AND($H82<=L$65,$I82>=L$65),$K82*(1+AV!$D$101)^'Source Use'!L$64,0) -> 2960731.2 | M68: =IF(AND($H82<=M$65,$I82>=M$65),$K82*(1+AV!$D$101)^'Source Use'!M$64,0) -> 3019945.8 | N68: =IF(AND($H82<=N$65,$I82>=N$65),$K82*(1+AV!$D$101)^'Source Use'!N$64,0) -> 0 | O68: =IF(AND($H82<=O$65,$I82>=O$65),$K82*(1+AV!$D$101)^'Source Use'!O$64,0) -> 0 | ... X68: =IF(AND($H82<=X$65,$I82>=X$65),$K82*(1+AV!$D$101)^'Source Use'!X$64,0) -> 0
B69: Sale 4 | D69: 0 | E69: 0 | G69: =SUM(H69:Y69) -> 0 | H69: =IF(AND($H83<=H$65,$I83>=H$65),$K83*(1+AV!$D$101)^'Source Use'!H$64,0) -> 0 | I69: =IF(AND($H83<=I$65,$I83>=I$65),$K83*(1+AV!$D$101)^'Source Use'!I$64,0) -> 0 | J69: =IF(AND($H83<=J$65,$I83>=J$65),$K83*(1+AV!$D$101)^'Source Use'!J$64,0) -> 0 | K69: =IF(AND($H83<=K$65,$I83>=K$65),$K83*(1+AV!$D$101)^'Source Use'!K$64,0) -> 0 | L69: =IF(AND($H83<=L$65,$I83>=L$65),$K83*(1+AV!$D$101)^'Source Use'!L$64,0) -> 0 | M69: =IF(AND($H83<=M$65,$I83>=M$65),$K83*(1+AV!$D$101)^'Source Use'!M$64,0) -> 0 | N69: =IF(AND($H83<=N$65,$I83>=N$65),$K83*(1+AV!$D$101)^'Source Use'!N$64,0) -> 0 | O69: =IF(AND($H83<=O$65,$I83>=O$65),$K83*(1+AV!$D$101)^'Source Use'!O$64,0) -> 0 | ... X69: =IF(AND($H83<=X$65,$I83>=X$65),$K83*(1+AV!$D$101)^'Source Use'!X$64,0) -> 0
B70: Sale 5 | D70: 0 | E70: 0 | G70: =SUM(H70:Y70) -> 0 | H70: =IF(AND($H84<=H$65,$I84>=H$65),$K84*(1+AV!$D$101)^'Source Use'!H$64,0) -> 0 | I70: =IF(AND($H84<=I$65,$I84>=I$65),$K84*(1+AV!$D$101)^'Source Use'!I$64,0) -> 0 | J70: =IF(AND($H84<=J$65,$I84>=J$65),$K84*(1+AV!$D$101)^'Source Use'!J$64,0) -> 0 | K70: =IF(AND($H84<=K$65,$I84>=K$65),$K84*(1+AV!$D$101)^'Source Use'!K$64,0) -> 0 | L70: =IF(AND($H84<=L$65,$I84>=L$65),$K84*(1+AV!$D$101)^'Source Use'!L$64,0) -> 0 | M70: =IF(AND($H84<=M$65,$I84>=M$65),$K84*(1+AV!$D$101)^'Source Use'!M$64,0) -> 0 | N70: =IF(AND($H84<=N$65,$I84>=N$65),$K84*(1+AV!$D$101)^'Source Use'!N$64,0) -> 0 | O70: =IF(AND($H84<=O$65,$I84>=O$65),$K84*(1+AV!$D$101)^'Source Use'!O$64,0) -> 0 | ... X70: =IF(AND($H84<=X$65,$I84>=X$65),$K84*(1+AV!$D$101)^'Source Use'!X$64,0) -> 0
B71: Totals | D71: =SUM(D66:D70) -> 0 | E71: =SUM(E66:E70) -> 920 | F71: =SUM(F66:F70) -> 30997323 | G71: =SUM(G66:G70) -> 31730299 | H71: =SUM(H66:H70) -> 21141033 | I71: =SUM(I66:I70) -> 0 | J71: =SUM(J66:J70) -> 2281479.6 | K71: =SUM(K66:K70) -> 2327109.2 | ... X71: =SUM(X66:X70) -> 0
B73: Source: | C73: Applicant
B75: Footnote:
B76: (1) Includes low, medium, medium-high, high density and mixed use products.
B77: (2) Estimate
B78: (3) One Year Delay after Start Date | F78: Eligible | H78: Start | I78: Completion | J78: Number | K78: Cost per
F79: Costs (2) | H79: Date | I79: Date | J79: Years | K79: Year (3)
E80: =(B66) -> Sale 1 | F80: =(F66) -> 21141033 | H80: 2020 | I80: 2020 | J80: =I80-H80+1 -> 1 | K80: =F80/J80 -> 21141033
E81: =(B67) -> Sale 2 | F81: =(F67) -> 4385774 | H81: 2022 | I81: 2023 | J81: =I81-H81+1 -> 2 | K81: =F81/J81 -> 2192887
E82: =(B68) -> Sale 3 | F82: =(F68) -> 5470516 | H82: 2024 | I82: 2025 | J82: =I82-H82+1 -> 2 | K82: =F82/J82 -> 2735258
E83: =(B69) -> Sale 4 | F83: =(F69) -> 0 | H83: 2029 | I83: 2031 | J83: =I83-H83+1 -> 3 | K83: =F83/J83 -> 0
E84: =(B70) -> Sale 5 | F84: =(F70) -> 0 | H84: 2031 | I84: 2035 | J84: =I84-H84+1 -> 5 | K84: =F84/J84 -> 0
F85: =SUM(F80:F84) -> 30997323

Sheet Land Use
G8: The Villages of Tortolita | O8: The Villages of Tortolita
G9: Community Facilities District | O9: Community Facilities District
G10: Land Use Plan | O10: Land Use To Be Uncluded In District
I13: Project Total | K13: Included in CFD | O13: Description | Q13: Included in CFD | T13: Excluded From CFD | W13: Project Total
G14: Description | I14: Acres | J14: Residential Units (1) | K14: Acres | L14: Residential Units (1) | O14: Phase | P14: Village | Q14: Acres | R14: Residential Units (1) | S14: MF Units (1) | T14: Acres | U14: Residential Units (1) | V14: MF Units (1) | W14: Acres
G15: Medium-Low Density Residential | I15: 422.68 | J15: 1214 | K15: 257.6 | L15: 740 | O15: Phase I | P15: Village IV | Q15: 536.75 | R15: 1405 | S15: 217 | T15: 0 | U15: 0 | V15: 0 | W15: =SUM(Q15,T15) -> 536.75
G16: Medium Density Residential | I16: 789.69 | J16: 3054 | K16: 708.45 | L16: 2740 | O16: Phase II | P16: Village III | Q16: 190.89 | R16: 642 | S16: 0 | T16: 200.08 | U16: 673 | V16: 0 | W16: =SUM(Q16,T16) -> 390.97
G17: Medium-High Density Residential | I17: 62.96 | J17: 452 | K17: 62.96 | L17: 404 | O17: Phase III | P17: Village II | Q17: 320.1 | R17: 0 | S17: 2015 | T17: 0 | U17: 0 | V17: 0 | W17: =SUM(Q17,T17) -> 320.1
G18: Mixed Use | I18: 411.94 | J18: 1780 | K18: 411.94 | L18: 1780 | O18: Phase IV | P18: Village I | Q18: 393.21 | R18: 1385 | S18: 0 | T18: 46.24 | U18: 163 | V18: 0 | W18: =SUM(Q18,T18) -> 439.45
G19: Industrial | I19: 93.17 | J19: 0 | K19: 78.84 | L19: 0 | O19: Phase V | P19: Industrial | Q19: 78.87 | R19: 0 | S19: 0 | T19: 14.3 | U19: 0 | V19: 0 | W19: =SUM(Q19,T19) -> 93.17
G20: Total | I20: =SUM(I15:I19) -> 1780.44 | J20: =SUM(J15:J19) -> 6500 | K20: =SUM(K15:K19) -> 1519.79 | L20: =SUM(L15:L19) -> 5664 | O20: Total | Q20: =SUM(Q15:Q19) -> 1519.82 | R20: =SUM(R15:R19) -> 3432 | S20: =SUM(S15:S19) -> 2232 | T20: =SUM(T15:T19) -> 260.62 | U20: =SUM(U15:U19) -> 836 | V20: =SUM(V15:V19) -> 0 | W20: =SUM(W15:W19) -> 1780.44
G22: Source: Applicant | O22: Source: Applicant
G23: Footnote: | O23: Footnote:
G24: (1) Unit counts are approximate and provided by the Applicant. | O24: (1) Unit counts are approximate and provided by the Applicant.
G27: Notes:
G28: Currently included in the CFD Application
G29: Acres ties to District legal description acreage
I31: =SUM(I15:I19) -> 1780.44
G33: =CFDName -> #REF! | U33: `
G34: Land Use Plan
G36: Village | H36: Land Use | J36: Acres | M36: Parcels | N36: AV
G37: I, III, IV | H37: MLDR | J37: =I15 -> 422.68 | M37: Pima Assessors Report Dated: 2/22/19 | P37: Parcel Number | Q37: Owner | S37: Acres | T37: County
G38: I, III, IV | H38: MDR | J38: =I16 -> 789.69 | M38: 21706001C (TMR INVESTORS LLC) | N38: 10488 | P38: 21706001C | Q38: TMR INVESTORS LLC | S38: 42.46 | T38: Pima | U38: 39.16
G39: II | H39: MHDR | J39: =I17 -> 62.96 | M39: 21706001F (TMR INVESTORS LLC) | N39: 75 | P39: 21706001F | Q39: TMR INVESTORS LLC | S39: 6.69 | T39: Pima | U39: 6.82
G40: II, IV | H40: Mixed Use | J40: =I18 -> 411.94 | M40: 21706001G (TMR INVESTORS LLC) | N40: 83 | P40: 21706001G | Q40: TMR INVESTORS LLC | S40: 55.64 | T40: Pima | U40: 64.48
G41: V | H41: Industrial | J41: =I19 -> 93.17 | M41: 21706001H (TMR INVESTORS LLC) | N41: 75 | P41: 21706001H | Q41: TMR INVESTORS LLC | S41: 40.83 | T41: Pima | U41: 39.02
G42: Total | J42: =SUM(J37:J41) -> 1780.44 | M42: 21707001A (TMR INVESTORS LLC) | N42: 14051 | P42: 21707001A | Q42: TMR INVESTORS LLC | S42: 59.12 | T42: Pima | U42: 56.8
G43: Source: | H43: =Developer -> #REF! | M43: 217070020 (TMR INVESTORS LLC) | N43: 75 | P43: 217070020 | Q43: TMR INVESTORS LLC | S43: 18.51 | T43: Pima | U43: 20.48
M44: 21707003C (TMR INVESTORS LLC) | N44: 7397 | P44: 21707003C | Q44: TMR INVESTORS LLC | S44: 18.72 | T44: Pima | U44: 19.97
G45: Notes: | M45: 217080030 (TMR INVESTORS LLC) | N45: 83 | P45: 217080030 | Q45: TMR INVESTORS LLC | S45: 77.66 | T45: Pima | U45: 77.66
G46: Provided by Gary Jones on 10/09/06. | M46: 21708004C (TMR INVESTORS LLC) | N46: 89 | P46: 21708004C | Q46: TMR INVESTORS LLC | S46: 59.28 | T46: Pima | U46: 60.59
G47: Acres tie to District legal description acreage of 1780.44 | M47: 21708004D (TMR INVESTORS LLC) | N47: 99 | P47: 21708004D | Q47: TMR INVESTORS LLC | S47: 120.07 | T47: Pima | U47: 117.26
M48: 217080060 (TMR INVESTORS LLC) | N48: 95 | P48: 217080060 | Q48: TMR INVESTORS LLC | S48: 95.11 | T48: Pima | U48: 98.98
M49: 21716001A (TMR INVESTORS LLC) | N49: 529 | P49: 21716001A | Q49: TMR INVESTORS LLC | S49: 507.95 | T49: Pima | U49: 507.59
M50: 217170010 (TMR INVESTORS LLC) | N50: 83 | P50: 217170010 | Q50: TMR INVESTORS LLC | S50: 64.73 | T50: Pima | U50: 61.5
M51: 21725001A (TMR INVESTORS LLC) | N51: 75 | P51: 21725001A | Q51: TMR INVESTORS LLC | S51: 24.82 | T51: Pima | U51: 25.55
M52: 217270030 (TMR INVESTORS LLC) | N52: 75 | P52: 217270030 | Q52: TMR INVESTORS LLC | S52: 5.6 | T52: Pima | U52: 5.56
P53: 410250010 | Q53: TMR INVESTORS LLC | S53: 362.6 | T53: Pinal
P54: 410250020 | Q54: TMR INVESTORS LLC | S54: 32.09 | T54: Pinal
P55: Total | S55: =SUM(S38:S54) -> 1591.88
M57: Total Pima | N57: =SUM(N38:N56) -> 33372
M59: Pinal Assessors Report Dated: 4/4/19
M60: 410250010 (TMR INVESTORS LLC) | N60: 595
M61: 410250020 (TMR INVESTORS LLC) | N61: 53
N62: 0
N63: 0
M64: Total Pinal | N64: =SUM(N60:N63) -> 648
M66: Grand Total Both Counties | N66: =SUM(N57+N64) -> 34020

Sheet AV
B2: The Villages of Tortolita
B3: Community Facilities District
B4: Estimated Assessed Valuation Build-Up
E6: 0 | F6: =E6+1 -> 1 | G6: =F6+1 -> 2 | H6: =G6+1 -> 3 | I6: =H6+1 -> 4 | J6: =I6+1 -> 5 | K6: =J6+1 -> 6 | L6: =K6+1 -> 7 | M6: =L6+1 -> 8 | ... S6: =R6+1 -> 14
C7: Year | E7: 2020 | F7: =1+E7 -> 2021 | G7: =1+F7 -> 2022 | H7: =1+G7 -> 2023 | I7: =1+H7 -> 2024 | J7: =1+I7 -> 2025 | K7: =1+J7 -> 2026 | L7: =1+K7 -> 2027 | M7: =1+L7 -> 2028 | ... U7: =1+T7 -> 2036
C9: Single Family
C10: Absorption (Builder Sales) | E10: 0 | F10: 192 | G10: 163 | H10: 81 | I10: 148 | J10: 144 | K10: 134 | L10: 58 | M10: 30
C11: Cumulative | E11: =+E10+D11 -> 0 | F11: =+F10+E11 -> 192 | G11: =+G10+F11 -> 355 | H11: =+H10+G11 -> 436 | I11: =+I10+H11 -> 584 | J11: =+J10+I11 -> 728 | K11: =+K10+J11 -> 862 | L11: =+L10+K11 -> 920 | ... U11: =+U10+T11 -> 950
C12: Average Unit Price | E12: =IF(E10=0,0,$G$105*(1+$D$99)^E6) -> 0 | F12: =IF(F10=0,0,$G$105*(1+$D$99)^F6) -> 300900 | G12: =IF(G10=0,0,$G$105*(1+$D$99)^G6) -> 306918 | H12: =IF(H10=0,0,$G$105*(1+$D$99)^H6) -> 313056.36 | I12: =IF(I10=0,0,$G$105*(1+$D$99)^I6) -> 319317.49 | J12: =IF(J10=0,0,$G$105*(1+$D$99)^J6) -> 325703.84 | K12: =IF(K10=0,0,$G$105*(1+$D$99)^K6) -> 332217.91 | L12: =IF(L10=0,0,$G$105*(1+$D$99)^L6) -> 338862.27 | ... U12: =IF(U10=0,0,$G$105*(1+$D$99)^U6) -> 0
C13: Uninflated | E13: =$E$12 -> 0 | F13: =IF(F10=0,0,$G$105) -> 295000 | G13: =IF(G10=0,0,$G$105) -> 295000 | H13: =IF(H10=0,0,$G$105) -> 295000 | I13: =IF(I10=0,0,$G$105) -> 295000 | J13: =IF(J10=0,0,$G$105) -> 295000 | K13: =IF(K10=0,0,$G$105) -> 295000 | L13: =IF(L10=0,0,$G$105) -> 295000 | M13: =IF(M10=0,0,$G$105) -> 295000 | ... U13: =IF(U10=0,0,$G$105) -> 0
C14: Uninflated Sales | E14: =E13*E10 -> 0 | F14: =F13*F10 -> 56640000 | G14: =G13*G10 -> 48085000 | H14: =H13*H10 -> 23895000 | I14: =I13*I10 -> 43660000 | J14: =J13*J10 -> 42480000 | K14: =K13*K10 -> 39530000 | L14: =L13*L10 -> 17110000 | ... U14: =U13*U10 -> 0
B15: INFLATED | C15: Single Family Sales | E15: =E10*E12 -> 0 | F15: =F10*F12 -> 57772800 | G15: =G10*G12 -> 50027634 | H15: =H10*H12 -> 25357565 | I15: =I10*I12 -> 47258988 | J15: =J10*J12 -> 46901353 | K15: =K10*K12 -> 44517200 | L15: =L10*L12 -> 19654012 | ... U15: =U10*U12 -> 0
F16: 57257365 | G16: 49555581 | H16: 25080766 | I16: 46851188 | J16: 46516525 | K16: 44088067 | L16: 19497096 | M16: 10268469 | N16: 0 | O16: 0 | P16: 0 | Q16: 0 | R16: 0 | S16: 0 | T16: 0 | U16: 0 | V16: 0 | W16: 0 | X16: 0 | Y16: 0 | Z16: 0 | AA16: 0 | AB16: 0 | AC16: 0 | AD16: 0 | AE16: 0 | AF16: 0 | AG16: 0 | AH16: 0
C17: Multi Family
C18: Absorption | E18: 0 | F18: 0 | G18: 0 | H18: 0 | I18: 0 | J18: 0 | K18: 0 | L18: 0 | M18: 0 | N18: 0 | O18: 0 | P18: 0 | Q18: 0 | R18: 0 | S18: 0 | T18: 0 | U18: 0
C19: Cumulative | E19: =+E18+D19 -> 0 | F19: =+F18+E19 -> 0 | G19: =+G18+F19 -> 0 | H19: =+H18+G19 -> 0 | I19: =+I18+H19 -> 0 | J19: =+J18+I19 -> 0 | K19: =+K18+J19 -> 0 | L19: =+L18+K19 -> 0 | ... U19: =+U18+T19 -> 0
C20: Average Unit Price | E20: 0 | F20: =IF(F18=0,0,$E$20*(1+$D$99)^F6) -> 0 | G20: =IF(G18=0,0,$E$20*(1+$D$99)^G6) -> 0 | H20: =IF(H18=0,0,$E$20*(1+$D$99)^H6) -> 0 | I20: =IF(I18=0,0,$E$20*(1+$D$99)^I6) -> 0 | J20: =IF(J18=0,0,$E$20*(1+$D$99)^J6) -> 0 | K20: =IF(K18=0,0,$E$20*(1+$D$99)^K6) -> 0 | L20: =IF(L18=0,0,$E$20*(1+$D$99)^L6) -> 0 | M20: =IF(M18=0,0,$E$20*(1+$D$99)^M6) -> 0 | ... U20: =IF(U18=0,0,$E$20*(1+$D$99)^U6) -> 0
C21: Uninflated | E21: 0 | F21: =IF(F18=0,0,$E$20) -> 0 | G21: =IF(G18=0,0,$E$20) -> 0 | H21: =IF(H18=0,0,$E$20) -> 0 | I21: =IF(I18=0,0,$E$20) -> 0 | J21: =IF(J18=0,0,$E$20) -> 0 | K21: =IF(K18=0,0,$E$20) -> 0 | L21: =IF(L18=0,0,$E$20) -> 0 | M21: =IF(M18=0,0,$E$20) -> 0 | ... U21: =IF(U18=0,0,$E$20) -> 0
C22: Uninflated Sales | E22: =E21*E18 -> 0 | F22: =F21*F18 -> 0 | G22: =G21*G18 -> 0 | H22: =H21*H18 -> 0 | I22: =I21*I18 -> 0 | J22: =J21*J18 -> 0 | K22: =K21*K18 -> 0 | L22: =L21*L18 -> 0 | ... U22: =U21*U18 -> 0
C23: Multi Family Sales | E23: =E18*E20 -> 0 | F23: =F18*F20 -> 0 | G23: =G18*G20 -> 0 | H23: =H18*H20 -> 0 | I23: =I18*I20 -> 0 | J23: =J18*J20 -> 0 | K23: =K18*K20 -> 0 | L23: =L18*L20 -> 0 | ... U23: =U18*U20 -> 0
C25: Commercial | F25: =1-(F16/F15) -> 0.0089217513 | G25: =1-(G16/G15) -> 0.0094358501 | H25: =1-(H16/H15) -> 0.01091586 | I25: =1-(I16/I15) -> 0.0086290533 | J25: =1-(J16/J15) -> 0.0082050436 | K25: =1-(K16/K15) -> 0.0096397121
C26: Absorption - EDUs | E26: 0 | F26: 0 | G26: 0 | H26: =U113+U119 -> 0 | I26: =U113+U119 -> 0 | J26: =U113+U119+U125 -> 0 | K26: =U113+U119+U125 -> 0 | L26: =U113+U119 -> 0 | M26: =L130-L26-K26-J26-I26-H26 -> 0 | N26: 0 | O26: 0 | P26: 0 | Q26: 0 | R26: 0 | S26: 0 | T26: 0 | U26: 0
C27: Cumulative | E27: =E26 -> 0 | F27: =E27+F26 -> 0 | G27: =F27+G26 -> 0 | H27: =G27+H26 -> 0 | I27: =H27+I26 -> 0 | J27: =I27+J26 -> 0 | K27: =J27+K26 -> 0 | L27: =K27+L26 -> 0 | M27: =L27+M26 -> 0 | ... U27: =T27+U26 -> 0
C28: Average EDU Price | E28: 0 | F28: 0 | G28: 0 | H28: =IF(H26=0,0,$G$105*(1+$D$99)^H6) -> 0 | I28: =IF(I26=0,0,$G$105*(1+$D$99)^I6) -> 0 | J28: =IF(J26=0,0,$G$105*(1+$D$99)^J6) -> 0 | K28: =IF(K26=0,0,$G$105*(1+$D$99)^K6) -> 0 | L28: =IF(L26=0,0,$G$105*(1+$D$99)^L6) -> 0 | M28: =IF(M26=0,0,$G$105*(1+$D$99)^M6) -> 0 | N28: =IF(N26=0,0,$G$105*(1+$D$99)^N6) -> 0 | O28: =IF(O26=0,0,$G$105*(1+$D$99)^O6) -> 0 | ... U28: =IF(U26=0,0,$G$105*(1+$D$99)^U6) -> 0
C29: Uninflated | E29: =E28 -> 0 | F29: =IF(F26=0,0,$G$105) -> 0 | G29: =IF(G26=0,0,$G$105) -> 0 | H29: =IF(H26=0,0,$G$105) -> 0 | I29: =IF(I26=0,0,$G$105) -> 0 | J29: =IF(J26=0,0,$G$105) -> 0 | K29: =IF(K26=0,0,$G$105) -> 0 | L29: =IF(L26=0,0,$G$105) -> 0 | M29: =IF(M26=0,0,$G$105) -> 0 | ... U29: =IF(U26=0,0,$G$105) -> 0
C30: Uninflated Sales | E30: =E26*E28 -> 0 | F30: =F26*F29 -> 0 | G30: =G26*G29 -> 0 | H30: =H26*H29 -> 0 | I30: =I26*I29 -> 0 | J30: =J26*J29 -> 0 | K30: =K26*K29 -> 0 | L30: =L26*L29 -> 0 | M30: =M26*M29 -> 0 | ... U30: =U26*U29 -> 0
B31: INFLATED | C31: Commercial Sales | E31: =E26*E28 -> 0 | F31: =F26*F28 -> 0 | G31: =G26*G28 -> 0 | H31: =H26*H28 -> 0 | I31: =I26*I28 -> 0 | J31: =J26*J28 -> 0 | K31: =K26*K28 -> 0 | L31: =L26*L28 -> 0 | ... U31: =U26*U28 -> 0
C33: Total
C34: Absorption | E34: =+E10+E18+E26 -> 0 | F34: =+F10+F18+F26 -> 192 | G34: =+G10+G18+G26 -> 163 | H34: =+H10+H18+H26 -> 81 | I34: =+I10+I18+I26 -> 148 | J34: =+J10+J18+J26 -> 144 | K34: =+K10+K18+K26 -> 134 | L34: =+L10+L18+L26 -> 58 | ... U34: =+U10+U18+U26 -> 0
C35: Cumulative | E35: =+E34 -> 0 | F35: =+F34+E35 -> 192 | G35: =+G34+F35 -> 355 | H35: =+H34+G35 -> 436 | I35: =+I34+H35 -> 584 | J35: =+J34+I35 -> 728 | K35: =+K34+J35 -> 862 | L35: =+L34+K35 -> 920 | M35: =+M34+L35 -> 950 | ... U35: =+U34+T35 -> 950
C36: Average Unit Price | E36: =IF(E10+E18+E26=0,0,(E10*E12+E18*E20+E26*E28)/(E10+E18+E26)) -> 0 | F36: =IF(F10+F18+F26=0,0,(F10*F12+F18*F20+F26*F28)/(F10+F18+F26)) -> 300900 | G36: =IF(G10+G18+G26=0,0,(G10*G12+G18*G20+G26*G28)/(G10+G18+G26)) -> 306918 | H36: =IF(H10+H18+H26=0,0,(H10*H12+H18*H20+H26*H28)/(H10+H18+H26)) -> 313056.36 | I36: =IF(I10+I18+I26=0,0,(I10*I12+I18*I20+I26*I28)/(I10+I18+I26)) -> 319317.49 | J36: =IF(J10+J18+J26=0,0,(J10*J12+J18*J20+J26*J28)/(J10+J18+J26)) -> 325703.84 | K36: =IF(K10+K18+K26=0,0,(K10*K12+K18*K20+K26*K28)/(K10+K18+K26)) -> 332217.91 | L36: =IF(L10+L18+L26=0,0,(L10*L12+L18*L20+L26*L28)/(L10+L18+L26)) -> 338862.27 | ... U36: =IF(U10+U18+U26=0,0,(U10*U12+U18*U20+U26*U28)/(U10+U18+U26)) -> 0
C37: Uninflated | E37: =$E$36 -> 0 | F37: =IF(F10+F18+F26=0,0,(F10*F13+F18*F21+F26*F29)/(F10+F18+F26)) -> 295000 | G37: =IF(G10+G18+G26=0,0,(G10*G13+G18*G21+G26*G29)/(G10+G18+G26)) -> 295000 | H37: =IF(H10+H18+H26=0,0,(H10*H13+H18*H21+H26*H29)/(H10+H18+H26)) -> 295000 | I37: =IF(I10+I18+I26=0,0,(I10*I13+I18*I21+I26*I29)/(I10+I18+I26)) -> 295000 | J37: =IF(J10+J18+J26=0,0,(J10*J13+J18*J21+J26*J29)/(J10+J18+J26)) -> 295000 | K37: =IF(K10+K18+K26=0,0,(K10*K13+K18*K21+K26*K29)/(K10+K18+K26)) -> 295000 | L37: =IF(L10+L18+L26=0,0,(L10*L13+L18*L21+L26*L29)/(L10+L18+L26)) -> 295000 | M37: =IF(M10+M18+M26=0,0,(M10*M13+M18*M21+M26*M29)/(M10+M18+M26)) -> 295000 | ... U37: =IF(U10+U18+U26=0,0,(U10*U13+U18*U21+U26*U29)/(U10+U18+U26)) -> 0
C38: Uninflated Sales | E38: =+E14+E22+E30 -> 0 | F38: =+F14+F22+F30 -> 56640000 | G38: =+G14+G22+G30 -> 48085000 | H38: =+H14+H22+H30 -> 23895000 | I38: =+I14+I22+I30 -> 43660000 | J38: =+J14+J22+J30 -> 42480000 | K38: =+K14+K22+K30 -> 39530000 | L38: =+L14+L22+L30 -> 17110000 | ... U38: =+U14+U22+U30 -> 0
B39: INFLATED | C39: Total Sales | E39: =+E15+E23+E31 -> 0 | F39: =+F15+F23+F31 -> 57772800 | G39: =+G15+G23+G31 -> 50027634 | H39: =+H15+H23+H31 -> 25357565 | I39: =+I15+I23+I31 -> 47258988 | J39: =+J15+J23+J31 -> 46901353 | K39: =+K15+K23+K31 -> 44517200 | L39: =+L15+L23+L31 -> 19654012 | ... U39: =+U15+U23+U31 -> 0
C40: Cumulative | E40: =+E39+D40 -> 0 | F40: =+F39+E40 -> 57772800 | G40: =+G39+F40 -> 107800434 | H40: =+H39+G40 -> 1.33158e+08 | I40: =+I39+H40 -> 1.8041699e+08 | J40: =+J39+I40 -> 2.2731834e+08 | K40: =+K39+J40 -> 2.7183554e+08 | L40: =+L39+K40 -> 2.9148955e+08 | ... U40: =+U39+T40 -> 3.0185874e+08
C42: Added to Tax Roll
B43: INFLATED | C43: Single Family Value | E43: =E15*$D$103+D15*$D$104 -> 0 | F43: =F15*$D$103+E15*$D$104+D15*$D$105 -> 14443200 | G43: =G15*$D$103+F15*$D$104+E15*$D$105 -> 41393308 | H43: =H15*$D$103+G15*$D$104+F15*$D$105 -> 45796408 | I43: =I15*$D$103+H15*$D$104+G15*$D$105 -> 37000438 | J43: =J15*$D$103+I15*$D$104+H15*$D$105 -> 41694223 | K43: =K15*$D$103+J15*$D$104+I15*$D$105 -> 46394723 | L43: =L15*$D$103+K15*$D$104+J15*$D$105 -> 38897441 | M43: =M15*$D$103+L15*$D$104+K15*$D$105 -> 23548602 | ... U43: =U15*$D$103+T15*$D$104+S15*$D$105 -> 0
C44: Multi Family Value | E44: =E23*$D$103+D23*D104 -> 0 | F44: =F23*$D$103+E23*$D$104+D23*$D$105 -> 0 | G44: =G23*$D$103+F23*$D$104+E23*$D$105 -> 0 | H44: =H23*$D$103+G23*$D$104+F23*$D$105 -> 0 | I44: =I23*$D$103+H23*$D$104+G23*$D$105 -> 0 | J44: =J23*$D$103+I23*$D$104+H23*$D$105 -> 0 | K44: =K23*$D$103+J23*$D$104+I23*$D$105 -> 0 | L44: =L23*$D$103+K23*$D$104+J23*$D$105 -> 0 | M44: =M23*$D$103+L23*$D$104+K23*$D$105 -> 0 | ... U44: =U23*$D$103+T23*$D$104+S23*$D$105 -> 0
C45: Commercial Value | E45: =E31*$D$103+D31*$D$104 -> 0 | F45: =F31*$D$103+E31*$D$104+D31*$D$105 -> 0 | G45: =G31*$D$103+F31*$D$104+E31*$D$105 -> 0 | H45: =H31*$D$103+G31*$D$104+F31*$D$105 -> 0 | I45: =I31*$D$103+H31*$D$104+G31*$D$105 -> 0 | J45: =J31*$D$103+I31*$D$104+H31*$D$105 -> 0 | K45: =K31*$D$103+J31*$D$104+I31*$D$105 -> 0 | L45: =L31*$D$103+K31*$D$104+J31*$D$105 -> 0 | M45: =M31*$D$103+L31*$D$104+K31*$D$105 -> 0 | ... U45: =U31*$D$103+T31*$D$104+S31*$D$105 -> 0
C46: Total Value | E46: =(E39*$D$103+D39*$D$104) -> 0 | F46: =(F39*$D$103+E39*$D$104+D39*$D$105) -> 14443200 | G46: =(G39*$D$103+F39*$D$104+E39*$D$105) -> 41393308 | H46: =(H39*$D$103+G39*$D$104+F39*$D$105) -> 45796408 | I46: =(I39*$D$103+H39*$D$104+G39*$D$105) -> 37000438 | J46: =(J39*$D$103+I39*$D$104+H39*$D$105) -> 41694223 | K46: =(K39*$D$103+J39*$D$104+I39*$D$105) -> 46394723 | L46: =(L39*$D$103+K39*$D$104+J39*$D$105) -> 38897441 | M46: =(M39*$D$103+L39*$D$104+K39*$D$105) -> 23548602 | ... U46: =(U39*$D$103+T39*$D$104+S39*$D$105) -> 0
C47: Cumulative Total Value | E47: =+E46 -> 0 | F47: =+E47+F46 -> 14443200 | G47: =+F47+G46 -> 55836508 | H47: =+G47+H46 -> 1.0163292e+08 | I47: =+H47+I46 -> 1.3863335e+08 | J47: =+I47+J46 -> 1.8032758e+08 | K47: =+J47+K46 -> 2.267223e+08 | L47: =+K47+L46 -> 2.6561974e+08 | M47: =+L47+M46 -> 2.8916835e+08 | ... U47: =+T47+U46 -> 3.0185874e+08
C48: Cumulative Units on Tax Roll (1) | E48: =E35*$D$103+D35*$D$104 -> 0 | F48: =F35*$D$103+E35*$D$104 -> 48 | G48: =G35*$D$103+F35*$D$104+E35*$D$105 -> 184.75 | H48: =H35*$D$103+G35*$D$104+F35*$D$105 -> 334.5 | I48: =I35*$D$103+H35*$D$104+G35*$D$105 -> 452.75 | J48: =J35*$D$103+I35*$D$104+H35*$D$105 -> 583 | K48: =K35*$D$103+J35*$D$104+I35*$D$105 -> 725.5 | L48: =L35*$D$103+K35*$D$104+J35*$D$105 -> 843 | M48: =M35*$D$103+L35*$D$104+K35*$D$105 -> 913 | N48: =N35*$D$103+M35*$D$104+L35*$D$105 -> 942.5 | ... U48: =U35*$D$103+T35*$D$104+S35*$D$105 -> 950
C50: Added to Tax Roll - Inflated
C51: Single Family Value | E51: =E46*(1+$D$99)^E6 -> 0 | F51: =F46*(1+$D$99)^F6 -> 14732064 | G51: =G46*(1+$D$99)^G6 -> 43065598 | H51: =H46*(1+$D$99)^H6 -> 48599515 | I51: =I46*(1+$D$99)^I6 -> 40050464 | J51: =J46*(1+$D$99)^J$6 -> 46033792 | K51: =K46*(1+$D$99)^K6 -> 52247994 | L51: =L46*(1+$D$99)^L6 -> 44680933 | M51: =M46*(1+$D$99)^M6 -> 27590941 | N51: =N46*(1+$D$99)^N6 -> 12068159 | O51: =O46*(1+$D$99)^O6 -> 3159994.8 | P51: =P46*(1+$D$99)^P6 -> 0 | Q51: =Q46*(1+$D$99)^Q6 -> 0 | R51: =R46*(1+$D$99)^R6 -> 0 | ... U51: =U46*(1+$D$99)^U6 -> 0
C52: Multi Family Value
C53: Commercial Value
C54: Total Value
B55: INFLATED - twice | C55: Cumulative Total Value | E55: =E47*(1+$D$99)^E$6 -> 0 | F55: =F47*(1+$D$99)^F$6 -> 14732064 | G55: =G47*(1+$D$99)^G$6 -> 58092303 | H55: =H47*(1+$D$99)^H$6 -> 1.0785366e+08 | I55: =I47*(1+$D$99)^I$6 -> 1.500612e+08 | J55: =J47*(1+$D$99)^J$6 -> 1.9909622e+08 | K55: =K47*(1+$D$99)^K$6 -> 2.5532614e+08 | L55: =L47*(1+$D$99)^L$6 -> 3.0511359e+08 | ... U55: =U47*(1+$D$99)^U$6 -> 3.0185874e+08
C56: Cumulative Units on Tax Roll (1) | E56: =E48 -> 0 | F56: =F48 -> 48 | G56: =G48 -> 184.75 | H56: =H48 -> 334.5 | I56: =I48 -> 452.75 | J56: =J48 -> 583 | K56: =K48 -> 725.5 | L56: =L48 -> 843 | ... U56: =U48 -> 950
C58: Assessed Value | E58: =(((E43+E44)*$G$97*$G$98)+(E45*$G$97*$G$99))*(1+$D$100)^E6 -> 0 | F58: =(((F43+F44)*$G$97*$G$98)+(F45*$G$97*$G$99)) -> 866592 | G58: =(((G43+G44)*$G$97*$G$98)+(G45*$G$97*$G$99)) -> 2483598.5 | H58: =(((H43+H44)*$G$97*$G$98)+(H45*$G$97*$G$99)) -> 2747784.5 | I58: =(((I43+I44)*$G$97*$G$98)+(I45*$G$97*$G$99)) -> 2220026.3 | J58: =(((J43+J44)*$G$97*$G$98)+(J45*$G$97*$G$99)) -> 2501653.4 | K58: =(((K43+K44)*$G$97*$G$98)+(K45*$G$97*$G$99)) -> 2783683.4 | L58: =(((L43+L44)*$G$97*$G$98)+(L45*$G$97*$G$99)) -> 2333846.5 | M58: =(((M43+M44)*$G$97*$G$98)+(M45*$G$97*$G$99)) -> 1412916.1 | ... U58: =(((U43+U44)*$G$97*$G$98)+(U45*$G$97*$G$99)) -> 0
C59: Existing Undeveloped AV (2) | E59: =D140*(1+$D$100)^E6 -> 0 | F59: =($E$59-($E$59*F86))*(1+$D$100)^F6 -> 0 | G59: =($E$59-($E$59*G86))*(1+$D$100)^G6 -> 0 | H59: =($E$59-($E$59*H86))*(1+$D$100)^H6 -> 0 | I59: =($E$59-($E$59*I86))*(1+$D$100)^I6 -> 0 | J59: =($E$59-($E$59*J86))*(1+$D$100)^J6 -> 0 | K59: =($E$59-($E$59*K86))*(1+$D$100)^K6 -> 0 | L59: =($E$59-($E$59*L86))*(1+$D$100)^L6 -> 0 | M59: =($E$59-($E$59*M86))*(1+$D$100)^M6 -> 0 | ... U59: =($E$59-($E$59*U86))*(1+$D$100)^U6 -> 0
C60: Total AV | E60: =SUM(E58:E59) -> 0 | F60: =SUM(F58:F59) -> 866592 | G60: =SUM(G58:G59) -> 2483598.5 | H60: =SUM(H58:H59) -> 2747784.5 | I60: =SUM(I58:I59) -> 2220026.3 | J60: =SUM(J58:J59) -> 2501653.4 | K60: =SUM(K58:K59) -> 2783683.4 | L60: =SUM(L58:L59) -> 2333846.5 | ... U60: =SUM(U58:U59) -> 0
C61: Total Cumulative AV | E61: =E58+E59+D61-D59 -> 0 | F61: =(F58+F59+E61-E59)*(1+$D$100) -> 883923.84 | G61: =(G58+G59+F61-F59)*(1+$D$100) -> 3434872.8 | H61: =(H58+H59+G61-G59)*(1+$D$100) -> 6306310.4 | I61: =(I58+I59+H61-H59)*(1+$D$100) -> 8696863.5 | J61: =(J58+J59+I61-I59)*(1+$D$100) -> 11422487 | K61: =(K58+K59+J61-J59)*(1+$D$100) -> 14490294 | L61: =(L58+L59+K61-K59)*(1+$D$100) -> 17160623 | M61: =(M58+M59+L61-L59)*(1+$D$100) -> 18945010 | ... U61: =(U58+U59+T61-T59)*(1+$D$100) -> 23085655
C63: Inflated
B64: =MAX(E64:U64) -> 23897772 | C64: Assessed Value | E64: =E55*$G$98*$G$97 -> 0 | F64: =F55*$G$98*$G$97 -> 883923.84 | G64: =G55*$G$98*$G$97 -> 3485538.2 | H64: =H55*$G$98*$G$97 -> 6471219.9 | I64: =I55*$G$98*$G$97 -> 9003672.1 | J64: =J55*$G$98*$G$97 -> 11945773 | K64: =K55*$G$98*$G$97 -> 15319568 | L64: =L55*$G$98*$G$97 -> 18306816 | ... U64: =U55*$G$98*$G$97 -> 18111524
C65: Existing Undeveloped AV (2) | E65: 2496 | F65: =$E$65*(1+$D$99)^F$6-($E$65*(1+$D$99)^F$6*F$86) -> 2031.3762 | G65: =$E$65*(1+$D$99)^G$6-($E$65*(1+$D$99)^G$6*G$86) -> 1626.4409 | H65: =$E$65*(1+$D$99)^H$6-($E$65*(1+$D$99)^H$6*H$86) -> 1433.1268 | I65: =$E$65*(1+$D$99)^I$6-($E$65*(1+$D$99)^I$6*I$86) -> 1040.885 | J65: =$E$65*(1+$D$99)^J$6-($E$65*(1+$D$99)^J$6*J$86) -> 643.9836 | K65: =$E$65*(1+$D$99)^K$6-($E$65*(1+$D$99)^K$6*K$86) -> 260.37823 | L65: =$E$65*(1+$D$99)^L$6-($E$65*(1+$D$99)^L$6*L$86) -> 90.540613 | M65: =$E$65*(1+$D$99)^M$6-($E$65*(1+$D$99)^M$6*M$86) -> 0 | ... U65: =$E$65*(1+$D$99)^U$6-($E$65*(1+$D$99)^U$6*U$86) -> 0
C66: Total AV | E66: =SUM(E64:E65) -> 2496 | F66: =SUM(F64:F65) -> 885955.22 | G66: =SUM(G64:G65) -> 3487164.6 | H66: =SUM(H64:H65) -> 6472653 | I66: =SUM(I64:I65) -> 9004713 | J66: =SUM(J64:J65) -> 11946417 | K66: =SUM(K64:K65) -> 15319829 | L66: =SUM(L64:L65) -> 18306906 | ... U66: =SUM(U64:U65) -> 18111524
C69: Cumulative Debt Service (3) | E69: =(E61/100*$G$100)*$G$104 -> 0 | F69: =(F61/100*$G$100)*$G$104 -> 35688.425 | G69: =(G61/100*$G$100)*$G$104 -> 138682.99 | H69: =(H61/100*$G$100)*$G$104 -> 254617.28 | I69: =(I61/100*$G$100)*$G$104 -> 351135.86 | J69: =(J61/100*$G$100)*$G$104 -> 461182.92 | K69: =(K61/100*$G$100)*$G$104 -> 585045.62 | L69: =(L61/100*$G$100)*$G$104 -> 692860.17 | ... U69: =(U61/100*$G$100)*$G$104 -> 932083.31
C70: Annual Debt Service (3) | E70: =(E60/100*$G$100)*$G$104 -> 0 | F70: =(F60/100*$G$100)*$G$104 -> 34988.652 | G70: =(G60/100*$G$100)*$G$104 -> 100275.29 | H70: =(H60/100*$G$100)*$G$104 -> 110941.8 | I70: =(I60/100*$G$100)*$G$104 -> 89633.561 | J70: =(J60/100*$G$100)*$G$104 -> 101004.26 | K70: =(K60/100*$G$100)*$G$104 -> 112391.22 | L70: =(L60/100*$G$100)*$G$104 -> 94229.052 | ... U70: =(U60/100*$G$100)*$G$104 -> 0
C71: O&M Funds | E71: =E61/100*$G$101 -> 0 | F71: =F61/100*$G$101 -> 2651.7715 | G71: =G61/100*$G$101 -> 10304.618 | H71: =H61/100*$G$101 -> 18918.931 | I71: =I61/100*$G$101 -> 26090.59 | J71: =J61/100*$G$101 -> 34267.462 | K71: =K61/100*$G$101 -> 43470.882 | L71: =L61/100*$G$101 -> 51481.87 | ... U71: =U61/100*$G$101 -> 69256.964
C72: Total Payment | E72: =SUM(E69+E71) -> 0 | F72: =SUM(F69+F71) -> 38340.197 | G72: =SUM(G69+G71) -> 148987.61 | H72: =SUM(H69+H71) -> 273536.22 | I72: =SUM(I69+I71) -> 377226.45 | J72: =SUM(J69+J71) -> 495450.38 | K72: =SUM(K69+K71) -> 628516.5 | L72: =SUM(L69+L71) -> 744342.04 | ... U72: =SUM(U69+U71) -> 1001340.3
C74: Potential Cumulative Bonding Capacity (4) | E74: =-PV($G$103,$G$102,E69) -> 0 | F74: =-PV($G$103,$G$102,F69) -> 502990.68 | G74: =-PV($G$103,$G$102,G69) -> 1954590.4 | H74: =-PV($G$103,$G$102,H69) -> 3588561.9 | I74: =-PV($G$103,$G$102,I69) -> 4948889.4 | J74: =-PV($G$103,$G$102,J69) -> 6499886.5 | K74: =-PV($G$103,$G$102,K69) -> 8245600.6 | L74: =-PV($G$103,$G$102,L69) -> 9765132.8 | ... U74: =-PV($G$103,$G$102,U69) -> 13136730
C75: Inflated
C76: Debt Service | E76: =E66/100*$G$100 -> 106.08 | F76: =F66/100*$G$100 -> 37653.097 | G76: =G66/100*$G$100 -> 148204.5 | H76: =H66/100*$G$100 -> 275087.75 | I76: =I66/100*$G$100 -> 382700.3 | J76: =J66/100*$G$100 -> 507722.72 | K76: =K66/100*$G$100 -> 651092.71 | L76: =L66/100*$G$100 -> 778043.51 | ... U76: =U66/100*$G$100 -> 769739.78
C77: O&M Funds | E77: =E66/100*$G$101 -> 7.488 | F77: =F66/100*$G$101 -> 2657.8656 | G77: =G66/100*$G$101 -> 10461.494 | H77: =H66/100*$G$101 -> 19417.959 | I77: =I66/100*$G$101 -> 27014.139 | J77: =J66/100*$G$101 -> 35839.251 | K77: =K66/100*$G$101 -> 45959.486 | L77: =L66/100*$G$101 -> 54920.718 | ... U77: =U66/100*$G$101 -> 54334.573
C78: Total PMT | E78: =SUM(E76:E77) -> 113.568 | F78: =SUM(F76:F77) -> 40310.962 | G78: =SUM(G76:G77) -> 158665.99 | H78: =SUM(H76:H77) -> 294505.71 | I78: =SUM(I76:I77) -> 409714.44 | J78: =SUM(J76:J77) -> 543561.98 | K78: =SUM(K76:K77) -> 697052.2 | L78: =SUM(L76:L77) -> 832964.23 | ... U78: =SUM(U76:U77) -> 824074.35
C80: Potential Bonding Capacity (3) | E80: =-PV($G$103,$G$102,E76) -> 1495.0856 | F80: =-PV($G$103,$G$102,F76) -> 530680.66 | G80: =-PV($G$103,$G$102,G76) -> 2088786 | H80: =-PV($G$103,$G$102,H76) -> 3877071.5 | I80: =-PV($G$103,$G$102,I76) -> 5393756.8 | J80: =-PV($G$103,$G$102,J76) -> 7155815.9 | K80: =-PV($G$103,$G$102,K76) -> 9176464.6 | L80: =-PV($G$103,$G$102,L76) -> 10965702 | ... U80: =-PV($G$103,$G$102,U76) -> 10848670
C82: Cumulative Proceeds | E82: =E74*$I$97 -> 0 | F82: =F74*$I$97 -> 472811.24 | G82: =G74*$I$97 -> 1837314.9 | H82: =H74*$I$97 -> 3373248.2 | I82: =I74*$I$97 -> 4651956 | J82: =J74*$I$97 -> 6109893.3 | K82: =K74*$I$97 -> 7750864.5 | L82: =L74*$I$97 -> 9179224.8 | ... U82: =U74*$I$97 -> 12348527
C83: Potential Annual Bonding Capacity (4) | E83: =PV($G$103,$G$102,-E$70) -> 0 | F83: =PV($G$103,$G$102,-F$70) -> 493128.12 | G83: =PV($G$103,$G$102,-G$70) -> 1413274.4 | H83: =PV($G$103,$G$102,-H$70) -> 1563607.6 | I83: =PV($G$103,$G$102,-I$70) -> 1263290.4 | J83: =PV($G$103,$G$102,-J$70) -> 1423548.4 | K83: =PV($G$103,$G$102,-K$70) -> 1584035.6 | L83: =PV($G$103,$G$102,-L$70) -> 1328059 | ... U83: =PV($G$103,$G$102,-U$70) -> 0
C84: Annual Proceeds | E84: =E$83*$I$97 -> 0 | F84: =F$83*$I$97 -> 463540.43 | G84: =G$83*$I$97 -> 1328477.9 | H84: =H$83*$I$97 -> 1469791.1 | I84: =I$83*$I$97 -> 1187493 | J84: =J$83*$I$97 -> 1338135.5 | K84: =K$83*$I$97 -> 1488993.5 | L84: =L$83*$I$97 -> 1248375.5 | ... U84: =U$83*$I$97 -> 0
C86: Reduction of Beginning Land | D86: Cumulative | E86: =(1-(-E35/$D$97))-1 -> 0 | F86: =(1-(-F35/$D$97))-1 -> 0.20210526 | G86: =(1-(-G35/$D$97))-1 -> 0.37368421 | H86: =(1-(-H35/$D$97))-1 -> 0.45894737 | I86: =(1-(-I35/$D$97))-1 -> 0.61473684 | J86: =(1-(-J35/$D$97))-1 -> 0.76631579 | K86: =(1-(-K35/$D$97))-1 -> 0.90736842 | L86: =(1-(-L35/$D$97))-1 -> 0.96842105 | ... U86: =(1-(-U35/$D$97))-1 -> 1
D87: Annual | E87: =E86 -> 0 | F87: =MAX(0,F86-E86) -> 0.20210526 | G87: =MAX(0,G86-F86) -> 0.17157895 | H87: =MAX(0,H86-G86) -> 0.085263158 | I87: =MAX(0,I86-H86) -> 0.15578947 | J87: =MAX(0,J86-I86) -> 0.15157895 | K87: =MAX(0,K86-J86) -> 0.14105263 | L87: =MAX(0,L86-K86) -> 0.061052632 | M87: =MAX(0,M86-L86) -> 0.031578947 | ... U87: =MAX(0,U86-T86) -> 0
B89: Footnotes:
B90: 1 | C90: Assumes the following: 25% of homes sales will be placed on the County tax rolls in the year in which they are constructed and sold, 50% will be placed on the tax rolls in the following year, and the remaining 25% will be placed on the tax rolls in year three.
B91: 2 | C91: Source: Pima/Pinal County Assessor
B92: 3 | C92: Represents 95% of the total amount for debt service to account for potential delinquency.
B93: 4 | C93: ="Assumes the following: "&$G$102&" year amortization period, "&TEXT(G103,"0.00%")&" interest rate. The number represents the cumulative bonding capacity for the year indicated." -> Assumes the following: 25 year amortization period, 5.00% interest rate. The number represents the cumulative bonding capacity for the year indicated.
C95: Assumptions
C97: Total Absorption | D97: =SUM(E10:U10,E26:U26) -> 950 | F97: FCV Ratio | G97: 0.6 | I97: ='Source Use'!C52 -> 0.94
C98: Absorption / Mo | D98: 0 | F98: Residential AV Ratio | G98: 0.1
C99: Price Inflation Rate | D99: 0.02 | F99: Commercial AV Ratio | G99: 0.18
C100: Tax Roll AV Inflation Rate | D100: 0.02 | F100: Tax Rate for Debt Service | G100: 4.25
C101: Cost Inflation Rate | D101: 0.02 | F101: O&M | G101: 0.3 | L101: =C84 -> Annual Proceeds | M101: =F84 -> 463540.43
C102: Tax Rolled | F102: Term | G102: 25
C103: Year 1 | D103: 0.25 | F103: Rate | G103: 0.05 | L103: Potential Annual Bonding | M103: =F83 -> 493128.12 | N103: PV of
C104: Year 2 | D104: 0.5 | F104: Delinquency Factor | G104: 0.95 | L104: =C70 -> Annual Debt Service (3) | M104: total AV * tax rate
C105: Year 3 | D105: 0.25 | F105: Avg. Home Price | G105: 295000
F108: Commercial Acreage to EDU Conversion Area Below
A110: OLD PARCELS | C110: Parcels | D110: AV
C111: Pima Assessors Report Dated: 2/22/19 | F111: Village II Commercial
A112: 21706001C | C112: 21706001C (TMR INVESTORS LLC) | D112: 10488 | E112: 80 | O112: Q1 2009 | P112: Q3 2015 | Q112: construction time | S112: # quarters | T112: # of Years | U112: # EDUs per Year
A113: 21706001D | C113: 21706001F (TMR INVESTORS LLC) | D113: 75 | E113: 83 | F113: Acres | G113: Price/Ft. | H113: FAR | I113: Sq Ft | J113: Avg. Home Price | K113: EDUs/Acre | L113: Units | O113: Q1 2010 | P113: Q3 2016 | Q113: 1 year from start of construction | S113: 27 | T113: 6 | U113: =L114/T113 -> 0
A114: 217060020 | C114: 21706001G (TMR INVESTORS LLC) | D114: 83 | E114: 7040 | F114: 0 | G114: 250 | H114: 0.25 | I114: =F114*43560*H114 -> 0 | J114: 260000 | K114: =43560*H114*G114/J114 -> 10.471154 | L114: =K114*F114 -> 0 | T114: *we phased this commercial in over 6 years starting in 2010
A115: 21707001A | C115: 21706001H (TMR INVESTORS LLC) | D115: 75 | E115: 80
A116: 21707001B | C116: 21707001A (TMR INVESTORS LLC) | D116: 14051 | E116: 3903
A117: 217070020 | C117: 217070020 (TMR INVESTORS LLC) | D117: 75 | E117: 80 | F117: Village IV Commercial
A118: 21707003A | C118: 21707003C (TMR INVESTORS LLC) | D118: 7397 | E118: 2496 | O118: Q3 2008 | P118: Q1 2014 | Q118: construction time | S118: # quarters | T118: # of Years | U118: # EDUs per year
A119: 21707003B | C119: 217080030 (TMR INVESTORS LLC) | D119: 83 | E119: 2406 | F119: Acres | G119: Price/Ft. | H119: FAR | I119: Sq Ft | J119: Avg. Home Price | K119: EDUs/Acre | L119: Units | O119: Q1 2010 | P119: Q1 2015 | Q119: 1 year from start of construction | S119: 23 | T119: 6 | U119: =L120/T119 -> 0
A120: 21707004B | C120: 21708004C (TMR INVESTORS LLC) | D120: 89 | E120: 80 | F120: 0 | G120: 250 | H120: 0.25 | I120: =F120*43560*H120 -> 0 | J120: 260000 | K120: =43560*H120*G120/J120 -> 10.471154 | L120: =K120*F120 -> 0 | T120: *we phased this commercial in over 6 years starting in 2010
A121: 21707004C | C121: 21708004D (TMR INVESTORS LLC) | D121: 99 | E121: 6253
...
