Workbook

Sheet Executive Summary
B4: =Assumptions!C3&" Executive Summary" -> Brownstone Apartments Executive Summary
B6: Property Summary | E6: Project Capitalization | H6: Financing Assumptions | J6: Refinancing Assumptions
B8: Property Name | C8: =Assumptions!C3 -> Brownstone Apartments | E8: Purchase Price | F8: =Assumptions!C23 -> 3725000 | H8: Loan Amount | I8: ='Loan Summary'!G30 -> 2778100 | J8: Loan Amount | K8: =IF(OR(Assumptions!$AD$3>'Sale Analysis'!$E$3,Assumptions!$AD$3=""),"",ROUND('Loan Summary'!C9,-3)) -> 3740000
B9: Property Address | C9: =Assumptions!C4 -> 9559 Flower St | E9: Closing Costs & Reserves | F9: =ROUND(Assumptions!C24,-3) -> 65000 | H9: Loan Type | I9: =Assumptions!W2 -> Bridge | J9: Interest Rate | K9: =IF(OR(Assumptions!$AD$3>'Sale Analysis'!$E$3,Assumptions!$AD$3>=""),"",'Loan Summary'!C10) -> 0.055
B10: City, State | C10: =Assumptions!C5 -> Bellflower, CA 90706 | E10: Capital Expenditures | F10: =ROUND(Assumptions!C28+Assumptions!C45,-3) -> 484000 | H10: Interest Rate | I10: ='Loan Summary'!C3 -> 0.0585 | J10: Refi Cap Rate | K10: =IF(OR(Assumptions!$AD$3>'Sale Analysis'!$E$3,Assumptions!$AD$3=""),"",Assumptions!AD9) -> 0.0575
B11: Year Built | C11: =Assumptions!C6 -> 1967 | E11: Total Capitalization | F11: =SUM(F8:F10) -> 4274000 | H11: LTC | I11: =G13 -> 0.6499766 | J11: Net Refi Proceeds | K11: =IFERROR(ROUND(Assumptions!AD26,-3),"") -> 943000
B12: Total Units | C12: =Assumptions!C10 -> 17 | E12: Total Equity | F12: =ROUND(Assumptions!C36,-3) -> 1498000 | G12: =F12/F11 -> 0.35049134 | H12: Term* | I12: ='Loan Summary'!C5 -> 60 | J12: % of Equity Returned | K12: =IFERROR(K11/F12,"") -> 0.62950601
B13: Purchase Price/Per Unit | C13: =Assumptions!C23/Assumptions!C10 -> 219117.65 | E13: Total Debt & Pref. Equity | F13: =ROUND(I8,-3) -> 2778000 | G13: =F13/F11 -> 0.6499766 | H13: I/O Period | I13: ='Loan Summary'!C6 -> 60 | J13: Refi Month | K13: =IF(OR(Assumptions!$AD$3>'Sale Analysis'!$E$3,Assumptions!$AD$3=""),"",Assumptions!AD3) -> 35
B14: Purchase Price/Per Sqft. | C14: =Assumptions!C23/C15 -> 313.84278 | J14: TLV Max | K14: =IF(OR(Assumptions!$AD$3>'Sale Analysis'!$E$3,Assumptions!$AD$3=""),"",Assumptions!AD11) -> 0.7
B15: Gross Rentable Square Footage | C15: =Assumptions!C9 -> 11869 | J15: DSCR Max | K15: =IF(OR(Assumptions!$AD$3>'Sale Analysis'!$E$3,Assumptions!$AD$3=""),"",Assumptions!AD16) -> 1.25
B17: Economics | E17: Sale Analysis | H17: Unit Type | I17: # of units | J17: Current Rent | K17: Proforma Rent
B19: Deal Returns | E19: Sale Price | F19: ='Sale Analysis'!E11 -> 5406000 | H19: =IF(H18="TOTAL","",IF('Unit Mix'!B4=0,'Unit Mix'!$B$18,'Unit Mix'!B4)) -> Stu - ADU | I19: =IF('Unit Mix'!C4=0,'Unit Mix'!$C$18,'Unit Mix'!C4) -> 1 | J19: =IF('Unit Mix'!E4=0,'Unit Mix'!$E$18,'Unit Mix'!E4) -> 1340 | K19: =IF('Unit Mix'!H4="",'Unit Mix'!$H$18,'Unit Mix'!H4) -> 1650
B20: Total Investment | C20: =-ROUND('Waterfall Split'!C55,-3) -> 1498000 | E20: Proceeds From Sale | F20: ='Sale Analysis'!E18 -> 1553458.1 | H20: =IF(OR(H19="TOTAL",H19=""),"",IF('Unit Mix'!B5=0,'Unit Mix'!$B$18,'Unit Mix'!B5)) -> 1x1 | I20: =IF(OR(H19="TOTAL",H19=""),"",IF('Unit Mix'!C5=0,'Unit Mix'!$C$18,'Unit Mix'!C5)) -> 9 | J20: =IF(OR(H19="TOTAL",H19=""),"",IF('Unit Mix'!E5=0,'Unit Mix'!$E$18,'Unit Mix'!E5)) -> 1427 | K20: =IF(OR(H19="TOTAL",H19=""),"",IF('Unit Mix'!H5="",'Unit Mix'!$H$18,'Unit Mix'!H5)) -> 1925
B21: Gross Distributions | C21: =ROUND('Waterfall Split'!C56,-3) -> 2965000 | E21: Sale Cap Rate | F21: ='Sale Analysis'!E4 -> 0.0575 | H21: =IF(OR(H20="TOTAL",H20=""),"",IF('Unit Mix'!B6=0,'Unit Mix'!$B$18,'Unit Mix'!B6)) -> 2x1 | I21: =IF(OR(H20="TOTAL",H20=""),"",IF('Unit Mix'!C6=0,'Unit Mix'!$C$18,'Unit Mix'!C6)) -> 7 | J21: =IF(OR(H20="TOTAL",H20=""),"",IF('Unit Mix'!E6=0,'Unit Mix'!$E$18,'Unit Mix'!E6)) -> 1676 | K21: =IF(OR(H20="TOTAL",H20=""),"",IF('Unit Mix'!H6="",'Unit Mix'!$H$18,'Unit Mix'!H6)) -> 2250
B22: Gross Equity Multiple | C22: ='Waterfall Split'!C59 -> 1.9795314 | E22: Sale Month | F22: ='Sale Analysis'!E3 -> 83 | H22: =IF(OR(H21="TOTAL",H21=""),"",IF('Unit Mix'!B7=0,'Unit Mix'!$B$18,'Unit Mix'!B7)) -> TOTAL | I22: =IF(OR(H21="TOTAL",H21=""),"",IF('Unit Mix'!C7=0,'Unit Mix'!$C$18,'Unit Mix'!C7)) -> 17 | J22: =IF(OR(H21="TOTAL",H21=""),"",IF('Unit Mix'!E7=0,'Unit Mix'!$E$18,'Unit Mix'!E7)) -> 1524.4118 | K22: =IF(OR(H21="TOTAL",H21=""),"",IF('Unit Mix'!H7="",'Unit Mix'!$H$18,'Unit Mix'!H7)) -> 2042.6471
B23: Gross IRR | C23: ='Waterfall Split'!C58 -> 0.15240298 | H23: =IF(OR(H22="TOTAL",H22=""),"",IF('Unit Mix'!B8=0,'Unit Mix'!$B$18,'Unit Mix'!B8)) | I23: =IF(OR(H22="TOTAL",H22=""),"",IF('Unit Mix'!C8=0,'Unit Mix'!$C$18,'Unit Mix'!C8)) | J23: =IF(OR(H22="TOTAL",H22=""),"",IF('Unit Mix'!E8=0,'Unit Mix'!$E$18,'Unit Mix'!E8)) | K23: =IF(OR(H22="TOTAL",H22=""),"",IF('Unit Mix'!H8="",'Unit Mix'!$H$18,'Unit Mix'!H8))
B24: Investor Returns | H24: =IF(OR(H23="TOTAL",H23=""),"",IF('Unit Mix'!B9=0,'Unit Mix'!$B$18,'Unit Mix'!B9)) | I24: =IF(OR(H23="TOTAL",H23=""),"",IF('Unit Mix'!C9=0,'Unit Mix'!$C$18,'Unit Mix'!C9)) | J24: =IF(OR(H23="TOTAL",H23=""),"",IF('Unit Mix'!E9=0,'Unit Mix'!$E$18,'Unit Mix'!E9)) | K24: =IF(OR(H23="TOTAL",H23=""),"",IF('Unit Mix'!H9="",'Unit Mix'!$H$18,'Unit Mix'!H9))
B25: Total Investment | C25: =-ROUND('Waterfall Split'!C62,-3) -> 1423000 | H25: =IF(OR(H24="TOTAL",H24=""),"",IF('Unit Mix'!B10=0,'Unit Mix'!$B$18,'Unit Mix'!B10)) | I25: =IF(OR(H24="TOTAL",H24=""),"",IF('Unit Mix'!C10=0,'Unit Mix'!$C$18,'Unit Mix'!C10)) | J25: =IF(OR(H24="TOTAL",H24=""),"",IF('Unit Mix'!E10=0,'Unit Mix'!$E$18,'Unit Mix'!E10)) | K25: =IF(OR(H24="TOTAL",H24=""),"",IF('Unit Mix'!H10="",'Unit Mix'!$H$18,'Unit Mix'!H10))
B26: Gross Distributions | C26: =ROUND('Waterfall Split'!C63,-3) -> 2544000 | E26: CoC Dist. | G26: YoC | H26: =IF(OR(H25="TOTAL",H25=""),"",IF('Unit Mix'!B11=0,'Unit Mix'!$B$18,'Unit Mix'!B11)) | I26: =IF(OR(H25="TOTAL",H25=""),"",IF('Unit Mix'!C11=0,'Unit Mix'!$C$18,'Unit Mix'!C11)) | J26: =IF(OR(H25="TOTAL",H25=""),"",IF('Unit Mix'!E11=0,'Unit Mix'!$E$18,'Unit Mix'!E11)) | K26: =IF(OR(H25="TOTAL",H25=""),"",IF('Unit Mix'!H11="",'Unit Mix'!$H$18,'Unit Mix'!H11))
B27: Net Equity Multiple | C27: ='Waterfall Split'!C66 -> 1.788103 | E27: Year 1 | F27: ='Cash Flow Summary'!D29 -> 0 | G27: ='Cash Flow Summary'!E15 -> 0.065173381 | H27: =IF(OR(H26="TOTAL",H26=""),"",IF('Unit Mix'!B12=0,'Unit Mix'!$B$18,'Unit Mix'!B12)) | I27: =IF(OR(H26="TOTAL",H26=""),"",IF('Unit Mix'!C12=0,'Unit Mix'!$C$18,'Unit Mix'!C12)) | J27: =IF(OR(H26="TOTAL",H26=""),"",IF('Unit Mix'!E12=0,'Unit Mix'!$E$18,'Unit Mix'!E12)) | K27: =IF(OR(H26="TOTAL",H26=""),"",IF('Unit Mix'!H12="",'Unit Mix'!$H$18,'Unit Mix'!H12))
B28: Net IRR | C28: ='Waterfall Split'!C65 -> 0.13274836 | E28: Year 2 | F28: ='Cash Flow Summary'!E29 -> 0.05 | G28: ='Cash Flow Summary'!F15 -> 0.075702648 | H28: =IF(OR(H27="TOTAL",H27=""),"",IF('Unit Mix'!B13=0,'Unit Mix'!$B$18,'Unit Mix'!B13)) | I28: =IF(OR(H27="TOTAL",H27=""),"",IF('Unit Mix'!C13=0,'Unit Mix'!$C$18,'Unit Mix'!C13)) | J28: =IF(OR(H27="TOTAL",H27=""),"",IF('Unit Mix'!E13=0,'Unit Mix'!$E$18,'Unit Mix'!E13)) | K28: =IF(OR(H27="TOTAL",H27=""),"",IF('Unit Mix'!H13="",'Unit Mix'!$H$18,'Unit Mix'!H13))
E29: =IF(F22<24,"","Year 3") -> Year 3 | F29: =IF(F22<24,"",'Cash Flow Summary'!F29) -> 0.075 | G29: =IF(F22<24,"",'Cash Flow Summary'!G15) -> 0.075010153 | H29: =IF(OR(H28="TOTAL",H28=""),"",IF('Unit Mix'!B14=0,'Unit Mix'!$B$18,'Unit Mix'!B14)) | I29: =IF(OR(H28="TOTAL",H28=""),"",IF('Unit Mix'!C14=0,'Unit Mix'!$C$18,'Unit Mix'!C14)) | J29: =IF(OR(H28="TOTAL",H28=""),"",IF('Unit Mix'!E14=0,'Unit Mix'!$E$18,'Unit Mix'!E14)) | K29: =IF(OR(H28="TOTAL",H28=""),"",IF('Unit Mix'!H14="",'Unit Mix'!$H$18,'Unit Mix'!H14))
E30: =IF(F22<36,"","Year 4") -> Year 4 | F30: =IF(F22<36,"",'Cash Flow Summary'!G29) -> 0.12 | G30: =IF(F22<36,"",'Cash Flow Summary'!H15) -> 0.076101844 | H30: =IF(OR(H29="TOTAL",H29=""),"",IF('Unit Mix'!B15=0,'Unit Mix'!$B$18,'Unit Mix'!B15)) | I30: =IF(OR(H29="TOTAL",H29=""),"",IF('Unit Mix'!C15=0,'Unit Mix'!$C$18,'Unit Mix'!C15)) | J30: =IF(OR(H29="TOTAL",H29=""),"",IF('Unit Mix'!E15=0,'Unit Mix'!$E$18,'Unit Mix'!E15)) | K30: =IF(OR(H29="TOTAL",H29=""),"",IF('Unit Mix'!H15="",'Unit Mix'!$H$18,'Unit Mix'!H15))
E31: =IF(F22<48,"","Year 5") -> Year 5 | F31: =IF(F22<48,"",'Cash Flow Summary'!H29) -> 0.13 | G31: =IF(F22<48,"",'Cash Flow Summary'!I15) -> 0.077036158 | H31: =IF(OR(H30="TOTAL",H30=""),"",IF('Unit Mix'!B16=0,'Unit Mix'!$B$18,'Unit Mix'!B16)) | I31: =IF(OR(H30="TOTAL",H30=""),"",IF('Unit Mix'!C16=0,'Unit Mix'!$C$18,'Unit Mix'!C16)) | J31: =IF(OR(H30="TOTAL",H30=""),"",IF('Unit Mix'!E16=0,'Unit Mix'!$E$18,'Unit Mix'!E16)) | K31: =IF(OR(H30="TOTAL",H30=""),"",IF('Unit Mix'!H16="",'Unit Mix'!$H$18,'Unit Mix'!H16))
E32: =IF(F22<60,"","Year 6") -> Year 6 | F32: =IF(F22<60,"",'Cash Flow Summary'!I29) -> 0.14 | G32: =IF(F22<60,"",'Cash Flow Summary'!J15) -> 0.077987488 | I32: =IF(OR(H31="TOTAL",H31=""),"",IF('Unit Mix'!C17=0,'Unit Mix'!$C$18,'Unit Mix'!C17)) | J32: =IF(OR(H31="TOTAL",H31=""),"",IF('Unit Mix'!E17=0,'Unit Mix'!$E$18,'Unit Mix'!E17)) | K32: =IF(OR(H31="TOTAL",H31=""),"",IF('Unit Mix'!H17="",'Unit Mix'!$H$18,'Unit Mix'!H17))
E33: =IF(F22<72,"","Year 7") -> Year 7 | F33: =IF(F22<72,"",'Cash Flow Summary'!J29) -> 0.15 | G33: =IF(F22<72,"",'Cash Flow Summary'!J15) -> 0.077987488

Sheet Sale Matrix
B2: Sale Matrix
B3: Exit Cap Rate | C3: ='Sale Analysis'!C4 -> 0.0525 | D3: ='Sale Analysis'!D4 -> 0.055 | E3: ='Sale Analysis'!E4 -> 0.0575 | F3: ='Sale Analysis'!F4 -> 0.06 | G3: ='Sale Analysis'!G4 -> 0.0625
B4: Total Investment | C4: =ROUND('Sale Analysis'!C20,-3) -> 1498000 | D4: =ROUND('Sale Analysis'!D20,-3) -> 1498000 | E4: =ROUND('Sale Analysis'!E20,-3) -> 1498000 | F4: =ROUND('Sale Analysis'!F20,-3) -> 1498000 | G4: =ROUND('Sale Analysis'!G20,-3) -> 1498000
B5: Gross Distributions | C5: =ROUND('Sale Analysis'!C20+'Sale Analysis'!C21,-3) -> 3369000 | D5: =ROUND('Sale Analysis'!D20+'Sale Analysis'!D21,-3) -> 3160000 | E5: =ROUND('Sale Analysis'!E20+'Sale Analysis'!E21,-3) -> 2965000 | F5: =ROUND('Sale Analysis'!F20+'Sale Analysis'!F21,-3) -> 2783000 | G5: =ROUND('Sale Analysis'!G20+'Sale Analysis'!G21,-3) -> 2614000
B6: Gross Equity Multiple | C6: ='Sale Analysis'!C22 -> 2.249616 | D6: ='Sale Analysis'!D22 -> 2.1097161 | E6: ='Sale Analysis'!E22 -> 1.9795314 | F6: ='Sale Analysis'!F22 -> 1.8584143 | G6: ='Sale Analysis'!G22 -> 1.7457171
B7: Gross IRR | C7: ='Sale Analysis'!C23 -> 0.17656094 | D7: ='Sale Analysis'!D23 -> 0.16449794 | E7: ='Sale Analysis'!E23 -> 0.15240298 | F7: ='Sale Analysis'!F23 -> 0.14025808 | G7: ='Sale Analysis'!G23 -> 0.12803772

Sheet P&L OM
B4: =Assumptions!C3 -> Brownstone Apartments
B5: Proforma Operating Statement
C6: Year 1 | D6: Year 2 | E6: Year 3 | F6: Year 4
B7: Revenue
B8: Gross Potential Rent | C8: ='Monthly Cash Flow'!P10 -> 418953.69 | D8: ='Monthly Cash Flow'!AC10 -> 426544.74 | E8: ='Monthly Cash Flow'!AP10 -> 437208.36 | F8: ='Monthly Cash Flow'!BC10 -> 448138.57
B9: Loss to Lease | C9: ='Monthly Cash Flow'!P11 -> 77858.225 | D9: ='Monthly Cash Flow'!AC11 -> 13584.558 | E9: ='Monthly Cash Flow'!AP11 -> 5410.3301 | F9: ='Monthly Cash Flow'!BC11 -> 8214.1492
B10: Gross Rental Income | C10: ='Monthly Cash Flow'!P12 -> 341095.47 | D10: ='Monthly Cash Flow'!AC12 -> 412960.18 | E10: ='Monthly Cash Flow'!AP12 -> 431798.03 | F10: ='Monthly Cash Flow'!BC12 -> 439924.42
B11: Loss to Vacancy | C11: ='Monthly Cash Flow'!P13+'Monthly Cash Flow'!P14 -> -45882.087 | D11: ='Monthly Cash Flow'!AC13+'Monthly Cash Flow'!AC14 -> -41454.616 | E11: ='Monthly Cash Flow'!AP13+'Monthly Cash Flow'!AP14 -> -12953.941 | F11: ='Monthly Cash Flow'!BC13+'Monthly Cash Flow'!BC14 -> -13197.733
B12: Concessions | C12: ='Monthly Cash Flow'!P16 -> 0 | D12: ='Monthly Cash Flow'!AC16 -> 0 | E12: ='Monthly Cash Flow'!AP16 -> 0 | F12: ='Monthly Cash Flow'!BC16 -> 0
B13: RUBS Income | C13: ='Monthly Cash Flow'!P28 -> 3019.6078 | D13: ='Monthly Cash Flow'!AC28 -> 10298.235 | E13: ='Monthly Cash Flow'!AP28 -> 11767 | F13: ='Monthly Cash Flow'!BC28 -> 12061.175
B14: Other Income | C14: ='Monthly Cash Flow'!P30-C13 -> 8567.1 | D14: ='Monthly Cash Flow'!AC30-D13 -> 11417.1 | E14: ='Monthly Cash Flow'!AP30-E13 -> 11417.1 | F14: ='Monthly Cash Flow'!BC30-F13 -> 11417.1
B15: Total Revenue | C15: =SUM(C10:C14) -> 306800.09 | D15: =SUM(D10:D14) -> 393220.9 | E15: =SUM(E10:E14) -> 442028.19 | F15: =SUM(F10:F14) -> 450204.96
B16: Per Unit | C16: =C15/Assumptions!$C$10 -> 18047.064 | D16: =D15/Assumptions!$C$10 -> 23130.641 | E16: =E15/Assumptions!$C$10 -> 26001.658 | F16: =F15/Assumptions!$C$10 -> 26482.645
B17: Incr % YoY | D17: =(D15/C15)-1 -> 0.28168444 | E17: =(E15/D15)-1 -> 0.1241218 | F17: =(F15/E15)-1 -> 0.018498307
B18: Operating Expenses
B19: Property Taxes | C19: ='Monthly Cash Flow'!P36 -> 45817.5 | D19: ='Monthly Cash Flow'!AC36 -> 46733.85 | E19: ='Monthly Cash Flow'!AP36 -> 47668.527 | F19: ='Monthly Cash Flow'!BC36 -> 48621.898
B20: Insurance | C20: ='Monthly Cash Flow'!P37 -> 14000 | D20: ='Monthly Cash Flow'!AC37 -> 14350 | E20: ='Monthly Cash Flow'!AP37 -> 14708.75 | F20: ='Monthly Cash Flow'!BC37 -> 15076.469
B21: Property Mgmt Fee | C21: ='Monthly Cash Flow'!P38 -> 9204.0027 | D21: ='Monthly Cash Flow'!AC38 -> 11796.627 | E21: ='Monthly Cash Flow'!AP38 -> 13260.846 | F21: ='Monthly Cash Flow'!BC38 -> 13506.149
B22: Utilities | C22: ='Monthly Cash Flow'!P47 -> 14000 | D22: ='Monthly Cash Flow'!AC47 -> 14350 | E22: ='Monthly Cash Flow'!AP47 -> 14708.75 | F22: ='Monthly Cash Flow'!BC47 -> 15076.469
B23: R&M | C23: ='Monthly Cash Flow'!P49 -> 12750 | D23: ='Monthly Cash Flow'!AC49 -> 13068.75 | E23: ='Monthly Cash Flow'!AP49 -> 13395.469 | F23: ='Monthly Cash Flow'!BC49 -> 13730.355
B24: Turnover | C24: ='Monthly Cash Flow'!P50 -> 0 | D24: ='Monthly Cash Flow'!AC50 -> 0 | E24: ='Monthly Cash Flow'!AP50 -> 0 | F24: ='Monthly Cash Flow'!BC50 -> 8500
B25: Grounds/Landscaping | C25: ='Monthly Cash Flow'!P51 -> 3500 | D25: ='Monthly Cash Flow'!AC51 -> 3587.5 | E25: ='Monthly Cash Flow'!AP51 -> 3677.1875 | F25: ='Monthly Cash Flow'!BC51 -> 3769.1172
B26: Advertising | C26: ='Monthly Cash Flow'!P52 -> 1500 | D26: ='Monthly Cash Flow'!AC52 -> 1537.5 | E26: ='Monthly Cash Flow'!AP52 -> 1575.9375 | F26: ='Monthly Cash Flow'!BC52 -> 1615.3359
B27: Administration | C27: ='Monthly Cash Flow'!P53 -> 0 | D27: ='Monthly Cash Flow'!AC53 -> 0 | E27: ='Monthly Cash Flow'!AP53 -> 0 | F27: ='Monthly Cash Flow'!BC53 -> 0
B28: Payroll | C28: ='Monthly Cash Flow'!P54 -> 9000 | D28: ='Monthly Cash Flow'!AC54 -> 9225 | E28: ='Monthly Cash Flow'!AP54 -> 9455.625 | F28: ='Monthly Cash Flow'!BC54 -> 9692.0156
B29: Total operating Expenses | C29: =SUM(C19:C28) -> 109771.5 | D29: =SUM(D19:D28) -> 114649.23 | E29: =SUM(E19:E28) -> 118451.09 | F29: =SUM(F19:F28) -> 129587.81
B30: Per Unit | C30: =C29/Assumptions!$C$10 -> 6457.1472 | D30: =D29/Assumptions!$C$10 -> 6744.0722 | E30: =E29/Assumptions!$C$10 -> 6967.7113 | F30: =F29/Assumptions!$C$10 -> 7622.8122
B31: % of Net Rental Income | C31: =C29/C15 -> 0.35779488 | D31: =D29/D15 -> 0.29156443 | E31: =E29/E15 -> 0.2679718 | F31: =F29/F15 -> 0.2878418
B33: Net Operating Income | C33: =C15-C29 -> 197028.59 | D33: =D15-D29 -> 278571.68 | E33: =E15-E29 -> 323577.1 | F33: =F15-F29 -> 320617.15
B34: Per Unit | C34: =C33/Assumptions!$C$10 -> 11589.917 | D34: =D33/Assumptions!$C$10 -> 16386.569 | E34: =E33/Assumptions!$C$10 -> 19033.947 | F34: =F33/Assumptions!$C$10 -> 18859.833
B35: Operating Margin (%) | C35: =C33/C15 -> 0.64220512 | D35: =D33/D15 -> 0.70843557 | E35: =E33/E15 -> 0.7320282 | F35: =F33/F15 -> 0.7121582
B36: Incr % YoY | D36: =(D33/C33)-1 -> 0.41386425 | E36: =(E33/D33)-1 -> 0.16155778 | F36: =(F33/E33)-1 -> -0.0091475681
B37: F&C Yield on Cost | C37: ='Cash Flow Summary'!D15 -> 0.046095926 | D37: ='Cash Flow Summary'!E15 -> 0.065173381 | E37: ='Cash Flow Summary'!F15 -> 0.075702648 | F37: ='Cash Flow Summary'!G15 -> 0.075010153

Sheet Cash Flow OM
B4: =Assumptions!C3 -> Brownstone Apartments
B5: Proforma Cash Flow Summary
C6: Year 0 | D6: Year 1 | E6: Year 2 | F6: Year 3
B8: Net Operating Income | D8: ='Cash Flow Summary'!D13 -> 197028.59 | E8: ='Cash Flow Summary'!E13 -> 278571.68 | F8: ='Cash Flow Summary'!F13 -> 323577.1
B10: Other Cash Sources (Uses)
B12: Acquisition Cost
B13: Purchase Price | C13: =-Assumptions!C23 -> -3725000
B14: Closing and Formation Costs | C14: =-Assumptions!C24 -> -65030
B16: Financing
B17: Senior Loan Proceeds | C17: =Assumptions!C16 -> 2357500 | D17: =SUM('Loan Summary'!K2:K13) -> 286827.94 | E17: =SUM('Loan Summary'!K14:K25) -> 133772.06 | F17: =SUM('Loan Summary'!K26:K37) -> 0
B18: Refinance Proceeds | D18: =SUM('Cont. Dist.'!D13:O13) -> 0 | E18: =SUM('Cont. Dist.'!P13:AA13) -> 0 | F18: =SUM('Cont. Dist.'!AB13:AM13) -> 943390.35
B19: Debt Service | D19: =-'Cash Flow Summary'!D18-'Cash Flow Summary'!D19 -> -146549.76 | E19: =-'Cash Flow Summary'!E18-'Cash Flow Summary'!E19 -> -159910.29 | F19: =-'Cash Flow Summary'!F18-'Cash Flow Summary'!F19 -> -169717.46
B20: Debt Repayment | D20: =IF(AND('Sale Analysis'!$E$3>0,'Sale Analysis'!$E$3<13),'Sale Analysis'!$E$13,0) -> 0 | E20: =IF(AND('Sale Analysis'!$E$3>12,'Sale Analysis'!$E$3<25),'Sale Analysis'!$E$13,0) -> 0 | F20: =IF(AND('Sale Analysis'!$E$3>24,'Sale Analysis'!$E$3<37),'Sale Analysis'!$E$13,0) -> 0
B22: Renovation Budget
B23: Interior Renovations & Buyouts | D23: =-'Monthly Cash Flow'!P81*(1-'Renovation Budget'!$D$18) -> -181547.79 | E23: =('Monthly Cash Flow'!AC81*(1-'Renovation Budget'!$D$18))*-1 -> -127083.46 | F23: =('Monthly Cash Flow'!AP81*(1-'Renovation Budget'!$D$18))*-1 -> 0
B24: Exterior Renovations | D24: =('Monthly Cash Flow'!P82*(1-'Renovation Budget'!$D$18))*-1 -> -89585 | E24: =('Monthly Cash Flow'!AC82*(1-'Renovation Budget'!$D$18))*-1 -> 0 | F24: =('Monthly Cash Flow'!AP82*(1-'Renovation Budget'!$D$18))*-1 -> 0
B26: Sale Proceeds
B27: Sale Price | D27: =IF(AND('Sale Analysis'!$E$3>0,'Sale Analysis'!$E$3<13),'Sale Analysis'!$E$11,0) -> 0 | E27: =IF(AND('Sale Analysis'!$E$3>12,'Sale Analysis'!$E$3<25),'Sale Analysis'!$E$11,0) -> 0 | F27: =IF(AND('Sale Analysis'!$E$3>24,'Sale Analysis'!$E$3<37),'Sale Analysis'!$E$11,0) -> 0
B28: Selling Expenses | D28: =IF(AND('Sale Analysis'!$E$3>0,'Sale Analysis'!$E$3<13),SUM('Sale Analysis'!$E$14:$E$17,'Sale Analysis'!$E$12),0) -> 0 | E28: =IF(AND('Sale Analysis'!$E$3>12,'Sale Analysis'!$E$3<25),SUM('Sale Analysis'!$E$14:$E$17,'Sale Analysis'!$E$12),0) -> 0 | F28: =IF(AND('Sale Analysis'!$E$3>24,'Sale Analysis'!$E$3<37),SUM('Sale Analysis'!$E$14:$E$17,'Sale Analysis'!$E$12),0) -> 0
B30: Paladin Fees
B31: Acquisition Fee | C31: =-Assumptions!C39 -> -42092.05
B32: Asset Management Fee | D32: =('Monthly Cash Flow'!P66)*-1 -> -22464.626 | E32: =('Monthly Cash Flow'!AC66)*-1 -> -22464.626 | F32: =('Monthly Cash Flow'!AP66)*-1 -> -22464.626
B33: Construction Management Fee | D33: =((D24/0.95)*0.05)+((D23/0.95)*0.05) -> -14270.147 | E33: =((E24/0.95)*0.05)+((E23/0.95)*0.05) -> -6688.6029 | F33: =((F24/0.95)*0.05)+((F23/0.95)*0.05) -> 0
B35: Partnership Expenses & Rep Reserve | D35: =('Monthly Cash Flow'!P62)*-1 -> -20000 | E35: =('Monthly Cash Flow'!AC62)*-1 -> -20500 | F35: =('Monthly Cash Flow'!AP62)*-1 -> -21012.5
B37: Net Cash Flow | C37: =SUM(C8:C35) -> -1474622.1 | D37: =SUM(D8:D35) -> 9439.2058 | E37: =SUM(E8:E35) -> 75696.754 | F37: =SUM(F8:F35) -> 1053772.9
B40: Investor Net Cash Flow | C40: ='Waterfall Split'!H64 -> -1422759.7 | D40: =SUM('Waterfall Split'!I64:T64) -> 0 | E40: =SUM('Waterfall Split'!U64:AF64) -> 71137.983 | F40: =SUM('Waterfall Split'!AG64:AR64) -> 991725.05
B42: Cumulative Total Cost | D42: =Assumptions!$C$16-'Cont. Dist.'!O8 -> 3855141.8 | E42: =Assumptions!$C$16-'Cont. Dist.'!AA8 -> 3855141.8 | F42: =Assumptions!$C$16-'Cont. Dist.'!AM8 -> 3855141.8
B43: Free & Clear Yield | D43: ='Cash Flow Summary'!D15 -> 0.046095926 | E43: ='Cash Flow Summary'!E15 -> 0.065173381 | F43: ='Cash Flow Summary'!F15 -> 0.075702648
B45: Gross Equity Multiple | C45: ='Executive Summary'!C22 -> 1.9795314
B46: Gross IRR | C46: ='Executive Summary'!C23 -> 0.15240298
B48: Net Equity Multiple | C48: ='Executive Summary'!C27 -> 1.788103
B49: Net IRR | C49: ='Executive Summary'!C28 -> 0.13274836

Sheet 3 Pager Graphs
B2: Purchase Snapshot | E2: Planned Improvements | F2: Total | G2: Per Unit | I2: Net Operating Income | J2: Current | K2: Stabilized (Mo. 36) | X2: Sales Comps | Y2: Location | Z2: Property Status | AA2: Cap Rate | AB2: Price/Unit | AC2: Price/Sqft. | AD2: Sale Date | AE2: Year Built | AF2: Notes | AP2: Fee Schedule | AS2: JV Deal Structure
B3: Purchase Price | C3: ='Executive Summary'!F8 -> 3725000 | E3: Exterior Improvements | F3: ='Renovation Budget'!C15 -> 82000 | G3: =F3/$C$4 -> 4823.5294 | I3: Gross Potential Rent | J3: ='Monthly Cash Flow'!D10*12 -> 417045.67 | K3: ='Monthly Cash Flow'!AO10*12 -> 442173.39 | AP3: Asset Management Fee | AQ3: 1% of invested equity | AS3: GP Equity Participation | AT3: 5% of total equity
B4: Number of Units | C4: ='Executive Summary'!C12 -> 17 | E4: Interior Improvements | F4: ='Renovation Budget'!C6 -> 282500 | G4: =F4/$C$4 -> 16617.647 | I4: Less: Loss to Lease | J4: =J5-J3 -> -106065.67 | K4: =K5-K3 -> -5620.1046 | AP4: Construction Management Fee | AQ4: 5% of renovation budget | AS4: Preferred Return | AT4: 8% IRR
B5: Price Per Unit | C5: ='Executive Summary'!C13 -> 219117.65 | E5: Contingency / Other Costs | F5: =ROUND('Renovation Budget'!C17+'Renovation Budget'!C18,-3) -> 55000 | G5: =ROUND(F5/$C$4,-2) -> 3200 | I5: Gross Scheduled Rent | J5: ='Monthly Cash Flow'!C12*12 -> 310980 | K5: ='Monthly Cash Flow'!AO12*12 -> 436553.29 | AP5: Acquisition Fee | AQ5: 1.5% of total capitalization | AS5: Tier 1 LP/GP Split | AT5: 65%/35% up to 17% IRR
B6: Price Per Sqft. | C6: ='Executive Summary'!C14 -> 313.84278 | E6: Total Renovation Budget | F6: =SUM(F3:F5) -> 419500 | G6: =ROUND(F6/$C$4,-2) -> 24700 | I6: Other Income | J6: ='Monthly Cash Flow'!C30*12 -> 3000 | K6: ='Monthly Cash Flow'!AO30*12 -> 23184.1 | AS6: Tier 2 LP/GP Split | AT6: 50%/50% above 17% IRR
B7: Rentable Sqft. | C7: ='Executive Summary'!C15 -> 11869 | E7: Closing / Loan Costs | F7: =ROUND(Assumptions!C42+Assumptions!C35+Assumptions!C34,-3) -> 130000 | G7: =ROUND(F7/$C$4,-2) -> 7600 | I7: Gross Operating Income | J7: =J5+J6 -> 313980 | K7: =K5+K6 -> 459737.39
B8: Year Built | C8: ='Executive Summary'!C11 -> 1967 | E8: Purchase Price | F8: =Assumptions!C23 -> 3725000 | G8: =ROUND(F8/$C$4,-2) -> 219100 | I8: Less: Vacancy (3%) | J8: =-3%*J5 -> -9329.4 | K8: =-3%*K5 -> -13096.599
E9: Total Projected Capitalization | F9: =F6+F7+F8 -> 4274500 | G9: =ROUND(F9/$C$4,-2) -> 251400 | I9: Effective Gross Income | J9: =J7+J8 -> 304650.6 | K9: =K7+K8 -> 446640.79
I10: Less: Operating Expenses | J10: ='Monthly Cash Flow'!C58*12 -> 109520.43 | K10: ='Monthly Cash Flow'!AO58*12 -> 118589.47
I11: Net Operating Income | J11: =J9-J10 -> 195130.17 | K11: =K9-K10 -> 328051.32
I12: Free-and-clear Yield on Cost | J12: =J11/(F8+F7) -> 0.050617424 | K12: =K11/F9 -> 0.076746127
M15: Sale Analysis
M16: Sale Month | N16: ='Sale Analysis'!C3 -> 83 | O16: ='Sale Analysis'!D3 -> 83 | P16: ='Sale Analysis'!E3 -> 83 | Q16: ='Sale Analysis'!F3 -> 83 | R16: ='Sale Analysis'!G3 -> 83
M17: Cap Rate | N17: ='Sale Analysis'!C4 -> 0.0525 | O17: ='Sale Analysis'!D4 -> 0.055 | P17: ='Sale Analysis'!E4 -> 0.0575 | Q17: ='Sale Analysis'!F4 -> 0.06 | R17: ='Sale Analysis'!G4 -> 0.0625
M18: Revenue | N18: ='Sale Analysis'!C5 -> 464200.75 | O18: ='Sale Analysis'!D5 -> 464200.75 | P18: ='Sale Analysis'!E5 -> 464200.75 | Q18: ='Sale Analysis'!F5 -> 464200.75 | R18: ='Sale Analysis'!G5 -> 464200.75
M19: Expenses | N19: ='Sale Analysis'!C6 -> 86850.573 | O19: ='Sale Analysis'!D6 -> 86850.573 | P19: ='Sale Analysis'!E6 -> 86850.573 | Q19: ='Sale Analysis'!F6 -> 86850.573 | R19: ='Sale Analysis'!G6 -> 86850.573
M20: Tax Adjustment | N20: ='Sale Analysis'!C7 -> 71622.9 | O20: ='Sale Analysis'!D7 -> 68966.1 | P20: ='Sale Analysis'!E7 -> 66493.8 | Q20: ='Sale Analysis'!F7 -> 64193.7 | R20: ='Sale Analysis'!G7 -> 62053.5
M21: NOI | N21: ='Sale Analysis'!C8 -> 305727.28 | O21: ='Sale Analysis'!D8 -> 308384.08 | P21: ='Sale Analysis'!E8 -> 310856.38 | Q21: ='Sale Analysis'!F8 -> 313156.48 | R21: ='Sale Analysis'!G8 -> 315296.68
M23: Sale Price (Per Unit) | N23: ='Sale Analysis'!C10 -> 342529.41 | O23: ='Sale Analysis'!D10 -> 329823.53 | P23: ='Sale Analysis'!E10 -> 318000 | Q23: ='Sale Analysis'!F10 -> 307000 | R23: ='Sale Analysis'!G10 -> 296764.71
M24: Sale Price | N24: ='Sale Analysis'!C11 -> 5823000 | O24: ='Sale Analysis'!D11 -> 5607000 | P24: ='Sale Analysis'!E11 -> 5406000 | Q24: ='Sale Analysis'!F11 -> 5219000 | R24: ='Sale Analysis'!G11 -> 5045000
M25: Plus: Working Capital Dist. | N25: ='Sale Analysis'!C12 -> 49829.382 | O25: ='Sale Analysis'!D12 -> 49829.382 | P25: ='Sale Analysis'!E12 -> 49829.382 | Q25: ='Sale Analysis'!F12 -> 49829.382 | R25: ='Sale Analysis'!G12 -> 49829.382
M26: Less: Loan | N26: ='Sale Analysis'!C13 -> -3740191.3 | O26: ='Sale Analysis'!D13 -> -3740191.3 | P26: ='Sale Analysis'!E13 -> -3740191.3 | Q26: ='Sale Analysis'!F13 -> -3740191.3 | R26: ='Sale Analysis'!G13 -> -3740191.3
M27: Less: Broker Fee | N27: ='Sale Analysis'!#REF! -> #REF! | O27: ='Sale Analysis'!D15 -> -56070 | P27: ='Sale Analysis'!E15 -> -54060 | Q27: ='Sale Analysis'!F15 -> -52190 | R27: ='Sale Analysis'!G15 -> -50450
M28: Less: Closing Costs (1.25%) | N28: ='Sale Analysis'!C14 -> -116460 | O28: ='Sale Analysis'!D14+O27 -> -168210 | P28: ='Sale Analysis'!E14+P27 -> -162180 | Q28: ='Sale Analysis'!F14+Q27 -> -156570 | R28: ='Sale Analysis'!G14+R27 -> -151350
M31: Total Distributions | N31: ='Sale Analysis'!C17 -> 0 | O31: ='Sale Analysis'!D18 -> 1748428.1 | P31: ='Sale Analysis'!E18 -> 1553458.1 | Q31: ='Sale Analysis'!F18 -> 1372068.1 | R31: ='Sale Analysis'!G18 -> 1203288.1
M33: Equity Contribution | N33: ='Sale Analysis'!C19 -> 0 | O33: ='Sale Analysis'!C20 -> 1497641.8 | P33: ='Sale Analysis'!D20 -> 1497641.8 | Q33: ='Sale Analysis'!E20 -> 1497641.8 | R33: ='Sale Analysis'!F20 -> 1497641.8
M34: Equity Gains | N34: ='Sale Analysis'!C20 -> 1497641.8 | O34: ='Sale Analysis'!D21 -> 1661957.1 | P34: ='Sale Analysis'!E21 -> 1466987.1 | Q34: ='Sale Analysis'!F21 -> 1285597.1 | R34: ='Sale Analysis'!G21 -> 1116817.1
M35: Equity Multiple | N35: ='Sale Analysis'!C21 -> 1871477.1 | O35: ='Sale Analysis'!D22 -> 2.1097161 | P35: ='Sale Analysis'!E22 -> 1.9795314 | Q35: ='Sale Analysis'!F22 -> 1.8584143 | R35: ='Sale Analysis'!G22 -> 1.7457171
M36: IRR | N36: ='Sale Analysis'!C22 -> 2.249616 | O36: ='Sale Analysis'!D23 -> 0.16449794 | P36: ='Sale Analysis'!E23 -> 0.15240298 | Q36: ='Sale Analysis'!F23 -> 0.14025808 | R36: ='Sale Analysis'!G23 -> 0.12803772
T39: Deal Returns
T40: Total Investment | U40: ='Executive Summary'!C20 -> 1498000
T41: Gross Distributions | U41: ='Executive Summary'!C21 -> 2965000
T42: Gross Equity Multiple | U42: ='Executive Summary'!C22 -> 1.9795314
T43: Gross IRR | U43: ='Executive Summary'!C23 -> 0.15240298
T44: Stabilized Yield on Cost | U44: =K12 -> 0.076746127
AH50: Competitive Properties
AH52: Unit Type | AI52: SUBJECT PROPERTY (In Place) | AJ52: SUBJECT PROPERTY (Pro Forma)
AH54: ='Executive Summary'!H19 -> Stu - ADU
AH55: ='Executive Summary'!H20 -> 1x1
AH56: ='Executive Summary'!H21 -> 2x1
AH57: Proximity
AH58: Notes

Sheet Rent Comps
B2: Competitive Properties
B3: Unit Type | C3: 1 Bed | D3: 2 Bed | E3: 2 Bed TH | F3: Proximity | G3: Notes
K20: Fees
K21: Acquisition Fee | L21: =Assumptions!C39 -> 42092.05 | M21: 1% of Capitalization
K22: Closing Costs | L22: 105000 | M22: Legal, DD, and Escrow
K23: Buyer Broker Fee | L23: =Assumptions!C23*1% -> 37250 | M23: 1% of Purchase Price
K24: Equity Brokerage Fee | L24: =Assumptions!C41-L25 -> -118218 | M24: Tiered Fee
K25: Debt Brokerage Fee | L25: 145998 | M25: 1% of Loan Sizing
K26: Total Fees & Formation Costs | L26: =SUM(L21:L25) -> 212122.05

Sheet Assumptions
AF1: REFI OUT BRIDGE CALC
B2: Property Information | F2: Market | G2: Yr0 | H2: Yr1 | I2: Yr2 | J2: Yr3 | K2: Yr4 | L2: Yr5 | M2: Yr6 | N2: Yr7 | R2: Acquisition Loan | W2: Bridge | Y2: Refinance Loan | AD2: =IF(AND(AD3>12,AD3<25),2,IF(AND(AD3>24,AD3<37),3,IF(AND(AD3>36,AD3<49),4,IF(AND(AD3>48,AD3<61),5,IF(AND(AD3>60,AD3<73),6,IF(AND(AD3>72,AD3<85),7,1)))))) -> 3 | AF2: Refinance Loan | AK2: =IF(AND(AK3>12,AK3<25),2,IF(AND(AK3>24,AK3<37),3,IF(AND(AK3>36,AK3<49),4,IF(AND(AK3>48,AK3<61),5,IF(AND(AK3>60,AK3<73),6,IF(AND(AK3>72,AK3<85),7,1)))))) -> 3
B3: Property Name | C3: Brownstone Apartments | F3: Market Rent Growth | H3: 0.01 | I3: 0.025 | J3: 0.025 | K3: 0.025 | L3: 0.02 | M3: 0.02 | N3: 0.02 | Y3: Refinance Month | AD3: 35 | AF3: Refinance Month | AK3: =W21 -> 26
B4: Address | C4: 9559 Flower St | F4: Effective Rent Growth | H4: =H3+(G8-H8) -> 0.01 | I4: =I3+(H8-I8) -> 0.025 | J4: =J3+(I8-J8) -> 0.025 | K4: =K3+(J8-K8) -> 0.025 | L4: =L3+(K8-L8) -> 0.02 | M4: =M3+(L8-M8) -> 0.02 | N4: =N3+(M8-N8) -> 0.02 | R4: Amortization Period | W4: 30 | Y4: Amortization Period (Years) | AD4: 30 | AF4: Amortization Period (Years) | AK4: 30
B5: City/State | C5: Bellflower, CA 90706 | F5: Vacancy | H5: 0.02 | I5: 0.02 | J5: 0.03 | K5: 0.03 | L5: 0.03 | M5: 0.03 | N5: 0.03 | R5: Annual Interest Rate | W5: 0.0585 | Y5: Annual Interest Rate | AD5: 0.055 | AF5: Annual Interest Rate | AK5: =W24 -> 0.0535
B6: Year of Construction | C6: 1967 | F6: Collections Loss
B7: Acquisition Date | C7: 46204 | F7: Concessions (# Mo. Free) | R7: Loan-to-Value Test | Y7: Loan-to-Value Test | AF7: Loan-to-Value Test
B8: Total Square Footage | C8: 18737 | F8: Concessions % | G8: =(G7/12)*G9 -> 0 | H8: =(H7/12)*H9 -> 0 | I8: =(I7/12)*I9 -> 0 | J8: =(J7/12)*J9 -> 0 | K8: =(K7/12)*K9 -> 0 | L8: =(L7/12)*L9 -> 0 | M8: =(M7/12)*M9 -> 0 | N8: =(N7/12)*N9 -> 0 | R8: In-Place NOI | W8: ='Monthly Cash Flow'!C60*12 -> 188910.57 | Y8: NOI at Point of Refinance | AD8: ='Sale Analysis'!T7 -> 318545.92 | AF8: NOI at Point of Refinance | AK8: ='Sale Analysis'!Q7 -> 326725.61
B9: Gross Rentable SF | C9: 11869 | F9: Retention | R9: Capitalization Rate at Point of Purchase | W9: =C12 -> 0.050714247 | Y9: Capitalization Rate at Point of Refinance | AD9: 0.0575 | AF9: Capitalization Rate at Point of Refinance | AK9: =W25 -> 0.05
B10: Units | C10: 17 | R10: Valuation at Point of Purchase | W10: =W8/W9 -> 3725000 | Y10: Valuation at Point of Refinance | AD10: =AD8/AD9 -> 5539929.1 | AF10: Total Cost | AK10: ='Executive Summary'!F11 -> 4274000
B11: Asking Price | C11: 3850000 | F11: Other Income | G11: Yr0 | H11: Yr1 | I11: Yr2 | J11: Yr3 | K11: Yr4 | L11: Yr5 | M11: Yr6 | N11: Yr7 | R11: Maximum LTV | W11: 0.65 | Y11: Maximum LTV | AD11: 0.7 | AF11: Maximum LTV | AK11: =W23 -> 0.65
B12: Current Cap Rate | C12: ='Monthly Cash Flow'!A60/Assumptions!C23 -> 0.050714247 | R12: Maximum Loan Proceeds | W12: =W10*W11 -> 2421250 | Y12: Maximum Loan Proceeds | AD12: =AD10*AD11 -> 3877950.4 | AF12: Maximum Loan Proceeds | AK12: =AK10*AK11 -> 2778100
F13: Credit Check Fees
B14: Capitalization & Project Costs | F14: Late Fees | H14: =75*0.33*$C$10 -> 420.75 | I14: =75*0.33*$C$10 -> 420.75 | J14: =75*0.33*$C$10 -> 420.75 | K14: =75*0.33*$C$10 -> 420.75 | L14: =75*0.33*$C$10 -> 420.75 | M14: =75*0.33*$C$10 -> 420.75 | N14: =75*0.33*$C$10 -> 420.75 | R14: Debt Service Coverage Ratio Test | Y14: Debt Service Coverage Ratio Test | AF14: Debt Service Coverage Ratio Test
B15: Sources | F15: NSF Fees | H15: =35*0.33*$C$10 -> 196.35 | I15: =35*0.33*$C$10 -> 196.35 | J15: =35*0.33*$C$10 -> 196.35 | K15: =35*0.33*$C$10 -> 196.35 | L15: =35*0.33*$C$10 -> 196.35 | M15: =35*0.33*$C$10 -> 196.35 | N15: =35*0.33*$C$10 -> 196.35 | R15: =R8 -> In-Place NOI | W15: =W8 -> 188910.57 | Y15: =Y8 -> NOI at Point of Refinance | AD15: =AD8 -> 318545.92 | AF15: =AF8 -> NOI at Point of Refinance | AK15: =AK8 -> 326725.61
B16: Senior Debt | C16: =W32 -> 2357500 | F16: Early Termination Fees | R16: Required Minimum Debt Service Coverage Ratio | W16: 1.15 | Y16: Required Minimum Debt Service Coverage Ratio | AD16: 1.25 | AF16: Required Minimum Debt Service Coverage Ratio | AK16: =W22 -> 1.25
B17: Loan Draws | C17: =C26+C25 -> 419175 | F17: Laundry & Valet Trash Income | G17: =2400 -> 2400 | H17: =300*$C$10 -> 5100 | I17: =300*$C$10 -> 5100 | J17: =300*$C$10 -> 5100 | K17: =300*$C$10 -> 5100 | L17: =300*$C$10 -> 5100 | M17: =300*$C$10 -> 5100 | N17: =300*$C$10 -> 5100 | R17: Maximum Allowable Debt Service | W17: =W15/W16 -> 164270.06 | Y17: Maximum Allowable Debt Service | AD17: =AD15/AD16 -> 254836.74 | AF17: Maximum Allowable Debt Service | AK17: =AK15/AK16 -> 261380.49
B18: Equity | C18: =C36 -> 1497641.8 | F18: Pet Rent | R18: Maximum Loan Proceeds | W18: =-PV(W5/12,W4*12,W17/12) -> 2320430.9 | Y18: Maximum Loan Proceeds | AD18: =-PV(AD5/12,AD4*12,AD17/12) -> 3740191.3 | AF18: Maximum Loan Proceeds | AK18: =-PV(AK5/12,AK4*12,AK17/12) -> 3900639.9
B19: Reinvested Operating CF | F19: Application Fees
B20: Total Capitalization | C20: =SUM(C16:C19) -> 4274316.8 | F20: Parking | G20: =50*12 -> 600 | H20: =(((100*4)+(25*3))*12)/2 -> 2850 | I20: =(((100*4)+(25*3))*12) -> 5700 | J20: =(((100*4)+(25*3))*12) -> 5700 | K20: =(((100*4)+(25*3))*12) -> 5700 | L20: =(((100*4)+(25*3))*12) -> 5700 | M20: =(((100*4)+(25*3))*12) -> 5700 | N20: =(((100*4)+(25*3))*12) -> 5700 | R20: Future Refi DSCR Test - For Bridge
F21: RUBs | R21: DSCR Test Month | W21: 26 | Y21: Lesser of the three values above (Loan Size) | AD21: =MIN(AD12,AD18) -> 3740191.3 | AF21: Lesser of the three values above (Loan Size) | AK21: =MIN(AK12,AK18)-SUM('Loan Summary'!K2:K361) -> 2357500
B22: Uses | R22: Required Minimum Debt Service Coverage Ratio | W22: 1.25 | Y22: Less: Senior Debt | AD22: =-VLOOKUP($AD$3-1,'Loan Summary'!$F$2:$L$361,7,FALSE) -> -2778100
B23: Purchase Price | C23: 3725000 | F23: Expenses | G23: Yr0 | H23: Yr1 | I23: Yr2 | J23: Yr3 | K23: Yr4 | L23: Yr5 | M23: Yr6 | N23: Yr7 | R23: Maximum Loan To Cost | W23: 0.65 | Y23: Less: Refi Fee | AD23: =-'Loan Summary'!C15 -> -18700.957 | AF23: Mortgage Constant Calculation
B24: Closing & Formation Costs | C24: =C40+C41 -> 65030 | F24: Property Taxes | G24: =H24 -> 45817.5 | H24: =C23*P24 -> 45817.5 | I24: =H24*1.02 -> 46733.85 | J24: =I24*1.02 -> 47668.527 | K24: =J24*1.02 -> 48621.898 | L24: =K24*1.02 -> 49594.335 | M24: =L24*1.02 -> 50586.222 | N24: =M24*1.02 -> 51597.947 | O24: mill rate | P24: 0.0123 | R24: New Loan Interest Rate | W24: 0.0535 | Y24: Less: Loan Buydown | AD24: =-'Loan Summary'!C14 -> 0 | AF24: Annual Interest Rate | AK24: =AK5 -> 0.0535
B25: Buyouts | C25: ='Renovation Budget'!C4+('Renovation Budget'!C4*'Renovation Budget'!D17)+('Renovation Budget'!C4*'Renovation Budget'!D18) -> 48875 | F25: Insurance | G25: 14000 | H25: =G25 -> 14000 | I25: =H25*(1+$G$40) -> 14350 | J25: =I25*(1+$G$40) -> 14708.75 | K25: =J25*(1+$G$40) -> 15076.469 | L25: =K25*(1+$G$40) -> 15453.38 | M25: =L25*(1+$G$40) -> 15839.715 | N25: =M25*(1+$G$40) -> 16235.708 | R25: Capitalization Rate at Date of Refinance | W25: 0.05 | Y25: Less: Preferred Equity | AF25: Monthly Interest Rate | AK25: =AK24/12 -> 0.0044583333
B26: Renovation Budget | C26: =C45-C25 -> 370300 | F26: Management Fee | G26: % of Revenue | I26: 0.03 | K26: If Fixed: Increase/Year? | R26: Maximum Loan Proceeds | W26: =AK21 -> 2357500 | Y26: Distributions from Refinance | AD26: =SUM(AD21:AD25) -> 943390.35 | AE26: =AD26/C36 -> 0.62991723 | AF26: Months of Amortization | AK26: =AK4*12 -> 360
B27: Total Cost | C27: =SUM(C23:C26) -> 4209205 | E27: =G27/$C$10 -> 823.52941 | F27: Electric | G27: 14000 | H27: =G27 -> 14000 | I27: =H27*(1+$G$40) -> 14350 | J27: =I27*(1+$G$40) -> 14708.75 | K27: =J27*(1+$G$40) -> 15076.469 | L27: =K27*(1+$G$40) -> 15453.38 | M27: =L27*(1+$G$40) -> 15839.715 | N27: =M27*(1+$G$40) -> 16235.708 | R27: Interest Reserve? | W27: Yes | AF27: Monthly Mortgage Constant | AK27: =AK25/(1-(1/(1+AK25)^AK26)) -> 0.0055841369
B28: Plus: Acq Fee /Working Capital/Reserves | C28: =C39+C35+C34 -> 65111.752 | E28: =G28/$C$10 -> 0 | F28: Gas | I28: =H28*(1+$G$40) -> 0 | J28: =I28*(1+$G$40) -> 0 | K28: =J28*(1+$G$40) -> 0 | L28: =K28*(1+$G$40) -> 0 | M28: =L28*(1+$G$40) -> 0 | N28: =M28*(1+$G$40) -> 0 | R28: Lender Draw for Capital? | W28: Yes | Y28: Mortgage Constant Calculation | AF28: Annual Mortgage Constant | AK28: =AK27*12 -> 0.067009643
B29: Total Uses | C29: =SUM(C27:C28) -> 4274316.8 | E29: =G29/$C$10 -> 0 | F29: Water/Sewer | I29: =H29*(1+$G$40) -> 0 | J29: =I29*(1+$G$40) -> 0 | K29: =J29*(1+$G$40) -> 0 | L29: =K29*(1+$G$40) -> 0 | M29: =L29*(1+$G$40) -> 0 | N29: =M29*(1+$G$40) -> 0 | Y29: Annual Interest Rate | AD29: =AD5 -> 0.055 | AF29: Check on Cap Rate Calculation by Sizing Loan | AK29: =AK17/AK28 -> 3900639.9
E30: =G30/$C$10 -> 0 | F30: Trash (Inc Valet Trash) | I30: =H30*(1+$G$40) -> 0 | J30: =I30*(1+$G$40) -> 0 | K30: =J30*(1+$G$40) -> 0 | L30: =K30*(1+$G$40) -> 0 | M30: =L30*(1+$G$40) -> 0 | N30: =M30*(1+$G$40) -> 0 | Y30: Monthly Interest Rate | AD30: =AD29/12 -> 0.0045833333
B31: Total Equity | E31: =G31/$C$10 -> 750 | F31: R&M | G31: =750*C10 -> 12750 | H31: =G31 -> 12750 | I31: =H31*(1+$G$40) -> 13068.75 | J31: =I31*(1+$G$40) -> 13395.469 | K31: =J31*(1+$G$40) -> 13730.355 | L31: =K31*(1+$G$40) -> 14073.614 | M31: =L31*(1+$G$40) -> 14425.455 | N31: =M31*(1+$G$40) -> 14786.091 | R31: ASSUMED OVERRIDE | Y31: Months of Amortization | AD31: =AD4*12 -> 360
B32: Closing Equity | C32: =C23-C16+C42 -> 1474622.1 | E32: =G32/$C$10 -> 0 | F32: Turnover | I32: =H32*(1+$G$40) -> 0 | J32: =I32*(1+$G$40) -> 0 | K32: =500*C10 -> 8500 | L32: =K32*(1+$G$40) -> 8712.5 | M32: =L32*(1+$G$40) -> 8930.3125 | N32: =M32*(1+$G$40) -> 9153.5703 | R32: Lesser of the three values above (Loan Size) | W32: =IF(W2="Assumed",$W$31,IF(W2="Bridge",W26,MIN(W12,W18))) -> 2357500 | Y32: Monthly Mortgage Constant | AD32: =AD30/(1-(1/(1+AD30)^AD31)) -> 0.00567789
B33: Renovation Equity | C33: =IF('Monthly Cash Flow'!C88="Lender Draw",0,C45) -> 0 | E33: =G33/$C$10 -> 205.88235 | F33: Grounds/Landscaping | G33: 3500 | H33: =G33 -> 3500 | I33: =H33*(1+$G$40) -> 3587.5 | J33: =I33*(1+$G$40) -> 3677.1875 | K33: =J33*(1+$G$40) -> 3769.1172 | L33: =K33*(1+$G$40) -> 3863.3451 | M33: =L33*(1+$G$40) -> 3959.9287 | N33: =M33*(1+$G$40) -> 4058.927 | Y33: Annual Mortgage Constant | AD33: =AD32*12 -> 0.06813468
B34: Lender Reserves | C34: =-IF(AND(W2="Bridge",W27="Yes"),'Monthly Cash Flow'!B77,0) -> 23019.702 | D34: =D36-C36 -> 0 | E34: =G34/$C$10 -> 88.235294 | F34: Advertising | G34: 1500 | H34: =G34 -> 1500 | I34: =H34*(1+$G$40) -> 1537.5 | J34: =I34*(1+$G$40) -> 1575.9375 | K34: =J34*(1+$G$40) -> 1615.3359 | L34: =K34*(1+$G$40) -> 1655.7193 | M34: =L34*(1+$G$40) -> 1697.1123 | N34: =M34*(1+$G$40) -> 1739.5401 | R34: Mortgage Constant Calculation | Y34: Check on Cap Rate Calculation by Sizing Loan | AD34: =AD17/AD33 -> 3740191.3
B35: Additional Paid In Capital | D35: check | E35: =G35/$C$10 -> 0 | F35: Administration | I35: =H35*(1+$G$40) -> 0 | J35: =I35*(1+$G$40) -> 0 | K35: =J35*(1+$G$40) -> 0 | L35: =K35*(1+$G$40) -> 0 | M35: =L35*(1+$G$40) -> 0 | N35: =M35*(1+$G$40) -> 0 | R35: Annual Interest Rate | W35: =W5 -> 0.0585
B36: TOTAL EQUITY | C36: =C32+C33+C34+C35 -> 1497641.8 | D36: =-'Cont. Dist.'!CI8 -> 1497641.8 | E36: =G36/$C$10 -> 529.41176 | F36: Payroll | G36: 9000 | H36: =G36 -> 9000 | I36: =H36*(1+$G$40) -> 9225 | J36: =I36*(1+$G$40) -> 9455.625 | K36: =J36*(1+$G$40) -> 9692.0156 | L36: =K36*(1+$G$40) -> 9934.316 | M36: =L36*(1+$G$40) -> 10182.674 | N36: =M36*(1+$G$40) -> 10437.241 | R36: Monthly Interest Rate | W36: =W35/12 -> 0.004875
E37: =G37/$C$10 -> 1176.4706 | F37: Capital Rsrv & Partnership | G37: 20000 | H37: =G37 -> 20000 | I37: =H37*(1+$G$40) -> 20500 | J37: =I37*(1+$G$40) -> 21012.5 | K37: =J37*(1+$G$40) -> 21537.812 | L37: =K37*(1+$G$40) -> 22076.258 | M37: =L37*(1+$G$40) -> 22628.164 | N37: =M37*(1+$G$40) -> 23193.868 | R37: Months of Amortization | W37: =W4*12 -> 360
B38: Fees | F38: Asset Mgmt. Fee | G38: 0.015 | R38: Monthly Mortgage Constant | W38: =W36/(1-(1/(1+W36)^W37)) -> 0.0058994093
B39: Acquisition Fee | C39: =C27*D39 -> 42092.05 | D39: 0.01 | R39: Annual Mortgage Constant | W39: =W38*12 -> 0.070792912
B40: Closing Costs | C40: =(C23*D40) -> 37250 | D40: 0.01 | F40: Yearly Expense % Increase | G40: 0.025 | R40: Check on Cap Rate Calculation by Sizing Loan | W40: =W17/W39 -> 2320430.9
B41: Loan Closing Fee | C41: =D41*'Executive Summary'!F13 -> 27780 | D41: 0.01
B42: Total Closing & Formation | C42: =SUM(C39:C41) -> 107122.05
B44: Renovation Summary
B45: Total Budget | C45: ='Renovation Budget'!C20 -> 419175
B46: Total Budget/Unit | C46: =C45/C10 -> 24657.353
B48: Interior Renovation Summary
B49: Total Budget | C49: ='Renovation Budget'!C6*(1+'Renovation Budget'!$D$17)+('Renovation Budget'!$C$6*'Renovation Budget'!$D$18) -> 324875
B50: Total Budget/Unit | C50: =C49/C53 -> 19110.294
B51: Total Renovation Period | C51: =C56-C55+1 -> 18
B52: Units Renovated/Month | C52: =(C53/C51) -> 0.94444444
B53: # of Units to Renovate | C53: 17
B54: # of Months Vacant | C54: 2
B55: Renovation Start | C55: 2
B56: Renovation End | C56: 19
B58: Exterior Renovation Summary
B59: Total Budget | C59: ='Renovation Budget'!C15*(1+'Renovation Budget'!D17)+('Renovation Budget'!$C$15*'Renovation Budget'!$D$18) -> 94300
B60: Total Budget/Unit | C60: =C59/Assumptions!C10 -> 5547.0588
B61: Total Renovation Period | C61: =C63-C62+1 -> 4
B62: Renovation Start | C62: 1
B63: Renovation End | C63: 4

Sheet Unit Mix
B2: Unit Mix | E2: Rents
B3: Unit Type | C3: # of Units | D3: Sqft. | E3: Current RR | F3: Current Market | G3: Post Reno Rent Increase | H3: Post Reno Rents | I3: Total Monthly Rent
B4: Stu - ADU | C4: 1 | D4: 499 | E4: 1340 | F4: 1650 | H4: =IF(F4+G4=0,"",F4+G4) -> 1650 | I4: =IF(C4="","",C4*H4) -> 1650
B5: 1x1 | C5: 9 | D5: 648 | E5: 1427 | F5: 1925 | H5: =IF(F5+G5=0,"",F5+G5) -> 1925 | I5: =IF(C5="","",C5*H5) -> 17325
B6: 2x1 | C6: 7 | D6: 840 | E6: 1676 | F6: 2250 | H6: =IF(F6+G6=0,"",F6+G6) -> 2250 | I6: =IF(C6="","",C6*H6) -> 15750
H7: =IF(F7+G7=0,"",F7+G7) | I7: =IF(C7="","",C7*H7)
H8: =IF(F8+G8=0,"",F8+G8) | I8: =IF(C8="","",C8*H8)
H9: =IF(F9+G9=0,"",F9+G9) | I9: =IF(C9="","",C9*H9)
H10: =IF(F10+G10=0,"",F10+G10) | I10: =IF(C10="","",C10*H10)
H11: =IF(F11+G11=0,"",F11+G11) | I11: =IF(C11="","",C11*H11)
H12: =IF(F12+G12=0,"",F12+G12) | I12: =IF(C12="","",C12*H12)
H13: =IF(F13+G13=0,"",F13+G13) | I13: =IF(C13="","",C13*H13)
H14: =IF(F14+G14=0,"",F14+G14) | I14: =IF(C14="","",C14*H14)
H15: =IF(F15+G15=0,"",F15+G15) | I15: =IF(C15="","",C15*H15)
H16: =IF(F16+G16=0,"",F16+G16) | I16: =IF(C16="","",C16*H16)
H17: =IF(F17+G17=0,"",F17+G17) | I17: =IF(C17="","",C17*H17)
B18: TOTAL | C18: =SUM(C3:C17) -> 17 | D18: =IFERROR(AVERAGE(D4:D17),"") -> 662.33333 | E18: =IFERROR(SUMPRODUCT(E4:E17,C4:C17)/SUM(C4:C17),"") -> 1524.4118 | F18: =IFERROR(AVERAGE(F4:F17),"") -> 1941.6667 | G18: =IFERROR(AVERAGE(G4:G17),"") | H18: =IFERROR(SUMPRODUCT(H4:H17,C4:C17)/SUM(C4:C17),"") -> 2042.6471
D19: Current GR | E19: =SUMPRODUCT(C4:C17,E4:E17) -> 25915 | G19: Post Reno Market Rent | I19: =SUM(I4:I17) -> 34725 | K19: =(I19/E19)-1 -> 0.33995755
B29: Rent Comps

Sheet Renovation Budget
B2: Interiors & Buyouts | D2: Notes | E2: Interiors & Buyouts
B3: Interior Renovations | C3: =F3*Assumptions!C53 -> 240000 | E3: Interior Renovations | F3: =L3 -> 14117.647 | J3: 15000 | K3: =J3/17 -> 882.35294 | L3: =K3*16 -> 14117.647
B4: Buyouts | C4: =Assumptions!C53*'Renovation Budget'!F4*'Renovation Budget'!F5 -> 42500 | E4: Buyouts | F4: 5000
E5: % of Turns as Buyouts | F5: 0.5
B6: TOTAL INTERIOR RENOVATIONS | C6: =SUM(C3:C5) -> 282500
B8: Exterior Renovations | D8: Notes
B9: Gate repair/paint | C9: 25000
B10: Paint | C10: 25000
B11: New Doors | C11: 17000
B12: Landscape | C12: 5000
B13: Garage Door | C13: 10000
B15: TOTAL EXTERIOR RENOVATIONS | C15: =SUM(C9:C14) -> 82000
B17: Contingency | C17: =(C15+C6)*D17 -> 36450 | D17: 0.1
B18: Construction Mgmt. Fee | C18: =(C6+C15)*D18 -> 18225 | D18: 0.05
B20: TOTAL RENOVATION CAPITAL | C20: =C6+C15+C17+C18 -> 419175

Sheet Loan Summary
B1: ACQUISITION LOAN SUMMARY | F1: Month | G1: Beginning | H1: Payment | I1: Interest | J1: Principal | K1: Draw | L1: Ending Balance | O1: MEMBER LOAN SUMMARY | R1: Month | S1: Beginning | T1: Accrued Return | U1: Pay | V1: Refi Paydown | W1: Ending Balance
B2: Principal Balance | C2: =Assumptions!W32 -> 2357500 | F2: 1 | G2: =IF(F2<$C$16,$C$2,$C$9) -> 2357500 | H2: =IF(F2<$C$16,IF(F2>$C$6,-PMT(($C$3/12),$C$4,$C$2),I2),-PMT($C$10/12,$C$11,$C$9)) -> 11492.812 | I2: =IF(F2<$C$16,G2*($C$3/12),G2*($C$10/12)) -> 11492.812 | J2: =IF(F2<$C$16,IF(F2<=$C$6,0,H2-I2),IF(F2<=$C$16+$C$13,0,H2-I2)) -> 0 | K2: =IF('Monthly Cash Flow'!$C$88="Lender Draw",HLOOKUP(F2,'Monthly Cash Flow'!$D$79:$CP$88,10),0) -> 25000 | L2: =G2-J2+K2 -> 2382500 | O2: Principal Balance | P2: =Assumptions!C17 -> 419175 | R2: 1 | S2: =P2 -> 419175 | T2: =(S2*$P$3)/12 -> 4191.75 | U2: =-IF('Cash Flow Summary'!$D$24="No",0,IF(AND('Cash Flow Summary'!$D$24="Yes",HLOOKUP($R2,'Monthly Cash Flow'!$D$6:$CP$68,61,FALSE)>0),HLOOKUP($R2,'Monthly Cash Flow'!$D$6:$CP$68,61,FALSE),IF('Cash Flow Summary'!$D$24="Current Pay",('Loan Summary'!S2*'Loan Summary'!$P$3)/12,0))) -> 0 | V2: =IF('Loan Summary'!R2=Assumptions!$AD$3,Assumptions!$AD$25,0) -> 0 | W2: =S2+T2+U2+V2 -> 423366.75
B3: Interest Rate | C3: =Assumptions!W5 -> 0.0585 | F3: 2 | G3: =IF(F3<$C$16,L2,IF(F3=$C$16,$C$9,L2)) -> 2382500 | H3: =IF(F3<$C$16,IF(F3>$C$6,-PMT(($C$3/12),$C$4,$C$2),I3),-PMT($C$10/12,$C$11,$C$9)) -> 11614.688 | I3: =IF(F3<$C$16,G3*($C$3/12),G3*($C$10/12)) -> 11614.688 | J3: =IF(F3<$C$16,IF(F3<=$C$6,0,H3-I3),IF(F3<=$C$16+$C$13,0,H3-I3)) -> 0 | K3: =IF('Monthly Cash Flow'!$C$88="Lender Draw",HLOOKUP(F3,'Monthly Cash Flow'!$D$79:$CP$88,10),0) -> 23575 | L3: =G3-J3+K3 -> 2406075 | O3: Pref Rate | P3: 0.12 | R3: 2 | S3: =W2 -> 423366.75 | T3: =(S3*$P$3)/12 -> 4233.6675 | U3: =-IF('Cash Flow Summary'!$D$24="No",0,IF(AND('Cash Flow Summary'!$D$24="Yes",HLOOKUP($R3,'Monthly Cash Flow'!$D$6:$CP$68,61,FALSE)>0),HLOOKUP($R3,'Monthly Cash Flow'!$D$6:$CP$68,61,FALSE),IF('Cash Flow Summary'!$D$24="Current Pay",('Loan Summary'!S3*'Loan Summary'!$P$3)/12,0))) -> 0 | V3: =IF('Loan Summary'!R3=Assumptions!$AD$3,Assumptions!$AD$25,0) -> 0 | W3: =S3+T3+U3+V3 -> 427600.42
B4: Amortization Schd | C4: 360 | D4: Months | F4: 3 | G4: =IF(F4<$C$16,L3,IF(F4=$C$16,$C$9,L3)) -> 2406075 | H4: =IF(F4<$C$16,IF(F4>$C$6,-PMT(($C$3/12),$C$4,$C$2),I4),-PMT($C$10/12,$C$11,$C$9)) -> 11729.616 | I4: =IF(F4<$C$16,G4*($C$3/12),G4*($C$10/12)) -> 11729.616 | J4: =IF(F4<$C$16,IF(F4<=$C$6,0,H4-I4),IF(F4<=$C$16+$C$13,0,H4-I4)) -> 0 | K4: =IF('Monthly Cash Flow'!$C$88="Lender Draw",HLOOKUP(F4,'Monthly Cash Flow'!$D$79:$CP$88,10),0) -> 42685.294 | L4: =G4-J4+K4 -> 2448760.3 | O4: Compounding Periods/Yr | P4: 12 | R4: 3 | S4: =W3 -> 427600.42 | T4: =(S4*$P$3)/12 -> 4276.0042 | U4: =-IF('Cash Flow Summary'!$D$24="No",0,IF(AND('Cash Flow Summary'!$D$24="Yes",HLOOKUP($R4,'Monthly Cash Flow'!$D$6:$CP$68,61,FALSE)>0),HLOOKUP($R4,'Monthly Cash Flow'!$D$6:$CP$68,61,FALSE),IF('Cash Flow Summary'!$D$24="Current Pay",('Loan Summary'!S4*'Loan Summary'!$P$3)/12,0))) -> 0 | V4: =IF('Loan Summary'!R4=Assumptions!$AD$3,Assumptions!$AD$25,0) -> 0 | W4: =S4+T4+U4+V4 -> 431876.42
B5: Term | C5: 60 | D5: Months | F5: 4 | G5: =IF(F5<$C$16,L4,IF(F5=$C$16,$C$9,L4)) -> 2448760.3 | H5: =IF(F5<$C$16,IF(F5>$C$6,-PMT(($C$3/12),$C$4,$C$2),I5),-PMT($C$10/12,$C$11,$C$9)) -> 11937.706 | I5: =IF(F5<$C$16,G5*($C$3/12),G5*($C$10/12)) -> 11937.706 | J5: =IF(F5<$C$16,IF(F5<=$C$6,0,H5-I5),IF(F5<=$C$16+$C$13,0,H5-I5)) -> 0 | K5: =IF('Monthly Cash Flow'!$C$88="Lender Draw",HLOOKUP(F5,'Monthly Cash Flow'!$D$79:$CP$88,10),0) -> 42685.294 | L5: =G5-J5+K5 -> 2491445.6 | O5: Paydown through CF? | P5: No | R5: 4 | S5: =W4 -> 431876.42 | T5: =(S5*$P$3)/12 -> 4318.7642 | U5: =-IF('Cash Flow Summary'!$D$24="No",0,IF(AND('Cash Flow Summary'!$D$24="Yes",HLOOKUP($R5,'Monthly Cash Flow'!$D$6:$CP$68,61,FALSE)>0),HLOOKUP($R5,'Monthly Cash Flow'!$D$6:$CP$68,61,FALSE),IF('Cash Flow Summary'!$D$24="Current Pay",('Loan Summary'!S5*'Loan Summary'!$P$3)/12,0))) -> 0 | V5: =IF('Loan Summary'!R5=Assumptions!$AD$3,Assumptions!$AD$25,0) -> 0 | W5: =S5+T5+U5+V5 -> 436195.19
B6: Interest Only | C6: 60 | D6: Months | F6: 5 | G6: =IF(F6<$C$16,L5,IF(F6=$C$16,$C$9,L5)) -> 2491445.6 | H6: =IF(F6<$C$16,IF(F6>$C$6,-PMT(($C$3/12),$C$4,$C$2),I6),-PMT($C$10/12,$C$11,$C$9)) -> 12145.797 | I6: =IF(F6<$C$16,G6*($C$3/12),G6*($C$10/12)) -> 12145.797 | J6: =IF(F6<$C$16,IF(F6<=$C$6,0,H6-I6),IF(F6<=$C$16+$C$13,0,H6-I6)) -> 0 | K6: =IF('Monthly Cash Flow'!$C$88="Lender Draw",HLOOKUP(F6,'Monthly Cash Flow'!$D$79:$CP$88,10),0) -> 19110.294 | L6: =G6-J6+K6 -> 2510555.9 | R6: 5 | S6: =W5 -> 436195.19 | T6: =(S6*$P$3)/12 -> 4361.9519 | U6: =-IF('Cash Flow Summary'!$D$24="No",0,IF(AND('Cash Flow Summary'!$D$24="Yes",HLOOKUP($R6,'Monthly Cash Flow'!$D$6:$CP$68,61,FALSE)>0),HLOOKUP($R6,'Monthly Cash Flow'!$D$6:$CP$68,61,FALSE),IF('Cash Flow Summary'!$D$24="Current Pay",('Loan Summary'!S6*'Loan Summary'!$P$3)/12,0))) -> 0 | V6: =IF('Loan Summary'!R6=Assumptions!$AD$3,Assumptions!$AD$25,0) -> 0 | W6: =S6+T6+U6+V6 -> 440557.14
F7: 6 | G7: =IF(F7<$C$16,L6,IF(F7=$C$16,$C$9,L6)) -> 2510555.9 | H7: =IF(F7<$C$16,IF(F7>$C$6,-PMT(($C$3/12),$C$4,$C$2),I7),-PMT($C$10/12,$C$11,$C$9)) -> 12238.96 | I7: =IF(F7<$C$16,G7*($C$3/12),G7*($C$10/12)) -> 12238.96 | J7: =IF(F7<$C$16,IF(F7<=$C$6,0,H7-I7),IF(F7<=$C$16+$C$13,0,H7-I7)) -> 0 | K7: =IF('Monthly Cash Flow'!$C$88="Lender Draw",HLOOKUP(F7,'Monthly Cash Flow'!$D$79:$CP$88,10),0) -> 19110.294 | L7: =G7-J7+K7 -> 2529666.2 | R7: 6 | S7: =W6 -> 440557.14 | T7: =(S7*$P$3)/12 -> 4405.5714 | U7: =-IF('Cash Flow Summary'!$D$24="No",0,IF(AND('Cash Flow Summary'!$D$24="Yes",HLOOKUP($R7,'Monthly Cash Flow'!$D$6:$CP$68,61,FALSE)>0),HLOOKUP($R7,'Monthly Cash Flow'!$D$6:$CP$68,61,FALSE),IF('Cash Flow Summary'!$D$24="Current Pay",('Loan Summary'!S7*'Loan Summary'!$P$3)/12,0))) -> 0 | V7: =IF('Loan Summary'!R7=Assumptions!$AD$3,Assumptions!$AD$25,0) -> 0 | W7: =S7+T7+U7+V7 -> 444962.71
B8: REFINANCE LOAN SUMMARY | F8: 7 | G8: =IF(F8<$C$16,L7,IF(F8=$C$16,$C$9,L7)) -> 2529666.2 | H8: =IF(F8<$C$16,IF(F8>$C$6,-PMT(($C$3/12),$C$4,$C$2),I8),-PMT($C$10/12,$C$11,$C$9)) -> 12332.123 | I8: =IF(F8<$C$16,G8*($C$3/12),G8*($C$10/12)) -> 12332.123 | J8: =IF(F8<$C$16,IF(F8<=$C$6,0,H8-I8),IF(F8<=$C$16+$C$13,0,H8-I8)) -> 0 | K8: =IF('Monthly Cash Flow'!$C$88="Lender Draw",HLOOKUP(F8,'Monthly Cash Flow'!$D$79:$CP$88,10),0) -> 19110.294 | L8: =G8-J8+K8 -> 2548776.5 | R8: 7 | S8: =W7 -> 444962.71 | T8: =(S8*$P$3)/12 -> 4449.6271 | U8: =-IF('Cash Flow Summary'!$D$24="No",0,IF(AND('Cash Flow Summary'!$D$24="Yes",HLOOKUP($R8,'Monthly Cash Flow'!$D$6:$CP$68,61,FALSE)>0),HLOOKUP($R8,'Monthly Cash Flow'!$D$6:$CP$68,61,FALSE),IF('Cash Flow Summary'!$D$24="Current Pay",('Loan Summary'!S8*'Loan Summary'!$P$3)/12,0))) -> 0 | V8: =IF('Loan Summary'!R8=Assumptions!$AD$3,Assumptions!$AD$25,0) -> 0 | W8: =S8+T8+U8+V8 -> 449412.34
B9: Principal Balance | C9: =Assumptions!AD21 -> 3740191.3 | F9: 8 | G9: =IF(F9<$C$16,L8,IF(F9=$C$16,$C$9,L8)) -> 2548776.5 | H9: =IF(F9<$C$16,IF(F9>$C$6,-PMT(($C$3/12),$C$4,$C$2),I9),-PMT($C$10/12,$C$11,$C$9)) -> 12425.285 | I9: =IF(F9<$C$16,G9*($C$3/12),G9*($C$10/12)) -> 12425.285 | J9: =IF(F9<$C$16,IF(F9<=$C$6,0,H9-I9),IF(F9<=$C$16+$C$13,0,H9-I9)) -> 0 | K9: =IF('Monthly Cash Flow'!$C$88="Lender Draw",HLOOKUP(F9,'Monthly Cash Flow'!$D$79:$CP$88,10),0) -> 19110.294 | L9: =G9-J9+K9 -> 2567886.8 | R9: 8 | S9: =W8 -> 449412.34 | T9: =(S9*$P$3)/12 -> 4494.1234 | U9: =-IF('Cash Flow Summary'!$D$24="No",0,IF(AND('Cash Flow Summary'!$D$24="Yes",HLOOKUP($R9,'Monthly Cash Flow'!$D$6:$CP$68,61,FALSE)>0),HLOOKUP($R9,'Monthly Cash Flow'!$D$6:$CP$68,61,FALSE),IF('Cash Flow Summary'!$D$24="Current Pay",('Loan Summary'!S9*'Loan Summary'!$P$3)/12,0))) -> 0 | V9: =IF('Loan Summary'!R9=Assumptions!$AD$3,Assumptions!$AD$25,0) -> 0 | W9: =S9+T9+U9+V9 -> 453906.46
B10: Interest Rate | C10: =Assumptions!AD5 -> 0.055 | F10: 9 | G10: =IF(F10<$C$16,L9,IF(F10=$C$16,$C$9,L9)) -> 2567886.8 | H10: =IF(F10<$C$16,IF(F10>$C$6,-PMT(($C$3/12),$C$4,$C$2),I10),-PMT($C$10/12,$C$11,$C$9)) -> 12518.448 | I10: =IF(F10<$C$16,G10*($C$3/12),G10*($C$10/12)) -> 12518.448 | J10: =IF(F10<$C$16,IF(F10<=$C$6,0,H10-I10),IF(F10<=$C$16+$C$13,0,H10-I10)) -> 0 | K10: =IF('Monthly Cash Flow'!$C$88="Lender Draw",HLOOKUP(F10,'Monthly Cash Flow'!$D$79:$CP$88,10),0) -> 19110.294 | L10: =G10-J10+K10 -> 2586997.1 | R10: 9 | S10: =W9 -> 453906.46 | T10: =(S10*$P$3)/12 -> 4539.0646 | U10: =-IF('Cash Flow Summary'!$D$24="No",0,IF(AND('Cash Flow Summary'!$D$24="Yes",HLOOKUP($R10,'Monthly Cash Flow'!$D$6:$CP$68,61,FALSE)>0),HLOOKUP($R10,'Monthly Cash Flow'!$D$6:$CP$68,61,FALSE),IF('Cash Flow Summary'!$D$24="Current Pay",('Loan Summary'!S10*'Loan Summary'!$P$3)/12,0))) -> 0 | V10: =IF('Loan Summary'!R10=Assumptions!$AD$3,Assumptions!$AD$25,0) -> 0 | W10: =S10+T10+U10+V10 -> 458445.52
B11: Amortization Schd | C11: =Assumptions!AD4*12 -> 360 | D11: Months | F11: 10 | G11: =IF(F11<$C$16,L10,IF(F11=$C$16,$C$9,L10)) -> 2586997.1 | H11: =IF(F11<$C$16,IF(F11>$C$6,-PMT(($C$3/12),$C$4,$C$2),I11),-PMT($C$10/12,$C$11,$C$9)) -> 12611.611 | I11: =IF(F11<$C$16,G11*($C$3/12),G11*($C$10/12)) -> 12611.611 | J11: =IF(F11<$C$16,IF(F11<=$C$6,0,H11-I11),IF(F11<=$C$16+$C$13,0,H11-I11)) -> 0 | K11: =IF('Monthly Cash Flow'!$C$88="Lender Draw",HLOOKUP(F11,'Monthly Cash Flow'!$D$79:$CP$88,10),0) -> 19110.294 | L11: =G11-J11+K11 -> 2606107.4 | R11: 10 | S11: =W10 -> 458445.52 | T11: =(S11*$P$3)/12 -> 4584.4552 | U11: =-IF('Cash Flow Summary'!$D$24="No",0,IF(AND('Cash Flow Summary'!$D$24="Yes",HLOOKUP($R11,'Monthly Cash Flow'!$D$6:$CP$68,61,FALSE)>0),HLOOKUP($R11,'Monthly Cash Flow'!$D$6:$CP$68,61,FALSE),IF('Cash Flow Summary'!$D$24="Current Pay",('Loan Summary'!S11*'Loan Summary'!$P$3)/12,0))) -> 0 | V11: =IF('Loan Summary'!R11=Assumptions!$AD$3,Assumptions!$AD$25,0) -> 0 | W11: =S11+T11+U11+V11 -> 463029.98
B12: Term | C12: 120 | D12: Months | F12: 11 | G12: =IF(F12<$C$16,L11,IF(F12=$C$16,$C$9,L11)) -> 2606107.4 | H12: =IF(F12<$C$16,IF(F12>$C$6,-PMT(($C$3/12),$C$4,$C$2),I12),-PMT($C$10/12,$C$11,$C$9)) -> 12704.773 | I12: =IF(F12<$C$16,G12*($C$3/12),G12*($C$10/12)) -> 12704.773 | J12: =IF(F12<$C$16,IF(F12<=$C$6,0,H12-I12),IF(F12<=$C$16+$C$13,0,H12-I12)) -> 0 | K12: =IF('Monthly Cash Flow'!$C$88="Lender Draw",HLOOKUP(F12,'Monthly Cash Flow'!$D$79:$CP$88,10),0) -> 19110.294 | L12: =G12-J12+K12 -> 2625217.6 | R12: 11 | S12: =W11 -> 463029.98 | T12: =(S12*$P$3)/12 -> 4630.2998 | U12: =-IF('Cash Flow Summary'!$D$24="No",0,IF(AND('Cash Flow Summary'!$D$24="Yes",HLOOKUP($R12,'Monthly Cash Flow'!$D$6:$CP$68,61,FALSE)>0),HLOOKUP($R12,'Monthly Cash Flow'!$D$6:$CP$68,61,FALSE),IF('Cash Flow Summary'!$D$24="Current Pay",('Loan Summary'!S12*'Loan Summary'!$P$3)/12,0))) -> 0 | V12: =IF('Loan Summary'!R12=Assumptions!$AD$3,Assumptions!$AD$25,0) -> 0 | W12: =S12+T12+U12+V12 -> 467660.28
B13: Interest Only | C13: 120 | D13: Months | F13: 12 | G13: =IF(F13<$C$16,L12,IF(F13=$C$16,$C$9,L12)) -> 2625217.6 | H13: =IF(F13<$C$16,IF(F13>$C$6,-PMT(($C$3/12),$C$4,$C$2),I13),-PMT($C$10/12,$C$11,$C$9)) -> 12797.936 | I13: =IF(F13<$C$16,G13*($C$3/12),G13*($C$10/12)) -> 12797.936 | J13: =IF(F13<$C$16,IF(F13<=$C$6,0,H13-I13),IF(F13<=$C$16+$C$13,0,H13-I13)) -> 0 | K13: =IF('Monthly Cash Flow'!$C$88="Lender Draw",HLOOKUP(F13,'Monthly Cash Flow'!$D$79:$CP$88,10),0) -> 19110.294 | L13: =G13-J13+K13 -> 2644327.9 | R13: 12 | S13: =W12 -> 467660.28 | T13: =(S13*$P$3)/12 -> 4676.6028 | U13: =-IF('Cash Flow Summary'!$D$24="No",0,IF(AND('Cash Flow Summary'!$D$24="Yes",HLOOKUP($R13,'Monthly Cash Flow'!$D$6:$CP$68,61,FALSE)>0),HLOOKUP($R13,'Monthly Cash Flow'!$D$6:$CP$68,61,FALSE),IF('Cash Flow Summary'!$D$24="Current Pay",('Loan Summary'!S13*'Loan Summary'!$P$3)/12,0))) -> 0 | V13: =IF('Loan Summary'!R13=Assumptions!$AD$3,Assumptions!$AD$25,0) -> 0 | W13: =S13+T13+U13+V13 -> 472336.88
B14: Rate Buydown | F14: 13 | G14: =IF(F14<$C$16,L13,IF(F14=$C$16,$C$9,L13)) -> 2644327.9 | H14: =IF(F14<$C$16,IF(F14>$C$6,-PMT(($C$3/12),$C$4,$C$2),I14),-PMT($C$10/12,$C$11,$C$9)) -> 12891.099 | I14: =IF(F14<$C$16,G14*($C$3/12),G14*($C$10/12)) -> 12891.099 | J14: =IF(F14<$C$16,IF(F14<=$C$6,0,H14-I14),IF(F14<=$C$16+$C$13,0,H14-I14)) -> 0 | K14: =IF('Monthly Cash Flow'!$C$88="Lender Draw",HLOOKUP(F14,'Monthly Cash Flow'!$D$79:$CP$88,10),0) -> 19110.294 | L14: =G14-J14+K14 -> 2663438.2 | R14: 13 | S14: =W13 -> 472336.88 | T14: =(S14*$P$3)/12 -> 4723.3688 | U14: =-IF('Cash Flow Summary'!$E$24="No",0,IF(AND('Cash Flow Summary'!$D$24="Yes",HLOOKUP($R14,'Monthly Cash Flow'!$D$6:$CP$68,61,FALSE)>0),HLOOKUP($R14,'Monthly Cash Flow'!$D$6:$CP$68,61,FALSE),IF('Cash Flow Summary'!$E$24="Current Pay",('Loan Summary'!S14*'Loan Summary'!$P$3)/12,0))) -> 0 | V14: =IF('Loan Summary'!R14=Assumptions!$AD$3,Assumptions!$AD$25,0) -> 0 | W14: =S14+T14+U14+V14 -> 477060.25
B15: Refi Fee | C15: =D15*C9 -> 18700.957 | D15: 0.005 | F15: 14 | G15: =IF(F15<$C$16,L14,IF(F15=$C$16,$C$9,L14)) -> 2663438.2 | H15: =IF(F15<$C$16,IF(F15>$C$6,-PMT(($C$3/12),$C$4,$C$2),I15),-PMT($C$10/12,$C$11,$C$9)) -> 12984.261 | I15: =IF(F15<$C$16,G15*($C$3/12),G15*($C$10/12)) -> 12984.261 | J15: =IF(F15<$C$16,IF(F15<=$C$6,0,H15-I15),IF(F15<=$C$16+$C$13,0,H15-I15)) -> 0 | K15: =IF('Monthly Cash Flow'!$C$88="Lender Draw",HLOOKUP(F15,'Monthly Cash Flow'!$D$79:$CP$88,10),0) -> 19110.294 | L15: =G15-J15+K15 -> 2682548.5 | R15: 14 | S15: =W14 -> 477060.25 | T15: =(S15*$P$3)/12 -> 4770.6025 | U15: =-IF('Cash Flow Summary'!$E$24="No",0,IF(AND('Cash Flow Summary'!$D$24="Yes",HLOOKUP($R15,'Monthly Cash Flow'!$D$6:$CP$68,61,FALSE)>0),HLOOKUP($R15,'Monthly Cash Flow'!$D$6:$CP$68,61,FALSE),IF('Cash Flow Summary'!$E$24="Current Pay",('Loan Summary'!S15*'Loan Summary'!$P$3)/12,0))) -> 0 | V15: =IF('Loan Summary'!R15=Assumptions!$AD$3,Assumptions!$AD$25,0) -> 0 | W15: =S15+T15+U15+V15 -> 481830.85
B16: Refi Month | C16: =IF(Assumptions!AD3="","",Assumptions!AD3) -> 35 | F16: 15 | G16: =IF(F16<$C$16,L15,IF(F16=$C$16,$C$9,L15)) -> 2682548.5 | H16: =IF(F16<$C$16,IF(F16>$C$6,-PMT(($C$3/12),$C$4,$C$2),I16),-PMT($C$10/12,$C$11,$C$9)) -> 13077.424 | I16: =IF(F16<$C$16,G16*($C$3/12),G16*($C$10/12)) -> 13077.424 | J16: =IF(F16<$C$16,IF(F16<=$C$6,0,H16-I16),IF(F16<=$C$16+$C$13,0,H16-I16)) -> 0 | K16: =IF('Monthly Cash Flow'!$C$88="Lender Draw",HLOOKUP(F16,'Monthly Cash Flow'!$D$79:$CP$88,10),0) -> 19110.294 | L16: =G16-J16+K16 -> 2701658.8 | R16: 15 | S16: =W15 -> 481830.85 | T16: =(S16*$P$3)/12 -> 4818.3085 | U16: =-IF('Cash Flow Summary'!$E$24="No",0,IF(AND('Cash Flow Summary'!$D$24="Yes",HLOOKUP($R16,'Monthly Cash Flow'!$D$6:$CP$68,61,FALSE)>0),HLOOKUP($R16,'Monthly Cash Flow'!$D$6:$CP$68,61,FALSE),IF('Cash Flow Summary'!$E$24="Current Pay",('Loan Summary'!S16*'Loan Summary'!$P$3)/12,0))) -> 0 | V16: =IF('Loan Summary'!R16=Assumptions!$AD$3,Assumptions!$AD$25,0) -> 0 | W16: =S16+T16+U16+V16 -> 486649.16
F17: 16 | G17: =IF(F17<$C$16,L16,IF(F17=$C$16,$C$9,L16)) -> 2701658.8 | H17: =IF(F17<$C$16,IF(F17>$C$6,-PMT(($C$3/12),$C$4,$C$2),I17),-PMT($C$10/12,$C$11,$C$9)) -> 13170.587 | I17: =IF(F17<$C$16,G17*($C$3/12),G17*($C$10/12)) -> 13170.587 | J17: =IF(F17<$C$16,IF(F17<=$C$6,0,H17-I17),IF(F17<=$C$16+$C$13,0,H17-I17)) -> 0 | K17: =IF('Monthly Cash Flow'!$C$88="Lender Draw",HLOOKUP(F17,'Monthly Cash Flow'!$D$79:$CP$88,10),0) -> 19110.294 | L17: =G17-J17+K17 -> 2720769.1 | R17: 16 | S17: =W16 -> 486649.16 | T17: =(S17*$P$3)/12 -> 4866.4916 | U17: =-IF('Cash Flow Summary'!$E$24="No",0,IF(AND('Cash Flow Summary'!$D$24="Yes",HLOOKUP($R17,'Monthly Cash Flow'!$D$6:$CP$68,61,FALSE)>0),HLOOKUP($R17,'Monthly Cash Flow'!$D$6:$CP$68,61,FALSE),IF('Cash Flow Summary'!$E$24="Current Pay",('Loan Summary'!S17*'Loan Summary'!$P$3)/12,0))) -> 0 | V17: =IF('Loan Summary'!R17=Assumptions!$AD$3,Assumptions!$AD$25,0) -> 0 | W17: =S17+T17+U17+V17 -> 491515.65
F18: 17 | G18: =IF(F18<$C$16,L17,IF(F18=$C$16,$C$9,L17)) -> 2720769.1 | H18: =IF(F18<$C$16,IF(F18>$C$6,-PMT(($C$3/12),$C$4,$C$2),I18),-PMT($C$10/12,$C$11,$C$9)) -> 13263.749 | I18: =IF(F18<$C$16,G18*($C$3/12),G18*($C$10/12)) -> 13263.749 | J18: =IF(F18<$C$16,IF(F18<=$C$6,0,H18-I18),IF(F18<=$C$16+$C$13,0,H18-I18)) -> 0 | K18: =IF('Monthly Cash Flow'!$C$88="Lender Draw",HLOOKUP(F18,'Monthly Cash Flow'!$D$79:$CP$88,10),0) -> 19110.294 | L18: =G18-J18+K18 -> 2739879.4 | R18: 17 | S18: =W17 -> 491515.65 | T18: =(S18*$P$3)/12 -> 4915.1565 | U18: =-IF('Cash Flow Summary'!$E$24="No",0,IF(AND('Cash Flow Summary'!$D$24="Yes",HLOOKUP($R18,'Monthly Cash Flow'!$D$6:$CP$68,61,FALSE)>0),HLOOKUP($R18,'Monthly Cash Flow'!$D$6:$CP$68,61,FALSE),IF('Cash Flow Summary'!$E$24="Current Pay",('Loan Summary'!S18*'Loan Summary'!$P$3)/12,0))) -> 0 | V18: =IF('Loan Summary'!R18=Assumptions!$AD$3,Assumptions!$AD$25,0) -> 0 | W18: =S18+T18+U18+V18 -> 496430.81
F19: 18 | G19: =IF(F19<$C$16,L18,IF(F19=$C$16,$C$9,L18)) -> 2739879.4 | H19: =IF(F19<$C$16,IF(F19>$C$6,-PMT(($C$3/12),$C$4,$C$2),I19),-PMT($C$10/12,$C$11,$C$9)) -> 13356.912 | I19: =IF(F19<$C$16,G19*($C$3/12),G19*($C$10/12)) -> 13356.912 | J19: =IF(F19<$C$16,IF(F19<=$C$6,0,H19-I19),IF(F19<=$C$16+$C$13,0,H19-I19)) -> 0 | K19: =IF('Monthly Cash Flow'!$C$88="Lender Draw",HLOOKUP(F19,'Monthly Cash Flow'!$D$79:$CP$88,10),0) -> 19110.294 | L19: =G19-J19+K19 -> 2758989.7 | R19: 18 | S19: =W18 -> 496430.81 | T19: =(S19*$P$3)/12 -> 4964.3081 | U19: =-IF('Cash Flow Summary'!$E$24="No",0,IF(AND('Cash Flow Summary'!$D$24="Yes",HLOOKUP($R19,'Monthly Cash Flow'!$D$6:$CP$68,61,FALSE)>0),HLOOKUP($R19,'Monthly Cash Flow'!$D$6:$CP$68,61,FALSE),IF('Cash Flow Summary'!$E$24="Current Pay",('Loan Summary'!S19*'Loan Summary'!$P$3)/12,0))) -> 0 | V19: =IF('Loan Summary'!R19=Assumptions!$AD$3,Assumptions!$AD$25,0) -> 0 | W19: =S19+T19+U19+V19 -> 501395.12
F20: 19 | G20: =IF(F20<$C$16,L19,IF(F20=$C$16,$C$9,L19)) -> 2758989.7 | H20: =IF(F20<$C$16,IF(F20>$C$6,-PMT(($C$3/12),$C$4,$C$2),I20),-PMT($C$10/12,$C$11,$C$9)) -> 13450.075 | I20: =IF(F20<$C$16,G20*($C$3/12),G20*($C$10/12)) -> 13450.075 | J20: =IF(F20<$C$16,IF(F20<=$C$6,0,H20-I20),IF(F20<=$C$16+$C$13,0,H20-I20)) -> 0 | K20: =IF('Monthly Cash Flow'!$C$88="Lender Draw",HLOOKUP(F20,'Monthly Cash Flow'!$D$79:$CP$88,10),0) -> 19110.294 | L20: =G20-J20+K20 -> 2778100 | R20: 19 | S20: =W19 -> 501395.12 | T20: =(S20*$P$3)/12 -> 5013.9512 | U20: =-IF('Cash Flow Summary'!$E$24="No",0,IF(AND('Cash Flow Summary'!$D$24="Yes",HLOOKUP($R20,'Monthly Cash Flow'!$D$6:$CP$68,61,FALSE)>0),HLOOKUP($R20,'Monthly Cash Flow'!$D$6:$CP$68,61,FALSE),IF('Cash Flow Summary'!$E$24="Current Pay",('Loan Summary'!S20*'Loan Summary'!$P$3)/12,0))) -> 0 | V20: =IF('Loan Summary'!R20=Assumptions!$AD$3,Assumptions!$AD$25,0) -> 0 | W20: =S20+T20+U20+V20 -> 506409.07
F21: 20 | G21: =IF(F21<$C$16,L20,IF(F21=$C$16,$C$9,L20)) -> 2778100 | H21: =IF(F21<$C$16,IF(F21>$C$6,-PMT(($C$3/12),$C$4,$C$2),I21),-PMT($C$10/12,$C$11,$C$9)) -> 13543.238 | I21: =IF(F21<$C$16,G21*($C$3/12),G21*($C$10/12)) -> 13543.238 | J21: =IF(F21<$C$16,IF(F21<=$C$6,0,H21-I21),IF(F21<=$C$16+$C$13,0,H21-I21)) -> 0 | K21: =IF('Monthly Cash Flow'!$C$88="Lender Draw",HLOOKUP(F21,'Monthly Cash Flow'!$D$79:$CP$88,10),0) -> 0 | L21: =G21-J21+K21 -> 2778100 | R21: 20 | S21: =W20 -> 506409.07 | T21: =(S21*$P$3)/12 -> 5064.0907 | U21: =-IF('Cash Flow Summary'!$E$24="No",0,IF(AND('Cash Flow Summary'!$D$24="Yes",HLOOKUP($R21,'Monthly Cash Flow'!$D$6:$CP$68,61,FALSE)>0),HLOOKUP($R21,'Monthly Cash Flow'!$D$6:$CP$68,61,FALSE),IF('Cash Flow Summary'!$E$24="Current Pay",('Loan Summary'!S21*'Loan Summary'!$P$3)/12,0))) -> 0 | V21: =IF('Loan Summary'!R21=Assumptions!$AD$3,Assumptions!$AD$25,0) -> 0 | W21: =S21+T21+U21+V21 -> 511473.16
F22: 21 | G22: =IF(F22<$C$16,L21,IF(F22=$C$16,$C$9,L21)) -> 2778100 | H22: =IF(F22<$C$16,IF(F22>$C$6,-PMT(($C$3/12),$C$4,$C$2),I22),-PMT($C$10/12,$C$11,$C$9)) -> 13543.238 | I22: =IF(F22<$C$16,G22*($C$3/12),G22*($C$10/12)) -> 13543.238 | J22: =IF(F22<$C$16,IF(F22<=$C$6,0,H22-I22),IF(F22<=$C$16+$C$13,0,H22-I22)) -> 0 | K22: =IF('Monthly Cash Flow'!$C$88="Lender Draw",HLOOKUP(F22,'Monthly Cash Flow'!$D$79:$CP$88,10),0) -> 0 | L22: =G22-J22+K22 -> 2778100 | R22: 21 | S22: =W21 -> 511473.16 | T22: =(S22*$P$3)/12 -> 5114.7316 | U22: =-IF('Cash Flow Summary'!$E$24="No",0,IF(AND('Cash Flow Summary'!$D$24="Yes",HLOOKUP($R22,'Monthly Cash Flow'!$D$6:$CP$68,61,FALSE)>0),HLOOKUP($R22,'Monthly Cash Flow'!$D$6:$CP$68,61,FALSE),IF('Cash Flow Summary'!$E$24="Current Pay",('Loan Summary'!S22*'Loan Summary'!$P$3)/12,0))) -> 0 | V22: =IF('Loan Summary'!R22=Assumptions!$AD$3,Assumptions!$AD$25,0) -> 0 | W22: =S22+T22+U22+V22 -> 516587.89
F23: 22 | G23: =IF(F23<$C$16,L22,IF(F23=$C$16,$C$9,L22)) -> 2778100 | H23: =IF(F23<$C$16,IF(F23>$C$6,-PMT(($C$3/12),$C$4,$C$2),I23),-PMT($C$10/12,$C$11,$C$9)) -> 13543.238 | I23: =IF(F23<$C$16,G23*($C$3/12),G23*($C$10/12)) -> 13543.238 | J23: =IF(F23<$C$16,IF(F23<=$C$6,0,H23-I23),IF(F23<=$C$16+$C$13,0,H23-I23)) -> 0 | K23: =IF('Monthly Cash Flow'!$C$88="Lender Draw",HLOOKUP(F23,'Monthly Cash Flow'!$D$79:$CP$88,10),0) -> 0 | L23: =G23-J23+K23 -> 2778100 | R23: 22 | S23: =W22 -> 516587.89 | T23: =(S23*$P$3)/12 -> 5165.8789 | U23: =-IF('Cash Flow Summary'!$E$24="No",0,IF(AND('Cash Flow Summary'!$D$24="Yes",HLOOKUP($R23,'Monthly Cash Flow'!$D$6:$CP$68,61,FALSE)>0),HLOOKUP($R23,'Monthly Cash Flow'!$D$6:$CP$68,61,FALSE),IF('Cash Flow Summary'!$E$24="Current Pay",('Loan Summary'!S23*'Loan Summary'!$P$3)/12,0))) -> 0 | V23: =IF('Loan Summary'!R23=Assumptions!$AD$3,Assumptions!$AD$25,0) -> 0 | W23: =S23+T23+U23+V23 -> 521753.77
F24: 23 | G24: =IF(F24<$C$16,L23,IF(F24=$C$16,$C$9,L23)) -> 2778100 | H24: =IF(F24<$C$16,IF(F24>$C$6,-PMT(($C$3/12),$C$4,$C$2),I24),-PMT($C$10/12,$C$11,$C$9)) -> 13543.238 | I24: =IF(F24<$C$16,G24*($C$3/12),G24*($C$10/12)) -> 13543.238 | J24: =IF(F24<$C$16,IF(F24<=$C$6,0,H24-I24),IF(F24<=$C$16+$C$13,0,H24-I24)) -> 0 | K24: =IF('Monthly Cash Flow'!$C$88="Lender Draw",HLOOKUP(F24,'Monthly Cash Flow'!$D$79:$CP$88,10),0) -> 0 | L24: =G24-J24+K24 -> 2778100 | R24: 23 | S24: =W23 -> 521753.77 | T24: =(S24*$P$3)/12 -> 5217.5377 | U24: =-IF('Cash Flow Summary'!$E$24="No",0,IF(AND('Cash Flow Summary'!$D$24="Yes",HLOOKUP($R24,'Monthly Cash Flow'!$D$6:$CP$68,61,FALSE)>0),HLOOKUP($R24,'Monthly Cash Flow'!$D$6:$CP$68,61,FALSE),IF('Cash Flow Summary'!$E$24="Current Pay",('Loan Summary'!S24*'Loan Summary'!$P$3)/12,0))) -> 0 | V24: =IF('Loan Summary'!R24=Assumptions!$AD$3,Assumptions!$AD$25,0) -> 0 | W24: =S24+T24+U24+V24 -> 526971.31
F25: 24 | G25: =IF(F25<$C$16,L24,IF(F25=$C$16,$C$9,L24)) -> 2778100 | H25: =IF(F25<$C$16,IF(F25>$C$6,-PMT(($C$3/12),$C$4,$C$2),I25),-PMT($C$10/12,$C$11,$C$9)) -> 13543.238 | I25: =IF(F25<$C$16,G25*($C$3/12),G25*($C$10/12)) -> 13543.238 | J25: =IF(F25<$C$16,IF(F25<=$C$6,0,H25-I25),IF(F25<=$C$16+$C$13,0,H25-I25)) -> 0 | K25: =IF('Monthly Cash Flow'!$C$88="Lender Draw",HLOOKUP(F25,'Monthly Cash Flow'!$D$79:$CP$88,10),0) -> 0 | L25: =G25-J25+K25 -> 2778100 | R25: 24 | S25: =W24 -> 526971.31 | T25: =(S25*$P$3)/12 -> 5269.7131 | U25: =-IF('Cash Flow Summary'!$E$24="No",0,IF(AND('Cash Flow Summary'!$D$24="Yes",HLOOKUP($R25,'Monthly Cash Flow'!$D$6:$CP$68,61,FALSE)>0),HLOOKUP($R25,'Monthly Cash Flow'!$D$6:$CP$68,61,FALSE),IF('Cash Flow Summary'!$E$24="Current Pay",('Loan Summary'!S25*'Loan Summary'!$P$3)/12,0))) -> 0 | V25: =IF('Loan Summary'!R25=Assumptions!$AD$3,Assumptions!$AD$25,0) -> 0 | W25: =S25+T25+U25+V25 -> 532241.02
F26: 25 | G26: =IF(F26<$C$16,L25,IF(F26=$C$16,$C$9,L25)) -> 2778100 | H26: =IF(F26<$C$16,IF(F26>$C$6,-PMT(($C$3/12),$C$4,$C$2),I26),-PMT($C$10/12,$C$11,$C$9)) -> 13543.238 | I26: =IF(F26<$C$16,G26*($C$3/12),G26*($C$10/12)) -> 13543.238 | J26: =IF(F26<$C$16,IF(F26<=$C$6,0,H26-I26),IF(F26<=$C$16+$C$13,0,H26-I26)) -> 0 | K26: =IF('Monthly Cash Flow'!$C$88="Lender Draw",HLOOKUP(F26,'Monthly Cash Flow'!$D$79:$CP$88,10),0) -> 0 | L26: =G26-J26+K26 -> 2778100 | R26: 25 | S26: =W25 -> 532241.02 | T26: =(S26*$P$3)/12 -> 5322.4102 | U26: =-IF('Cash Flow Summary'!$F$24="No",0,IF(AND('Cash Flow Summary'!$D$24="Yes",HLOOKUP($R26,'Monthly Cash Flow'!$D$6:$CP$68,61,FALSE)>0),HLOOKUP($R26,'Monthly Cash Flow'!$D$6:$CP$68,61,FALSE),IF('Cash Flow Summary'!$F$24="Current Pay",('Loan Summary'!S26*'Loan Summary'!$P$3)/12,0))) -> 0 | V26: =IF('Loan Summary'!R26=Assumptions!$AD$3,Assumptions!$AD$25,0) -> 0 | W26: =S26+T26+U26+V26 -> 537563.43
F27: 26 | G27: =IF(F27<$C$16,L26,IF(F27=$C$16,$C$9,L26)) -> 2778100 | H27: =IF(F27<$C$16,IF(F27>$C$6,-PMT(($C$3/12),$C$4,$C$2),I27),-PMT($C$10/12,$C$11,$C$9)) -> 13543.238 | I27: =IF(F27<$C$16,G27*($C$3/12),G27*($C$10/12)) -> 13543.238 | J27: =IF(F27<$C$16,IF(F27<=$C$6,0,H27-I27),IF(F27<=$C$16+$C$13,0,H27-I27)) -> 0 | K27: =IF('Monthly Cash Flow'!$C$88="Lender Draw",HLOOKUP(F27,'Monthly Cash Flow'!$D$79:$CP$88,10),0) -> 0 | L27: =G27-J27+K27 -> 2778100 | R27: 26 | S27: =W26 -> 537563.43 | T27: =(S27*$P$3)/12 -> 5375.6343 | U27: =-IF('Cash Flow Summary'!$F$24="No",0,IF(AND('Cash Flow Summary'!$D$24="Yes",HLOOKUP($R27,'Monthly Cash Flow'!$D$6:$CP$68,61,FALSE)>0),HLOOKUP($R27,'Monthly Cash Flow'!$D$6:$CP$68,61,FALSE),IF('Cash Flow Summary'!$F$24="Current Pay",('Loan Summary'!S27*'Loan Summary'!$P$3)/12,0))) -> 0 | V27: =IF('Loan Summary'!R27=Assumptions!$AD$3,Assumptions!$AD$25,0) -> 0 | W27: =S27+T27+U27+V27 -> 542939.07
F28: 27 | G28: =IF(F28<$C$16,L27,IF(F28=$C$16,$C$9,L27)) -> 2778100 | H28: =IF(F28<$C$16,IF(F28>$C$6,-PMT(($C$3/12),$C$4,$C$2),I28),-PMT($C$10/12,$C$11,$C$9)) -> 13543.238 | I28: =IF(F28<$C$16,G28*($C$3/12),G28*($C$10/12)) -> 13543.238 | J28: =IF(F28<$C$16,IF(F28<=$C$6,0,H28-I28),IF(F28<=$C$16+$C$13,0,H28-I28)) -> 0 | K28: =IF('Monthly Cash Flow'!$C$88="Lender Draw",HLOOKUP(F28,'Monthly Cash Flow'!$D$79:$CP$88,10),0) -> 0 | L28: =G28-J28+K28 -> 2778100 | R28: 27 | S28: =W27 -> 542939.07 | T28: =(S28*$P$3)/12 -> 5429.3907 | U28: =-IF('Cash Flow Summary'!$F$24="No",0,IF(AND('Cash Flow Summary'!$D$24="Yes",HLOOKUP($R28,'Monthly Cash Flow'!$D$6:$CP$68,61,FALSE)>0),HLOOKUP($R28,'Monthly Cash Flow'!$D$6:$CP$68,61,FALSE),IF('Cash Flow Summary'!$F$24="Current Pay",('Loan Summary'!S28*'Loan Summary'!$P$3)/12,0))) -> 0 | V28: =IF('Loan Summary'!R28=Assumptions!$AD$3,Assumptions!$AD$25,0) -> 0 | W28: =S28+T28+U28+V28 -> 548368.46
F29: 28 | G29: =IF(F29<$C$16,L28,IF(F29=$C$16,$C$9,L28)) -> 2778100 | H29: =IF(F29<$C$16,IF(F29>$C$6,-PMT(($C$3/12),$C$4,$C$2),I29),-PMT($C$10/12,$C$11,$C$9)) -> 13543.238 | I29: =IF(F29<$C$16,G29*($C$3/12),G29*($C$10/12)) -> 13543.238 | J29: =IF(F29<$C$16,IF(F29<=$C$6,0,H29-I29),IF(F29<=$C$16+$C$13,0,H29-I29)) -> 0 | K29: =IF('Monthly Cash Flow'!$C$88="Lender Draw",HLOOKUP(F29,'Monthly Cash Flow'!$D$79:$CP$88,10),0) -> 0 | L29: =G29-J29+K29 -> 2778100 | R29: 28 | S29: =W28 -> 548368.46 | T29: =(S29*$P$3)/12 -> 5483.6846 | U29: =-IF('Cash Flow Summary'!$F$24="No",0,IF(AND('Cash Flow Summary'!$D$24="Yes",HLOOKUP($R29,'Monthly Cash Flow'!$D$6:$CP$68,61,FALSE)>0),HLOOKUP($R29,'Monthly Cash Flow'!$D$6:$CP$68,61,FALSE),IF('Cash Flow Summary'!$F$24="Current Pay",('Loan Summary'!S29*'Loan Summary'!$P$3)/12,0))) -> 0 | V29: =IF('Loan Summary'!R29=Assumptions!$AD$3,Assumptions!$AD$25,0) -> 0 | W29: =S29+T29+U29+V29 -> 553852.14
F30: 29 | G30: =IF(F30<$C$16,L29,IF(F30=$C$16,$C$9,L29)) -> 2778100 | H30: =IF(F30<$C$16,IF(F30>$C$6,-PMT(($C$3/12),$C$4,$C$2),I30),-PMT($C$10/12,$C$11,$C$9)) -> 13543.238 | I30: =IF(F30<$C$16,G30*($C$3/12),G30*($C$10/12)) -> 13543.238 | J30: =IF(F30<$C$16,IF(F30<=$C$6,0,H30-I30),IF(F30<=$C$16+$C$13,0,H30-I30)) -> 0 | K30: =IF('Monthly Cash Flow'!$C$88="Lender Draw",HLOOKUP(F30,'Monthly Cash Flow'!$D$79:$CP$88,10),0) -> 0 | L30: =G30-J30+K30 -> 2778100 | R30: 29 | S30: =W29 -> 553852.14 | T30: =(S30*$P$3)/12 -> 5538.5214 | U30: =-IF('Cash Flow Summary'!$F$24="No",0,IF(AND('Cash Flow Summary'!$D$24="Yes",HLOOKUP($R30,'Monthly Cash Flow'!$D$6:$CP$68,61,FALSE)>0),HLOOKUP($R30,'Monthly Cash Flow'!$D$6:$CP$68,61,FALSE),IF('Cash Flow Summary'!$F$24="Current Pay",('Loan Summary'!S30*'Loan Summary'!$P$3)/12,0))) -> 0 | V30: =IF('Loan Summary'!R30=Assumptions!$AD$3,Assumptions!$AD$25,0) -> 0 | W30: =S30+T30+U30+V30 -> 559390.66
F31: 30 | G31: =IF(F31<$C$16,L30,IF(F31=$C$16,$C$9,L30)) -> 2778100 | H31: =IF(F31<$C$16,IF(F31>$C$6,-PMT(($C$3/12),$C$4,$C$2),I31),-PMT($C$10/12,$C$11,$C$9)) -> 13543.238 | I31: =IF(F31<$C$16,G31*($C$3/12),G31*($C$10/12)) -> 13543.238 | J31: =IF(F31<$C$16,IF(F31<=$C$6,0,H31-I31),IF(F31<=$C$16+$C$13,0,H31-I31)) -> 0 | K31: =IF('Monthly Cash Flow'!$C$88="Lender Draw",HLOOKUP(F31,'Monthly Cash Flow'!$D$79:$CP$88,10),0) -> 0 | L31: =G31-J31+K31 -> 2778100 | R31: 30 | S31: =W30 -> 559390.66 | T31: =(S31*$P$3)/12 -> 5593.9066 | U31: =-IF('Cash Flow Summary'!$F$24="No",0,IF(AND('Cash Flow Summary'!$D$24="Yes",HLOOKUP($R31,'Monthly Cash Flow'!$D$6:$CP$68,61,FALSE)>0),HLOOKUP($R31,'Monthly Cash Flow'!$D$6:$CP$68,61,FALSE),IF('Cash Flow Summary'!$F$24="Current Pay",('Loan Summary'!S31*'Loan Summary'!$P$3)/12,0))) -> 0 | V31: =IF('Loan Summary'!R31=Assumptions!$AD$3,Assumptions!$AD$25,0) -> 0 | W31: =S31+T31+U31+V31 -> 564984.57
F32: 31 | G32: =IF(F32<$C$16,L31,IF(F32=$C$16,$C$9,L31)) -> 2778100 | H32: =IF(F32<$C$16,IF(F32>$C$6,-PMT(($C$3/12),$C$4,$C$2),I32),-PMT($C$10/12,$C$11,$C$9)) -> 13543.238 | I32: =IF(F32<$C$16,G32*($C$3/12),G32*($C$10/12)) -> 13543.238 | J32: =IF(F32<$C$16,IF(F32<=$C$6,0,H32-I32),IF(F32<=$C$16+$C$13,0,H32-I32)) -> 0 | K32: =IF('Monthly Cash Flow'!$C$88="Lender Draw",HLOOKUP(F32,'Monthly Cash Flow'!$D$79:$CP$88,10),0) -> 0 | L32: =G32-J32+K32 -> 2778100 | R32: 31 | S32: =W31 -> 564984.57 | T32: =(S32*$P$3)/12 -> 5649.8457 | U32: =-IF('Cash Flow Summary'!$F$24="No",0,IF(AND('Cash Flow Summary'!$D$24="Yes",HLOOKUP($R32,'Monthly Cash Flow'!$D$6:$CP$68,61,FALSE)>0),HLOOKUP($R32,'Monthly Cash Flow'!$D$6:$CP$68,61,FALSE),IF('Cash Flow Summary'!$F$24="Current Pay",('Loan Summary'!S32*'Loan Summary'!$P$3)/12,0))) -> 0 | V32: =IF('Loan Summary'!R32=Assumptions!$AD$3,Assumptions!$AD$25,0) -> 0 | W32: =S32+T32+U32+V32 -> 570634.41
F33: 32 | G33: =IF(F33<$C$16,L32,IF(F33=$C$16,$C$9,L32)) -> 2778100 | H33: =IF(F33<$C$16,IF(F33>$C$6,-PMT(($C$3/12),$C$4,$C$2),I33),-PMT($C$10/12,$C$11,$C$9)) -> 13543.238 | I33: =IF(F33<$C$16,G33*($C$3/12),G33*($C$10/12)) -> 13543.238 | J33: =IF(F33<$C$16,IF(F33<=$C$6,0,H33-I33),IF(F33<=$C$16+$C$13,0,H33-I33)) -> 0 | K33: =IF('Monthly Cash Flow'!$C$88="Lender Draw",HLOOKUP(F33,'Monthly Cash Flow'!$D$79:$CP$88,10),0) -> 0 | L33: =G33-J33+K33 -> 2778100 | R33: 32 | S33: =W32 -> 570634.41 | T33: =(S33*$P$3)/12 -> 5706.3441 | U33: =-IF('Cash Flow Summary'!$F$24="No",0,IF(AND('Cash Flow Summary'!$D$24="Yes",HLOOKUP($R33,'Monthly Cash Flow'!$D$6:$CP$68,61,FALSE)>0),HLOOKUP($R33,'Monthly Cash Flow'!$D$6:$CP$68,61,FALSE),IF('Cash Flow Summary'!$F$24="Current Pay",('Loan Summary'!S33*'Loan Summary'!$P$3)/12,0))) -> 0 | V33: =IF('Loan Summary'!R33=Assumptions!$AD$3,Assumptions!$AD$25,0) -> 0 | W33: =S33+T33+U33+V33 -> 576340.76
F34: 33 | G34: =IF(F34<$C$16,L33,IF(F34=$C$16,$C$9,L33)) -> 2778100 | H34: =IF(F34<$C$16,IF(F34>$C$6,-PMT(($C$3/12),$C$4,$C$2),I34),-PMT($C$10/12,$C$11,$C$9)) -> 13543.238 | I34: =IF(F34<$C$16,G34*($C$3/12),G34*($C$10/12)) -> 13543.238 | J34: =IF(F34<$C$16,IF(F34<=$C$6,0,H34-I34),IF(F34<=$C$16+$C$13,0,H34-I34)) -> 0 | K34: =IF('Monthly Cash Flow'!$C$88="Lender Draw",HLOOKUP(F34,'Monthly Cash Flow'!$D$79:$CP$88,10),0) -> 0 | L34: =G34-J34+K34 -> 2778100 | R34: 33 | S34: =W33 -> 576340.76 | T34: =(S34*$P$3)/12 -> 5763.4076 | U34: =-IF('Cash Flow Summary'!$F$24="No",0,IF(AND('Cash Flow Summary'!$D$24="Yes",HLOOKUP($R34,'Monthly Cash Flow'!$D$6:$CP$68,61,FALSE)>0),HLOOKUP($R34,'Monthly Cash Flow'!$D$6:$CP$68,61,FALSE),IF('Cash Flow Summary'!$F$24="Current Pay",('Loan Summary'!S34*'Loan Summary'!$P$3)/12,0))) -> 0 | V34: =IF('Loan Summary'!R34=Assumptions!$AD$3,Assumptions!$AD$25,0) -> 0 | W34: =S34+T34+U34+V34 -> 582104.17
F35: 34 | G35: =IF(F35<$C$16,L34,IF(F35=$C$16,$C$9,L34)) -> 2778100 | H35: =IF(F35<$C$16,IF(F35>$C$6,-PMT(($C$3/12),$C$4,$C$2),I35),-PMT($C$10/12,$C$11,$C$9)) -> 13543.238 | I35: =IF(F35<$C$16,G35*($C$3/12),G35*($C$10/12)) -> 13543.238 | J35: =IF(F35<$C$16,IF(F35<=$C$6,0,H35-I35),IF(F35<=$C$16+$C$13,0,H35-I35)) -> 0 | K35: =IF('Monthly Cash Flow'!$C$88="Lender Draw",HLOOKUP(F35,'Monthly Cash Flow'!$D$79:$CP$88,10),0) -> 0 | L35: =G35-J35+K35 -> 2778100 | R35: 34 | S35: =W34 -> 582104.17 | T35: =(S35*$P$3)/12 -> 5821.0417 | U35: =-IF('Cash Flow Summary'!$F$24="No",0,IF(AND('Cash Flow Summary'!$D$24="Yes",HLOOKUP($R35,'Monthly Cash Flow'!$D$6:$CP$68,61,FALSE)>0),HLOOKUP($R35,'Monthly Cash Flow'!$D$6:$CP$68,61,FALSE),IF('Cash Flow Summary'!$F$24="Current Pay",('Loan Summary'!S35*'Loan Summary'!$P$3)/12,0))) -> 0 | V35: =IF('Loan Summary'!R35=Assumptions!$AD$3,Assumptions!$AD$25,0) -> 0 | W35: =S35+T35+U35+V35 -> 587925.21
F36: 35 | G36: =IF(F36<$C$16,L35,IF(F36=$C$16,$C$9,L35)) -> 3740191.3 | H36: =IF(F36<$C$16,IF(F36>$C$6,-PMT(($C$3/12),$C$4,$C$2),I36),-PMT($C$10/12,$C$11,$C$9)) -> 21236.395 | I36: =IF(F36<$C$16,G36*($C$3/12),G36*($C$10/12)) -> 17142.543 | J36: =IF(F36<$C$16,IF(F36<=$C$6,0,H36-I36),IF(F36<=$C$16+$C$13,0,H36-I36)) -> 0 | K36: =IF('Monthly Cash Flow'!$C$88="Lender Draw",HLOOKUP(F36,'Monthly Cash Flow'!$D$79:$CP$88,10),0) -> 0 | L36: =G36-J36+K36 -> 3740191.3 | R36: 35 | S36: =W35 -> 587925.21 | T36: =(S36*$P$3)/12 -> 5879.2521 | U36: =-IF('Cash Flow Summary'!$F$24="No",0,IF(AND('Cash Flow Summary'!$D$24="Yes",HLOOKUP($R36,'Monthly Cash Flow'!$D$6:$CP$68,61,FALSE)>0),HLOOKUP($R36,'Monthly Cash Flow'!$D$6:$CP$68,61,FALSE),IF('Cash Flow Summary'!$F$24="Current Pay",('Loan Summary'!S36*'Loan Summary'!$P$3)/12,0))) -> 0 | V36: =IF('Loan Summary'!R36=Assumptions!$AD$3,Assumptions!$AD$25,0) -> 0 | W36: =S36+T36+U36+V36 -> 593804.46
F37: 36 | G37: =IF(F37<$C$16,L36,IF(F37=$C$16,$C$9,L36)) -> 3740191.3 | H37: =IF(F37<$C$16,IF(F37>$C$6,-PMT(($C$3/12),$C$4,$C$2),I37),-PMT($C$10/12,$C$11,$C$9)) -> 21236.395 | I37: =IF(F37<$C$16,G37*($C$3/12),G37*($C$10/12)) -> 17142.543 | J37: =IF(F37<$C$16,IF(F37<=$C$6,0,H37-I37),IF(F37<=$C$16+$C$13,0,H37-I37)) -> 0 | K37: =IF('Monthly Cash Flow'!$C$88="Lender Draw",HLOOKUP(F37,'Monthly Cash Flow'!$D$79:$CP$88,10),0) -> 0 | L37: =G37-J37+K37 -> 3740191.3 | R37: 36 | S37: =W36 -> 593804.46 | T37: =(S37*$P$3)/12 -> 5938.0446 | U37: =-IF('Cash Flow Summary'!$F$24="No",0,IF(AND('Cash Flow Summary'!$D$24="Yes",HLOOKUP($R37,'Monthly Cash Flow'!$D$6:$CP$68,61,FALSE)>0),HLOOKUP($R37,'Monthly Cash Flow'!$D$6:$CP$68,61,FALSE),IF('Cash Flow Summary'!$F$24="Current Pay",('Loan Summary'!S37*'Loan Summary'!$P$3)/12,0))) -> 0 | V37: =IF('Loan Summary'!R37=Assumptions!$AD$3,Assumptions!$AD$25,0) -> 0 | W37: =S37+T37+U37+V37 -> 599742.5
F38: 37 | G38: =IF(F38<$C$16,L37,IF(F38=$C$16,$C$9,L37)) -> 3740191.3 | H38: =IF(F38<$C$16,IF(F38>$C$6,-PMT(($C$3/12),$C$4,$C$2),I38),-PMT($C$10/12,$C$11,$C$9)) -> 21236.395 | I38: =IF(F38<$C$16,G38*($C$3/12),G38*($C$10/12)) -> 17142.543 | J38: =IF(F38<$C$16,IF(F38<=$C$6,0,H38-I38),IF(F38<=$C$16+$C$13,0,H38-I38)) -> 0 | K38: =IF('Monthly Cash Flow'!$C$88="Lender Draw",HLOOKUP(F38,'Monthly Cash Flow'!$D$79:$CP$88,10),0) -> 0 | L38: =G38-J38+K38 -> 3740191.3 | R38: 37 | S38: =W37 -> 599742.5 | T38: =(S38*$P$3)/12 -> 5997.425 | U38: =-IF('Cash Flow Summary'!$G$24="No",0,IF(AND('Cash Flow Summary'!$D$24="Yes",HLOOKUP($R38,'Monthly Cash Flow'!$D$6:$CP$68,61,FALSE)>0),HLOOKUP($R38,'Monthly Cash Flow'!$D$6:$CP$68,61,FALSE),IF('Cash Flow Summary'!$G$24="Current Pay",('Loan Summary'!S38*'Loan Summary'!$P$3)/12,0))) -> 0 | V38: =IF('Loan Summary'!R38=Assumptions!$AD$3,Assumptions!$AD$25,0) -> 0 | W38: =S38+T38+U38+V38 -> 605739.93
F39: 38 | G39: =IF(F39<$C$16,L38,IF(F39=$C$16,$C$9,L38)) -> 3740191.3 | H39: =IF(F39<$C$16,IF(F39>$C$6,-PMT(($C$3/12),$C$4,$C$2),I39),-PMT($C$10/12,$C$11,$C$9)) -> 21236.395 | I39: =IF(F39<$C$16,G39*($C$3/12),G39*($C$10/12)) -> 17142.543 | J39: =IF(F39<$C$16,IF(F39<=$C$6,0,H39-I39),IF(F39<=$C$16+$C$13,0,H39-I39)) -> 0 | K39: =IF('Monthly Cash Flow'!$C$88="Lender Draw",HLOOKUP(F39,'Monthly Cash Flow'!$D$79:$CP$88,10),0) -> 0 | L39: =G39-J39+K39 -> 3740191.3 | R39: 38 | S39: =W38 -> 605739.93 | T39: =(S39*$P$3)/12 -> 6057.3993 | U39: =-IF('Cash Flow Summary'!$G$24="No",0,IF(AND('Cash Flow Summary'!$D$24="Yes",HLOOKUP($R39,'Monthly Cash Flow'!$D$6:$CP$68,61,FALSE)>0),HLOOKUP($R39,'Monthly Cash Flow'!$D$6:$CP$68,61,FALSE),IF('Cash Flow Summary'!$G$24="Current Pay",('Loan Summary'!S39*'Loan Summary'!$P$3)/12,0))) -> 0 | V39: =IF('Loan Summary'!R39=Assumptions!$AD$3,Assumptions!$AD$25,0) -> 0 | W39: =S39+T39+U39+V39 -> 611797.33
F40: 39 | G40: =IF(F40<$C$16,L39,IF(F40=$C$16,$C$9,L39)) -> 3740191.3 | H40: =IF(F40<$C$16,IF(F40>$C$6,-PMT(($C$3/12),$C$4,$C$2),I40),-PMT($C$10/12,$C$11,$C$9)) -> 21236.395 | I40: =IF(F40<$C$16,G40*($C$3/12),G40*($C$10/12)) -> 17142.543 | J40: =IF(F40<$C$16,IF(F40<=$C$6,0,H40-I40),IF(F40<=$C$16+$C$13,0,H40-I40)) -> 0 | K40: =IF('Monthly Cash Flow'!$C$88="Lender Draw",HLOOKUP(F40,'Monthly Cash Flow'!$D$79:$CP$88,10),0) -> 0 | L40: =G40-J40+K40 -> 3740191.3 | R40: 39 | S40: =W39 -> 611797.33 | T40: =(S40*$P$3)/12 -> 6117.9733 | U40: =-IF('Cash Flow Summary'!$G$24="No",0,IF(AND('Cash Flow Summary'!$D$24="Yes",HLOOKUP($R40,'Monthly Cash Flow'!$D$6:$CP$68,61,FALSE)>0),HLOOKUP($R40,'Monthly Cash Flow'!$D$6:$CP$68,61,FALSE),IF('Cash Flow Summary'!$G$24="Current Pay",('Loan Summary'!S40*'Loan Summary'!$P$3)/12,0))) -> 0 | V40: =IF('Loan Summary'!R40=Assumptions!$AD$3,Assumptions!$AD$25,0) -> 0 | W40: =S40+T40+U40+V40 -> 617915.3
F41: 40 | G41: =IF(F41<$C$16,L40,IF(F41=$C$16,$C$9,L40)) -> 3740191.3 | H41: =IF(F41<$C$16,IF(F41>$C$6,-PMT(($C$3/12),$C$4,$C$2),I41),-PMT($C$10/12,$C$11,$C$9)) -> 21236.395 | I41: =IF(F41<$C$16,G41*($C$3/12),G41*($C$10/12)) -> 17142.543 | J41: =IF(F41<$C$16,IF(F41<=$C$6,0,H41-I41),IF(F41<=$C$16+$C$13,0,H41-I41)) -> 0 | K41: =IF('Monthly Cash Flow'!$C$88="Lender Draw",HLOOKUP(F41,'Monthly Cash Flow'!$D$79:$CP$88,10),0) -> 0 | L41: =G41-J41+K41 -> 3740191.3 | R41: 40 | S41: =W40 -> 617915.3 | T41: =(S41*$P$3)/12 -> 6179.153 | U41: =-IF('Cash Flow Summary'!$G$24="No",0,IF(AND('Cash Flow Summary'!$D$24="Yes",HLOOKUP($R41,'Monthly Cash Flow'!$D$6:$CP$68,61,FALSE)>0),HLOOKUP($R41,'Monthly Cash Flow'!$D$6:$CP$68,61,FALSE),IF('Cash Flow Summary'!$G$24="Current Pay",('Loan Summary'!S41*'Loan Summary'!$P$3)/12,0))) -> 0 | V41: =IF('Loan Summary'!R41=Assumptions!$AD$3,Assumptions!$AD$25,0) -> 0 | W41: =S41+T41+U41+V41 -> 624094.46
F42: 41 | G42: =IF(F42<$C$16,L41,IF(F42=$C$16,$C$9,L41)) -> 3740191.3 | H42: =IF(F42<$C$16,IF(F42>$C$6,-PMT(($C$3/12),$C$4,$C$2),I42),-PMT($C$10/12,$C$11,$C$9)) -> 21236.395 | I42: =IF(F42<$C$16,G42*($C$3/12),G42*($C$10/12)) -> 17142.543 | J42: =IF(F42<$C$16,IF(F42<=$C$6,0,H42-I42),IF(F42<=$C$16+$C$13,0,H42-I42)) -> 0 | K42: =IF('Monthly Cash Flow'!$C$88="Lender Draw",HLOOKUP(F42,'Monthly Cash Flow'!$D$79:$CP$88,10),0) -> 0 | L42: =G42-J42+K42 -> 3740191.3 | R42: 41 | S42: =W41 -> 624094.46 | T42: =(S42*$P$3)/12 -> 6240.9446 | U42: =-IF('Cash Flow Summary'!$G$24="No",0,IF(AND('Cash Flow Summary'!$D$24="Yes",HLOOKUP($R42,'Monthly Cash Flow'!$D$6:$CP$68,61,FALSE)>0),HLOOKUP($R42,'Monthly Cash Flow'!$D$6:$CP$68,61,FALSE),IF('Cash Flow Summary'!$G$24="Current Pay",('Loan Summary'!S42*'Loan Summary'!$P$3)/12,0))) -> 0 | V42: =IF('Loan Summary'!R42=Assumptions!$AD$3,Assumptions!$AD$25,0) -> 0 | W42: =S42+T42+U42+V42 -> 630335.4
F43: 42 | G43: =IF(F43<$C$16,L42,IF(F43=$C$16,$C$9,L42)) -> 3740191.3 | H43: =IF(F43<$C$16,IF(F43>$C$6,-PMT(($C$3/12),$C$4,$C$2),I43),-PMT($C$10/12,$C$11,$C$9)) -> 21236.395 | I43: =IF(F43<$C$16,G43*($C$3/12),G43*($C$10/12)) -> 17142.543 | J43: =IF(F43<$C$16,IF(F43<=$C$6,0,H43-I43),IF(F43<=$C$16+$C$13,0,H43-I43)) -> 0 | K43: =IF('Monthly Cash Flow'!$C$88="Lender Draw",HLOOKUP(F43,'Monthly Cash Flow'!$D$79:$CP$88,10),0) -> 0 | L43: =G43-J43+K43 -> 3740191.3 | R43: 42 | S43: =W42 -> 630335.4 | T43: =(S43*$P$3)/12 -> 6303.354 | U43: =-IF('Cash Flow Summary'!$G$24="No",0,IF(AND('Cash Flow Summary'!$D$24="Yes",HLOOKUP($R43,'Monthly Cash Flow'!$D$6:$CP$68,61,FALSE)>0),HLOOKUP($R43,'Monthly Cash Flow'!$D$6:$CP$68,61,FALSE),IF('Cash Flow Summary'!$G$24="Current Pay",('Loan Summary'!S43*'Loan Summary'!$P$3)/12,0))) -> 0 | V43: =IF('Loan Summary'!R43=Assumptions!$AD$3,Assumptions!$AD$25,0) -> 0 | W43: =S43+T43+U43+V43 -> 636638.75
F44: 43 | G44: =IF(F44<$C$16,L43,IF(F44=$C$16,$C$9,L43)) -> 3740191.3 | H44: =IF(F44<$C$16,IF(F44>$C$6,-PMT(($C$3/12),$C$4,$C$2),I44),-PMT($C$10/12,$C$11,$C$9)) -> 21236.395 | I44: =IF(F44<$C$16,G44*($C$3/12),G44*($C$10/12)) -> 17142.543 | J44: =IF(F44<$C$16,IF(F44<=$C$6,0,H44-I44),IF(F44<=$C$16+$C$13,0,H44-I44)) -> 0 | K44: =IF('Monthly Cash Flow'!$C$88="Lender Draw",HLOOKUP(F44,'Monthly Cash Flow'!$D$79:$CP$88,10),0) -> 0 | L44: =G44-J44+K44 -> 3740191.3 | R44: 43 | S44: =W43 -> 636638.75 | T44: =(S44*$P$3)/12 -> 6366.3875 | U44: =-IF('Cash Flow Summary'!$G$24="No",0,IF(AND('Cash Flow Summary'!$D$24="Yes",HLOOKUP($R44,'Monthly Cash Flow'!$D$6:$CP$68,61,FALSE)>0),HLOOKUP($R44,'Monthly Cash Flow'!$D$6:$CP$68,61,FALSE),IF('Cash Flow Summary'!$G$24="Current Pay",('Loan Summary'!S44*'Loan Summary'!$P$3)/12,0))) -> 0 | V44: =IF('Loan Summary'!R44=Assumptions!$AD$3,Assumptions!$AD$25,0) -> 0 | W44: =S44+T44+U44+V44 -> 643005.14
F45: 44 | G45: =IF(F45<$C$16,L44,IF(F45=$C$16,$C$9,L44)) -> 3740191.3 | H45: =IF(F45<$C$16,IF(F45>$C$6,-PMT(($C$3/12),$C$4,$C$2),I45),-PMT($C$10/12,$C$11,$C$9)) -> 21236.395 | I45: =IF(F45<$C$16,G45*($C$3/12),G45*($C$10/12)) -> 17142.543 | J45: =IF(F45<$C$16,IF(F45<=$C$6,0,H45-I45),IF(F45<=$C$16+$C$13,0,H45-I45)) -> 0 | K45: =IF('Monthly Cash Flow'!$C$88="Lender Draw",HLOOKUP(F45,'Monthly Cash Flow'!$D$79:$CP$88,10),0) -> 0 | L45: =G45-J45+K45 -> 3740191.3 | R45: 44 | S45: =W44 -> 643005.14 | T45: =(S45*$P$3)/12 -> 6430.0514 | U45: =-IF('Cash Flow Summary'!$G$24="No",0,IF(AND('Cash Flow Summary'!$D$24="Yes",HLOOKUP($R45,'Monthly Cash Flow'!$D$6:$CP$68,61,FALSE)>0),HLOOKUP($R45,'Monthly Cash Flow'!$D$6:$CP$68,61,FALSE),IF('Cash Flow Summary'!$G$24="Current Pay",('Loan Summary'!S45*'Loan Summary'!$P$3)/12,0))) -> 0 | V45: =IF('Loan Summary'!R45=Assumptions!$AD$3,Assumptions!$AD$25,0) -> 0 | W45: =S45+T45+U45+V45 -> 649435.19
F46: 45 | G46: =IF(F46<$C$16,L45,IF(F46=$C$16,$C$9,L45)) -> 3740191.3 | H46: =IF(F46<$C$16,IF(F46>$C$6,-PMT(($C$3/12),$C$4,$C$2),I46),-PMT($C$10/12,$C$11,$C$9)) -> 21236.395 | I46: =IF(F46<$C$16,G46*($C$3/12),G46*($C$10/12)) -> 17142.543 | J46: =IF(F46<$C$16,IF(F46<=$C$6,0,H46-I46),IF(F46<=$C$16+$C$13,0,H46-I46)) -> 0 | K46: =IF('Monthly Cash Flow'!$C$88="Lender Draw",HLOOKUP(F46,'Monthly Cash Flow'!$D$79:$CP$88,10),0) -> 0 | L46: =G46-J46+K46 -> 3740191.3 | R46: 45 | S46: =W45 -> 649435.19 | T46: =(S46*$P$3)/12 -> 6494.3519 | U46: =-IF('Cash Flow Summary'!$G$24="No",0,IF(AND('Cash Flow Summary'!$D$24="Yes",HLOOKUP($R46,'Monthly Cash Flow'!$D$6:$CP$68,61,FALSE)>0),HLOOKUP($R46,'Monthly Cash Flow'!$D$6:$CP$68,61,FALSE),IF('Cash Flow Summary'!$G$24="Current Pay",('Loan Summary'!S46*'Loan Summary'!$P$3)/12,0))) -> 0 | V46: =IF('Loan Summary'!R46=Assumptions!$AD$3,Assumptions!$AD$25,0) -> 0 | W46: =S46+T46+U46+V46 -> 655929.54
F47: 46 | G47: =IF(F47<$C$16,L46,IF(F47=$C$16,$C$9,L46)) -> 3740191.3 | H47: =IF(F47<$C$16,IF(F47>$C$6,-PMT(($C$3/12),$C$4,$C$2),I47),-PMT($C$10/12,$C$11,$C$9)) -> 21236.395 | I47: =IF(F47<$C$16,G47*($C$3/12),G47*($C$10/12)) -> 17142.543 | J47: =IF(F47<$C$16,IF(F47<=$C$6,0,H47-I47),IF(F47<=$C$16+$C$13,0,H47-I47)) -> 0 | K47: =IF('Monthly Cash Flow'!$C$88="Lender Draw",HLOOKUP(F47,'Monthly Cash Flow'!$D$79:$CP$88,10),0) -> 0 | L47: =G47-J47+K47 -> 3740191.3 | R47: 46 | S47: =W46 -> 655929.54 | T47: =(S47*$P$3)/12 -> 6559.2954 | U47: =-IF('Cash Flow Summary'!$G$24="No",0,IF(AND('Cash Flow Summary'!$D$24="Yes",HLOOKUP($R47,'Monthly Cash Flow'!$D$6:$CP$68,61,FALSE)>0),HLOOKUP($R47,'Monthly Cash Flow'!$D$6:$CP$68,61,FALSE),IF('Cash Flow Summary'!$G$24="Current Pay",('Loan Summary'!S47*'Loan Summary'!$P$3)/12,0))) -> 0 | V47: =IF('Loan Summary'!R47=Assumptions!$AD$3,Assumptions!$AD$25,0) -> 0 | W47: =S47+T47+U47+V47 -> 662488.84
F48: 47 | G48: =IF(F48<$C$16,L47,IF(F48=$C$16,$C$9,L47)) -> 3740191.3 | H48: =IF(F48<$C$16,IF(F48>$C$6,-PMT(($C$3/12),$C$4,$C$2),I48),-PMT($C$10/12,$C$11,$C$9)) -> 21236.395 | I48: =IF(F48<$C$16,G48*($C$3/12),G48*($C$10/12)) -> 17142.543 | J48: =IF(F48<$C$16,IF(F48<=$C$6,0,H48-I48),IF(F48<=$C$16+$C$13,0,H48-I48)) -> 0 | K48: =IF('Monthly Cash Flow'!$C$88="Lender Draw",HLOOKUP(F48,'Monthly Cash Flow'!$D$79:$CP$88,10),0) -> 0 | L48: =G48-J48+K48 -> 3740191.3 | R48: 47 | S48: =W47 -> 662488.84 | T48: =(S48*$P$3)/12 -> 6624.8884 | U48: =-IF('Cash Flow Summary'!$G$24="No",0,IF(AND('Cash Flow Summary'!$D$24="Yes",HLOOKUP($R48,'Monthly Cash Flow'!$D$6:$CP$68,61,FALSE)>0),HLOOKUP($R48,'Monthly Cash Flow'!$D$6:$CP$68,61,FALSE),IF('Cash Flow Summary'!$G$24="Current Pay",('Loan Summary'!S48*'Loan Summary'!$P$3)/12,0))) -> 0 | V48: =IF('Loan Summary'!R48=Assumptions!$AD$3,Assumptions!$AD$25,0) -> 0 | W48: =S48+T48+U48+V48 -> 669113.73
F49: 48 | G49: =IF(F49<$C$16,L48,IF(F49=$C$16,$C$9,L48)) -> 3740191.3 | H49: =IF(F49<$C$16,IF(F49>$C$6,-PMT(($C$3/12),$C$4,$C$2),I49),-PMT($C$10/12,$C$11,$C$9)) -> 21236.395 | I49: =IF(F49<$C$16,G49*($C$3/12),G49*($C$10/12)) -> 17142.543 | J49: =IF(F49<$C$16,IF(F49<=$C$6,0,H49-I49),IF(F49<=$C$16+$C$13,0,H49-I49)) -> 0 | K49: =IF('Monthly Cash Flow'!$C$88="Lender Draw",HLOOKUP(F49,'Monthly Cash Flow'!$D$79:$CP$88,10),0) -> 0 | L49: =G49-J49+K49 -> 3740191.3 | R49: 48 | S49: =W48 -> 669113.73 | T49: =(S49*$P$3)/12 -> 6691.1373 | U49: =-IF('Cash Flow Summary'!$G$24="No",0,IF(AND('Cash Flow Summary'!$D$24="Yes",HLOOKUP($R49,'Monthly Cash Flow'!$D$6:$CP$68,61,FALSE)>0),HLOOKUP($R49,'Monthly Cash Flow'!$D$6:$CP$68,61,FALSE),IF('Cash Flow Summary'!$G$24="Current Pay",('Loan Summary'!S49*'Loan Summary'!$P$3)/12,0))) -> 0 | V49: =IF('Loan Summary'!R49=Assumptions!$AD$3,Assumptions!$AD$25,0) -> 0 | W49: =S49+T49+U49+V49 -> 675804.87
F50: 49 | G50: =IF(F50<$C$16,L49,IF(F50=$C$16,$C$9,L49)) -> 3740191.3 | H50: =IF(F50<$C$16,IF(F50>$C$6,-PMT(($C$3/12),$C$4,$C$2),I50),-PMT($C$10/12,$C$11,$C$9)) -> 21236.395 | I50: =IF(F50<$C$16,G50*($C$3/12),G50*($C$10/12)) -> 17142.543 | J50: =IF(F50<$C$16,IF(F50<=$C$6,0,H50-I50),IF(F50<=$C$16+$C$13,0,H50-I50)) -> 0 | K50: =IF('Monthly Cash Flow'!$C$88="Lender Draw",HLOOKUP(F50,'Monthly Cash Flow'!$D$79:$CP$88,10),0) -> 0 | L50: =G50-J50+K50 -> 3740191.3 | R50: 49 | S50: =W49 -> 675804.87 | T50: =(S50*$P$3)/12 -> 6758.0487 | U50: =-IF('Cash Flow Summary'!$H$24="No",0,IF(AND('Cash Flow Summary'!$D$24="Yes",HLOOKUP($R50,'Monthly Cash Flow'!$D$6:$CP$68,61,FALSE)>0),HLOOKUP($R50,'Monthly Cash Flow'!$D$6:$CP$68,61,FALSE),IF('Cash Flow Summary'!$H$24="Current Pay",('Loan Summary'!S50*'Loan Summary'!$P$3)/12,0))) -> 0 | V50: =IF('Loan Summary'!R50=Assumptions!$AD$3,Assumptions!$AD$25,0) -> 0 | W50: =S50+T50+U50+V50 -> 682562.91
F51: 50 | G51: =IF(F51<$C$16,L50,IF(F51=$C$16,$C$9,L50)) -> 3740191.3 | H51: =IF(F51<$C$16,IF(F51>$C$6,-PMT(($C$3/12),$C$4,$C$2),I51),-PMT($C$10/12,$C$11,$C$9)) -> 21236.395 | I51: =IF(F51<$C$16,G51*($C$3/12),G51*($C$10/12)) -> 17142.543 | J51: =IF(F51<$C$16,IF(F51<=$C$6,0,H51-I51),IF(F51<=$C$16+$C$13,0,H51-I51)) -> 0 | K51: =IF('Monthly Cash Flow'!$C$88="Lender Draw",HLOOKUP(F51,'Monthly Cash Flow'!$D$79:$CP$88,10),0) -> 0 | L51: =G51-J51+K51 -> 3740191.3 | R51: 50 | S51: =W50 -> 682562.91 | T51: =(S51*$P$3)/12 -> 6825.6291 | U51: =-IF('Cash Flow Summary'!$H$24="No",0,IF(AND('Cash Flow Summary'!$D$24="Yes",HLOOKUP($R51,'Monthly Cash Flow'!$D$6:$CP$68,61,FALSE)>0),HLOOKUP($R51,'Monthly Cash Flow'!$D$6:$CP$68,61,FALSE),IF('Cash Flow Summary'!$H$24="Current Pay",('Loan Summary'!S51*'Loan Summary'!$P$3)/12,0))) -> 0 | V51: =IF('Loan Summary'!R51=Assumptions!$AD$3,Assumptions!$AD$25,0) -> 0 | W51: =S51+T51+U51+V51 -> 689388.54
F52: 51 | G52: =IF(F52<$C$16,L51,IF(F52=$C$16,$C$9,L51)) -> 3740191.3 | H52: =IF(F52<$C$16,IF(F52>$C$6,-PMT(($C$3/12),$C$4,$C$2),I52),-PMT($C$10/12,$C$11,$C$9)) -> 21236.395 | I52: =IF(F52<$C$16,G52*($C$3/12),G52*($C$10/12)) -> 17142.543 | J52: =IF(F52<$C$16,IF(F52<=$C$6,0,H52-I52),IF(F52<=$C$16+$C$13,0,H52-I52)) -> 0 | K52: =IF('Monthly Cash Flow'!$C$88="Lender Draw",HLOOKUP(F52,'Monthly Cash Flow'!$D$79:$CP$88,10),0) -> 0 | L52: =G52-J52+K52 -> 3740191.3 | R52: 51 | S52: =W51 -> 689388.54 | T52: =(S52*$P$3)/12 -> 6893.8854 | U52: =-IF('Cash Flow Summary'!$H$24="No",0,IF(AND('Cash Flow Summary'!$D$24="Yes",HLOOKUP($R52,'Monthly Cash Flow'!$D$6:$CP$68,61,FALSE)>0),HLOOKUP($R52,'Monthly Cash Flow'!$D$6:$CP$68,61,FALSE),IF('Cash Flow Summary'!$H$24="Current Pay",('Loan Summary'!S52*'Loan Summary'!$P$3)/12,0))) -> 0 | V52: =IF('Loan Summary'!R52=Assumptions!$AD$3,Assumptions!$AD$25,0) -> 0 | W52: =S52+T52+U52+V52 -> 696282.43
F53: 52 | G53: =IF(F53<$C$16,L52,IF(F53=$C$16,$C$9,L52)) -> 3740191.3 | H53: =IF(F53<$C$16,IF(F53>$C$6,-PMT(($C$3/12),$C$4,$C$2),I53),-PMT($C$10/12,$C$11,$C$9)) -> 21236.395 | I53: =IF(F53<$C$16,G53*($C$3/12),G53*($C$10/12)) -> 17142.543 | J53: =IF(F53<$C$16,IF(F53<=$C$6,0,H53-I53),IF(F53<=$C$16+$C$13,0,H53-I53)) -> 0 | K53: =IF('Monthly Cash Flow'!$C$88="Lender Draw",HLOOKUP(F53,'Monthly Cash Flow'!$D$79:$CP$88,10),0) -> 0 | L53: =G53-J53+K53 -> 3740191.3 | R53: 52 | S53: =W52 -> 696282.43 | T53: =(S53*$P$3)/12 -> 6962.8243 | U53: =-IF('Cash Flow Summary'!$H$24="No",0,IF(AND('Cash Flow Summary'!$D$24="Yes",HLOOKUP($R53,'Monthly Cash Flow'!$D$6:$CP$68,61,FALSE)>0),HLOOKUP($R53,'Monthly Cash Flow'!$D$6:$CP$68,61,FALSE),IF('Cash Flow Summary'!$H$24="Current Pay",('Loan Summary'!S53*'Loan Summary'!$P$3)/12,0))) -> 0 | V53: =IF('Loan Summary'!R53=Assumptions!$AD$3,Assumptions!$AD$25,0) -> 0 | W53: =S53+T53+U53+V53 -> 703245.25
F54: 53 | G54: =IF(F54<$C$16,L53,IF(F54=$C$16,$C$9,L53)) -> 3740191.3 | H54: =IF(F54<$C$16,IF(F54>$C$6,-PMT(($C$3/12),$C$4,$C$2),I54),-PMT($C$10/12,$C$11,$C$9)) -> 21236.395 | I54: =IF(F54<$C$16,G54*($C$3/12),G54*($C$10/12)) -> 17142.543 | J54: =IF(F54<$C$16,IF(F54<=$C$6,0,H54-I54),IF(F54<=$C$16+$C$13,0,H54-I54)) -> 0 | K54: =IF('Monthly Cash Flow'!$C$88="Lender Draw",HLOOKUP(F54,'Monthly Cash Flow'!$D$79:$CP$88,10),0) -> 0 | L54: =G54-J54+K54 -> 3740191.3 | R54: 53 | S54: =W53 -> 703245.25 | T54: =(S54*$P$3)/12 -> 7032.4525 | U54: =-IF('Cash Flow Summary'!$H$24="No",0,IF(AND('Cash Flow Summary'!$D$24="Yes",HLOOKUP($R54,'Monthly Cash Flow'!$D$6:$CP$68,61,FALSE)>0),HLOOKUP($R54,'Monthly Cash Flow'!$D$6:$CP$68,61,FALSE),IF('Cash Flow Summary'!$H$24="Current Pay",('Loan Summary'!S54*'Loan Summary'!$P$3)/12,0))) -> 0 | V54: =IF('Loan Summary'!R54=Assumptions!$AD$3,Assumptions!$AD$25,0) -> 0 | W54: =S54+T54+U54+V54 -> 710277.71
F55: 54 | G55: =IF(F55<$C$16,L54,IF(F55=$C$16,$C$9,L54)) -> 3740191.3 | H55: =IF(F55<$C$16,IF(F55>$C$6,-PMT(($C$3/12),$C$4,$C$2),I55),-PMT($C$10/12,$C$11,$C$9)) -> 21236.395 | I55: =IF(F55<$C$16,G55*($C$3/12),G55*($C$10/12)) -> 17142.543 | J55: =IF(F55<$C$16,IF(F55<=$C$6,0,H55-I55),IF(F55<=$C$16+$C$13,0,H55-I55)) -> 0 | K55: =IF('Monthly Cash Flow'!$C$88="Lender Draw",HLOOKUP(F55,'Monthly Cash Flow'!$D$79:$CP$88,10),0) -> 0 | L55: =G55-J55+K55 -> 3740191.3 | R55: 54 | S55: =W54 -> 710277.71 | T55: =(S55*$P$3)/12 -> 7102.7771 | U55: =-IF('Cash Flow Summary'!$H$24="No",0,IF(AND('Cash Flow Summary'!$D$24="Yes",HLOOKUP($R55,'Monthly Cash Flow'!$D$6:$CP$68,61,FALSE)>0),HLOOKUP($R55,'Monthly Cash Flow'!$D$6:$CP$68,61,FALSE),IF('Cash Flow Summary'!$H$24="Current Pay",('Loan Summary'!S55*'Loan Summary'!$P$3)/12,0))) -> 0 | V55: =IF('Loan Summary'!R55=Assumptions!$AD$3,Assumptions!$AD$25,0) -> 0 | W55: =S55+T55+U55+V55 -> 717380.48
F56: 55 | G56: =IF(F56<$C$16,L55,IF(F56=$C$16,$C$9,L55)) -> 3740191.3 | H56: =IF(F56<$C$16,IF(F56>$C$6,-PMT(($C$3/12),$C$4,$C$2),I56),-PMT($C$10/12,$C$11,$C$9)) -> 21236.395 | I56: =IF(F56<$C$16,G56*($C$3/12),G56*($C$10/12)) -> 17142.543 | J56: =IF(F56<$C$16,IF(F56<=$C$6,0,H56-I56),IF(F56<=$C$16+$C$13,0,H56-I56)) -> 0 | K56: =IF('Monthly Cash Flow'!$C$88="Lender Draw",HLOOKUP(F56,'Monthly Cash Flow'!$D$79:$CP$88,10),0) -> 0 | L56: =G56-J56+K56 -> 3740191.3 | R56: 55 | S56: =W55 -> 717380.48 | T56: =(S56*$P$3)/12 -> 7173.8048 | U56: =-IF('Cash Flow Summary'!$H$24="No",0,IF(AND('Cash Flow Summary'!$D$24="Yes",HLOOKUP($R56,'Monthly Cash Flow'!$D$6:$CP$68,61,FALSE)>0),HLOOKUP($R56,'Monthly Cash Flow'!$D$6:$CP$68,61,FALSE),IF('Cash Flow Summary'!$H$24="Current Pay",('Loan Summary'!S56*'Loan Summary'!$P$3)/12,0))) -> 0 | V56: =IF('Loan Summary'!R56=Assumptions!$AD$3,Assumptions!$AD$25,0) -> 0 | W56: =S56+T56+U56+V56 -> 724554.29
F57: 56 | G57: =IF(F57<$C$16,L56,IF(F57=$C$16,$C$9,L56)) -> 3740191.3 | H57: =IF(F57<$C$16,IF(F57>$C$6,-PMT(($C$3/12),$C$4,$C$2),I57),-PMT($C$10/12,$C$11,$C$9)) -> 21236.395 | I57: =IF(F57<$C$16,G57*($C$3/12),G57*($C$10/12)) -> 17142.543 | J57: =IF(F57<$C$16,IF(F57<=$C$6,0,H57-I57),IF(F57<=$C$16+$C$13,0,H57-I57)) -> 0 | K57: =IF('Monthly Cash Flow'!$C$88="Lender Draw",HLOOKUP(F57,'Monthly Cash Flow'!$D$79:$CP$88,10),0) -> 0 | L57: =G57-J57+K57 -> 3740191.3 | R57: 56 | S57: =W56 -> 724554.29 | T57: =(S57*$P$3)/12 -> 7245.5429 | U57: =-IF('Cash Flow Summary'!$H$24="No",0,IF(AND('Cash Flow Summary'!$D$24="Yes",HLOOKUP($R57,'Monthly Cash Flow'!$D$6:$CP$68,61,FALSE)>0),HLOOKUP($R57,'Monthly Cash Flow'!$D$6:$CP$68,61,FALSE),IF('Cash Flow Summary'!$H$24="Current Pay",('Loan Summary'!S57*'Loan Summary'!$P$3)/12,0))) -> 0 | V57: =IF('Loan Summary'!R57=Assumptions!$AD$3,Assumptions!$AD$25,0) -> 0 | W57: =S57+T57+U57+V57 -> 731799.83
F58: 57 | G58: =IF(F58<$C$16,L57,IF(F58=$C$16,$C$9,L57)) -> 3740191.3 | H58: =IF(F58<$C$16,IF(F58>$C$6,-PMT(($C$3/12),$C$4,$C$2),I58),-PMT($C$10/12,$C$11,$C$9)) -> 21236.395 | I58: =IF(F58<$C$16,G58*($C$3/12),G58*($C$10/12)) -> 17142.543 | J58: =IF(F58<$C$16,IF(F58<=$C$6,0,H58-I58),IF(F58<=$C$16+$C$13,0,H58-I58)) -> 0 | K58: =IF('Monthly Cash Flow'!$C$88="Lender Draw",HLOOKUP(F58,'Monthly Cash Flow'!$D$79:$CP$88,10),0) -> 0 | L58: =G58-J58+K58 -> 3740191.3 | R58: 57 | S58: =W57 -> 731799.83 | T58: =(S58*$P$3)/12 -> 7317.9983 | U58: =-IF('Cash Flow Summary'!$H$24="No",0,IF(AND('Cash Flow Summary'!$D$24="Yes",HLOOKUP($R58,'Monthly Cash Flow'!$D$6:$CP$68,61,FALSE)>0),HLOOKUP($R58,'Monthly Cash Flow'!$D$6:$CP$68,61,FALSE),IF('Cash Flow Summary'!$H$24="Current Pay",('Loan Summary'!S58*'Loan Summary'!$P$3)/12,0))) -> 0 | V58: =IF('Loan Summary'!R58=Assumptions!$AD$3,Assumptions!$AD$25,0) -> 0 | W58: =S58+T58+U58+V58 -> 739117.83
F59: 58 | G59: =IF(F59<$C$16,L58,IF(F59=$C$16,$C$9,L58)) -> 3740191.3 | H59: =IF(F59<$C$16,IF(F59>$C$6,-PMT(($C$3/12),$C$4,$C$2),I59),-PMT($C$10/12,$C$11,$C$9)) -> 21236.395 | I59: =IF(F59<$C$16,G59*($C$3/12),G59*($C$10/12)) -> 17142.543 | J59: =IF(F59<$C$16,IF(F59<=$C$6,0,H59-I59),IF(F59<=$C$16+$C$13,0,H59-I59)) -> 0 | K59: =IF('Monthly Cash Flow'!$C$88="Lender Draw",HLOOKUP(F59,'Monthly Cash Flow'!$D$79:$CP$88,10),0) -> 0 | L59: =G59-J59+K59 -> 3740191.3 | R59: 58 | S59: =W58 -> 739117.83 | T59: =(S59*$P$3)/12 -> 7391.1783 | U59: =-IF('Cash Flow Summary'!$H$24="No",0,IF(AND('Cash Flow Summary'!$D$24="Yes",HLOOKUP($R59,'Monthly Cash Flow'!$D$6:$CP$68,61,FALSE)>0),HLOOKUP($R59,'Monthly Cash Flow'!$D$6:$CP$68,61,FALSE),IF('Cash Flow Summary'!$H$24="Current Pay",('Loan Summary'!S59*'Loan Summary'!$P$3)/12,0))) -> 0 | V59: =IF('Loan Summary'!R59=Assumptions!$AD$3,Assumptions!$AD$25,0) -> 0 | W59: =S59+T59+U59+V59 -> 746509.01
F60: 59 | G60: =IF(F60<$C$16,L59,IF(F60=$C$16,$C$9,L59)) -> 3740191.3 | H60: =IF(F60<$C$16,IF(F60>$C$6,-PMT(($C$3/12),$C$4,$C$2),I60),-PMT($C$10/12,$C$11,$C$9)) -> 21236.395 | I60: =IF(F60<$C$16,G60*($C$3/12),G60*($C$10/12)) -> 17142.543 | J60: =IF(F60<$C$16,IF(F60<=$C$6,0,H60-I60),IF(F60<=$C$16+$C$13,0,H60-I60)) -> 0 | K60: =IF('Monthly Cash Flow'!$C$88="Lender Draw",HLOOKUP(F60,'Monthly Cash Flow'!$D$79:$CP$88,10),0) -> 0 | L60: =G60-J60+K60 -> 3740191.3 | R60: 59 | S60: =W59 -> 746509.01 | T60: =(S60*$P$3)/12 -> 7465.0901 | U60: =-IF('Cash Flow Summary'!$H$24="No",0,IF(AND('Cash Flow Summary'!$D$24="Yes",HLOOKUP($R60,'Monthly Cash Flow'!$D$6:$CP$68,61,FALSE)>0),HLOOKUP($R60,'Monthly Cash Flow'!$D$6:$CP$68,61,FALSE),IF('Cash Flow Summary'!$H$24="Current Pay",('Loan Summary'!S60*'Loan Summary'!$P$3)/12,0))) -> 0 | V60: =IF('Loan Summary'!R60=Assumptions!$AD$3,Assumptions!$AD$25,0) -> 0 | W60: =S60+T60+U60+V60 -> 753974.1
F61: 60 | G61: =IF(F61<$C$16,L60,IF(F61=$C$16,$C$9,L60)) -> 3740191.3 | H61: =IF(F61<$C$16,IF(F61>$C$6,-PMT(($C$3/12),$C$4,$C$2),I61),-PMT($C$10/12,$C$11,$C$9)) -> 21236.395 | I61: =IF(F61<$C$16,G61*($C$3/12),G61*($C$10/12)) -> 17142.543 | J61: =IF(F61<$C$16,IF(F61<=$C$6,0,H61-I61),IF(F61<=$C$16+$C$13,0,H61-I61)) -> 0 | K61: =IF('Monthly Cash Flow'!$C$88="Lender Draw",HLOOKUP(F61,'Monthly Cash Flow'!$D$79:$CP$88,10),0) -> 0 | L61: =G61-J61+K61 -> 3740191.3 | R61: 60 | S61: =W60 -> 753974.1 | T61: =(S61*$P$3)/12 -> 7539.741 | U61: =-IF('Cash Flow Summary'!$H$24="No",0,IF(AND('Cash Flow Summary'!$D$24="Yes",HLOOKUP($R61,'Monthly Cash Flow'!$D$6:$CP$68,61,FALSE)>0),HLOOKUP($R61,'Monthly Cash Flow'!$D$6:$CP$68,61,FALSE),IF('Cash Flow Summary'!$H$24="Current Pay",('Loan Summary'!S61*'Loan Summary'!$P$3)/12,0))) -> 0 | V61: =IF('Loan Summary'!R61=Assumptions!$AD$3,Assumptions!$AD$25,0) -> 0 | W61: =S61+T61+U61+V61 -> 761513.84
F62: 61 | G62: =IF(F62<$C$16,L61,IF(F62=$C$16,$C$9,L61)) -> 3740191.3 | H62: =IF(F62<$C$16,IF(F62>$C$6,-PMT(($C$3/12),$C$4,$C$2),I62),-PMT($C$10/12,$C$11,$C$9)) -> 21236.395 | I62: =IF(F62<$C$16,G62*($C$3/12),G62*($C$10/12)) -> 17142.543 | J62: =IF(F62<$C$16,IF(F62<=$C$6,0,H62-I62),IF(F62<=$C$16+$C$13,0,H62-I62)) -> 0 | K62: =IF('Monthly Cash Flow'!$C$88="Lender Draw",HLOOKUP(F62,'Monthly Cash Flow'!$D$79:$CP$88,10),0) -> 0 | L62: =G62-J62+K62 -> 3740191.3 | R62: 61 | S62: =W61 -> 761513.84 | T62: =(S62*$P$3)/12 -> 7615.1384 | U62: =-IF('Cash Flow Summary'!$I$24="No",0,IF(AND('Cash Flow Summary'!$D$24="Yes",HLOOKUP($R62,'Monthly Cash Flow'!$D$6:$CP$68,61,FALSE)>0),HLOOKUP($R62,'Monthly Cash Flow'!$D$6:$CP$68,61,FALSE),IF('Cash Flow Summary'!$I$24="Current Pay",('Loan Summary'!S62*'Loan Summary'!$P$3)/12,0))) -> 0 | V62: =IF('Loan Summary'!R62=Assumptions!$AD$3,Assumptions!$AD$25,0) -> 0 | W62: =S62+T62+U62+V62 -> 769128.98
F63: 62 | G63: =IF(F63<$C$16,L62,IF(F63=$C$16,$C$9,L62)) -> 3740191.3 | H63: =IF(F63<$C$16,IF(F63>$C$6,-PMT(($C$3/12),$C$4,$C$2),I63),-PMT($C$10/12,$C$11,$C$9)) -> 21236.395 | I63: =IF(F63<$C$16,G63*($C$3/12),G63*($C$10/12)) -> 17142.543 | J63: =IF(F63<$C$16,IF(F63<=$C$6,0,H63-I63),IF(F63<=$C$16+$C$13,0,H63-I63)) -> 0 | K63: =IF('Monthly Cash Flow'!$C$88="Lender Draw",HLOOKUP(F63,'Monthly Cash Flow'!$D$79:$CP$88,10),0) -> 0 | L63: =G63-J63+K63 -> 3740191.3 | R63: 62 | S63: =W62 -> 769128.98 | T63: =(S63*$P$3)/12 -> 7691.2898 | U63: =-IF('Cash Flow Summary'!$I$24="No",0,IF(AND('Cash Flow Summary'!$D$24="Yes",HLOOKUP($R63,'Monthly Cash Flow'!$D$6:$CP$68,61,FALSE)>0),HLOOKUP($R63,'Monthly Cash Flow'!$D$6:$CP$68,61,FALSE),IF('Cash Flow Summary'!$I$24="Current Pay",('Loan Summary'!S63*'Loan Summary'!$P$3)/12,0))) -> 0 | V63: =IF('Loan Summary'!R63=Assumptions!$AD$3,Assumptions!$AD$25,0) -> 0 | W63: =S63+T63+U63+V63 -> 776820.27
F64: 63 | G64: =IF(F64<$C$16,L63,IF(F64=$C$16,$C$9,L63)) -> 3740191.3 | H64: =IF(F64<$C$16,IF(F64>$C$6,-PMT(($C$3/12),$C$4,$C$2),I64),-PMT($C$10/12,$C$11,$C$9)) -> 21236.395 | I64: =IF(F64<$C$16,G64*($C$3/12),G64*($C$10/12)) -> 17142.543 | J64: =IF(F64<$C$16,IF(F64<=$C$6,0,H64-I64),IF(F64<=$C$16+$C$13,0,H64-I64)) -> 0 | K64: =IF('Monthly Cash Flow'!$C$88="Lender Draw",HLOOKUP(F64,'Monthly Cash Flow'!$D$79:$CP$88,10),0) -> 0 | L64: =G64-J64+K64 -> 3740191.3 | R64: 63 | S64: =W63 -> 776820.27 | T64: =(S64*$P$3)/12 -> 7768.2027 | U64: =-IF('Cash Flow Summary'!$I$24="No",0,IF(AND('Cash Flow Summary'!$D$24="Yes",HLOOKUP($R64,'Monthly Cash Flow'!$D$6:$CP$68,61,FALSE)>0),HLOOKUP($R64,'Monthly Cash Flow'!$D$6:$CP$68,61,FALSE),IF('Cash Flow Summary'!$I$24="Current Pay",('Loan Summary'!S64*'Loan Summary'!$P$3)/12,0))) -> 0 | V64: =IF('Loan Summary'!R64=Assumptions!$AD$3,Assumptions!$AD$25,0) -> 0 | W64: =S64+T64+U64+V64 -> 784588.47
F65: 64 | G65: =IF(F65<$C$16,L64,IF(F65=$C$16,$C$9,L64)) -> 3740191.3 | H65: =IF(F65<$C$16,IF(F65>$C$6,-PMT(($C$3/12),$C$4,$C$2),I65),-PMT($C$10/12,$C$11,$C$9)) -> 21236.395 | I65: =IF(F65<$C$16,G65*($C$3/12),G65*($C$10/12)) -> 17142.543 | J65: =IF(F65<$C$16,IF(F65<=$C$6,0,H65-I65),IF(F65<=$C$16+$C$13,0,H65-I65)) -> 0 | K65: =IF('Monthly Cash Flow'!$C$88="Lender Draw",HLOOKUP(F65,'Monthly Cash Flow'!$D$79:$CP$88,10),0) -> 0 | L65: =G65-J65+K65 -> 3740191.3 | R65: 64 | S65: =W64 -> 784588.47 | T65: =(S65*$P$3)/12 -> 7845.8847 | U65: =-IF('Cash Flow Summary'!$I$24="No",0,IF(AND('Cash Flow Summary'!$D$24="Yes",HLOOKUP($R65,'Monthly Cash Flow'!$D$6:$CP$68,61,FALSE)>0),HLOOKUP($R65,'Monthly Cash Flow'!$D$6:$CP$68,61,FALSE),IF('Cash Flow Summary'!$I$24="Current Pay",('Loan Summary'!S65*'Loan Summary'!$P$3)/12,0))) -> 0 | V65: =IF('Loan Summary'!R65=Assumptions!$AD$3,Assumptions!$AD$25,0) -> 0 | W65: =S65+T65+U65+V65 -> 792434.35
F66: 65 | G66: =IF(F66<$C$16,L65,IF(F66=$C$16,$C$9,L65)) -> 3740191.3 | H66: =IF(F66<$C$16,IF(F66>$C$6,-PMT(($C$3/12),$C$4,$C$2),I66),-PMT($C$10/12,$C$11,$C$9)) -> 21236.395 | I66: =IF(F66<$C$16,G66*($C$3/12),G66*($C$10/12)) -> 17142.543 | J66: =IF(F66<$C$16,IF(F66<=$C$6,0,H66-I66),IF(F66<=$C$16+$C$13,0,H66-I66)) -> 0 | K66: =IF('Monthly Cash Flow'!$C$88="Lender Draw",HLOOKUP(F66,'Monthly Cash Flow'!$D$79:$CP$88,10),0) -> 0 | L66: =G66-J66+K66 -> 3740191.3 | R66: 65 | S66: =W65 -> 792434.35 | T66: =(S66*$P$3)/12 -> 7924.3435 | U66: =-IF('Cash Flow Summary'!$I$24="No",0,IF(AND('Cash Flow Summary'!$D$24="Yes",HLOOKUP($R66,'Monthly Cash Flow'!$D$6:$CP$68,61,FALSE)>0),HLOOKUP($R66,'Monthly Cash Flow'!$D$6:$CP$68,61,FALSE),IF('Cash Flow Summary'!$I$24="Current Pay",('Loan Summary'!S66*'Loan Summary'!$P$3)/12,0))) -> 0 | V66: =IF('Loan Summary'!R66=Assumptions!$AD$3,Assumptions!$AD$25,0) -> 0 | W66: =S66+T66+U66+V66 -> 800358.7
F67: 66 | G67: =IF(F67<$C$16,L66,IF(F67=$C$16,$C$9,L66)) -> 3740191.3 | H67: =IF(F67<$C$16,IF(F67>$C$6,-PMT(($C$3/12),$C$4,$C$2),I67),-PMT($C$10/12,$C$11,$C$9)) -> 21236.395 | I67: =IF(F67<$C$16,G67*($C$3/12),G67*($C$10/12)) -> 17142.543 | J67: =IF(F67<$C$16,IF(F67<=$C$6,0,H67-I67),IF(F67<=$C$16+$C$13,0,H67-I67)) -> 0 | K67: =IF('Monthly Cash Flow'!$C$88="Lender Draw",HLOOKUP(F67,'Monthly Cash Flow'!$D$79:$CP$88,10),0) -> 0 | L67: =G67-J67+K67 -> 3740191.3 | R67: 66 | S67: =W66 -> 800358.7 | T67: =(S67*$P$3)/12 -> 8003.587 | U67: =-IF('Cash Flow Summary'!$I$24="No",0,IF(AND('Cash Flow Summary'!$D$24="Yes",HLOOKUP($R67,'Monthly Cash Flow'!$D$6:$CP$68,61,FALSE)>0),HLOOKUP($R67,'Monthly Cash Flow'!$D$6:$CP$68,61,FALSE),IF('Cash Flow Summary'!$I$24="Current Pay",('Loan Summary'!S67*'Loan Summary'!$P$3)/12,0))) -> 0 | V67: =IF('Loan Summary'!R67=Assumptions!$AD$3,Assumptions!$AD$25,0) -> 0 | W67: =S67+T67+U67+V67 -> 808362.28
F68: 67 | G68: =IF(F68<$C$16,L67,IF(F68=$C$16,$C$9,L67)) -> 3740191.3 | H68: =IF(F68<$C$16,IF(F68>$C$6,-PMT(($C$3/12),$C$4,$C$2),I68),-PMT($C$10/12,$C$11,$C$9)) -> 21236.395 | I68: =IF(F68<$C$16,G68*($C$3/12),G68*($C$10/12)) -> 17142.543 | J68: =IF(F68<$C$16,IF(F68<=$C$6,0,H68-I68),IF(F68<=$C$16+$C$13,0,H68-I68)) -> 0 | K68: =IF('Monthly Cash Flow'!$C$88="Lender Draw",HLOOKUP(F68,'Monthly Cash Flow'!$D$79:$CP$88,10),0) -> 0 | L68: =G68-J68+K68 -> 3740191.3 | R68: 67 | S68: =W67 -> 808362.28 | T68: =(S68*$P$3)/12 -> 8083.6228 | U68: =-IF('Cash Flow Summary'!$I$24="No",0,IF(AND('Cash Flow Summary'!$D$24="Yes",HLOOKUP($R68,'Monthly Cash Flow'!$D$6:$CP$68,61,FALSE)>0),HLOOKUP($R68,'Monthly Cash Flow'!$D$6:$CP$68,61,FALSE),IF('Cash Flow Summary'!$I$24="Current Pay",('Loan Summary'!S68*'Loan Summary'!$P$3)/12,0))) -> 0 | V68: =IF('Loan Summary'!R68=Assumptions!$AD$3,Assumptions!$AD$25,0) -> 0 | W68: =S68+T68+U68+V68 -> 816445.91
F69: 68 | G69: =IF(F69<$C$16,L68,IF(F69=$C$16,$C$9,L68)) -> 3740191.3 | H69: =IF(F69<$C$16,IF(F69>$C$6,-PMT(($C$3/12),$C$4,$C$2),I69),-PMT($C$10/12,$C$11,$C$9)) -> 21236.395 | I69: =IF(F69<$C$16,G69*($C$3/12),G69*($C$10/12)) -> 17142.543 | J69: =IF(F69<$C$16,IF(F69<=$C$6,0,H69-I69),IF(F69<=$C$16+$C$13,0,H69-I69)) -> 0 | K69: =IF('Monthly Cash Flow'!$C$88="Lender Draw",HLOOKUP(F69,'Monthly Cash Flow'!$D$79:$CP$88,10),0) -> 0 | L69: =G69-J69+K69 -> 3740191.3 | R69: 68 | S69: =W68 -> 816445.91 | T69: =(S69*$P$3)/12 -> 8164.4591 | U69: =-IF('Cash Flow Summary'!$I$24="No",0,IF(AND('Cash Flow Summary'!$D$24="Yes",HLOOKUP($R69,'Monthly Cash Flow'!$D$6:$CP$68,61,FALSE)>0),HLOOKUP($R69,'Monthly Cash Flow'!$D$6:$CP$68,61,FALSE),IF('Cash Flow Summary'!$I$24="Current Pay",('Loan Summary'!S69*'Loan Summary'!$P$3)/12,0))) -> 0 | V69: =IF('Loan Summary'!R69=Assumptions!$AD$3,Assumptions!$AD$25,0) -> 0 | W69: =S69+T69+U69+V69 -> 824610.37
F70: 69 | G70: =IF(F70<$C$16,L69,IF(F70=$C$16,$C$9,L69)) -> 3740191.3 | H70: =IF(F70<$C$16,IF(F70>$C$6,-PMT(($C$3/12),$C$4,$C$2),I70),-PMT($C$10/12,$C$11,$C$9)) -> 21236.395 | I70: =IF(F70<$C$16,G70*($C$3/12),G70*($C$10/12)) -> 17142.543 | J70: =IF(F70<$C$16,IF(F70<=$C$6,0,H70-I70),IF(F70<=$C$16+$C$13,0,H70-I70)) -> 0 | K70: =IF('Monthly Cash Flow'!$C$88="Lender Draw",HLOOKUP(F70,'Monthly Cash Flow'!$D$79:$CP$88,10),0) -> 0 | L70: =G70-J70+K70 -> 3740191.3 | R70: 69 | S70: =W69 -> 824610.37 | T70: =(S70*$P$3)/12 -> 8246.1037 | U70: =-IF('Cash Flow Summary'!$I$24="No",0,IF(AND('Cash Flow Summary'!$D$24="Yes",HLOOKUP($R70,'Monthly Cash Flow'!$D$6:$CP$68,61,FALSE)>0),HLOOKUP($R70,'Monthly Cash Flow'!$D$6:$CP$68,61,FALSE),IF('Cash Flow Summary'!$I$24="Current Pay",('Loan Summary'!S70*'Loan Summary'!$P$3)/12,0))) -> 0 | V70: =IF('Loan Summary'!R70=Assumptions!$AD$3,Assumptions!$AD$25,0) -> 0 | W70: =S70+T70+U70+V70 -> 832856.47
F71: 70 | G71: =IF(F71<$C$16,L70,IF(F71=$C$16,$C$9,L70)) -> 3740191.3 | H71: =IF(F71<$C$16,IF(F71>$C$6,-PMT(($C$3/12),$C$4,$C$2),I71),-PMT($C$10/12,$C$11,$C$9)) -> 21236.395 | I71: =IF(F71<$C$16,G71*($C$3/12),G71*($C$10/12)) -> 17142.543 | J71: =IF(F71<$C$16,IF(F71<=$C$6,0,H71-I71),IF(F71<=$C$16+$C$13,0,H71-I71)) -> 0 | K71: =IF('Monthly Cash Flow'!$C$88="Lender Draw",HLOOKUP(F71,'Monthly Cash Flow'!$D$79:$CP$88,10),0) -> 0 | L71: =G71-J71+K71 -> 3740191.3 | R71: 70 | S71: =W70 -> 832856.47 | T71: =(S71*$P$3)/12 -> 8328.5647 | U71: =-IF('Cash Flow Summary'!$I$24="No",0,IF(AND('Cash Flow Summary'!$D$24="Yes",HLOOKUP($R71,'Monthly Cash Flow'!$D$6:$CP$68,61,FALSE)>0),HLOOKUP($R71,'Monthly Cash Flow'!$D$6:$CP$68,61,FALSE),IF('Cash Flow Summary'!$I$24="Current Pay",('Loan Summary'!S71*'Loan Summary'!$P$3)/12,0))) -> 0 | V71: =IF('Loan Summary'!R71=Assumptions!$AD$3,Assumptions!$AD$25,0) -> 0 | W71: =S71+T71+U71+V71 -> 841185.03
F72: 71 | G72: =IF(F72<$C$16,L71,IF(F72=$C$16,$C$9,L71)) -> 3740191.3 | H72: =IF(F72<$C$16,IF(F72>$C$6,-PMT(($C$3/12),$C$4,$C$2),I72),-PMT($C$10/12,$C$11,$C$9)) -> 21236.395 | I72: =IF(F72<$C$16,G72*($C$3/12),G72*($C$10/12)) -> 17142.543 | J72: =IF(F72<$C$16,IF(F72<=$C$6,0,H72-I72),IF(F72<=$C$16+$C$13,0,H72-I72)) -> 0 | K72: =IF('Monthly Cash Flow'!$C$88="Lender Draw",HLOOKUP(F72,'Monthly Cash Flow'!$D$79:$CP$88,10),0) -> 0 | L72: =G72-J72+K72 -> 3740191.3 | R72: 71 | S72: =W71 -> 841185.03 | T72: =(S72*$P$3)/12 -> 8411.8503 | U72: =-IF('Cash Flow Summary'!$I$24="No",0,IF(AND('Cash Flow Summary'!$D$24="Yes",HLOOKUP($R72,'Monthly Cash Flow'!$D$6:$CP$68,61,FALSE)>0),HLOOKUP($R72,'Monthly Cash Flow'!$D$6:$CP$68,61,FALSE),IF('Cash Flow Summary'!$I$24="Current Pay",('Loan Summary'!S72*'Loan Summary'!$P$3)/12,0))) -> 0 | V72: =IF('Loan Summary'!R72=Assumptions!$AD$3,Assumptions!$AD$25,0) -> 0 | W72: =S72+T72+U72+V72 -> 849596.89
F73: 72 | G73: =IF(F73<$C$16,L72,IF(F73=$C$16,$C$9,L72)) -> 3740191.3 | H73: =IF(F73<$C$16,IF(F73>$C$6,-PMT(($C$3/12),$C$4,$C$2),I73),-PMT($C$10/12,$C$11,$C$9)) -> 21236.395 | I73: =IF(F73<$C$16,G73*($C$3/12),G73*($C$10/12)) -> 17142.543 | J73: =IF(F73<$C$16,IF(F73<=$C$6,0,H73-I73),IF(F73<=$C$16+$C$13,0,H73-I73)) -> 0 | K73: =IF('Monthly Cash Flow'!$C$88="Lender Draw",HLOOKUP(F73,'Monthly Cash Flow'!$D$79:$CP$88,10),0) -> 0 | L73: =G73-J73+K73 -> 3740191.3 | R73: 72 | S73: =W72 -> 849596.89 | T73: =(S73*$P$3)/12 -> 8495.9689 | U73: =-IF('Cash Flow Summary'!$I$24="No",0,IF(AND('Cash Flow Summary'!$D$24="Yes",HLOOKUP($R73,'Monthly Cash Flow'!$D$6:$CP$68,61,FALSE)>0),HLOOKUP($R73,'Monthly Cash Flow'!$D$6:$CP$68,61,FALSE),IF('Cash Flow Summary'!$I$24="Current Pay",('Loan Summary'!S73*'Loan Summary'!$P$3)/12,0))) -> 0 | V73: =IF('Loan Summary'!R73=Assumptions!$AD$3,Assumptions!$AD$25,0) -> 0 | W73: =S73+T73+U73+V73 -> 858092.85
F74: 73 | G74: =IF(F74<$C$16,L73,IF(F74=$C$16,$C$9,L73)) -> 3740191.3 | H74: =IF(F74<$C$16,IF(F74>$C$6,-PMT(($C$3/12),$C$4,$C$2),I74),-PMT($C$10/12,$C$11,$C$9)) -> 21236.395 | I74: =IF(F74<$C$16,G74*($C$3/12),G74*($C$10/12)) -> 17142.543 | J74: =IF(F74<$C$16,IF(F74<=$C$6,0,H74-I74),IF(F74<=$C$16+$C$13,0,H74-I74)) -> 0 | K74: =IF('Monthly Cash Flow'!$C$88="Lender Draw",HLOOKUP(F74,'Monthly Cash Flow'!$D$79:$CP$88,10),0) -> 0 | L74: =G74-J74+K74 -> 3740191.3 | R74: 73 | S74: =W73 -> 858092.85 | T74: =(S74*$P$3)/12 -> 8580.9285 | U74: =-IF('Cash Flow Summary'!$J$24="No",0,IF(AND('Cash Flow Summary'!$D$24="Yes",HLOOKUP($R74,'Monthly Cash Flow'!$D$6:$CP$68,61,FALSE)>0),HLOOKUP($R74,'Monthly Cash Flow'!$D$6:$CP$68,61,FALSE),IF('Cash Flow Summary'!$J$24="Current Pay",('Loan Summary'!S74*'Loan Summary'!$P$3)/12,0))) -> 0 | V74: =IF('Loan Summary'!R74=Assumptions!$AD$3,Assumptions!$AD$25,0) -> 0 | W74: =S74+T74+U74+V74 -> 866673.78
F75: 74 | G75: =IF(F75<$C$16,L74,IF(F75=$C$16,$C$9,L74)) -> 3740191.3 | H75: =IF(F75<$C$16,IF(F75>$C$6,-PMT(($C$3/12),$C$4,$C$2),I75),-PMT($C$10/12,$C$11,$C$9)) -> 21236.395 | I75: =IF(F75<$C$16,G75*($C$3/12),G75*($C$10/12)) -> 17142.543 | J75: =IF(F75<$C$16,IF(F75<=$C$6,0,H75-I75),IF(F75<=$C$16+$C$13,0,H75-I75)) -> 0 | K75: =IF('Monthly Cash Flow'!$C$88="Lender Draw",HLOOKUP(F75,'Monthly Cash Flow'!$D$79:$CP$88,10),0) -> 0 | L75: =G75-J75+K75 -> 3740191.3 | R75: 74 | S75: =W74 -> 866673.78 | T75: =(S75*$P$3)/12 -> 8666.7378 | U75: =-IF('Cash Flow Summary'!$J$24="No",0,IF(AND('Cash Flow Summary'!$D$24="Yes",HLOOKUP($R75,'Monthly Cash Flow'!$D$6:$CP$68,61,FALSE)>0),HLOOKUP($R75,'Monthly Cash Flow'!$D$6:$CP$68,61,FALSE),IF('Cash Flow Summary'!$J$24="Current Pay",('Loan Summary'!S75*'Loan Summary'!$P$3)/12,0))) -> 0 | V75: =IF('Loan Summary'!R75=Assumptions!$AD$3,Assumptions!$AD$25,0) -> 0 | W75: =S75+T75+U75+V75 -> 875340.52
F76: 75 | G76: =IF(F76<$C$16,L75,IF(F76=$C$16,$C$9,L75)) -> 3740191.3 | H76: =IF(F76<$C$16,IF(F76>$C$6,-PMT(($C$3/12),$C$4,$C$2),I76),-PMT($C$10/12,$C$11,$C$9)) -> 21236.395 | I76: =IF(F76<$C$16,G76*($C$3/12),G76*($C$10/12)) -> 17142.543 | J76: =IF(F76<$C$16,IF(F76<=$C$6,0,H76-I76),IF(F76<=$C$16+$C$13,0,H76-I76)) -> 0 | K76: =IF('Monthly Cash Flow'!$C$88="Lender Draw",HLOOKUP(F76,'Monthly Cash Flow'!$D$79:$CP$88,10),0) -> 0 | L76: =G76-J76+K76 -> 3740191.3 | R76: 75 | S76: =W75 -> 875340.52 | T76: =(S76*$P$3)/12 -> 8753.4052 | U76: =-IF('Cash Flow Summary'!$J$24="No",0,IF(AND('Cash Flow Summary'!$D$24="Yes",HLOOKUP($R76,'Monthly Cash Flow'!$D$6:$CP$68,61,FALSE)>0),HLOOKUP($R76,'Monthly Cash Flow'!$D$6:$CP$68,61,FALSE),IF('Cash Flow Summary'!$J$24="Current Pay",('Loan Summary'!S76*'Loan Summary'!$P$3)/12,0))) -> 0 | V76: =IF('Loan Summary'!R76=Assumptions!$AD$3,Assumptions!$AD$25,0) -> 0 | W76: =S76+T76+U76+V76 -> 884093.93
F77: 76 | G77: =IF(F77<$C$16,L76,IF(F77=$C$16,$C$9,L76)) -> 3740191.3 | H77: =IF(F77<$C$16,IF(F77>$C$6,-PMT(($C$3/12),$C$4,$C$2),I77),-PMT($C$10/12,$C$11,$C$9)) -> 21236.395 | I77: =IF(F77<$C$16,G77*($C$3/12),G77*($C$10/12)) -> 17142.543 | J77: =IF(F77<$C$16,IF(F77<=$C$6,0,H77-I77),IF(F77<=$C$16+$C$13,0,H77-I77)) -> 0 | K77: =IF('Monthly Cash Flow'!$C$88="Lender Draw",HLOOKUP(F77,'Monthly Cash Flow'!$D$79:$CP$88,10),0) -> 0 | L77: =G77-J77+K77 -> 3740191.3 | R77: 76 | S77: =W76 -> 884093.93 | T77: =(S77*$P$3)/12 -> 8840.9393 | U77: =-IF('Cash Flow Summary'!$J$24="No",0,IF(AND('Cash Flow Summary'!$D$24="Yes",HLOOKUP($R77,'Monthly Cash Flow'!$D$6:$CP$68,61,FALSE)>0),HLOOKUP($R77,'Monthly Cash Flow'!$D$6:$CP$68,61,FALSE),IF('Cash Flow Summary'!$J$24="Current Pay",('Loan Summary'!S77*'Loan Summary'!$P$3)/12,0))) -> 0 | V77: =IF('Loan Summary'!R77=Assumptions!$AD$3,Assumptions!$AD$25,0) -> 0 | W77: =S77+T77+U77+V77 -> 892934.86
F78: 77 | G78: =IF(F78<$C$16,L77,IF(F78=$C$16,$C$9,L77)) -> 3740191.3 | H78: =IF(F78<$C$16,IF(F78>$C$6,-PMT(($C$3/12),$C$4,$C$2),I78),-PMT($C$10/12,$C$11,$C$9)) -> 21236.395 | I78: =IF(F78<$C$16,G78*($C$3/12),G78*($C$10/12)) -> 17142.543 | J78: =IF(F78<$C$16,IF(F78<=$C$6,0,H78-I78),IF(F78<=$C$16+$C$13,0,H78-I78)) -> 0 | K78: =IF('Monthly Cash Flow'!$C$88="Lender Draw",HLOOKUP(F78,'Monthly Cash Flow'!$D$79:$CP$88,10),0) -> 0 | L78: =G78-J78+K78 -> 3740191.3 | R78: 77 | S78: =W77 -> 892934.86 | T78: =(S78*$P$3)/12 -> 8929.3486 | U78: =-IF('Cash Flow Summary'!$J$24="No",0,IF(AND('Cash Flow Summary'!$D$24="Yes",HLOOKUP($R78,'Monthly Cash Flow'!$D$6:$CP$68,61,FALSE)>0),HLOOKUP($R78,'Monthly Cash Flow'!$D$6:$CP$68,61,FALSE),IF('Cash Flow Summary'!$J$24="Current Pay",('Loan Summary'!S78*'Loan Summary'!$P$3)/12,0))) -> 0 | V78: =IF('Loan Summary'!R78=Assumptions!$AD$3,Assumptions!$AD$25,0) -> 0 | W78: =S78+T78+U78+V78 -> 901864.21
F79: 78 | G79: =IF(F79<$C$16,L78,IF(F79=$C$16,$C$9,L78)) -> 3740191.3 | H79: =IF(F79<$C$16,IF(F79>$C$6,-PMT(($C$3/12),$C$4,$C$2),I79),-PMT($C$10/12,$C$11,$C$9)) -> 21236.395 | I79: =IF(F79<$C$16,G79*($C$3/12),G79*($C$10/12)) -> 17142.543 | J79: =IF(F79<$C$16,IF(F79<=$C$6,0,H79-I79),IF(F79<=$C$16+$C$13,0,H79-I79)) -> 0 | K79: =IF('Monthly Cash Flow'!$C$88="Lender Draw",HLOOKUP(F79,'Monthly Cash Flow'!$D$79:$CP$88,10),0) -> 0 | L79: =G79-J79+K79 -> 3740191.3 | R79: 78 | S79: =W78 -> 901864.21 | T79: =(S79*$P$3)/12 -> 9018.6421 | U79: =-IF('Cash Flow Summary'!$J$24="No",0,IF(AND('Cash Flow Summary'!$D$24="Yes",HLOOKUP($R79,'Monthly Cash Flow'!$D$6:$CP$68,61,FALSE)>0),HLOOKUP($R79,'Monthly Cash Flow'!$D$6:$CP$68,61,FALSE),IF('Cash Flow Summary'!$J$24="Current Pay",('Loan Summary'!S79*'Loan Summary'!$P$3)/12,0))) -> 0 | V79: =IF('Loan Summary'!R79=Assumptions!$AD$3,Assumptions!$AD$25,0) -> 0 | W79: =S79+T79+U79+V79 -> 910882.86
F80: 79 | G80: =IF(F80<$C$16,L79,IF(F80=$C$16,$C$9,L79)) -> 3740191.3 | H80: =IF(F80<$C$16,IF(F80>$C$6,-PMT(($C$3/12),$C$4,$C$2),I80),-PMT($C$10/12,$C$11,$C$9)) -> 21236.395 | I80: =IF(F80<$C$16,G80*($C$3/12),G80*($C$10/12)) -> 17142.543 | J80: =IF(F80<$C$16,IF(F80<=$C$6,0,H80-I80),IF(F80<=$C$16+$C$13,0,H80-I80)) -> 0 | K80: =IF('Monthly Cash Flow'!$C$88="Lender Draw",HLOOKUP(F80,'Monthly Cash Flow'!$D$79:$CP$88,10),0) -> 0 | L80: =G80-J80+K80 -> 3740191.3 | R80: 79 | S80: =W79 -> 910882.86 | T80: =(S80*$P$3)/12 -> 9108.8286 | U80: =-IF('Cash Flow Summary'!$J$24="No",0,IF(AND('Cash Flow Summary'!$D$24="Yes",HLOOKUP($R80,'Monthly Cash Flow'!$D$6:$CP$68,61,FALSE)>0),HLOOKUP($R80,'Monthly Cash Flow'!$D$6:$CP$68,61,FALSE),IF('Cash Flow Summary'!$J$24="Current Pay",('Loan Summary'!S80*'Loan Summary'!$P$3)/12,0))) -> 0 | V80: =IF('Loan Summary'!R80=Assumptions!$AD$3,Assumptions!$AD$25,0) -> 0 | W80: =S80+T80+U80+V80 -> 919991.68
F81: 80 | G81: =IF(F81<$C$16,L80,IF(F81=$C$16,$C$9,L80)) -> 3740191.3 | H81: =IF(F81<$C$16,IF(F81>$C$6,-PMT(($C$3/12),$C$4,$C$2),I81),-PMT($C$10/12,$C$11,$C$9)) -> 21236.395 | I81: =IF(F81<$C$16,G81*($C$3/12),G81*($C$10/12)) -> 17142.543 | J81: =IF(F81<$C$16,IF(F81<=$C$6,0,H81-I81),IF(F81<=$C$16+$C$13,0,H81-I81)) -> 0 | K81: =IF('Monthly Cash Flow'!$C$88="Lender Draw",HLOOKUP(F81,'Monthly Cash Flow'!$D$79:$CP$88,10),0) -> 0 | L81: =G81-J81+K81 -> 3740191.3 | R81: 80 | S81: =W80 -> 919991.68 | T81: =(S81*$P$3)/12 -> 9199.9168 | U81: =-IF('Cash Flow Summary'!$J$24="No",0,IF(AND('Cash Flow Summary'!$D$24="Yes",HLOOKUP($R81,'Monthly Cash Flow'!$D$6:$CP$68,61,FALSE)>0),HLOOKUP($R81,'Monthly Cash Flow'!$D$6:$CP$68,61,FALSE),IF('Cash Flow Summary'!$J$24="Current Pay",('Loan Summary'!S81*'Loan Summary'!$P$3)/12,0))) -> 0 | V81: =IF('Loan Summary'!R81=Assumptions!$AD$3,Assumptions!$AD$25,0) -> 0 | W81: =S81+T81+U81+V81 -> 929191.6
F82: 81 | G82: =IF(F82<$C$16,L81,IF(F82=$C$16,$C$9,L81)) -> 3740191.3 | H82: =IF(F82<$C$16,IF(F82>$C$6,-PMT(($C$3/12),$C$4,$C$2),I82),-PMT($C$10/12,$C$11,$C$9)) -> 21236.395 | I82: =IF(F82<$C$16,G82*($C$3/12),G82*($C$10/12)) -> 17142.543 | J82: =IF(F82<$C$16,IF(F82<=$C$6,0,H82-I82),IF(F82<=$C$16+$C$13,0,H82-I82)) -> 0 | K82: =IF('Monthly Cash Flow'!$C$88="Lender Draw",HLOOKUP(F82,'Monthly Cash Flow'!$D$79:$CP$88,10),0) -> 0 | L82: =G82-J82+K82 -> 3740191.3 | R82: 81 | S82: =W81 -> 929191.6 | T82: =(S82*$P$3)/12 -> 9291.916 | U82: =-IF('Cash Flow Summary'!$J$24="No",0,IF(AND('Cash Flow Summary'!$D$24="Yes",HLOOKUP($R82,'Monthly Cash Flow'!$D$6:$CP$68,61,FALSE)>0),HLOOKUP($R82,'Monthly Cash Flow'!$D$6:$CP$68,61,FALSE),IF('Cash Flow Summary'!$J$24="Current Pay",('Loan Summary'!S82*'Loan Summary'!$P$3)/12,0))) -> 0 | V82: =IF('Loan Summary'!R82=Assumptions!$AD$3,Assumptions!$AD$25,0) -> 0 | W82: =S82+T82+U82+V82 -> 938483.52
F83: 82 | G83: =IF(F83<$C$16,L82,IF(F83=$C$16,$C$9,L82)) -> 3740191.3 | H83: =IF(F83<$C$16,IF(F83>$C$6,-PMT(($C$3/12),$C$4,$C$2),I83),-PMT($C$10/12,$C$11,$C$9)) -> 21236.395 | I83: =IF(F83<$C$16,G83*($C$3/12),G83*($C$10/12)) -> 17142.543 | J83: =IF(F83<$C$16,IF(F83<=$C$6,0,H83-I83),IF(F83<=$C$16+$C$13,0,H83-I83)) -> 0 | K83: =IF('Monthly Cash Flow'!$C$88="Lender Draw",HLOOKUP(F83,'Monthly Cash Flow'!$D$79:$CP$88,10),0) -> 0 | L83: =G83-J83+K83 -> 3740191.3 | R83: 82 | S83: =W82 -> 938483.52 | T83: =(S83*$P$3)/12 -> 9384.8352 | U83: =-IF('Cash Flow Summary'!$J$24="No",0,IF(AND('Cash Flow Summary'!$D$24="Yes",HLOOKUP($R83,'Monthly Cash Flow'!$D$6:$CP$68,61,FALSE)>0),HLOOKUP($R83,'Monthly Cash Flow'!$D$6:$CP$68,61,FALSE),IF('Cash Flow Summary'!$J$24="Current Pay",('Loan Summary'!S83*'Loan Summary'!$P$3)/12,0))) -> 0 | V83: =IF('Loan Summary'!R83=Assumptions!$AD$3,Assumptions!$AD$25,0) -> 0 | W83: =S83+T83+U83+V83 -> 947868.35
F84: 83 | G84: =IF(F84<$C$16,L83,IF(F84=$C$16,$C$9,L83)) -> 3740191.3 | H84: =IF(F84<$C$16,IF(F84>$C$6,-PMT(($C$3/12),$C$4,$C$2),I84),-PMT($C$10/12,$C$11,$C$9)) -> 21236.395 | I84: =IF(F84<$C$16,G84*($C$3/12),G84*($C$10/12)) -> 17142.543 | J84: =IF(F84<$C$16,IF(F84<=$C$6,0,H84-I84),IF(F84<=$C$16+$C$13,0,H84-I84)) -> 0 | K84: =IF('Monthly Cash Flow'!$C$88="Lender Draw",HLOOKUP(F84,'Monthly Cash Flow'!$D$79:$CP$88,10),0) -> 0 | L84: =G84-J84+K84 -> 3740191.3 | R84: 83 | S84: =W83 -> 947868.35 | T84: =(S84*$P$3)/12 -> 9478.6835 | U84: =-IF('Cash Flow Summary'!$J$24="No",0,IF(AND('Cash Flow Summary'!$D$24="Yes",HLOOKUP($R84,'Monthly Cash Flow'!$D$6:$CP$68,61,FALSE)>0),HLOOKUP($R84,'Monthly Cash Flow'!$D$6:$CP$68,61,FALSE),IF('Cash Flow Summary'!$J$24="Current Pay",('Loan Summary'!S84*'Loan Summary'!$P$3)/12,0))) -> 0 | V84: =IF('Loan Summary'!R84=Assumptions!$AD$3,Assumptions!$AD$25,0) -> 0 | W84: =S84+T84+U84+V84 -> 957347.04
F85: 84 | G85: =IF(F85<$C$16,L84,IF(F85=$C$16,$C$9,L84)) -> 3740191.3 | H85: =IF(F85<$C$16,IF(F85>$C$6,-PMT(($C$3/12),$C$4,$C$2),I85),-PMT($C$10/12,$C$11,$C$9)) -> 21236.395 | I85: =IF(F85<$C$16,G85*($C$3/12),G85*($C$10/12)) -> 17142.543 | J85: =IF(F85<$C$16,IF(F85<=$C$6,0,H85-I85),IF(F85<=$C$16+$C$13,0,H85-I85)) -> 0 | K85: =IF('Monthly Cash Flow'!$C$88="Lender Draw",HLOOKUP(F85,'Monthly Cash Flow'!$D$79:$CP$88,10),0) -> 0 | L85: =G85-J85+K85 -> 3740191.3 | R85: 84 | S85: =W84 -> 957347.04 | T85: =(S85*$P$3)/12 -> 9573.4704 | U85: =-IF('Cash Flow Summary'!$J$24="No",0,IF(AND('Cash Flow Summary'!$D$24="Yes",HLOOKUP($R85,'Monthly Cash Flow'!$D$6:$CP$68,61,FALSE)>0),HLOOKUP($R85,'Monthly Cash Flow'!$D$6:$CP$68,61,FALSE),IF('Cash Flow Summary'!$J$24="Current Pay",('Loan Summary'!S85*'Loan Summary'!$P$3)/12,0))) -> 0 | V85: =IF('Loan Summary'!R85=Assumptions!$AD$3,Assumptions!$AD$25,0) -> 0 | W85: =S85+T85+U85+V85 -> 966920.51
F86: 85 | G86: =IF(F86<$C$16,L85,IF(F86=$C$16,$C$9,L85)) -> 3740191.3 | H86: =IF(F86<$C$16,IF(F86>$C$6,-PMT(($C$3/12),$C$4,$C$2),I86),-PMT($C$10/12,$C$11,$C$9)) -> 21236.395 | I86: =IF(F86<$C$16,G86*($C$3/12),G86*($C$10/12)) -> 17142.543 | J86: =IF(F86<$C$16,IF(F86<=$C$6,0,H86-I86),IF(F86<=$C$16+$C$13,0,H86-I86)) -> 0 | K86: =IF('Monthly Cash Flow'!$C$88="Lender Draw",HLOOKUP(F86,'Monthly Cash Flow'!$D$79:$CP$88,10),0) -> 0 | L86: =G86-J86+K86 -> 3740191.3 | R86: 85 | S86: =W85 -> 966920.51 | T86: =(S86*$P$3)/12 -> 9669.2051 | U86: =-IF(AND($P$5="No",HLOOKUP('Loan Summary'!$R86,'Monthly Cash Flow'!$D$6:$CP$76,63,FALSE)>T86),T86,(HLOOKUP('Loan Summary'!$R86,'Monthly Cash Flow'!$D$6:$CP$76,63,FALSE))) -> #N/A | V86: =IF('Loan Summary'!R86=Assumptions!$AD$3,Assumptions!$AD$25,0) -> 0 | W86: =S86+T86+U86+V86 -> #N/A
F87: 86 | G87: =IF(F87<$C$16,L86,IF(F87=$C$16,$C$9,L86)) -> 3740191.3 | H87: =IF(F87<$C$16,IF(F87>$C$6,-PMT(($C$3/12),$C$4,$C$2),I87),-PMT($C$10/12,$C$11,$C$9)) -> 21236.395 | I87: =IF(F87<$C$16,G87*($C$3/12),G87*($C$10/12)) -> 17142.543 | J87: =IF(F87<$C$16,IF(F87<=$C$6,0,H87-I87),IF(F87<=$C$16+$C$13,0,H87-I87)) -> 0 | K87: =IF('Monthly Cash Flow'!$C$88="Lender Draw",HLOOKUP(F87,'Monthly Cash Flow'!$D$79:$CP$88,10),0) -> 0 | L87: =G87-J87+K87 -> 3740191.3 | R87: 86 | S87: =W86 -> #N/A | T87: =(S87*$P$3)/12 -> #N/A | U87: =-IF(AND($P$5="No",HLOOKUP('Loan Summary'!$R87,'Monthly Cash Flow'!$D$6:$CP$76,63,FALSE)>T87),T87,(HLOOKUP('Loan Summary'!$R87,'Monthly Cash Flow'!$D$6:$CP$76,63,FALSE))) -> #N/A | V87: =IF('Loan Summary'!R87=Assumptions!$AD$3,Assumptions!$AD$25,0) -> 0 | W87: =S87+T87+U87+V87 -> #N/A
F88: 87 | G88: =IF(F88<$C$16,L87,IF(F88=$C$16,$C$9,L87)) -> 3740191.3 | H88: =IF(F88<$C$16,IF(F88>$C$6,-PMT(($C$3/12),$C$4,$C$2),I88),-PMT($C$10/12,$C$11,$C$9)) -> 21236.395 | I88: =IF(F88<$C$16,G88*($C$3/12),G88*($C$10/12)) -> 17142.543 | J88: =IF(F88<$C$16,IF(F88<=$C$6,0,H88-I88),IF(F88<=$C$16+$C$13,0,H88-I88)) -> 0 | K88: =IF('Monthly Cash Flow'!$C$88="Lender Draw",HLOOKUP(F88,'Monthly Cash Flow'!$D$79:$CP$88,10),0) -> 0 | L88: =G88-J88+K88 -> 3740191.3 | R88: 87 | S88: =W87 -> #N/A | T88: =(S88*$P$3)/12 -> #N/A | U88: =-IF(AND($P$5="No",HLOOKUP('Loan Summary'!$R88,'Monthly Cash Flow'!$D$6:$CP$76,63,FALSE)>T88),T88,(HLOOKUP('Loan Summary'!$R88,'Monthly Cash Flow'!$D$6:$CP$76,63,FALSE))) -> #N/A | V88: =IF('Loan Summary'!R88=Assumptions!$AD$3,Assumptions!$AD$25,0) -> 0 | W88: =S88+T88+U88+V88 -> #N/A
F89: 88 | G89: =IF(F89<$C$16,L88,IF(F89=$C$16,$C$9,L88)) -> 3740191.3 | H89: =IF(F89<$C$16,IF(F89>$C$6,-PMT(($C$3/12),$C$4,$C$2),I89),-PMT($C$10/12,$C$11,$C$9)) -> 21236.395 | I89: =IF(F89<$C$16,G89*($C$3/12),G89*($C$10/12)) -> 17142.543 | J89: =IF(F89<$C$16,IF(F89<=$C$6,0,H89-I89),IF(F89<=$C$16+$C$13,0,H89-I89)) -> 0 | K89: =IF('Monthly Cash Flow'!$C$88="Lender Draw",HLOOKUP(F89,'Monthly Cash Flow'!$D$79:$CP$88,10),0) -> 0 | L89: =G89-J89+K89 -> 3740191.3 | R89: 88 | S89: =W88 -> #N/A | T89: =(S89*$P$3)/12 -> #N/A | U89: =-IF(AND($P$5="No",HLOOKUP('Loan Summary'!$R89,'Monthly Cash Flow'!$D$6:$CP$76,63,FALSE)>T89),T89,(HLOOKUP('Loan Summary'!$R89,'Monthly Cash Flow'!$D$6:$CP$76,63,FALSE))) -> #N/A | V89: =IF('Loan Summary'!R89=Assumptions!$AD$3,Assumptions!$AD$25,0) -> 0 | W89: =S89+T89+U89+V89 -> #N/A
F90: 89 | G90: =IF(F90<$C$16,L89,IF(F90=$C$16,$C$9,L89)) -> 3740191.3 | H90: =IF(F90<$C$16,IF(F90>$C$6,-PMT(($C$3/12),$C$4,$C$2),I90),-PMT($C$10/12,$C$11,$C$9)) -> 21236.395 | I90: =IF(F90<$C$16,G90*($C$3/12),G90*($C$10/12)) -> 17142.543 | J90: =IF(F90<$C$16,IF(F90<=$C$6,0,H90-I90),IF(F90<=$C$16+$C$13,0,H90-I90)) -> 0 | K90: =IF('Monthly Cash Flow'!$C$88="Lender Draw",HLOOKUP(F90,'Monthly Cash Flow'!$D$79:$CP$88,10),0) -> 0 | L90: =G90-J90+K90 -> 3740191.3 | R90: 89 | S90: =W89 -> #N/A | T90: =(S90*$P$3)/12 -> #N/A | U90: =-IF(AND($P$5="No",HLOOKUP('Loan Summary'!$R90,'Monthly Cash Flow'!$D$6:$CP$76,63,FALSE)>T90),T90,(HLOOKUP('Loan Summary'!$R90,'Monthly Cash Flow'!$D$6:$CP$76,63,FALSE))) -> #N/A | V90: =IF('Loan Summary'!R90=Assumptions!$AD$3,Assumptions!$AD$25,0) -> 0 | W90: =S90+T90+U90+V90 -> #N/A
F91: 90 | G91: =IF(F91<$C$16,L90,IF(F91=$C$16,$C$9,L90)) -> 3740191.3 | H91: =IF(F91<$C$16,IF(F91>$C$6,-PMT(($C$3/12),$C$4,$C$2),I91),-PMT($C$10/12,$C$11,$C$9)) -> 21236.395 | I91: =IF(F91<$C$16,G91*($C$3/12),G91*($C$10/12)) -> 17142.543 | J91: =IF(F91<$C$16,IF(F91<=$C$6,0,H91-I91),IF(F91<=$C$16+$C$13,0,H91-I91)) -> 0 | K91: =IF('Monthly Cash Flow'!$C$88="Lender Draw",HLOOKUP(F91,'Monthly Cash Flow'!$D$79:$CP$88,10),0) -> 0 | L91: =G91-J91+K91 -> 3740191.3 | R91: 90 | S91: =W90 -> #N/A | T91: =(S91*$P$3)/12 -> #N/A | U91: =-IF(AND($P$5="No",HLOOKUP('Loan Summary'!$R91,'Monthly Cash Flow'!$D$6:$CP$76,63,FALSE)>T91),T91,(HLOOKUP('Loan Summary'!$R91,'Monthly Cash Flow'!$D$6:$CP$76,63,FALSE))) -> #N/A | V91: =IF('Loan Summary'!R91=Assumptions!$AD$3,Assumptions!$AD$25,0) -> 0 | W91: =S91+T91+U91+V91 -> #N/A
F92: 91 | G92: =IF(F92<$C$16,L91,IF(F92=$C$16,$C$9,L91)) -> 3740191.3 | H92: =IF(F92<$C$16,IF(F92>$C$6,-PMT(($C$3/12),$C$4,$C$2),I92),-PMT($C$10/12,$C$11,$C$9)) -> 21236.395 | I92: =IF(F92<$C$16,G92*($C$3/12),G92*($C$10/12)) -> 17142.543 | J92: =IF(F92<$C$16,IF(F92<=$C$6,0,H92-I92),IF(F92<=$C$16+$C$13,0,H92-I92)) -> 0 | K92: =IF('Monthly Cash Flow'!$C$88="Lender Draw",HLOOKUP(F92,'Monthly Cash Flow'!$D$79:$CP$88,10),0) -> 0 | L92: =G92-J92+K92 -> 3740191.3 | R92: 91 | S92: =W91 -> #N/A | T92: =(S92*$P$3)/12 -> #N/A | U92: =-IF(AND($P$5="No",HLOOKUP('Loan Summary'!$R92,'Monthly Cash Flow'!$D$6:$CP$76,63,FALSE)>T92),T92,(HLOOKUP('Loan Summary'!$R92,'Monthly Cash Flow'!$D$6:$CP$76,63,FALSE))) -> #N/A | V92: =IF('Loan Summary'!R92=Assumptions!$AD$3,Assumptions!$AD$25,0) -> 0 | W92: =S92+T92+U92+V92 -> #N/A
F93: 92 | G93: =IF(F93<$C$16,L92,IF(F93=$C$16,$C$9,L92)) -> 3740191.3 | H93: =IF(F93<$C$16,IF(F93>$C$6,-PMT(($C$3/12),$C$4,$C$2),I93),-PMT($C$10/12,$C$11,$C$9)) -> 21236.395 | I93: =IF(F93<$C$16,G93*($C$3/12),G93*($C$10/12)) -> 17142.543 | J93: =IF(F93<$C$16,IF(F93<=$C$6,0,H93-I93),IF(F93<=$C$16+$C$13,0,H93-I93)) -> 0 | K93: =IF('Monthly Cash Flow'!$C$88="Lender Draw",HLOOKUP(F93,'Monthly Cash Flow'!$D$79:$CP$88,10),0) -> 0 | L93: =G93-J93+K93 -> 3740191.3 | R93: 92 | S93: =W92 -> #N/A | T93: =(S93*$P$3)/12 -> #N/A | U93: =-IF(AND($P$5="No",HLOOKUP('Loan Summary'!$R93,'Monthly Cash Flow'!$D$6:$CP$76,63,FALSE)>T93),T93,(HLOOKUP('Loan Summary'!$R93,'Monthly Cash Flow'!$D$6:$CP$76,63,FALSE))) -> #N/A | V93: =IF('Loan Summary'!R93=Assumptions!$AD$3,Assumptions!$AD$25,0) -> 0 | W93: =S93+T93+U93+V93 -> #N/A
F94: 93 | G94: =IF(F94<$C$16,L93,IF(F94=$C$16,$C$9,L93)) -> 3740191.3 | H94: =IF(F94<$C$16,IF(F94>$C$6,-PMT(($C$3/12),$C$4,$C$2),I94),-PMT($C$10/12,$C$11,$C$9)) -> 21236.395 | I94: =IF(F94<$C$16,G94*($C$3/12),G94*($C$10/12)) -> 17142.543 | J94: =IF(F94<$C$16,IF(F94<=$C$6,0,H94-I94),IF(F94<=$C$16+$C$13,0,H94-I94)) -> 0 | K94: =IF('Monthly Cash Flow'!$C$88="Lender Draw",HLOOKUP(F94,'Monthly Cash Flow'!$D$79:$CP$88,10),0) -> 0 | L94: =G94-J94+K94 -> 3740191.3 | R94: 93 | S94: =W93 -> #N/A | T94: =(S94*$P$3)/12 -> #N/A | U94: =-IF(AND($P$5="No",HLOOKUP('Loan Summary'!$R94,'Monthly Cash Flow'!$D$6:$CP$76,63,FALSE)>T94),T94,(HLOOKUP('Loan Summary'!$R94,'Monthly Cash Flow'!$D$6:$CP$76,63,FALSE))) -> #N/A | V94: =IF('Loan Summary'!R94=Assumptions!$AD$3,Assumptions!$AD$25,0) -> 0 | W94: =S94+T94+U94+V94 -> #N/A
F95: 94 | G95: =IF(F95<$C$16,L94,IF(F95=$C$16,$C$9,L94)) -> 3740191.3 | H95: =IF(F95<$C$16,IF(F95>$C$6,-PMT(($C$3/12),$C$4,$C$2),I95),-PMT($C$10/12,$C$11,$C$9)) -> 21236.395 | I95: =IF(F95<$C$16,G95*($C$3/12),G95*($C$10/12)) -> 17142.543 | J95: =IF(F95<$C$16,IF(F95<=$C$6,0,H95-I95),IF(F95<=$C$16+$C$13,0,H95-I95)) -> 0 | K95: =IF('Monthly Cash Flow'!$C$88="Lender Draw",HLOOKUP(F95,'Monthly Cash Flow'!$D$79:$CP$88,10),0) -> 0 | L95: =G95-J95+K95 -> 3740191.3 | R95: 94 | S95: =W94 -> #N/A | T95: =(S95*$P$3)/12 -> #N/A | U95: =-IF(AND($P$5="No",HLOOKUP('Loan Summary'!$R95,'Monthly Cash Flow'!$D$6:$CP$76,63,FALSE)>T95),T95,(HLOOKUP('Loan Summary'!$R95,'Monthly Cash Flow'!$D$6:$CP$76,63,FALSE))) -> #N/A | V95: =IF('Loan Summary'!R95=Assumptions!$AD$3,Assumptions!$AD$25,0) -> 0 | W95: =S95+T95+U95+V95 -> #N/A
F96: 95 | G96: =IF(F96<$C$16,L95,IF(F96=$C$16,$C$9,L95)) -> 3740191.3 | H96: =IF(F96<$C$16,IF(F96>$C$6,-PMT(($C$3/12),$C$4,$C$2),I96),-PMT($C$10/12,$C$11,$C$9)) -> 21236.395 | I96: =IF(F96<$C$16,G96*($C$3/12),G96*($C$10/12)) -> 17142.543 | J96: =IF(F96<$C$16,IF(F96<=$C$6,0,H96-I96),IF(F96<=$C$16+$C$13,0,H96-I96)) -> 0 | K96: =IF('Monthly Cash Flow'!$C$88="Lender Draw",HLOOKUP(F96,'Monthly Cash Flow'!$D$79:$CP$88,10),0) -> 0 | L96: =G96-J96+K96 -> 3740191.3 | R96: 95 | S96: =W95 -> #N/A | T96: =(S96*$P$3)/12 -> #N/A | U96: =-IF(AND($P$5="No",HLOOKUP('Loan Summary'!$R96,'Monthly Cash Flow'!$D$6:$CP$76,63,FALSE)>T96),T96,(HLOOKUP('Loan Summary'!$R96,'Monthly Cash Flow'!$D$6:$CP$76,63,FALSE))) -> #N/A | V96: =IF('Loan Summary'!R96=Assumptions!$AD$3,Assumptions!$AD$25,0) -> 0 | W96: =S96+T96+U96+V96 -> #N/A
F97: 96 | G97: =IF(F97<$C$16,L96,IF(F97=$C$16,$C$9,L96)) -> 3740191.3 | H97: =IF(F97<$C$16,IF(F97>$C$6,-PMT(($C$3/12),$C$4,$C$2),I97),-PMT($C$10/12,$C$11,$C$9)) -> 21236.395 | I97: =IF(F97<$C$16,G97*($C$3/12),G97*($C$10/12)) -> 17142.543 | J97: =IF(F97<$C$16,IF(F97<=$C$6,0,H97-I97),IF(F97<=$C$16+$C$13,0,H97-I97)) -> 0 | K97: =IF('Monthly Cash Flow'!$C$88="Lender Draw",HLOOKUP(F97,'Monthly Cash Flow'!$D$79:$CP$88,10),0) -> 0 | L97: =G97-J97+K97 -> 3740191.3 | R97: 96 | S97: =W96 -> #N/A | T97: =(S97*$P$3)/12 -> #N/A | U97: =-IF(AND($P$5="No",HLOOKUP('Loan Summary'!$R97,'Monthly Cash Flow'!$D$6:$CP$76,63,FALSE)>T97),T97,(HLOOKUP('Loan Summary'!$R97,'Monthly Cash Flow'!$D$6:$CP$76,63,FALSE))) -> #N/A | V97: =IF('Loan Summary'!R97=Assumptions!$AD$3,Assumptions!$AD$25,0) -> 0 | W97: =S97+T97+U97+V97 -> #N/A
... F361: 360 | G361: =IF(F361<$C$16,L360,IF(F361=$C$16,$C$9,L360)) -> 2363069.2 | H361: =IF(F361<$C$16,IF(F361>$C$6,-PMT(($C$3/12),$C$4,$C$2),I361),-PMT($C$10/12,$C$11,$C$9)) -> 21236.395 | I361: =IF(F361<$C$16,G361*($C$3/12),G361*($C$10/12)) -> 10830.734 | J361: =IF(F361<$C$16,IF(F361<=$C$6,0,H361-I361),IF(F361<=$C$16+$C$13,0,H361-I361)) -> 10405.661 | K361: =IF('Monthly Cash Flow'!$C$88="Lender Draw",HLOOKUP(F361,'Monthly Cash Flow'!$D$79:$CP$88,10),0) -> 0 | L361: =G361-J361+K361 -> 2352663.5 | R361: 360 | S361: =W360 -> #N/A | T361: =(S361*$P$3)/12 -> #N/A | U361: =-IF(AND($P$5="No",HLOOKUP('Loan Summary'!$R361,'Monthly Cash Flow'!$D$6:$CP$76,63,FALSE)>T361),T361,(HLOOKUP('Loan Summary'!$R361,'Monthly Cash Flow'!$D$6:$CP$76,63,FALSE))) -> #N/A | V361: =IF('Loan Summary'!R361=Assumptions!$AD$3,Assumptions!$AD$25,0) -> 0 | W361: =S361+T361+U361+V361 -> #N/A

Sheet Sale Analysis
E1: Main Scenario | H1: Second Option
B2: Sale Analysis | K2: Sale Inputs | P2: Conventional Loan Test | S2: Refi Test | W2: REFI OUT OF BRIDGE CALC
B3: Sale Month | C3: =E3 -> 83 | D3: =E3 -> 83 | E3: 83 | F3: =E3 -> 83 | G3: =F3 -> 83 | H3: 84 | K3: Broker Fee | L3: 0.02 | P3: Test Month | Q3: =Assumptions!W21 -> 26 | S3: Test Month | T3: =Assumptions!AD3 -> 35 | W3: Test Month | X3: =Assumptions!AD3 -> 35
B4: Cap Rate | C4: =D4-0.25% -> 0.0525 | D4: =E4-0.25% -> 0.055 | E4: 0.0575 | F4: =E4+0.25% -> 0.06 | G4: =F4+0.25% -> 0.0625 | H4: 0.055 | K4: Closing Costs | L4: 0.01 | P4: Revenue | Q4: =HLOOKUP((Assumptions!$W$21-2),'Monthly Cash Flow'!$D$6:$CP$34,27)*12+-HLOOKUP((Assumptions!$W$21-2),'Monthly Cash Flow'!$D$6:$CP$34,9)*12 -> 442864.14 | S4: Revenue | T4: =(HLOOKUP((Assumptions!$AD$3),'Monthly Cash Flow'!$D$6:$CP$34,27)-HLOOKUP((Assumptions!$AD$3),'Monthly Cash Flow'!$D$6:$CP$34,9)-HLOOKUP((Assumptions!$AD$3),'Monthly Cash Flow'!$D$6:$CP$34,8)-(HLOOKUP((Assumptions!$AD$3),'Monthly Cash Flow'!$D$6:$CP$34,7)*5%))*12 -> 437057.21 | W4: Revenue | X4: =HLOOKUP((Assumptions!$AD$3-2),'Monthly Cash Flow'!$D$6:$CP$34,27)*12+-HLOOKUP((Assumptions!$W$21-2),'Monthly Cash Flow'!$D$6:$CP$34,9)*12 -> 444034.78
B5: Revenue | C5: =D5 -> 464200.75 | D5: =E5 -> 464200.75 | E5: =HLOOKUP((E$3-2),'Monthly Cash Flow'!$D$6:$CP$34,27)*12+-HLOOKUP((E$3-2),'Monthly Cash Flow'!$D$6:$CP$34,9)*12+-HLOOKUP((E$3-2),'Monthly Cash Flow'!$D$6:$CP$34,8)*12-HLOOKUP((E$3-2),'Monthly Cash Flow'!$D$6:$CP$34,7)*12*0.05 -> 464200.75 | F5: =E5 -> 464200.75 | G5: =F5 -> 464200.75 | H5: =HLOOKUP((H$3-2),'Monthly Cash Flow'!$D$6:$CP$34,27)*12+-HLOOKUP((H$3-2),'Monthly Cash Flow'!$D$6:$CP$34,9)*12+-HLOOKUP((H$3-2),'Monthly Cash Flow'!$D$6:$CP$34,8)*12-HLOOKUP((H$3-2),'Monthly Cash Flow'!$D$6:$CP$34,7)*12*0.05 -> 464927.11 | P5: Expenses | Q5: =(HLOOKUP((Q$3-2),'Monthly Cash Flow'!$D$6:$CP$58,53))*12 -> 116138.52 | S5: Expenses | T5: =(HLOOKUP((T$3-2),'Monthly Cash Flow'!$D$6:$CP$58,53))*12 -> 118511.29 | W5: Expenses | X5: =(HLOOKUP((X$3-2),'Monthly Cash Flow'!$D$6:$CP$58,53))*12 -> 118511.29
B6: Expenses | C6: =D6 -> 86850.573 | D6: =E6 -> 86850.573 | E6: =(HLOOKUP((E$3-2),'Monthly Cash Flow'!$D$6:$CP$58,53)-HLOOKUP((E$3-2),'Monthly Cash Flow'!$D$6:$CP$58,31))*12 -> 86850.573 | F6: =E6 -> 86850.573 | G6: =F6 -> 86850.573 | H6: =(HLOOKUP((H$3-2),'Monthly Cash Flow'!$D$6:$CP$58,53)-HLOOKUP((H$3-2),'Monthly Cash Flow'!$D$6:$CP$58,31))*12 -> 86872.822
B7: Tax Adjustment | C7: =C11*Assumptions!$P$24 -> 71622.9 | D7: =D11*Assumptions!$P$24 -> 68966.1 | E7: =E11*Assumptions!$P$24 -> 66493.8 | F7: =F11*Assumptions!$P$24 -> 64193.7 | G7: =G11*Assumptions!$P$24 -> 62053.5 | H7: =H11*Assumptions!$P$24 -> 69101.4 | P7: NOI | Q7: =Q4-Q5 -> 326725.61 | S7: NOI | T7: =T4-T5 -> 318545.92 | W7: NOI | X7: =X4-X5 -> 325523.49
B8: NOI | C8: =C5-C6-C7 -> 305727.28 | D8: =D5-D6-D7 -> 308384.08 | E8: =E5-E6-E7 -> 310856.38 | F8: =F5-F6-F7 -> 313156.48 | G8: =G5-G6-G7 -> 315296.68 | H8: =H5-H6-H7 -> 308952.89
B10: Sale Price (Per Unit) | C10: =C11/Assumptions!$C$10 -> 342529.41 | D10: =D11/Assumptions!$C$10 -> 329823.53 | E10: =E11/Assumptions!$C$10 -> 318000 | F10: =F11/Assumptions!$C$10 -> 307000 | G10: =G11/Assumptions!$C$10 -> 296764.71 | H10: =H11/Assumptions!$C$10 -> 330470.59
B11: Sale Price | C11: =ROUND($C$8/C4,-3) -> 5823000 | D11: =ROUND($D$8/D4,-3) -> 5607000 | E11: =ROUND(E8/$E$4,-3) -> 5406000 | F11: =ROUND($F$8/F4,-3) -> 5219000 | G11: =ROUND($G$8/G4,-3) -> 5045000 | H11: =ROUND(H8/$H$4,-3) -> 5617000
B12: Plus: Working Capital Dist. | C12: =E12 -> 49829.382 | D12: =E12 -> 49829.382 | E12: =HLOOKUP(E$3,'Monthly Cash Flow'!$D$79:$CP$87,9) -> 49829.382 | F12: =E12 -> 49829.382 | G12: =E12 -> 49829.382 | H12: =HLOOKUP(H$3,'Monthly Cash Flow'!$D$79:$CP$87,9) -> 49991.41
B13: Less: Loan | C13: =E13 -> -3740191.3 | D13: =E13 -> -3740191.3 | E13: =-VLOOKUP($E$3,'Loan Summary'!$F$2:$L$361,7,FALSE) -> -3740191.3 | F13: =E13 -> -3740191.3 | G13: =E13 -> -3740191.3 | H13: =-VLOOKUP($H$3,'Loan Summary'!$F$2:$L$361,7,FALSE) -> -3740191.3
B14: Less: Broker Fee | C14: =-C11*$L$3 -> -116460 | D14: =-D11*$L$3 -> -112140 | E14: =-E11*$L$3 -> -108120 | F14: =-F11*$L$3 -> -104380 | G14: =-G11*$L$3 -> -100900 | H14: =-H11*$L$3 -> -112340
B15: Less: Closing Cost | C15: =-C11*$L$4 -> -58230 | D15: =-D11*$L$4 -> -56070 | E15: =-E11*$L$4 -> -54060 | F15: =-F11*$L$4 -> -52190 | G15: =-G11*$L$4 -> -50450 | H15: =-H11*$L$4 -> -56170
B16: Less: Prepayment Fee
B18: Total Distributions | C18: =SUM(C11:C17) -> 1957948.1 | D18: =SUM(D11:D17) -> 1748428.1 | E18: =SUM(E11:E17) -> 1553458.1 | F18: =SUM(F11:F17) -> 1372068.1 | G18: =SUM(G11:G17) -> 1203288.1 | H18: =SUM(H11:H15) -> 1758290.1
B20: Equity Contribution | C20: =Assumptions!$C$36 -> 1497641.8 | D20: =Assumptions!$C$36 -> 1497641.8 | E20: =Assumptions!$C$36 -> 1497641.8 | F20: =Assumptions!$C$36 -> 1497641.8 | G20: =Assumptions!$C$36 -> 1497641.8 | H20: =Assumptions!$C$36 -> 1497641.8
B21: Equity Gains | C21: =SUM('Cont. Dist.'!$D$61:$CI$61)-Assumptions!$C$36 -> 1871477.1 | D21: =SUM('Cont. Dist.'!$D$58:$CI$58)-Assumptions!$C$36 -> 1661957.1 | E21: =SUM('Cont. Dist.'!$D$15:$CI$15)-Assumptions!$C$36 -> 1466987.1 | F21: =SUM('Cont. Dist.'!$D$55:$CI$55)-Assumptions!$C$36 -> 1285597.1 | G21: =SUM('Cont. Dist.'!$D$52:$CI$52)-Assumptions!$C$36 -> 1116817.1 | H21: =SUM('Cont. Dist.'!$D$40:$CI$40)-'Sale Analysis'!H20 -> 1679717.3
B22: Equity Multiple | C22: =SUM('Cont. Dist.'!$D$61:$CI$61)/Assumptions!$C$36 -> 2.249616 | D22: =SUM('Cont. Dist.'!$D$58:$CI$58)/Assumptions!$C$36 -> 2.1097161 | E22: =SUM('Cont. Dist.'!$D$15:$CI$15)/Assumptions!$C$36 -> 1.9795314 | F22: =SUM('Cont. Dist.'!$D$55:$CI$55)/Assumptions!$C$36 -> 1.8584143 | G22: =SUM('Cont. Dist.'!$D$52:$CI$52)/Assumptions!$C$36 -> 1.7457171 | H22: =SUM('Cont. Dist.'!$D$40:$CI$40)/H20 -> 2.1215748
B23: IRR | C23: =XIRR('Cont. Dist.'!$C$62:$CI$62,'Cont. Dist.'!$C$17:$CI$17) -> 0.17656094 | D23: =XIRR('Cont. Dist.'!$C$59:$CI$59,'Cont. Dist.'!$C$17:$CI$17) -> 0.16449794 | E23: =XIRR('Cont. Dist.'!$C$20:$CI$20,'Cont. Dist.'!$C$17:$CI$17) -> 0.15240298 | F23: =XIRR('Cont. Dist.'!$C$56:$CI$56,'Cont. Dist.'!$C$17:$CI$17) -> 0.14025808 | G23: =XIRR('Cont. Dist.'!$C$53:$CI$53,'Cont. Dist.'!$C$17:$CI$17) -> 0.12803772 | H23: =XIRR('Cont. Dist.'!$C$45:$CI$45,'Cont. Dist.'!$C$42:$CI$42) -> 0.16811591

Sheet Waterfall Split
B2: 3-Tier IRR-Hurdle Waterfall - Compounded, Cumulative, Monthly Accrual and Monthly Distribution shown | Q2: Sponsor | R2: Investor
B3: First, Preferred Return is distributed to Investor and Sponsor Pari-Passu; | P3: Tier 1 | Q3: =C27 -> 0.05 | R3: =C26 -> 0.95
B4: Second, Investor and Sponsor capital are returned. | P4: Tier 2 | Q4: =SUM(C41:C42) -> 0.335 | R4: =C40 -> 0.665
B5: Third, Tier 2 promote is distributed to Sponsor. | P5: Tier 3 | Q5: =SUM(C48:C49) -> 0.43 | R5: =C47 -> 0.57
B6: Fourth, Tier 3 promote is distributed to Sponsor.
H10: ='Cont. Dist.'!C17 -> 46204 | I10: ='Cont. Dist.'!D17 -> 46204 | J10: ='Cont. Dist.'!E17 -> 46235 | K10: ='Cont. Dist.'!F17 -> 46266 | L10: ='Cont. Dist.'!G17 -> 46296 | M10: ='Cont. Dist.'!H17 -> 46327 | N10: ='Cont. Dist.'!I17 -> 46357 | O10: ='Cont. Dist.'!J17 -> 46388 | ... CN10: ='Cont. Dist.'!CI17 -> 48731
H11: Time 0 | I11: 1 | J11: =I11+1 -> 2 | K11: =J11+1 -> 3 | L11: =K11+1 -> 4 | M11: =L11+1 -> 5 | N11: =M11+1 -> 6 | O11: =N11+1 -> 7 | P11: =O11+1 -> 8 | Q11: =P11+1 -> 9 | ... CN11: =CM11+1 -> 84
E12: Total
B13: Levered Cash Flow | E13: =SUM(H13:BP13) -> -240275.71 | H13: ='Cont. Dist.'!C20 -> -1497641.8 | I13: ='Cont. Dist.'!D20 -> 0 | J13: ='Cont. Dist.'!E20 -> 0 | K13: ='Cont. Dist.'!F20 -> 0 | L13: ='Cont. Dist.'!G20 -> 0 | M13: ='Cont. Dist.'!H20 -> 0 | N13: ='Cont. Dist.'!I20 -> 0 | O13: ='Cont. Dist.'!J20 -> 0 | ... CN13: ='Cont. Dist.'!CI20 -> 0
B15: Equity Investment | C15: =Assumptions!C36 -> 1497641.8
B16: Sponsor Portion | C16: 0.05 | E16: =SUM(H16:BP16) -> -74882.088 | H16: =IF('Cont. Dist.'!C18>0,0,'Cont. Dist.'!C18*$C$16) -> -74882.088 | I16: =IF('Cont. Dist.'!D18>0,0,'Cont. Dist.'!D18*$C$16) -> 0 | J16: =IF('Cont. Dist.'!E18>0,0,'Cont. Dist.'!E18*$C$16) -> 0 | K16: =IF('Cont. Dist.'!F18>0,0,'Cont. Dist.'!F18*$C$16) -> 0 | L16: =IF('Cont. Dist.'!G18>0,0,'Cont. Dist.'!G18*$C$16) -> 0 | M16: =IF('Cont. Dist.'!H18>0,0,'Cont. Dist.'!H18*$C$16) -> 0 | N16: =IF('Cont. Dist.'!I18>0,0,'Cont. Dist.'!I18*$C$16) -> 0 | O16: =IF('Cont. Dist.'!J18>0,0,'Cont. Dist.'!J18*$C$16) -> 0 | ... CN16: =IF('Cont. Dist.'!CI18>0,0,'Cont. Dist.'!CI18*$C$16) -> 0
B17: Investor Portion | C17: =1-C16 -> 0.95 | E17: =SUM(H17:BP17) -> -1422759.7 | H17: =IF('Cont. Dist.'!C18>0,0,'Cont. Dist.'!C18*$C$17) -> -1422759.7 | I17: =IF('Cont. Dist.'!D18>0,0,'Cont. Dist.'!D18*$C$17) -> 0 | J17: =IF('Cont. Dist.'!E18>0,0,'Cont. Dist.'!E18*$C$17) -> 0 | K17: =IF('Cont. Dist.'!F18>0,0,'Cont. Dist.'!F18*$C$17) -> 0 | L17: =IF('Cont. Dist.'!G18>0,0,'Cont. Dist.'!G18*$C$17) -> 0 | M17: =IF('Cont. Dist.'!H18>0,0,'Cont. Dist.'!H18*$C$17) -> 0 | N17: =IF('Cont. Dist.'!I18>0,0,'Cont. Dist.'!I18*$C$17) -> 0 | O17: =IF('Cont. Dist.'!J18>0,0,'Cont. Dist.'!J18*$C$17) -> 0 | ... CN17: =IF('Cont. Dist.'!CI18>0,0,'Cont. Dist.'!CI18*$C$17) -> 0
C18: Investor IRR through:
B19: TIER 1 | D19: 0.08
B20: BOP Balance | D20: =(1+D19)^(1/12)-1 -> 0.0064340301 | H20: =G24 -> 0 | I20: =H24 -> 1422759.7 | J20: =I24 -> 1431913.7 | K20: =J24 -> 1441126.7 | L20: =K24 -> 1450399 | M20: =L24 -> 1459730.9 | N20: =M24 -> 1469122.8 | O20: =N24 -> 1478575.2 | ... CN20: =CM24 -> 0
B21: Investor Injections | E21: =SUM(H21:BP21) -> 1422759.7 | H21: =-H17 -> 1422759.7 | I21: =-I17 -> 0 | J21: =-J17 -> 0 | K21: =-K17 -> 0 | L21: =-L17 -> 0 | M21: =-M17 -> 0 | N21: =-N17 -> 0 | O21: =-O17 -> 0 | ... CN21: =-CN17 -> 0
B22: Investor Accruals | E22: =SUM(H22:BP22) -> 459821.34 | H22: =$D$20*H20 -> 0 | I22: =$D$20*I20 -> 9154.0785 | J22: =$D$20*J20 -> 9212.9761 | K22: =$D$20*K20 -> 9272.2527 | L22: =$D$20*L20 -> 9331.9107 | M22: =$D$20*M20 -> 9391.9525 | N22: =$D$20*N20 -> 9452.3806 | O22: =$D$20*O20 -> 9513.1975 | ... CN22: =$D$20*CN20 -> 0
B23: Tier 1 Accrual Distribution | E23: =SUM(H23:BP23) -> -1194497.7 | H23: =-IF(H56>0,MIN($C$26*H56,H20+H21+H22),0) -> 0 | I23: =-IF(I56>0,MIN($C$26*I56,I20+I21+I22),0) -> 0 | J23: =-IF(J56>0,MIN($C$26*J56,J20+J21+J22),0) -> 0 | K23: =-IF(K56>0,MIN($C$26*K56,K20+K21+K22),0) -> 0 | L23: =-IF(L56>0,MIN($C$26*L56,L20+L21+L22),0) -> 0 | M23: =-IF(M56>0,MIN($C$26*M56,M20+M21+M22),0) -> 0 | N23: =-IF(N56>0,MIN($C$26*N56,N20+N21+N22),0) -> 0 | O23: =-IF(O56>0,MIN($C$26*O56,O20+O21+O22),0) -> 0 | ... CN23: =-IF(CN56>0,MIN($C$26*CN56,CN20+CN21+CN22),0) -> 0
B24: EOP Balance | E24: =SUM(E21:E23) -> 688083.27 | H24: =SUM(H20:H23) -> 1422759.7 | I24: =SUM(I20:I23) -> 1431913.7 | J24: =SUM(J20:J23) -> 1441126.7 | K24: =SUM(K20:K23) -> 1450399 | L24: =SUM(L20:L23) -> 1459730.9 | M24: =SUM(M20:M23) -> 1469122.8 | N24: =SUM(N20:N23) -> 1478575.2 | O24: =SUM(O20:O23) -> 1488088.4 | ... CN24: =SUM(CN20:CN23) -> 0
B26: Investor Cash Flow | C26: =C17 -> 0.95 | E26: =SUM(H26:BP26) -> -228261.93 | H26: =-H21-H23 -> -1422759.7 | I26: =-I21-I23 -> 0 | J26: =-J21-J23 -> 0 | K26: =-K21-K23 -> 0 | L26: =-L21-L23 -> 0 | M26: =-M21-M23 -> 0 | N26: =-N21-N23 -> 0 | O26: =-O21-O23 -> 0 | ... CN26: =-CN21-CN23 -> 0
B27: Sponsor Equity Cash Flow | C27: =C16 -> 0.05 | E27: =SUM(H27:BP27) -> 62868.302 | H27: =-H23/$C$26*$C$27 -> 0 | I27: =-I23/$C$26*$C$27 -> 0 | J27: =-J23/$C$26*$C$27 -> 0 | K27: =-K23/$C$26*$C$27 -> 0 | L27: =-L23/$C$26*$C$27 -> 0 | M27: =-M23/$C$26*$C$27 -> 0 | N27: =-N23/$C$26*$C$27 -> 0 | O27: =-O23/$C$26*$C$27 -> 0 | ... CN27: =-CN23/$C$26*$C$27 -> 0
B29: Remaining Cash to Distribute | E29: =SUM(H29:BP29) -> 4.5474735e-13 | H29: =IF(H13>0,H13-SUM(H26:H27),0) -> 0 | I29: =IF(I13>0,I13-SUM(I26:I27),0) -> 0 | J29: =IF(J13>0,J13-SUM(J26:J27),0) -> 0 | K29: =IF(K13>0,K13-SUM(K26:K27),0) -> 0 | L29: =IF(L13>0,L13-SUM(L26:L27),0) -> 0 | M29: =IF(M13>0,M13-SUM(M26:M27),0) -> 0 | N29: =IF(N13>0,N13-SUM(N26:N27),0) -> 0 | O29: =IF(O13>0,O13-SUM(O26:O27),0) -> 0 | ... CN29: =IF(CN13>0,CN13-SUM(CN26:CN27),0) -> 0
B30: Investor IRR Check | H30: =IFERROR((IRR($H26:H26)+1)^12-1,0) -> 0 | I30: =IFERROR((IRR($H26:I26)+1)^12-1,0) -> 0 | J30: =IFERROR((IRR($H26:J26)+1)^12-1,0) -> 0 | K30: =IFERROR((IRR($H26:K26)+1)^12-1,0) -> 0 | L30: =IFERROR((IRR($H26:L26)+1)^12-1,0) -> 0 | M30: =IFERROR((IRR($H26:M26)+1)^12-1,0) -> 0 | N30: =IFERROR((IRR($H26:N26)+1)^12-1,0) -> 0 | O30: =IFERROR((IRR($H26:O26)+1)^12-1,0) -> 0 | ... CN30: =IFERROR((IRR($H26:CN26)+1)^12-1,0) -> 0.08
C31: Investor IRR above: | D31: =D19 -> 0.08
B32: TIER 2 | C32: through: | D32: 0.12
B33: BOP Balance | D33: =(1+D32)^(1/12)-1 -> 0.0094887929 | H33: =G38 -> 0 | I33: =H38 -> 1422759.7 | J33: =I38 -> 1436259.9 | K33: =J38 -> 1449888.3 | L33: =K38 -> 1463646 | M33: =L38 -> 1477534.2 | N33: =M38 -> 1491554.2 | O33: =N38 -> 1505707.3 | ... CN33: =CM38 -> 0
B34: Investor Injections | E34: =SUM(H34:BP34) -> 1422759.7 | H34: =H21 -> 1422759.7 | I34: =I21 -> 0 | J34: =J21 -> 0 | K34: =K21 -> 0 | L34: =L21 -> 0 | M34: =M21 -> 0 | N34: =N21 -> 0 | O34: =O21 -> 0 | ... CN34: =CN21 -> 0
B35: Investor Accruals | E35: =SUM(H35:BP35) -> 765249.36 | H35: =$D$33*H33 -> 0 | I35: =$D$33*I33 -> 13500.272 | J35: =$D$33*J33 -> 13628.373 | K35: =$D$33*K33 -> 13757.69 | L35: =$D$33*L33 -> 13888.234 | M35: =$D$33*M33 -> 14020.016 | N35: =$D$33*N33 -> 14153.049 | O35: =$D$33*O33 -> 14287.345 | ... CN35: =$D$33*CN33 -> 0
B36: Tier 1 Accrual Distribution | E36: =SUM(H36:BP36) -> -1194497.7 | H36: =H23 -> 0 | I36: =I23 -> 0 | J36: =J23 -> 0 | K36: =K23 -> 0 | L36: =L23 -> 0 | M36: =M23 -> 0 | N36: =N23 -> 0 | O36: =O23 -> 0 | ... CN36: =CN23 -> 0
B37: Tier 2 Accrual Distribution | E37: =SUM(H37:BP37) -> -3.0240699e-13 | H37: =-IF(H29>0,MIN($C$40*H29,H33+H35+H36),0) -> 0 | I37: =-IF(I29>0,MIN($C$40*I29,I33+I35+I36),0) -> 0 | J37: =-IF(J29>0,MIN($C$40*J29,J33+J35+J36),0) -> 0 | K37: =-IF(K29>0,MIN($C$40*K29,K33+K35+K36),0) -> 0 | L37: =-IF(L29>0,MIN($C$40*L29,L33+L35+L36),0) -> 0 | M37: =-IF(M29>0,MIN($C$40*M29,M33+M35+M36),0) -> 0 | N37: =-IF(N29>0,MIN($C$40*N29,N33+N35+N36),0) -> 0 | O37: =-IF(O29>0,MIN($C$40*O29,O33+O35+O36),0) -> 0 | ... CN37: =-IF(CN29>0,MIN($C$40*CN29,CN33+CN35+CN36),0) -> 0
B38: EOP Balance | E38: =SUM(E34:E37) -> 993511.28 | H38: =SUM(H33:H37) -> 1422759.7 | I38: =SUM(I33:I37) -> 1436259.9 | J38: =SUM(J33:J37) -> 1449888.3 | K38: =SUM(K33:K37) -> 1463646 | L38: =SUM(L33:L37) -> 1477534.2 | M38: =SUM(M33:M37) -> 1491554.2 | N38: =SUM(N33:N37) -> 1505707.3 | O38: =SUM(O33:O37) -> 1519994.6 | ... CN38: =SUM(CN33:CN37) -> 0
B40: Investor Cash Flow | C40: =1-SUM(C41:C42) -> 0.665 | E40: =SUM(H40:BP40) -> 3.0240699e-13 | H40: =-H37 -> 0 | I40: =-I37 -> 0 | J40: =-J37 -> 0 | K40: =-K37 -> 0 | L40: =-L37 -> 0 | M40: =-M37 -> 0 | N40: =-N37 -> 0 | O40: =-O37 -> 0 | ... CN40: =-CN37 -> 0
B41: Sponsor Equity Cash Flow | C41: =C16*(1-C42) -> 0.035 | E41: =SUM(H41:BP41) -> 1.5916157e-14 | H41: =-H37/$C$40*$C$41 -> 0 | I41: =-I37/$C$40*$C$41 -> 0 | J41: =-J37/$C$40*$C$41 -> 0 | K41: =-K37/$C$40*$C$41 -> 0 | L41: =-L37/$C$40*$C$41 -> 0 | M41: =-M37/$C$40*$C$41 -> 0 | N41: =-N37/$C$40*$C$41 -> 0 | O41: =-O37/$C$40*$C$41 -> 0 | ... CN41: =-CN37/$C$40*$C$41 -> 0
B42: Sponsor Promote Cash Flow | C42: 0.3 | E42: =SUM(H42:BP42) -> 1.3642421e-13 | H42: =-H37/$C$40*$C$42 -> 0 | I42: =-I37/$C$40*$C$42 -> 0 | J42: =-J37/$C$40*$C$42 -> 0 | K42: =-K37/$C$40*$C$42 -> 0 | L42: =-L37/$C$40*$C$42 -> 0 | M42: =-M37/$C$40*$C$42 -> 0 | N42: =-N37/$C$40*$C$42 -> 0 | O42: =-O37/$C$40*$C$42 -> 0 | ... CN42: =-CN37/$C$40*$C$42 -> 0
B44: Remaining Cash to Distribute | E44: =SUM(H44:BP44) -> 0 | H44: =H29-SUM(H40:H42) -> 0 | I44: =I29-SUM(I40:I42) -> 0 | J44: =J29-SUM(J40:J42) -> 0 | K44: =K29-SUM(K40:K42) -> 0 | L44: =L29-SUM(L40:L42) -> 0 | M44: =M29-SUM(M40:M42) -> 0 | N44: =N29-SUM(N40:N42) -> 0 | O44: =O29-SUM(O40:O42) -> 0 | ... CN44: =CN29-SUM(CN40:CN42) -> 0
C45: Investor IRR above:
B46: TIER 3 | D46: =D32 -> 0.12
B47: Investor Cash Flow | C47: =1-SUM(C48:C49) -> 0.57 | E47: =SUM(H47:BP47) -> 0 | H47: =$C$47*H44 -> 0 | I47: =$C$47*I44 -> 0 | J47: =$C$47*J44 -> 0 | K47: =$C$47*K44 -> 0 | L47: =$C$47*L44 -> 0 | M47: =$C$47*M44 -> 0 | N47: =$C$47*N44 -> 0 | O47: =$C$47*O44 -> 0 | ... CN47: =$C$47*CN44 -> 0
B48: Sponsor Equity Cash Flow | C48: =C16*(1-C49) -> 0.03 | E48: =SUM(H48:BP48) -> 0 | H48: =$C$48*H44 -> 0 | I48: =$C$48*I44 -> 0 | J48: =$C$48*J44 -> 0 | K48: =$C$48*K44 -> 0 | L48: =$C$48*L44 -> 0 | M48: =$C$48*M44 -> 0 | N48: =$C$48*N44 -> 0 | O48: =$C$48*O44 -> 0 | ... CN48: =$C$48*CN44 -> 0
B49: Sponsor Promote Cash Flow | C49: 0.4 | E49: =SUM(H49:BP49) -> 0 | H49: =$C$49*H44 -> 0 | I49: =$C$49*I44 -> 0 | J49: =$C$49*J44 -> 0 | K49: =$C$49*K44 -> 0 | L49: =$C$49*L44 -> 0 | M49: =$C$49*M44 -> 0 | N49: =$C$49*N44 -> 0 | O49: =$C$49*O44 -> 0 | ... CN49: =$C$49*CN44 -> 0
B51: Remaining Cash to Distribute | E51: =SUM(H51:BP51) -> 0 | H51: =H44-SUM(H47:H49) -> 0 | I51: =I44-SUM(I47:I49) -> 0 | J51: =J44-SUM(J47:J49) -> 0 | K51: =K44-SUM(K47:K49) -> 0 | L51: =L44-SUM(L47:L49) -> 0 | M51: =M44-SUM(M47:M49) -> 0 | N51: =N44-SUM(N47:N49) -> 0 | O51: =O44-SUM(O47:O49) -> 0 | ... CN51: =CN44-SUM(CN47:CN49) -> 0
H53: Time 0 | I53: =I11 -> 1 | J53: =J11 -> 2 | K53: =K11 -> 3 | L53: =L11 -> 4 | M53: =M11 -> 5 | N53: =N11 -> 6 | O53: =O11 -> 7 | P53: =P11 -> 8 | ... CN53: =CN11 -> 84
B54: Deal Summary
B55: Total Investment | C55: =SUM(H55:CN55) -> -1497641.8 | H55: =H16+H17 -> -1497641.8 | I55: =I16+I17 -> 0 | J55: =J16+J17 -> 0 | K55: =K16+K17 -> 0 | L55: =L16+L17 -> 0 | M55: =M16+M17 -> 0 | N55: =N16+N17 -> 0 | O55: =O16+O17 -> 0 | ... CN55: =CN16+CN17 -> 0
B56: Gross Distributions | C56: =SUM(H56:CN56) -> 2964628.9 | I56: ='Cont. Dist.'!D19 -> 0 | J56: ='Cont. Dist.'!E19 -> 0 | K56: ='Cont. Dist.'!F19 -> 0 | L56: ='Cont. Dist.'!G19 -> 0 | M56: ='Cont. Dist.'!H19 -> 0 | N56: ='Cont. Dist.'!I19 -> 0 | O56: ='Cont. Dist.'!J19 -> 0 | P56: ='Cont. Dist.'!K19 -> 0 | ... CN56: ='Cont. Dist.'!CI19 -> 0
B57: Levered Net Cash Flow | C57: =SUM(H57:CN57) -> 1466987.1 | H57: =SUM(H55:H56) -> -1497641.8 | I57: =SUM(I55:I56) -> 0 | J57: =SUM(J55:J56) -> 0 | K57: =SUM(K55:K56) -> 0 | L57: =SUM(L55:L56) -> 0 | M57: =SUM(M55:M56) -> 0 | N57: =SUM(N55:N56) -> 0 | O57: =SUM(O55:O56) -> 0 | ... CN57: =SUM(CN55:CN56) -> 0
B58: IRR | C58: =XIRR(H57:CN57,H10:CN10) -> 0.15240298
B59: Multiple on Equity | C59: =C57/-C55+1 -> 1.9795314
B61: Investor Summary
B62: Investment | C62: =SUM(H62:CN62) -> -1422759.7 | H62: =H17 -> -1422759.7 | I62: =I17 -> 0 | J62: =J17 -> 0 | K62: =K17 -> 0 | L62: =L17 -> 0 | M62: =M17 -> 0 | N62: =N17 -> 0 | O62: =O17 -> 0 | ... CN62: =CN17 -> 0
B63: Gross Distributions | C63: =SUM(H63:CN63) -> 2544040.9 | H63: =-H23-H37+H47 -> 0 | I63: =-I23-I37+I47 -> 0 | J63: =-J23-J37+J47 -> 0 | K63: =-K23-K37+K47 -> 0 | L63: =-L23-L37+L47 -> 0 | M63: =-M23-M37+M47 -> 0 | N63: =-N23-N37+N47 -> 0 | O63: =-O23-O37+O47 -> 0 | ... CN63: =-CN23-CN37+CN47 -> 0
B64: Net Cash Flow | C64: =SUM(H64:CN64) -> 1121281.2 | H64: =SUM(H62:H63) -> -1422759.7 | I64: =SUM(I62:I63) -> 0 | J64: =SUM(J62:J63) -> 0 | K64: =SUM(K62:K63) -> 0 | L64: =SUM(L62:L63) -> 0 | M64: =SUM(M62:M63) -> 0 | N64: =SUM(N62:N63) -> 0 | O64: =SUM(O62:O63) -> 0 | ... CN64: =SUM(CN62:CN63) -> 0
B65: IRR | C65: =XIRR(H64:CN64,H10:CN10) -> 0.13274836
B66: Multiple on Equity | C66: =C64/-C62+1 -> 1.788103
B68: Sponsor Summary
B69: Investment | C69: =SUM(H69:CN69) -> -74882.088 | H69: =H16 -> -74882.088 | I69: =I16 -> 0 | J69: =J16 -> 0 | K69: =K16 -> 0 | L69: =L16 -> 0 | M69: =M16 -> 0 | N69: =N16 -> 0 | O69: =O16 -> 0 | ... CN69: =CN16 -> 0
B70: Equity Cash Flow | C70: =SUM(H70:CN70) -> 133896.89 | H70: =+H27+H41+H48 -> 0 | I70: =+I27+I41+I48 -> 0 | J70: =+J27+J41+J48 -> 0 | K70: =+K27+K41+K48 -> 0 | L70: =+L27+L41+L48 -> 0 | M70: =+M27+M41+M48 -> 0 | N70: =+N27+N41+N48 -> 0 | O70: =+O27+O41+O48 -> 0 | ... CN70: =+CN27+CN41+CN48 -> 0
B71: Promote Cash Flow | C71: =SUM(H71:CN71) -> 286691.11 | H71: =H42+H49 -> 0 | I71: =I42+I49 -> 0 | J71: =J42+J49 -> 0 | K71: =K42+K49 -> 0 | L71: =L42+L49 -> 0 | M71: =M42+M49 -> 0 | N71: =N42+N49 -> 0 | O71: =O42+O49 -> 0 | ... CN71: =CN42+CN49 -> 0
B72: Net Cash Flow | C72: =SUM(H72:CN72) -> 345705.91 | H72: =SUM(H69:H71) -> -74882.088 | I72: =SUM(I69:I71) -> 0 | J72: =SUM(J69:J71) -> 0 | K72: =SUM(K69:K71) -> 0 | L72: =SUM(L69:L71) -> 0 | M72: =SUM(M69:M71) -> 0 | N72: =SUM(N69:N71) -> 0 | O72: =SUM(O69:O71) -> 0 | ... CN72: =SUM(CN69:CN71) -> 0
B73: IRR | C73: =XIRR(H72:CN72,H10:CN10) -> 0.3449657
B74: Multiple on Equity | C74: =C72/-C69+1 -> 5.6166704
B76: Cash Flow Check | C76: =ROUND(C57-C64-C72,0) -> 0 | D76: =IF(ROUND(C76,0)=0,"OK","Fix") -> OK | H76: =H57-H64-H72 -> 0 | I76: =I57-I64-I72 -> 0 | J76: =J57-J64-J72 -> 0 | K76: =K57-K64-K72 -> 0 | L76: =L57-L64-L72 -> 0 | M76: =M57-M64-M72 -> 0 | N76: =N57-N64-N72 -> 0 | O76: =O57-O64-O72 -> 0 | ... CN76: =CN57-CN64-CN72 -> 0
B77: Must be $0
B79: Internal Rate of Return Check: if the cash flows clear the Hurdle, the IRR Check will be equal to the Hurdle; if the cash flows do not clear the Hurdle, the IRR Check will be equal to the Investor IRR.
C80: IRR Hurdle | E80: IRR Check
B81: Tier 1 | C81: =D19 -> 0.08 | E81: =(IRR(H81:CC81)+1)^12-1 -> -0.034720874 | H81: =-(H21+H23) -> -1422759.7 | I81: =-(I21+I23) -> 0 | J81: =-(J21+J23) -> 0 | K81: =-(K21+K23) -> 0 | L81: =-(L21+L23) -> 0 | M81: =-(M21+M23) -> 0 | N81: =-(N21+N23) -> 0 | O81: =-(O21+O23) -> 0 | ... CN81: =-(CN21+CN23) -> 0
B82: Tier 2 | C82: =D32 -> 0.12 | E82: =(IRR(H82:CC82)+1)^12-1 -> -0.034720874 | H82: =-(H34+H36+H37) -> -1422759.7 | I82: =-(I34+I36+I37) -> 0 | J82: =-(J34+J36+J37) -> 0 | K82: =-(K34+K36+K37) -> 0 | L82: =-(L34+L36+L37) -> 0 | M82: =-(M34+M36+M37) -> 0 | N82: =-(N34+N36+N37) -> 0 | O82: =-(O34+O36+O37) -> 0 | ... CN82: =-(CN34+CN36+CN37) -> 0
B85: Financial Risk/Reward Summary
C86: Financial Risk | D86: Financial Reward * | F86: * Exclusive of any fees
B87: Sponsor | C87: =C16 -> 0.05 | D87: =1-D88 -> 0.23565709
B88: Investor | C88: =C17 -> 0.95 | D88: =C64/C57 -> 0.76434291
B89: IRR
B90: Deal | C90: =C58 -> 0.15240298
B91: Investor | C91: =C65 -> 0.13274836
B92: Sponsor | C92: =C73 -> 0.3449657
B93: Multiple on Equity
B94: Deal | C94: =C59 -> 1.9795314
B95: Investor | C95: =C66 -> 1.788103
B96: Sponsor | C96: =C74 -> 5.6166704
B97: Cash Flows By Tier Summary
C98: Cash Flows | D98: Share
B99: Tier 1 | C99: =SUM(E26:E27) -> -165393.62 | D99: =C99/C102 -> 1
B100: Tier 2 | C100: =SUM(E40:E42) -> 4.5474735e-13 | D100: =C100/C102 -> -2.7494854e-18
B101: Tier 3 | C101: =SUM(E47:E49) -> 0 | D101: =C101/C102 -> 0
B102: Total | C102: =SUM(C99:C101) -> -165393.62 | D102: =SUM(D99:D101) -> 1
B103: Less Sponsor Investment | C103: =C69 -> -74882.088
B104: Net Cash Flow | C104: =SUM(C102:C103) -> -240275.71
P119: * Exclusive of any fees

Sheet Monthly Cash Flow
B1: Cumulative # of renovated units | C1: 0 | D1: =MIN((D2+$C$1),Assumptions!$C$10) -> 0 | E1: =MIN((E2+$C$1),Assumptions!$C$10) -> 0 | F1: =MIN((F2+$C$1),Assumptions!$C$10) -> 1 | G1: =MIN((G2+$C$1),Assumptions!$C$10) -> 2 | H1: =MIN((H2+$C$1),Assumptions!$C$10) -> 3 | I1: =MIN((I2+$C$1),Assumptions!$C$10) -> 4 | J1: =MIN((J2+$C$1),Assumptions!$C$10) -> 5 | K1: =MIN((K2+$C$1),Assumptions!$C$10) -> 6 | ... O1: =MIN((O2+$C$1),Assumptions!$C$10) -> 10 | Q1: =MIN((Q2+$C$1),Assumptions!$C$10) -> 11 | R1: =MIN((R2+$C$1),Assumptions!$C$10) -> 12 | S1: =MIN((S2+$C$1),Assumptions!$C$10) -> 13 | T1: =MIN((T2+$C$1),Assumptions!$C$10) -> 14 | U1: =MIN((U2+$C$1),Assumptions!$C$10) -> 15 | V1: =MIN((V2+$C$1),Assumptions!$C$10) -> 16 | W1: =MIN((W2+$C$1),Assumptions!$C$10) -> 17 | X1: =MIN((X2+$C$1),Assumptions!$C$10) -> 17 | ... AB1: =MIN((AB2+$C$1),Assumptions!$C$10) -> 17 | AD1: =MIN((AD2+$C$1),Assumptions!$C$10) -> 17 | AE1: =MIN((AE2+$C$1),Assumptions!$C$10) -> 17 | AF1: =MIN((AF2+$C$1),Assumptions!$C$10) -> 17 | AG1: =MIN((AG2+$C$1),Assumptions!$C$10) -> 17 | AH1: =MIN((AH2+$C$1),Assumptions!$C$10) -> 17 | AI1: =MIN((AI2+$C$1),Assumptions!$C$10) -> 17 | AJ1: =MIN((AJ2+$C$1),Assumptions!$C$10) -> 17 | AK1: =MIN((AK2+$C$1),Assumptions!$C$10) -> 17 | ... AO1: =MIN((AO2+$C$1),Assumptions!$C$10) -> 17 | AQ1: =MIN((AQ2+$C$1),Assumptions!$C$10) -> 17 | AR1: =MIN((AR2+$C$1),Assumptions!$C$10) -> 17 | AS1: =MIN((AS2+$C$1),Assumptions!$C$10) -> 17 | AT1: =MIN((AT2+$C$1),Assumptions!$C$10) -> 17 | AU1: =MIN((AU2+$C$1),Assumptions!$C$10) -> 17 | AV1: =MIN((AV2+$C$1),Assumptions!$C$10) -> 17 | AW1: =MIN((AW2+$C$1),Assumptions!$C$10) -> 17 | AX1: =MIN((AX2+$C$1),Assumptions!$C$10) -> 17 | ... BB1: =MIN((BB2+$C$1),Assumptions!$C$10) -> 17 | BD1: =MIN((BD2+$C$1),Assumptions!$C$10) -> 17 | BE1: =MIN((BE2+$C$1),Assumptions!$C$10) -> 17 | BF1: =MIN((BF2+$C$1),Assumptions!$C$10) -> 17 | BG1: =MIN((BG2+$C$1),Assumptions!$C$10) -> 17 | BH1: =MIN((BH2+$C$1),Assumptions!$C$10) -> 17 | BI1: =MIN((BI2+$C$1),Assumptions!$C$10) -> 17 | BJ1: =MIN((BJ2+$C$1),Assumptions!$C$10) -> 17 | BK1: =MIN((BK2+$C$1),Assumptions!$C$10) -> 17 | ... BO1: =MIN((BO2+$C$1),Assumptions!$C$10) -> 17 | BQ1: =MIN((BQ2+$C$1),Assumptions!$C$10) -> 17 | BR1: =MIN((BR2+$C$1),Assumptions!$C$10) -> 17 | BS1: =MIN((BS2+$C$1),Assumptions!$C$10) -> 17 | BT1: =MIN((BT2+$C$1),Assumptions!$C$10) -> 17 | BU1: =MIN((BU2+$C$1),Assumptions!$C$10) -> 17 | BV1: =MIN((BV2+$C$1),Assumptions!$C$10) -> 17 | BW1: =MIN((BW2+$C$1),Assumptions!$C$10) -> 17 | BX1: =MIN((BX2+$C$1),Assumptions!$C$10) -> 17 | ... CB1: =MIN((CB2+$C$1),Assumptions!$C$10) -> 17 | CD1: =MIN((CD2+$C$1),Assumptions!$C$10) -> 17 | CE1: =MIN((CE2+$C$1),Assumptions!$C$10) -> 17 | CF1: =MIN((CF2+$C$1),Assumptions!$C$10) -> 17 | CG1: =MIN((CG2+$C$1),Assumptions!$C$10) -> 17 | CH1: =MIN((CH2+$C$1),Assumptions!$C$10) -> 17 | CI1: =MIN((CI2+$C$1),Assumptions!$C$10) -> 17 | CJ1: =MIN((CJ2+$C$1),Assumptions!$C$10) -> 17 | CK1: =MIN((CK2+$C$1),Assumptions!$C$10) -> 17 | ... CO1: =MIN((CO2+$C$1),Assumptions!$C$10) -> 17
B2: Total # of Units Renovated by Sponsor | D2: =IF(D6>Assumptions!$C$56,Assumptions!$C$53,IF(D6>=Assumptions!$C$55,MIN(ROUNDDOWN(Assumptions!$C$52*'Monthly Cash Flow'!D$4,0),Assumptions!$C$53),0)) -> 0 | E2: =IF(E6>Assumptions!$C$56,Assumptions!$C$53,IF(E6>=Assumptions!$C$55,MIN(ROUNDDOWN(Assumptions!$C$52*'Monthly Cash Flow'!E$4,0),Assumptions!$C$53),0)) -> 0 | F2: =IF(F6>Assumptions!$C$56,Assumptions!$C$53,IF(F6>=Assumptions!$C$55,MIN(ROUNDDOWN(Assumptions!$C$52*'Monthly Cash Flow'!F$4,0),Assumptions!$C$53),0)) -> 1 | G2: =IF(G6>Assumptions!$C$56,Assumptions!$C$53,IF(G6>=Assumptions!$C$55,MIN(ROUNDDOWN(Assumptions!$C$52*'Monthly Cash Flow'!G$4,0),Assumptions!$C$53),0)) -> 2 | H2: =IF(H6>Assumptions!$C$56,Assumptions!$C$53,IF(H6>=Assumptions!$C$55,MIN(ROUNDDOWN(Assumptions!$C$52*'Monthly Cash Flow'!H$4,0),Assumptions!$C$53),0)) -> 3 | I2: =IF(I6>Assumptions!$C$56,Assumptions!$C$53,IF(I6>=Assumptions!$C$55,MIN(ROUNDDOWN(Assumptions!$C$52*'Monthly Cash Flow'!I$4,0),Assumptions!$C$53),0)) -> 4 | J2: =IF(J6>Assumptions!$C$56,Assumptions!$C$53,IF(J6>=Assumptions!$C$55,MIN(ROUNDDOWN(Assumptions!$C$52*'Monthly Cash Flow'!J$4,0),Assumptions!$C$53),0)) -> 5 | K2: =IF(K6>Assumptions!$C$56,Assumptions!$C$53,IF(K6>=Assumptions!$C$55,MIN(ROUNDDOWN(Assumptions!$C$52*'Monthly Cash Flow'!K$4,0),Assumptions!$C$53),0)) -> 6 | ... O2: =IF(O6>Assumptions!$C$56,Assumptions!$C$53,IF(O6>=Assumptions!$C$55,MIN(ROUNDDOWN(Assumptions!$C$52*'Monthly Cash Flow'!O$4,0),Assumptions!$C$53),0)) -> 10 | Q2: =IF(Q6>Assumptions!$C$56,Assumptions!$C$53,IF(Q6>=Assumptions!$C$55,MIN(ROUNDDOWN(Assumptions!$C$52*'Monthly Cash Flow'!Q$4,0),Assumptions!$C$53),0)) -> 11 | R2: =IF(R6>Assumptions!$C$56,Assumptions!$C$53,IF(R6>=Assumptions!$C$55,MIN(ROUNDDOWN(Assumptions!$C$52*'Monthly Cash Flow'!R$4,0),Assumptions!$C$53),0)) -> 12 | S2: =IF(S6>Assumptions!$C$56,Assumptions!$C$53,IF(S6>=Assumptions!$C$55,MIN(ROUNDDOWN(Assumptions!$C$52*'Monthly Cash Flow'!S$4,0),Assumptions!$C$53),0)) -> 13 | T2: =IF(T6>Assumptions!$C$56,Assumptions!$C$53,IF(T6>=Assumptions!$C$55,MIN(ROUNDDOWN(Assumptions!$C$52*'Monthly Cash Flow'!T$4,0),Assumptions!$C$53),0)) -> 14 | U2: =IF(U6>Assumptions!$C$56,Assumptions!$C$53,IF(U6>=Assumptions!$C$55,MIN(ROUNDDOWN(Assumptions!$C$52*'Monthly Cash Flow'!U$4,0),Assumptions!$C$53),0)) -> 15 | V2: =IF(V6>Assumptions!$C$56,Assumptions!$C$53,IF(V6>=Assumptions!$C$55,MIN(ROUNDDOWN(Assumptions!$C$52*'Monthly Cash Flow'!V$4,0),Assumptions!$C$53),0)) -> 16 | W2: =IF(W6>Assumptions!$C$56,Assumptions!$C$53,IF(W6>=Assumptions!$C$55,MIN(ROUNDDOWN(Assumptions!$C$52*'Monthly Cash Flow'!W$4,0),Assumptions!$C$53),0)) -> 17 | X2: =IF(X6>Assumptions!$C$56,Assumptions!$C$53,IF(X6>=Assumptions!$C$55,MIN(ROUNDDOWN(Assumptions!$C$52*'Monthly Cash Flow'!X$4,0),Assumptions!$C$53),0)) -> 17 | ... AB2: =IF(AB6>Assumptions!$C$56,Assumptions!$C$53,IF(AB6>=Assumptions!$C$55,MIN(ROUNDDOWN(Assumptions!$C$52*'Monthly Cash Flow'!AB$4,0),Assumptions!$C$53),0)) -> 17 | AD2: =IF(AD6>Assumptions!$C$56,Assumptions!$C$53,IF(AD6>=Assumptions!$C$55,MIN(ROUNDDOWN(Assumptions!$C$52*'Monthly Cash Flow'!AD$4,0),Assumptions!$C$53),0)) -> 17 | AE2: =IF(AE6>Assumptions!$C$56,Assumptions!$C$53,IF(AE6>=Assumptions!$C$55,MIN(ROUNDDOWN(Assumptions!$C$52*'Monthly Cash Flow'!AE$4,0),Assumptions!$C$53),0)) -> 17 | AF2: =IF(AF6>Assumptions!$C$56,Assumptions!$C$53,IF(AF6>=Assumptions!$C$55,MIN(ROUNDDOWN(Assumptions!$C$52*'Monthly Cash Flow'!AF$4,0),Assumptions!$C$53),0)) -> 17 | AG2: =IF(AG6>Assumptions!$C$56,Assumptions!$C$53,IF(AG6>=Assumptions!$C$55,MIN(ROUNDDOWN(Assumptions!$C$52*'Monthly Cash Flow'!AG$4,0),Assumptions!$C$53),0)) -> 17 | AH2: =IF(AH6>Assumptions!$C$56,Assumptions!$C$53,IF(AH6>=Assumptions!$C$55,MIN(ROUNDDOWN(Assumptions!$C$52*'Monthly Cash Flow'!AH$4,0),Assumptions!$C$53),0)) -> 17 | AI2: =IF(AI6>Assumptions!$C$56,Assumptions!$C$53,IF(AI6>=Assumptions!$C$55,MIN(ROUNDDOWN(Assumptions!$C$52*'Monthly Cash Flow'!AI$4,0),Assumptions!$C$53),0)) -> 17 | AJ2: =IF(AJ6>Assumptions!$C$56,Assumptions!$C$53,IF(AJ6>=Assumptions!$C$55,MIN(ROUNDDOWN(Assumptions!$C$52*'Monthly Cash Flow'!AJ$4,0),Assumptions!$C$53),0)) -> 17 | AK2: =IF(AK6>Assumptions!$C$56,Assumptions!$C$53,IF(AK6>=Assumptions!$C$55,MIN(ROUNDDOWN(Assumptions!$C$52*'Monthly Cash Flow'!AK$4,0),Assumptions!$C$53),0)) -> 17 | ... AO2: =IF(AO6>Assumptions!$C$56,Assumptions!$C$53,IF(AO6>=Assumptions!$C$55,MIN(ROUNDDOWN(Assumptions!$C$52*'Monthly Cash Flow'!AO$4,0),Assumptions!$C$53),0)) -> 17 | AQ2: =IF(AQ6>Assumptions!$C$56,Assumptions!$C$53,IF(AQ6>=Assumptions!$C$55,MIN(ROUNDDOWN(Assumptions!$C$52*'Monthly Cash Flow'!AQ$4,0),Assumptions!$C$53),0)) -> 17 | AR2: =IF(AR6>Assumptions!$C$56,Assumptions!$C$53,IF(AR6>=Assumptions!$C$55,MIN(ROUNDDOWN(Assumptions!$C$52*'Monthly Cash Flow'!AR$4,0),Assumptions!$C$53),0)) -> 17 | AS2: =IF(AS6>Assumptions!$C$56,Assumptions!$C$53,IF(AS6>=Assumptions!$C$55,MIN(ROUNDDOWN(Assumptions!$C$52*'Monthly Cash Flow'!AS$4,0),Assumptions!$C$53),0)) -> 17 | AT2: =IF(AT6>Assumptions!$C$56,Assumptions!$C$53,IF(AT6>=Assumptions!$C$55,MIN(ROUNDDOWN(Assumptions!$C$52*'Monthly Cash Flow'!AT$4,0),Assumptions!$C$53),0)) -> 17 | AU2: =IF(AU6>Assumptions!$C$56,Assumptions!$C$53,IF(AU6>=Assumptions!$C$55,MIN(ROUNDDOWN(Assumptions!$C$52*'Monthly Cash Flow'!AU$4,0),Assumptions!$C$53),0)) -> 17 | AV2: =IF(AV6>Assumptions!$C$56,Assumptions!$C$53,IF(AV6>=Assumptions!$C$55,MIN(ROUNDDOWN(Assumptions!$C$52*'Monthly Cash Flow'!AV$4,0),Assumptions!$C$53),0)) -> 17 | AW2: =IF(AW6>Assumptions!$C$56,Assumptions!$C$53,IF(AW6>=Assumptions!$C$55,MIN(ROUNDDOWN(Assumptions!$C$52*'Monthly Cash Flow'!AW$4,0),Assumptions!$C$53),0)) -> 17 | AX2: =IF(AX6>Assumptions!$C$56,Assumptions!$C$53,IF(AX6>=Assumptions!$C$55,MIN(ROUNDDOWN(Assumptions!$C$52*'Monthly Cash Flow'!AX$4,0),Assumptions!$C$53),0)) -> 17 | ... BB2: =IF(BB6>Assumptions!$C$56,Assumptions!$C$53,IF(BB6>=Assumptions!$C$55,MIN(ROUNDDOWN(Assumptions!$C$52*'Monthly Cash Flow'!BB$4,0),Assumptions!$C$53),0)) -> 17 | BD2: =IF(BD6>Assumptions!$C$56,Assumptions!$C$53,IF(BD6>=Assumptions!$C$55,MIN(ROUNDDOWN(Assumptions!$C$52*'Monthly Cash Flow'!BD$4,0),Assumptions!$C$53),0)) -> 17 | BE2: =IF(BE6>Assumptions!$C$56,Assumptions!$C$53,IF(BE6>=Assumptions!$C$55,MIN(ROUNDDOWN(Assumptions!$C$52*'Monthly Cash Flow'!BE$4,0),Assumptions!$C$53),0)) -> 17 | BF2: =IF(BF6>Assumptions!$C$56,Assumptions!$C$53,IF(BF6>=Assumptions!$C$55,MIN(ROUNDDOWN(Assumptions!$C$52*'Monthly Cash Flow'!BF$4,0),Assumptions!$C$53),0)) -> 17 | BG2: =IF(BG6>Assumptions!$C$56,Assumptions!$C$53,IF(BG6>=Assumptions!$C$55,MIN(ROUNDDOWN(Assumptions!$C$52*'Monthly Cash Flow'!BG$4,0),Assumptions!$C$53),0)) -> 17 | BH2: =IF(BH6>Assumptions!$C$56,Assumptions!$C$53,IF(BH6>=Assumptions!$C$55,MIN(ROUNDDOWN(Assumptions!$C$52*'Monthly Cash Flow'!BH$4,0),Assumptions!$C$53),0)) -> 17 | BI2: =IF(BI6>Assumptions!$C$56,Assumptions!$C$53,IF(BI6>=Assumptions!$C$55,MIN(ROUNDDOWN(Assumptions!$C$52*'Monthly Cash Flow'!BI$4,0),Assumptions!$C$53),0)) -> 17 | BJ2: =IF(BJ6>Assumptions!$C$56,Assumptions!$C$53,IF(BJ6>=Assumptions!$C$55,MIN(ROUNDDOWN(Assumptions!$C$52*'Monthly Cash Flow'!BJ$4,0),Assumptions!$C$53),0)) -> 17 | BK2: =IF(BK6>Assumptions!$C$56,Assumptions!$C$53,IF(BK6>=Assumptions!$C$55,MIN(ROUNDDOWN(Assumptions!$C$52*'Monthly Cash Flow'!BK$4,0),Assumptions!$C$53),0)) -> 17 | ... BO2: =IF(BO6>Assumptions!$C$56,Assumptions!$C$53,IF(BO6>=Assumptions!$C$55,MIN(ROUNDDOWN(Assumptions!$C$52*'Monthly Cash Flow'!BO$4,0),Assumptions!$C$53),0)) -> 17 | BQ2: =IF(BQ6>Assumptions!$C$56,Assumptions!$C$53,IF(BQ6>=Assumptions!$C$55,MIN(ROUNDDOWN(Assumptions!$C$52*'Monthly Cash Flow'!BQ$4,0),Assumptions!$C$53),0)) -> 17 | BR2: =IF(BR6>Assumptions!$C$56,Assumptions!$C$53,IF(BR6>=Assumptions!$C$55,MIN(ROUNDDOWN(Assumptions!$C$52*'Monthly Cash Flow'!BR$4,0),Assumptions!$C$53),0)) -> 17 | BS2: =IF(BS6>Assumptions!$C$56,Assumptions!$C$53,IF(BS6>=Assumptions!$C$55,MIN(ROUNDDOWN(Assumptions!$C$52*'Monthly Cash Flow'!BS$4,0),Assumptions!$C$53),0)) -> 17 | BT2: =IF(BT6>Assumptions!$C$56,Assumptions!$C$53,IF(BT6>=Assumptions!$C$55,MIN(ROUNDDOWN(Assumptions!$C$52*'Monthly Cash Flow'!BT$4,0),Assumptions!$C$53),0)) -> 17 | BU2: =IF(BU6>Assumptions!$C$56,Assumptions!$C$53,IF(BU6>=Assumptions!$C$55,MIN(ROUNDDOWN(Assumptions!$C$52*'Monthly Cash Flow'!BU$4,0),Assumptions!$C$53),0)) -> 17 | BV2: =IF(BV6>Assumptions!$C$56,Assumptions!$C$53,IF(BV6>=Assumptions!$C$55,MIN(ROUNDDOWN(Assumptions!$C$52*'Monthly Cash Flow'!BV$4,0),Assumptions!$C$53),0)) -> 17 | BW2: =IF(BW6>Assumptions!$C$56,Assumptions!$C$53,IF(BW6>=Assumptions!$C$55,MIN(ROUNDDOWN(Assumptions!$C$52*'Monthly Cash Flow'!BW$4,0),Assumptions!$C$53),0)) -> 17 | BX2: =IF(BX6>Assumptions!$C$56,Assumptions!$C$53,IF(BX6>=Assumptions!$C$55,MIN(ROUNDDOWN(Assumptions!$C$52*'Monthly Cash Flow'!BX$4,0),Assumptions!$C$53),0)) -> 17 | ... CB2: =IF(CB6>Assumptions!$C$56,Assumptions!$C$53,IF(CB6>=Assumptions!$C$55,MIN(ROUNDDOWN(Assumptions!$C$52*'Monthly Cash Flow'!CB$4,0),Assumptions!$C$53),0)) -> 17 | CD2: =IF(CD6>Assumptions!$C$56,Assumptions!$C$53,IF(CD6>=Assumptions!$C$55,MIN(ROUNDDOWN(Assumptions!$C$52*'Monthly Cash Flow'!CD$4,0),Assumptions!$C$53),0)) -> 17 | CE2: =IF(CE6>Assumptions!$C$56,Assumptions!$C$53,IF(CE6>=Assumptions!$C$55,MIN(ROUNDDOWN(Assumptions!$C$52*'Monthly Cash Flow'!CE$4,0),Assumptions!$C$53),0)) -> 17 | CF2: =IF(CF6>Assumptions!$C$56,Assumptions!$C$53,IF(CF6>=Assumptions!$C$55,MIN(ROUNDDOWN(Assumptions!$C$52*'Monthly Cash Flow'!CF$4,0),Assumptions!$C$53),0)) -> 17 | CG2: =IF(CG6>Assumptions!$C$56,Assumptions!$C$53,IF(CG6>=Assumptions!$C$55,MIN(ROUNDDOWN(Assumptions!$C$52*'Monthly Cash Flow'!CG$4,0),Assumptions!$C$53),0)) -> 17 | CH2: =IF(CH6>Assumptions!$C$56,Assumptions!$C$53,IF(CH6>=Assumptions!$C$55,MIN(ROUNDDOWN(Assumptions!$C$52*'Monthly Cash Flow'!CH$4,0),Assumptions!$C$53),0)) -> 17 | CI2: =IF(CI6>Assumptions!$C$56,Assumptions!$C$53,IF(CI6>=Assumptions!$C$55,MIN(ROUNDDOWN(Assumptions!$C$52*'Monthly Cash Flow'!CI$4,0),Assumptions!$C$53),0)) -> 17 | CJ2: =IF(CJ6>Assumptions!$C$56,Assumptions!$C$53,IF(CJ6>=Assumptions!$C$55,MIN(ROUNDDOWN(Assumptions!$C$52*'Monthly Cash Flow'!CJ$4,0),Assumptions!$C$53),0)) -> 17 | CK2: =IF(CK6>Assumptions!$C$56,Assumptions!$C$53,IF(CK6>=Assumptions!$C$55,MIN(ROUNDDOWN(Assumptions!$C$52*'Monthly Cash Flow'!CK$4,0),Assumptions!$C$53),0)) -> 17 | ... CO2: =IF(CO6>Assumptions!$C$56,Assumptions!$C$53,IF(CO6>=Assumptions!$C$55,MIN(ROUNDDOWN(Assumptions!$C$52*'Monthly Cash Flow'!CO$4,0),Assumptions!$C$53),0)) -> 17
B3: % of Exterior Renovations Complete | D3: =IF(D6>=Assumptions!$C$63,100%,IF(D6<Assumptions!$C$62,0%,(D6-Assumptions!$C$62+1)/Assumptions!$C$61)) -> 0.25 | E3: =IF(E6>=Assumptions!$C$63,100%,IF(E6<Assumptions!$C$62,0%,(E6-Assumptions!$C$62+1)/Assumptions!$C$61)) -> 0.5 | F3: =IF(F6>=Assumptions!$C$63,100%,IF(F6<Assumptions!$C$62,0%,(F6-Assumptions!$C$62+1)/Assumptions!$C$61)) -> 0.75 | G3: =IF(G6>=Assumptions!$C$63,100%,IF(G6<Assumptions!$C$62,0%,(G6-Assumptions!$C$62+1)/Assumptions!$C$61)) -> 1 | H3: =IF(H6>=Assumptions!$C$63,100%,IF(H6<Assumptions!$C$62,0%,(H6-Assumptions!$C$62+1)/Assumptions!$C$61)) -> 1 | I3: =IF(I6>=Assumptions!$C$63,100%,IF(I6<Assumptions!$C$62,0%,(I6-Assumptions!$C$62+1)/Assumptions!$C$61)) -> 1 | J3: =IF(J6>=Assumptions!$C$63,100%,IF(J6<Assumptions!$C$62,0%,(J6-Assumptions!$C$62+1)/Assumptions!$C$61)) -> 1 | K3: =IF(K6>=Assumptions!$C$63,100%,IF(K6<Assumptions!$C$62,0%,(K6-Assumptions!$C$62+1)/Assumptions!$C$61)) -> 1 | ... O3: =IF(O6>=Assumptions!$C$63,100%,IF(O6<Assumptions!$C$62,0%,(O6-Assumptions!$C$62+1)/Assumptions!$C$61)) -> 1 | Q3: =IF(Q6>=Assumptions!$C$63,100%,IF(Q6<Assumptions!$C$62,0%,(Q6-Assumptions!$C$62+1)/Assumptions!$C$61)) -> 1 | R3: =IF(R6>=Assumptions!$C$63,100%,IF(R6<Assumptions!$C$62,0%,(R6-Assumptions!$C$62+1)/Assumptions!$C$61)) -> 1 | S3: =IF(S6>=Assumptions!$C$63,100%,IF(S6<Assumptions!$C$62,0%,(S6-Assumptions!$C$62+1)/Assumptions!$C$61)) -> 1 | T3: =IF(T6>=Assumptions!$C$63,100%,IF(T6<Assumptions!$C$62,0%,(T6-Assumptions!$C$62+1)/Assumptions!$C$61)) -> 1 | U3: =IF(U6>=Assumptions!$C$63,100%,IF(U6<Assumptions!$C$62,0%,(U6-Assumptions!$C$62+1)/Assumptions!$C$61)) -> 1 | V3: =IF(V6>=Assumptions!$C$63,100%,IF(V6<Assumptions!$C$62,0%,(V6-Assumptions!$C$62+1)/Assumptions!$C$61)) -> 1 | W3: =IF(W6>=Assumptions!$C$63,100%,IF(W6<Assumptions!$C$62,0%,(W6-Assumptions!$C$62+1)/Assumptions!$C$61)) -> 1 | X3: =IF(X6>=Assumptions!$C$63,100%,IF(X6<Assumptions!$C$62,0%,(X6-Assumptions!$C$62+1)/Assumptions!$C$61)) -> 1 | ... AB3: =IF(AB6>=Assumptions!$C$63,100%,IF(AB6<Assumptions!$C$62,0%,(AB6-Assumptions!$C$62+1)/Assumptions!$C$61)) -> 1 | AD3: =IF(AD6>=Assumptions!$C$63,100%,IF(AD6<Assumptions!$C$62,0%,(AD6-Assumptions!$C$62+1)/Assumptions!$C$61)) -> 1 | AE3: =IF(AE6>=Assumptions!$C$63,100%,IF(AE6<Assumptions!$C$62,0%,(AE6-Assumptions!$C$62+1)/Assumptions!$C$61)) -> 1 | AF3: =IF(AF6>=Assumptions!$C$63,100%,IF(AF6<Assumptions!$C$62,0%,(AF6-Assumptions!$C$62+1)/Assumptions!$C$61)) -> 1 | AG3: =IF(AG6>=Assumptions!$C$63,100%,IF(AG6<Assumptions!$C$62,0%,(AG6-Assumptions!$C$62+1)/Assumptions!$C$61)) -> 1 | AH3: =IF(AH6>=Assumptions!$C$63,100%,IF(AH6<Assumptions!$C$62,0%,(AH6-Assumptions!$C$62+1)/Assumptions!$C$61)) -> 1 | AI3: =IF(AI6>=Assumptions!$C$63,100%,IF(AI6<Assumptions!$C$62,0%,(AI6-Assumptions!$C$62+1)/Assumptions!$C$61)) -> 1 | AJ3: =IF(AJ6>=Assumptions!$C$63,100%,IF(AJ6<Assumptions!$C$62,0%,(AJ6-Assumptions!$C$62+1)/Assumptions!$C$61)) -> 1 | AK3: =IF(AK6>=Assumptions!$C$63,100%,IF(AK6<Assumptions!$C$62,0%,(AK6-Assumptions!$C$62+1)/Assumptions!$C$61)) -> 1 | ... AO3: =IF(AO6>=Assumptions!$C$63,100%,IF(AO6<Assumptions!$C$62,0%,(AO6-Assumptions!$C$62+1)/Assumptions!$C$61)) -> 1 | AQ3: =IF(AQ6>=Assumptions!$C$63,100%,IF(AQ6<Assumptions!$C$62,0%,(AQ6-Assumptions!$C$62+1)/Assumptions!$C$61)) -> 1 | AR3: =IF(AR6>=Assumptions!$C$63,100%,IF(AR6<Assumptions!$C$62,0%,(AR6-Assumptions!$C$62+1)/Assumptions!$C$61)) -> 1 | AS3: =IF(AS6>=Assumptions!$C$63,100%,IF(AS6<Assumptions!$C$62,0%,(AS6-Assumptions!$C$62+1)/Assumptions!$C$61)) -> 1 | AT3: =IF(AT6>=Assumptions!$C$63,100%,IF(AT6<Assumptions!$C$62,0%,(AT6-Assumptions!$C$62+1)/Assumptions!$C$61)) -> 1 | AU3: =IF(AU6>=Assumptions!$C$63,100%,IF(AU6<Assumptions!$C$62,0%,(AU6-Assumptions!$C$62+1)/Assumptions!$C$61)) -> 1 | AV3: =IF(AV6>=Assumptions!$C$63,100%,IF(AV6<Assumptions!$C$62,0%,(AV6-Assumptions!$C$62+1)/Assumptions!$C$61)) -> 1 | AW3: =IF(AW6>=Assumptions!$C$63,100%,IF(AW6<Assumptions!$C$62,0%,(AW6-Assumptions!$C$62+1)/Assumptions!$C$61)) -> 1 | AX3: =IF(AX6>=Assumptions!$C$63,100%,IF(AX6<Assumptions!$C$62,0%,(AX6-Assumptions!$C$62+1)/Assumptions!$C$61)) -> 1 | ... BB3: =IF(BB6>=Assumptions!$C$63,100%,IF(BB6<Assumptions!$C$62,0%,(BB6-Assumptions!$C$62+1)/Assumptions!$C$61)) -> 1 | BD3: =IF(BD6>=Assumptions!$C$63,100%,IF(BD6<Assumptions!$C$62,0%,(BD6-Assumptions!$C$62+1)/Assumptions!$C$61)) -> 1 | BE3: =IF(BE6>=Assumptions!$C$63,100%,IF(BE6<Assumptions!$C$62,0%,(BE6-Assumptions!$C$62+1)/Assumptions!$C$61)) -> 1 | BF3: =IF(BF6>=Assumptions!$C$63,100%,IF(BF6<Assumptions!$C$62,0%,(BF6-Assumptions!$C$62+1)/Assumptions!$C$61)) -> 1 | BG3: =IF(BG6>=Assumptions!$C$63,100%,IF(BG6<Assumptions!$C$62,0%,(BG6-Assumptions!$C$62+1)/Assumptions!$C$61)) -> 1 | BH3: =IF(BH6>=Assumptions!$C$63,100%,IF(BH6<Assumptions!$C$62,0%,(BH6-Assumptions!$C$62+1)/Assumptions!$C$61)) -> 1 | BI3: =IF(BI6>=Assumptions!$C$63,100%,IF(BI6<Assumptions!$C$62,0%,(BI6-Assumptions!$C$62+1)/Assumptions!$C$61)) -> 1 | BJ3: =IF(BJ6>=Assumptions!$C$63,100%,IF(BJ6<Assumptions!$C$62,0%,(BJ6-Assumptions!$C$62+1)/Assumptions!$C$61)) -> 1 | BK3: =IF(BK6>=Assumptions!$C$63,100%,IF(BK6<Assumptions!$C$62,0%,(BK6-Assumptions!$C$62+1)/Assumptions!$C$61)) -> 1 | ... BO3: =IF(BO6>=Assumptions!$C$63,100%,IF(BO6<Assumptions!$C$62,0%,(BO6-Assumptions!$C$62+1)/Assumptions!$C$61)) -> 1 | BQ3: =IF(BQ6>=Assumptions!$C$63,100%,IF(BQ6<Assumptions!$C$62,0%,(BQ6-Assumptions!$C$62+1)/Assumptions!$C$61)) -> 1 | BR3: =IF(BR6>=Assumptions!$C$63,100%,IF(BR6<Assumptions!$C$62,0%,(BR6-Assumptions!$C$62+1)/Assumptions!$C$61)) -> 1 | BS3: =IF(BS6>=Assumptions!$C$63,100%,IF(BS6<Assumptions!$C$62,0%,(BS6-Assumptions!$C$62+1)/Assumptions!$C$61)) -> 1 | BT3: =IF(BT6>=Assumptions!$C$63,100%,IF(BT6<Assumptions!$C$62,0%,(BT6-Assumptions!$C$62+1)/Assumptions!$C$61)) -> 1 | BU3: =IF(BU6>=Assumptions!$C$63,100%,IF(BU6<Assumptions!$C$62,0%,(BU6-Assumptions!$C$62+1)/Assumptions!$C$61)) -> 1 | BV3: =IF(BV6>=Assumptions!$C$63,100%,IF(BV6<Assumptions!$C$62,0%,(BV6-Assumptions!$C$62+1)/Assumptions!$C$61)) -> 1 | BW3: =IF(BW6>=Assumptions!$C$63,100%,IF(BW6<Assumptions!$C$62,0%,(BW6-Assumptions!$C$62+1)/Assumptions!$C$61)) -> 1 | BX3: =IF(BX6>=Assumptions!$C$63,100%,IF(BX6<Assumptions!$C$62,0%,(BX6-Assumptions!$C$62+1)/Assumptions!$C$61)) -> 1 | ... CB3: =IF(CB6>=Assumptions!$C$63,100%,IF(CB6<Assumptions!$C$62,0%,(CB6-Assumptions!$C$62+1)/Assumptions!$C$61)) -> 1 | CD3: =IF(CD6>=Assumptions!$C$63,100%,IF(CD6<Assumptions!$C$62,0%,(CD6-Assumptions!$C$62+1)/Assumptions!$C$61)) -> 1 | CE3: =IF(CE6>=Assumptions!$C$63,100%,IF(CE6<Assumptions!$C$62,0%,(CE6-Assumptions!$C$62+1)/Assumptions!$C$61)) -> 1 | CF3: =IF(CF6>=Assumptions!$C$63,100%,IF(CF6<Assumptions!$C$62,0%,(CF6-Assumptions!$C$62+1)/Assumptions!$C$61)) -> 1 | CG3: =IF(CG6>=Assumptions!$C$63,100%,IF(CG6<Assumptions!$C$62,0%,(CG6-Assumptions!$C$62+1)/Assumptions!$C$61)) -> 1 | CH3: =IF(CH6>=Assumptions!$C$63,100%,IF(CH6<Assumptions!$C$62,0%,(CH6-Assumptions!$C$62+1)/Assumptions!$C$61)) -> 1 | CI3: =IF(CI6>=Assumptions!$C$63,100%,IF(CI6<Assumptions!$C$62,0%,(CI6-Assumptions!$C$62+1)/Assumptions!$C$61)) -> 1 | CJ3: =IF(CJ6>=Assumptions!$C$63,100%,IF(CJ6<Assumptions!$C$62,0%,(CJ6-Assumptions!$C$62+1)/Assumptions!$C$61)) -> 1 | CK3: =IF(CK6>=Assumptions!$C$63,100%,IF(CK6<Assumptions!$C$62,0%,(CK6-Assumptions!$C$62+1)/Assumptions!$C$61)) -> 1 | ... CO3: =IF(CO6>=Assumptions!$C$63,100%,IF(CO6<Assumptions!$C$62,0%,(CO6-Assumptions!$C$62+1)/Assumptions!$C$61)) -> 1
B4: Renovation Start | D4: =IF(AND(D6>Assumptions!$C$55,D6<=Assumptions!$C$56),'Monthly Cash Flow'!C4+1,IF('Monthly Cash Flow'!D6=Assumptions!$C$55,1,0)) -> 0 | E4: =IF(AND(E6>Assumptions!$C$55,E6<=Assumptions!$C$56),'Monthly Cash Flow'!D4+1,IF('Monthly Cash Flow'!E6=Assumptions!$C$55,1,0)) -> 1 | F4: =IF(AND(F6>Assumptions!$C$55,F6<=Assumptions!$C$56),'Monthly Cash Flow'!E4+1,IF('Monthly Cash Flow'!F6=Assumptions!$C$55,1,0)) -> 2 | G4: =IF(AND(G6>Assumptions!$C$55,G6<=Assumptions!$C$56),'Monthly Cash Flow'!F4+1,IF('Monthly Cash Flow'!G6=Assumptions!$C$55,1,0)) -> 3 | H4: =IF(AND(H6>Assumptions!$C$55,H6<=Assumptions!$C$56),'Monthly Cash Flow'!G4+1,IF('Monthly Cash Flow'!H6=Assumptions!$C$55,1,0)) -> 4 | I4: =IF(AND(I6>Assumptions!$C$55,I6<=Assumptions!$C$56),'Monthly Cash Flow'!H4+1,IF('Monthly Cash Flow'!I6=Assumptions!$C$55,1,0)) -> 5 | J4: =IF(AND(J6>Assumptions!$C$55,J6<=Assumptions!$C$56),'Monthly Cash Flow'!I4+1,IF('Monthly Cash Flow'!J6=Assumptions!$C$55,1,0)) -> 6 | K4: =IF(AND(K6>Assumptions!$C$55,K6<=Assumptions!$C$56),'Monthly Cash Flow'!J4+1,IF('Monthly Cash Flow'!K6=Assumptions!$C$55,1,0)) -> 7 | ... O4: =IF(AND(O6>Assumptions!$C$55,O6<=Assumptions!$C$56),'Monthly Cash Flow'!N4+1,IF('Monthly Cash Flow'!O6=Assumptions!$C$55,1,0)) -> 11 | Q4: =IF(AND(Q6>Assumptions!$C$55,Q6<=Assumptions!$C$56),'Monthly Cash Flow'!O4+1,IF('Monthly Cash Flow'!Q6=Assumptions!$C$55,1,0)) -> 12 | R4: =IF(AND(R6>Assumptions!$C$55,R6<=Assumptions!$C$56),'Monthly Cash Flow'!Q4+1,IF('Monthly Cash Flow'!R6=Assumptions!$C$55,1,0)) -> 13 | S4: =IF(AND(S6>Assumptions!$C$55,S6<=Assumptions!$C$56),'Monthly Cash Flow'!R4+1,IF('Monthly Cash Flow'!S6=Assumptions!$C$55,1,0)) -> 14 | T4: =IF(AND(T6>Assumptions!$C$55,T6<=Assumptions!$C$56),'Monthly Cash Flow'!S4+1,IF('Monthly Cash Flow'!T6=Assumptions!$C$55,1,0)) -> 15 | U4: =IF(AND(U6>Assumptions!$C$55,U6<=Assumptions!$C$56),'Monthly Cash Flow'!T4+1,IF('Monthly Cash Flow'!U6=Assumptions!$C$55,1,0)) -> 16 | V4: =IF(AND(V6>Assumptions!$C$55,V6<=Assumptions!$C$56),'Monthly Cash Flow'!U4+1,IF('Monthly Cash Flow'!V6=Assumptions!$C$55,1,0)) -> 17 | W4: =IF(AND(W6>Assumptions!$C$55,W6<=Assumptions!$C$56),'Monthly Cash Flow'!V4+1,IF('Monthly Cash Flow'!W6=Assumptions!$C$55,1,0)) -> 18 | X4: =IF(AND(X6>Assumptions!$C$55,X6<=Assumptions!$C$56),'Monthly Cash Flow'!W4+1,IF('Monthly Cash Flow'!X6=Assumptions!$C$55,1,0)) -> 0 | Y4: =IF(AND(Y6>Assumptions!$C$55,Y6<=Assumptions!$C$56),'Monthly Cash Flow'!X4+1,IF('Monthly Cash Flow'!Y6=Assumptions!$C$55,1,0)) -> 0 | ... AB4: =IF(AND(AB6>Assumptions!$C$55,AB6<=Assumptions!$C$56),'Monthly Cash Flow'!AA4+1,IF('Monthly Cash Flow'!AB6=Assumptions!$C$55,1,0)) -> 0 | AD4: =IF(AND(AD6>Assumptions!$C$55,AD6<=Assumptions!$C$56),'Monthly Cash Flow'!AB4+1,IF('Monthly Cash Flow'!AD6=Assumptions!$C$55,1,0)) -> 0 | AE4: =IF(AND(AE6>Assumptions!$C$55,AE6<=Assumptions!$C$56),'Monthly Cash Flow'!AD4+1,IF('Monthly Cash Flow'!AE6=Assumptions!$C$55,1,0)) -> 0 | AF4: =IF(AND(AF6>Assumptions!$C$55,AF6<=Assumptions!$C$56),'Monthly Cash Flow'!AE4+1,IF('Monthly Cash Flow'!AF6=Assumptions!$C$55,1,0)) -> 0 | AG4: =IF(AND(AG6>Assumptions!$C$55,AG6<=Assumptions!$C$56),'Monthly Cash Flow'!AF4+1,IF('Monthly Cash Flow'!AG6=Assumptions!$C$55,1,0)) -> 0 | AH4: =IF(AND(AH6>Assumptions!$C$55,AH6<=Assumptions!$C$56),'Monthly Cash Flow'!AG4+1,IF('Monthly Cash Flow'!AH6=Assumptions!$C$55,1,0)) -> 0 | AI4: =IF(AND(AI6>Assumptions!$C$55,AI6<=Assumptions!$C$56),'Monthly Cash Flow'!AH4+1,IF('Monthly Cash Flow'!AI6=Assumptions!$C$55,1,0)) -> 0 | AJ4: =IF(AND(AJ6>Assumptions!$C$55,AJ6<=Assumptions!$C$56),'Monthly Cash Flow'!AI4+1,IF('Monthly Cash Flow'!AJ6=Assumptions!$C$55,1,0)) -> 0 | AK4: =IF(AND(AK6>Assumptions!$C$55,AK6<=Assumptions!$C$56),'Monthly Cash Flow'!AJ4+1,IF('Monthly Cash Flow'!AK6=Assumptions!$C$55,1,0)) -> 0 | AL4: =IF(AND(AL6>Assumptions!$C$55,AL6<=Assumptions!$C$56),'Monthly Cash Flow'!AK4+1,IF('Monthly Cash Flow'!AL6=Assumptions!$C$55,1,0)) -> 0 | ... AO4: =IF(AND(AO6>Assumptions!$C$55,AO6<=Assumptions!$C$56),'Monthly Cash Flow'!AN4+1,IF('Monthly Cash Flow'!AO6=Assumptions!$C$55,1,0)) -> 0 | AQ4: =IF(AND(AQ6>Assumptions!$C$55,AQ6<=Assumptions!$C$56),'Monthly Cash Flow'!AO4+1,IF('Monthly Cash Flow'!AQ6=Assumptions!$C$55,1,0)) -> 0 | AR4: =IF(AND(AR6>Assumptions!$C$55,AR6<=Assumptions!$C$56),'Monthly Cash Flow'!AQ4+1,IF('Monthly Cash Flow'!AR6=Assumptions!$C$55,1,0)) -> 0 | AS4: =IF(AND(AS6>Assumptions!$C$55,AS6<=Assumptions!$C$56),'Monthly Cash Flow'!AR4+1,IF('Monthly Cash Flow'!AS6=Assumptions!$C$55,1,0)) -> 0 | AT4: =IF(AND(AT6>Assumptions!$C$55,AT6<=Assumptions!$C$56),'Monthly Cash Flow'!AS4+1,IF('Monthly Cash Flow'!AT6=Assumptions!$C$55,1,0)) -> 0 | AU4: =IF(AND(AU6>Assumptions!$C$55,AU6<=Assumptions!$C$56),'Monthly Cash Flow'!AT4+1,IF('Monthly Cash Flow'!AU6=Assumptions!$C$55,1,0)) -> 0 | AV4: =IF(AND(AV6>Assumptions!$C$55,AV6<=Assumptions!$C$56),'Monthly Cash Flow'!AU4+1,IF('Monthly Cash Flow'!AV6=Assumptions!$C$55,1,0)) -> 0 | AW4: =IF(AND(AW6>Assumptions!$C$55,AW6<=Assumptions!$C$56),'Monthly Cash Flow'!AV4+1,IF('Monthly Cash Flow'!AW6=Assumptions!$C$55,1,0)) -> 0 | AX4: =IF(AND(AX6>Assumptions!$C$55,AX6<=Assumptions!$C$56),'Monthly Cash Flow'!AW4+1,IF('Monthly Cash Flow'!AX6=Assumptions!$C$55,1,0)) -> 0 | AY4: =IF(AND(AY6>Assumptions!$C$55,AY6<=Assumptions!$C$56),'Monthly Cash Flow'!AX4+1,IF('Monthly Cash Flow'!AY6=Assumptions!$C$55,1,0)) -> 0 | ... BB4: =IF(AND(BB6>Assumptions!$C$55,BB6<=Assumptions!$C$56),'Monthly Cash Flow'!BA4+1,IF('Monthly Cash Flow'!BB6=Assumptions!$C$55,1,0)) -> 0 | BD4: =IF(AND(BD6>Assumptions!$C$55,BD6<=Assumptions!$C$56),'Monthly Cash Flow'!BB4+1,IF('Monthly Cash Flow'!BD6=Assumptions!$C$55,1,0)) -> 0 | BE4: =IF(AND(BE6>Assumptions!$C$55,BE6<=Assumptions!$C$56),'Monthly Cash Flow'!BD4+1,IF('Monthly Cash Flow'!BE6=Assumptions!$C$55,1,0)) -> 0 | BF4: =IF(AND(BF6>Assumptions!$C$55,BF6<=Assumptions!$C$56),'Monthly Cash Flow'!BE4+1,IF('Monthly Cash Flow'!BF6=Assumptions!$C$55,1,0)) -> 0 | BG4: =IF(AND(BG6>Assumptions!$C$55,BG6<=Assumptions!$C$56),'Monthly Cash Flow'!BF4+1,IF('Monthly Cash Flow'!BG6=Assumptions!$C$55,1,0)) -> 0 | BH4: =IF(AND(BH6>Assumptions!$C$55,BH6<=Assumptions!$C$56),'Monthly Cash Flow'!BG4+1,IF('Monthly Cash Flow'!BH6=Assumptions!$C$55,1,0)) -> 0 | BI4: =IF(AND(BI6>Assumptions!$C$55,BI6<=Assumptions!$C$56),'Monthly Cash Flow'!BH4+1,IF('Monthly Cash Flow'!BI6=Assumptions!$C$55,1,0)) -> 0 | BJ4: =IF(AND(BJ6>Assumptions!$C$55,BJ6<=Assumptions!$C$56),'Monthly Cash Flow'!BI4+1,IF('Monthly Cash Flow'!BJ6=Assumptions!$C$55,1,0)) -> 0 | BK4: =IF(AND(BK6>Assumptions!$C$55,BK6<=Assumptions!$C$56),'Monthly Cash Flow'!BJ4+1,IF('Monthly Cash Flow'!BK6=Assumptions!$C$55,1,0)) -> 0 | BL4: =IF(AND(BL6>Assumptions!$C$55,BL6<=Assumptions!$C$56),'Monthly Cash Flow'!BK4+1,IF('Monthly Cash Flow'!BL6=Assumptions!$C$55,1,0)) -> 0 | ... BO4: =IF(AND(BO6>Assumptions!$C$55,BO6<=Assumptions!$C$56),'Monthly Cash Flow'!BN4+1,IF('Monthly Cash Flow'!BO6=Assumptions!$C$55,1,0)) -> 0 | BQ4: =IF(AND(BQ6>Assumptions!$C$55,BQ6<=Assumptions!$C$56),'Monthly Cash Flow'!BO4+1,IF('Monthly Cash Flow'!BQ6=Assumptions!$C$55,1,0)) -> 0 | BR4: =IF(AND(BR6>Assumptions!$C$55,BR6<=Assumptions!$C$56),'Monthly Cash Flow'!BQ4+1,IF('Monthly Cash Flow'!BR6=Assumptions!$C$55,1,0)) -> 0 | BS4: =IF(AND(BS6>Assumptions!$C$55,BS6<=Assumptions!$C$56),'Monthly Cash Flow'!BR4+1,IF('Monthly Cash Flow'!BS6=Assumptions!$C$55,1,0)) -> 0 | BT4: =IF(AND(BT6>Assumptions!$C$55,BT6<=Assumptions!$C$56),'Monthly Cash Flow'!BS4+1,IF('Monthly Cash Flow'!BT6=Assumptions!$C$55,1,0)) -> 0 | BU4: =IF(AND(BU6>Assumptions!$C$55,BU6<=Assumptions!$C$56),'Monthly Cash Flow'!BT4+1,IF('Monthly Cash Flow'!BU6=Assumptions!$C$55,1,0)) -> 0 | BV4: =IF(AND(BV6>Assumptions!$C$55,BV6<=Assumptions!$C$56),'Monthly Cash Flow'!BU4+1,IF('Monthly Cash Flow'!BV6=Assumptions!$C$55,1,0)) -> 0 | BW4: =IF(AND(BW6>Assumptions!$C$55,BW6<=Assumptions!$C$56),'Monthly Cash Flow'!BV4+1,IF('Monthly Cash Flow'!BW6=Assumptions!$C$55,1,0)) -> 0 | BX4: =IF(AND(BX6>Assumptions!$C$55,BX6<=Assumptions!$C$56),'Monthly Cash Flow'!BW4+1,IF('Monthly Cash Flow'!BX6=Assumptions!$C$55,1,0)) -> 0 | BY4: =IF(AND(BY6>Assumptions!$C$55,BY6<=Assumptions!$C$56),'Monthly Cash Flow'!BX4+1,IF('Monthly Cash Flow'!BY6=Assumptions!$C$55,1,0)) -> 0 | ... CB4: =IF(AND(CB6>Assumptions!$C$55,CB6<=Assumptions!$C$56),'Monthly Cash Flow'!CA4+1,IF('Monthly Cash Flow'!CB6=Assumptions!$C$55,1,0)) -> 0 | CD4: =IF(AND(CD6>Assumptions!$C$55,CD6<=Assumptions!$C$56),'Monthly Cash Flow'!CB4+1,IF('Monthly Cash Flow'!CD6=Assumptions!$C$55,1,0)) -> 0 | CE4: =IF(AND(CE6>Assumptions!$C$55,CE6<=Assumptions!$C$56),'Monthly Cash Flow'!CD4+1,IF('Monthly Cash Flow'!CE6=Assumptions!$C$55,1,0)) -> 0 | CF4: =IF(AND(CF6>Assumptions!$C$55,CF6<=Assumptions!$C$56),'Monthly Cash Flow'!CE4+1,IF('Monthly Cash Flow'!CF6=Assumptions!$C$55,1,0)) -> 0 | CG4: =IF(AND(CG6>Assumptions!$C$55,CG6<=Assumptions!$C$56),'Monthly Cash Flow'!CF4+1,IF('Monthly Cash Flow'!CG6=Assumptions!$C$55,1,0)) -> 0 | CH4: =IF(AND(CH6>Assumptions!$C$55,CH6<=Assumptions!$C$56),'Monthly Cash Flow'!CG4+1,IF('Monthly Cash Flow'!CH6=Assumptions!$C$55,1,0)) -> 0 | CI4: =IF(AND(CI6>Assumptions!$C$55,CI6<=Assumptions!$C$56),'Monthly Cash Flow'!CH4+1,IF('Monthly Cash Flow'!CI6=Assumptions!$C$55,1,0)) -> 0 | CJ4: =IF(AND(CJ6>Assumptions!$C$55,CJ6<=Assumptions!$C$56),'Monthly Cash Flow'!CI4+1,IF('Monthly Cash Flow'!CJ6=Assumptions!$C$55,1,0)) -> 0 | CK4: =IF(AND(CK6>Assumptions!$C$55,CK6<=Assumptions!$C$56),'Monthly Cash Flow'!CJ4+1,IF('Monthly Cash Flow'!CK6=Assumptions!$C$55,1,0)) -> 0 | CL4: =IF(AND(CL6>Assumptions!$C$55,CL6<=Assumptions!$C$56),'Monthly Cash Flow'!CK4+1,IF('Monthly Cash Flow'!CL6=Assumptions!$C$55,1,0)) -> 0 | ... CO4: =IF(AND(CO6>Assumptions!$C$55,CO6<=Assumptions!$C$56),'Monthly Cash Flow'!CN4+1,IF('Monthly Cash Flow'!CO6=Assumptions!$C$55,1,0)) -> 0
P5: 1 | AB5: =AB10/Q10 -> 1.022893 | AC5: 2 | AP5: 3 | BC5: 4 | BP5: 5 | CC5: 6 | CP5: 7
C6: 0 | D6: 1 | E6: 2 | F6: 3 | G6: 4 | H6: 5 | I6: 6 | J6: 7 | K6: 8 | L6: 9 | M6: 10 | N6: 11 | O6: 12 | Q6: 13 | R6: 14 | S6: 15 | T6: 16 | U6: 17 | V6: 18 | W6: 19 | X6: 20 | Y6: 21 | Z6: 22 | AA6: 23 | AB6: 24 | AD6: 25 | AE6: 26 | AF6: 27 | AG6: 28 | AH6: 29 | AI6: 30 | AJ6: 31 | AK6: 32 | AL6: 33 | AM6: 34 | AN6: 35 | AO6: 36 | AQ6: 37 | AR6: 38 | AS6: 39 | AT6: 40 | AU6: 41 | AV6: 42 | AW6: 43 | AX6: 44 | AY6: 45 | AZ6: 46 | BA6: 47 | BB6: 48 | BD6: 49 | BE6: 50 | BF6: 51 | BG6: 52 | BH6: 53 | BI6: 54 | BJ6: 55 | BK6: 56 | BL6: 57 | BM6: 58 | BN6: 59 | BO6: 60 | BQ6: 61 | BR6: 62 | BS6: 63 | BT6: 64 | BU6: 65 | BV6: 66 | BW6: 67 | BX6: 68 | BY6: 69 | BZ6: 70 | CA6: 71 | CB6: 72 | CD6: 73 | CE6: 74 | CF6: 75 | CG6: 76 | CH6: 77 | CI6: 78 | CJ6: 79 | CK6: 80 | CL6: 81 | CM6: 82 | CN6: 83 | CO6: 84
C7: At Close | D7: =Assumptions!C7 -> 46204 | E7: =EDATE(D7,1) -> 46235 | F7: =EDATE(E7,1) -> 46266 | G7: =EDATE(F7,1) -> 46296 | H7: =EDATE(G7,1) -> 46327 | I7: =EDATE(H7,1) -> 46357 | J7: =EDATE(I7,1) -> 46388 | K7: =EDATE(J7,1) -> 46419 | L7: =EDATE(K7,1) -> 46447 | ... O7: =EDATE(N7,1) -> 46539 | P7: Total | Q7: =EDATE(O7,1) -> 46569 | R7: =EDATE(Q7,1) -> 46600 | S7: =EDATE(R7,1) -> 46631 | T7: =EDATE(S7,1) -> 46661 | U7: =EDATE(T7,1) -> 46692 | V7: =EDATE(U7,1) -> 46722 | W7: =EDATE(V7,1) -> 46753 | X7: =EDATE(W7,1) -> 46784 | Y7: =EDATE(X7,1) -> 46813 | ... AB7: =EDATE(AA7,1) -> 46905 | AC7: Total | AD7: =EDATE(AB7,1) -> 46935 | AE7: =EDATE(AD7,1) -> 46966 | AF7: =EDATE(AE7,1) -> 46997 | AG7: =EDATE(AF7,1) -> 47027 | AH7: =EDATE(AG7,1) -> 47058 | AI7: =EDATE(AH7,1) -> 47088 | AJ7: =EDATE(AI7,1) -> 47119 | AK7: =EDATE(AJ7,1) -> 47150 | AL7: =EDATE(AK7,1) -> 47178 | ... AO7: =EDATE(AN7,1) -> 47270 | AP7: Total | AQ7: =EDATE(AO7,1) -> 47300 | AR7: =EDATE(AQ7,1) -> 47331 | AS7: =EDATE(AR7,1) -> 47362 | AT7: =EDATE(AS7,1) -> 47392 | AU7: =EDATE(AT7,1) -> 47423 | AV7: =EDATE(AU7,1) -> 47453 | AW7: =EDATE(AV7,1) -> 47484 | AX7: =EDATE(AW7,1) -> 47515 | AY7: =EDATE(AX7,1) -> 47543 | ... BB7: =EDATE(BA7,1) -> 47635 | BC7: Total | BD7: =EDATE(BB7,1) -> 47665 | BE7: =EDATE(BD7,1) -> 47696 | BF7: =EDATE(BE7,1) -> 47727 | BG7: =EDATE(BF7,1) -> 47757 | BH7: =EDATE(BG7,1) -> 47788 | BI7: =EDATE(BH7,1) -> 47818 | BJ7: =EDATE(BI7,1) -> 47849 | BK7: =EDATE(BJ7,1) -> 47880 | BL7: =EDATE(BK7,1) -> 47908 | ... BO7: =EDATE(BN7,1) -> 48000 | BP7: Total | BQ7: =EDATE(BO7,1) -> 48030 | BR7: =EDATE(BQ7,1) -> 48061 | BS7: =EDATE(BR7,1) -> 48092 | BT7: =EDATE(BS7,1) -> 48122 | BU7: =EDATE(BT7,1) -> 48153 | BV7: =EDATE(BU7,1) -> 48183 | BW7: =EDATE(BV7,1) -> 48214 | BX7: =EDATE(BW7,1) -> 48245 | BY7: =EDATE(BX7,1) -> 48274 | ... CB7: =EDATE(CA7,1) -> 48366 | CC7: Total | CD7: =EDATE(CB7,1) -> 48396 | CE7: =EDATE(CD7,1) -> 48427 | CF7: =EDATE(CE7,1) -> 48458 | CG7: =EDATE(CF7,1) -> 48488 | CH7: =EDATE(CG7,1) -> 48519 | CI7: =EDATE(CH7,1) -> 48549 | CJ7: =EDATE(CI7,1) -> 48580 | CK7: =EDATE(CJ7,1) -> 48611 | CL7: =EDATE(CK7,1) -> 48639 | ... CO7: =EDATE(CN7,1) -> 48731 | CP7: Total
B8: Income
B10: Gross Potential Rent | D10: ='Unit Mix'!$I$19*(1+Assumptions!$H$3)^('Monthly Cash Flow'!D6/12) -> 34753.806 | E10: ='Unit Mix'!$I$19*(1+Assumptions!$H$3)^('Monthly Cash Flow'!E6/12) -> 34782.635 | F10: ='Unit Mix'!$I$19*(1+Assumptions!$H$3)^('Monthly Cash Flow'!F6/12) -> 34811.489 | G10: ='Unit Mix'!$I$19*(1+Assumptions!$H$3)^('Monthly Cash Flow'!G6/12) -> 34840.366 | H10: ='Unit Mix'!$I$19*(1+Assumptions!$H$3)^('Monthly Cash Flow'!H6/12) -> 34869.268 | I10: ='Unit Mix'!$I$19*(1+Assumptions!$H$3)^('Monthly Cash Flow'!I6/12) -> 34898.193 | J10: ='Unit Mix'!$I$19*(1+Assumptions!$H$3)^('Monthly Cash Flow'!J6/12) -> 34927.142 | K10: ='Unit Mix'!$I$19*(1+Assumptions!$H$3)^('Monthly Cash Flow'!K6/12) -> 34956.116 | ... O10: ='Unit Mix'!$I$19*(1+Assumptions!$H$3)^('Monthly Cash Flow'!O6/12) -> 35072.25 | P10: =SUM(D10:O10) -> 418953.69 | Q10: =$O$10*(1+Assumptions!$I$3)^(('Monthly Cash Flow'!Q6-12)/12) -> 35144.493 | R10: =$O$10*(1+Assumptions!$I$3)^(('Monthly Cash Flow'!R6-12)/12) -> 35216.885 | S10: =$O$10*(1+Assumptions!$I$3)^(('Monthly Cash Flow'!S6-12)/12) -> 35289.426 | T10: =$O$10*(1+Assumptions!$I$3)^(('Monthly Cash Flow'!T6-12)/12) -> 35362.116 | U10: =$O$10*(1+Assumptions!$I$3)^(('Monthly Cash Flow'!U6-12)/12) -> 35434.957 | V10: =$O$10*(1+Assumptions!$I$3)^(('Monthly Cash Flow'!V6-12)/12) -> 35507.947 | W10: =$O$10*(1+Assumptions!$I$3)^(('Monthly Cash Flow'!W6-12)/12) -> 35581.087 | X10: =$O$10*(1+Assumptions!$I$3)^(('Monthly Cash Flow'!X6-12)/12) -> 35654.379 | ... AB10: =$O$10*(1+Assumptions!$I$3)^(('Monthly Cash Flow'!AB6-12)/12) -> 35949.056 | AC10: =SUM(Q10:AB10) -> 426544.74 | AD10: =$AB$10*(1+Assumptions!$J$3)^(('Monthly Cash Flow'!AD6-24)/12) -> 36023.105 | AE10: =$AB$10*(1+Assumptions!$J$3)^(('Monthly Cash Flow'!AE6-24)/12) -> 36097.307 | AF10: =$AB$10*(1+Assumptions!$J$3)^(('Monthly Cash Flow'!AF6-24)/12) -> 36171.662 | AG10: =$AB$10*(1+Assumptions!$J$3)^(('Monthly Cash Flow'!AG6-24)/12) -> 36246.169 | AH10: =$AB$10*(1+Assumptions!$J$3)^(('Monthly Cash Flow'!AH6-24)/12) -> 36320.831 | AI10: =$AB$10*(1+Assumptions!$J$3)^(('Monthly Cash Flow'!AI6-24)/12) -> 36395.646 | AJ10: =$AB$10*(1+Assumptions!$J$3)^(('Monthly Cash Flow'!AJ6-24)/12) -> 36470.615 | AK10: =$AB$10*(1+Assumptions!$J$3)^(('Monthly Cash Flow'!AK6-24)/12) -> 36545.738 | ... AO10: =$AB$10*(1+Assumptions!$J$3)^(('Monthly Cash Flow'!AO6-24)/12) -> 36847.783 | AP10: =SUM(AD10:AO10) -> 437208.36 | AQ10: =$AO$10*(1+Assumptions!$K$3)^(('Monthly Cash Flow'!AQ6-36)/12) -> 36923.683 | AR10: =$AO$10*(1+Assumptions!$K$3)^(('Monthly Cash Flow'!AR6-36)/12) -> 36999.74 | AS10: =$AO$10*(1+Assumptions!$K$3)^(('Monthly Cash Flow'!AS6-36)/12) -> 37075.953 | AT10: =$AO$10*(1+Assumptions!$K$3)^(('Monthly Cash Flow'!AT6-36)/12) -> 37152.324 | AU10: =$AO$10*(1+Assumptions!$K$3)^(('Monthly Cash Flow'!AU6-36)/12) -> 37228.851 | AV10: =$AO$10*(1+Assumptions!$K$3)^(('Monthly Cash Flow'!AV6-36)/12) -> 37305.537 | AW10: =$AO$10*(1+Assumptions!$K$3)^(('Monthly Cash Flow'!AW6-36)/12) -> 37382.38 | AX10: =$AO$10*(1+Assumptions!$K$3)^(('Monthly Cash Flow'!AX6-36)/12) -> 37459.382 | ... BB10: =$AO$10*(1+Assumptions!$K$3)^(('Monthly Cash Flow'!BB6-36)/12) -> 37768.977 | BC10: =SUM(AQ10:BB10) -> 448138.57 | BD10: =$BB$10*(1+Assumptions!$L$3)^(('Monthly Cash Flow'!BD6-48)/12) -> 37831.356 | BE10: =$BB$10*(1+Assumptions!$L$3)^(('Monthly Cash Flow'!BE6-48)/12) -> 37893.837 | BF10: =$BB$10*(1+Assumptions!$L$3)^(('Monthly Cash Flow'!BF6-48)/12) -> 37956.422 | BG10: =$BB$10*(1+Assumptions!$L$3)^(('Monthly Cash Flow'!BG6-48)/12) -> 38019.11 | BH10: =$BB$10*(1+Assumptions!$L$3)^(('Monthly Cash Flow'!BH6-48)/12) -> 38081.902 | BI10: =$BB$10*(1+Assumptions!$L$3)^(('Monthly Cash Flow'!BI6-48)/12) -> 38144.797 | BJ10: =$BB$10*(1+Assumptions!$L$3)^(('Monthly Cash Flow'!BJ6-48)/12) -> 38207.796 | BK10: =$BB$10*(1+Assumptions!$L$3)^(('Monthly Cash Flow'!BK6-48)/12) -> 38270.9 | ... BO10: =$BB$10*(1+Assumptions!$L$3)^(('Monthly Cash Flow'!BO6-48)/12) -> 38524.357 | BP10: =SUM(BD10:BO10) -> 458122.84 | BQ10: =$BO$10*(1+Assumptions!$M$3)^(('Monthly Cash Flow'!BQ6-60)/12) -> 38587.983 | BR10: =$BO$10*(1+Assumptions!$M$3)^(('Monthly Cash Flow'!BR6-60)/12) -> 38651.714 | BS10: =$BO$10*(1+Assumptions!$M$3)^(('Monthly Cash Flow'!BS6-60)/12) -> 38715.551 | BT10: =$BO$10*(1+Assumptions!$M$3)^(('Monthly Cash Flow'!BT6-60)/12) -> 38779.492 | BU10: =$BO$10*(1+Assumptions!$M$3)^(('Monthly Cash Flow'!BU6-60)/12) -> 38843.54 | BV10: =$BO$10*(1+Assumptions!$M$3)^(('Monthly Cash Flow'!BV6-60)/12) -> 38907.693 | BW10: =$BO$10*(1+Assumptions!$M$3)^(('Monthly Cash Flow'!BW6-60)/12) -> 38971.952 | BX10: =$BO$10*(1+Assumptions!$M$3)^(('Monthly Cash Flow'!BX6-60)/12) -> 39036.318 | ... CB10: =$BO$10*(1+Assumptions!$M$3)^(('Monthly Cash Flow'!CB6-60)/12) -> 39294.844 | CC10: =SUM(BQ10:CB10) -> 467285.3 | CD10: =$CB$10*(1+Assumptions!$N$3)^(('Monthly Cash Flow'!CD6-72)/12) -> 39359.743 | CE10: =$CB$10*(1+Assumptions!$N$3)^(('Monthly Cash Flow'!CE6-72)/12) -> 39424.748 | CF10: =$CB$10*(1+Assumptions!$N$3)^(('Monthly Cash Flow'!CF6-72)/12) -> 39489.862 | CG10: =$CB$10*(1+Assumptions!$N$3)^(('Monthly Cash Flow'!CG6-72)/12) -> 39555.082 | CH10: =$CB$10*(1+Assumptions!$N$3)^(('Monthly Cash Flow'!CH6-72)/12) -> 39620.411 | CI10: =$CB$10*(1+Assumptions!$N$3)^(('Monthly Cash Flow'!CI6-72)/12) -> 39685.847 | CJ10: =$CB$10*(1+Assumptions!$N$3)^(('Monthly Cash Flow'!CJ6-72)/12) -> 39751.391 | CK10: =$CB$10*(1+Assumptions!$N$3)^(('Monthly Cash Flow'!CK6-72)/12) -> 39817.044 | ... CO10: =$CB$10*(1+Assumptions!$N$3)^(('Monthly Cash Flow'!CO6-72)/12) -> 40080.741 | CP10: =SUM(CD10:CO10) -> 476631
B11: Loss to Lease | D11: =D10-D12 -> 8838.8057 | E11: =E10-E12 -> 8846.1378 | F11: =F10-F12 -> 8334.3806 | G11: =G10-G12 -> 7821.7682 | H11: =H10-H12 -> 7308.2997 | I11: =I10-I12 -> 6793.9738 | J11: =J10-J12 -> 6278.7897 | K11: =K10-K12 -> 5762.7461 | ... O11: =O10-O12 -> 3689.9563 | P11: =SUM(D11:O11) -> 77858.225 | Q11: =Q10-Q12 -> 3269.7549 | R11: =R10-R12 -> 2757.1872 | S11: =S10-S12 -> 2310.4255 | T11: =T10-T12 -> 1794.8121 | U11: =U10-U12 -> 1277.0648 | V11: =V10-V12 -> 757.17694 | W11: =W10-W12 -> 235.14187 | X11: =X10-X12 -> 235.62622 | ... AB11: =AB10-AB12 -> 237.57364 | AC11: =SUM(Q11:AB11) -> 13584.558 | AD11: =AD10-AD12 -> 384.60167 | AE11: =AE10-AE12 -> 385.39389 | AF11: =AF10-AF12 -> 459.74843 | AG11: =AG10-AG12 -> 460.69544 | AH11: =AH10-AH12 -> 461.64439 | AI11: =AI10-AI12 -> 462.5953 | AJ11: =AJ10-AJ12 -> 463.54817 | AK11: =AK10-AK12 -> 464.50301 | ... AO11: =AO10-AO12 -> 468.34205 | AP11: =SUM(AD11:AO11) -> 5410.3301 | AQ11: =AQ10-AQ12 -> 614.46671 | AR11: =AR10-AR12 -> 615.73241 | AS11: =AS10-AS12 -> 691.94582 | AT11: =AT10-AT12 -> 693.37111 | AU11: =AU10-AU12 -> 694.79934 | AV11: =AV10-AV12 -> 696.23052 | AW11: =AW10-AW12 -> 697.66464 | AX11: =AX10-AX12 -> 699.10171 | ... BB11: =BB10-BB12 -> 704.87968 | BC11: =SUM(AQ11:BB11) -> 8214.1492 | BD11: =BD10-BD12 -> 834.65901 | BE11: =BE10-BE12 -> 836.03751 | BF11: =BF10-BF12 -> 898.62227 | BG11: =BG10-BG12 -> 900.10642 | BH11: =BH10-BH12 -> 901.59301 | BI11: =BI10-BI12 -> 903.08207 | BJ11: =BJ10-BJ12 -> 904.57358 | BK11: =BK10-BK12 -> 906.06756 | ... BO11: =BO10-BO12 -> 912.06818 | BP11: =SUM(BD11:BO11) -> 10724.001 | BQ11: =BQ10-BQ12 -> 1027.5522 | BR11: =BR10-BR12 -> 1029.2493 | BS11: =BS10-BS12 -> 1093.0857 | BT11: =BT10-BT12 -> 1094.891 | BU11: =BU10-BU12 -> 1096.6993 | BV11: =BV10-BV12 -> 1098.5106 | BW11: =BW10-BW12 -> 1100.3249 | BX11: =BX10-BX12 -> 1102.1422 | ... CB11: =CB10-CB12 -> 1109.4414 | CC11: =SUM(BQ11:CB11) -> 13069.257 | CD11: =CD10-CD12 -> 1224.3032 | CE11: =CE10-CE12 -> 1226.3253 | CF11: =CF10-CF12 -> 1291.4384 | CG11: =CG10-CG12 -> 1293.5714 | CH11: =CH10-CH12 -> 1295.7078 | CI11: =CI10-CI12 -> 1297.8478 | CJ11: =CJ10-CJ12 -> 1299.9913 | CK11: =CK10-CK12 -> 1302.1383 | ... CO11: =CO10-CO12 -> 1310.762 | CP11: =SUM(CD11:CO11) -> 15461.418
