Workbook
Name _off3: [10]Marina!#REF!
Name _off4: [10]Marina!#REF!
Name _off5: [10]Marina!#REF!
Name _off6: [10]Marina!#REF!
Name _ret1: #REF!
Name _ret2: #REF!
Name _ret3: #REF!
Name _ret4: #REF!
Name _ret5: #REF!
Name _ret6: #REF!
Name _sa1: #REF!
Name _sa2: #REF!
Name _sa3: #REF!
Name _sa4: #REF!
Name _sa5: #REF!
Name _sa6: #REF!
Name ArgusInput: [12]ArgusRaw.Primary!$A$1:$EZ$100
Name ArgusInput.New: [12]ArgusRaw.Secondary!$A$1:$EZ$100
Name Budget.AnalystReport.Rows: #REF!
Name Budget.BudgetPeriods.Columns: #REF!
Name Budget.ColumnHeadings.Row: #REF!
Name Budget.HideColumns.Row: #REF!
Name Budget.HideRows.Column: #REF!
Name Budget.RowOrderBy.Column: #REF!
Name Budget.RowOrderByDescription.Column: #REF!
Name Budget.Total.Column: #REF!
Name Budget.WBCol.Column: #REF!
Name Budget.WBStatus.Column: #REF!
Name Case_A: '[14]PRO FORMA'!#REF!
Name CAT_Com: '[15]PF Base 5 yr'!$B$93:$E$97
Name Choices_Wrapper: #N/A
Name Choices_Wrapper5: #N/A
Name cnsld2: [10]consolsum!#REF!
Name cnsld3: [10]consolsum!#REF!
Name cnsld4: [10]consolsum!#REF!
Name cost1: #REF!
Name CostInflation: [12]Assumptions!$F$15
Name Cur_QTD_Total_Revenue: #REF!
Name Date_Acquisition: [12]Assumptions!$C$20
Name Date_AmortStart1: [12]Assumptions!$C$38
Name Date_AmortStart2: [12]Assumptions!$D$38
Name Date_CostsPricing: [12]Assumptions!$F$13
Name Date_PreDevEnd: [12]Assumptions!$C$21
Name Date_Refi: [12]Assumptions!$C$25
Name Date_Sale: [12]Assumptions!$C$26
Name Date_SaleParcel: [12]Assumptions!$C$27
Name Date_Stabilization: [12]Assumptions!$C$23
Name Description: #REF!
Name DevFeeTarget: '[12]Dev Costs'!$G$109
Name EntryCapRt: [12]Assumptions!$C$13
Name ExitCapRt: [12]Assumptions!$C$14
Name FileVersion: [12]Assumptions!$C$9
Name FinFeeTarget: '[12]Dev Costs'!$G$118
Name Hello: #N/A
Name Hello5: #N/A
Name hotl1: #REF!
Name hotl2: #REF!
Name hotl3: #REF!
Name hotl4: #REF!
Name hotl5: #REF!

Sheet Assumptions
B1: CLARENDON - LAND+HOME, AMENITY+HOTEL DEVELOPMENT - ASSUMPTIONS
B2: OVERALL ASSUMPTIONS
B4: General | E4: Debt Financing | F4: LAND + HOME | G4: AMENITY + HOTEL | I4: Sub-Debt/ Equity Financing | K4: LAND + HOME | L4: AMENITY + HOTEL | N4: Land & Infrastructure
B5: Development Start Date (Yr 0) | C5: 45658 | E5: Origination Year | F5: 2024 | G5: 2026 | I5: Pref Accrual Rate | K5: 0.1 | L5: 0.1 | P5: Acres | Q5: Value
B6: Development Start Year | C6: =YEAR(C5) -> 2025 | E6: Original Term (Years) | F6: 3 | G6: 3 | I6: EB-5 Interest Rate (Debt+1/5) | K6: =F8+0.015 -> 0.135 | L6: =G8+0.015 -> 0.135 | N6: Total Land | P6: =P7+P8 -> 319 | Q6: =Q7+Q8 -> 22000000
B7: Fiscal Year Start Month | C7: =MONTH(C5) -> 1 | E7: Underwritten LTC | F7: 0.6 | G7: 0.77 | I7: EB-5 Origination Fee | K7: 0.01 | L7: =K7 -> 0.01 | N7: RESI | P7: 240 | Q7: 15000000
B8: Repayment Waterfall | E8: Interest Rate | F8: 0.12 | G8: =F8 -> 0.12 | I8: EB-5 Exit Fee | K8: 0.01 | L8: =K8 -> 0.01 | N8: AMENITY + HOTEL | P8: 79 | Q8: 7000000
B9: Loan | E9: Debt Placement & Origination Fee | F9: 0.035 | G9: =F9 -> 0.035 | I9: Bridge Loan Placement Fee | K9: 0.02 | L9: N/A | N9: Infrastructure Cost | Q9: 15000000
B10: Preferred Return | E10: 1 Year Extension Fee | F10: =0.005*4 -> 0.02 | I10: Bridge Loan Interest Rate | K10: 0.15 | L10: N/A
B11: Capital Return | E11: Financing Cost Gross-up | F11: 0.242 | G11: 0.26317942 | I11: JV GP Promote Split | K11: 0.4 | L11: 0.4
F12: ='Proforma L+H'!V156-'Proforma L+H'!U156 -> -3436770.5 | G12: ='Proforma A+H'!W189-'Proforma A+H'!X189 -> -600699.11
B14: LAND + HOME ASSUMPTIONS
B16: Build / Sale Cost | E16: Unit Mix | J16: Unit Sales
B17: Vertical Construction Cost psft | C17: =850*C18 -> 850 | F17: Avg Size | G17: PPSF | H17: Escalation | J17: Sales Price Scalar | M17: 1
B18: Vertical Construction Costs Scalar | C18: 1 | E18: Homesites | F18: 3500 | G18: 1750 | H18: 0.1 | J18: Net Profit % | M18: 0.2
B19: Cost of Sale - RE Fees | C19: 0.045 | E19: Village | F19: 4500 | G19: 1650 | H19: 0.075 | J19: Phantom Tax Rate | M19: 0.3
B20: Real Estate Taxes (Annual) / mils | C20: =10000/39 -> 256.41026 | E20: Cottages | F20: 2500 | G20: 1850 | H20: 0.075
B23: AMENITY + HOTEL ASSUMPTIONS
B25: Hotel Details | E25: Hotel Guest Rooms | K25: Build Cost
B26: Start Date | C26: 46053 | F26: Lodge Rooms | G26: Villa/Cabin | H26: Cottages | I26: Auton. Tents | K26: Vertical Construction Costs Scalar | N26: ='Returns A+H'!L14 -> 1
B27: Member Dues / year / unit | C27: 15000 | E27: Guest Rooms | F27: 20 | G27: 24 | H27: 24 | I27: 12 | K27: Real Estate Taxes (Annual) / mils | N27: ='Proforma Resi'!C269 -> 256
B28: Loan Interest Rate | C28: 0.03 | E28: SQFT | F28: 500 | G28: 750 | H28: 1250 | I28: 625
B29: Loan Origination Fees | C29: 0 | E29: Sales Price / SF | F29: 0 | G29: 2500 | H29: 2250 | I29: 0
B30: Disposition Year | C30: 7 | E30: Average Daily Rate | F30: 1175 | G30: 1800 | H30: 3125 | I30: 850
B31: Terminal Cap Rate | C31: 0.065 | E31: Average Sales Price | F31: =F28*F29 -> 0 | G31: =G28*G29 -> 1875000 | H31: =H28*H29 -> 2812500 | I31: =I28*I29 -> 0
B32: Selling Costs | C32: 0.05 | E32: Sales Price Escalation | F32: 0.05 | G32: 0.1 | H32: 0.1 | I32: 0.05
B33: Hold Period | C33: 132 | E33: % Rooms for Sale | F33: 0 | G33: =5/6 -> 0.83333333 | H33: 1 | I33: 0
B34: Hotel Room Rent Growth Rate | C34: 0.03
B35: Hotel Days | C35: 365
B36: Hotel Rooms Operating Cost | C36: =35%-F33*15% -> 0.35
B37: Condo Owner Revenue Split | C37: 0.5
F38: 1 | G38: 2 | H38: 3 | I38: 4 | J38: 5 | K38: 6 | L38: 7 | M38: 8 | N38: 9 | O38: 10 | P38: 11 | Q38: 12
B39: Bar Details | F39: 44562 | G39: =F39+31 -> 44593 | H39: =G39+31 -> 44624 | I39: =H39+31 -> 44655 | J39: =I39+31 -> 44686 | K39: =J39+31 -> 44717 | L39: =K39+31 -> 44748 | M39: =L39+31 -> 44779 | N39: =M39+31 -> 44810 | ... Q39: =P39+31 -> 44903 | R39: Avg
B40: Start Date | C40: 46753 | E40: Seasonal Occupancy - Hotel | F40: 0.75 | G40: 0.75 | H40: 0.65 | I40: 0.3 | J40: 0.3 | K40: 0.55 | L40: 0.65 | M40: 0.55 | N40: 0.5 | O40: 0.3 | P40: 0.2 | Q40: 0.55 | R40: =AVERAGE(F40:Q40) -> 0.50416667
B41: Available room/nights | C41: =(F27+G27)*C35 -> 16060 | E41: Conference Center Occupancy | F41: 0.25 | G41: 0.25 | H41: 0.25 | I41: 0.5 | J41: 0.75 | K41: 1 | L41: 1 | M41: 1 | N41: 0.75 | O41: 0.5 | P41: 0.25 | Q41: 0.25 | R41: =AVERAGE(F41:Q41) -> 0.5625
B42: Paid Room Nights | C42: =C41*R40 -> 8096.9167 | E42: Adj. Conf Center Occupancy | F42: =IF(OR(F38<MONTH($C$63),F38>$C$64),0,F41) -> 0.25 | G42: =IF(OR(G38<MONTH($C$63),G38>$C$64),0,G41) -> 0.25 | H42: =IF(OR(H38<MONTH($C$63),H38>$C$64),0,H41) -> 0.25 | I42: =IF(OR(I38<MONTH($C$63),I38>$C$64),0,I41) -> 0.5 | J42: =IF(OR(J38<MONTH($C$63),J38>$C$64),0,J41) -> 0.75 | K42: =IF(OR(K38<MONTH($C$63),K38>$C$64),0,K41) -> 1 | L42: =IF(OR(L38<MONTH($C$63),L38>$C$64),0,L41) -> 1 | M42: =IF(OR(M38<MONTH($C$63),M38>$C$64),0,M41) -> 1 | ... Q42: =IF(OR(Q38<MONTH($C$63),Q38>$C$64),0,Q41) -> 0.25 | R42: =AVERAGE(F42:Q42) -> 0.5625
B43: Bar Revenue (% of Room Rev) | C43: 0.2
B44: Bar COS (% of Bar Rev) | C44: 0.75 | F44: 1 | G44: =F44+1 -> 2 | H44: =G44+1 -> 3 | I44: =H44+1 -> 4 | J44: =I44+1 -> 5 | K44: =J44+1 -> 6 | L44: =K44+1 -> 7 | M44: =L44+1 -> 8 | N44: =M44+1 -> 9 | O44: =N44+1 -> 10
F45: =EDATE(C5,12) -> 46023 | G45: =EDATE(F45,12) -> 46388 | H45: =EDATE(G45,12) -> 46753 | I45: =EDATE(H45,12) -> 47119 | J45: =EDATE(I45,12) -> 47484 | K45: =EDATE(J45,12) -> 47849 | L45: =EDATE(K45,12) -> 48214 | M45: =EDATE(L45,12) -> 48580 | N45: =EDATE(M45,12) -> 48945 | O45: =EDATE(N45,12) -> 49310 | P45: Total Rooms | Q45: Condos
B46: Spa / Wellness Center Details | E46: Conf Center Rental Rates | F46: =Assumptions!$C$60 -> 50000 | G46: =F46*(1+$C$61) -> 51500 | H46: =G46*(1+$C$61) -> 53045 | I46: =H46*(1+$C$61) -> 54636.35 | J46: =I46*(1+$C$61) -> 56275.44 | K46: =J46*(1+$C$61) -> 57963.704 | L46: =K46*(1+$C$61) -> 59702.615 | M46: =L46*(1+$C$61) -> 61493.693 | N46: =M46*(1+$C$61) -> 63338.504 | O46: =N46*(1+$C$61) -> 65238.659
B47: Start Date | C47: 46753 | E47: Avg Daily Hotel Rates - Lodge Rooms | F47: =Assumptions!$F$30 -> 1175 | G47: =F47*(1+$C$34) -> 1210.25 | H47: =G47*(1+$C$34) -> 1246.5575 | I47: =H47*(1+$C$34) -> 1283.9542 | J47: =I47*(1+$C$34) -> 1322.4729 | K47: =J47*(1+$C$34) -> 1362.147 | L47: =K47*(1+$C$34) -> 1403.0114 | M47: =L47*(1+$C$34) -> 1445.1018 | N47: =M47*(1+$C$34) -> 1488.4548 | O47: =N47*(1+$C$34) -> 1533.1085 | P47: =F27 -> 20 | Q47: =P47*F33 -> 0
B48: Available room/nights | C48: =(F27+G27)*C35 -> 16060 | E48: Avg Daily Hotel Rates - Villa/ Cabin | F48: =Assumptions!$G$30 -> 1800 | G48: =F48*(1+$C$34) -> 1854 | H48: =G48*(1+$C$34) -> 1909.62 | I48: =H48*(1+$C$34) -> 1966.9086 | J48: =I48*(1+$C$34) -> 2025.9159 | K48: =J48*(1+$C$34) -> 2086.6933 | L48: =K48*(1+$C$34) -> 2149.2941 | M48: =L48*(1+$C$34) -> 2213.773 | N48: =M48*(1+$C$34) -> 2280.1861 | O48: =N48*(1+$C$34) -> 2348.5917 | P48: =G27 -> 24 | Q48: =P48*G33 -> 20
B49: Paid Room Nights | C49: =C48*R40 -> 8096.9167 | E49: Avg Daily Hotel Rates - Cottages | F49: =Assumptions!$H$30 -> 3125 | G49: =F49*(1+$C$34) -> 3218.75 | H49: =G49*(1+$C$34) -> 3315.3125 | I49: =H49*(1+$C$34) -> 3414.7719 | J49: =I49*(1+$C$34) -> 3517.215 | K49: =J49*(1+$C$34) -> 3622.7315 | L49: =K49*(1+$C$34) -> 3731.4134 | M49: =L49*(1+$C$34) -> 3843.3558 | N49: =M49*(1+$C$34) -> 3958.6565 | O49: =N49*(1+$C$34) -> 4077.4162 | P49: =H27 -> 24 | Q49: =P49*H33 -> 24
B50: Spa / Wellness Center Revenue (% of Room Rev) | C50: 0.05 | E50: Avg Daily Hotel Rates - Auton. Tents | F50: =I30 -> 850 | G50: =F50*(1+$C$34) -> 875.5 | H50: =G50*(1+$C$34) -> 901.765 | I50: =H50*(1+$C$34) -> 928.81795 | J50: =I50*(1+$C$34) -> 956.68249 | K50: =J50*(1+$C$34) -> 985.38296 | L50: =K50*(1+$C$34) -> 1014.9445 | M50: =L50*(1+$C$34) -> 1045.3928 | N50: =M50*(1+$C$34) -> 1076.7546 | O50: =N50*(1+$C$34) -> 1109.0572 | P50: =I27 -> 12 | Q50: =P50*I33 -> 0
E51: Avg Daily Hotel Rates - Total | F51: =SUMPRODUCT(F47:F50,$P$47:$P$50,F56:F59) -> 0 | G51: =SUMPRODUCT(G47:G50,$P$47:$P$50,G56:G59) -> 25338 | H51: =SUMPRODUCT(H47:H50,$P$47:$P$50,H56:H59) -> 26098.14 | I51: =SUMPRODUCT(I47:I50,$P$47:$P$50,I56:I59) -> 109272.7 | J51: =SUMPRODUCT(J47:J50,$P$47:$P$50,J56:J59) -> 170964.79 | K51: =SUMPRODUCT(K47:K50,$P$47:$P$50,K56:K59) -> 176093.73 | L51: =SUMPRODUCT(L47:L50,$P$47:$P$50,L56:L59) -> 181376.54 | M51: =SUMPRODUCT(M47:M50,$P$47:$P$50,M56:M59) -> 186817.84 | ... O51: =SUMPRODUCT(O47:O50,$P$47:$P$50,O56:O59) -> 198195.05 | P51: =SUM(P47:P50) -> 80 | Q51: =SUM(Q47:Q50) -> 44
B52: Spa / Wellness Center COS (% Spa Revenue) | C52: 0.25 | E52: Avg Daily Rates - Villa/ Cabin Condo | F52: =F48*$P48*F57 -> 0 | G52: =G48*$P48*G57 -> 14832 | H52: =H48*$P48*H57 -> 15276.96 | I52: =I48*$P48*I57 -> 31470.538 | J52: =J48*$P48*J57 -> 48621.981 | K52: =K48*$P48*K57 -> 50080.64 | L52: =L48*$P48*L57 -> 51583.059 | M52: =M48*$P48*M57 -> 53130.551 | ... O52: =O48*$P48*O57 -> 56366.202
E53: Avg Daily Rates - Cottages Condo | F53: =F49*$P49*F58 -> 0 | G53: =G49*$P49*G58 -> 0 | H53: =H49*$P49*H58 -> 0 | I53: =I49*$P49*I58 -> 40977.262 | J53: =J49*$P49*J58 -> 84413.161 | K53: =K49*$P49*K58 -> 86945.556 | L53: =L49*$P49*L58 -> 89553.922 | M53: =M49*$P49*M58 -> 92240.54 | ... O53: =O49*$P49*O58 -> 97857.989
B54: Restaurant / Event Center
B55: Start Date | C55: 46753 | E55: Availability
B56: Available room/nights | C56: =(F27+G27)*C35 -> 16060 | E56: Lodge Rooms | F56: 0 | G56: =SUM('Proforma A+H'!$G6:H6)/'Proforma A+H'!$T6 -> 0 | H56: 0 | I56: =SUM('Proforma A+H'!$G6:J6)/'Proforma A+H'!$T6 -> 1 | J56: =SUM('Proforma A+H'!$G6:K6)/'Proforma A+H'!$T6 -> 1 | K56: {=SUM('Proforma A+H'!$G6:K6/'Proforma A+H'!$T6)} -> 1 | L56: {=SUM('Proforma A+H'!$G6:L6/'Proforma A+H'!$T6)} -> 1 | M56: {=SUM('Proforma A+H'!$G6:M6/'Proforma A+H'!$T6)} -> 1 | N56: {=SUM('Proforma A+H'!$G6:N6/'Proforma A+H'!$T6)} -> 1 | O56: {=SUM('Proforma A+H'!$G6:O6/'Proforma A+H'!$T6)} -> 1
B57: Paid Room Nights | C57: =C56*R40 -> 8096.9167 | E57: Villa/Cabin | F57: 0 | G57: =SUM('Proforma A+H'!$G7:I7)/'Proforma A+H'!$T7 -> 0.33333333 | H57: =SUM('Proforma A+H'!$G7:I7)/'Proforma A+H'!$T7 -> 0.33333333 | I57: =SUM('Proforma A+H'!$G7:J7)/'Proforma A+H'!$T7 -> 0.66666667 | J57: =SUM('Proforma A+H'!$G7:K7)/'Proforma A+H'!$T7 -> 1 | K57: =SUM('Proforma A+H'!$G7:L7)/'Proforma A+H'!$T7 -> 1 | L57: =SUM('Proforma A+H'!$G7:M7)/'Proforma A+H'!$T7 -> 1 | M57: =SUM('Proforma A+H'!$G7:N7)/'Proforma A+H'!$T7 -> 1 | N57: =SUM('Proforma A+H'!$G7:O7)/'Proforma A+H'!$T7 -> 1 | O57: =SUM('Proforma A+H'!$G7:P7)/'Proforma A+H'!$T7 -> 1
B58: F&B Revenue (% Rooms Revenue) | C58: 0.27 | E58: Cottages | F58: 0 | G58: =SUM('Proforma A+H'!$G8:H8)/'Proforma A+H'!$T8 -> 0 | H58: =SUM('Proforma A+H'!$G8:I8)/'Proforma A+H'!$T8 -> 0 | I58: =SUM('Proforma A+H'!$G8:J8)/'Proforma A+H'!$T8 -> 0.5 | J58: =SUM('Proforma A+H'!$G8:K8)/'Proforma A+H'!$T8 -> 1 | K58: =SUM('Proforma A+H'!$G8:L8)/'Proforma A+H'!$T8 -> 1 | L58: =SUM('Proforma A+H'!$G8:M8)/'Proforma A+H'!$T8 -> 1 | M58: =SUM('Proforma A+H'!$G8:N8)/'Proforma A+H'!$T8 -> 1 | N58: =SUM('Proforma A+H'!$G8:O8)/'Proforma A+H'!$T8 -> 1 | O58: =SUM('Proforma A+H'!$G8:P8)/'Proforma A+H'!$T8 -> 1
B59: F&B COS (% F&B Revenue) | C59: 0.9 | E59: Auton. Tents | F59: 0 | G59: =SUM('Proforma A+H'!$G9:H9)/'Proforma A+H'!$T9 -> 1 | H59: =SUM('Proforma A+H'!$G9:I9)/'Proforma A+H'!$T9 -> 1 | I59: =SUM('Proforma A+H'!$G9:J9)/'Proforma A+H'!$T9 -> 1 | J59: =SUM('Proforma A+H'!$G9:K9)/'Proforma A+H'!$T9 -> 1 | K59: {=SUM('Proforma A+H'!$G9:K9/'Proforma A+H'!$T9)} -> 1 | L59: {=SUM('Proforma A+H'!$G9:L9/'Proforma A+H'!$T9)} -> 1 | M59: {=SUM('Proforma A+H'!$G9:M9/'Proforma A+H'!$T9)} -> 1 | N59: {=SUM('Proforma A+H'!$G9:N9/'Proforma A+H'!$T9)} -> 1 | O59: {=SUM('Proforma A+H'!$G9:O9/'Proforma A+H'!$T9)} -> 1
B60: Event Center Rental Rates | C60: 50000 | E60: Total Rooms | F60: =SUMPRODUCT(F56:F59,$P47:$P50) -> 0 | G60: =SUMPRODUCT(G56:G59,$P47:$P50) -> 20 | H60: =SUMPRODUCT(H56:H59,$P47:$P50) -> 20 | I60: =SUMPRODUCT(I56:I59,$P47:$P50) -> 60 | J60: =SUMPRODUCT(J56:J59,$P47:$P50) -> 80 | K60: =SUMPRODUCT(K56:K59,$P47:$P50) -> 80 | L60: =SUMPRODUCT(L56:L59,$P47:$P50) -> 80 | M60: =SUMPRODUCT(M56:M59,$P47:$P50) -> 80 | ... O60: =SUMPRODUCT(O56:O59,$P47:$P50) -> 80
B61: Event Center Rent Growth Rate | C61: 0.03
B62: Daily/ Weekend Rental Schedule | C62: 1
B63: Event Rental Start | C63: 47119
B64: Event Rental Finish | C64: 47483
B65: Event Rental Days | C65: {=IF(C62=1,SUMPRODUCT(--(WEEKDAY(ROW(INDIRECT(C63&":"&C64)),2)>5)),C64-C63)} -> 104
B66: Months | C66: =(YEAR(C64)-YEAR(C63))*12+(MONTH(C64)-MONTH(C63)+1) -> 12
B67: F&B Commission | C67: 0.1
B68: Events COS | C68: 40000
B70: Minor Operating Departments
B71: MOD Revenue (% Room Revenue) | C71: 0 | E71: BMR to handle all recreation ops…consider adding a commission for booking
B72: MOD COS (% MOD Revenue) | C72: 0
B74: Undistributed OpEx (% Total Revenue) | E74: Stuart
B75: Admin & General Ops | C75: 0.09 | E75: 0.16
B76: Sales & Marketing | C76: 0.05 | E76: 0.06
B77: POMEC | C77: 0.08 | E77: 0.09
B78: Credit Card Comissions | C78: 0.025 | E78: 0.025
B80: Non-Operating Expense (% Total Revenue)
B81: Operator management fee | C81: 0.025 | E81: 0.025
B82: Operator marketing fee | C82: 0.01 | E82: 0.015
B83: Annual Property Tax | C83: 25000 | E83: 25000
B84: Insurance | C84: 0.01 | E84: 0.016
NJ91: 0
B105: 1 | C105: Weekend
B106: 0 | C106: Daily

Sheet Exhibits
B4: CLARENDON - OVERALL DEVELOPMENT: PROFORMA | H4: =B4 -> CLARENDON - OVERALL DEVELOPMENT: PROFORMA | N4: CLARENDON - OVERALL DEVELOPMENT: PROFORMA
B5: PROFORMA - SOURCES & USES SUMMARY | H5: PROFORMA - SOURCES & USES PRE-REVENUE | N5: PROFORMA - BUSINESS CASE ANALYSIS
B6: SOURCES | C6: $ | D6: $/SF | E6: Per Home | F6: % Total | H6: =B6 -> SOURCES | I6: Pre-EB5 | J6: Post EB-5 Closing | L6: % Total | O6: $ | P6: % Total
B7: =B41 -> MTN ORIGINS - PURSUIT CAPITAL | C7: =C41+C74 -> 1500000 | F7: =C7/$C$18 -> 0.0016951519 | H7: =B7 -> MTN ORIGINS - PURSUIT CAPITAL | I7: =C7 -> 1500000 | J7: =C7 -> 1500000 | L7: =SUM(J7:K7)/$J$18 -> 0.0065615802 | N7: =B13 -> LAND SALE TO AMENITY | O7: =O40 -> 15000000 | P7: =O7/$O$12 -> 0.022856343
B8: =B42 -> JV - EQUITY CAPITAL | C8: =C42+C75 -> 10000000 | F8: =C8/$C$18 -> 0.011301013 | H8: =B8 -> JV - EQUITY CAPITAL | I8: =C8 -> 10000000 | J8: =C8 -> 10000000 | L8: =SUM(J8:K8)/$J$18 -> 0.043743868 | N8: =B14 -> PRESALE REVENUES | O8: =O41 -> 81794306 | P8: =O8/$O$12 -> 0.12463458
B9: =B43 -> JV BRIDGE LOAN | C9: =C43 -> 15000000 | F9: =C9/$C$18 -> 0.016951519 | H9: =B9 -> JV BRIDGE LOAN | I9: =C9 -> 15000000 | L9: =SUM(J9:K9)/$J$18 -> 0 | N9: =B15 -> UNIT SALES | O9: =O42+O73 -> 4.0967444e+08 | P9: =O9/$O$12 -> 0.62424396
B10: =B44 -> SELLER FINANCE | C10: =C44 -> 0 | F10: =C10/$C$18 -> 0 | H10: =B10 -> SELLER FINANCE | I10: =C10 -> 0 | L10: =SUM(J10:K10)/$J$18 -> 0 | N10: =B16 -> TOTAL NET OPERATING INCOME (NOI) | O10: =O72 -> 30073583 | P10: =O10/$O$12 -> 0.045824809
B11: =B45 -> EB5 - MEZZ DEBT | C11: =C45+C76 -> 49600000 | F11: =C11/$C$18 -> 0.056053023 | H11: =B11 -> EB5 - MEZZ DEBT | J11: =C11 -> 49600000 | L11: =SUM(J11:K11)/$J$18 -> 0.21696958 | N11: =B17 -> HOTEL SALE PROCEEDS / DISPOSITION | O11: =O74 -> 1.1973065e+08 | P11: =O11/$O$12 -> 0.18244031
B12: =B46 -> DEV LOAN | C12: =C46+C77 -> 1.5250347e+08 | F12: =C12/$C$18 -> 0.17234437 | H12: =B12 -> DEV LOAN | J12: =C12 -> 1.5250347e+08 | L12: =SUM(J12:K12)/$J$18 -> 0.66710917 | N12: TOTAL REVENUE | O12: =SUM(O7:O11) -> 6.5627297e+08 | P12: =O12/$O$12 -> 1
B13: =B47 -> LAND SALE TO AMENITY | C13: =C47 -> 15000000 | F13: =C13/$C$18 -> 0.016951519 | H13: =B13 -> LAND SALE TO AMENITY | J13: =C13 -> 15000000 | L13: =SUM(J13:K13)/$J$18 -> 0.065615802
B14: =B48 -> PRESALE REVENUES | C14: =C48 -> 81794306 | F14: =C14/$C$18 -> 0.09243585 | N14: =B21 -> LAND & PROJECT ACQUISITION | O14: =C21 -> 33977750 | P14: =O14/$O$25 -> 0.070704279
B15: =B49 -> UNIT SALES | C15: =C49+C79 -> 4.0967444e+08 | F15: =C15/$C$18 -> 0.46297361 | N15: =B22 -> HARD COSTS - SITE, RESTORATION & INFRASTRUCTURE | O15: =C22 -> 20734437 | P15: =O15/$O$25 -> 0.043146277
B16: =B78 -> TOTAL NET OPERATING INCOME (NOI) | C16: =C78 -> 30073583 | F16: =C16/$C$18 -> 0.033986195 | N16: =B23 -> TOTAL VERTICAL CONSTRUCTION COSTS | O16: =C23 -> 2.7232005e+08 | P16: =O16/$O$25 -> 0.56667062
B17: =B80 -> HOTEL SALE PROCEEDS / DISPOSITION | C17: =C80 -> 1.1973065e+08 | F17: =C17/$C$18 -> 0.13530776 | N17: =B24 -> SOFT COSTS PROFESSIONALS - FINAL ENTITLEMENTS & SITE INFRA. | O17: =C24 -> 13754560 | P17: =O17/$O$25 -> 0.028621856
B18: TOTAL SOURCES | C18: =SUM(C7:C17) -> 8.8487644e+08 | F18: =C18/$C$18 -> 1 | H18: =B18 -> TOTAL SOURCES | I18: =SUM(I7:I17) -> 26500000 | J18: =SUM(J7:J17) -> 2.2860347e+08 | L18: =I18/$I$18 -> 1 | N18: =B25 -> SOFT COSTS PROFESSIONALS - HOMES | O18: =C25 -> 6141551.6 | P18: =O18/$O$25 -> 0.012779951
N19: =B26 -> SOFT COSTS - SALES | O19: =C26-O24 -> 1050000 | P19: =O19/$O$25 -> 0.0021849443
B20: USES | C20: $ | D20: $/SF | E20: Per Home | F20: % Total | H20: =B20 -> USES | I20: $ | L20: % Total | N20: =B27 -> SOFT COSTS - TAXES AND INSURANCE | O20: =C27 -> 1694303.5 | P20: =O20/$O$25 -> 0.003525675
B21: =B53 -> LAND & PROJECT ACQUISITION | C21: =C53+C84 -> 33977750 | F21: =C21/$C$33 -> 0.038398299 | H21: =B21 -> LAND & PROJECT ACQUISITION | I21: =I53+I84 -> 33977750 | L21: =I21/$I$33 -> 0.14863182 | N21: =B28 -> SOFT COSTS - MUNICIPALITY FEES | O21: =C28 -> 2334431.8 | P21: =O21/$O$25 -> 0.0048577177
B22: =B54 -> HARD COSTS - SITE, RESTORATION & INFRASTRUCTURE | C22: =C54+C86 -> 20734437 | F22: =C22/$C$33 -> 0.023432014 | H22: =B22 -> HARD COSTS - SITE, RESTORATION & INFRASTRUCTURE | I22: =I54+I86 -> 13660311 | L22: =I22/$I$33 -> 0.059755485 | N22: =B29 -> DEVELOPMENT FEES | O22: =C29 -> 13294099 | P22: =O22/$O$25 -> 0.027663683
B23: =B85 -> TOTAL VERTICAL CONSTRUCTION COSTS | C23: =C55+C85 -> 2.7232005e+08 | F23: =C23/$C$33 -> 0.30774924 | H23: =B23 -> TOTAL VERTICAL CONSTRUCTION COSTS | I23: =I55+I85 -> 1.0096407e+08 | L23: =I23/$I$33 -> 0.4416559 | N23: FINANCING COSTS | O23: =O54+O85 -> 87157632 | P23: =O23/$O$25 -> 0.18136626
B24: =B56 -> SOFT COSTS PROFESSIONALS - FINAL ENTITLEMENTS & SITE INFRA. | C24: =C56+C87 -> 13754560 | F24: =C24/$C$33 -> 0.015544046 | H24: =B24 -> SOFT COSTS PROFESSIONALS - FINAL ENTITLEMENTS & SITE INFRA. | I24: =I56+I87 -> 11260236 | L24: =I24/$I$33 -> 0.049256626 | N24: POST SALE COSTS | O24: =O55+O86 -> 28102626 | P24: =O24/$O$25 -> 0.058478736
B25: =B57 -> SOFT COSTS PROFESSIONALS - HOMES | C25: =C57 -> 6141551.6 | F25: =C25/$C$33 -> 0.0069405753 | H25: =B25 -> SOFT COSTS PROFESSIONALS - HOMES | I25: =I57 -> 1162353.1 | L25: =I25/$I$33 -> 0.0050845822 | N25: TOTAL COSTS | O25: =SUM(O14:O24) -> 4.8056144e+08 | P25: =O25/$O$25 -> 1
B26: =B58 -> SOFT COSTS - SALES | C26: =C58+C88 -> 29152626 | F26: =C26/$C$33 -> 0.03294542 | H26: =B26 -> SOFT COSTS - SALES | I26: =I58+I88 -> 1375506.2 | L26: =I26/$I$33 -> 0.0060169964
B27: =B59 -> SOFT COSTS - TAXES AND INSURANCE | C27: =C59+C89 -> 1694303.5 | F27: =C27/$C$33 -> 0.0019147345 | H27: =B27 -> SOFT COSTS - TAXES AND INSURANCE | I27: =I59+I89 -> 686279.03 | L27: =I27/$I$33 -> 0.0030020499 | N27: NET PROFIT | O27: =O12-O25 -> 1.7571153e+08 | P27: =O27/O12 -> 0.26774153
B28: =B60 -> SOFT COSTS - MUNICIPALITY FEES | C28: =C60+C90 -> 2334431.8 | F28: =C28/$C$33 -> 0.0026381444 | H28: =B28 -> SOFT COSTS - MUNICIPALITY FEES | I28: =I60+I90 -> 473003.67 | L28: =I28/$I$33 -> 0.002069101
B29: =B61 -> DEVELOPMENT FEES | C29: =C61+C91 -> 13294099 | F29: =C29/$C$33 -> 0.015023679 | H29: =B29 -> DEVELOPMENT FEES | I29: =I61+I91 -> 6049088.5 | L29: =I29/$I$33 -> 0.026461053
B30: =B62 -> FINANCING COSTS & REPAYMENT | C30: =C62+C92 -> 2.6017864e+08 | F30: =C30/$C$33 -> 0.29402821 | H30: =B30 -> FINANCING COSTS & REPAYMENT | I30: =I62+I92 -> 49683122 | L30: =I30/$I$33 -> 0.21733319
B31: EB-5 SINKING FUND | C31: =C63+C93 -> 49600000 | F31: =C31/$C$33 -> 0.056053023 | L31: =I31/$I$33 -> 0
B32: =B64 -> DISTRIBUTIONS | C32: =C64+C94 -> 1.81694e+08 | F32: =C32/$C$33 -> 0.20533262 | H32: WORKING CAPITAL | I32: =I33-SUM(I21:I30) -> 9311749 | L32: =I32/$I$33 -> 0.040733192
B33: TOTAL USES | C33: =SUM(C21:C32) -> 8.8487644e+08 | F33: =C33/$C$33 -> 1 | H33: =B33 -> TOTAL USES | I33: =J18 -> 2.2860347e+08 | L33: =I33/$I$33 -> 1
F34: =C34/$C$33 -> 0
N36: CLARENDON - RESI DEVELOPMENT: PROFORMA
N37: PROFORMA - BUSINESS CASE ANALYSIS
B38: CLARENDON - RESI DEVELOPMENT: PROFORMA | H38: =B38 -> CLARENDON - RESI DEVELOPMENT: PROFORMA | O38: $ | P38: % Total
B39: PROFORMA - SOURCES & USES SUMMARY | D39: ='Proforma L+H'!$D$17 -> 158750 | E39: ='Proforma L+H'!$R$16 -> 45 | H39: PROFORMA - SOURCES & USES PRE-REVENUE (Year 0-1)
B40: SOURCES | C40: $ | D40: $/SF | E40: Per Home | F40: % Total | H40: =B40 -> SOURCES | I40: $ | J40: $/SF | K40: Per Home | L40: % Total | N40: =B47 -> LAND SALE TO AMENITY | O40: =C47 -> 15000000 | P40: =O40/$O$43 -> 0.040316553
B41: ='Proforma L+H'!B229 -> MTN ORIGINS - PURSUIT CAPITAL | C41: ='Proforma L+H'!R229 -> 1500000 | D41: =C41/'Proforma L+H'!$D$17 -> 9.4488189 | E41: =C41/'Proforma L+H'!$R$16 -> 33333.333 | F41: =C41/$C$50 -> 0.0032024503 | H41: =B41 -> MTN ORIGINS - PURSUIT CAPITAL | I41: =C41 -> 1500000 | J41: =I41/$D$39 -> 9.4488189 | K41: =I41/$E$39 -> 33333.333 | L41: =I41/$I$50 -> 0.013472764 | N41: =B48 -> PRESALE REVENUES | O41: =C48 -> 81794306 | P41: =O41/$O$43 -> 0.2198443
B42: ='Proforma L+H'!B230 -> JV - EQUITY CAPITAL | C42: ='Proforma L+H'!R230 -> 10000000 | D42: =C42/'Proforma L+H'!$D$17 -> 62.992126 | E42: =C42/'Proforma L+H'!$R$16 -> 222222.22 | F42: =C42/$C$50 -> 0.021349668 | H42: =B42 -> JV - EQUITY CAPITAL | I42: =C42 -> 10000000 | J42: =I42/$D$39 -> 62.992126 | K42: =I42/$E$39 -> 222222.22 | L42: =I42/$I$50 -> 0.089818426 | N42: =B49 -> UNIT SALES | O42: =C49 -> 2.7526131e+08 | P42: =O42/$O$43 -> 0.73983915
B43: ='Proforma L+H'!B231 -> JV BRIDGE LOAN | C43: ='Proforma L+H'!R231 -> 15000000 | D43: =C43/'Proforma L+H'!$D$17 -> 94.488189 | E43: =C43/'Proforma L+H'!$R$16 -> 333333.33 | F43: =C43/$C$50 -> 0.032024503 | H43: =B43 -> JV BRIDGE LOAN | I43: =C43 -> 15000000 | J43: =I43/$D$39 -> 94.488189 | K43: =I43/$E$39 -> 333333.33 | L43: =I43/$I$50 -> 0.13472764 | N43: TOTAL REVENUE | O43: =SUM(O40:O42) -> 3.7205562e+08 | P43: =O43/$O$43 -> 1
B44: ='Proforma L+H'!B232 -> SELLER FINANCE | C44: ='Proforma L+H'!R232 -> 0 | D44: =C44/'Proforma L+H'!$D$17 -> 0 | E44: =C44/'Proforma L+H'!$R$16 -> 0 | F44: =C44/$C$50 -> 0 | H44: =B44 -> SELLER FINANCE | I44: =C44 -> 0 | J44: =I44/$D$39 -> 0 | K44: =I44/$E$39 -> 0 | L44: =I44/$I$50 -> 0
B45: ='Proforma L+H'!B233 -> EB5 - MEZZ DEBT | C45: ='Proforma L+H'!R233 -> 20800000 | D45: =C45/'Proforma L+H'!$D$17 -> 131.02362 | E45: =C45/'Proforma L+H'!$R$16 -> 462222.22 | F45: =C45/$C$50 -> 0.04440731 | H45: =B45 -> EB5 - MEZZ DEBT | I45: =SUM('Proforma L+H'!E233:F233) -> 20800000 | J45: =I45/$D$39 -> 131.02362 | K45: =I45/$E$39 -> 462222.22 | L45: =I45/$I$50 -> 0.18682233 | N45: =B53 -> LAND & PROJECT ACQUISITION | O45: =C53 -> 18977750 | P45: =O45/$O$56 -> 0.069342927
B46: ='Proforma L+H'!B234 -> DEV LOAN | C46: ='Proforma L+H'!R234 -> 49035729 | D46: =C46/'Proforma L+H'!$D$17 -> 308.88648 | E46: =C46/'Proforma L+H'!$R$16 -> 1089682.9 | F46: =C46/$C$50 -> 0.10468966 | H46: =B46 -> DEV LOAN | I46: =C46 -> 49035729 | J46: =I46/$D$39 -> 308.88648 | K46: =I46/$E$39 -> 1089682.9 | L46: =I46/$I$50 -> 0.4404312 | N46: =B54 -> HARD COSTS - SITE, RESTORATION & INFRASTRUCTURE | O46: =C54 -> 8698186.8 | P46: =O46/$O$56 -> 0.031782363
B47: ='Proforma L+H'!B235 -> LAND SALE TO AMENITY | C47: ='Proforma L+H'!R235 -> 15000000 | D47: =C47/'Proforma L+H'!$D$17 -> 94.488189 | E47: =C47/'Proforma L+H'!$R$16 -> 333333.33 | F47: =C47/$C$50 -> 0.032024503 | H47: =B47 -> LAND SALE TO AMENITY | I47: =C47 -> 15000000 | J47: =I47/$D$39 -> 94.488189 | K47: =I47/$E$39 -> 333333.33 | L47: =I47/$I$50 -> 0.13472764 | N47: =B55 -> HARD COSTS - HOMES | O47: =C55 -> 1.6451232e+08 | P47: =O47/$O$56 -> 0.60111266
B48: ='Proforma L+H'!B236 -> PRESALE REVENUES | C48: ='Proforma L+H'!R236 -> 81794306 | D48: =C48/'Proforma L+H'!$D$17 -> 515.23972 | E48: =C48/'Proforma L+H'!$R$16 -> 1817651.2 | F48: =C48/$C$50 -> 0.17462813 | N48: =B56 -> SOFT COSTS PROFESSIONALS - FINAL ENTITLEMENTS & SITE INFRA. | O48: =C56 -> 3763315.6 | P48: =O48/$O$56 -> 0.013750804
B49: ='Proforma L+H'!B237 -> UNIT SALES | C49: ='Proforma L+H'!R237 -> 2.7526131e+08 | D49: =C49/'Proforma L+H'!$D$17 -> 1733.9295 | E49: =C49/'Proforma L+H'!$R$16 -> 6116918.1 | F49: =C49/$C$50 -> 0.58767378 | N49: =B57 -> SOFT COSTS PROFESSIONALS - HOMES | O49: =C57 -> 6141551.6 | P49: =O49/$O$56 -> 0.022440656
B50: ='Proforma L+H'!B238 -> TOTAL SOURCES | C50: ='Proforma L+H'!R238 -> 4.6839135e+08 | D50: =C50/'Proforma L+H'!$D$17 -> 2950.4967 | E50: =C50/'Proforma L+H'!$R$16 -> 10408697 | F50: =E50/$E$50 -> 1 | H50: =B50 -> TOTAL SOURCES | I50: =SUM(I41:I49) -> 1.1133573e+08 | J50: =I50/$D$39 -> 701.32743 | K50: =I50/$E$39 -> 2474127.3 | L50: =I50/$I$50 -> 1 | N50: =B58 -> SOFT COSTS - SALES | O50: =C58-O55 -> 750000 | P50: =O50/$O$56 -> 0.00274043
N51: =B59 -> SOFT COSTS - TAXES AND INSURANCE | O51: =C59 -> 997529.58 | P51: =O51/$O$56 -> 0.00364488
B52: USES | C52: $ | D52: $/SF | E52: Per Home | F52: % Total | H52: =B52 -> USES | I52: $ | J52: $/SF | K52: Per Home | L52: % Total | N52: =B60 -> SOFT COSTS - MUNICIPALITY FEES | O52: =C60 -> 2064912.5 | P52: =O52/$O$56 -> 0.0075449975
B53: ='Proforma L+H'!B241 -> LAND & PROJECT ACQUISITION | C53: ='Proforma L+H'!R241 -> 18977750 | D53: =C53/'Proforma L+H'!$D$17 -> 119.54488 | E53: =C53/'Proforma L+H'!$R$16 -> 421727.78 | F53: =E53/$E$65 -> 0.040516867 | H53: ='Proforma L+H'!B241 -> LAND & PROJECT ACQUISITION | I53: =SUM('Proforma L+H'!E241:F241) -> 18977750 | J53: =I53/$D$39 -> 119.54488 | K53: =I53/$E$39 -> 421727.78 | L53: =I53/$I$65 -> 0.17045516 | N53: =B61 -> DEVELOPMENT FEES | O53: =C61 -> 9000000 | P53: =O53/$O$56 -> 0.03288516
B54: ='Proforma L+H'!B242 -> HARD COSTS - SITE, RESTORATION & INFRASTRUCTURE | C54: ='Proforma L+H'!R242 -> 8698186.8 | D54: =C54/'Proforma L+H'!$D$17 -> 54.791728 | E54: =C54/'Proforma L+H'!$R$16 -> 193293.04 | F54: =E54/$E$65 -> 0.01857034 | H54: ='Proforma L+H'!B242 -> HARD COSTS - SITE, RESTORATION & INFRASTRUCTURE | I54: =SUM('Proforma L+H'!E242:F242) -> 5194373.7 | J54: =I54/$D$39 -> 32.720464 | K54: =I54/$E$39 -> 115430.53 | L54: =I54/$I$65 -> 0.046655047 | N54: FINANCING COSTS | O54: ='Proforma L+H'!R172 -> 42706610 | P54: =O54/$O$56 -> 0.15604597
B55: ='Proforma L+H'!B243 -> HARD COSTS - HOMES | C55: ='Proforma L+H'!R243 -> 1.6451232e+08 | D55: =C55/'Proforma L+H'!$D$17 -> 1036.2981 | E55: =C55/'Proforma L+H'!$R$16 -> 3655829.3 | F55: =E55/$E$65 -> 0.35122835 | H55: ='Proforma L+H'!B243 -> HARD COSTS - HOMES | I55: =SUM('Proforma L+H'!E243:F243) -> 18060938 | J55: =I55/$D$39 -> 113.76969 | K55: =I55/$E$39 -> 401354.17 | L55: =I55/$I$65 -> 0.1622205 | N55: POST SALE COSTS | O55: ='Proforma L+H'!R121 -> 16067503 | P55: =O55/$O$56 -> 0.058709156
B56: ='Proforma L+H'!B244 -> SOFT COSTS PROFESSIONALS - FINAL ENTITLEMENTS & SITE INFRA. | C56: ='Proforma L+H'!R244 -> 3763315.6 | D56: =C56/'Proforma L+H'!$D$17 -> 23.705925 | E56: =C56/'Proforma L+H'!$R$16 -> 83629.236 | F56: =E56/$E$65 -> 0.0080345541 | H56: ='Proforma L+H'!B244 -> SOFT COSTS PROFESSIONALS - FINAL ENTITLEMENTS & SITE INFRA. | I56: =SUM('Proforma L+H'!E244:F244) -> 2485268 | J56: =I56/$D$39 -> 15.655231 | K56: =I56/$E$39 -> 55228.177 | L56: =I56/$I$65 -> 0.022322286 | N56: TOTAL COSTS | O56: =SUM(O45:O55) -> 2.7367968e+08 | P56: =O56/$O$56 -> 1
B57: ='Proforma L+H'!B245 -> SOFT COSTS PROFESSIONALS - HOMES | C57: ='Proforma L+H'!R245 -> 6141551.6 | D57: =C57/'Proforma L+H'!$D$17 -> 38.686939 | E57: =C57/'Proforma L+H'!$R$16 -> 136478.92 | F57: =E57/$E$65 -> 0.013112009 | H57: ='Proforma L+H'!B245 -> SOFT COSTS PROFESSIONALS - HOMES | I57: =SUM('Proforma L+H'!E245:F245) -> 1162353.1 | J57: =I57/$D$39 -> 7.3219094 | K57: =I57/$E$39 -> 25830.069 | L57: =I57/$I$65 -> 0.010440073
B58: ='Proforma L+H'!B246 -> SOFT COSTS - SALES | C58: ='Proforma L+H'!R246 -> 16817503 | D58: =C58/'Proforma L+H'!$D$17 -> 105.93703 | E58: =C58/'Proforma L+H'!$R$16 -> 373722.29 | F58: =E58/$E$65 -> 0.035904811 | H58: ='Proforma L+H'!B246 -> SOFT COSTS - SALES | I58: =SUM('Proforma L+H'!E246:F246) -> 625818.75 | J58: =I58/$D$39 -> 3.9421654 | K58: =I58/$E$39 -> 13907.083 | L58: =I58/$I$65 -> 0.0056210055 | N58: NET PROFIT | O58: =O43-O56 -> 98375940 | P58: =O58/O43 -> 0.26441192
B59: ='Proforma L+H'!B247 -> SOFT COSTS - TAXES AND INSURANCE | C59: ='Proforma L+H'!R247 -> 997529.58 | D59: =C59/'Proforma L+H'!$D$17 -> 6.2836509 | E59: =C59/'Proforma L+H'!$R$16 -> 22167.324 | F59: =E59/$E$65 -> 0.0021296926 | H59: ='Proforma L+H'!B247 -> SOFT COSTS - TAXES AND INSURANCE | I59: =SUM('Proforma L+H'!E247:F247) -> 150981.13 | J59: =I59/$D$39 -> 0.95106227 | K59: =I59/$E$39 -> 3355.1363 | L59: =I59/$I$65 -> 0.0013560888
B60: ='Proforma L+H'!B248 -> SOFT COSTS - MUNICIPALITY FEES | C60: ='Proforma L+H'!R248 -> 2064912.5 | D60: =C60/'Proforma L+H'!$D$17 -> 13.007323 | E60: =C60/'Proforma L+H'!$R$16 -> 45886.944 | F60: =E60/$E$65 -> 0.0044085197 | H60: ='Proforma L+H'!B248 -> SOFT COSTS - MUNICIPALITY FEES | I60: =SUM('Proforma L+H'!E248:F248) -> 265745.83 | J60: =I60/$D$39 -> 1.6739895 | K60: =I60/$E$39 -> 5905.463 | L60: =I60/$I$65 -> 0.0023868873
B61: ='Proforma L+H'!B249 -> DEVELOPMENT FEES | C61: ='Proforma L+H'!R249 -> 9000000 | D61: =C61/'Proforma L+H'!$D$17 -> 56.692913 | E61: =C61/'Proforma L+H'!$R$16 -> 200000 | F61: =E61/$E$65 -> 0.019214702 | H61: ='Proforma L+H'!B249 -> DEVELOPMENT FEES | I61: =SUM('Proforma L+H'!E249:F249) -> 3000000 | J61: =I61/$D$39 -> 18.897638 | K61: =I61/$E$39 -> 66666.667 | L61: =I61/$I$65 -> 0.026945528
B62: ='Proforma L+H'!B250 -> FINANCING COSTS & REPAYMENT | C62: ='Proforma L+H'!R250-C63 -> 90958028 | D62: =C62/'Proforma L+H'!$D$17 -> 572.96395 | E62: =C62/'Proforma L+H'!$R$16 -> 2021289.5 | F62: =E62/$E$65 -> 0.19419237 | H62: ='Proforma L+H'!B250 -> FINANCING COSTS & REPAYMENT | I62: =SUM('Proforma L+H'!E250:F250) -> 25951178 | J62: =I62/$D$39 -> 163.47199 | K62: =I62/$E$39 -> 576692.84 | L62: =I62/$I$65 -> 0.2330894
B63: EB-5 SINKING FUND | C63: ='Proforma L+H'!R166 -> 36640000 | D63: =C63/'Proforma L+H'!$D$17 -> 230.80315 | E63: =C63/'Proforma L+H'!$R$16 -> 814222.22 | F63: =E63/$E$65 -> 0.078225185
B64: ='Proforma L+H'!B251 -> DISTRIBUTIONS | C64: ='Proforma L+H'!R251 -> 1.0982025e+08 | D64: =C64/'Proforma L+H'!$D$17 -> 691.78111 | E64: =C64/'Proforma L+H'!$R$16 -> 2440450 | F64: =E64/$E$65 -> 0.2344626 | H64: WORKING CAPITAL | I64: =I65-SUM(I53:I62) -> 35461324 | J64: =I64/$D$39 -> 223.37842 | K64: =I64/$E$39 -> 788029.41 | L64: =I64/$I$65 -> 0.31850803
B65: TOTAL USES | C65: ='Proforma L+H'!R252 -> 4.6839135e+08 | D65: =C65/'Proforma L+H'!$D$17 -> 2950.4967 | E65: =C65/'Proforma L+H'!$R$16 -> 10408697 | F65: =E65/$E$65 -> 1 | H65: ='Proforma L+H'!B252 -> TOTAL USES | I65: =I50 -> 1.1133573e+08 | J65: =I65/$D$39 -> 701.32743 | K65: =I65/$E$39 -> 2474127.3 | L65: =I65/$I$65 -> 1
N68: =B70 -> CLARENDON - AMENITY + HOTEL DEVELOPMENT: PROFORMA
N69: PROFORMA - BUSINESS CASE ANALYSIS
B70: ='Proforma A+H'!B1 -> CLARENDON - AMENITY + HOTEL DEVELOPMENT: PROFORMA | H70: ='Proforma A+H'!B1 -> CLARENDON - AMENITY + HOTEL DEVELOPMENT: PROFORMA | O70: $ | P70: % Total
B71: PROFORMA - SOURCES & USES SUMMARY | H71: PROFORMA - SOURCES & USES PRE-REVENUE (Year 0-3)
B72: =B40 -> SOURCES | C72: $ | D72: $/SF | F72: % Total | H72: =H40 -> SOURCES | I72: $ | J72: $/SF | L72: % Total | N72: =B78 -> TOTAL NET OPERATING INCOME (NOI) | O72: =C78 -> 30073583 | P72: =O72/$O$75 -> 0.10581192
B73: ='Proforma A+H'!B262 -> LAND EQUITY IN 80 ACRES - $15M in Equity derived from PUD | C73: ='Proforma A+H'!T262 -> 0 | F73: =C73/$C$81 -> 0 | H73: =B73 -> LAND EQUITY IN 80 ACRES - $15M in Equity derived from PUD | I73: =C73 -> 0 | L73: =I73/$I$81 -> 0 | N73: =B79 -> TOTAL UNIT SALES | O73: =C79 -> 134413125 | P73: =O73/$O$75 -> 0.47292371
B74: ='Proforma A+H'!B263 -> MTN ORIGINS - PURSUIT CAPITAL | C74: ='Proforma A+H'!T263 -> 0 | F74: =C74/$C$81 -> 0 | H74: =B74 -> MTN ORIGINS - PURSUIT CAPITAL | I74: =C74 -> 0 | L74: =I74/$I$81 -> 0 | N74: =B80 -> HOTEL SALE PROCEEDS / DISPOSITION | O74: =C80 -> 1.1973065e+08 | P74: =O74/$O$75 -> 0.42126438
B75: ='Proforma A+H'!B264 -> JV - EQUITY CAPITAL | C75: ='Proforma A+H'!T264 -> 0 | F75: =C75/$C$81 -> 0 | H75: =B75 -> JV - EQUITY CAPITAL | I75: =C75 -> 0 | L75: =I75/$I$81 -> 0 | N75: =N43 -> TOTAL REVENUE | O75: =SUM(O72:O74) -> 2.8421736e+08 | P75: =O75/$O$75 -> 1
B76: ='Proforma A+H'!B265 -> EB5 - MEZZ DEBT | C76: ='Proforma A+H'!T265 -> 28800000 | F76: =C76/$C$81 -> 0.069037697 | H76: =B76 -> EB5 - MEZZ DEBT | I76: =C76 -> 28800000 | L76: =I76/$I$81 -> 0.21774017
B77: ='Proforma A+H'!B266 -> DEV LOAN | C77: ='Proforma A+H'!T266 -> 1.0346774e+08 | F77: =C77/$C$81 -> 0.24802689 | H77: =B77 -> DEV LOAN | I77: =C77 -> 1.0346774e+08 | L77: =I77/$I$81 -> 0.78225983 | N77: =B84 -> LAND ACQUISITION COSTS | O77: =C84 -> 15000000 | P77: =O77/$O$87 -> 0.072505183
B78: ='Proforma A+H'!B267 -> TOTAL NET OPERATING INCOME (NOI) | C78: ='Proforma A+H'!T267 -> 30073583 | F78: =C78/$C$81 -> 0.072090658 | I78: ='Proforma A+H'!Z267 -> 0 | L78: =I78/$I$81 -> 0 | N78: =B85 -> TOTAL VERTICAL CONSTRUCTION COSTS | O78: =C85 -> 107807730 | P78: =O78/$O$87 -> 0.52110795
B79: ='Proforma A+H'!B268 -> TOTAL UNIT SALES | C79: ='Proforma A+H'!T268 -> 134413125 | F79: =C79/$C$81 -> 0.32220738 | I79: ='Proforma A+H'!Z268 -> 0 | L79: =I79/$I$81 -> 0 | N79: =B86 -> HARD COSTS - SITE | O79: =C86 -> 12036250 | P79: =O79/$O$87 -> 0.058179367
B80: ='Proforma A+H'!B269 -> HOTEL SALE PROCEEDS / DISPOSITION | C80: ='Proforma A+H'!T269 -> 1.1973065e+08 | F80: =C80/$C$81 -> 0.2870114 | I80: ='Proforma A+H'!Z269 -> 0 | L80: =I80/$I$81 -> 0 | N80: =B87 -> SOFT COSTS - PROFESSIONALS | O80: =C87 -> 9991244.7 | P80: =O80/$O$87 -> 0.048294468
B81: ='Proforma A+H'!B271 -> TOTAL SOURCES | C81: ='Proforma A+H'!T271 -> 4.1716339e+08 | F81: =C81/$C$81 -> 1 | H81: =B81 -> TOTAL SOURCES | I81: =SUM(I73:I80) -> 1.3226774e+08 | L81: =I81/$I$81 -> 1 | N81: =B88 -> SOFT COSTS - SALES | O81: =C88-O86 -> 300000 | P81: =O81/$O$87 -> 0.0014501037
N82: =B89 -> SOFT COSTS - TAXES AND INSURANCE | O82: =C89 -> 696773.89 | P82: =O82/$O$87 -> 0.0033679812
B83: =B52 -> USES | C83: $ | D83: $/SF | F83: % Total | H83: =H52 -> USES | I83: $ | J83: $/SF | L83: % Total | N83: =B90 -> SOFT COSTS - MUNICIPALITY FEES | O83: =C90 -> 269519.33 | P83: =O83/$O$87 -> 0.0013027699
B84: ='Proforma A+H'!B274 -> LAND ACQUISITION COSTS | C84: ='Proforma A+H'!T274 -> 15000000 | F84: =C84/$C$95 -> 0.035957134 | H84: =B84 -> LAND ACQUISITION COSTS | I84: =SUM('Proforma A+H'!G274:J274) -> 15000000 | L84: =I84/$I$95 -> 0.11340634 | N84: =B91 -> DEVELOPMENT FEES | O84: =C91 -> 4294099.2 | P84: =O84/$O$87 -> 0.020756297
B85: ='Proforma A+H'!B275 -> TOTAL VERTICAL CONSTRUCTION COSTS | C85: ='Proforma A+H'!T275 -> 107807730 | F85: =C85/$C$95 -> 0.25843047 | H85: =B85 -> TOTAL VERTICAL CONSTRUCTION COSTS | I85: =SUM('Proforma A+H'!G275:J275) -> 82903134 | L85: =I85/$I$95 -> 0.62678272 | N85: FINANCING COSTS | O85: ='Proforma A+H'!T209 -> 44451022 | P85: =O85/$O$87 -> 0.21486197
B86: ='Proforma A+H'!B276 -> HARD COSTS - SITE | C86: ='Proforma A+H'!T276 -> 12036250 | F86: =C86/$C$95 -> 0.028852604 | H86: =B86 -> HARD COSTS - SITE | I86: =SUM('Proforma A+H'!G276:J276) -> 8465937.5 | L86: =I86/$I$95 -> 0.064006064 | N86: POST SALE COSTS | O86: ='Proforma A+H'!T163+'Proforma A+H'!T167 -> 12035123 | P86: =O86/$O$87 -> 0.05817392
B87: ='Proforma A+H'!B277 -> SOFT COSTS - PROFESSIONALS | C87: ='Proforma A+H'!T277 -> 9991244.7 | F87: =C87/$C$95 -> 0.023950435 | H87: =B87 -> SOFT COSTS - PROFESSIONALS | I87: =SUM('Proforma A+H'!G277:J277) -> 8774967.7 | L87: =I87/$I$95 -> 0.066342463 | N87: =N56 -> TOTAL COSTS | O87: =SUM(O77:O86) -> 2.0688176e+08 | P87: =O87/$O$87 -> 1
B88: ='Proforma A+H'!B278 -> SOFT COSTS - SALES | C88: ='Proforma A+H'!T278 -> 12335123 | F88: =C88/$C$95 -> 0.029569045 | H88: =B88 -> SOFT COSTS - SALES | I88: =SUM('Proforma A+H'!G278:J278) -> 749687.5 | L88: =I88/$I$95 -> 0.0056679542
B89: ='Proforma A+H'!B279 -> SOFT COSTS - TAXES AND INSURANCE | C89: ='Proforma A+H'!T279 -> 696773.89 | F89: =C89/$C$95 -> 0.0016702661 | H89: =B89 -> SOFT COSTS - TAXES AND INSURANCE | I89: =SUM('Proforma A+H'!G279:J279) -> 535297.9 | L89: =I89/$I$95 -> 0.0040470782 | N89: NET PROFIT | O89: =O75-O87 -> 77335594 | P89: =O89/O75 -> 0.27210018
B90: ='Proforma A+H'!B280 -> SOFT COSTS - MUNICIPALITY FEES | C90: ='Proforma A+H'!T280 -> 269519.33 | F90: =C90/$C$95 -> 0.00064607617 | H90: =B90 -> SOFT COSTS - MUNICIPALITY FEES | I90: =SUM('Proforma A+H'!G280:J280) -> 207257.84 | L90: =I90/$I$95 -> 0.0015669568
B91: ='Proforma A+H'!B281 -> DEVELOPMENT FEES | C91: ='Proforma A+H'!T281 -> 4294099.2 | F91: =C91/$C$95 -> 0.010293567 | H91: =B91 -> DEVELOPMENT FEES | I91: =SUM('Proforma A+H'!G281:J281) -> 3049088.5 | L91: =I91/$I$95 -> 0.023052397
B92: ='Proforma A+H'!B282 -> FINANCING COSTS & REPAYMENT | C92: ='Proforma A+H'!T282-C93 -> 1.6922061e+08 | F92: =C92/$C$95 -> 0.40564588 | H92: =B92 -> FINANCING COSTS & REPAYMENT | I92: =SUM('Proforma A+H'!G282:J282) -> 23731944 | L92: =I92/$I$95 -> 0.17942352
B93: EB-5 SINKING FUND | C93: ='Proforma A+H'!T205 -> 12960000 | F93: =C93/$C$95 -> 0.031066964 | L93: =I93/$I$95 -> 0
B94: ='Proforma A+H'!B283 -> DISTRIBUTIONS | C94: ='Proforma A+H'!T283 -> 71873747 | F94: =C94/$C$95 -> 0.1722916 | H94: WORKING CAPITAL | I94: =I95-SUM(I84:I92) -> -11149575 | L94: =I94/$I$95 -> -0.084295495
B95: ='Proforma A+H'!B285 -> TOTAL USES | C95: ='Proforma A+H'!T285 -> 4.1716339e+08 | F95: =C95/$C$95 -> 1 | H95: =B95 -> TOTAL USES | I95: =I81 -> 1.3226774e+08 | L95: =I95/$I$95 -> 1

Sheet COMB CASH FLOWS
B4: COMBINED MONTHLY CASH FLOWS - UNDER DEVELOPMENT

Sheet Combined Returns
B1: CLARENDON - LAND, HOME, AMENITY DEVELOPMENT
B2: Returns Analysis
B4: PROJECT FINANCING ANALYSIS | F4: BUSINESS CASE ANALYSIS
B5: TOTAL PROJECT CAPITAL NEEDS: | D5: ='Returns L+H'!D5 -> 96335729 | F5: TOTAL PROJECT REVENUE (less brokers fees): | H5: ='Returns L+H'!H5 -> 3.7205562e+08
B6: TOTAL PROJECT VALUE (PV of FINAL BUILD OUT): | D6: ='Returns L+H'!D6 -> 287850000 | F6: - TOTAL PROJECT COST: | H6: ='Returns L+H'!H6 -> 2.7367968e+08
B7: STARTING SPEC DEVELOPMENT VALUE: | D7: ='Returns L+H'!D7 -> 0 | F7: = NET PROFIT | H7: ='Returns L+H'!H7 -> 98375940
B8: EQUITY to SPEC DEV VALUE (ETV): | D8: ='Returns L+H'!D8 -> #DIV/0! | F8: NET PROFIT %: | H8: ='Returns L+H'!H8 -> 0.26441192
B9: LOAN to COST (LTC): | D9: ='Returns L+H'!D9 -> 0.88062581 | F9: RETURN on EQUITY/CAPTIAL (ROE): | H9: ='Returns L+H'!H9 -> 8.5544296
B10: LOAN to VALUE (LTV): | D10: ='Returns L+H'!D10 -> 0.055454059
B12: PROJECT RETURNS ANALYSIS
B13: PROJECT NET CASH FLOWS: | D13: ='Returns L+H'!D13 -> 98320252
B14: EQUITY MULTIPLE: | D14: ='Returns L+H'!D14 -> 9.5495871
B15: MODELED ROI: | D15: ='Returns L+H'!D15 -> 8.5495871
B16: PROJECT IRR : | D16: ='Returns L+H'!D16 -> 0.64360042
F18: ='Proforma L+H'!E3 -> 0 | G18: ='Proforma L+H'!F3 -> 1 | H18: ='Proforma L+H'!G3 -> 2 | I18: ='Proforma L+H'!H3 -> 3 | J18: ='Proforma L+H'!I3 -> 4 | K18: ='Proforma L+H'!J3 -> 5 | L18: ='Proforma L+H'!K3 -> 6 | M18: ='Proforma L+H'!L3 -> 7 | ... R18: ='Proforma L+H'!Q3 -> 12
B19: SUMMARY OF RETURNS | F19: ='Proforma L+H'!E4 -> 45658 | G19: ='Proforma L+H'!F4 -> 46023 | H19: ='Proforma L+H'!G4 -> 46388 | I19: ='Proforma L+H'!H4 -> 46753 | J19: ='Proforma L+H'!I4 -> 47119 | K19: ='Proforma L+H'!J4 -> 47484 | L19: ='Proforma L+H'!K4 -> 47849 | M19: ='Proforma L+H'!L4 -> 48214 | ... R19: ='Proforma L+H'!Q4 -> 50041
B20: JV LP Returns
B21: Capital Return | D21: =SUM(F21:R21) -> 14641000 | F21: ='Returns L+H'!F21+'Returns A+H'!F21 -> 0 | G21: ='Returns L+H'!G21+'Returns A+H'!G21 -> 0 | H21: ='Returns L+H'!H21+'Returns A+H'!H21 -> 0 | I21: ='Returns L+H'!I21+'Returns A+H'!I21 -> 0 | J21: ='Returns L+H'!J21+'Returns A+H'!J21 -> 14641000 | K21: ='Returns L+H'!K21+'Returns A+H'!K21 -> 0 | L21: ='Returns L+H'!L21+'Returns A+H'!L21 -> 0 | M21: ='Returns L+H'!M21+'Returns A+H'!M21 -> 0 | ... R21: ='Returns L+H'!R21+'Returns A+H'!R21 -> 0
B22: Profit Split | D22: =SUM(F22:R22) -> 14953795 | F22: ='Returns L+H'!F22+'Returns A+H'!F22 -> 0 | G22: ='Returns L+H'!G22+'Returns A+H'!G22 -> 0 | H22: ='Returns L+H'!H22+'Returns A+H'!H22 -> 0 | I22: ='Returns L+H'!I22+'Returns A+H'!I22 -> 0 | J22: ='Returns L+H'!J22+'Returns A+H'!J22 -> 14953795 | K22: ='Returns L+H'!K22+'Returns A+H'!K22 -> 0 | L22: ='Returns L+H'!L22+'Returns A+H'!L22 -> 4.535136e-09 | M22: ='Returns L+H'!M22+'Returns A+H'!M22 -> 0 | ... R22: ='Returns L+H'!R22+'Returns A+H'!R22 -> 0
B23: Total Distributions | D23: =SUM(F23:R23) -> 29594795 | F23: =F21+F22 -> 0 | G23: =G21+G22 -> 0 | H23: =H21+H22 -> 0 | I23: =I21+I22 -> 0 | J23: =J21+J22 -> 29594795 | K23: =K21+K22 -> 0 | L23: =L21+L22 -> 4.535136e-09 | M23: =M21+M22 -> 0 | ... R23: =R21+R22 -> 0
B24: Total Contributions | D24: =SUM(F24:R24) -> 10000000 | F24: ='Returns L+H'!F24+'Returns A+H'!F24 -> 10000000 | G24: ='Returns L+H'!G24+'Returns A+H'!G24 -> 0 | H24: ='Returns L+H'!H24+'Returns A+H'!H24 -> 0
B25: Net Profit / Cash Flows | D25: =SUM(F25:R25) -> 19594795 | F25: =F23-F24 -> -10000000 | G25: =G23-G24 -> 0 | H25: =H23-H24 -> 0 | I25: =I23-I24 -> 0 | J25: =J23-J24 -> 29594795 | K25: =K23-K24 -> 0 | L25: =L23-L24 -> 4.535136e-09 | M25: =M23-M24 -> 0 | ... R25: =R23-R24 -> 0
B26: IRR | F26: =IRR(F25:R25) -> 0.31160732
B27: Equity Multiple | F27: =SUMIF(F25:R25,">0")/-SUMIF(F25:R25,"<0") -> 2.9594795
B28: Cumulative (Equity) Cash Position | F28: =F25+E28 -> -10000000 | G28: =G25+F28 -> -10000000 | H28: =H25+G28 -> -10000000 | I28: =I25+H28 -> -10000000 | J28: =J25+I28 -> 19594795 | K28: =K25+J28 -> 19594795 | L28: =L25+K28 -> 19594795 | M28: =M25+L28 -> 19594795 | ... R28: =R25+Q28 -> 19594795
B30: MO LP Returns
B31: Capital Return + Pref | D31: =SUM(F31:R31) -> 2196150 | F31: ='Returns L+H'!F31+'Returns A+H'!F31 -> 0 | G31: ='Returns L+H'!G31+'Returns A+H'!G31 -> 0 | H31: ='Returns L+H'!H31+'Returns A+H'!H31 -> 0 | I31: ='Returns L+H'!I31+'Returns A+H'!I31 -> 0 | J31: ='Returns L+H'!J31+'Returns A+H'!J31 -> 2196150 | K31: ='Returns L+H'!K31+'Returns A+H'!K31 -> 0 | L31: ='Returns L+H'!L31+'Returns A+H'!L31 -> 0 | M31: ='Returns L+H'!M31+'Returns A+H'!M31 -> 0 | ... R31: ='Returns L+H'!R31+'Returns A+H'!R31 -> 0
B32: Profit Split | D32: =SUM(F32:R32) -> 2243069.2 | F32: ='Returns L+H'!F32+'Returns A+H'!F32 -> 0 | G32: ='Returns L+H'!G32+'Returns A+H'!G32 -> 0 | H32: ='Returns L+H'!H32+'Returns A+H'!H32 -> 0 | I32: ='Returns L+H'!I32+'Returns A+H'!I32 -> 0 | J32: ='Returns L+H'!J32+'Returns A+H'!J32 -> 2243069.2 | K32: ='Returns L+H'!K32+'Returns A+H'!K32 -> 0 | L32: ='Returns L+H'!L32+'Returns A+H'!L32 -> 6.802704e-10 | M32: ='Returns L+H'!M32+'Returns A+H'!M32 -> 0 | ... R32: ='Returns L+H'!R32+'Returns A+H'!R32 -> 0
B33: Total Distributions | D33: =SUM(F33:R33) -> 4439219.2 | F33: =SUM(F31:F32) -> 0 | G33: =SUM(G31:G32) -> 0 | H33: =SUM(H31:H32) -> 0 | I33: =SUM(I31:I32) -> 0 | J33: =SUM(J31:J32) -> 4439219.2 | K33: =SUM(K31:K32) -> 0 | L33: =SUM(L31:L32) -> 6.802704e-10 | M33: =SUM(M31:M32) -> 0 | ... R33: =SUM(R31:R32) -> 0
B34: Total Contributions | D34: =SUM(F34:R34) -> 1500000 | F34: ='Returns L+H'!F34+'Returns A+H'!F34 -> 1500000 | G34: ='Returns L+H'!G34+'Returns A+H'!G34 -> 0 | H34: ='Returns L+H'!H34+'Returns A+H'!H34 -> 0 | I34: ='Returns L+H'!I34+'Returns A+H'!I34 -> 0 | J34: ='Returns L+H'!J34+'Returns A+H'!J34 -> 0 | K34: ='Returns L+H'!K34+'Returns A+H'!K34 -> 0 | L34: ='Returns L+H'!L34+'Returns A+H'!L34 -> 0 | M34: ='Returns L+H'!M34+'Returns A+H'!M34 -> 0 | N34: ='Returns L+H'!N34+'Returns A+H'!N34 -> 0
B35: Net Profit / Cash Flows | D35: =SUM(F35:R35) -> 2939219.2 | F35: =F33-F34 -> -1500000 | G35: =G33-G34 -> 0 | H35: =H33-H34 -> 0 | I35: =I33-I34 -> 0 | J35: =J33-J34 -> 4439219.2 | K35: =K33-K34 -> 0 | L35: =L33-L34 -> 6.802704e-10 | M35: =M33-M34 -> 0 | ... R35: =R33-R34 -> 0
B36: IRR | F36: =IRR(F35:R35) -> 0.31160732
B37: Equity Multiple | F37: =SUMIF(F35:R35,">0")/-SUMIF(F35:R35,"<0") -> 2.9594795
B38: Cumulative (Equity) Cash Position | F38: =F35+E38 -> -1500000 | G38: =G35+F38 -> -1500000 | H38: =H35+G38 -> -1500000 | I38: =I35+H38 -> -1500000 | J38: =J35+I38 -> 2939219.2 | K38: =K35+J38 -> 2939219.2 | L38: =L35+K38 -> 2939219.2 | M38: =M35+L38 -> 2939219.2 | ... R38: =R35+Q38 -> 2939219.2
B40: MO/JV JV GP Returns
B41: Total Distributions | D41: =SUM(F41:R41) -> 1.4765999e+08 | F41: ='Returns L+H'!F41+'Returns A+H'!F41 -> 0 | G41: ='Returns L+H'!G41+'Returns A+H'!G41 -> 7262.0859 | H41: ='Returns L+H'!H41+'Returns A+H'!H41 -> 0 | I41: ='Returns L+H'!I41+'Returns A+H'!I41 -> 0 | J41: ='Returns L+H'!J41+'Returns A+H'!J41 -> 9943752.6 | K41: ='Returns L+H'!K41+'Returns A+H'!K41 -> 98981767 | L41: ='Returns L+H'!L41+'Returns A+H'!L41 -> 2.2351742e-09 | M41: ='Returns L+H'!M41+'Returns A+H'!M41 -> 38727204 | ... R41: ='Returns L+H'!R41+'Returns A+H'!R41 -> 0
B42: Net Profit / Cash Flows | D42: =SUM(F42:R42) -> 1.4765999e+08 | F42: =SUM(F41:F41) -> 0 | G42: =SUM(G41:G41) -> 7262.0859 | H42: =SUM(H41:H41) -> 0 | I42: =SUM(I41:I41) -> 0 | J42: =SUM(J41:J41) -> 9943752.6 | K42: =SUM(K41:K41) -> 98981767 | L42: =SUM(L41:L41) -> 2.2351742e-09 | M42: =SUM(M41:M41) -> 38727204 | ... R42: =SUM(R41:R41) -> 0
B43: JV Portion | C43: =Assumptions!K11 -> 0.4 | D43: =SUM(F43:R43) -> 59063994 | F43: =F42*$C$43 -> 0 | G43: =G42*$C$43 -> 2904.8344 | H43: =H42*$C$43 -> 0 | I43: =I42*$C$43 -> 0 | J43: =J42*$C$43 -> 3977501 | K43: =K42*$C$43 -> 39592707 | L43: =L42*$C$43 -> 8.9406967e-10 | M43: =M42*$C$43 -> 15490881 | ... R43: =R42*$C$43 -> 0
B44: MO Portion | C44: =1-C43 -> 0.6 | D44: =SUM(F44:R44) -> 88595991 | F44: =F42*$C$44 -> 0 | G44: =G42*$C$44 -> 4357.2516 | H44: =H42*$C$44 -> 0 | I44: =I42*$C$44 -> 0 | J44: =J42*$C$44 -> 5966251.6 | K44: =K42*$C$44 -> 59389060 | L44: =L42*$C$44 -> 1.3411045e-09 | M44: =M42*$C$44 -> 23236322 | ... R44: =R42*$C$44 -> 0
B46: Net Cash Flow For Distributions - TOTAL PROJECT RETURNS
B47: Net Levered Before Tax Cash Flow | D47: =SUM(F47:R47) -> 1.70194e+08 | F47: ='Returns L+H'!F47+'Returns A+H'!F47 -> -11500000 | G47: ='Returns L+H'!G47+'Returns A+H'!G47 -> 7262.0859 | H47: ='Returns L+H'!H47+'Returns A+H'!H47 -> 0 | I47: ='Returns L+H'!I47+'Returns A+H'!I47 -> 2165625 | J47: ='Returns L+H'!J47+'Returns A+H'!J47 -> 52547454 | K47: ='Returns L+H'!K47+'Returns A+H'!K47 -> 88246455 | L47: ='Returns L+H'!L47+'Returns A+H'!L47 -> 7.4505806e-09 | M47: ='Returns L+H'!M47+'Returns A+H'!M47 -> 38727204 | ... R47: ='Returns L+H'!R47+'Returns A+H'!R47 -> 0
B48: Levered IRR | F48: =XIRR(F47:R47,F19:R19) -> 0.7707414
B49: Equity Multiple | F49: =SUMIF(F47:R47,">0")/-SUMIF(F47:R47,"<0") -> 15.799478
B51: Return of PM EQUITY & Hurdle 1 (Preferred Return)
B52: Net Levered Before Tax Cash Flow | F52: =F47 -> -11500000 | G52: =G47 -> 7262.0859 | H52: =H47 -> 0 | I52: =I47 -> 2165625 | J52: =J47 -> 52547454 | K52: =K47 -> 88246455 | L52: =L47 -> 7.4505806e-09 | M52: =M47 -> 38727204 | N52: ='Proforma L+H'!M217 -> 0 | O52: ='Proforma L+H'!N217 -> 0 | P52: ='Proforma L+H'!O217 -> 0 | Q52: ='Proforma L+H'!P217 -> 0 | R52: ='Proforma L+H'!Q217 -> 0
B53: Preferred returns | F53: =F52 -> -11500000 | G53: =G52 -> 7262.0859 | H53: =H52 -> 0 | I53: =I52 -> 2165625 | J53: =J52 -> 52547454 | L53: =L52 -> 7.4505806e-09 | M53: 27400000 | N53: =N52 -> 0 | O53: =O52 -> 0 | P53: =P52 -> 0 | Q53: =Q52 -> 0 | R53: =R52 -> 0 | T53: =SUM(F53:S53) -> 70620341
B54: IRR Check - preferred returns | F54: =XIRR(F53:R53,F45:R45) -> #NUM! | T54: =U76 -> 0
B55: Remaining Cash Flow for Split | F55: =F52-F53 -> 0 | G55: =G52-G53 -> 0 | H55: =H52-H53 -> 0 | I55: =I52-I53 -> 0 | J55: =J52-J53 -> 0 | K55: =K52-K53 -> 88246455 | L55: =L52-L53 -> 0 | M55: =M52-M53 -> 11327204 | ... R55: =R52-R53 -> 0
B56: =T79 -> 0 | C56: =U79 -> 0 | F56: =F$55*$C56 -> 0 | G56: =G$55*$C56 -> 0 | H56: =H$55*$C56 -> 0 | I56: =I$55*$C56 -> 0 | J56: =J$55*$C56 -> 0 | K56: =K$55*$C56 -> 0 | L56: =L$55*$C56 -> 0 | M56: =M$55*$C56 -> 0 | ... R56: =R$55*$C56 -> 0 | T56: =SUM(F56:S56) -> 0
B57: =T80 -> 0 | C57: =U80 -> 0 | F57: =F$55*$C57 -> 0 | G57: =G$55*$C57 -> 0 | H57: =H$55*$C57 -> 0 | I57: =I$55*$C57 -> 0 | J57: =J$55*$C57 -> 0 | K57: =K$55*$C57 -> 0 | L57: =L$55*$C57 -> 0 | M57: =M$55*$C57 -> 0 | ... R57: =R$55*$C57 -> 0 | T57: =SUM(F57:S57) -> 0
B59: CM Common Members SHARE
B60: Net Levered Before Tax Cash Flow | F60: =-#REF! -> #REF! | G60: =-#REF! -> #REF! | H60: =-#REF! -> #REF! | I60: =I57 -> 0 | J60: =J57 -> 0 | K60: =K57 -> 0 | L60: =L57 -> 0 | M60: =M57 -> 0 | N60: =N57 -> 0 | O60: =O57 -> 0 | P60: =P57 -> 0 | ... R60: =R57 -> 0
B61: Preferred returns | F61: =F60 -> #REF! | G61: =G60 -> #REF!
B62: IRR Check - preferred returns | F62: =XIRR(F61:R61,F45:R45) -> #REF! | T62: 0.1
B63: Remaining Cash Flow for Split | F63: =F60-F61 -> #REF! | G63: =G60-G61 -> #REF! | H63: =H60-H61 -> #REF! | I63: =I60-I61 -> 0 | J63: =J60-J61 -> 0 | K63: =K60-K61 -> 0 | L63: =L60-L61 -> 0 | M63: =M60-M61 -> 0 | ... R63: =R60-R61 -> 0
B64: CM SPONSOR SHARE | C64: 0 | F64: =F$63*$C64 -> #REF! | G64: =G$63*$C64 -> #REF! | H64: =H$63*$C64 -> #REF! | I64: =I$63*$C64 -> 0 | J64: =J$63*$C64 -> 0 | K64: =K$63*$C64 -> 0 | L64: =L$63*$C64 -> 0 | M64: =M$63*$C64 -> 0 | ... R64: =R$63*$C64 -> 0
B65: CM Common Members MANAGER SHARE | C65: =1-C64 -> 1 | F65: =F$63*$C65 -> #REF! | G65: =G$63*$C65 -> #REF! | H65: =H$63*$C65 -> #REF! | I65: =I$63*$C65 -> 0 | J65: =J$63*$C65 -> 0 | K65: =K$63*$C65 -> 0 | L65: =L$63*$C65 -> 0 | M65: =M$63*$C65 -> 0 | ... R65: =R$63*$C65 -> 0 | T65: =SUM(D65:S65) -> #REF!
V66: CM Share Returns | W66: PM Share Returns | AA66: NiCK | AB66: MTN O | AC66: DeREUS | AD66: TOTAL
B67: Proposed Sponsor Split
B68: Market rate Overhead & Fees Paid to Working Sponsors (e.g. Design Fees, Sales Commision, Asset Management, Common Members Fees, etc.)
B69: Cost of Contributed Capital (e.g. Cash Multiple for Pursuit Dollars, 10% Pref for Equity, etc.)
B70: Equal split of Sponsor Distribution (e.g. 3 ways, 4 ways or 5 ways depending on head count of Sponsor Principals)
T71: NICK | U71: =AA75 -> 0 | V71: =$T$57*U71 -> 0 | W71: =(5000000/$D$24)*$T$56+5000000 -> 5000000 | Y71: PURSUIT/ENT. | Z71: 0.33333 | AA71: =1/3 -> 0.33333333 | AB71: =1/3 -> 0.33333333 | AC71: =1/3 -> 0.33333333 | AD71: =SUM(AA71:AC71) -> 1

Sheet Proforma Resi
B1: BRUNDAGE - RESI DEVELOPMENT: PROFORMA | AB1: AMU Fee | AC1: =+IF(AC2<0,-$C$193*AC2,0) -> 0 | AD1: =+IF(AD2<0,-$C$193*AD2,0) -> #REF! | AE1: =+IF(AE2<0,-$C$193*AE2,0) -> #REF! | AF1: =+IF(AF2<0,-$C$193*AF2,0) -> #REF! | AG1: =+IF(AG2<0,-$C$193*AG2,0) -> #REF! | AH1: =+IF(AH2<0,-$C$193*AH2,0) -> #REF! | AI1: =+IF(AI2<0,-$C$193*AI2,0) -> #REF! | AJ1: =+IF(AJ2<0,-$C$193*AJ2,0) -> #REF!
B2: Build & Sales Proforma | AB2: Cumulative PM (Equity) Cash Position | AC2: =+'Returns Resi'!F30 -> 0 | AD2: =+'Returns Resi'!G40 -> #REF! | AE2: =+'Returns Resi'!H40 -> #REF! | AF2: =+'Returns Resi'!I40 -> #REF! | AG2: =+'Returns Resi'!J40 -> #REF! | AH2: =+'Returns Resi'!K40 -> #REF! | AI2: =+'Returns Resi'!L40 -> #REF! | AJ2: =+'Returns Resi'!M40 -> #REF!
E3: 0 | F3: =E3+1 -> 1 | G3: =F3+1 -> 2 | H3: =G3+1 -> 3 | I3: =H3+1 -> 4 | J3: =I3+1 -> 5 | K3: =J3+1 -> 6 | L3: =K3+1 -> 7 | M3: =L3+1 -> 8 | ... Q3: =P3+1 -> 12 | AC3: Year 0 | AD3: Year 1 | AE3: Year 2 | AF3: Year 3 | AG3: Year 4 | AH3: Year 5 | AI3: Year 6 | AJ3: Year 7
E4: =Assumptions!C6 -> 2025 | F4: =E4+1 -> 2026 | G4: =F4+1 -> 2027 | H4: =G4+1 -> 2028 | I4: =H4+1 -> 2029 | J4: =I4+1 -> 2030 | K4: =J4+1 -> 2031 | L4: =K4+1 -> 2032 | M4: =L4+1 -> 2033 | ... Q4: =P4+1 -> 2037 | R4: TOTALS
C5: Average. Sqft of Lots | D5: Average Unit Size (sf) | E5: 44927 | F5: =E5+365 -> 45292 | G5: =F5+366 -> 45658 | H5: =G5+365 -> 46023 | I5: =H5+365 -> 46388 | J5: =I5+365 -> 46753 | K5: =J5+366 -> 47119 | L5: =K5+365 -> 47484 | M5: =L5+365 -> 47849 | N5: =M5+365 -> 48214 | O5: =N5+365 -> 48579 | P5: =O5+366 -> 48945 | Q5: =P5+365 -> 49310 | S5: Basis per Lot+Unit
A6: Map | B6: Buildout schedule | D6: Unit Size
B7: ='Proforma Resi'!E265 -> Phase 1: Downhill SFR | C7: 10000 | D7: ='Proforma Resi'!G265 -> 2650 | F7: 1 | G7: 1 | H7: 5 | I7: 3 | R7: =SUM(F7:Q7) -> 10 | S7: =D7*F23 -> 3776250 | T7: =R7*S7 -> 37762500 | V7: =SUMPRODUCT(D7,R7) -> 26500
B8: ='Proforma Resi'!E266 -> Phase 1: Uphill SFR | C8: 10000 | D8: ='Proforma Resi'!G266 -> 2405 | F8: 1 | G8: 2 | R8: =SUM(F8:Q8) -> 3 | S8: =D8*F24 -> 3487250 | T8: =R8*S8 -> 10461750 | V8: =SUMPRODUCT(D8,R8) -> 7215
B9: ='Proforma Resi'!E267 -> Phase 1: Uphill/Downhill Duplex | C9: 5000 | D9: ='Proforma Resi'!G267 -> 1783 | F9: 2 | G9: 8 | H9: 4 | I9: 8 | R9: =SUM(F9:Q9) -> 22 | S9: =D9*F25 -> 2451625 | T9: =R9*S9 -> 53935750 | V9: =SUMPRODUCT(D9,R9) -> 39226
B10: ='Proforma Resi'!E268 -> Phase 1: Multi-unit | C10: 5000 | D10: ='Proforma Resi'!G268 -> 1350 | G10: 4 | H10: 4 | R10: =SUM(F10:Q10) -> 8 | S10: =D10*F26 -> 1957500 | T10: =R10*S10 -> 15660000 | V10: =SUMPRODUCT(D10,R10) -> 10800
B11: Total starts | F11: =SUM(F7:F10) -> 4 | G11: =SUM(G7:G10) -> 15 | H11: =SUM(H7:H10) -> 13 | I11: =SUM(I7:I10) -> 11 | J11: =SUM(J7:J10) -> 0 | K11: =SUM(K7:K10) -> 0 | L11: =SUM(L7:L10) -> 0 | M11: =SUM(M7:M10) -> 0 | ... R11: =SUM(R7:R10) -> 43 | S11: TOTAL HOMES | T11: =SUM(T7:T10) -> 117820000 | V11: =SUMPRODUCT(D7:D10,R7:R10) -> 83741 | W11: /sf | X11: =SUM(T7:T10)/V11 -> 1406.9572 | Y11: /sf | Z11: /sf
B12: Total Sellable SQFT | C12: =SUMPRODUCT(C7:C10,R7:R10) -> 280000 | D12: =SUMPRODUCT(D7:D10,R7:R10) -> 83741 | T12: =T11/R11 -> 2740000 | U12: Average
B13: Total Sellable ACRES | C13: =C12/43560 -> 6.4279155
B15: Sales Schedule
B16: =B7 -> Phase 1: Downhill SFR | C16: =R7 -> 10 | F16: 0 | G16: =F7 -> 1 | H16: =G7 -> 1 | I16: =H7 -> 5 | J16: =I7 -> 3 | K16: =J7 -> 0 | L16: =K7 -> 0 | M16: =L7 -> 0 | N16: =M7 -> 0 | ... Q16: =P7 -> 0 | R16: =SUM(F16:Q16) -> 10 | AC16: =+_xlfn.XLOOKUP($T16,$D$23:$D$26,O$23:O$26) -> 2541.4559 | AD16: =+_xlfn.XLOOKUP($T16,$D$23:$D$26,P$23:P$26) -> 2732.0651 | AE16: =+_xlfn.XLOOKUP($T16,$D$23:$D$26,Q$23:Q$26) -> 2936.97
B17: =B8 -> Phase 1: Uphill SFR | C17: =R8 -> 3 | F17: 0 | G17: =F8 -> 1 | H17: =G8 -> 2 | I17: =H8 -> 0 | J17: =I8 -> 0 | K17: =J8 -> 0 | L17: =K8 -> 0 | M17: =L8 -> 0 | N17: =M8 -> 0 | ... Q17: =P8 -> 0 | R17: =SUM(F17:Q17) -> 3 | AC17: =+AC16 -> 2541.4559 | AD17: =+AD16 -> 2732.0651 | AE17: =+AE16 -> 2936.97
B18: =B9 -> Phase 1: Uphill/Downhill Duplex | C18: =R9 -> 22 | F18: 0 | G18: =F9 -> 2 | H18: =G9 -> 8 | I18: =H9 -> 4 | J18: =I9 -> 8 | K18: =J9 -> 0 | L18: =K9 -> 0 | M18: =L9 -> 0 | N18: =M9 -> 0 | ... Q18: =P9 -> 0 | R18: =SUM(F18:Q18) -> 22 | AC18: =+_xlfn.XLOOKUP($T18,$D$23:$D$26,O$23:O$26) -> 2541.4559 | AD18: =+_xlfn.XLOOKUP($T18,$D$23:$D$26,P$23:P$26) -> 2732.0651 | AE18: =+_xlfn.XLOOKUP($T18,$D$23:$D$26,Q$23:Q$26) -> 2936.97
B19: =B10 -> Phase 1: Multi-unit | C19: =R10 -> 8 | F19: 0 | G19: =F10 -> 0 | H19: =G10 -> 4 | I19: =H10 -> 4 | J19: =I10 -> 0 | K19: =J10 -> 0 | L19: =K10 -> 0 | M19: =L10 -> 0 | N19: =M10 -> 0 | ... Q19: =P10 -> 0 | R19: =SUM(F19:Q19) -> 8 | AC19: =+AC18 -> 2541.4559 | AD19: =+AD18 -> 2732.0651 | AE19: =+AE18 -> 2936.97
B20: Total sales | C20: =SUM(C16:C19) -> 43 | F20: =SUM(F16:F19) -> 0 | G20: =SUM(G16:G19) -> 4 | H20: =SUM(H16:H19) -> 15 | I20: =SUM(I16:I19) -> 13 | J20: =SUM(J16:J19) -> 11 | K20: =SUM(K16:K19) -> 0 | L20: =SUM(L16:L19) -> 0 | M20: =SUM(M16:M19) -> 0 | ... R20: =SUM(R16:R19) -> 43
B22: Sales Price Escalation
B23: Phase 1: Large SFR | C23: 0.075 | F23: ='Proforma Resi'!H265 -> 1425 | G23: ='Proforma Resi'!H265 -> 1425 | H23: =G23*(1+$C23) -> 1531.875 | I23: =H23*(1+$C23) -> 1646.7656 | J23: =I23*(1+$C23) -> 1770.273 | K23: =J23*(1+$C23) -> 1903.0435 | L23: =K23*(1+$C23) -> 2045.7718 | M23: =L23*(1+$C23) -> 2199.2047 | N23: =M23*(1+$C$23) -> 2364.145 | O23: =N23*(1+$C$23) -> 2541.4559 | P23: =O23*(1+$C$23) -> 2732.0651 | Q23: =P23*(1+$C$23) -> 2936.97
B24: Phase 1: Small SFR | C24: 0.075 | F24: ='Proforma Resi'!H266 -> 1450 | G24: 1450 | H24: =G24*(1+$C24) -> 1558.75 | I24: =H24*(1+$C24) -> 1675.6562 | J24: =I24*(1+$C24) -> 1801.3305 | K24: =J24*(1+$C24) -> 1936.4303 | L24: =K24*(1+$C24) -> 2081.6625 | M24: =L24*(1+$C24) -> 2237.7872 | N24: =M24*(1+$C$24) -> 2405.6213 | O24: =N24*(1+$C$24) -> 2586.0428 | P24: =O24*(1+$C$24) -> 2779.9961 | Q24: =P24*(1+$C$24) -> 2988.4958
B25: Phase 1: Small Duplex | C25: 0.075 | F25: ='Proforma Resi'!H267 -> 1375 | G25: 1375 | H25: =G25*(1+$C25) -> 1478.125 | I25: =H25*(1+$C25) -> 1588.9844 | J25: =I25*(1+$C25) -> 1708.1582 | K25: =J25*(1+$C25) -> 1836.2701 | L25: =K25*(1+$C25) -> 1973.9903 | M25: =L25*(1+$C25) -> 2122.0396 | N25: =M25*(1+$C$25) -> 2281.1926 | O25: =N25*(1+$C$25) -> 2452.282 | P25: =O25*(1+$C$25) -> 2636.2032 | Q25: =P25*(1+$C$25) -> 2833.9184
B26: Phase 1: Multi-unit | C26: 0.075 | F26: ='Proforma Resi'!H268 -> 1450 | G26: ='Proforma Resi'!H268 -> 1450 | H26: ='Proforma Resi'!H268 -> 1450 | I26: ='Proforma Resi'!H268 -> 1450 | J26: =I26*(1+$C26) -> 1558.75 | K26: =J26*(1+$C26) -> 1675.6562 | L26: =K26*(1+$C26) -> 1801.3305 | M26: =L26*(1+$C26) -> 1936.4303 | N26: =M26*(1+$C$26) -> 2081.6625 | O26: =N26*(1+$C$26) -> 2237.7872 | P26: =O26*(1+$C$26) -> 2405.6213 | Q26: =P26*(1+$C$26) -> 2586.0428
B27: Average Sales $ per Unit | G27: =IFERROR(SUM(F42+G44)/G20,"") -> 3041687.5 | H27: =IFERROR(SUM(G42+H44)/H20,"") -> 2698068.8 | I27: =IFERROR(SUM(H42+I44)/I20,"") -> 3152483.2 | J27: =IFERROR(SUM(I42+J44)/J20,"") -> 3494439.9 | K27: =IFERROR(SUM(J42+K44)/K20,"") | L27: =IFERROR(SUM(K42+L44)/L20,"") | M27: =IFERROR(SUM(L42+M44)/M20,"") | N27: =IFERROR(SUM(M42+N44)/N20,"") | ... Q27: =IFERROR(SUM(P42+Q44)/Q20,"")
B28: SOURCES | T28: Loan / Equity Financing | W28: Project Financing Metrics
B29: CM - PURSUIT CAPITAL | E29: 75000 | L29: 0 | R29: =SUM(E29:Q29) -> 75000 | T29: Year 0-2 Dev Cost | U29: =SUM(E197:G197) -> #REF! | V29: Actual | W29: VALUE OF SPEC DEV | Y29: =SUMPRODUCT(D7:D10,F7:F10,F23:F26) -> 12166750
B30: PM1 - EQUITY CONTRIBUTION (LAND) | F30: $11.7M in LAND CONTRIBUTION SHOWN ON BALANCE SHEET OF DEV LLC | T30: Financing Cost Gross-Up | U30: =U29*(1+Assumptions!#REF!) -> #REF! | V30: =U29+SUMIF(E3:Q3,"<="&Assumptions!G6,'Proforma Resi'!E201:Q201)+R202 -> #REF! | W30: ETV | Y30: =(R32)/Y29 -> #REF!
B31: PM2 - EQUITY (CASH) | F31: =U34-SUM(E29:F29) -> #REF! | L31: 0 | R31: =SUM(E31:Q31) -> #REF! | T31: Year 0-2 Unit Sales | U31: =SUM(E44:G44) -> 12166750 | W31: LTV | Y31: =R35/(Y29+R64+F72+G72) -> #REF!
B32: EQUITY / PROJECT ACQUISITION + ENTITLEMENT | E32: =SUM(E29:E31) -> 75000 | F32: =SUM(F29:F31) -> #REF! | G32: =SUM(G29:G31) -> 0 | H32: =SUM(H29:H31) -> 0 | I32: =SUM(I29:I31) -> 0 | J32: =SUM(J29:J31) -> 0 | K32: =SUM(K29:K31) -> 0 | L32: =SUM(L29:L31) -> 0 | ... R32: =SUM(R29:R31) -> #REF! | T32: LTC | U32: =Assumptions!F7 -> 0.6 | W32: LTC Total (INCL LAND VALUE) | Y32: =(R35/(R58+R32+R35)) -> #REF!
T33: Loan Amount | U33: =U30*U32 -> #REF! | V33: Actual
B34: Development Loan | C34: =U33 -> #REF! | E34: 0 | F34: =MAX(F197-F32-F44-E230,0) -> #REF! | G34: =MAX(G197-G32-G44-F230,0) -> #REF! | H34: =MAX(H197-H32-H44-G230,0) -> #REF! | I34: =MAX(I197-I32-I44-H230,0) -> #REF! | J34: =MAX(J197-J32-J44-I230,0) -> #REF! | K34: =MAX(K197-K32-K44-J230,0) -> #REF! | L34: =MAX(L197-L32-L44-K230,0) -> #REF! | M34: =MAX(M197-M32-M44-L230,0) -> #REF! | O34: =MAX(O197-O32-O44-N230,0) -> #REF! | P34: =MAX(P197-P32-P44-O230,0) -> #REF! | Q34: =MAX(Q197-Q32-Q44-P230,0) -> #REF! | R34: =SUM(E34:Q34) -> #REF! | T34: Initial Equity | U34: =U30-U33-C56*0.89 -> #REF! | V34: =U34+C56 -> #REF!
B35: DEBT | E35: =SUM(E34:E34) -> 0 | F35: =SUM(F34:F34) -> #REF! | G35: =SUM(G34:G34) -> #REF! | H35: =SUM(H34:H34) -> #REF! | I35: =SUM(I34:I34) -> #REF! | J35: =SUM(J34:J34) -> #REF! | K35: =SUM(K34:K34) -> #REF! | L35: =SUM(L34:L34) -> #REF! | ... Q35: =SUM(Q34:Q34) -> #REF! | R35: =SUM(E35:Q35) -> #REF!
B37: Construction Start Draw
B38: Foundation Complete Draw
B39: Structure Complete Draw
B40: MEP 4-way Draw
B41: Finishes Start Draw
B42: PRESALE REVENUES | C42: =SUM(C37:C41) -> 0 | E42: =SUM(E37:E41) -> 0 | F42: =SUM(F37:F41) -> 0 | G42: =SUM(G37:G41) -> 0 | H42: =SUM(H37:H41) -> 0 | I42: =SUM(I37:I41) -> 0 | J42: =SUM(J37:J41) -> 0 | K42: =SUM(K37:K41) -> 0 | L42: =SUM(L37:L41) -> 0 | ... P42: =SUM(P37:P41) -> 0 | R42: =SUM(E42:Q42) -> 0 | T42: TOTAL HOME SALES
B43: INFRASTRUCTURE REPAYMENT FROM HOTEL PROFORMA | H43: ='Proforma A+H'!#REF! -> #REF!
B44: UNIT SALES | F44: =(1-$C$42)*SUMPRODUCT(F$16:F$19,$D$7:$D$10,F$23:F$26) -> 0 | G44: =+(1-$C$42)*SUMPRODUCT(G$16:G$19,$D$7:$D$10,G$23:G$26) -> 12166750 | H44: =(1-$C$42)*SUMPRODUCT(H$16:H$19,$D$7:$D$10,H$23:H$26) -> 40471031 | I44: =(1-$C$42)*SUMPRODUCT(I$16:I$19,$D$7:$D$10,I$23:I$26) -> 40982281 | J44: =(1-$C$42)*SUMPRODUCT(J$16:J$19,$D$7:$D$10,J$23:J$26) -> 38438839 | K44: =(1-$C$42)*SUMPRODUCT(K$16:K$19,$D$7:$D$10,K$23:K$26) -> 0 | L44: =(1-$C$42)*SUMPRODUCT(L$16:L$19,$D$7:$D$10,L$23:L$26) -> 0 | M44: =(1-$C$42)*SUMPRODUCT(M$16:M$19,$D$7:$D$10,M$23:M$26) -> 0 | N44: =(1-$C$42)*SUMPRODUCT(N$16:N$19,$D$7:$D$10,N$23:N$26) -> 0 | O44: =(1-$C$42)*SUMPRODUCT(O$16:O$19,$D$7:$D$10,O$23:O$26) -> 0 | ... Q44: =(1-$C$42)*SUMPRODUCT(Q$16:Q$19,$D$7:$D$10,Q$23:Q$26) -> 0 | R44: =SUM(E44:Q44) -> 1.320589e+08
B45: TOTAL SOURCES | E45: =E32+E35+E42+E43+E44 -> 75000 | F45: =F32+F35+F42+F43+F44 -> #REF! | G45: =G32+G35+G42+G43+G44 -> #REF! | H45: =H32+H35+H42+H43+H44 -> #REF! | I45: =I32+I35+I42+I43+I44 -> #REF! | J45: =J32+J35+J42+J43+J44 -> #REF! | K45: =K32+K35+K42+K43+K44 -> #REF! | L45: =L32+L35+L42+L43+L44 -> #REF! | M45: =M32+M35+M42+M43+M44 -> #REF! | N45: =N32+N35+N42+N44 -> 0 | O45: =O32+O35+O42+O44 -> #REF! | P45: =P32+P35+P42+P44 -> #REF! | Q45: =Q32+Q35+Q42+Q44 -> #REF! | R45: =SUM(E45:Q45) -> #REF! | T45: TOTAL SALES | U45: =T46/R11 -> 3071137.2 | V45: Ave. Unit $
T46: =(R42)+R44 -> 1.320589e+08 | U46: =T46/D12 -> 1576.9922 | V46: Ave. $/SF
B47: USES
A48: 01a | B48: LAND & PROJECT ACQUISITION
B49: Asset Acquisition Fee | C49: 0.02 | F49: =C49*C56 -> 300000 | R49: =SUM(E49:L49) -> 300000 | T49: =R49/T46 -> 0.0022717136
B50: Land Downpayment | C50: 0.2 | F50: =Assumptions!Q7*C50 -> 3000000 | R50: =SUM(E50:L50) -> 3000000
B52: Unit Sales Net Profit | C52: ='Proforma Resi'!M267 -> 0.2 | F52: =(F42+F44)*$C$52 -> 0 | G52: =(G42+G44)*$C$52 -> 2433350 | H52: =(H42+H44)*$C$52 -> 8094206.2 | I52: =(I42+I44)*$C$52 -> 8196456.2 | J52: =(J42+J44)*$C$52 -> 7687767.9 | K52: =(K42+K44)*$C$52 -> 0 | L52: =(L42+L44)*$C$52 -> 0 | M52: =(M42+M44)*$C$52 -> 0 | ... Q52: =(Q42+Q44)*$C$52 -> 0 | R52: =SUM(E52:L52) -> 26411780
B53: LESS Phantom Tax | C53: ='Proforma Resi'!M268 -> 0.3 | F53: =F52*$C$53 -> 0 | G53: =G52*$C$53 -> 730005 | H53: =H52*$C$53 -> 2428261.9 | I53: =I52*$C$53 -> 2458936.9 | J53: =J52*$C$53 -> 2306330.4 | K53: =K52*$C$53 -> 0 | L53: =L52*$C$53 -> 0 | M53: =M52*$C$53 -> 0 | ... Q53: =Q52*$C$53 -> 0 | R53: =SUM(E53:L53) -> 7923534.1
B54: Land Repayment | C54: 500000 | D54: Min pmt | G54: =MIN(MAX(G52-G53,$C$54),F56) -> 1703345 | H54: =MIN(MAX(H52-H53,$C$54),G56) -> 5665944.4 | I54: =MIN(MAX(I52-I53,$C$54),H56) -> 4630710.6 | J54: =MIN(MAX(J52-J53,$C$54),I56) -> 0 | K54: =MIN(MAX(K52-K53,$C$54),J56) -> 0 | L54: =MIN(MAX(L52-L53,$C$54),K56) -> 0 | M54: =MIN(MAX(M52-M53,$C$54),L56) -> 0 | N54: =MIN(MAX(N52-N53,$C$54),M56) -> 0 | ... Q54: =MIN(MAX(Q52-Q53,$C$54),P56) -> 0 | R54: =SUM(E54:L54) -> 12000000 | T54: =(R50+R54)/T46 -> 0.11358568 | U54: =Assumptions!Q7 -> 15000000 | V54: Total Land Acquisition
B56: Ending Land Balance | C56: =Assumptions!Q7 -> 15000000 | D56: Land value | F56: =C56-F50 -> 12000000 | G56: =F56-G54 -> 10296655 | H56: =G56-H54 -> 4630710.6 | I56: =H56-I54 -> 0 | J56: =I56-J54 -> 0 | K56: =J56-K54 -> 0 | L56: =K56-L54 -> 0 | M56: =L56-M54 -> 0 | N56: =M56-N54 -> 0 | ... Q56: =P56-Q54 -> 0
B57: Interest Cost | C57: =Assumptions!#REF! -> #REF! | F57: =F56*C57/2 -> #REF! | G57: =F56*$C$57 -> #REF! | H57: =G56*$C$57 -> #REF! | I57: =H56*$C$57 -> #REF! | J57: =I56*$C$57 -> #REF! | K57: =J56*$C$57 -> #REF! | L57: =K56*$C$57 -> #REF! | M57: =L56*$C$57 -> #REF! | N57: =M56*$C$57 -> #REF! | ... Q57: =P56*$C$57 -> #REF! | R57: =SUM(E57:Q57) -> #REF! | T57: =R57/T46 -> #REF!
B58: LAND & PROJECT ACQUISITION | E58: =SUM(E54:E57) -> 0 | F58: =F49+F50+F54+F57 -> #REF! | G58: =G49+G50+G54+G57 -> #REF! | H58: =H49+H50+H54+H57 -> #REF! | I58: =I49+I50+I54+I57 -> #REF! | J58: =J49+J50+J54+J57 -> #REF! | K58: =K49+K50+K54+K57 -> #REF! | L58: =L49+L50+L54+L57 -> #REF! | M58: =M49+M50+M54+M57 -> #REF! | ... Q58: =Q49+Q50+Q54+Q57 -> #REF! | R58: =SUM(E58:Q58) -> #REF! | T58: =+T54+T49+T57 -> #REF!
A60: 02a | B60: HARD COSTS - SITE INFRASTRUCTURE RESORT
B61: Infrastructure per Lot - SFR | C61: =F61/SUM(R7:R8) -> 451765.61 | F61: =(Assumptions!Q9*($T$7/SUM($T$7:$T$8))*Assumptions!P6/Assumptions!P6)/2 -> 5872952.9 | G61: =(Assumptions!Q9*($T$7/SUM($T$7:$T$8))*Assumptions!P6/Assumptions!P6)/2 -> 5872952.9 | H61: INCLUDES: Advanced Waste Water Treatment Plant, Water Main to Parcels, Sewer Main to Parcels, Goose Lake Rd Paving, New Well, Skiway Bridge, Skiway, Misc. | R61: =SUM(E61:P61) -> 11745906
B62: Infrastructure per Lot - Duplex/ Multi-unit | C62: =F62/SUM(R9:R10) -> 54234.903 | F62: =(Assumptions!Q9*($T$8/SUM($T$7:$T$8))*Assumptions!P6/Assumptions!P6)/2 -> 1627047.1 | G62: =(Assumptions!Q9*($T$8/SUM($T$7:$T$8))*Assumptions!P6/Assumptions!P6)/2 -> 1627047.1 | R62: =SUM(E62:P62) -> 3254094.2
B63: Developer Construction Contingency | C63: 0 | E63: =SUM(E61:E62)*$C$63 -> 0 | F63: =SUM(F61:F62)*$C$63 -> 0 | G63: =SUM(G61:G62)*$C$63 -> 0 | H63: =SUM(H61:H62)*$C$63 -> 0 | N63: =SUM(N61:N62)*$C$63 -> 0 | O63: =SUM(O61:O62)*$C$63 -> 0 | P63: =SUM(P61:P62)*$C$63 -> 0 | Q63: =SUM(Q61:Q62)*$C$63 -> 0 | R63: =SUM(E63:Q63) -> 0
B64: =B60 -> HARD COSTS - SITE INFRASTRUCTURE RESORT | E64: =SUM(E61:E63) -> 0 | F64: =SUM(F61:F63) -> 7500000 | G64: =SUM(G61:G63) -> 7500000 | H64: =SUM(H61:H63) -> 0 | I64: =SUM(I61:I63) -> 0 | J64: =SUM(J61:J63) -> 0 | K64: =SUM(K61:K63) -> 0 | L64: =SUM(L61:L63) -> 0 | ... P64: =SUM(P61:P63) -> 0 | R64: =SUM(E64:Q64) -> 15000000 | T64: =R64/$R$11 -> 348837.21 | U64: $/Lot
T65: =(R64-H43)/$T$46 -> #REF! | U65: of Sales
A66: 02a | B66: HARD COSTS - SITE INFRASTRUCTURE INTERNAL ROADS
B67: Infrastructure per Lot - SFR | C67: 85000 | F67: =+(F7+F8)*$C67 -> 170000 | G67: =+(G7+G8)*$C67 -> 255000 | H67: =+(H7+H8)*$C67 -> 425000 | I67: =+(I7+I8)*$C67 -> 255000 | J67: =+(J7+J8)*$C67 -> 0 | K67: =+(K7+K8)*$C67 -> 0 | L67: =+(L7+L8)*$C67 -> 0 | R67: =SUM(E67:P67) -> 1105000
B68: Infrastructure per Lot - Duplex | C68: 65000 | F68: =F9*$C68 -> 130000 | G68: =G9*$C68 -> 520000 | H68: =H9*$C68 -> 260000 | I68: =I9*$C68 -> 520000 | J68: =J9*$C68 -> 0 | K68: =K9*$C68 -> 0 | L68: =L9*$C68 -> 0 | R68: =SUM(E68:P68) -> 1430000
B69: Infrastructure per Lot - Multi-unit | C69: 25000 | F69: =F10*$C69 -> 0 | G69: =G10*$C69 -> 100000 | H69: =H10*$C69 -> 100000 | I69: =I10*$C69 -> 0 | J69: =J10*$C69 -> 0 | K69: =K10*$C69 -> 0 | L69: =L10*$C69 -> 0 | M69: =M10*$C69 -> 0 | ... P69: =P10*$C69 -> 0 | R69: =SUM(E69:P69) -> 200000
B70: Ski Tunnel | C70: 750000 | G70: =C70 -> 750000 | R70: =SUM(E70:P70) -> 750000
B71: Developer Construction Contingency | C71: 0.05 | E71: =SUM(E67:E68)*$C$71 -> 0 | F71: =SUM(F67:F68)*$C$71 -> 15000 | G71: =SUM(G67:G68)*$C$71 -> 38750 | H71: =SUM(H67:H68)*$C$71 -> 34250 | I71: =SUM(I67:I68)*$C$71 -> 38750 | J71: =SUM(J67:J68)*$C$71 -> 0 | K71: =SUM(K67:K68)*$C$71 -> 0 | L71: =SUM(L67:L68)*$C$71 -> 0 | M71: 0 | N71: 0 | O71: 0 | P71: 0 | Q71: 0 | R71: =SUM(E71:Q71) -> 126750
B72: =B66 -> HARD COSTS - SITE INFRASTRUCTURE INTERNAL ROADS | E72: =SUM(E67:E71) -> 0 | F72: =SUM(F67:F71) -> 315000 | G72: =SUM(G67:G71) -> 1663750 | H72: =SUM(H67:H71) -> 819250 | I72: =SUM(I67:I71) -> 813750 | J72: =SUM(J67:J71) -> 0 | K72: =SUM(K67:K71) -> 0 | L72: =SUM(L67:L71) -> 0 | ... P72: =SUM(P67:P71) -> 0 | R72: =SUM(E72:Q72) -> 3611750 | T72: =R72/$R$11 -> 83994.186 | U72: $/unit
T73: =R72/$T$46 -> 0.027349538 | U73: of Sales
A74: 02b | B74: HARD COSTS - HOMES: SFR Large
B75: Infrastructure (Utilities & Driveway) - SFR | C75: 50000 | F75: =((SUM(E$7)*$C75)*0.25)+((SUM(F$7)*$C75)*0.75) -> 37500 | G75: =((SUM(F$7)*$C75)*0.25)+((SUM(G$7)*$C75)*0.75) -> 50000 | H75: =((SUM(G$7)*$C75)*0.25)+((SUM(H$7)*$C75)*0.75) -> 200000 | I75: =((SUM(H$7)*$C75)*0.25)+((SUM(I$7)*$C75)*0.75) -> 175000 | J75: =((SUM(I$7)*$C75)*0.25)+((SUM(J$7)*$C75)*0.75) -> 37500 | K75: =((SUM(J$7)*$C75)*0.25)+((SUM(K$7)*$C75)*0.75) -> 0 | L75: =((SUM(K$7)*$C75)*0.25)+((SUM(L$7)*$C75)*0.75) -> 0 | M75: =((SUM(L$7)*$C75)*0.25)+((SUM(M$7)*$C75)*0.75) -> 0 | ... Q75: =((SUM(P$7)*$C75)*0.25)+((SUM(Q$7)*$C75)*0.75) -> 0 | R75: =SUM(E75:Q75) -> 500000 | T75: =R75/SUM($R$7) -> 50000 | U75: /UNIT | V75: Build Cost $/sf Check
B76: Vertical Construction Costs - SFR | C76: 635 | F76: =(IFERROR(SUMPRODUCT($D$7,E7)*$C76,0)*0.75)+(IFERROR(SUMPRODUCT($D$7,F7)*$C76,0)*0.25) -> 420687.5 | G76: =(IFERROR(SUMPRODUCT($D$7,F7)*$C76,0)*0.75)+(IFERROR(SUMPRODUCT($D$7,G7)*$C76,0)*0.25) -> 1682750 | H76: =(IFERROR(SUMPRODUCT($D$7,G7)*$C76,0)*0.75)+(IFERROR(SUMPRODUCT($D$7,H7)*$C76,0)*0.25) -> 3365500 | I76: =(IFERROR(SUMPRODUCT($D$7,H7)*$C76,0)*0.75)+(IFERROR(SUMPRODUCT($D$7,I7)*$C76,0)*0.25) -> 7572375 | J76: =(IFERROR(SUMPRODUCT($D$7,I7)*$C76,0)*0.75)+(IFERROR(SUMPRODUCT($D$7,J7)*$C76,0)*0.25) -> 3786187.5 | K76: =(IFERROR(SUMPRODUCT($D$7,J7)*$C76,0)*0.75)+(IFERROR(SUMPRODUCT($D$7,K7)*$C76,0)*0.25) -> 0 | L76: =(IFERROR(SUMPRODUCT($D$7,K7)*$C76,0)*0.75)+(IFERROR(SUMPRODUCT($D$7,L7)*$C76,0)*0.25) -> 0 | M76: =(IFERROR(SUMPRODUCT($D$7,L7)*$C76,0)*0.75)+(IFERROR(SUMPRODUCT($D$7,M7)*$C76,0)*0.25) -> 0 | ... Q76: =(IFERROR(SUMPRODUCT($D$7,P7)*$C76,0)*0.75)+(IFERROR(SUMPRODUCT($D$7,Q7)*$C76,0)*0.25) -> 0 | R76: =SUM(E76:Q76) -> 16827500 | T76: =R76/SUM($R$7) -> 1682750 | U76: AVE / UNIT | V76: =(R76)/V7 -> 635
B77: Landscape / Hardscape - SFR | C77: 50000 | F77: =SUM(E7)*$C77 -> 0 | G77: =SUM(F7)*$C77 -> 50000 | H77: =SUM(G7)*$C77 -> 50000 | I77: =SUM(H7)*$C77 -> 250000 | J77: =SUM(I7)*$C77 -> 150000 | K77: =SUM(J7)*$C77 -> 0 | L77: =SUM(K7)*$C77 -> 0 | M77: =SUM(L7)*$C77 -> 0 | ... Q77: =SUM(P7)*$C77 -> 0 | R77: =SUM(E77:Q77) -> 500000 | T77: =R77/SUM($R$7) -> 50000 | U77: /UNIT
B78: Construction Cost Escalation | C78: 0.05 | F78: =SUM(F75:F77,E78)*$C78 -> 22909.375 | G78: =SUM(G75:G77,F78)*$C78 -> 90282.969 | H78: =SUM(H75:H77,G78)*$C78 -> 185289.15 | I78: =SUM(I75:I77,H78)*$C78 -> 409133.21 | J78: =SUM(J75:J77,I78)*$C78 -> 219141.04 | L78: =SUM(L75:L77,K78)*$C78 -> 0 | M78: =SUM(M75:M77,L78)*$C78 -> 0 | R78: =SUM(E78:Q78) -> 926755.73 | T78: =R78/SUM($R$7) -> 92675.573 | U78: AVE / UNIT
B79: Developer Construction Contingency | C79: 0.035 | E79: =SUM(E74:E77)*$C79 -> 0 | F79: =SUM(F74:F78)*$C79 -> 16838.391 | G79: =SUM(G74:G78)*$C79 -> 65556.154 | H79: =SUM(H74:H78)*$C79 -> 133027.62 | I79: =SUM(I74:I78)*$C79 -> 294227.79 | J79: =SUM(J74:J78)*$C79 -> 146749 | K79: =SUM(K74:K78)*$C79 -> 0 | L79: =SUM(L74:L78)*$C79 -> 0 | M79: =SUM(M74:M77)*$C79 -> 0 | N79: =SUM(N74:N77)*$C79 -> 0 | O79: =SUM(O74:O77)*$C79 -> 0 | P79: =SUM(P74:P77)*$C79 -> 0 | Q79: =SUM(Q74:Q77)*$C79 -> 0 | R79: =SUM(E79:Q79) -> 656398.95 | T79: =R79/SUM($R$7) -> 65639.895 | U79: AVE / UNIT | V79: Total Cost $/sf Check
B80: =B74 -> HARD COSTS - HOMES: SFR Large | E80: =SUM(E74:E79) -> 0 | F80: =SUM(F74:F79) -> 497935.27 | G80: =SUM(G74:G79) -> 1938589.1 | H80: =SUM(H74:H79) -> 3933816.8 | I80: =SUM(I74:I79) -> 8700736 | J80: =SUM(J74:J79) -> 4339577.5 | K80: =SUM(K74:K79) -> 0 | L80: =SUM(L74:L79) -> 0 | ... Q80: =SUM(Q74:Q79) -> 0 | R80: =SUM(E80:Q80) -> 19410655 | T80: =R80/SUM($R$7) -> 1941065.5 | U80: AVE / UNIT | V80: =R80/V7 -> 732.47754
T81: {=R80/SUMPRODUCT(D7*F7:Q7*F$23:Q$23)} -> 0.47410556 | U81: of Sales
A82: 02b | B82: HARD COSTS - HOMES: SFR Small
B83: Infrastructure (Utilities & Driveway) - SFR | C83: 50000 | F83: =((SUM(E$8)*$C83)*0.25)+((SUM(F$8)*$C83)*0.75) -> 37500 | G83: =((SUM(F$8)*$C83)*0.25)+((SUM(G$8)*$C83)*0.75) -> 87500 | H83: =((SUM(G$8)*$C83)*0.25)+((SUM(H$8)*$C83)*0.75) -> 25000 | I83: =((SUM(H$8)*$C83)*0.25)+((SUM(I$8)*$C83)*0.75) -> 0 | J83: =((SUM(I$8)*$C83)*0.25)+((SUM(J$8)*$C83)*0.75) -> 0 | K83: =((SUM(J$8)*$C83)*0.25)+((SUM(K$8)*$C83)*0.75) -> 0 | L83: =((SUM(K$8)*$C83)*0.25)+((SUM(L$8)*$C83)*0.75) -> 0 | M83: =((SUM(L$8)*$C83)*0.25)+((SUM(M$8)*$C83)*0.75) -> 0 | ... Q83: =((SUM(P$8)*$C83)*0.25)+((SUM(Q$8)*$C83)*0.75) -> 0 | R83: =SUM(E83:Q83) -> 150000 | T83: =R83/SUM($R$8) -> 50000 | U83: /UNIT | V83: Build Cost $/sf Check
B84: Vertical Construction Costs - SFR | C84: 650 | F84: =(IFERROR((SUMPRODUCT($D$8,E8))*$C84,0)*0.75)+(IFERROR((SUMPRODUCT($D$8,F8))*$C84,0)*0.25) -> 390812.5 | G84: =(IFERROR((SUMPRODUCT($D$8,F8))*$C84,0)*0.75)+(IFERROR((SUMPRODUCT($D$8,G8))*$C84,0)*0.25) -> 1954062.5 | H84: =(IFERROR((SUMPRODUCT($D$8,G8))*$C84,0)*0.75)+(IFERROR((SUMPRODUCT($D$8,H8))*$C84,0)*0.25) -> 2344875 | I84: =(IFERROR((SUMPRODUCT($D$8,H8))*$C84,0)*0.75)+(IFERROR((SUMPRODUCT($D$8,I8))*$C84,0)*0.25) -> 0 | J84: =(IFERROR((SUMPRODUCT($D$8,I8))*$C84,0)*0.75)+(IFERROR((SUMPRODUCT($D$8,J8))*$C84,0)*0.25) -> 0 | K84: =(IFERROR((SUMPRODUCT($D$8,J8))*$C84,0)*0.75)+(IFERROR((SUMPRODUCT($D$8,K8))*$C84,0)*0.25) -> 0 | L84: =(IFERROR((SUMPRODUCT($D$8,K8))*$C84,0)*0.75)+(IFERROR((SUMPRODUCT($D$8,L8))*$C84,0)*0.25) -> 0 | M84: =(IFERROR((SUMPRODUCT($D$8,L8))*$C84,0)*0.75)+(IFERROR((SUMPRODUCT($D$8,M8))*$C84,0)*0.25) -> 0 | ... Q84: =(IFERROR((SUMPRODUCT($D$8,P8))*$C84,0)*0.75)+(IFERROR((SUMPRODUCT($D$8,Q8))*$C84,0)*0.25) -> 0 | R84: =SUM(E84:Q84) -> 4689750 | T84: =R84/SUM($R$8) -> 1563250 | U84: AVE / UNIT | V84: =(R84)/V8 -> 650
B85: Landscape / Hardscape - SFR | C85: 50000 | G85: =SUM(F8*$C85) -> 50000 | H85: =SUM(G8*$C85) -> 100000 | I85: =SUM(H8*$C85) -> 0 | J85: =SUM(I8*$C85) -> 0 | K85: =SUM(J8*$C85) -> 0 | L85: =SUM(K8*$C85) -> 0 | M85: =SUM(L8*$C85) -> 0 | N85: =SUM(M8*$C85) -> 0 | ... Q85: =SUM(P8*$C85) -> 0 | R85: =SUM(E85:Q85) -> 150000 | T85: =R85/SUM($R$8) -> 50000 | U85: /UNIT
B86: Construction Cost Escalation | C86: 0.05 | F86: =SUM(F83:F85,E86)*$C86 -> 21415.625 | G86: =SUM(G83:G85,F86)*$C86 -> 105648.91 | H86: =SUM(H83:H85,G86)*$C86 -> 128776.2 | I86: =SUM(I83:I85,H86)*$C86 -> 6438.8098 | J86: =SUM(J83:J85,I86)*$C86 -> 321.94049 | R86: =SUM(E86:Q86) -> 262601.48 | T86: =R86/SUM($R$8) -> 87533.826 | U86: AVE / UNIT
B87: Developer Construction Contingency | C87: 0.035 | E87: =SUM(E82:E85)*$C87 -> 0 | F87: =SUM(F82:F86)*$C87 -> 15740.484 | G87: =SUM(G82:G86)*$C87 -> 76902.399 | H87: =SUM(H82:H86)*$C87 -> 90952.792 | I87: =SUM(I82:I86)*$C87 -> 225.35834 | J87: =SUM(J82:J86)*$C87 -> 11.267917 | K87: =SUM(K82:K86)*$C87 -> 0 | L87: =SUM(L82:L86)*$C87 -> 0 | M87: =SUM(M82:M85)*$C87 -> 0 | N87: =SUM(N82:N85)*$C87 -> 0 | O87: =SUM(O82:O85)*$C87 -> 0 | P87: =SUM(P82:P85)*$C87 -> 0 | Q87: =SUM(Q82:Q85)*$C87 -> 0 | R87: =SUM(E87:Q87) -> 183832.3 | T87: =R87/SUM($R$8) -> 61277.434 | U87: AVE / UNIT | V87: Total Cost $/sf Check
B88: =B82 -> HARD COSTS - HOMES: SFR Small | E88: =SUM(E82:E87) -> 0 | F88: =SUM(F82:F87) -> 465468.61 | G88: =SUM(G82:G87) -> 2274113.8 | H88: =SUM(H82:H87) -> 2689604 | I88: =SUM(I82:I87) -> 6664.1681 | J88: =SUM(J82:J87) -> 333.20841 | K88: =SUM(K82:K87) -> 0 | L88: =SUM(L82:L87) -> 0 | ... Q88: =SUM(Q82:Q87) -> 0 | R88: =SUM(E88:Q88) -> 5436183.8 | T88: =R88/SUM($R$8) -> 1812061.3 | U88: AVE / UNIT | V88: =R88/V8 -> 753.45583
T89: {=R88/SUMPRODUCT(D8*F8:Q8*F$24:Q$24)} -> 0.51962471 | U89: of Sales
A90: 02b | B90: HARD COSTS - HOMES: Duplex Small
B91: Infrastructure (Utilities & Driveway) - Duplex | C91: 30000 | F91: =((SUM(E$9)*$C91)*0.25)+((SUM(F$9)*$C91)*0.75) -> 45000 | G91: =((SUM(F$9)*$C91)*0.25)+((SUM(G$9)*$C91)*0.75) -> 195000 | H91: =((SUM(G$9)*$C91)*0.25)+((SUM(H$9)*$C91)*0.75) -> 150000 | I91: =((SUM(H$9)*$C91)*0.25)+((SUM(I$9)*$C91)*0.75) -> 210000 | J91: =((SUM(I$9)*$C91)*0.25)+((SUM(J$9)*$C91)*0.75) -> 60000 | K91: =((SUM(J$9)*$C91)*0.25)+((SUM(K$9)*$C91)*0.75) -> 0 | L91: =((SUM(K$9)*$C91)*0.25)+((SUM(L$9)*$C91)*0.75) -> 0 | M91: =((SUM(L$9)*$C91)*0.25)+((SUM(M$9)*$C91)*0.75) -> 0 | ... Q91: =((SUM(P$9)*$C91)*0.25)+((SUM(Q$9)*$C91)*0.75) -> 0 | R91: =SUM(E91:Q91) -> 660000 | T91: =R91/SUM($R$9) -> 30000 | U91: /UNIT | V91: Build Cost $/sf Check
B92: Vertical Construction Costs - Duplex | C92: 615 | F92: =(IFERROR((SUMPRODUCT($D$9,E9))*$C92,0)*0.75)+(IFERROR((SUMPRODUCT($D$9,F9))*$C92,0)*0.25) -> 548272.5 | G92: =(IFERROR((SUMPRODUCT($D$9,F9))*$C92,0)*0.75)+(IFERROR((SUMPRODUCT($D$9,G9))*$C92,0)*0.25) -> 3837907.5 | H92: =(IFERROR((SUMPRODUCT($D$9,G9))*$C92,0)*0.75)+(IFERROR((SUMPRODUCT($D$9,H9))*$C92,0)*0.25) -> 7675815 | I92: =(IFERROR((SUMPRODUCT($D$9,H9))*$C92,0)*0.75)+(IFERROR((SUMPRODUCT($D$9,I9))*$C92,0)*0.25) -> 5482725 | J92: =(IFERROR((SUMPRODUCT($D$9,I9))*$C92,0)*0.75)+(IFERROR((SUMPRODUCT($D$9,J9))*$C92,0)*0.25) -> 6579270 | K92: =(IFERROR((SUMPRODUCT($D$9,J9))*$C92,0)*0.75)+(IFERROR((SUMPRODUCT($D$9,K9))*$C92,0)*0.25) -> 0 | L92: =(IFERROR((SUMPRODUCT($D$9,K9))*$C92,0)*0.75)+(IFERROR((SUMPRODUCT($D$9,L9))*$C92,0)*0.25) -> 0 | M92: =(IFERROR((SUMPRODUCT($D$9,L9))*$C92,0)*0.75)+(IFERROR((SUMPRODUCT($D$9,M9))*$C92,0)*0.25) -> 0 | ... Q92: =(IFERROR((SUMPRODUCT($D$9,P9))*$C92,0)*0.75)+(IFERROR((SUMPRODUCT($D$9,Q9))*$C92,0)*0.25) -> 0 | R92: =SUM(E92:Q92) -> 24123990 | T92: =R92/SUM($R$9) -> 1096545 | U92: AVE / UNIT | V92: =(R92)/V9 -> 615
B93: Landscape / Hardscape - Duplex | C93: 40000 | G93: =+$C$93*F9 -> 80000 | H93: =+$C$93*G9 -> 320000 | I93: =+$C$93*H9 -> 160000 | J93: =+$C$93*I9 -> 320000 | K93: =+$C$93*J9 -> 0 | L93: =+$C$93*K9 -> 0 | M93: =+$C$93*L9 -> 0 | N93: =+$C$93*M9 -> 0 | ... Q93: =+$C$93*P9 -> 0 | R93: =SUM(E93:Q93) -> 880000 | T93: =R93/SUM($R$9) -> 40000 | U93: /UNIT
B94: Construction Cost Escalation | C94: 0.05 | F94: =SUM(F91:F93,E94)*$C94 -> 29663.625 | G94: =SUM(G91:G93,F94)*$C94 -> 207128.56 | H94: =SUM(H91:H93,G94)*$C94 -> 417647.18 | I94: =SUM(I91:I93,H94)*$C94 -> 313518.61 | J94: =SUM(J91:J93,I94)*$C94 -> 363639.43 | R94: =SUM(E94:Q94) -> 1331597.4 | T94: =R94/SUM($R$9) -> 60527.154 | U94: AVE / UNIT
B95: Developer Construction Contingency | C95: 0.035 | E95: =SUM(E90:E93)*$C95 -> 0 | F95: =SUM(F90:F94)*$C95 -> 21802.764 | G95: =SUM(G90:G94)*$C95 -> 151201.26 | H95: =SUM(H90:H94)*$C95 -> 299721.18 | I95: =SUM(I90:I94)*$C95 -> 215818.53 | J95: =SUM(J90:J94)*$C95 -> 256301.83 | K95: =SUM(K90:K94)*$C95 -> 0 | L95: =SUM(L90:L94)*$C95 -> 0 | M95: =SUM(M90:M93)*$C95 -> 0 | N95: =SUM(N90:N93)*$C95 -> 0 | O95: =SUM(O90:O93)*$C95 -> 0 | P95: =SUM(P90:P93)*$C95 -> 0 | Q95: =SUM(Q90:Q93)*$C95 -> 0 | R95: =SUM(E95:Q95) -> 944845.56 | T95: =R95/SUM($R$9) -> 42947.525 | U95: AVE / UNIT | V95: Total Cost $/sf Check
B96: =B90 -> HARD COSTS - HOMES: Duplex Small | E96: =SUM(E90:E95) -> 0 | F96: =SUM(F90:F95) -> 644738.89 | G96: =SUM(G90:G95) -> 4471237.3 | H96: =SUM(H90:H95) -> 8863183.4 | I96: =SUM(I90:I95) -> 6382062.1 | J96: =SUM(J90:J95) -> 7579211.3 | K96: =SUM(K90:K95) -> 0 | L96: =SUM(L90:L95) -> 0 | ... Q96: =SUM(Q90:Q95) -> 0 | R96: =SUM(E96:Q96) -> 27940433 | T96: =R96/SUM($R$9) -> 1270019.7 | U96: AVE / UNIT | V96: =R96/V9 -> 712.29371
T97: {=R96/SUMPRODUCT(D9*F9:Q9*F$25:Q$25)} -> 0.48403905 | U97: of Sales
A98: 02b | B98: HARD COSTS - HOMES: Multi-Unit
B99: Infrastructure (Utilities & Driveway) - Multi-unit | C99: =35000/2 -> 17500 | F99: =((SUM(E$10)*$C99)*0.25)+((SUM(F$10)*$C99)*0.75) -> 0 | G99: =((SUM(F$10)*$C99)*0.25)+((SUM(G$10)*$C99)*0.75) -> 52500 | H99: =((SUM(G$10)*$C99)*0.25)+((SUM(H$10)*$C99)*0.75) -> 70000 | I99: =((SUM(H$10)*$C99)*0.25)+((SUM(I$10)*$C99)*0.75) -> 17500 | J99: =((SUM(I$10)*$C99)*0.25)+((SUM(J$10)*$C99)*0.75) -> 0 | K99: =((SUM(J$10)*$C99)*0.25)+((SUM(K$10)*$C99)*0.75) -> 0 | L99: =((SUM(K$10)*$C99)*0.25)+((SUM(L$10)*$C99)*0.75) -> 0 | M99: =((SUM(L$10)*$C99)*0.25)+((SUM(M$10)*$C99)*0.75) -> 0 | ... Q99: =((SUM(P$10)*$C99)*0.25)+((SUM(Q$10)*$C99)*0.75) -> 0 | R99: =SUM(E99:Q99) -> 140000 | T99: =R99/SUM($R$10) -> 17500 | U99: /UNIT | V99: Build Cost $/sf Check
B100: Underground Parking - per unit $ | C100: 100000 | F100: =$C100*F10 -> 0 | G100: =$C100*G10 -> 400000 | H100: =$C100*H10 -> 400000 | I100: =$C100*I10 -> 0 | J100: =$C100*J10 -> 0 | K100: =$C100*K10 -> 0 | L100: =$C100*L10 -> 0 | M100: =$C100*M10 -> 0 | ... Q100: =$C100*Q10 -> 0 | R100: =SUM(E100:Q100) -> 800000 | T100: =R100/SUM($R$10) -> 100000 | U100: /UNIT
B101: Vertical Construction Costs - Multi-unit | C101: 550 | F101: =(IFERROR((SUMPRODUCT($D$10,E10))*$C101,0)*0.75)+(IFERROR((SUMPRODUCT($D$10,F10))*$C101,0)*0.25) -> 0 | G101: =(IFERROR((SUMPRODUCT($D$10,F10))*$C101,0)*0.75)+(IFERROR((SUMPRODUCT($D$10,G10))*$C101,0)*0.25) -> 742500 | H101: =(IFERROR((SUMPRODUCT($D$10,G10))*$C101,0)*0.75)+(IFERROR((SUMPRODUCT($D$10,H10))*$C101,0)*0.25) -> 2970000 | I101: =(IFERROR((SUMPRODUCT($D$10,H10))*$C101,0)*0.75)+(IFERROR((SUMPRODUCT($D$10,I10))*$C101,0)*0.25) -> 2227500 | J101: =(IFERROR((SUMPRODUCT($D$10,I10))*$C101,0)*0.75)+(IFERROR((SUMPRODUCT($D$10,J10))*$C101,0)*0.25) -> 0 | K101: =(IFERROR((SUMPRODUCT($D$10,J10))*$C101,0)*0.75)+(IFERROR((SUMPRODUCT($D$10,K10))*$C101,0)*0.25) -> 0 | L101: =(IFERROR((SUMPRODUCT($D$10,K10))*$C101,0)*0.75)+(IFERROR((SUMPRODUCT($D$10,L10))*$C101,0)*0.25) -> 0 | M101: =(IFERROR((SUMPRODUCT($D$10,L10))*$C101,0)*0.75)+(IFERROR((SUMPRODUCT($D$10,M10))*$C101,0)*0.25) -> 0 | ... Q101: =(IFERROR((SUMPRODUCT($D$10,P10))*$C101,0)*0.75)+(IFERROR((SUMPRODUCT($D$10,Q10))*$C101,0)*0.25) -> 0 | R101: =SUM(E101:Q101) -> 5940000 | T101: =R101/SUM($R$10) -> 742500 | U101: AVE / UNIT | V101: =(R101)/V10 -> 550
B102: Landscape / Hardscape - Multi-unit | C102: 15000 | G102: =SUM(F10*$C102) -> 0 | H102: =SUM(G10*$C102) -> 60000 | I102: =SUM(H10*$C102) -> 60000 | J102: =SUM(I10*$C102) -> 0 | K102: =SUM(J10*$C102) -> 0 | L102: =SUM(K10*$C102) -> 0 | M102: =SUM(L10*$C102) -> 0 | N102: =SUM(M10*$C102) -> 0 | ... Q102: =SUM(P10*$C102) -> 0 | R102: =SUM(E102:Q102) -> 120000 | T102: =R102/SUM($R$10) -> 15000 | U102: /UNIT
B103: Construction Cost Escalation | C103: 0.05 | G103: =SUM(G99:G102,F103)*$C103 -> 59750 | H103: =SUM(H99:H102,G103)*$C103 -> 177987.5 | I103: =SUM(I99:I102,H103)*$C103 -> 124149.38 | J103: =SUM(J99:J102,I103)*$C103 -> 6207.4688 | R103: =SUM(E103:Q103) -> 368094.34 | T103: =R103/SUM($R$10) -> 46011.793 | U103: AVE / UNIT
B104: Developer Construction Contingency | C104: 0.035 | E104: =SUM(E98:E102)*$C104 -> 0 | F104: =SUM(F98:F103)*$C104 -> 0 | G104: =SUM(G98:G103)*$C104 -> 43916.25 | H104: =SUM(H98:H103)*$C104 -> 128729.56 | I104: =SUM(I98:I103)*$C104 -> 85020.228 | J104: =SUM(J98:J103)*$C104 -> 217.26141 | K104: =SUM(K98:K103)*$C104 -> 0 | L104: =SUM(L98:L103)*$C104 -> 0 | M104: =SUM(M98:M102)*$C104 -> 0 | N104: =SUM(N98:N102)*$C104 -> 0 | O104: =SUM(O98:O102)*$C104 -> 0 | P104: =SUM(P98:P102)*$C104 -> 0 | Q104: =SUM(Q98:Q102)*$C104 -> 0 | R104: =SUM(E104:Q104) -> 257883.3 | T104: =R104/SUM($R$10) -> 32235.413 | U104: AVE / UNIT | V104: Total Cost $/sf Check
B105: =B98 -> HARD COSTS - HOMES: Multi-Unit | E105: =SUM(E98:E104) -> 0 | F105: =SUM(F98:F104) -> 0 | G105: =SUM(G98:G104) -> 1298666.2 | H105: =SUM(H98:H104) -> 3806717.1 | I105: =SUM(I98:I104) -> 2514169.6 | J105: =SUM(J98:J104) -> 6424.7302 | K105: =SUM(K98:K104) -> 0 | L105: =SUM(L98:L104) -> 0 | ... Q105: =SUM(Q98:Q104) -> 0 | R105: =SUM(E105:Q105) -> 7625977.6 | T105: =R105/SUM($R$10) -> 953247.21 | U105: AVE / UNIT | V105: =R105/V10 -> 706.10904
T106: {=R105/SUMPRODUCT(D10*F10:Q10*F$26:Q$26)} -> 0.48697175 | U106: of Sales
...

Sheet Returns Resi
B1: BRUNDAGE - Resi DEVELOPMENT: RETURNS
B2: Returns Analysis
B4: PROJECT FINANCING ANALYSIS | F4: PROJECT RETURNS ANALYSIS | J4: SENSITIVITY ANALYSIS - PROJECT-LEVEL RETURNS, LEVERED
B5: TOTAL PROJECT CAPITAL NEEDS | D5: =SUM('Proforma Resi'!R32,'Proforma Resi'!R35) -> #REF! | F5: TOTAL RETURN | H5: =D54 -> #REF!
B6: TOTAL PROJECT VALUE (PV of FINAL BUILD OUT) | D6: ='Proforma Resi'!T11 -> 117820000 | F6: INVESTED CAPITAL | H6: =D55 -> #REF! | J6: Metric: | K6: IRR | L6: Sales Price Scalar
B7: STARTING SPEC DEVELOPMENT VALUE | D7: ='Proforma Resi'!G44+'Proforma Resi'!F42 -> 12166750 | F7: NET PROFIT | H7: =D56 -> #REF! | J7: Vertical Const. Costs Scalar | K7: =SUMIF(F5:F10,K6,H5:H10) -> #REF! | L7: =M7-10% -> 0.8 | M7: =N7-10% -> 0.9 | N7: 1 | O7: =N7+10% -> 1.1 | P7: =O7+10% -> 1.2
B8: EQUITY to SPEC DEV VALUE (ETV) | D8: ='Proforma Resi'!Y30 -> #REF! | F8: EQUITY MULTIPLE | H8: =H5/H6 -> #REF! | K8: =K9-10% -> 0.8 | L8: #REF! | M8: #REF! | N8: #REF! | O8: #REF! | P8: #REF!
B9: LOAN to COST (LTC) | D9: ='Proforma Resi'!Y32 -> #REF! | F9: ROI | H9: =H7/H6 -> #REF! | K9: =K10-10% -> 0.9 | L9: #REF! | M9: #REF! | N9: #REF! | O9: #REF! | P9: #REF!
B10: LOAN to VALUE (LTV) | D10: ='Proforma Resi'!Y31 -> #REF! | F10: IRR | H10: =XIRR(F56:N56,F20:N20) -> #REF! | K10: 1 | L10: #REF! | M10: #REF! | N10: #REF! | O10: #REF! | P10: #REF!
K11: =K10+10% -> 1.1 | L11: #REF! | M11: #REF! | N11: #REF! | O11: #REF! | P11: #REF!
B12: BUSINESS CASE ANALYSIS | K12: =K11+10% -> 1.2 | L12: #REF! | M12: #REF! | N12: #REF! | O12: #REF! | P12: #REF!
B13: TOTAL PROJECT REVENUE (less brokers fees): | D13: =('Proforma Resi'!R44+'Proforma Resi'!R42)-'Proforma Resi'!R172 -> 1.2545596e+08 | J13: Current Assumptions
B14: - TOTAL PROJECT COST | D14: ='Proforma Resi'!R197-'Proforma Resi'!R172+'Proforma Resi'!R202+'Proforma Resi'!R201 -> #REF! | J14: Vertical Const. Costs Scalar | L14: 1
B15: = NET PROFIT | D15: =D13-D14 -> #REF! | J15: Sales Price Scalar | L15: 1
B16: NET PROFIT %: | D16: =D15/D13 -> #REF!
B17: RETURN on EQUITY/CAPTIAL (ROE): | D17: =D15/H6 -> #REF!
F18: ='Proforma Resi'!E3 -> 0 | G18: ='Proforma Resi'!F3 -> 1 | H18: ='Proforma Resi'!G3 -> 2 | I18: ='Proforma Resi'!H3 -> 3 | J18: ='Proforma Resi'!I3 -> 4 | K18: ='Proforma Resi'!J3 -> 5 | L18: ='Proforma Resi'!K3 -> 6 | M18: ='Proforma Resi'!L3 -> 7 | ... R18: ='Proforma Resi'!Q3 -> 12
F19: =Assumptions!C6 -> 2025 | G19: =F19+1 -> 2026 | H19: =G19+1 -> 2027 | I19: =H19+1 -> 2028 | J19: =I19+1 -> 2029 | K19: =J19+1 -> 2030 | L19: =K19+1 -> 2031 | M19: =L19+1 -> 2032 | N19: =M19+1 -> 2033 | ... R19: =Q19+1 -> 2037
B20: SUMMARY OF RETURNS | F20: =DATE(F19,12,31) -> 46022 | G20: =EDATE(F20,12) -> 46387 | H20: =EDATE(G20,12) -> 46752 | I20: =EDATE(H20,12) -> 47118 | J20: =EDATE(I20,12) -> 47483 | K20: =EDATE(J20,12) -> 47848 | L20: =EDATE(K20,12) -> 48213 | M20: =EDATE(L20,12) -> 48579 | N20: =EDATE(M20,12) -> 48944 | ... R20: =EDATE(Q20,12) -> 50405
B21: Preferred Members 1 (PM1) Returns
B22: Land Repayment | D22: =SUM(F22:R22) -> 15000000 | F22: ='Proforma Resi'!E50+'Proforma Resi'!E54 -> 0 | G22: ='Proforma Resi'!F50+'Proforma Resi'!F54 -> 3000000 | H22: ='Proforma Resi'!G50+'Proforma Resi'!G54 -> 1703345 | I22: ='Proforma Resi'!H50+'Proforma Resi'!H54 -> 5665944.4 | J22: ='Proforma Resi'!I50+'Proforma Resi'!I54 -> 4630710.6 | K22: ='Proforma Resi'!J50+'Proforma Resi'!J54 -> 0 | L22: ='Proforma Resi'!K50+'Proforma Resi'!K54 -> 0 | M22: ='Proforma Resi'!L50+'Proforma Resi'!L54 -> 0 | ... R22: ='Proforma Resi'!Q50+'Proforma Resi'!Q54 -> 0
B23: Interest | D23: =SUM(F23:R23) -> #REF! | F23: ='Proforma Resi'!E57 -> 0 | G23: ='Proforma Resi'!F57 -> #REF! | H23: ='Proforma Resi'!G57 -> #REF! | I23: ='Proforma Resi'!H57 -> #REF! | J23: ='Proforma Resi'!I57 -> #REF! | K23: ='Proforma Resi'!J57 -> #REF! | L23: ='Proforma Resi'!K57 -> #REF! | M23: ='Proforma Resi'!L57 -> #REF! | ... R23: ='Proforma Resi'!Q57 -> #REF!
B24: ="Additional Profit Split ("&TEXT(Assumptions!#REF!,"0%")&")" -> #REF! | D24: =SUM(F24:R24) -> #REF! | F24: ='Proforma Resi'!E223 -> 0 | G24: ='Proforma Resi'!F223 -> #REF! | H24: ='Proforma Resi'!G223 -> #REF! | I24: ='Proforma Resi'!H223 -> #REF! | J24: ='Proforma Resi'!I223 -> #REF! | K24: ='Proforma Resi'!J223 -> #REF! | L24: ='Proforma Resi'!K223 -> #REF! | M24: ='Proforma Resi'!L223 -> #REF! | ... R24: ='Proforma Resi'!Q223 -> #REF!
B25: Total PM Distributions | D25: =SUM(F25:R25) -> #REF! | F25: =SUM(F22:F24) -> 0 | G25: =SUM(G22:G24) -> #REF! | H25: =SUM(H22:H24) -> #REF! | I25: =SUM(I22:I24) -> #REF! | J25: =SUM(J22:J24) -> #REF! | K25: =SUM(K22:K24) -> #REF! | L25: =SUM(L22:L24) -> #REF! | M25: =SUM(M22:M24) -> #REF! | ... R25: =SUM(R22:R24) -> #REF!
B26: Total PM Contributions | D26: =SUM(F26:R26) -> 15000000 | G26: ='Proforma Resi'!C56 -> 15000000 | H26: 0 | I26: 0 | J26: 0 | K26: 0 | L26: 0 | M26: 0 | N26: 0 | O26: 0 | P26: 0 | Q26: 0 | R26: 0
B27: PM Net Profit / Cash Flows | D27: =SUM(F27:R27) -> #REF! | F27: =F25-F26 -> 0 | G27: =G25-G26 -> #REF! | H27: =H25-H26 -> #REF! | I27: =I25-I26 -> #REF! | J27: =J25-J26 -> #REF! | K27: =K25-K26 -> #REF! | L27: =L25-L26 -> #REF! | M27: =M25-M26 -> #REF! | ... R27: =R25-R26 -> #REF!
B28: PM IRR | F28: =XIRR(G27:R27,G20:R20) -> #REF!
B29: PM Equity Multiple | F29: =SUMIF(F27:R27,">0")/-SUMIF(F27:R27,"<0") -> #DIV/0!
B30: Cumulative PM (Equity) Cash Position | F30: =F27+E30 -> 0 | G30: =G27+F30 -> #REF! | H30: =H27+G30 -> #REF! | I30: =I27+H30 -> #REF! | J30: =J27+I30 -> #REF! | K30: =K27+J30 -> #REF! | L30: =L27+K30 -> #REF! | M30: =M27+L30 -> #REF! | ... R30: =R27+Q30 -> #REF!
B32: Preferred Members 2 (PM2) Returns
B33: Preferred Returns | D33: =SUM(F33:R33) -> 0 | F33: ='Proforma Resi'!E221 -> 0 | G33: ='Proforma Resi'!F221 -> 0 | H33: ='Proforma Resi'!G221 -> 0 | I33: ='Proforma Resi'!H221 -> 0 | J33: ='Proforma Resi'!I221 -> 0 | K33: ='Proforma Resi'!J221 -> 0 | L33: ='Proforma Resi'!K221 -> 0 | M33: ='Proforma Resi'!L221 -> 0 | ... R33: ='Proforma Resi'!Q221 -> 0
B34: ="Additional Profit Split ("&TEXT(Assumptions!#REF!,"0%")&")" -> #REF! | D34: =SUM(F34:R34) -> #REF! | F34: ='Proforma Resi'!E224 -> 0 | G34: ='Proforma Resi'!F224 -> #REF! | H34: ='Proforma Resi'!G224 -> #REF! | I34: ='Proforma Resi'!H224 -> #REF! | J34: ='Proforma Resi'!I224 -> #REF! | K34: ='Proforma Resi'!J224 -> #REF! | L34: ='Proforma Resi'!K224 -> #REF! | M34: ='Proforma Resi'!L224 -> #REF! | ... R34: ='Proforma Resi'!Q224 -> #REF!
B35: Total PM Distributions | D35: =SUM(F35:R35) -> #REF! | F35: =SUM(F33:F34) -> 0 | G35: =SUM(G33:G34) -> #REF! | H35: =SUM(H33:H34) -> #REF! | I35: =SUM(I33:I34) -> #REF! | J35: =SUM(J33:J34) -> #REF! | K35: =SUM(K33:K34) -> #REF! | L35: =SUM(L33:L34) -> #REF! | M35: =SUM(M33:M34) -> #REF! | ... R35: =SUM(R33:R34) -> #REF!
B36: Total PM Contributions | D36: =SUM(F36:R36) -> #REF! | F36: ='Proforma Resi'!E31 -> 0 | G36: ='Proforma Resi'!F31 -> #REF! | H36: ='Proforma Resi'!G31 -> 0 | I36: ='Proforma Resi'!H31 -> 0 | J36: ='Proforma Resi'!I31 -> 0 | K36: ='Proforma Resi'!J31 -> 0 | L36: ='Proforma Resi'!K31 -> 0 | M36: ='Proforma Resi'!L31 -> 0 | ... R36: ='Proforma Resi'!Q31 -> 0
B37: PM Net Profit / Cash Flows | D37: =SUM(F37:R37) -> #REF! | F37: =F35-F36 -> 0 | G37: =G35-G36 -> #REF! | H37: =H35-H36 -> #REF! | I37: =I35-I36 -> #REF! | J37: =J35-J36 -> #REF! | K37: =K35-K36 -> #REF! | L37: =L35-L36 -> #REF! | M37: =M35-M36 -> #REF! | ... R37: =R35-R36 -> #REF!
B38: PM IRR | F38: =XIRR(G37:R37,G20:R20) -> #REF!
B39: PM Equity Multiple | F39: =SUMIF(F37:R37,">0")/-SUMIF(F37:R37,"<0") -> #DIV/0!
B40: Cumulative PM (Equity) Cash Position | F40: =F37+E40 -> 0 | G40: =G37+F40 -> #REF! | H40: =H37+G40 -> #REF! | I40: =I37+H40 -> #REF! | J40: =J37+I40 -> #REF! | K40: =K37+J40 -> #REF! | L40: =L37+K40 -> #REF! | M40: =M37+L40 -> #REF! | ... R40: =R37+Q40 -> #REF!
B42: Common Members (CM) Returns
B43: ="CM Profit Split ("&TEXT(Assumptions!#REF!,"0%")&")" -> #REF! | D43: =SUM(F43:R43) -> #REF! | F43: ='Proforma Resi'!E225 -> 0 | G43: ='Proforma Resi'!F225 -> #REF! | H43: ='Proforma Resi'!G225 -> #REF! | I43: ='Proforma Resi'!H225 -> #REF! | J43: ='Proforma Resi'!I225 -> #REF! | K43: ='Proforma Resi'!J225 -> #REF! | L43: ='Proforma Resi'!K225 -> #REF! | M43: ='Proforma Resi'!L225 -> #REF! | ... R43: ='Proforma Resi'!Q225 -> #REF!
B44: Total CM Contributions | D44: =SUM(F44:R44) -> 75000 | F44: ='Proforma Resi'!E29 -> 75000 | G44: ='Proforma Resi'!F29 -> 0 | H44: ='Proforma Resi'!G29 -> 0 | I44: ='Proforma Resi'!H29 -> 0 | J44: ='Proforma Resi'!I29 -> 0 | K44: ='Proforma Resi'!J29 -> 0 | L44: ='Proforma Resi'!K29 -> 0 | M44: ='Proforma Resi'!L29 -> 0 | ... R44: ='Proforma Resi'!Q29 -> 0
B45: CM Net Profit/ Cash Flows | D45: =SUM(F45:R45) -> #REF! | F45: =F43-F44 -> -75000 | G45: =G43-G44 -> #REF! | H45: =H43-H44 -> #REF! | I45: =I43-I44 -> #REF! | J45: =J43-J44 -> #REF! | K45: =K43-K44 -> #REF! | L45: =L43-L44 -> #REF! | M45: =M43-M44 -> #REF! | ... R45: =R43-R44 -> #REF!
B46: ='Proforma Resi'!B49 -> Asset Acquisition Fee | F46: ='Proforma Resi'!E49 -> 0 | G46: ='Proforma Resi'!F49 -> 300000 | H46: ='Proforma Resi'!G49 -> 0 | I46: ='Proforma Resi'!H49 -> 0 | J46: ='Proforma Resi'!I49 -> 0 | K46: ='Proforma Resi'!J49 -> 0 | L46: ='Proforma Resi'!K49 -> 0 | M46: ='Proforma Resi'!L49 -> 0 | ... R46: ='Proforma Resi'!Q49 -> 0
B47: ='Proforma Resi'!B191 -> Developer Overhead (% of COSTS less LAND & RE Fees) | D47: =SUM(F47:R47) -> #REF! | F47: ='Proforma Resi'!E191 -> 0 | G47: ='Proforma Resi'!F191 -> #REF! | H47: ='Proforma Resi'!G191 -> #REF! | I47: ='Proforma Resi'!H191 -> #REF! | J47: ='Proforma Resi'!I191 -> #REF! | K47: ='Proforma Resi'!J191 -> #REF! | L47: ='Proforma Resi'!K191 -> 0 | M47: ='Proforma Resi'!L191 -> 0 | ... R47: ='Proforma Resi'!Q191 -> 0
B48: ='Proforma Resi'!B192 -> Disposition Fees | D48: =SUM(F48:R48) -> 2641178 | F48: ='Proforma Resi'!E192 -> 0 | G48: ='Proforma Resi'!F192 -> 0 | H48: ='Proforma Resi'!G192 -> 243335 | I48: ='Proforma Resi'!H192 -> 809420.62 | J48: ='Proforma Resi'!I192 -> 819645.62 | K48: ='Proforma Resi'!J192 -> 768776.79 | L48: ='Proforma Resi'!K192 -> 0 | M48: ='Proforma Resi'!L192 -> 0 | ... R48: ='Proforma Resi'!Q192 -> 0
B49: ='Proforma Resi'!B193 -> Asset Management Fees | D49: =SUM(F49:R49) -> 650404.04 | F49: ='Proforma Resi'!E193 -> 0 | G49: ='Proforma Resi'!F193 -> 168534.63 | H49: ='Proforma Resi'!G193 -> 168534.63 | I49: ='Proforma Resi'!H193 -> 168534.63 | J49: ='Proforma Resi'!I193 -> 129838.88 | K49: ='Proforma Resi'!J193 -> 14961.263 | L49: ='Proforma Resi'!K193 -> 0 | M49: ='Proforma Resi'!L193 -> 0 | ... R49: ='Proforma Resi'!Q193 -> 0
B50: CM Total Cash Flows | D50: =SUM(F50:R50) -> #REF! | F50: =SUM(F45:F49) -> -75000 | G50: =SUM(G45:G49) -> #REF! | H50: =SUM(H45:H49) -> #REF! | I50: =SUM(I45:I49) -> #REF! | J50: =SUM(J45:J49) -> #REF! | K50: =SUM(K45:K49) -> #REF! | L50: =SUM(L45:L49) -> #REF! | M50: =SUM(M45:M49) -> #REF! | ... R50: =SUM(R45:R49) -> #REF!
F52: =F20 -> 46022 | G52: =G20 -> 46387 | H52: =H20 -> 46752 | I52: =I20 -> 47118 | J52: =J20 -> 47483 | K52: =K20 -> 47848 | L52: =L20 -> 48213 | M52: =M20 -> 48579 | ... R52: =R20 -> 50405
B53: Net Cash Flow For Distributions - TOTAL PROJECT RETURNS
B54: Total Return | D54: =SUM(F54:R54) -> #REF! | F54: =F25+F35+F43 -> 0 | G54: =G25+G35+G43 -> #REF! | H54: =H25+H35+H43 -> #REF! | I54: =I25+I35+I43 -> #REF! | J54: =J25+J35+J43 -> #REF! | K54: =K25+K35+K43 -> #REF! | L54: =L25+L35+L43 -> #REF! | M54: =M25+M35+M43 -> #REF! | ... R54: =R25+R35+R43 -> #REF!
B55: Invested Capital | D55: =SUM(F55:R55) -> #REF! | F55: =F26+F36+F44 -> 75000 | G55: =G26+G36+G44 -> #REF! | H55: =H26+H36+H44 -> 0 | I55: =I26+I36+I44 -> 0 | J55: =J26+J36+J44 -> 0 | K55: =K26+K36+K44 -> 0 | L55: =L26+L36+L44 -> 0 | M55: =M26+M36+M44 -> 0 | ... R55: =R26+R36+R44 -> 0
B56: Net Levered Before Tax Cash Flow | D56: =SUM(F56:R56) -> #REF! | F56: =F27+F37+F45 -> -75000 | G56: =G27+G37+G45 -> #REF! | H56: =H27+H37+H45 -> #REF! | I56: =I27+I37+I45 -> #REF! | J56: =J27+J37+J45 -> #REF! | K56: =K27+K37+K45 -> #REF! | L56: =L27+L37+L45 -> #REF! | M56: =M27+M37+M45 -> #REF! | ... R56: =R27+R37+R45 -> #REF!
B57: Check | F57: ='Proforma Resi'!E232-F56 -> 0 | G57: ='Proforma Resi'!F232-G56 -> #REF! | H57: ='Proforma Resi'!G232-H56 -> #REF! | I57: ='Proforma Resi'!H232-I56 -> #REF! | J57: ='Proforma Resi'!I232-J56 -> #REF! | K57: ='Proforma Resi'!J232-K56 -> #REF! | L57: ='Proforma Resi'!K232-L56 -> #REF! | M57: ='Proforma Resi'!L232-M56 -> #REF! | ... R57: ='Proforma Resi'!Q232-R56 -> #REF!
B58: Levered IRR | F58: =XIRR(F56:R56,F52:R52) -> #REF!
B59: Equity Multiple | F59: =SUMIF(F56:R56,">0")/-SUMIF(F56:R56,"<0") -> 0

Sheet Proforma L+H
B1: CLARENDON - LAND & HOME DEVELOPMENT | AC1: Year 0 | AD1: Year 1 | AE1: Year 2 | AF1: Year 3 | AG1: Year 4 | AH1: Year 5 | AI1: Year 6 | AJ1: Year 7
B2: Build & Sales Proforma
E3: 0 | F3: =E3+1 -> 1 | G3: =F3+1 -> 2 | H3: =G3+1 -> 3 | I3: =H3+1 -> 4 | J3: =I3+1 -> 5 | K3: =J3+1 -> 6 | L3: =K3+1 -> 7 | M3: =L3+1 -> 8 | ... Q3: =P3+1 -> 12 | Z3: Checks | AA3: =SUM(AA4:AA223) -> #REF!
D4: Year Beginning | E4: =Assumptions!C5 -> 45658 | F4: =EDATE(E4,12) -> 46023 | G4: =EDATE(F4,12) -> 46388 | H4: =EDATE(G4,12) -> 46753 | I4: =EDATE(H4,12) -> 47119 | J4: =EDATE(I4,12) -> 47484 | K4: =EDATE(J4,12) -> 47849 | L4: =EDATE(K4,12) -> 48214 | M4: =EDATE(L4,12) -> 48580 | ... Q4: =EDATE(P4,12) -> 50041 | S4: Basis per Lot+Unit
A5: Map | B5: Buildout schedule | D5: Avg Unit Size
A6: A- | B6: Pondside Cabins @ Event Barn (13ea) | D6: 1500 | R6: =SUM(F6:Q6) -> 0 | S6: =D6*$E$33 -> 2850000 | T6: =R6*S6 -> 0 | V6: =#REF!*#REF! -> #REF!
A7: B- | B7: Village Cabins (13ea) | D7: 2000 | R7: =SUM(F7:Q7) -> 0 | S7: =D7*$E$33 -> 3800000 | T7: =R7*S7 -> 0
A8: C- | B8: Village Cottages (13ea) | D8: 2500 | R8: =SUM(F8:Q8) -> 0 | S8: =D8*$E$33 -> 4750000 | T8: =R8*S8 -> 0
A9: D- | B9: Guest Cabins @ Fitness Spa (13ea) | D9: 2500 | R9: =SUM(F9:Q9) -> 0 | S9: =D9*$E$33 -> 4750000 | T9: =R9*S9 -> 0
A10: F- | B10: Jimmy Creek Homes (4ea) | D10: 3500 | F10: 4 | R10: =SUM(E10:Q10) -> 4 | S10: =D10*$E$31 -> 6300000 | T10: =R10*S10 -> 25200000
A11: G- | B11: Bench Homesites (15ea) | D11: 3250 | G11: 10 | H11: 5 | R11: =SUM(E11:Q11) -> 15 | S11: =D11*$E$31 -> 5850000 | T11: =R11*S11 -> 87750000
A12: H- | B12: Forest Homesites (10ea) | D12: 3750 | H12: 10 | R12: =SUM(E12:Q12) -> 10 | S12: =D12*$E$31 -> 6750000 | T12: =R12*S12 -> 67500000 | U12: Improved Value Before Escalation
A13: J- | B13: Hillside Homesites (10ea) | D13: 3750 | I13: 10 | R13: =SUM(E13:Q13) -> 10 | S13: =D13*$E$31 -> 6750000 | T13: =R13*S13 -> 67500000
A14: E- | B14: Village Homesites (6ea) | D14: 4500 | R14: =SUM(E14:Q14) -> 0 | S14: =D14*$E$32 -> 7425000 | T14: =R14*S14 -> 0
A15: K- | B15: Deer Creek Homesites (5ea + 1 lot used for Clubhouse) | D15: 3500 | F15: 1 | I15: 5 | R15: =SUM(E15:Q15) -> 6 | S15: =D15*$E$33 -> 6650000 | T15: =R15*S15 -> 39900000
B16: Total starts | E16: =SUM(E6:E15) -> 0 | F16: =SUM(F6:F15) -> 5 | G16: =SUM(G6:G15) -> 10 | H16: =SUM(H6:H15) -> 15 | I16: =SUM(I6:I15) -> 15 | J16: =SUM(J6:J15) -> 0 | K16: =SUM(K6:K15) -> 0 | L16: =SUM(L6:L15) -> 0 | ... R16: =SUM(R6:R15) -> 45 | S16: TOTAL HOMES | T16: =SUM(T6:T15) -> 287850000 | V16: =SUMPRODUCT(D6:D15,R6:R15) -> 158750 | W16: sf | X16: =SUM(T6:T15)/V16 -> 1813.2283 | Y16: /sf | Z16: /sf
B17: Total Sellable SQFT | D17: =SUMPRODUCT(D6:D15,R6:R15) -> 158750 | T17: =T16/R16 -> 6396666.7 | U17: Average | V17: =D17/R16 -> 3527.7778
B19: Sales Schedule | U19: Year 1 | V19: Year 2 | W19: Year 3 | X19: Year 4 | Y19: Year 5 | Z19: Year 6 | AA19: Year 7
B20: =B6 -> Pondside Cabins @ Event Barn (13ea) | C20: =R6 -> 0 | D20: =T20 -> Cottages | G20: =F6 -> 0 | H20: =G6 -> 0 | I20: =H6 -> 0 | J20: =I6 -> 0 | K20: =J6 -> 0 | L20: =K6 -> 0 | M20: =L6 -> 0 | N20: =M6 -> 0 | ... Q20: =P6 -> 0 | R20: =SUM(F20:Q20) -> 0 | T20: Cottages | U20: =+F33 -> 1900 | V20: =+G33 -> 1900 | W20: =+H33 -> 2090 | X20: =+I33 -> 2299 | Y20: =+J33 -> 2528.9 | Z20: =+K33 -> 2781.79 | AA20: {=+L33:P33} -> 3059.969 | AB20: 3365.9659 | AC20: 3702.5625 | AD20: 4072.8187 | AE20: 4480.1006
B21: =B7 -> Village Cabins (13ea) | C21: =R7 -> 0 | D21: =T21 -> Cottages | G21: =F7 -> 0 | H21: =G7 -> 0 | I21: =H7 -> 0 | J21: =I7 -> 0 | K21: =J7 -> 0 | L21: =K7 -> 0 | M21: =L7 -> 0 | N21: =M7 -> 0 | ... Q21: =P7 -> 0 | R21: =SUM(F21:Q21) -> 0 | T21: Cottages | U21: =+U20 -> 1900 | V21: =+V20 -> 1900 | W21: =+W20 -> 2090 | X21: =+X20 -> 2299 | Y21: =+Y20 -> 2528.9 | Z21: =+Z20 -> 2781.79 | AA21: =+AA20 -> 3059.969
B22: =B8 -> Village Cottages (13ea) | C22: =R8 -> 0 | D22: =T22 -> Cottages | G22: =F8 -> 0 | H22: =G8 -> 0 | I22: =H8 -> 0 | J22: =I8 -> 0 | K22: =J8 -> 0 | L22: =K8 -> 0 | M22: =L8 -> 0 | N22: =M8 -> 0 | ... Q22: =P8 -> 0 | R22: =SUM(F22:Q22) -> 0 | T22: Cottages | U22: =+U21 -> 1900 | V22: =+V21 -> 1900 | W22: =+W21 -> 2090 | X22: =+X21 -> 2299 | Y22: =+Y21 -> 2528.9 | Z22: =+Z21 -> 2781.79 | AA22: =+AA21 -> 3059.969
B23: =B9 -> Guest Cabins @ Fitness Spa (13ea) | C23: =R9 -> 0 | D23: =T23 -> Cottages | G23: =F9 -> 0 | H23: =G9 -> 0 | I23: =H9 -> 0 | J23: =I9 -> 0 | K23: =J9 -> 0 | L23: =K9 -> 0 | M23: =L9 -> 0 | N23: =M9 -> 0 | ... Q23: =P9 -> 0 | R23: =SUM(F23:Q23) -> 0 | T23: Cottages | U23: =+U22 -> 1900 | V23: =+V22 -> 1900 | W23: =+W22 -> 2090 | X23: =+X22 -> 2299 | Y23: =+Y22 -> 2528.9 | Z23: =+Z22 -> 2781.79 | AA23: =+AA22 -> 3059.969
B24: =B10 -> Jimmy Creek Homes (4ea) | C24: =R10 -> 4 | D24: =T24 -> Village | F24: =E10 -> 0 | G24: =F10 -> 4 | H24: =G10 -> 0 | I24: =H10 -> 0 | J24: =I10 -> 0 | K24: =J10 -> 0 | L24: =K10 -> 0 | M24: =L14 -> 0 | N24: =M14 -> 0 | O24: =N14 -> 0 | P24: =O14 -> 0 | Q24: =P14 -> 0 | R24: =SUM(F24:Q24) -> 4 | T24: Village | U24: =+F31 -> 1800 | V24: =+G32 -> 1773.75 | W24: =+H32 -> 1906.7812 | X24: =+I32 -> 2049.7898 | Y24: =+J32 -> 2203.5241 | Z24: =+K32 -> 2368.7884 | AA24: =+L32 -> 2546.4475
B25: =B11 -> Bench Homesites (15ea) | C25: =R11 -> 15 | D25: =T25 -> Homesites | F25: =E11 -> 0 | G25: =F11 -> 0 | H25: =G11 -> 10 | I25: =H11 -> 5 | J25: =I11 -> 0 | K25: =J11 -> 0 | L25: =K11 -> 0 | M25: =L10 -> 0 | N25: =M10 -> 0 | O25: =N10 -> 0 | P25: =O10 -> 0 | Q25: =P10 -> 0 | R25: =SUM(F25:Q25) -> 15 | T25: Homesites | U25: =+F31 -> 1800 | V25: =+G31 -> 1800 | W25: =+H31 -> 1980 | X25: =+I31 -> 2178 | Y25: =+J31 -> 2395.8 | Z25: =+K31 -> 2635.38 | AA25: =+L31 -> 2898.918
B26: =B12 -> Forest Homesites (10ea) | C26: =R12 -> 10 | D26: =T26 -> Homesites | F26: =E12 -> 0 | G26: =F12 -> 0 | H26: =G12 -> 0 | I26: =H12 -> 10 | J26: =I12 -> 0 | K26: =J12 -> 0 | L26: =K12 -> 0 | M26: =L11 -> 0 | N26: =M11 -> 0 | O26: =N11 -> 0 | P26: =O11 -> 0 | Q26: =P11 -> 0 | R26: =SUM(F26:Q26) -> 10 | T26: Homesites | U26: =+U25 -> 1800 | V26: =+V25 -> 1800 | W26: =+W25 -> 1980 | X26: =+X25 -> 2178 | Y26: =+Y25 -> 2395.8 | Z26: =+Z25 -> 2635.38 | AA26: =+AA25 -> 2898.918
B27: =B13 -> Hillside Homesites (10ea) | C27: =R13 -> 10 | D27: =T27 -> Homesites | F27: =E13 -> 0 | G27: =F13 -> 0 | H27: =G13 -> 0 | I27: =H13 -> 0 | J27: =I13 -> 10 | K27: =J13 -> 0 | L27: =K13 -> 0 | M27: =L13 -> 0 | ... P27: =O13 -> 0 | Q27: =P12 -> 0 | R27: =SUM(F27:Q27) -> 10 | T27: Homesites | U27: =+U26 -> 1800 | V27: =+V26 -> 1800 | W27: =+W26 -> 1980 | X27: =+X26 -> 2178 | Y27: =+Y26 -> 2395.8 | Z27: =+Z26 -> 2635.38 | AA27: =+AA26 -> 2898.918
B28: =B14 -> Village Homesites (6ea) | C28: =R14 -> 0 | D28: =T28 -> Homesites | F28: =E14 -> 0 | G28: =F14 -> 0 | H28: =G14 -> 0 | I28: =H14 -> 0 | J28: =I14 -> 0 | K28: =J14 -> 0 | L28: =K14 -> 0 | M28: =L13 -> 0 | N28: =M13 -> 0 | O28: =N13 -> 0 | P28: =O13 -> 0 | Q28: =P13 -> 0 | R28: =SUM(F28:Q28) -> 0 | T28: Homesites | U28: =+U27 -> 1800 | V28: =+V27 -> 1800 | W28: =+W27 -> 1980 | X28: =+X27 -> 2178 | Y28: =+Y27 -> 2395.8 | Z28: =+Z27 -> 2635.38 | AA28: =+AA27 -> 2898.918
B29: =B15 -> Deer Creek Homesites (5ea + 1 lot used for Clubhouse) | C29: =R15 -> 6 | D29: =T29 -> Cottages | F29: =E15 -> 0 | G29: =F15 -> 1 | H29: =G15 -> 0 | I29: =H15 -> 0 | J29: =I15 -> 5 | K29: =J15 -> 0 | L29: =K15 -> 0 | M29: =L15 -> 0 | ... Q29: =P15 -> 0 | R29: =SUM(F29:Q29) -> 6 | T29: Cottages | U29: =+U23 -> 1900 | V29: =+V23 -> 1900 | W29: =+W23 -> 2090 | X29: =+X23 -> 2299 | Y29: =+Y23 -> 2528.9 | Z29: =+Z23 -> 2781.79 | AA29: =+AA23 -> 3059.969
B30: Total sales | C30: =SUM(C20:C29) -> 45 | F30: =SUM(F20:F29) -> 0 | G30: =SUM(G20:G29) -> 5 | H30: =SUM(H20:H29) -> 10 | I30: =SUM(I20:I29) -> 15 | J30: =SUM(J20:J29) -> 15 | K30: =SUM(K20:K29) -> 0 | L30: =SUM(L20:L29) -> 0 | M30: =SUM(M20:M29) -> 0 | ... R30: =SUM(R20:R29) -> 45 | Z30: Check on Sales & Build out | AA30: =+R16-R30 -> 0
B31: Sales Price Escalation / Residential Sales Sqft Price | C31: =Assumptions!H18 -> 0.1 | D31: Homesites | E31: 1800 | F31: =E31 -> 1800 | G31: =F31 -> 1800 | H31: =G31*(1+$C$31) -> 1980 | I31: =H31*(1+$C$31) -> 2178 | J31: =I31*(1+$C$31) -> 2395.8 | K31: =J31*(1+$C$31) -> 2635.38 | L31: =K31*(1+$C$31) -> 2898.918 | M31: =L31*(1+$C$31) -> 3188.8098 | N31: =M31*(1+$C$31) -> 3507.6908 | O31: =N31*(1+$C$31) -> 3858.4599 | ... Q31: =P31*(1+$C$31) -> 4668.7364
B32: Sales Price Escalation / Residential Sales Sqft Price | C32: =Assumptions!H19 -> 0.075 | D32: Village | E32: =Assumptions!G19 -> 1650 | F32: =E32 -> 1650 | G32: =F32*(1+$C$32) -> 1773.75 | H32: =G32*(1+$C$32) -> 1906.7812 | I32: =H32*(1+$C$32) -> 2049.7898 | J32: =I32*(1+$C$32) -> 2203.5241 | K32: =J32*(1+$C$32) -> 2368.7884 | L32: =K32*(1+$C$32) -> 2546.4475 | M32: =L32*(1+$C$32) -> 2737.4311 | N32: =M32*(1+$C$32) -> 2942.7384 | ... Q32: =P32*(1+$C$32) -> 3655.7547
B33: Sales Price Escalation / Residential Sales Sqft Price | C33: 0.1 | D33: Cottages | E33: 1900 | F33: =E33 -> 1900 | G33: =F33 -> 1900 | H33: =G33*(1+$C$33) -> 2090 | I33: =H33*(1+$C$33) -> 2299 | J33: =I33*(1+$C$33) -> 2528.9 | K33: =J33*(1+$C$33) -> 2781.79 | L33: =K33*(1+$C$33) -> 3059.969 | M33: =L33*(1+$C$33) -> 3365.9659 | N33: =M33*(1+$C$33) -> 3702.5625 | O33: =N33*(1+$C$33) -> 4072.8187 | ... Q33: =P33*(1+$C$33) -> 4928.1107 | U33: Average Res Unit Sales Price
F34: Average Sales $ per Unit | H34: =SUM(G56+H57)/H30 -> 6435000 | I34: =SUM(H56+I57)/I30 -> 7804500 | J34: =SUM(I56+J57)/J30 -> 8939883.3 | R34: TOTALS | T34: =(R56+R57)/R16 -> 7934569.3 | W34: =T34/T17 -> 1.2404225
B35: SOURCES
L36: 0 | R36: =SUM(E36:Q36) -> 0
B37: EQUITY INVESTMENT | L37: 0 | R37: =SUM(E37:Q37) -> 0 | T37: {=SUMPRODUCT(E10:E15*S10:S15)} -> 0 | U37: VALUE OF SPEC DEV
B38: MTN ORIGINS - PURSUIT CAPITAL | E38: 1500000 | R38: =SUM(E38:Q38) -> 1500000
B39: JV - EQUITY CAPITAL | E39: 10000000 | R39: =SUM(E39:Q39) -> 10000000
B40: EQUITY INVESTMENT | E40: =SUM(E38:E39) -> 11500000 | F40: =SUM(F38:F39) -> 0 | G40: =SUM(G38:G39) -> 0 | H40: =SUM(H38:H39) -> 0 | I40: =SUM(I38:I39) -> 0 | J40: =SUM(J38:J39) -> 0 | K40: =SUM(K38:K39) -> 0 | L40: =SUM(L38:L39) -> 0 | R40: =SUM(E40:Q40) -> 11500000 | T40: =(C184+E40)/T37 -> #DIV/0! | U40: ETV | V40: =25000000-E40 -> 13500000 | W40: =25000000-F40 -> 25000000 | Z40: Force to 40mm for total | AA40: =ROUND(40000000-R40,0) -> 28500000
B42: DEBT | C42: =U158 -> 49035729 | T42: =(E48+F48)/(E40+F40+E48+F48) -> 0.83846603 | U42: LTC Year 0+1
B43: JV BRIDGE LOAN | E43: 15000000 | R43: =SUM(E43:Q43) -> 15000000
B44: SELLER FINANCE | R44: =SUM(E44:Q44) -> 0
B45: EB5 - MEZZ DEBT | C45: =F159-F39+SUM(E157:F157) -> 17250000 | F45: =800000*26 -> 20800000 | R45: =SUM(E45:Q45) -> 20800000
B46: DEV LOAN - DEV COSTS | C46: =U157 -> 0.70215819 | D46: LTC | F46: =MAX(F143+F149+SUM(F157:F159)+SUM(F163:F166)+F178-F40-SUM(F43:F45)-F51-SUM(F56:F57)-E221,0) -> 19800183 | R46: =SUM(E46:Q46) -> 19800183 | T46: =(R48)/(R48+R40) -> 0.88062581 | U46: LTC Total
B47: DEV LOAN - FINANCING / RESERVE | F47: =F152+F153 -> 4092272.5 | G47: =G152+G153 -> 2867094.7 | H47: =H152+H153 -> 3746337.1 | I47: =C42-SUM(F46:H47) -> 18529842 | R47: =SUM(E47:Q47) -> 29235546
B48: DEBT | E48: =SUM(E43:E47) -> 15000000 | F48: =SUM(F43:F47) -> 44692456 | G48: =SUM(G43:G47) -> 2867094.7 | H48: =SUM(H43:H47) -> 3746337.1 | I48: =SUM(I43:I47) -> 18529842 | J48: =SUM(J43:J47) -> 0 | K48: =SUM(K43:K47) -> 0 | L48: =SUM(L43:L47) -> 0 | M48: =M46 -> 0 | N48: =N46 -> 0 | O48: =O46 -> 0 | P48: =P46 -> 0 | Q48: =Q46 -> 0 | R48: =SUM(E48:Q48) -> 84835729 | T48: =R46/SUM(R51,R56,R57) -> 0.055454059 | U48: LTV
B50: VALUE CREATED POST PUD of 80 ACRES | G50: 15000000 | R50: =SUM(E50:Q50) -> 15000000
B51: LAND SALE TO AMENITY | R51: =SUM(E51:Q51) -> 0
B52: Construction Start Draw + Foundation Complete | C52: 0.2 | F52: =((SUMPRODUCT(G20:G29,$D$6:$D$15,U20:U29))*$C52) -> 6370000 | G52: =((SUMPRODUCT(H20:H29,$D$6:$D$15,V20:V29))*$C52) -> 11700000 | H52: =((SUMPRODUCT(I20:I29,$D$6:$D$15,W20:W29))*$C52) -> 21285000 | I52: =((SUMPRODUCT(J20:J29,$D$6:$D$15,X20:X29))*$C52) -> 24381500 | J52: =((SUMPRODUCT(K20:K29,$D$6:$D$15,Y20:Y29))*$C52) -> 0 | K52: =((SUMPRODUCT(L20:L29,$D$6:$D$15,Z20:Z29))*$C52) -> 0 | L52: =((SUMPRODUCT(M20:M29,$D$6:$D$15,AA20:AA29))*$C52) -> 0
B53: Structure Complete Draw | C53: 0.15 | F53: =((SUMPRODUCT(G20:G29,$D$6:$D$15,U20:U29))*$C53) -> 4777500 | G53: =((SUMPRODUCT(H20:H29,$D$6:$D$15,V20:V29))*$C53) -> 8775000 | H53: =((SUMPRODUCT(I20:I29,$D$6:$D$15,W20:W29))*$C53) -> 15963750 | I53: =((SUMPRODUCT(J20:J29,$D$6:$D$15,X20:X29))*$C53) -> 18286125 | J53: =((SUMPRODUCT(K20:K29,$D$6:$D$15,Y20:Y29))*$C53) -> 0 | K53: =((SUMPRODUCT(L20:L29,$D$6:$D$15,Z20:Z29))*$C53) -> 0 | L53: =((SUMPRODUCT(M20:M29,$D$6:$D$15,AA20:AA29))*$C53) -> 0
B54: MEP 4-way + Finishes Start Draw | C54: 0.15 | F54: =((SUMPRODUCT(F20:F29,$D$6:$D$15,U20:U29))*$C54) -> 0 | G54: =((SUMPRODUCT(G20:G29,$D$6:$D$15,V20:V29))*$C54) -> 4722375 | H54: =((SUMPRODUCT(H20:H29,$D$6:$D$15,W20:W29))*$C54) -> 9652500 | I54: =((SUMPRODUCT(I20:I29,$D$6:$D$15,X20:X29))*$C54) -> 17560125 | J54: =((SUMPRODUCT(J20:J29,$D$6:$D$15,Y20:Y29))*$C54) -> 20114738 | K54: =((SUMPRODUCT(K20:K29,$D$6:$D$15,Z20:Z29))*$C54) -> 0 | L54: =((SUMPRODUCT(L20:L29,$D$6:$D$15,AA20:AA29))*$C54) -> 0 | M54: =((SUMPRODUCT(M$20:M$29,$D$6:$D$15)*M$33)*$C54) -> 0 | N54: =((SUMPRODUCT(N$20:N$29,$D$6:$D$15)*N$33)*$C54) -> 0 | O54: =((SUMPRODUCT(O$20:O$29,$D$6:$D$15)*O$33)*$C54) -> 0 | P54: =((SUMPRODUCT(P$20:P$29,$D$6:$D$15)*P$33)*$C54) -> 0 | Q54: =((SUMPRODUCT(Q$20:Q$29,$D$6:$D$15)*Q$33)*$C54) -> 0
B55: Unit Reservations w/ Membership Purchase (50/50) | C55: 0 | F55: =+$C55*SUMPRODUCT(G6:G15,$D$6:$D$15,U$20:U$29) -> 0 | G55: =+$C55*SUMPRODUCT(H6:H15,$D$6:$D$15,V$20:V$29) -> 0 | H55: =+$C55*SUMPRODUCT(I6:I15,$D$6:$D$15,W$20:W$29) -> 0 | I55: =+$C55*SUMPRODUCT(J6:J15,$D$6:$D$15,X$20:X$29) -> 0 | J55: =+$C55*SUMPRODUCT(K6:K15,$D$6:$D$15,Y$20:Y$29) -> 0 | K55: =+$C55*SUMPRODUCT(L6:L15,$D$6:$D$15,Z$20:Z$29) -> 0 | L55: =+$C55*SUMPRODUCT(M6:M15,$D$6:$D$15,AA$20:AA$29) -> 0 | M55: =+$C55*SUMPRODUCT(N6:N15,$D$6:$D$15,AB$20:AB$29) -> 0 | ... Q55: =+$C55*SUMPRODUCT(R6:R15,$D$6:$D$15,AF$20:AF$29) -> 0
B56: PRESALE REVENUES | C56: =SUM(C52:C55) -> 0.5 | F56: =SUM(F52:F55)/2 -> 5573750 | G56: =SUM(G52:G55)/2 -> 12598688 | H56: =SUM(H52:H55)/2 -> 23450625 | I56: =SUM(I52:I55)/2 -> 30113875 | J56: =SUM(J52:J55)/2 -> 10057369 | K56: =SUM(K52:K55)/2 -> 0 | L56: =SUM(L52:L55)/2 -> 0 | M56: =SUM(M52:M54) -> 0 | N56: =SUM(N52:N54) -> 0 | O56: =SUM(O52:O54) -> 0 | P56: =SUM(P52:P54) -> 0 | Q56: =SUM(Q52:Q54) -> 0 | R56: =SUM(E56:Q56) -> 81794306 | T56: TOTAL HOME SALES
B57: UNIT SALES | F57: =SUMPRODUCT(E$6:E$13,$D6:$D$13,U$20:U$27)-(E56) -> 0 | G57: =SUMPRODUCT(F$6:F$15,$D6:$D$15,V$20:V$29)-(F56) -> 25908750 | H57: =SUMPRODUCT(G$6:G$15,$D6:$D$15,W$20:W$29)-(G56) -> 51751313 | I57: =SUMPRODUCT(H$6:H$15,$D6:$D$15,X$20:X$29)-(H56) -> 93616875 | J57: =SUMPRODUCT(I$6:I$15,$D6:$D$15,Y$20:Y$29)-(I56) -> 1.0398438e+08 | L57: =SUMPRODUCT(K$6:K$15,$D6:$D$15,AA$20:AA$29)-(K56) -> 0 | M57: 0 | N57: =SUMPRODUCT(N$20:N$29,$D6:$D$15,AB$20:AB$29)-M56 -> 0 | O57: =SUMPRODUCT(O$20:O$29,$D6:$D$15,AC$20:AC$29)-N56 -> 0 | P57: =SUMPRODUCT(P$20:P$29,$D6:$D$15,AD$20:AD$29)-O56 -> 0 | Q57: =SUMPRODUCT(Q$20:Q$29,$D6:$D$15,AE$20:AE$29)-P56 -> 0 | R57: =SUM(E57:Q57) -> 2.7526131e+08 | T57: =R57+(R56) -> 3.5705562e+08 | U57: =T57/R16 -> 7934569.3 | V57: =T57/D17 -> 2249.1693 | W57: average $/sf
B58: TOTAL SOURCES | E58: =E40+E48+SUM(E50:E51)+SUM(E56:E57) -> 26500000 | F58: =F40+F48+SUM(F50:F51)+SUM(F56:F57) -> 50266206 | G58: =G40+G48+SUM(G50:G51)+SUM(G56:G57) -> 56374532 | H58: =H40+H48+SUM(H50:H51)+SUM(H56:H57) -> 78948275 | I58: =I40+I48+SUM(I50:I51)+SUM(I56:I57) -> 1.4226059e+08 | J58: =J40+J48+SUM(J50:J51)+SUM(J56:J57) -> 1.1404174e+08 | K58: =K40+K48+SUM(K50:K51)+SUM(K56:K57) -> 0 | L58: =L40+L48+SUM(L50:L51)+SUM(L56:L57) -> 0 | M58: =M40+M48+SUM(M51:M57) -> 0 | N58: =N40+N48+SUM(N51:N57) -> 0 | O58: =O40+O48+SUM(O51:O57) -> 0 | P58: =P40+P48+SUM(P51:P57) -> 0 | Q58: =Q40+Q48+SUM(Q51:Q57) -> 0 | R58: =SUM(E58:Q58) -> 4.6839135e+08 | T58: TOTAL SALES
T59: =(R56)+R57 -> 3.5705562e+08 | U59: =T59/D17 -> 2249.1693 | V59: average $/sf
B60: USES
B61: LAND & PROJECT ACQUISITION | V61: =E62*0.65 -> 12025000 | W61: 0.65
B62: Project Acquisition | E62: 18500000 | F62: 0 | G62: 0 | H62: 0 | I62: 0 | J62: 0 | K62: 0 | L62: 0 | R62: =SUM(E62:L62) -> 18500000 | V62: =E62*0.85 -> 15725000 | W62: 0.85
B63: Asset Acquisition Fee (based on total project initial value Equity + Debt) | C63: 0.005 | E63: =180000000*$C$63*0.5 -> 450000 | G63: 0 | H63: 0 | I63: 0 | J63: 0 | K63: 0 | L63: 0 | R63: =SUM(E63:L63) -> 450000
B64: Closing Costs | C64: 0.0015 | E64: =E62*$C$64 -> 27750 | F64: 0 | G64: 0 | H64: 0 | I64: 0 | J64: 0 | K64: 0 | L64: 0 | M64: =M62*$C$64 -> 0 | N64: =N62*$C$64 -> 0 | O64: =O62*$C$64 -> 0 | P64: =P62*$C$64 -> 0 | Q64: =Q62*$C$64 -> 0 | R64: =SUM(E64:Q64) -> 27750 | V64: 18423158 | W64: 1
B65: LAND & PROJECT ACQUISITION | E65: =SUM(E62:E64) -> 18977750 | F65: =SUM(F62:F64) -> 0 | G65: =SUM(G62:G64) -> 0 | H65: =SUM(H62:H64) -> 0 | I65: =SUM(I62:I64) -> 0 | J65: =SUM(J62:J64) -> 0 | K65: =SUM(K62:K64) -> 0 | L65: =SUM(L62:L64) -> 0 | ... Q65: =SUM(Q62:Q64) -> 0 | R65: =SUM(E65:Q65) -> 18977750 | T65: =R65/R16 -> 421727.78 | U65: $/Lot
B67: HARD COSTS - SITE, RESTORATION & INFRASTRUCTURE
B68: Internal Road: Base + Gravel Finish @ Lower 80 | C68: =235000*1.25 -> 293750 | F68: =$C$68*0.5 -> 146875 | G68: =$C$68*0.5 -> 146875 | H68: =$C68*I$67 -> 0 | I68: 0 | J68: 0 | K68: 0 | L68: 0 | M68: 0 | N68: 0 | O68: 0 | P68: 0 | R68: =SUM(F68:P68) -> 293750 | T68: =C68-R68 -> 0
B69: Internal Road: Base + Gravel Finish @ 45 Lots | C69: =590000*1.25 -> 737500 | F69: =$C$69/3 -> 245833.33 | G69: =$C$69/3 -> 245833.33 | H69: =$C$69/3 -> 245833.33 | I69: 0 | J69: 0 | K69: 0 | L69: 0 | M69: 0 | N69: 0 | O69: 0 | P69: 0 | R69: =SUM(E69:P69) -> 737500 | T69: =C69-R69 -> 0
B70: Internal Road: Paving @ 45 Lots | C70: =350000*1.25 -> 437500 | E70: =$C70*F$67 -> 0 | F70: =$C$70/3 -> 145833.33 | G70: =$C$70/3 -> 145833.33 | H70: =$C$70/3 -> 145833.33 | I70: 0 | J70: 0 | K70: 0 | L70: 0 | M70: 0 | N70: 0 | O70: 0 | P70: 0 | R70: =SUM(E70:P70) -> 437500 | T70: =C70-R70 -> 0
B71: County/USFS Road: BASE + GRAVEL FINISH @ end of existing | C71: =500000*1.25 -> 625000 | E71: =$C$71/2 -> 312500 | F71: 0 | G71: =$C$71/2 -> 312500 | H71: 0 | I71: 0 | J71: 0 | K71: 0 | L71: 0 | M71: 0 | N71: 0 | O71: 0 | P71: 0 | R71: =SUM(E71:P71) -> 625000 | T71: =C71-R71 -> 0
B72: County/USFS Road: PAVING @ end of existing to back gate | C72: =500000*1.25 -> 625000 | E72: 0 | F72: =$C72/2 -> 312500 | G72: 0 | H72: =$C72/2 -> 312500 | I72: 0 | J72: 0 | K72: 0 | L72: 0 | M72: 0 | N72: 0 | O72: 0 | P72: 0 | R72: =SUM(E72:P72) -> 625000 | T72: =C72-R72 -> 0
B73: Road: Bridges (1) @ Spillway | C73: 150000 | E73: =$C$73 -> 150000 | F73: 0 | G73: 0 | H73: 0 | I73: 0 | J73: 0 | K73: 0 | L73: 0 | M73: 0 | N73: 0 | O73: 0 | P73: 0 | R73: =SUM(E73:P73) -> 150000 | T73: =C73-R73 -> 0
B74: Utilities: County/USFS Power Trench+Line (4.5 miles) | C74: =650000*1.25 -> 812500 | E74: =$C$74 -> 812500 | F74: 0 | G74: 0 | H74: 0 | I74: 0 | J74: 0 | K74: 0 | L74: 0 | M74: 0 | N74: 0 | O74: 0 | P74: 0 | R74: =SUM(E74:P74) -> 812500 | T74: =C74-R74 -> 0
B75: Utilities: Power & Transformers @ 45 Lots (8,500 LF) | C75: =(105000*1.25)+15*4000 -> 191250 | F75: =$C75/3 -> 63750 | G75: =$C75/3 -> 63750 | H75: =$C75/3 -> 63750 | I75: 0 | J75: 0 | K75: 0 | L75: 0 | M75: 0 | N75: 0 | O75: 0 | P75: 0 | R75: =SUM(F75:P75) -> 191250 | T75: =C75-R75 -> 0
B76: Utilities: Comm. Distrib. @ 45 Lots (8,500 LF) | C76: =(8500*15)*1.25 -> 159375 | F76: =$C76/3 -> 53125 | G76: =$C76/3 -> 53125 | H76: =$C76/3 -> 53125 | I76: 0 | J76: 0 | K76: 0 | L76: 0 | M76: 0 | N76: 0 | O76: 0 | P76: 0 | R76: =SUM(F76:P76) -> 159375 | T76: =C76-R76 -> 0
B77: Utilities: Water Main @ 45 Lots | C77: =550000*1.25 -> 687500 | E77: =$C77/3 -> 229166.67 | F77: =$C77/3 -> 229166.67 | G77: =$C77/3 -> 229166.67 | H77: 0 | I77: 0 | J77: 0 | K77: 0 | L77: 0 | M77: 0 | N77: 0 | O77: 0 | P77: 0 | R77: =SUM(E77:P77) -> 687500 | T77: =C77-R77 -> 0
B78: Utilities: Water Wells, Pumps & Backup Power Requirements | C78: =1000000*1.25 -> 1250000 | E78: =$C$78/2 -> 625000 | F78: =$C$78/2 -> 625000 | G78: 0 | H78: 0 | I78: 0 | J78: 0 | K78: 0 | L78: 0 | M78: 0 | N78: 0 | O78: 0 | P78: 0 | R78: =SUM(E78:P78) -> 1250000 | T78: =C78-R78 -> 0
B79: Utilities: Lift Station @ 45 Lots (8,500 LF) | C79: =125000*1.25 -> 156250 | F79: =($C79)/3 -> 52083.333 | G79: =($C79)/3 -> 52083.333 | H79: =($C79)/3 -> 52083.333 | I79: 0 | J79: 0 | K79: 0 | L79: 0 | M79: 0 | N79: 0 | O79: 0 | P79: 0 | R79: =SUM(F79:P79) -> 156250 | T79: =C79-R79 -> 0
B80: Utilities: Sewer Treatment Drainfield Sys (4 EA) | C80: =625000*1.25 -> 781250 | E80: =$C80/4 -> 195312.5 | F80: =$C80/4 -> 195312.5 | G80: =$C80/4 -> 195312.5 | H80: =$C80/4 -> 195312.5 | I80: 0 | J80: 0 | K80: 0 | L80: 0 | M80: 0 | N80: 0 | O80: 0 | P80: 0 | R80: =SUM(E80:P80) -> 781250 | T80: =C80-R80 -> 0
B81: Utilities: Geothermal Infrastructure @ 45 Lots | C81: =175000*1.25 -> 218750 | F81: =$C81/3 -> 72916.667 | G81: =$C81/3 -> 72916.667 | H81: =$C81/3 -> 72916.667 | I81: 0 | J81: 0 | K81: 0 | L81: 0 | M81: 0 | N81: 0 | O81: 0 | P81: 0 | R81: =SUM(F81:P81) -> 218750 | T81: =C81-R81 -> 0
B82: Landscape: Early Plantings in Public Areas | C82: 750000 | F82: =$C$82/3 -> 250000 | G82: =$C$82/3 -> 250000 | H82: =$C$82/3 -> 250000 | I82: =$C82*I$67 -> 0 | J82: =$C82*J$67 -> 0 | K82: 0 | L82: 0 | M82: 0 | N82: 0 | O82: 0 | P82: 0 | R82: =SUM(F82:P82) -> 750000 | T82: =C82-R82 -> 0
B83: Construction Cost Escalation | C83: 0.05 | E83: =SUM(E67:E82,D83)*$C83 -> 116223.96 | F83: =SUM(F67:F82,E83)*$C83 -> 125430.99 | G83: =SUM(G67:G82,E83:F83)*$C83 -> 100452.54 | H83: =SUM(H67:H82,E83:G83)*$C83 -> 86673.083 | I83: 0 | J83: 0 | K83: 0 | L83: 0 | R83: =SUM(E83:Q83) -> 428780.57
B84: Developer Construction Contingency | C84: 0.05 | E84: =SUM(E68:E82)*$C$84 -> 116223.96 | F84: =SUM(F68:F82)*$C$84 -> 119619.79 | G84: =SUM(G68:G82)*$C$84 -> 88369.792 | H84: =SUM(H68:H82)*$C$84 -> 69567.708 | I84: =SUM(I68:I82)*$C$84 -> 0 | J84: =SUM(J68:J82)*$C$84 -> 0 | K84: =SUM(K68:K82)*$C$84 -> 0 | L84: =SUM(L68:L82)*$C$84 -> 0 | M84: 0 | N84: 0 | O84: 0 | P84: 0 | R84: =SUM(E84:Q84) -> 393781.25
B85: =B67 -> HARD COSTS - SITE, RESTORATION & INFRASTRUCTURE | E85: =SUM(E67:E84) -> 2556927.1 | F85: =SUM(F67:F84) -> 2637446.6 | G85: =SUM(G67:G84) -> 1956218.2 | H85: =SUM(H67:H84) -> 1547595 | I85: =SUM(I67:I84) -> 0 | J85: =SUM(J67:J84) -> 0 | K85: =SUM(K67:K84) -> 0 | L85: =SUM(L67:L84) -> 0 | ... P85: =SUM(P67:P84) -> 0 | R85: =SUM(E85:Q85) -> 8698186.8 | T85: =R85/$R$16 -> 193293.04 | U85: $/Lot
T86: =R85/$T$59 -> 0.024360874 | U86: of Sales
B87: HARD COSTS - HOMES
B88: Infrastructure (Utilities & Driveway) | C88: 100000 | E88: =((E$16*$C88)*0.25)+((F$16*$C88)*0.75) -> 375000 | F88: =((F$16*$C88)*0.25)+((G$16*$C88)*0.75) -> 875000 | G88: =((G$16*$C88)*0.25)+((H$16*$C88)*0.75) -> 1375000 | H88: =((H$16*$C88)*0.25)+((I$16*$C88)*0.75) -> 1500000 | I88: =((I$16*$C88)*0.25)+((J$16*$C88)*0.75) -> 375000 | J88: =((J$16*$C88)*0.25)+((K$16*$C88)*0.75) -> 0 | K88: =((K$16*$C88)*0.25)+((L$16*$C88)*0.75) -> 0 | L88: =((L$16*$C88)*0.25)+((M$16*$C88)*0.75) -> 0 | M88: =((L$16*$C88)*0.25)+((M$16*$C88)*0.75) -> 0 | N88: =((M$16*$C88)*0.25)+((N$16*$C88)*0.75) -> 0 | O88: =((N$16*$C88)*0.25)+((O$16*$C88)*0.75) -> 0 | P88: =((O$16*$C88)*0.25)+((P$16*$C88)*0.75) -> 0 | Q88: =((P$16*$C88)*0.25)+((Q$16*$C88)*0.75) -> 0 | R88: =SUM(E88:Q88) -> 4500000 | T88: =R88/$R$16 -> 100000 | U88: /LOT | V88: Build Cost $/sf Check
B89: Vertical Construction Costs | C89: =Assumptions!C17 -> 850 | E89: =(((SUMPRODUCT($D$6:$D$15,E6:E15))*$C89)) -> 0 | F89: =(((SUMPRODUCT($D$6:$D$15,F6:F15))*$C89)) -> 14875000 | G89: =(((SUMPRODUCT($D$6:$D$15,G6:G15))*$C89)) -> 27625000 | H89: =(((SUMPRODUCT($D$6:$D$15,H6:H15))*$C89)) -> 45687500 | I89: =(((SUMPRODUCT($D$6:$D$15,I6:I15))*$C89)) -> 46750000 | J89: =(((SUMPRODUCT($D$6:$D$15,J6:J15))*$C89)) -> 0 | K89: =(((SUMPRODUCT($D$6:$D$15,K6:K15))*$C89)) -> 0 | L89: =(((SUMPRODUCT($D$6:$D$15,L6:L15))*$C89)) -> 0 | M89: =(((SUMPRODUCT($D$6:$D$15,L6:L15))*$C89)*0.5)+(((SUMPRODUCT($D$6:$D$15,M6:M15))*$C89)*0.5) -> 0 | N89: =(((SUMPRODUCT($D$6:$D$15,M6:M15))*$C89)*0.5)+(((SUMPRODUCT($D$6:$D$15,N6:N15))*$C89)*0.5) -> 0 | O89: =(((SUMPRODUCT($D$6:$D$15,N6:N15))*$C89)*0.5)+(((SUMPRODUCT($D$6:$D$15,O6:O15))*$C89)*0.5) -> 0 | P89: =(((SUMPRODUCT($D$6:$D$15,O6:O15))*$C89)*0.5)+(((SUMPRODUCT($D$6:$D$15,P6:P15))*$C89)*0.5) -> 0 | Q89: =(((SUMPRODUCT($D$6:$D$15,P6:P15))*$C89)*0.5)+(((SUMPRODUCT($D$6:$D$15,Q6:Q15))*$C89)*0.5) -> 0 | R89: =SUM(E89:Q89) -> 134937500 | T89: =R89/$R$16 -> 2998611.1 | U89: AVE / HOME | V89: =R89/$V$16 -> 850
B90: Landscape / Hardscape | C90: 150000 | F90: =E$16*$C90 -> 0 | G90: =F$16*$C90 -> 750000 | H90: =G$16*$C90 -> 1500000 | I90: =H$16*$C90 -> 2250000 | J90: =I$16*$C90 -> 2250000 | K90: =J$16*$C90 -> 0 | L90: =K$16*$C90 -> 0 | M90: =L$16*$C90 -> 0 | ... Q90: =P$16*$C90 -> 0 | R90: =SUM(F90:Q90) -> 6750000 | T90: =R90/$R$16 -> 150000 | U90: /LOT
B91: Construction Management | C91: 0.035 | E91: =SUM(E88:E90)*$C91 -> 13125 | F91: =SUM(F88:F90)*$C91 -> 551250 | G91: =SUM(G88:G90)*$C91 -> 1041250 | H91: =SUM(H88:H90)*$C91 -> 1704062.5 | I91: =SUM(I88:I90)*$C91 -> 1728125 | J91: =SUM(J88:J90)*$C91 -> 78750 | K91: =SUM(K88:K90)*$C91 -> 0 | L91: =SUM(L88:L90)*$C91 -> 0 | R91: =SUM(E91:Q91) -> 5116562.5 | T91: =R91/$R$16 -> 113701.39 | U91: AVE / HOME
B92: Construction Cost Escalation | C92: 0.05 | E92: =SUM(E88:E90)*$C92 -> 18750 | F92: =SUM(F88:F90,E92)*$C92 -> 788437.5 | G92: =SUM(G88:G90,E92:F92)*$C92 -> 1527859.4 | H92: =SUM(H88:H90,E92:G92)*$C92 -> 2551127.3 | I92: =SUM(I88:I90,E92:H92)*$C92 -> 2713058.7 | J92: =SUM(J88:J90,E92:I92)*$C92 -> 492461.65 | R92: =SUM(E92:Q92) -> 8091694.6 | T92: =R92/$R$16 -> 179815.44 | U92: AVE / HOME
B93: Developer Construction Contingency | C93: 0.035 | E93: =SUM(E87:E90)*$C93 -> 13125 | F93: =SUM(F87:F90)*$C93 -> 551250 | G93: =SUM(G87:G90)*$C93 -> 1041250 | H93: =SUM(H87:H90)*$C93 -> 1704062.5 | I93: =SUM(I87:I90)*$C93 -> 1728125 | J93: =SUM(J87:J90)*$C93 -> 78750 | K93: =SUM(K87:K90)*$C93 -> 0 | L93: =SUM(L87:L90)*$C93 -> 0 | ... Q93: =SUM(Q87:Q90)*$C93 -> 0 | R93: =SUM(E93:Q93) -> 5116562.5 | T93: =R93/$R$16 -> 113701.39 | U93: AVE / HOME | V93: Total Cost $/sf Check
B94: =B87 -> HARD COSTS - HOMES | E94: =SUM(E87:E93) -> 420000 | F94: =SUM(F87:F93) -> 17640938 | G94: =SUM(G87:G93) -> 33360359 | H94: =SUM(H87:H93) -> 54646752 | I94: =SUM(I87:I93) -> 55544309 | J94: =SUM(J87:J93) -> 2899961.6 | K94: =SUM(K87:K93) -> 0 | L94: =SUM(L87:L93) -> 0 | ... Q94: =SUM(Q87:Q93) -> 0 | R94: =SUM(E94:Q94) -> 1.6451232e+08 | T94: =R94/$R$16 -> 3655829.3 | U94: AVE / HOME | V94: =R94/$V$16 -> 1036.2981
T95: =R94/$T$59 -> 0.46074704 | U95: of Sales
B96: SOFT COSTS PROFESSIONALS - FINAL ENTITLEMENTS & SITE INFRA.
B97: Land Planning & PUD App Prep/Revisions (15% of Cost) | C97: =(SUM(C82:C82))*0.15 -> 112500 | E97: =$C$97*0.75 -> 84375 | F97: =$C$97*0.25 -> 28125 | R97: =SUM(E97:Q97) -> 112500 | T97: =C97-R97 -> 0
B98: Future Entitlement Management Overhead | C98: 500000 | E98: =$C98 -> 500000 | F98: =$C98 -> 500000 | G98: =$C98 -> 500000 | H98: =$C98 -> 500000 | R98: =SUM(E98:Q98) -> 2000000
B99: Civil, Surveying & PUD App Prep/Revisions (10% of Infra Cost) | C99: =(SUM(C68:C81))*0.1 -> 712562.5 | E99: =$C$99*0.55 -> 391909.38 | F99: =$C$99*0.2 -> 142512.5 | G99: =$C$99*0.2 -> 142512.5 | H99: =$C$99*0.05 -> 35628.125 | R99: =SUM(E99:Q99) -> 712562.5 | T99: =C99-R99 -> 0
B100: Traffic, Enviro, Economist & Misc. Studies | C100: 300000 | E100: =$C$100 -> 300000 | R100: =SUM(E100:Q100) -> 300000 | T100: =C100-R100 -> 0
B101: Legal / Entitlement | C101: 400000 | E101: =C101*0.75 -> 300000 | F101: =C101*0.25 -> 100000 | R101: =SUM(E101:Q101) -> 400000 | T101: =C101-R101 -> 0
B102: Accounting & CPA costs ($ per year) | C102: 10000 | E102: =$C$102 -> 10000 | F102: =$C$102 -> 10000 | G102: =$C$102 -> 10000 | H102: =$C$102 -> 10000 | I102: =$C$102 -> 10000 | J102: =$C$102 -> 10000 | R102: =SUM(E102:Q102) -> 60000
B103: Professionals Contingency | C103: 0.05 | E103: =SUM(E96:E102)*$C$103 -> 79314.219 | F103: =SUM(F96:F102)*$C$103 -> 39031.875 | G103: =SUM(G96:G102)*$C$103 -> 32625.625 | H103: =SUM(H96:H102)*$C$103 -> 27281.406 | Q103: =SUM(Q99:Q102)*$C$103 -> 0 | R103: =SUM(E103:Q103) -> 178253.12
B104: =B96 -> SOFT COSTS PROFESSIONALS - FINAL ENTITLEMENTS & SITE INFRA. | E104: =SUM(E96:E103) -> 1665598.6 | F104: =SUM(F96:F103) -> 819669.38 | G104: =SUM(G96:G103) -> 685138.12 | H104: =SUM(H96:H103) -> 572909.53 | I104: =SUM(I96:I103) -> 10000 | J104: =SUM(J96:J103) -> 10000 | K104: =SUM(K96:K103) -> 0 | L104: =SUM(L96:L103) -> 0 | ... Q104: =SUM(Q96:Q103) -> 0 | R104: =SUM(E104:Q104) -> 3763315.6 | T104: =R104/$R$16 -> 83629.236 | U104: $/Lot
...

Sheet L+H Monthly CF
B1: CLARENDON - LAND & HOME DEVELOPMENT
B2: Build & Sales Proforma
E3: 0 | F3: 0 | G3: 0 | H3: 0 | I3: 0 | J3: 0 | K3: 0 | L3: 0 | M3: 0 | N3: 0 | O3: 0 | P3: 0 | Q3: =E3+1 -> 1 | R3: =F3+1 -> 1 | S3: =G3+1 -> 1 | T3: =H3+1 -> 1 | U3: =I3+1 -> 1 | V3: =J3+1 -> 1 | W3: =K3+1 -> 1 | X3: =L3+1 -> 1 | ... AZ3: =AN3+1 -> 3 | BA3: 48mo Total | BB3: Check
D4: Month Beginning | E4: =Assumptions!C5 -> 45658 | F4: =EDATE(E4,1) -> 45689 | G4: =EDATE(F4,1) -> 45717 | H4: =EDATE(G4,1) -> 45748 | I4: =EDATE(H4,1) -> 45778 | J4: =EDATE(I4,1) -> 45809 | K4: =EDATE(J4,1) -> 45839 | L4: =EDATE(K4,1) -> 45870 | M4: =EDATE(L4,1) -> 45901 | ... AZ4: =EDATE(AY4,1) -> 47088
F5: Average Sales $ per Unit
B6: SOURCES
B8: ='Proforma L+H'!B37 -> EQUITY INVESTMENT
B9: ='Proforma L+H'!B38 -> MTN ORIGINS - PURSUIT CAPITAL | E9: ='Proforma L+H'!E38 -> 1500000 | Q9: ='Proforma L+H'!F38 -> 0 | AC9: ='Proforma L+H'!G38 -> 0 | AO9: ='Proforma L+H'!H38 -> 0 | BA9: =SUM(E9:AZ9) -> 1500000 | BB9: =SUM('Proforma L+H'!E38:H38)-BA9 -> 0
B10: ='Proforma L+H'!B39 -> JV - EQUITY CAPITAL | E10: ='Proforma L+H'!E39 -> 10000000 | Q10: ='Proforma L+H'!F39 -> 0 | AC10: ='Proforma L+H'!G39 -> 0 | AO10: ='Proforma L+H'!H39 -> 0 | BA10: =SUM(E10:AZ10) -> 10000000 | BB10: =SUM('Proforma L+H'!E39:H39)-BA10 -> 0
B11: ='Proforma L+H'!B40 -> EQUITY INVESTMENT | E11: ='Proforma L+H'!E40 -> 11500000 | Q11: ='Proforma L+H'!F40 -> 0 | AC11: ='Proforma L+H'!G40 -> 0 | AO11: ='Proforma L+H'!H40 -> 0 | BA11: =SUM(E11:AZ11) -> 11500000 | BB11: =SUM('Proforma L+H'!E40:H40)-BA11 -> 0
B13: ='Proforma L+H'!B42 -> DEBT | C13: =U259 -> 0
B14: ='Proforma L+H'!B43 -> JV BRIDGE LOAN | E14: ='Proforma L+H'!E43 -> 15000000 | Q14: ='Proforma L+H'!F43 -> 0 | AC14: ='Proforma L+H'!G43 -> 0 | AO14: ='Proforma L+H'!H43 -> 0 | BA14: =SUM(E14:AZ14) -> 15000000 | BB14: =SUM('Proforma L+H'!E43:H43)-BA14 -> 0
B15: ='Proforma L+H'!B44 -> SELLER FINANCE | E15: ='Proforma L+H'!E44 -> 0 | Q15: ='Proforma L+H'!F44 -> 0 | AC15: ='Proforma L+H'!G44 -> 0 | AO15: ='Proforma L+H'!H44 -> 0 | BA15: =SUM(E15:AZ15) -> 0 | BB15: =SUM('Proforma L+H'!E44:H44)-BA15 -> 0
B16: ='Proforma L+H'!B45 -> EB5 - MEZZ DEBT | E16: ='Proforma L+H'!E45 -> 0 | Q16: ='Proforma L+H'!F45 -> 20800000 | AC16: ='Proforma L+H'!G45 -> 0 | AO16: ='Proforma L+H'!H45 -> 0 | BA16: =SUM(E16:AZ16) -> 20800000 | BB16: =SUM('Proforma L+H'!E45:H45)-BA16 -> 0
B17: ='Proforma L+H'!B46 -> DEV LOAN - DEV COSTS | C17: =U258 -> 0 | E17: ='Proforma L+H'!E46 -> 0 | Q17: ='Proforma L+H'!F46 -> 19800183 | AC17: ='Proforma L+H'!G46 -> 0 | AO17: ='Proforma L+H'!H46 -> 0 | BA17: =SUM(E17:AZ17) -> 19800183 | BB17: =SUM('Proforma L+H'!E46:H46)-BA17 -> 0
B18: ='Proforma L+H'!B47 -> DEV LOAN - FINANCING / RESERVE | E18: ='Proforma L+H'!E47 -> 0 | Q18: ='Proforma L+H'!F47 -> 4092272.5 | AC18: ='Proforma L+H'!G47 -> 2867094.7 | AO18: ='Proforma L+H'!H47 -> 3746337.1 | BA18: =SUM(E18:AZ18) -> 10705704 | BB18: =SUM('Proforma L+H'!E47:H47)-BA18 -> 0
B19: ='Proforma L+H'!B48 -> DEBT | E19: ='Proforma L+H'!E48 -> 15000000 | Q19: ='Proforma L+H'!F48 -> 44692456 | AC19: ='Proforma L+H'!G48 -> 2867094.7 | AO19: ='Proforma L+H'!H48 -> 3746337.1 | BA19: =SUM(E19:AZ19) -> 66305888 | BB19: =SUM('Proforma L+H'!E48:H48)-BA19 -> 0
B21: ='Proforma L+H'!B50 -> VALUE CREATED POST PUD of 80 ACRES | E21: ='Proforma L+H'!E50 -> 0 | Q21: ='Proforma L+H'!F50 -> 0 | AC21: ='Proforma L+H'!G50 -> 15000000 | AO21: ='Proforma L+H'!H50 -> 0 | BA21: =SUM(E21:AZ21) -> 15000000 | BB21: =SUM('Proforma L+H'!E50:H50)-BA21 -> 0
B22: ='Proforma L+H'!B51 -> LAND SALE TO AMENITY | E22: ='Proforma L+H'!E51 -> 0 | Q22: ='Proforma L+H'!F51 -> 0 | AC22: ='Proforma L+H'!G51 -> 0 | AO22: ='Proforma L+H'!H51 -> 0 | BA22: =SUM(E22:AZ22) -> 0 | BB22: =SUM('Proforma L+H'!E51:H51)-BA22 -> 0
B27: ='Proforma L+H'!B56 -> PRESALE REVENUES | C27: =SUM(#REF!) -> #REF! | E27: ='Proforma L+H'!E56 -> 0 | F27: =OFFSET('Proforma L+H'!$E56,0,'L+H Monthly CF'!F$3)/12 -> 0 | G27: =OFFSET('Proforma L+H'!$E56,0,'L+H Monthly CF'!G$3)/12 -> 0 | H27: =OFFSET('Proforma L+H'!$E56,0,'L+H Monthly CF'!H$3)/12 -> 0 | I27: =OFFSET('Proforma L+H'!$E56,0,'L+H Monthly CF'!I$3)/12 -> 0 | J27: =OFFSET('Proforma L+H'!$E56,0,'L+H Monthly CF'!J$3)/12 -> 0 | K27: =OFFSET('Proforma L+H'!$E56,0,'L+H Monthly CF'!K$3)/12 -> 0 | L27: =OFFSET('Proforma L+H'!$E56,0,'L+H Monthly CF'!L$3)/12 -> 0 | M27: =OFFSET('Proforma L+H'!$E56,0,'L+H Monthly CF'!M$3)/12 -> 0 | ... AZ27: =OFFSET('Proforma L+H'!$E56,0,'L+H Monthly CF'!AZ$3)/12 -> 1954218.8 | BA27: =SUM(E27:AZ27) -> 41623062 | BB27: =SUM('Proforma L+H'!E56:H56)-BA27 -> 0
B28: ='Proforma L+H'!B57 -> UNIT SALES | E28: ='Proforma L+H'!E57 -> 0 | F28: =OFFSET('Proforma L+H'!$E57,0,'L+H Monthly CF'!F$3)/12 -> 0 | G28: =OFFSET('Proforma L+H'!$E57,0,'L+H Monthly CF'!G$3)/12 -> 0 | H28: =OFFSET('Proforma L+H'!$E57,0,'L+H Monthly CF'!H$3)/12 -> 0 | I28: =OFFSET('Proforma L+H'!$E57,0,'L+H Monthly CF'!I$3)/12 -> 0 | J28: =OFFSET('Proforma L+H'!$E57,0,'L+H Monthly CF'!J$3)/12 -> 0 | K28: =OFFSET('Proforma L+H'!$E57,0,'L+H Monthly CF'!K$3)/12 -> 0 | L28: =OFFSET('Proforma L+H'!$E57,0,'L+H Monthly CF'!L$3)/12 -> 0 | M28: =OFFSET('Proforma L+H'!$E57,0,'L+H Monthly CF'!M$3)/12 -> 0 | ... AZ28: =OFFSET('Proforma L+H'!$E57,0,'L+H Monthly CF'!AZ$3)/12 -> 4312609.4 | BA28: =SUM(E28:AZ28) -> 77660062 | BB28: =SUM('Proforma L+H'!E57:H57)-BA28 -> 0
B29: ='Proforma L+H'!B58 -> TOTAL SOURCES | E29: =E11+E19+SUM(E21:E28) -> 26500000 | F29: =F11+F19+SUM(F21:F28) -> 0 | G29: =G11+G19+SUM(G21:G28) -> 0 | H29: =H11+H19+SUM(H21:H28) -> 0 | I29: =I11+I19+SUM(I21:I28) -> 0 | J29: =J11+J19+SUM(J21:J28) -> 0 | K29: =K11+K19+SUM(K21:K28) -> 0 | L29: =L11+L19+SUM(L21:L28) -> 0 | ... AZ29: =AZ11+AZ19+SUM(AZ21:AZ28) -> 6266828.1 | BA29: =SUM(E29:AZ29) -> 2.1208901e+08 | BB29: =SUM('Proforma L+H'!E58:H58)-BA29 -> 0
B31: USES
B32: ='Proforma L+H'!B61 -> LAND & PROJECT ACQUISITION
B33: ='Proforma L+H'!B62 -> Project Acquisition | E33: ='Proforma L+H'!E62 -> 18500000 | Q33: ='Proforma L+H'!F62 -> 0 | BA33: =SUM(E33:AZ33) -> 18500000 | BB33: =SUM('Proforma L+H'!E62:H62)-BA33 -> 0
B34: ='Proforma L+H'!B63 -> Asset Acquisition Fee (based on total project initial value Equity + Debt) | C34: 0.02 | E34: ='Proforma L+H'!E63 -> 450000 | Q34: ='Proforma L+H'!F63 -> 0 | BA34: =SUM(E34:AZ34) -> 450000 | BB34: =SUM('Proforma L+H'!E63:H63)-BA34 -> 0
B35: ='Proforma L+H'!B64 -> Closing Costs | C35: 0.0015 | E35: ='Proforma L+H'!E64 -> 27750 | Q35: ='Proforma L+H'!F64 -> 0 | BA35: =SUM(E35:AZ35) -> 27750 | BB35: =SUM('Proforma L+H'!E64:H64)-BA35 -> 0
B36: ='Proforma L+H'!B65 -> LAND & PROJECT ACQUISITION | E36: ='Proforma L+H'!E65 -> 18977750 | Q36: ='Proforma L+H'!F65 -> 0 | BA36: =SUM(E36:AZ36) -> 18977750 | BB36: =SUM('Proforma L+H'!E65:H65)-BA36 -> 0
B38: ='Proforma L+H'!B67 -> HARD COSTS - SITE, RESTORATION & INFRASTRUCTURE
B39: ='Proforma L+H'!B68 -> Internal Road: Base + Gravel Finish @ Lower 80 | C39: =235000*1.25 -> 293750 | E39: =OFFSET('Proforma L+H'!$E68,0,'L+H Monthly CF'!E$3)/12 -> 0 | F39: =OFFSET('Proforma L+H'!$E68,0,'L+H Monthly CF'!F$3)/12 -> 0 | G39: =OFFSET('Proforma L+H'!$E68,0,'L+H Monthly CF'!G$3)/12 -> 0 | H39: =OFFSET('Proforma L+H'!$E68,0,'L+H Monthly CF'!H$3)/12 -> 0 | I39: =OFFSET('Proforma L+H'!$E68,0,'L+H Monthly CF'!I$3)/12 -> 0 | J39: =OFFSET('Proforma L+H'!$E68,0,'L+H Monthly CF'!J$3)/12 -> 0 | K39: =OFFSET('Proforma L+H'!$E68,0,'L+H Monthly CF'!K$3)/12 -> 0 | L39: =OFFSET('Proforma L+H'!$E68,0,'L+H Monthly CF'!L$3)/12 -> 0 | ... AZ39: =OFFSET('Proforma L+H'!$E68,0,'L+H Monthly CF'!AZ$3)/12 -> 0 | BA39: =SUM(E39:AZ39) -> 293750 | BB39: =SUM('Proforma L+H'!E68:H68)-BA39 -> 0
B40: ='Proforma L+H'!B69 -> Internal Road: Base + Gravel Finish @ 45 Lots | C40: =590000*1.25 -> 737500 | E40: =OFFSET('Proforma L+H'!$E69,0,'L+H Monthly CF'!E$3)/12 -> 0 | F40: =OFFSET('Proforma L+H'!$E69,0,'L+H Monthly CF'!F$3)/12 -> 0 | G40: =OFFSET('Proforma L+H'!$E69,0,'L+H Monthly CF'!G$3)/12 -> 0 | H40: =OFFSET('Proforma L+H'!$E69,0,'L+H Monthly CF'!H$3)/12 -> 0 | I40: =OFFSET('Proforma L+H'!$E69,0,'L+H Monthly CF'!I$3)/12 -> 0 | J40: =OFFSET('Proforma L+H'!$E69,0,'L+H Monthly CF'!J$3)/12 -> 0 | K40: =OFFSET('Proforma L+H'!$E69,0,'L+H Monthly CF'!K$3)/12 -> 0 | L40: =OFFSET('Proforma L+H'!$E69,0,'L+H Monthly CF'!L$3)/12 -> 0 | ... AZ40: =OFFSET('Proforma L+H'!$E69,0,'L+H Monthly CF'!AZ$3)/12 -> 20486.111 | BA40: =SUM(E40:AZ40) -> 737500 | BB40: =SUM('Proforma L+H'!E69:H69)-BA40 -> 0
B41: ='Proforma L+H'!B70 -> Internal Road: Paving @ 45 Lots | C41: =350000*1.25 -> 437500 | E41: =OFFSET('Proforma L+H'!$E70,0,'L+H Monthly CF'!E$3)/12 -> 0 | F41: =OFFSET('Proforma L+H'!$E70,0,'L+H Monthly CF'!F$3)/12 -> 0 | G41: =OFFSET('Proforma L+H'!$E70,0,'L+H Monthly CF'!G$3)/12 -> 0 | H41: =OFFSET('Proforma L+H'!$E70,0,'L+H Monthly CF'!H$3)/12 -> 0 | I41: =OFFSET('Proforma L+H'!$E70,0,'L+H Monthly CF'!I$3)/12 -> 0 | J41: =OFFSET('Proforma L+H'!$E70,0,'L+H Monthly CF'!J$3)/12 -> 0 | K41: =OFFSET('Proforma L+H'!$E70,0,'L+H Monthly CF'!K$3)/12 -> 0 | L41: =OFFSET('Proforma L+H'!$E70,0,'L+H Monthly CF'!L$3)/12 -> 0 | ... AZ41: =OFFSET('Proforma L+H'!$E70,0,'L+H Monthly CF'!AZ$3)/12 -> 12152.778 | BA41: =SUM(E41:AZ41) -> 437500 | BB41: =SUM('Proforma L+H'!E70:H70)-BA41 -> 0
B42: ='Proforma L+H'!B71 -> County/USFS Road: BASE + GRAVEL FINISH @ end of existing | C42: =500000*1.25 -> 625000 | E42: =OFFSET('Proforma L+H'!$E71,0,'L+H Monthly CF'!E$3)/12 -> 26041.667 | F42: =OFFSET('Proforma L+H'!$E71,0,'L+H Monthly CF'!F$3)/12 -> 26041.667 | G42: =OFFSET('Proforma L+H'!$E71,0,'L+H Monthly CF'!G$3)/12 -> 26041.667 | H42: =OFFSET('Proforma L+H'!$E71,0,'L+H Monthly CF'!H$3)/12 -> 26041.667 | I42: =OFFSET('Proforma L+H'!$E71,0,'L+H Monthly CF'!I$3)/12 -> 26041.667 | J42: =OFFSET('Proforma L+H'!$E71,0,'L+H Monthly CF'!J$3)/12 -> 26041.667 | K42: =OFFSET('Proforma L+H'!$E71,0,'L+H Monthly CF'!K$3)/12 -> 26041.667 | L42: =OFFSET('Proforma L+H'!$E71,0,'L+H Monthly CF'!L$3)/12 -> 26041.667 | ... AZ42: =OFFSET('Proforma L+H'!$E71,0,'L+H Monthly CF'!AZ$3)/12 -> 0 | BA42: =SUM(E42:AZ42) -> 625000 | BB42: =SUM('Proforma L+H'!E71:H71)-BA42 -> 0
B43: ='Proforma L+H'!B72 -> County/USFS Road: PAVING @ end of existing to back gate | C43: =500000*1.25 -> 625000 | E43: =OFFSET('Proforma L+H'!$E72,0,'L+H Monthly CF'!E$3)/12 -> 0 | F43: =OFFSET('Proforma L+H'!$E72,0,'L+H Monthly CF'!F$3)/12 -> 0 | G43: =OFFSET('Proforma L+H'!$E72,0,'L+H Monthly CF'!G$3)/12 -> 0 | H43: =OFFSET('Proforma L+H'!$E72,0,'L+H Monthly CF'!H$3)/12 -> 0 | I43: =OFFSET('Proforma L+H'!$E72,0,'L+H Monthly CF'!I$3)/12 -> 0 | J43: =OFFSET('Proforma L+H'!$E72,0,'L+H Monthly CF'!J$3)/12 -> 0 | K43: =OFFSET('Proforma L+H'!$E72,0,'L+H Monthly CF'!K$3)/12 -> 0 | L43: =OFFSET('Proforma L+H'!$E72,0,'L+H Monthly CF'!L$3)/12 -> 0 | ... AZ43: =OFFSET('Proforma L+H'!$E72,0,'L+H Monthly CF'!AZ$3)/12 -> 26041.667 | BA43: =SUM(E43:AZ43) -> 625000 | BB43: =SUM('Proforma L+H'!E72:H72)-BA43 -> 0
B44: ='Proforma L+H'!B73 -> Road: Bridges (1) @ Spillway | C44: 150000 | E44: =OFFSET('Proforma L+H'!$E73,0,'L+H Monthly CF'!E$3)/12 -> 12500 | F44: =OFFSET('Proforma L+H'!$E73,0,'L+H Monthly CF'!F$3)/12 -> 12500 | G44: =OFFSET('Proforma L+H'!$E73,0,'L+H Monthly CF'!G$3)/12 -> 12500 | H44: =OFFSET('Proforma L+H'!$E73,0,'L+H Monthly CF'!H$3)/12 -> 12500 | I44: =OFFSET('Proforma L+H'!$E73,0,'L+H Monthly CF'!I$3)/12 -> 12500 | J44: =OFFSET('Proforma L+H'!$E73,0,'L+H Monthly CF'!J$3)/12 -> 12500 | K44: =OFFSET('Proforma L+H'!$E73,0,'L+H Monthly CF'!K$3)/12 -> 12500 | L44: =OFFSET('Proforma L+H'!$E73,0,'L+H Monthly CF'!L$3)/12 -> 12500 | ... AZ44: =OFFSET('Proforma L+H'!$E73,0,'L+H Monthly CF'!AZ$3)/12 -> 0 | BA44: =SUM(E44:AZ44) -> 150000 | BB44: =SUM('Proforma L+H'!E73:H73)-BA44 -> 0
B45: ='Proforma L+H'!B74 -> Utilities: County/USFS Power Trench+Line (4.5 miles) | C45: =650000*1.25 -> 812500 | E45: =OFFSET('Proforma L+H'!$E74,0,'L+H Monthly CF'!E$3)/12 -> 67708.333 | F45: =OFFSET('Proforma L+H'!$E74,0,'L+H Monthly CF'!F$3)/12 -> 67708.333 | G45: =OFFSET('Proforma L+H'!$E74,0,'L+H Monthly CF'!G$3)/12 -> 67708.333 | H45: =OFFSET('Proforma L+H'!$E74,0,'L+H Monthly CF'!H$3)/12 -> 67708.333 | I45: =OFFSET('Proforma L+H'!$E74,0,'L+H Monthly CF'!I$3)/12 -> 67708.333 | J45: =OFFSET('Proforma L+H'!$E74,0,'L+H Monthly CF'!J$3)/12 -> 67708.333 | K45: =OFFSET('Proforma L+H'!$E74,0,'L+H Monthly CF'!K$3)/12 -> 67708.333 | L45: =OFFSET('Proforma L+H'!$E74,0,'L+H Monthly CF'!L$3)/12 -> 67708.333 | ... AZ45: =OFFSET('Proforma L+H'!$E74,0,'L+H Monthly CF'!AZ$3)/12 -> 0 | BA45: =SUM(E45:AZ45) -> 812500 | BB45: =SUM('Proforma L+H'!E74:H74)-BA45 -> 0
B46: ='Proforma L+H'!B75 -> Utilities: Power & Transformers @ 45 Lots (8,500 LF) | C46: =(105000*1.25)+15*4000 -> 191250 | E46: =OFFSET('Proforma L+H'!$E75,0,'L+H Monthly CF'!E$3)/12 -> 0 | F46: =OFFSET('Proforma L+H'!$E75,0,'L+H Monthly CF'!F$3)/12 -> 0 | G46: =OFFSET('Proforma L+H'!$E75,0,'L+H Monthly CF'!G$3)/12 -> 0 | H46: =OFFSET('Proforma L+H'!$E75,0,'L+H Monthly CF'!H$3)/12 -> 0 | I46: =OFFSET('Proforma L+H'!$E75,0,'L+H Monthly CF'!I$3)/12 -> 0 | J46: =OFFSET('Proforma L+H'!$E75,0,'L+H Monthly CF'!J$3)/12 -> 0 | K46: =OFFSET('Proforma L+H'!$E75,0,'L+H Monthly CF'!K$3)/12 -> 0 | L46: =OFFSET('Proforma L+H'!$E75,0,'L+H Monthly CF'!L$3)/12 -> 0 | ... AZ46: =OFFSET('Proforma L+H'!$E75,0,'L+H Monthly CF'!AZ$3)/12 -> 5312.5 | BA46: =SUM(E46:AZ46) -> 191250 | BB46: =SUM('Proforma L+H'!E75:H75)-BA46 -> 0
B47: ='Proforma L+H'!B76 -> Utilities: Comm. Distrib. @ 45 Lots (8,500 LF) | C47: =(8500*15)*1.25 -> 159375 | E47: =OFFSET('Proforma L+H'!$E76,0,'L+H Monthly CF'!E$3)/12 -> 0 | F47: =OFFSET('Proforma L+H'!$E76,0,'L+H Monthly CF'!F$3)/12 -> 0 | G47: =OFFSET('Proforma L+H'!$E76,0,'L+H Monthly CF'!G$3)/12 -> 0 | H47: =OFFSET('Proforma L+H'!$E76,0,'L+H Monthly CF'!H$3)/12 -> 0 | I47: =OFFSET('Proforma L+H'!$E76,0,'L+H Monthly CF'!I$3)/12 -> 0 | J47: =OFFSET('Proforma L+H'!$E76,0,'L+H Monthly CF'!J$3)/12 -> 0 | K47: =OFFSET('Proforma L+H'!$E76,0,'L+H Monthly CF'!K$3)/12 -> 0 | L47: =OFFSET('Proforma L+H'!$E76,0,'L+H Monthly CF'!L$3)/12 -> 0 | ... AZ47: =OFFSET('Proforma L+H'!$E76,0,'L+H Monthly CF'!AZ$3)/12 -> 4427.0833 | BA47: =SUM(E47:AZ47) -> 159375 | BB47: =SUM('Proforma L+H'!E76:H76)-BA47 -> 0
B48: ='Proforma L+H'!B77 -> Utilities: Water Main @ 45 Lots | C48: =550000*1.25 -> 687500 | E48: =OFFSET('Proforma L+H'!$E77,0,'L+H Monthly CF'!E$3)/12 -> 19097.222 | F48: =OFFSET('Proforma L+H'!$E77,0,'L+H Monthly CF'!F$3)/12 -> 19097.222 | G48: =OFFSET('Proforma L+H'!$E77,0,'L+H Monthly CF'!G$3)/12 -> 19097.222 | H48: =OFFSET('Proforma L+H'!$E77,0,'L+H Monthly CF'!H$3)/12 -> 19097.222 | I48: =OFFSET('Proforma L+H'!$E77,0,'L+H Monthly CF'!I$3)/12 -> 19097.222 | J48: =OFFSET('Proforma L+H'!$E77,0,'L+H Monthly CF'!J$3)/12 -> 19097.222 | K48: =OFFSET('Proforma L+H'!$E77,0,'L+H Monthly CF'!K$3)/12 -> 19097.222 | L48: =OFFSET('Proforma L+H'!$E77,0,'L+H Monthly CF'!L$3)/12 -> 19097.222 | ... AZ48: =OFFSET('Proforma L+H'!$E77,0,'L+H Monthly CF'!AZ$3)/12 -> 0 | BA48: =SUM(E48:AZ48) -> 687500 | BB48: =SUM('Proforma L+H'!E77:H77)-BA48 -> 0
B49: ='Proforma L+H'!B78 -> Utilities: Water Wells, Pumps & Backup Power Requirements | C49: =1000000*1.25 -> 1250000 | E49: =OFFSET('Proforma L+H'!$E78,0,'L+H Monthly CF'!E$3)/12 -> 52083.333 | F49: =OFFSET('Proforma L+H'!$E78,0,'L+H Monthly CF'!F$3)/12 -> 52083.333 | G49: =OFFSET('Proforma L+H'!$E78,0,'L+H Monthly CF'!G$3)/12 -> 52083.333 | H49: =OFFSET('Proforma L+H'!$E78,0,'L+H Monthly CF'!H$3)/12 -> 52083.333 | I49: =OFFSET('Proforma L+H'!$E78,0,'L+H Monthly CF'!I$3)/12 -> 52083.333 | J49: =OFFSET('Proforma L+H'!$E78,0,'L+H Monthly CF'!J$3)/12 -> 52083.333 | K49: =OFFSET('Proforma L+H'!$E78,0,'L+H Monthly CF'!K$3)/12 -> 52083.333 | L49: =OFFSET('Proforma L+H'!$E78,0,'L+H Monthly CF'!L$3)/12 -> 52083.333 | ... AZ49: =OFFSET('Proforma L+H'!$E78,0,'L+H Monthly CF'!AZ$3)/12 -> 0 | BA49: =SUM(E49:AZ49) -> 1250000 | BB49: =SUM('Proforma L+H'!E78:H78)-BA49 -> 0
B50: ='Proforma L+H'!B79 -> Utilities: Lift Station @ 45 Lots (8,500 LF) | C50: =125000*1.25 -> 156250 | E50: =OFFSET('Proforma L+H'!$E79,0,'L+H Monthly CF'!E$3)/12 -> 0 | F50: =OFFSET('Proforma L+H'!$E79,0,'L+H Monthly CF'!F$3)/12 -> 0 | G50: =OFFSET('Proforma L+H'!$E79,0,'L+H Monthly CF'!G$3)/12 -> 0 | H50: =OFFSET('Proforma L+H'!$E79,0,'L+H Monthly CF'!H$3)/12 -> 0 | I50: =OFFSET('Proforma L+H'!$E79,0,'L+H Monthly CF'!I$3)/12 -> 0 | J50: =OFFSET('Proforma L+H'!$E79,0,'L+H Monthly CF'!J$3)/12 -> 0 | K50: =OFFSET('Proforma L+H'!$E79,0,'L+H Monthly CF'!K$3)/12 -> 0 | L50: =OFFSET('Proforma L+H'!$E79,0,'L+H Monthly CF'!L$3)/12 -> 0 | ... AZ50: =OFFSET('Proforma L+H'!$E79,0,'L+H Monthly CF'!AZ$3)/12 -> 4340.2778 | BA50: =SUM(E50:AZ50) -> 156250 | BB50: =SUM('Proforma L+H'!E79:H79)-BA50 -> 0
B51: ='Proforma L+H'!B80 -> Utilities: Sewer Treatment Drainfield Sys (4 EA) | C51: =625000*1.25 -> 781250 | E51: =OFFSET('Proforma L+H'!$E80,0,'L+H Monthly CF'!E$3)/12 -> 16276.042 | F51: =OFFSET('Proforma L+H'!$E80,0,'L+H Monthly CF'!F$3)/12 -> 16276.042 | G51: =OFFSET('Proforma L+H'!$E80,0,'L+H Monthly CF'!G$3)/12 -> 16276.042 | H51: =OFFSET('Proforma L+H'!$E80,0,'L+H Monthly CF'!H$3)/12 -> 16276.042 | I51: =OFFSET('Proforma L+H'!$E80,0,'L+H Monthly CF'!I$3)/12 -> 16276.042 | J51: =OFFSET('Proforma L+H'!$E80,0,'L+H Monthly CF'!J$3)/12 -> 16276.042 | K51: =OFFSET('Proforma L+H'!$E80,0,'L+H Monthly CF'!K$3)/12 -> 16276.042 | L51: =OFFSET('Proforma L+H'!$E80,0,'L+H Monthly CF'!L$3)/12 -> 16276.042 | ... AZ51: =OFFSET('Proforma L+H'!$E80,0,'L+H Monthly CF'!AZ$3)/12 -> 16276.042 | BA51: =SUM(E51:AZ51) -> 781250 | BB51: =SUM('Proforma L+H'!E80:H80)-BA51 -> 0
B52: ='Proforma L+H'!B81 -> Utilities: Geothermal Infrastructure @ 45 Lots | C52: =175000*1.25 -> 218750 | E52: =OFFSET('Proforma L+H'!$E81,0,'L+H Monthly CF'!E$3)/12 -> 0 | F52: =OFFSET('Proforma L+H'!$E81,0,'L+H Monthly CF'!F$3)/12 -> 0 | G52: =OFFSET('Proforma L+H'!$E81,0,'L+H Monthly CF'!G$3)/12 -> 0 | H52: =OFFSET('Proforma L+H'!$E81,0,'L+H Monthly CF'!H$3)/12 -> 0 | I52: =OFFSET('Proforma L+H'!$E81,0,'L+H Monthly CF'!I$3)/12 -> 0 | J52: =OFFSET('Proforma L+H'!$E81,0,'L+H Monthly CF'!J$3)/12 -> 0 | K52: =OFFSET('Proforma L+H'!$E81,0,'L+H Monthly CF'!K$3)/12 -> 0 | L52: =OFFSET('Proforma L+H'!$E81,0,'L+H Monthly CF'!L$3)/12 -> 0 | ... AZ52: =OFFSET('Proforma L+H'!$E81,0,'L+H Monthly CF'!AZ$3)/12 -> 6076.3889 | BA52: =SUM(E52:AZ52) -> 218750 | BB52: =SUM('Proforma L+H'!E81:H81)-BA52 -> 0
B53: ='Proforma L+H'!B82 -> Landscape: Early Plantings in Public Areas | C53: 750000 | E53: =OFFSET('Proforma L+H'!$E82,0,'L+H Monthly CF'!E$3)/12 -> 0 | F53: =OFFSET('Proforma L+H'!$E82,0,'L+H Monthly CF'!F$3)/12 -> 0 | G53: =OFFSET('Proforma L+H'!$E82,0,'L+H Monthly CF'!G$3)/12 -> 0 | H53: =OFFSET('Proforma L+H'!$E82,0,'L+H Monthly CF'!H$3)/12 -> 0 | I53: =OFFSET('Proforma L+H'!$E82,0,'L+H Monthly CF'!I$3)/12 -> 0 | J53: =OFFSET('Proforma L+H'!$E82,0,'L+H Monthly CF'!J$3)/12 -> 0 | K53: =OFFSET('Proforma L+H'!$E82,0,'L+H Monthly CF'!K$3)/12 -> 0 | L53: =OFFSET('Proforma L+H'!$E82,0,'L+H Monthly CF'!L$3)/12 -> 0 | ... AZ53: =OFFSET('Proforma L+H'!$E82,0,'L+H Monthly CF'!AZ$3)/12 -> 20833.333 | BA53: =SUM(E53:AZ53) -> 750000 | BB53: =SUM('Proforma L+H'!E82:H82)-BA53 -> 0
B54: ='Proforma L+H'!B83 -> Construction Cost Escalation | C54: 0.05 | E54: =OFFSET('Proforma L+H'!$E83,0,'L+H Monthly CF'!E$3)/12 -> 9685.3299 | F54: =OFFSET('Proforma L+H'!$E83,0,'L+H Monthly CF'!F$3)/12 -> 9685.3299 | G54: =OFFSET('Proforma L+H'!$E83,0,'L+H Monthly CF'!G$3)/12 -> 9685.3299 | H54: =OFFSET('Proforma L+H'!$E83,0,'L+H Monthly CF'!H$3)/12 -> 9685.3299 | I54: =OFFSET('Proforma L+H'!$E83,0,'L+H Monthly CF'!I$3)/12 -> 9685.3299 | J54: =OFFSET('Proforma L+H'!$E83,0,'L+H Monthly CF'!J$3)/12 -> 9685.3299 | K54: =OFFSET('Proforma L+H'!$E83,0,'L+H Monthly CF'!K$3)/12 -> 9685.3299 | L54: =OFFSET('Proforma L+H'!$E83,0,'L+H Monthly CF'!L$3)/12 -> 9685.3299 | ... AZ54: =OFFSET('Proforma L+H'!$E83,0,'L+H Monthly CF'!AZ$3)/12 -> 7222.7569 | BA54: =SUM(E54:AZ54) -> 428780.57 | BB54: =SUM('Proforma L+H'!E83:H83)-BA54 -> 0
B55: ='Proforma L+H'!B84 -> Developer Construction Contingency | C55: 0.05 | E55: =OFFSET('Proforma L+H'!$E84,0,'L+H Monthly CF'!E$3)/12 -> 9685.3299 | F55: =OFFSET('Proforma L+H'!$E84,0,'L+H Monthly CF'!F$3)/12 -> 9685.3299 | G55: =OFFSET('Proforma L+H'!$E84,0,'L+H Monthly CF'!G$3)/12 -> 9685.3299 | H55: =OFFSET('Proforma L+H'!$E84,0,'L+H Monthly CF'!H$3)/12 -> 9685.3299 | I55: =OFFSET('Proforma L+H'!$E84,0,'L+H Monthly CF'!I$3)/12 -> 9685.3299 | J55: =OFFSET('Proforma L+H'!$E84,0,'L+H Monthly CF'!J$3)/12 -> 9685.3299 | K55: =OFFSET('Proforma L+H'!$E84,0,'L+H Monthly CF'!K$3)/12 -> 9685.3299 | L55: =OFFSET('Proforma L+H'!$E84,0,'L+H Monthly CF'!L$3)/12 -> 9685.3299 | ... AZ55: =OFFSET('Proforma L+H'!$E84,0,'L+H Monthly CF'!AZ$3)/12 -> 5797.309 | BA55: =SUM(E55:AZ55) -> 393781.25 | BB55: =SUM('Proforma L+H'!E84:H84)-BA55 -> 0
B56: ='Proforma L+H'!B85 -> HARD COSTS - SITE, RESTORATION & INFRASTRUCTURE | E56: =OFFSET('Proforma L+H'!$E85,0,'L+H Monthly CF'!E$3)/12 -> 213077.26 | F56: =OFFSET('Proforma L+H'!$E85,0,'L+H Monthly CF'!F$3)/12 -> 213077.26 | G56: =OFFSET('Proforma L+H'!$E85,0,'L+H Monthly CF'!G$3)/12 -> 213077.26 | H56: =OFFSET('Proforma L+H'!$E85,0,'L+H Monthly CF'!H$3)/12 -> 213077.26 | I56: =OFFSET('Proforma L+H'!$E85,0,'L+H Monthly CF'!I$3)/12 -> 213077.26 | J56: =OFFSET('Proforma L+H'!$E85,0,'L+H Monthly CF'!J$3)/12 -> 213077.26 | K56: =OFFSET('Proforma L+H'!$E85,0,'L+H Monthly CF'!K$3)/12 -> 213077.26 | L56: =OFFSET('Proforma L+H'!$E85,0,'L+H Monthly CF'!L$3)/12 -> 213077.26 | ... AZ56: =OFFSET('Proforma L+H'!$E85,0,'L+H Monthly CF'!AZ$3)/12 -> 128966.25 | BA56: =SUM(E56:AZ56) -> 8698186.8 | BB56: =SUM('Proforma L+H'!E85:H85)-BA56 -> 0
B58: ='Proforma L+H'!B87 -> HARD COSTS - HOMES
B59: ='Proforma L+H'!B88 -> Infrastructure (Utilities & Driveway) | C59: 100000 | E59: =OFFSET('Proforma L+H'!$E88,0,'L+H Monthly CF'!E$3)/12 -> 31250 | F59: =OFFSET('Proforma L+H'!$E88,0,'L+H Monthly CF'!F$3)/12 -> 31250 | G59: =OFFSET('Proforma L+H'!$E88,0,'L+H Monthly CF'!G$3)/12 -> 31250 | H59: =OFFSET('Proforma L+H'!$E88,0,'L+H Monthly CF'!H$3)/12 -> 31250 | I59: =OFFSET('Proforma L+H'!$E88,0,'L+H Monthly CF'!I$3)/12 -> 31250 | J59: =OFFSET('Proforma L+H'!$E88,0,'L+H Monthly CF'!J$3)/12 -> 31250 | K59: =OFFSET('Proforma L+H'!$E88,0,'L+H Monthly CF'!K$3)/12 -> 31250 | L59: =OFFSET('Proforma L+H'!$E88,0,'L+H Monthly CF'!L$3)/12 -> 31250 | ... AZ59: =OFFSET('Proforma L+H'!$E88,0,'L+H Monthly CF'!AZ$3)/12 -> 125000 | BA59: =SUM(E59:AZ59) -> 4125000 | BB59: =SUM('Proforma L+H'!E88:H88)-BA59 -> 0
B60: ='Proforma L+H'!B89 -> Vertical Construction Costs | C60: =Assumptions!#REF! -> #REF! | E60: =OFFSET('Proforma L+H'!$E89,0,'L+H Monthly CF'!E$3)/12 -> 0 | F60: =OFFSET('Proforma L+H'!$E89,0,'L+H Monthly CF'!F$3)/12 -> 0 | G60: =OFFSET('Proforma L+H'!$E89,0,'L+H Monthly CF'!G$3)/12 -> 0 | H60: =OFFSET('Proforma L+H'!$E89,0,'L+H Monthly CF'!H$3)/12 -> 0 | I60: =OFFSET('Proforma L+H'!$E89,0,'L+H Monthly CF'!I$3)/12 -> 0 | J60: =OFFSET('Proforma L+H'!$E89,0,'L+H Monthly CF'!J$3)/12 -> 0 | K60: =OFFSET('Proforma L+H'!$E89,0,'L+H Monthly CF'!K$3)/12 -> 0 | L60: =OFFSET('Proforma L+H'!$E89,0,'L+H Monthly CF'!L$3)/12 -> 0 | ... AZ60: =OFFSET('Proforma L+H'!$E89,0,'L+H Monthly CF'!AZ$3)/12 -> 3807291.7 | BA60: =SUM(E60:AZ60) -> 88187500 | BB60: =SUM('Proforma L+H'!E89:H89)-BA60 -> 0
B61: ='Proforma L+H'!B90 -> Landscape / Hardscape | C61: 150000 | E61: =OFFSET('Proforma L+H'!$E90,0,'L+H Monthly CF'!E$3)/12 -> 0 | F61: =OFFSET('Proforma L+H'!$E90,0,'L+H Monthly CF'!F$3)/12 -> 0 | G61: =OFFSET('Proforma L+H'!$E90,0,'L+H Monthly CF'!G$3)/12 -> 0 | H61: =OFFSET('Proforma L+H'!$E90,0,'L+H Monthly CF'!H$3)/12 -> 0 | I61: =OFFSET('Proforma L+H'!$E90,0,'L+H Monthly CF'!I$3)/12 -> 0 | J61: =OFFSET('Proforma L+H'!$E90,0,'L+H Monthly CF'!J$3)/12 -> 0 | K61: =OFFSET('Proforma L+H'!$E90,0,'L+H Monthly CF'!K$3)/12 -> 0 | L61: =OFFSET('Proforma L+H'!$E90,0,'L+H Monthly CF'!L$3)/12 -> 0 | ... AZ61: =OFFSET('Proforma L+H'!$E90,0,'L+H Monthly CF'!AZ$3)/12 -> 125000 | BA61: =SUM(E61:AZ61) -> 2250000 | BB61: =SUM('Proforma L+H'!E90:H90)-BA61 -> 0
B62: ='Proforma L+H'!B91 -> Construction Management | C62: 0.035 | E62: =OFFSET('Proforma L+H'!$E91,0,'L+H Monthly CF'!E$3)/12 -> 1093.75 | F62: =OFFSET('Proforma L+H'!$E91,0,'L+H Monthly CF'!F$3)/12 -> 1093.75 | G62: =OFFSET('Proforma L+H'!$E91,0,'L+H Monthly CF'!G$3)/12 -> 1093.75 | H62: =OFFSET('Proforma L+H'!$E91,0,'L+H Monthly CF'!H$3)/12 -> 1093.75 | I62: =OFFSET('Proforma L+H'!$E91,0,'L+H Monthly CF'!I$3)/12 -> 1093.75 | J62: =OFFSET('Proforma L+H'!$E91,0,'L+H Monthly CF'!J$3)/12 -> 1093.75 | K62: =OFFSET('Proforma L+H'!$E91,0,'L+H Monthly CF'!K$3)/12 -> 1093.75 | L62: =OFFSET('Proforma L+H'!$E91,0,'L+H Monthly CF'!L$3)/12 -> 1093.75 | ... AZ62: =OFFSET('Proforma L+H'!$E91,0,'L+H Monthly CF'!AZ$3)/12 -> 142005.21 | BA62: =SUM(E62:AZ62) -> 3309687.5 | BB62: =SUM('Proforma L+H'!E91:H91)-BA62 -> 0
B63: ='Proforma L+H'!B92 -> Construction Cost Escalation | C63: 0.05 | E63: =OFFSET('Proforma L+H'!$E92,0,'L+H Monthly CF'!E$3)/12 -> 1562.5 | F63: =OFFSET('Proforma L+H'!$E92,0,'L+H Monthly CF'!F$3)/12 -> 1562.5 | G63: =OFFSET('Proforma L+H'!$E92,0,'L+H Monthly CF'!G$3)/12 -> 1562.5 | H63: =OFFSET('Proforma L+H'!$E92,0,'L+H Monthly CF'!H$3)/12 -> 1562.5 | I63: =OFFSET('Proforma L+H'!$E92,0,'L+H Monthly CF'!I$3)/12 -> 1562.5 | J63: =OFFSET('Proforma L+H'!$E92,0,'L+H Monthly CF'!J$3)/12 -> 1562.5 | K63: =OFFSET('Proforma L+H'!$E92,0,'L+H Monthly CF'!K$3)/12 -> 1562.5 | L63: =OFFSET('Proforma L+H'!$E92,0,'L+H Monthly CF'!L$3)/12 -> 1562.5 | ... AZ63: =OFFSET('Proforma L+H'!$E92,0,'L+H Monthly CF'!AZ$3)/12 -> 212593.95 | BA63: =SUM(E63:AZ63) -> 4886174.2 | BB63: =SUM('Proforma L+H'!E92:H92)-BA63 -> 0
B64: ='Proforma L+H'!B93 -> Developer Construction Contingency | C64: 0.035 | E64: =OFFSET('Proforma L+H'!$E93,0,'L+H Monthly CF'!E$3)/12 -> 1093.75 | F64: =OFFSET('Proforma L+H'!$E93,0,'L+H Monthly CF'!F$3)/12 -> 1093.75 | G64: =OFFSET('Proforma L+H'!$E93,0,'L+H Monthly CF'!G$3)/12 -> 1093.75 | H64: =OFFSET('Proforma L+H'!$E93,0,'L+H Monthly CF'!H$3)/12 -> 1093.75 | I64: =OFFSET('Proforma L+H'!$E93,0,'L+H Monthly CF'!I$3)/12 -> 1093.75 | J64: =OFFSET('Proforma L+H'!$E93,0,'L+H Monthly CF'!J$3)/12 -> 1093.75 | K64: =OFFSET('Proforma L+H'!$E93,0,'L+H Monthly CF'!K$3)/12 -> 1093.75 | L64: =OFFSET('Proforma L+H'!$E93,0,'L+H Monthly CF'!L$3)/12 -> 1093.75 | ... AZ64: =OFFSET('Proforma L+H'!$E93,0,'L+H Monthly CF'!AZ$3)/12 -> 142005.21 | BA64: =SUM(E64:AZ64) -> 3309687.5 | BB64: =SUM('Proforma L+H'!E93:H93)-BA64 -> 0
B65: ='Proforma L+H'!B94 -> HARD COSTS - HOMES | E65: =OFFSET('Proforma L+H'!$E94,0,'L+H Monthly CF'!E$3)/12 -> 35000 | F65: =OFFSET('Proforma L+H'!$E94,0,'L+H Monthly CF'!F$3)/12 -> 35000 | G65: =OFFSET('Proforma L+H'!$E94,0,'L+H Monthly CF'!G$3)/12 -> 35000 | H65: =OFFSET('Proforma L+H'!$E94,0,'L+H Monthly CF'!H$3)/12 -> 35000 | I65: =OFFSET('Proforma L+H'!$E94,0,'L+H Monthly CF'!I$3)/12 -> 35000 | J65: =OFFSET('Proforma L+H'!$E94,0,'L+H Monthly CF'!J$3)/12 -> 35000 | K65: =OFFSET('Proforma L+H'!$E94,0,'L+H Monthly CF'!K$3)/12 -> 35000 | L65: =OFFSET('Proforma L+H'!$E94,0,'L+H Monthly CF'!L$3)/12 -> 35000 | ... AZ65: =OFFSET('Proforma L+H'!$E94,0,'L+H Monthly CF'!AZ$3)/12 -> 4553896 | BA65: =SUM(E65:AZ65) -> 1.0606805e+08 | BB65: =SUM('Proforma L+H'!E94:H94)-BA65 -> 0
B67: ='Proforma L+H'!B96 -> SOFT COSTS PROFESSIONALS - FINAL ENTITLEMENTS & SITE INFRA.
B68: ='Proforma L+H'!B97 -> Land Planning & PUD App Prep/Revisions (15% of Cost) | C68: =(SUM(C53:C53))*0.15 -> 112500 | E68: =OFFSET('Proforma L+H'!$E97,0,'L+H Monthly CF'!E$3)/12 -> 7031.25 | F68: =OFFSET('Proforma L+H'!$E97,0,'L+H Monthly CF'!F$3)/12 -> 7031.25 | G68: =OFFSET('Proforma L+H'!$E97,0,'L+H Monthly CF'!G$3)/12 -> 7031.25 | H68: =OFFSET('Proforma L+H'!$E97,0,'L+H Monthly CF'!H$3)/12 -> 7031.25 | I68: =OFFSET('Proforma L+H'!$E97,0,'L+H Monthly CF'!I$3)/12 -> 7031.25 | J68: =OFFSET('Proforma L+H'!$E97,0,'L+H Monthly CF'!J$3)/12 -> 7031.25 | K68: =OFFSET('Proforma L+H'!$E97,0,'L+H Monthly CF'!K$3)/12 -> 7031.25 | L68: =OFFSET('Proforma L+H'!$E97,0,'L+H Monthly CF'!L$3)/12 -> 7031.25 | ... AZ68: =OFFSET('Proforma L+H'!$E97,0,'L+H Monthly CF'!AZ$3)/12 -> 0 | BA68: =SUM(E68:AZ68) -> 112500 | BB68: =SUM('Proforma L+H'!E97:H97)-BA68 -> 0
B69: ='Proforma L+H'!B98 -> Future Entitlement Management Overhead | C69: 500000 | E69: =OFFSET('Proforma L+H'!$E98,0,'L+H Monthly CF'!E$3)/12 -> 41666.667 | F69: =OFFSET('Proforma L+H'!$E98,0,'L+H Monthly CF'!F$3)/12 -> 41666.667 | G69: =OFFSET('Proforma L+H'!$E98,0,'L+H Monthly CF'!G$3)/12 -> 41666.667 | H69: =OFFSET('Proforma L+H'!$E98,0,'L+H Monthly CF'!H$3)/12 -> 41666.667 | I69: =OFFSET('Proforma L+H'!$E98,0,'L+H Monthly CF'!I$3)/12 -> 41666.667 | J69: =OFFSET('Proforma L+H'!$E98,0,'L+H Monthly CF'!J$3)/12 -> 41666.667 | K69: =OFFSET('Proforma L+H'!$E98,0,'L+H Monthly CF'!K$3)/12 -> 41666.667 | L69: =OFFSET('Proforma L+H'!$E98,0,'L+H Monthly CF'!L$3)/12 -> 41666.667 | ... AZ69: =OFFSET('Proforma L+H'!$E98,0,'L+H Monthly CF'!AZ$3)/12 -> 41666.667 | BA69: =SUM(E69:AZ69) -> 2000000 | BB69: =SUM('Proforma L+H'!E98:H98)-BA69 -> 0
B70: ='Proforma L+H'!B99 -> Civil, Surveying & PUD App Prep/Revisions (10% of Infra Cost) | C70: =(SUM(C39:C52))*0.1 -> 712562.5 | E70: =OFFSET('Proforma L+H'!$E99,0,'L+H Monthly CF'!E$3)/12 -> 32659.115 | F70: =OFFSET('Proforma L+H'!$E99,0,'L+H Monthly CF'!F$3)/12 -> 32659.115 | G70: =OFFSET('Proforma L+H'!$E99,0,'L+H Monthly CF'!G$3)/12 -> 32659.115 | H70: =OFFSET('Proforma L+H'!$E99,0,'L+H Monthly CF'!H$3)/12 -> 32659.115 | I70: =OFFSET('Proforma L+H'!$E99,0,'L+H Monthly CF'!I$3)/12 -> 32659.115 | J70: =OFFSET('Proforma L+H'!$E99,0,'L+H Monthly CF'!J$3)/12 -> 32659.115 | K70: =OFFSET('Proforma L+H'!$E99,0,'L+H Monthly CF'!K$3)/12 -> 32659.115 | L70: =OFFSET('Proforma L+H'!$E99,0,'L+H Monthly CF'!L$3)/12 -> 32659.115 | ... AZ70: =OFFSET('Proforma L+H'!$E99,0,'L+H Monthly CF'!AZ$3)/12 -> 2969.0104 | BA70: =SUM(E70:AZ70) -> 712562.5 | BB70: =SUM('Proforma L+H'!E99:H99)-BA70 -> 0
B71: ='Proforma L+H'!B100 -> Traffic, Enviro, Economist & Misc. Studies | C71: 300000 | E71: =OFFSET('Proforma L+H'!$E100,0,'L+H Monthly CF'!E$3)/12 -> 25000 | F71: =OFFSET('Proforma L+H'!$E100,0,'L+H Monthly CF'!F$3)/12 -> 25000 | G71: =OFFSET('Proforma L+H'!$E100,0,'L+H Monthly CF'!G$3)/12 -> 25000 | H71: =OFFSET('Proforma L+H'!$E100,0,'L+H Monthly CF'!H$3)/12 -> 25000 | I71: =OFFSET('Proforma L+H'!$E100,0,'L+H Monthly CF'!I$3)/12 -> 25000 | J71: =OFFSET('Proforma L+H'!$E100,0,'L+H Monthly CF'!J$3)/12 -> 25000 | K71: =OFFSET('Proforma L+H'!$E100,0,'L+H Monthly CF'!K$3)/12 -> 25000 | L71: =OFFSET('Proforma L+H'!$E100,0,'L+H Monthly CF'!L$3)/12 -> 25000 | ... AZ71: =OFFSET('Proforma L+H'!$E100,0,'L+H Monthly CF'!AZ$3)/12 -> 0 | BA71: =SUM(E71:AZ71) -> 300000 | BB71: =SUM('Proforma L+H'!E100:H100)-BA71 -> 0
B72: ='Proforma L+H'!B101 -> Legal / Entitlement | C72: 400000 | E72: =OFFSET('Proforma L+H'!$E101,0,'L+H Monthly CF'!E$3)/12 -> 25000 | F72: =OFFSET('Proforma L+H'!$E101,0,'L+H Monthly CF'!F$3)/12 -> 25000 | G72: =OFFSET('Proforma L+H'!$E101,0,'L+H Monthly CF'!G$3)/12 -> 25000 | H72: =OFFSET('Proforma L+H'!$E101,0,'L+H Monthly CF'!H$3)/12 -> 25000 | I72: =OFFSET('Proforma L+H'!$E101,0,'L+H Monthly CF'!I$3)/12 -> 25000 | J72: =OFFSET('Proforma L+H'!$E101,0,'L+H Monthly CF'!J$3)/12 -> 25000 | K72: =OFFSET('Proforma L+H'!$E101,0,'L+H Monthly CF'!K$3)/12 -> 25000 | L72: =OFFSET('Proforma L+H'!$E101,0,'L+H Monthly CF'!L$3)/12 -> 25000 | ... AZ72: =OFFSET('Proforma L+H'!$E101,0,'L+H Monthly CF'!AZ$3)/12 -> 0 | BA72: =SUM(E72:AZ72) -> 400000 | BB72: =SUM('Proforma L+H'!E101:H101)-BA72 -> 0
B73: ='Proforma L+H'!B102 -> Accounting & CPA costs ($ per year) | C73: 10000 | E73: =OFFSET('Proforma L+H'!$E102,0,'L+H Monthly CF'!E$3)/12 -> 833.33333 | F73: =OFFSET('Proforma L+H'!$E102,0,'L+H Monthly CF'!F$3)/12 -> 833.33333 | G73: =OFFSET('Proforma L+H'!$E102,0,'L+H Monthly CF'!G$3)/12 -> 833.33333 | H73: =OFFSET('Proforma L+H'!$E102,0,'L+H Monthly CF'!H$3)/12 -> 833.33333 | I73: =OFFSET('Proforma L+H'!$E102,0,'L+H Monthly CF'!I$3)/12 -> 833.33333 | J73: =OFFSET('Proforma L+H'!$E102,0,'L+H Monthly CF'!J$3)/12 -> 833.33333 | K73: =OFFSET('Proforma L+H'!$E102,0,'L+H Monthly CF'!K$3)/12 -> 833.33333 | L73: =OFFSET('Proforma L+H'!$E102,0,'L+H Monthly CF'!L$3)/12 -> 833.33333 | ... AZ73: =OFFSET('Proforma L+H'!$E102,0,'L+H Monthly CF'!AZ$3)/12 -> 833.33333 | BA73: =SUM(E73:AZ73) -> 40000 | BB73: =SUM('Proforma L+H'!E102:H102)-BA73 -> 0
B74: ='Proforma L+H'!B103 -> Professionals Contingency | C74: 0.05 | E74: =OFFSET('Proforma L+H'!$E103,0,'L+H Monthly CF'!E$3)/12 -> 6609.5182 | F74: =OFFSET('Proforma L+H'!$E103,0,'L+H Monthly CF'!F$3)/12 -> 6609.5182 | G74: =OFFSET('Proforma L+H'!$E103,0,'L+H Monthly CF'!G$3)/12 -> 6609.5182 | H74: =OFFSET('Proforma L+H'!$E103,0,'L+H Monthly CF'!H$3)/12 -> 6609.5182 | I74: =OFFSET('Proforma L+H'!$E103,0,'L+H Monthly CF'!I$3)/12 -> 6609.5182 | J74: =OFFSET('Proforma L+H'!$E103,0,'L+H Monthly CF'!J$3)/12 -> 6609.5182 | K74: =OFFSET('Proforma L+H'!$E103,0,'L+H Monthly CF'!K$3)/12 -> 6609.5182 | L74: =OFFSET('Proforma L+H'!$E103,0,'L+H Monthly CF'!L$3)/12 -> 6609.5182 | ... AZ74: =OFFSET('Proforma L+H'!$E103,0,'L+H Monthly CF'!AZ$3)/12 -> 2273.4505 | BA74: =SUM(E74:AZ74) -> 178253.13 | BB74: =SUM('Proforma L+H'!E103:H103)-BA74 -> 0
B75: ='Proforma L+H'!B104 -> SOFT COSTS PROFESSIONALS - FINAL ENTITLEMENTS & SITE INFRA. | E75: =OFFSET('Proforma L+H'!$E104,0,'L+H Monthly CF'!E$3)/12 -> 138799.88 | F75: =OFFSET('Proforma L+H'!$E104,0,'L+H Monthly CF'!F$3)/12 -> 138799.88 | G75: =OFFSET('Proforma L+H'!$E104,0,'L+H Monthly CF'!G$3)/12 -> 138799.88 | H75: =OFFSET('Proforma L+H'!$E104,0,'L+H Monthly CF'!H$3)/12 -> 138799.88 | I75: =OFFSET('Proforma L+H'!$E104,0,'L+H Monthly CF'!I$3)/12 -> 138799.88 | J75: =OFFSET('Proforma L+H'!$E104,0,'L+H Monthly CF'!J$3)/12 -> 138799.88 | K75: =OFFSET('Proforma L+H'!$E104,0,'L+H Monthly CF'!K$3)/12 -> 138799.88 | L75: =OFFSET('Proforma L+H'!$E104,0,'L+H Monthly CF'!L$3)/12 -> 138799.88 | ... AZ75: =OFFSET('Proforma L+H'!$E104,0,'L+H Monthly CF'!AZ$3)/12 -> 47742.461 | BA75: =SUM(E75:AZ75) -> 3743315.6 | BB75: =SUM('Proforma L+H'!E104:H104)-BA75 -> 0
B77: ='Proforma L+H'!B106 -> SOFT COSTS PROFESSIONALS - HOMES
B78: ='Proforma L+H'!B107 -> Planning & Arch Concepts (4 prototype designs, amenities, etc.) | C78: 500000 | E78: =OFFSET('Proforma L+H'!$E107,0,'L+H Monthly CF'!E$3)/12 -> 41666.667 | F78: =OFFSET('Proforma L+H'!$E107,0,'L+H Monthly CF'!F$3)/12 -> 41666.667 | G78: =OFFSET('Proforma L+H'!$E107,0,'L+H Monthly CF'!G$3)/12 -> 41666.667 | H78: =OFFSET('Proforma L+H'!$E107,0,'L+H Monthly CF'!H$3)/12 -> 41666.667 | I78: =OFFSET('Proforma L+H'!$E107,0,'L+H Monthly CF'!I$3)/12 -> 41666.667 | J78: =OFFSET('Proforma L+H'!$E107,0,'L+H Monthly CF'!J$3)/12 -> 41666.667 | K78: =OFFSET('Proforma L+H'!$E107,0,'L+H Monthly CF'!K$3)/12 -> 41666.667 | L78: =OFFSET('Proforma L+H'!$E107,0,'L+H Monthly CF'!L$3)/12 -> 41666.667 | ... AZ78: =OFFSET('Proforma L+H'!$E107,0,'L+H Monthly CF'!AZ$3)/12 -> 0 | BA78: =SUM(E78:AZ78) -> 500000 | BB78: =SUM('Proforma L+H'!E107:H107)-BA78 -> 0
B79: ='Proforma L+H'!B108 -> Civil Engineering (Unit Infra. & Geotech) | C79: 0.05 | E79: =OFFSET('Proforma L+H'!$E108,0,'L+H Monthly CF'!E$3)/12 -> 1562.5 | F79: =OFFSET('Proforma L+H'!$E108,0,'L+H Monthly CF'!F$3)/12 -> 1562.5 | G79: =OFFSET('Proforma L+H'!$E108,0,'L+H Monthly CF'!G$3)/12 -> 1562.5 | H79: =OFFSET('Proforma L+H'!$E108,0,'L+H Monthly CF'!H$3)/12 -> 1562.5 | I79: =OFFSET('Proforma L+H'!$E108,0,'L+H Monthly CF'!I$3)/12 -> 1562.5 | J79: =OFFSET('Proforma L+H'!$E108,0,'L+H Monthly CF'!J$3)/12 -> 1562.5 | K79: =OFFSET('Proforma L+H'!$E108,0,'L+H Monthly CF'!K$3)/12 -> 1562.5 | L79: =OFFSET('Proforma L+H'!$E108,0,'L+H Monthly CF'!L$3)/12 -> 1562.5 | ... AZ79: =OFFSET('Proforma L+H'!$E108,0,'L+H Monthly CF'!AZ$3)/12 -> 6250 | BA79: =SUM(E79:AZ79) -> 206250 | BB79: =SUM('Proforma L+H'!E108:H108)-BA79 -> 0
B80: ='Proforma L+H'!B109 -> Architectural Design & CDs | C80: 0.02 | E80: =OFFSET('Proforma L+H'!$E109,0,'L+H Monthly CF'!E$3)/12 -> 0 | F80: =OFFSET('Proforma L+H'!$E109,0,'L+H Monthly CF'!F$3)/12 -> 0 | G80: =OFFSET('Proforma L+H'!$E109,0,'L+H Monthly CF'!G$3)/12 -> 0 | H80: =OFFSET('Proforma L+H'!$E109,0,'L+H Monthly CF'!H$3)/12 -> 0 | I80: =OFFSET('Proforma L+H'!$E109,0,'L+H Monthly CF'!I$3)/12 -> 0 | J80: =OFFSET('Proforma L+H'!$E109,0,'L+H Monthly CF'!J$3)/12 -> 0 | K80: =OFFSET('Proforma L+H'!$E109,0,'L+H Monthly CF'!K$3)/12 -> 0 | L80: =OFFSET('Proforma L+H'!$E109,0,'L+H Monthly CF'!L$3)/12 -> 0 | ... AZ80: =OFFSET('Proforma L+H'!$E109,0,'L+H Monthly CF'!AZ$3)/12 -> 76145.833 | BA80: =SUM(E80:AZ80) -> 1763750 | BB80: =SUM('Proforma L+H'!E109:H109)-BA80 -> 0
B81: ='Proforma L+H'!B110 -> Architectural C/A | C81: 10000 | E81: =OFFSET('Proforma L+H'!$E110,0,'L+H Monthly CF'!E$3)/12 -> 0 | F81: =OFFSET('Proforma L+H'!$E110,0,'L+H Monthly CF'!F$3)/12 -> 0 | G81: =OFFSET('Proforma L+H'!$E110,0,'L+H Monthly CF'!G$3)/12 -> 0 | H81: =OFFSET('Proforma L+H'!$E110,0,'L+H Monthly CF'!H$3)/12 -> 0 | I81: =OFFSET('Proforma L+H'!$E110,0,'L+H Monthly CF'!I$3)/12 -> 0 | J81: =OFFSET('Proforma L+H'!$E110,0,'L+H Monthly CF'!J$3)/12 -> 0 | K81: =OFFSET('Proforma L+H'!$E110,0,'L+H Monthly CF'!K$3)/12 -> 0 | L81: =OFFSET('Proforma L+H'!$E110,0,'L+H Monthly CF'!L$3)/12 -> 0 | ... AZ81: =OFFSET('Proforma L+H'!$E110,0,'L+H Monthly CF'!AZ$3)/12 -> 12500 | BA81: =SUM(E81:AZ81) -> 300000 | BB81: =SUM('Proforma L+H'!E110:H110)-BA81 -> 0
B82: ='Proforma L+H'!B111 -> Landscape Architecture Design & CDs | C82: 0.05 | E82: =OFFSET('Proforma L+H'!$E111,0,'L+H Monthly CF'!E$3)/12 -> 0 | F82: =OFFSET('Proforma L+H'!$E111,0,'L+H Monthly CF'!F$3)/12 -> 0 | G82: =OFFSET('Proforma L+H'!$E111,0,'L+H Monthly CF'!G$3)/12 -> 0 | H82: =OFFSET('Proforma L+H'!$E111,0,'L+H Monthly CF'!H$3)/12 -> 0 | I82: =OFFSET('Proforma L+H'!$E111,0,'L+H Monthly CF'!I$3)/12 -> 0 | J82: =OFFSET('Proforma L+H'!$E111,0,'L+H Monthly CF'!J$3)/12 -> 0 | K82: =OFFSET('Proforma L+H'!$E111,0,'L+H Monthly CF'!K$3)/12 -> 0 | L82: =OFFSET('Proforma L+H'!$E111,0,'L+H Monthly CF'!L$3)/12 -> 0 | ... AZ82: =OFFSET('Proforma L+H'!$E111,0,'L+H Monthly CF'!AZ$3)/12 -> 9375 | BA82: =SUM(E82:AZ82) -> 225000 | BB82: =SUM('Proforma L+H'!E111:H111)-BA82 -> 0
B83: ='Proforma L+H'!B112 -> Landscape Arch. C/A | C83: 3500 | E83: =OFFSET('Proforma L+H'!$E112,0,'L+H Monthly CF'!E$3)/12 -> 0 | F83: =OFFSET('Proforma L+H'!$E112,0,'L+H Monthly CF'!F$3)/12 -> 0 | G83: =OFFSET('Proforma L+H'!$E112,0,'L+H Monthly CF'!G$3)/12 -> 0 | H83: =OFFSET('Proforma L+H'!$E112,0,'L+H Monthly CF'!H$3)/12 -> 0 | I83: =OFFSET('Proforma L+H'!$E112,0,'L+H Monthly CF'!I$3)/12 -> 0 | J83: =OFFSET('Proforma L+H'!$E112,0,'L+H Monthly CF'!J$3)/12 -> 0 | K83: =OFFSET('Proforma L+H'!$E112,0,'L+H Monthly CF'!K$3)/12 -> 0 | L83: =OFFSET('Proforma L+H'!$E112,0,'L+H Monthly CF'!L$3)/12 -> 0 | ... AZ83: =OFFSET('Proforma L+H'!$E112,0,'L+H Monthly CF'!AZ$3)/12 -> 4375 | BA83: =SUM(E83:AZ83) -> 105000 | BB83: =SUM('Proforma L+H'!E112:H112)-BA83 -> 0
B84: ='Proforma L+H'!B113 -> Structural Engineering | C84: 2.25 | E84: =OFFSET('Proforma L+H'!$E113,0,'L+H Monthly CF'!E$3)/12 -> 0 | F84: =OFFSET('Proforma L+H'!$E113,0,'L+H Monthly CF'!F$3)/12 -> 0 | G84: =OFFSET('Proforma L+H'!$E113,0,'L+H Monthly CF'!G$3)/12 -> 0 | H84: =OFFSET('Proforma L+H'!$E113,0,'L+H Monthly CF'!H$3)/12 -> 0 | I84: =OFFSET('Proforma L+H'!$E113,0,'L+H Monthly CF'!I$3)/12 -> 0 | J84: =OFFSET('Proforma L+H'!$E113,0,'L+H Monthly CF'!J$3)/12 -> 0 | K84: =OFFSET('Proforma L+H'!$E113,0,'L+H Monthly CF'!K$3)/12 -> 0 | L84: =OFFSET('Proforma L+H'!$E113,0,'L+H Monthly CF'!L$3)/12 -> 0 | ... AZ84: =OFFSET('Proforma L+H'!$E113,0,'L+H Monthly CF'!AZ$3)/12 -> 10078.125 | BA84: =SUM(E84:AZ84) -> 233437.5 | BB84: =SUM('Proforma L+H'!E113:H113)-BA84 -> 0
B85: ='Proforma L+H'!B114 -> Interior Design | C85: 0.0035 | E85: =OFFSET('Proforma L+H'!$E114,0,'L+H Monthly CF'!E$3)/12 -> 0 | F85: =OFFSET('Proforma L+H'!$E114,0,'L+H Monthly CF'!F$3)/12 -> 0 | G85: =OFFSET('Proforma L+H'!$E114,0,'L+H Monthly CF'!G$3)/12 -> 0 | H85: =OFFSET('Proforma L+H'!$E114,0,'L+H Monthly CF'!H$3)/12 -> 0 | I85: =OFFSET('Proforma L+H'!$E114,0,'L+H Monthly CF'!I$3)/12 -> 0 | J85: =OFFSET('Proforma L+H'!$E114,0,'L+H Monthly CF'!J$3)/12 -> 0 | K85: =OFFSET('Proforma L+H'!$E114,0,'L+H Monthly CF'!K$3)/12 -> 0 | L85: =OFFSET('Proforma L+H'!$E114,0,'L+H Monthly CF'!L$3)/12 -> 0 | ... AZ85: =OFFSET('Proforma L+H'!$E114,0,'L+H Monthly CF'!AZ$3)/12 -> 13325.521 | BA85: =SUM(E85:AZ85) -> 308656.25 | BB85: =SUM('Proforma L+H'!E114:H114)-BA85 -> 0
B86: ='Proforma L+H'!B115 -> Preconstruction Estimating | C86: 0.0025 | E86: =OFFSET('Proforma L+H'!$E115,0,'L+H Monthly CF'!E$3)/12 -> 0 | F86: =OFFSET('Proforma L+H'!$E115,0,'L+H Monthly CF'!F$3)/12 -> 0 | G86: =OFFSET('Proforma L+H'!$E115,0,'L+H Monthly CF'!G$3)/12 -> 0 | H86: =OFFSET('Proforma L+H'!$E115,0,'L+H Monthly CF'!H$3)/12 -> 0 | I86: =OFFSET('Proforma L+H'!$E115,0,'L+H Monthly CF'!I$3)/12 -> 0 | J86: =OFFSET('Proforma L+H'!$E115,0,'L+H Monthly CF'!J$3)/12 -> 0 | K86: =OFFSET('Proforma L+H'!$E115,0,'L+H Monthly CF'!K$3)/12 -> 0 | L86: =OFFSET('Proforma L+H'!$E115,0,'L+H Monthly CF'!L$3)/12 -> 0 | ... AZ86: =OFFSET('Proforma L+H'!$E115,0,'L+H Monthly CF'!AZ$3)/12 -> 9518.2292 | BA86: =SUM(E86:AZ86) -> 220468.75 | BB86: =SUM('Proforma L+H'!E115:H115)-BA86 -> 0
B87: ='Proforma L+H'!B116 -> BIM / VDC | C87: 0.0025 | E87: =OFFSET('Proforma L+H'!$E116,0,'L+H Monthly CF'!E$3)/12 -> 0 | F87: =OFFSET('Proforma L+H'!$E116,0,'L+H Monthly CF'!F$3)/12 -> 0 | G87: =OFFSET('Proforma L+H'!$E116,0,'L+H Monthly CF'!G$3)/12 -> 0 | H87: =OFFSET('Proforma L+H'!$E116,0,'L+H Monthly CF'!H$3)/12 -> 0 | I87: =OFFSET('Proforma L+H'!$E116,0,'L+H Monthly CF'!I$3)/12 -> 0 | J87: =OFFSET('Proforma L+H'!$E116,0,'L+H Monthly CF'!J$3)/12 -> 0 | K87: =OFFSET('Proforma L+H'!$E116,0,'L+H Monthly CF'!K$3)/12 -> 0 | L87: =OFFSET('Proforma L+H'!$E116,0,'L+H Monthly CF'!L$3)/12 -> 0 | ... AZ87: =OFFSET('Proforma L+H'!$E116,0,'L+H Monthly CF'!AZ$3)/12 -> 9518.2292 | BA87: =SUM(E87:AZ87) -> 220468.75 | BB87: =SUM('Proforma L+H'!E116:H116)-BA87 -> 0
B88: ='Proforma L+H'!B117 -> Professionals Contingency | C88: 0.05 | E88: =OFFSET('Proforma L+H'!$E117,0,'L+H Monthly CF'!E$3)/12 -> 78.125 | F88: =OFFSET('Proforma L+H'!$E117,0,'L+H Monthly CF'!F$3)/12 -> 78.125 | G88: =OFFSET('Proforma L+H'!$E117,0,'L+H Monthly CF'!G$3)/12 -> 78.125 | H88: =OFFSET('Proforma L+H'!$E117,0,'L+H Monthly CF'!H$3)/12 -> 78.125 | I88: =OFFSET('Proforma L+H'!$E117,0,'L+H Monthly CF'!I$3)/12 -> 78.125 | J88: =OFFSET('Proforma L+H'!$E117,0,'L+H Monthly CF'!J$3)/12 -> 78.125 | K88: =OFFSET('Proforma L+H'!$E117,0,'L+H Monthly CF'!K$3)/12 -> 78.125 | L88: =OFFSET('Proforma L+H'!$E117,0,'L+H Monthly CF'!L$3)/12 -> 78.125 | ... AZ88: =OFFSET('Proforma L+H'!$E117,0,'L+H Monthly CF'!AZ$3)/12 -> 7554.2969 | BA88: =SUM(E88:AZ88) -> 179151.56 | BB88: =SUM('Proforma L+H'!E117:H117)-BA88 -> 0
B89: ='Proforma L+H'!B118 -> SOFT COSTS PROFESSIONALS - HOMES | E89: =OFFSET('Proforma L+H'!$E118,0,'L+H Monthly CF'!E$3)/12 -> 43307.292 | F89: =OFFSET('Proforma L+H'!$E118,0,'L+H Monthly CF'!F$3)/12 -> 43307.292 | G89: =OFFSET('Proforma L+H'!$E118,0,'L+H Monthly CF'!G$3)/12 -> 43307.292 | H89: =OFFSET('Proforma L+H'!$E118,0,'L+H Monthly CF'!H$3)/12 -> 43307.292 | I89: =OFFSET('Proforma L+H'!$E118,0,'L+H Monthly CF'!I$3)/12 -> 43307.292 | J89: =OFFSET('Proforma L+H'!$E118,0,'L+H Monthly CF'!J$3)/12 -> 43307.292 | K89: =OFFSET('Proforma L+H'!$E118,0,'L+H Monthly CF'!K$3)/12 -> 43307.292 | L89: =OFFSET('Proforma L+H'!$E118,0,'L+H Monthly CF'!L$3)/12 -> 43307.292 | ... AZ89: =OFFSET('Proforma L+H'!$E118,0,'L+H Monthly CF'!AZ$3)/12 -> 158640.23 | BA89: =SUM(E89:AZ89) -> 4262182.8 | BB89: =SUM('Proforma L+H'!E118:H118)-BA89 -> 0
B91: ='Proforma L+H'!B120 -> SOFT COSTS - SALES
B92: ='Proforma L+H'!B121 -> Cost of Sale - RE Fees | C92: 0.05 | E92: =OFFSET('Proforma L+H'!$E121,0,'L+H Monthly CF'!E$3)/12 -> 0 | F92: =OFFSET('Proforma L+H'!$E121,0,'L+H Monthly CF'!F$3)/12 -> 0 | G92: =OFFSET('Proforma L+H'!$E121,0,'L+H Monthly CF'!G$3)/12 -> 0 | H92: =OFFSET('Proforma L+H'!$E121,0,'L+H Monthly CF'!H$3)/12 -> 0 | I92: =OFFSET('Proforma L+H'!$E121,0,'L+H Monthly CF'!I$3)/12 -> 0 | J92: =OFFSET('Proforma L+H'!$E121,0,'L+H Monthly CF'!J$3)/12 -> 0 | K92: =OFFSET('Proforma L+H'!$E121,0,'L+H Monthly CF'!K$3)/12 -> 0 | L92: =OFFSET('Proforma L+H'!$E121,0,'L+H Monthly CF'!L$3)/12 -> 0 | ... AZ92: =OFFSET('Proforma L+H'!$E121,0,'L+H Monthly CF'!AZ$3)/12 -> 282007.27 | BA92: =SUM(E92:AZ92) -> 5367740.6 | BB92: =SUM('Proforma L+H'!E121:H121)-BA92 -> 0
B93: ='Proforma L+H'!B122 -> Hard Marketing Costs | C93: 75000 | E93: =OFFSET('Proforma L+H'!$E122,0,'L+H Monthly CF'!E$3)/12 -> 12500 | F93: =OFFSET('Proforma L+H'!$E122,0,'L+H Monthly CF'!F$3)/12 -> 12500 | G93: =OFFSET('Proforma L+H'!$E122,0,'L+H Monthly CF'!G$3)/12 -> 12500 | H93: =OFFSET('Proforma L+H'!$E122,0,'L+H Monthly CF'!H$3)/12 -> 12500 | I93: =OFFSET('Proforma L+H'!$E122,0,'L+H Monthly CF'!I$3)/12 -> 12500 | J93: =OFFSET('Proforma L+H'!$E122,0,'L+H Monthly CF'!J$3)/12 -> 12500 | K93: =OFFSET('Proforma L+H'!$E122,0,'L+H Monthly CF'!K$3)/12 -> 12500 | L93: =OFFSET('Proforma L+H'!$E122,0,'L+H Monthly CF'!L$3)/12 -> 12500 | ... AZ93: =OFFSET('Proforma L+H'!$E122,0,'L+H Monthly CF'!AZ$3)/12 -> 6250 | BA93: =SUM(E93:AZ93) -> 600000 | BB93: =SUM('Proforma L+H'!E122:H122)-BA93 -> 0
B94: ='Proforma L+H'!B123 -> Model Home Furnishings (Sell Furnished) | E94: =OFFSET('Proforma L+H'!$E123,0,'L+H Monthly CF'!E$3)/12 -> 0 | F94: =OFFSET('Proforma L+H'!$E123,0,'L+H Monthly CF'!F$3)/12 -> 0 | G94: =OFFSET('Proforma L+H'!$E123,0,'L+H Monthly CF'!G$3)/12 -> 0 | H94: =OFFSET('Proforma L+H'!$E123,0,'L+H Monthly CF'!H$3)/12 -> 0 | I94: =OFFSET('Proforma L+H'!$E123,0,'L+H Monthly CF'!I$3)/12 -> 0 | J94: =OFFSET('Proforma L+H'!$E123,0,'L+H Monthly CF'!J$3)/12 -> 0 | K94: =OFFSET('Proforma L+H'!$E123,0,'L+H Monthly CF'!K$3)/12 -> 0 | L94: =OFFSET('Proforma L+H'!$E123,0,'L+H Monthly CF'!L$3)/12 -> 0 | ... AZ94: =OFFSET('Proforma L+H'!$E123,0,'L+H Monthly CF'!AZ$3)/12 -> 0 | BA94: =SUM(E94:AZ94) -> 0 | BB94: =SUM('Proforma L+H'!E123:H123)-BA94 -> 0
B95: ='Proforma L+H'!B124 -> SOFT COSTS - SALES | E95: =OFFSET('Proforma L+H'!$E124,0,'L+H Monthly CF'!E$3)/12 -> 12500 | F95: =OFFSET('Proforma L+H'!$E124,0,'L+H Monthly CF'!F$3)/12 -> 12500 | G95: =OFFSET('Proforma L+H'!$E124,0,'L+H Monthly CF'!G$3)/12 -> 12500 | H95: =OFFSET('Proforma L+H'!$E124,0,'L+H Monthly CF'!H$3)/12 -> 12500 | I95: =OFFSET('Proforma L+H'!$E124,0,'L+H Monthly CF'!I$3)/12 -> 12500 | J95: =OFFSET('Proforma L+H'!$E124,0,'L+H Monthly CF'!J$3)/12 -> 12500 | K95: =OFFSET('Proforma L+H'!$E124,0,'L+H Monthly CF'!K$3)/12 -> 12500 | L95: =OFFSET('Proforma L+H'!$E124,0,'L+H Monthly CF'!L$3)/12 -> 12500 | ... AZ95: =OFFSET('Proforma L+H'!$E124,0,'L+H Monthly CF'!AZ$3)/12 -> 288257.27 | BA95: =SUM(E95:AZ95) -> 5967740.6 | BB95: =SUM('Proforma L+H'!E124:H124)-BA95 -> 0
B97: ='Proforma L+H'!B126 -> SOFT COSTS - TAXES AND INSURANCE
B98: ='Proforma L+H'!B127 -> Real Estate Taxes (Annual) | C98: =Assumptions!#REF! -> #REF! | E98: =OFFSET('Proforma L+H'!$E127,0,'L+H Monthly CF'!E$3)/12 -> 961.53846 | F98: =OFFSET('Proforma L+H'!$E127,0,'L+H Monthly CF'!F$3)/12 -> 961.53846 | G98: =OFFSET('Proforma L+H'!$E127,0,'L+H Monthly CF'!G$3)/12 -> 961.53846 | H98: =OFFSET('Proforma L+H'!$E127,0,'L+H Monthly CF'!H$3)/12 -> 961.53846 | I98: =OFFSET('Proforma L+H'!$E127,0,'L+H Monthly CF'!I$3)/12 -> 961.53846 | J98: =OFFSET('Proforma L+H'!$E127,0,'L+H Monthly CF'!J$3)/12 -> 961.53846 | K98: =OFFSET('Proforma L+H'!$E127,0,'L+H Monthly CF'!K$3)/12 -> 961.53846 | L98: =OFFSET('Proforma L+H'!$E127,0,'L+H Monthly CF'!L$3)/12 -> 961.53846 | ... AZ98: =OFFSET('Proforma L+H'!$E127,0,'L+H Monthly CF'!AZ$3)/12 -> 641.02564 | BA98: =SUM(E98:AZ98) -> 41025.641 | BB98: =SUM('Proforma L+H'!E127:H127)-BA98 -> 0
B99: ='Proforma L+H'!B128 -> Liability Insurance (Annual) | C99: 0.0055 | E99: =OFFSET('Proforma L+H'!$E128,0,'L+H Monthly CF'!E$3)/12 -> 1364.4249 | F99: =OFFSET('Proforma L+H'!$E128,0,'L+H Monthly CF'!F$3)/12 -> 1364.4249 | G99: =OFFSET('Proforma L+H'!$E128,0,'L+H Monthly CF'!G$3)/12 -> 1364.4249 | H99: =OFFSET('Proforma L+H'!$E128,0,'L+H Monthly CF'!H$3)/12 -> 1364.4249 | I99: =OFFSET('Proforma L+H'!$E128,0,'L+H Monthly CF'!I$3)/12 -> 1364.4249 | J99: =OFFSET('Proforma L+H'!$E128,0,'L+H Monthly CF'!J$3)/12 -> 1364.4249 | K99: =OFFSET('Proforma L+H'!$E128,0,'L+H Monthly CF'!K$3)/12 -> 1364.4249 | L99: =OFFSET('Proforma L+H'!$E128,0,'L+H Monthly CF'!L$3)/12 -> 1364.4249 | ... AZ99: =OFFSET('Proforma L+H'!$E128,0,'L+H Monthly CF'!AZ$3)/12 -> 25755.743 | BA99: =SUM(E99:AZ99) -> 631214.3 | BB99: =SUM('Proforma L+H'!E128:H128)-BA99 -> 0
B100: ='Proforma L+H'!B129 -> SOFT COSTS - TAXES AND INSURANCE | E100: =OFFSET('Proforma L+H'!$E129,0,'L+H Monthly CF'!E$3)/12 -> 2325.9634 | F100: =OFFSET('Proforma L+H'!$E129,0,'L+H Monthly CF'!F$3)/12 -> 2325.9634 | G100: =OFFSET('Proforma L+H'!$E129,0,'L+H Monthly CF'!G$3)/12 -> 2325.9634 | H100: =OFFSET('Proforma L+H'!$E129,0,'L+H Monthly CF'!H$3)/12 -> 2325.9634 | I100: =OFFSET('Proforma L+H'!$E129,0,'L+H Monthly CF'!I$3)/12 -> 2325.9634 | J100: =OFFSET('Proforma L+H'!$E129,0,'L+H Monthly CF'!J$3)/12 -> 2325.9634 | K100: =OFFSET('Proforma L+H'!$E129,0,'L+H Monthly CF'!K$3)/12 -> 2325.9634 | L100: =OFFSET('Proforma L+H'!$E129,0,'L+H Monthly CF'!L$3)/12 -> 2325.9634 | ... AZ100: =OFFSET('Proforma L+H'!$E129,0,'L+H Monthly CF'!AZ$3)/12 -> 26396.768 | BA100: =SUM(E100:AZ100) -> 672239.94 | BB100: =SUM('Proforma L+H'!E129:H129)-BA100 -> 0
B102: ='Proforma L+H'!B131 -> SOFT COSTS - MUNICIPALITY FEES
B103: ='Proforma L+H'!B132 -> County Permit Fees - Site | C103: =(((10*250)+(30*175))*1.4)+5000 -> 15850 | E103: =OFFSET('Proforma L+H'!$E132,0,'L+H Monthly CF'!E$3)/12 -> 1320.8333 | F103: =OFFSET('Proforma L+H'!$E132,0,'L+H Monthly CF'!F$3)/12 -> 1320.8333 | G103: =OFFSET('Proforma L+H'!$E132,0,'L+H Monthly CF'!G$3)/12 -> 1320.8333 | H103: =OFFSET('Proforma L+H'!$E132,0,'L+H Monthly CF'!H$3)/12 -> 1320.8333 | I103: =OFFSET('Proforma L+H'!$E132,0,'L+H Monthly CF'!I$3)/12 -> 1320.8333 | J103: =OFFSET('Proforma L+H'!$E132,0,'L+H Monthly CF'!J$3)/12 -> 1320.8333 | K103: =OFFSET('Proforma L+H'!$E132,0,'L+H Monthly CF'!K$3)/12 -> 1320.8333 | L103: =OFFSET('Proforma L+H'!$E132,0,'L+H Monthly CF'!L$3)/12 -> 1320.8333 | ... AZ103: =OFFSET('Proforma L+H'!$E132,0,'L+H Monthly CF'!AZ$3)/12 -> 0 | BA103: =SUM(E103:AZ103) -> 15850 | BB103: =SUM('Proforma L+H'!E132:H132)-BA103 -> 0
B104: ='Proforma L+H'!B133 -> County Permit Fees - Build | C104: =0.015*T60 -> 18593.75 | E104: =OFFSET('Proforma L+H'!$E133,0,'L+H Monthly CF'!E$3)/12 -> 0 | F104: =OFFSET('Proforma L+H'!$E133,0,'L+H Monthly CF'!F$3)/12 -> 0 | G104: =OFFSET('Proforma L+H'!$E133,0,'L+H Monthly CF'!G$3)/12 -> 0 | H104: =OFFSET('Proforma L+H'!$E133,0,'L+H Monthly CF'!H$3)/12 -> 0 | I104: =OFFSET('Proforma L+H'!$E133,0,'L+H Monthly CF'!I$3)/12 -> 0 | J104: =OFFSET('Proforma L+H'!$E133,0,'L+H Monthly CF'!J$3)/12 -> 0 | K104: =OFFSET('Proforma L+H'!$E133,0,'L+H Monthly CF'!K$3)/12 -> 0 | L104: =OFFSET('Proforma L+H'!$E133,0,'L+H Monthly CF'!L$3)/12 -> 0 | ... AZ104: =OFFSET('Proforma L+H'!$E133,0,'L+H Monthly CF'!AZ$3)/12 -> 56223.958 | BA104: =SUM(E104:AZ104) -> 1349375 | BB104: =SUM('Proforma L+H'!E133:H133)-BA104 -> 0
B105: ='Proforma L+H'!B134 -> Replacement Bond Cost | C105: 25000 | E105: =OFFSET('Proforma L+H'!$E134,0,'L+H Monthly CF'!E$3)/12 -> 2083.3333 | F105: =OFFSET('Proforma L+H'!$E134,0,'L+H Monthly CF'!F$3)/12 -> 2083.3333 | G105: =OFFSET('Proforma L+H'!$E134,0,'L+H Monthly CF'!G$3)/12 -> 2083.3333 | H105: =OFFSET('Proforma L+H'!$E134,0,'L+H Monthly CF'!H$3)/12 -> 2083.3333 | I105: =OFFSET('Proforma L+H'!$E134,0,'L+H Monthly CF'!I$3)/12 -> 2083.3333 | J105: =OFFSET('Proforma L+H'!$E134,0,'L+H Monthly CF'!J$3)/12 -> 2083.3333 | K105: =OFFSET('Proforma L+H'!$E134,0,'L+H Monthly CF'!K$3)/12 -> 2083.3333 | L105: =OFFSET('Proforma L+H'!$E134,0,'L+H Monthly CF'!L$3)/12 -> 2083.3333 | ... AZ105: =OFFSET('Proforma L+H'!$E134,0,'L+H Monthly CF'!AZ$3)/12 -> 0 | BA105: =SUM(E105:AZ105) -> 25000 | BB105: =SUM('Proforma L+H'!E134:H134)-BA105 -> 0
B106: ='Proforma L+H'!B135 -> SOFT COSTS - MUNICIPALITY FEES | E106: =OFFSET('Proforma L+H'!$E135,0,'L+H Monthly CF'!E$3)/12 -> 3404.1667 | F106: =OFFSET('Proforma L+H'!$E135,0,'L+H Monthly CF'!F$3)/12 -> 3404.1667 | G106: =OFFSET('Proforma L+H'!$E135,0,'L+H Monthly CF'!G$3)/12 -> 3404.1667 | H106: =OFFSET('Proforma L+H'!$E135,0,'L+H Monthly CF'!H$3)/12 -> 3404.1667 | I106: =OFFSET('Proforma L+H'!$E135,0,'L+H Monthly CF'!I$3)/12 -> 3404.1667 | J106: =OFFSET('Proforma L+H'!$E135,0,'L+H Monthly CF'!J$3)/12 -> 3404.1667 | K106: =OFFSET('Proforma L+H'!$E135,0,'L+H Monthly CF'!K$3)/12 -> 3404.1667 | L106: =OFFSET('Proforma L+H'!$E135,0,'L+H Monthly CF'!L$3)/12 -> 3404.1667 | ... AZ106: =OFFSET('Proforma L+H'!$E135,0,'L+H Monthly CF'!AZ$3)/12 -> 56223.958 | BA106: =SUM(E106:AZ106) -> 1390225 | BB106: =SUM('Proforma L+H'!E135:H135)-BA106 -> 0
B108: ='Proforma L+H'!B137 -> DEVELOPMENT FEES
B109: ='Proforma L+H'!B138 -> Developer Overhead | C109: =V109 -> 125000 | E109: =OFFSET('Proforma L+H'!$E138,0,'L+H Monthly CF'!E$3)/12 -> 125000 | F109: =OFFSET('Proforma L+H'!$E138,0,'L+H Monthly CF'!F$3)/12 -> 125000 | G109: =OFFSET('Proforma L+H'!$E138,0,'L+H Monthly CF'!G$3)/12 -> 125000 | H109: =OFFSET('Proforma L+H'!$E138,0,'L+H Monthly CF'!H$3)/12 -> 125000 | I109: =OFFSET('Proforma L+H'!$E138,0,'L+H Monthly CF'!I$3)/12 -> 125000 | J109: =OFFSET('Proforma L+H'!$E138,0,'L+H Monthly CF'!J$3)/12 -> 125000 | K109: =OFFSET('Proforma L+H'!$E138,0,'L+H Monthly CF'!K$3)/12 -> 125000 | L109: =OFFSET('Proforma L+H'!$E138,0,'L+H Monthly CF'!L$3)/12 -> 125000 | ... AZ109: =OFFSET('Proforma L+H'!$E138,0,'L+H Monthly CF'!AZ$3)/12 -> 125000 | BA109: =SUM(E109:AZ109) -> 6000000 | BB109: =SUM('Proforma L+H'!E138:H138)-BA109 -> 0
BB110: =SUM('Proforma L+H'!E139:H139)-BA110 -> 0
B111: ='Proforma L+H'!B140 -> Asset Management Fees | C111: 0 | BB111: =SUM('Proforma L+H'!E140:H140)-BA111 -> 0
B112: ='Proforma L+H'!B141 -> DEVELOPMENT FEES | E112: =OFFSET('Proforma L+H'!$E141,0,'L+H Monthly CF'!E$3)/12 -> 125000 | F112: =OFFSET('Proforma L+H'!$E141,0,'L+H Monthly CF'!F$3)/12 -> 125000 | G112: =OFFSET('Proforma L+H'!$E141,0,'L+H Monthly CF'!G$3)/12 -> 125000 | H112: =OFFSET('Proforma L+H'!$E141,0,'L+H Monthly CF'!H$3)/12 -> 125000 | I112: =OFFSET('Proforma L+H'!$E141,0,'L+H Monthly CF'!I$3)/12 -> 125000 | J112: =OFFSET('Proforma L+H'!$E141,0,'L+H Monthly CF'!J$3)/12 -> 125000 | K112: =OFFSET('Proforma L+H'!$E141,0,'L+H Monthly CF'!K$3)/12 -> 125000 | L112: =OFFSET('Proforma L+H'!$E141,0,'L+H Monthly CF'!L$3)/12 -> 125000 | ... AZ112: =OFFSET('Proforma L+H'!$E141,0,'L+H Monthly CF'!AZ$3)/12 -> 125000 | BA112: =SUM(E112:AZ112) -> 6000000 | BB112: =SUM('Proforma L+H'!E141:H141)-BA112 -> 0
BB113: =SUM('Proforma L+H'!E142:H142)-BA113 -> 0
B114: ='Proforma L+H'!B143 -> TOTAL DEVELOPMENT COSTS | E114: =E36+E56+E65+E75+E89+E95+E100+E106+E112 -> 19551165 | F114: =F36+F56+F65+F75+F89+F95+F100+F106+F112 -> 573414.56 | G114: =G36+G56+G65+G75+G89+G95+G100+G106+G112 -> 573414.56 | H114: =H36+H56+H65+H75+H89+H95+H100+H106+H112 -> 573414.56 | I114: =I36+I56+I65+I75+I89+I95+I100+I106+I112 -> 573414.56 | J114: =J36+J56+J65+J75+J89+J95+J100+J106+J112 -> 573414.56 | K114: =K36+K56+K65+K75+K89+K95+K100+K106+K112 -> 573414.56 | L114: =L36+L56+L65+L75+L89+L95+L100+L106+L112 -> 573414.56 | ... P114: =P36+P56+P65+P75+P89+P95+P100+P106+P112 -> 573414.56 | Q114: =OFFSET('Proforma L+H'!$E143,0,'L+H Monthly CF'!Q$3)/12 -> 2005375.3 | R114: =OFFSET('Proforma L+H'!$E143,0,'L+H Monthly CF'!R$3)/12 -> 2005375.3 | S114: =OFFSET('Proforma L+H'!$E143,0,'L+H Monthly CF'!S$3)/12 -> 2005375.3 | T114: =OFFSET('Proforma L+H'!$E143,0,'L+H Monthly CF'!T$3)/12 -> 2005375.3 | U114: =OFFSET('Proforma L+H'!$E143,0,'L+H Monthly CF'!U$3)/12 -> 2005375.3 | V114: =OFFSET('Proforma L+H'!$E143,0,'L+H Monthly CF'!V$3)/12 -> 2005375.3 | W114: =OFFSET('Proforma L+H'!$E143,0,'L+H Monthly CF'!W$3)/12 -> 2005375.3 | X114: =OFFSET('Proforma L+H'!$E143,0,'L+H Monthly CF'!X$3)/12 -> 2005375.3 | ... AZ114: =OFFSET('Proforma L+H'!$E143,0,'L+H Monthly CF'!AZ$3)/12 -> 5385123 | BA114: =SUM(E114:AZ114) -> 1.5577969e+08 | BB114: =SUM('Proforma L+H'!E143:H143)-BA114 -> 0
B116: ='Proforma L+H'!B145 -> FINANCING COSTS
B117: ='Proforma L+H'!B146 -> Seller Finance Loan - Beginning Balance | E117: ='Proforma L+H'!E146 -> 0 | F117: =E117+E118-E120 -> 0 | G117: =F117+F118-F120 -> 0 | H117: =G117+G118-G120 -> 0 | I117: =H117+H118-H120 -> 0 | J117: =I117+I118-I120 -> 0 | K117: =J117+J118-J120 -> 0 | L117: =K117+K118-K120 -> 0 | M117: =L117+L118-L120 -> 0 | ... Q117: =P117+P118-P120 -> 0 | AC117: ='Proforma L+H'!G146 -> 0 | AO117: ='Proforma L+H'!H146 -> 0
...

Sheet Returns L+H
B1: ='Proforma L+H'!B1 -> CLARENDON - LAND & HOME DEVELOPMENT
B2: Returns Analysis
B4: PROJECT FINANCING ANALYSIS | F4: BUSINESS CASE ANALYSIS
B5: TOTAL PROJECT CAPITAL NEEDS: | D5: ='Proforma L+H'!R40+'Proforma L+H'!R48 -> 96335729 | F5: TOTAL PROJECT REVENUE: | H5: =SUM('Proforma L+H'!R50:R57) -> 3.7205562e+08
B6: TOTAL PROJECT VALUE (PV of FINAL BUILD OUT): | D6: ='Proforma L+H'!T16 -> 287850000 | F6: - TOTAL PROJECT COST: | H6: ='Proforma L+H'!R143+'Proforma L+H'!R172 -> 2.7367968e+08
B7: STARTING SPEC DEVELOPMENT VALUE: | D7: ='Proforma L+H'!T37 -> 0 | F7: = NET PROFIT | H7: =H5-H6 -> 98375940
B8: EQUITY to SPEC DEV VALUE (ETV): | D8: ='Proforma L+H'!T40 -> #DIV/0! | F8: NET PROFIT %: | H8: =H7/H5 -> 0.26441192
B9: LOAN to COST (LTC): | D9: ='Proforma L+H'!T46 -> 0.88062581 | F9: RETURN on EQUITY/CAPTIAL (ROE): | H9: =H7/'Proforma L+H'!E40 -> 8.5544296
B10: LOAN to VALUE (LTV): | D10: ='Proforma L+H'!T48 -> 0.055454059
B12: PROJECT RETURNS ANALYSIS
B13: PROJECT NET CASH FLOWS: | D13: =SUM('Proforma L+H'!E223:Q223) -> 98320252
B14: EQUITY MULTIPLE: | D14: ='Proforma L+H'!R217/-F47 -> 9.5495871
B15: MODELED ROI: | D15: =D13/-F47 -> 8.5495871
B16: PROJECT IRR : | D16: =XIRR('Proforma L+H'!E223:Q223,'Proforma L+H'!E4:Q4) -> 0.64360042
F18: ='Proforma L+H'!E3 -> 0 | G18: ='Proforma L+H'!F3 -> 1 | H18: ='Proforma L+H'!G3 -> 2 | I18: ='Proforma L+H'!H3 -> 3 | J18: ='Proforma L+H'!I3 -> 4 | K18: ='Proforma L+H'!J3 -> 5 | L18: ='Proforma L+H'!K3 -> 6 | M18: ='Proforma L+H'!L3 -> 7 | ... R18: ='Proforma L+H'!Q3 -> 12
B19: SUMMARY OF RETURNS | E19: Year Beginning | F19: ='Proforma L+H'!E4 -> 45658 | G19: ='Proforma L+H'!F4 -> 46023 | H19: ='Proforma L+H'!G4 -> 46388 | I19: ='Proforma L+H'!H4 -> 46753 | J19: ='Proforma L+H'!I4 -> 47119 | K19: ='Proforma L+H'!J4 -> 47484 | L19: ='Proforma L+H'!K4 -> 47849 | M19: ='Proforma L+H'!L4 -> 48214 | ... R19: ='Proforma L+H'!Q4 -> 50041
B20: JV LP Returns
B21: Capital Return + Pref | D21: =SUM(F21:R21) -> 14641000 | F21: ='Proforma L+H'!E183 -> 0 | G21: ='Proforma L+H'!F183 -> 0 | H21: ='Proforma L+H'!G183 -> 0 | I21: ='Proforma L+H'!H183 -> 0 | J21: ='Proforma L+H'!I183 -> 14641000 | K21: ='Proforma L+H'!J183 -> 0 | L21: ='Proforma L+H'!K183 -> 0 | M21: ='Proforma L+H'!L183 -> 0 | ... R21: ='Proforma L+H'!Q183 -> 0
B22: Profit Split | D22: =SUM(F22:R22) -> 14953795 | F22: ='Proforma L+H'!E214-F21 -> 0 | G22: ='Proforma L+H'!F214-G21 -> 0 | H22: ='Proforma L+H'!G214-H21 -> 0 | I22: ='Proforma L+H'!H214-I21 -> 0 | J22: ='Proforma L+H'!I214-J21 -> 14953795 | K22: ='Proforma L+H'!J214-K21-D29 -> 0 | L22: ='Proforma L+H'!K214-L21 -> 4.535136e-09 | M22: ='Proforma L+H'!L214-M21 -> 0 | N22: ='Proforma L+H'!M214-N21 -> 0 | O22: ='Proforma L+H'!N214-O21 -> 0 | P22: ='Proforma L+H'!O214-P21 -> 0 | Q22: ='Proforma L+H'!P214-Q21 -> 0 | R22: ='Proforma L+H'!Q214-R21 -> 0
B23: Total Distributions | D23: =SUM(F23:R23) -> 29594795 | F23: =F21+F22 -> 0 | G23: =G21+G22 -> 0 | H23: =H21+H22 -> 0 | I23: =I21+I22 -> 0 | J23: =J21+J22 -> 29594795 | K23: =K21+K22 -> 0 | L23: =L21+L22 -> 4.535136e-09 | M23: =M21+M22 -> 0 | ... R23: =R21+R22 -> 0
B24: Total Contributions | D24: =SUM(F24:R24) -> 10000000 | F24: =-'Proforma L+H'!E185 -> 10000000 | G24: =-'Proforma L+H'!F185 -> 0
B25: Net Profit / Cash Flows | D25: =SUM(F25:R25) -> 19594795 | F25: =F23-F24 -> -10000000 | G25: =G23-G24 -> 0 | H25: =H23-H24 -> 0 | I25: =I23-I24 -> 0 | J25: =J23-J24 -> 29594795 | K25: =K23-K24 -> 0 | L25: =L23-L24 -> 4.535136e-09 | M25: =M23-M24 -> 0 | ... R25: =R23-R24 -> 0
B26: IRR | F26: =IRR(F25:R25) -> 0.31160732
B27: Equity Multiple | F27: =SUMIF(F25:R25,">0")/-SUMIF(F25:R25,"<0") -> 2.9594795
B28: Cumulative (Equity) Cash Position | F28: =F25+E28 -> -10000000 | G28: =G25+F28 -> -10000000 | H28: =H25+G28 -> -10000000 | I28: =I25+H28 -> -10000000 | J28: =J25+I28 -> 19594795 | K28: =K25+J28 -> 19594795 | L28: =L25+K28 -> 19594795 | M28: =M25+L28 -> 19594795 | ... R28: =R25+Q28 -> 19594795
B29: Profit Split Rebalance
B30: MO LP Returns
B31: Capital Return + Pref | D31: =SUM(F31:R31) -> 2196150 | F31: ='Proforma L+H'!E189 -> 0 | G31: ='Proforma L+H'!F189 -> 0 | H31: ='Proforma L+H'!G189 -> 0 | I31: ='Proforma L+H'!H189 -> 0 | J31: ='Proforma L+H'!I189 -> 2196150 | K31: ='Proforma L+H'!J189 -> 0 | L31: ='Proforma L+H'!K189 -> 0 | M31: ='Proforma L+H'!L189 -> 0 | ... R31: ='Proforma L+H'!Q189 -> 0
B32: Profit Split | D32: =SUM(F32:R32) -> 2243069.2 | F32: ='Proforma L+H'!E215-F31 -> 0 | G32: ='Proforma L+H'!F215-G31 -> 0 | H32: ='Proforma L+H'!G215-H31 -> 0 | I32: ='Proforma L+H'!H215-I31 -> 0 | J32: ='Proforma L+H'!I215-J31 -> 2243069.2 | K32: ='Proforma L+H'!J215-K31+D29 -> 0 | L32: ='Proforma L+H'!K215-L31 -> 6.802704e-10 | M32: ='Proforma L+H'!L215-M31 -> 0 | N32: ='Proforma L+H'!M215-N31 -> 0 | O32: ='Proforma L+H'!N215-O31 -> 0 | P32: ='Proforma L+H'!O215-P31 -> 0 | Q32: ='Proforma L+H'!P215-Q31 -> 0 | R32: ='Proforma L+H'!Q215-R31 -> 0
B33: Total Distributions | D33: =SUM(F33:R33) -> 4439219.2 | F33: =SUM(F31:F32) -> 0 | G33: =SUM(G31:G32) -> 0 | H33: =SUM(H31:H32) -> 0 | I33: =SUM(I31:I32) -> 0 | J33: =SUM(J31:J32) -> 4439219.2 | K33: =SUM(K31:K32) -> 0 | L33: =SUM(L31:L32) -> 6.802704e-10 | M33: =SUM(M31:M32) -> 0 | ... R33: =SUM(R31:R32) -> 0
B34: Total Contributions | D34: =SUM(F34:R34) -> 1500000 | F34: ='Proforma L+H'!D190 -> 1500000
B35: Net Profit / Cash Flows | D35: =SUM(F35:R35) -> 2939219.2 | F35: =F33-F34 -> -1500000 | G35: =G33-G34 -> 0 | H35: =H33-H34 -> 0 | I35: =I33-I34 -> 0 | J35: =J33-J34 -> 4439219.2 | K35: =K33-K34 -> 0 | L35: =L33-L34 -> 6.802704e-10 | M35: =M33-M34 -> 0 | ... R35: =R33-R34 -> 0
B36: IRR | F36: =IRR(F35:R35) -> 0.31160732
B37: Equity Multiple | F37: =SUMIF(F35:R35,">0")/-SUMIF(F35:R35,"<0") -> 2.9594795
B38: Cumulative (Equity) Cash Position | F38: =F35+E38 -> -1500000 | G38: =G35+F38 -> -1500000 | H38: =H35+G38 -> -1500000 | I38: =I35+H38 -> -1500000 | J38: =J35+I38 -> 2939219.2 | K38: =K35+J38 -> 2939219.2 | L38: =L35+K38 -> 2939219.2 | M38: =M35+L38 -> 2939219.2 | ... R38: =R35+Q38 -> 2939219.2
B40: MO/JV JV GP Returns
B41: Total Distributions | D41: =SUM(F41:R41) -> 75786238 | F41: ='Proforma L+H'!E216 -> 0 | G41: ='Proforma L+H'!F216 -> 0 | H41: ='Proforma L+H'!G216 -> 0 | I41: ='Proforma L+H'!H216 -> 0 | J41: ='Proforma L+H'!I216 -> 9943752.6 | K41: ='Proforma L+H'!J216 -> 65842486 | L41: ='Proforma L+H'!K216 -> 2.2351742e-09 | M41: ='Proforma L+H'!L216 -> 0 | ... R41: ='Proforma L+H'!Q216 -> 0
B42: Net Profit / Cash Flows | D42: =SUM(F42:R42) -> 75786238 | F42: =SUM(F41:F41) -> 0 | G42: =SUM(G41:G41) -> 0 | H42: =SUM(H41:H41) -> 0 | I42: =SUM(I41:I41) -> 0 | J42: =SUM(J41:J41) -> 9943752.6 | K42: =SUM(K41:K41) -> 65842486 | L42: =SUM(L41:L41) -> 2.2351742e-09 | M42: =SUM(M41:M41) -> 0 | ... R42: =SUM(R41:R41) -> 0
B43: JV Portion | C43: 0 | D43: =SUM(F43:R43) -> 0 | F43: =F42*$C$43 -> 0 | G43: =G42*$C$43 -> 0 | H43: =H42*$C$43 -> 0 | I43: =I42*$C$43 -> 0 | J43: =J42*$C$43 -> 0 | K43: =K42*$C$43 -> 0 | L43: =L42*$C$43 -> 0 | M43: =M42*$C$43 -> 0 | ... R43: =R42*$C$43 -> 0
B44: MO Portion | C44: =1-C43 -> 1 | D44: =SUM(F44:R44) -> 75786238 | F44: =F42*$C$44 -> 0 | G44: =G42*$C$44 -> 0 | H44: =H42*$C$44 -> 0 | I44: =I42*$C$44 -> 0 | J44: =J42*$C$44 -> 9943752.6 | K44: =K42*$C$44 -> 65842486 | L44: =L42*$C$44 -> 2.2351742e-09 | M44: =M42*$C$44 -> 0 | ... R44: =R42*$C$44 -> 0
B46: Net Cash Flow For Distributions - TOTAL PROJECT RETURNS
B47: Net Levered Before Tax Cash Flow | D47: =SUM(F47:R47) -> 98320252 | F47: ='Proforma L+H'!E223 -> -11500000 | G47: ='Proforma L+H'!F223 -> 0 | H47: ='Proforma L+H'!G223 -> 0 | I47: ='Proforma L+H'!H223 -> 0 | J47: ='Proforma L+H'!I223 -> 43977766 | K47: ='Proforma L+H'!J223 -> 65842486 | L47: ='Proforma L+H'!K223 -> 7.4505806e-09 | M47: ='Proforma L+H'!L223 -> 0 | ... R47: ='Proforma L+H'!Q223 -> 0
B48: Levered IRR | F48: =XIRR(F47:R47,F19:R19) -> 0.64360042
B49: Equity Multiple | F49: =SUMIF(F47:R47,">0")/-SUMIF(F47:R47,"<0") -> 9.5495871 | G49: =IRR(F47:M47) -> 0.64410031
F50: =F35+F25+F42-'Proforma L+H'!E223 -> 0 | G50: =G35+G25+G42-'Proforma L+H'!F223 -> 0 | H50: =H35+H25+H42-'Proforma L+H'!G223 -> 0 | I50: =I35+I25+I42-'Proforma L+H'!H223 -> 0 | J50: =J35+J25+J42-'Proforma L+H'!I223 -> 0 | K50: =K35+K25+K42-'Proforma L+H'!J223 -> 0 | L50: =L35+L25+L42-'Proforma L+H'!K223 -> 0 | M50: =M35+M25+M42-'Proforma L+H'!L223 -> 0 | ... P50: =P35+P25+P42-'Proforma L+H'!O223 -> 0 | Q50: =Q35+Q25+Q42 -> 0
B51: Return of PM EQUITY & Hurdle 1 (Preferred Return)
B52: Net Levered Before Tax Cash Flow | F52: =F47 -> -11500000 | G52: =G47 -> 0 | H52: =H47 -> 0 | I52: =I47 -> 0 | J52: =J47 -> 43977766 | K52: =K47 -> 65842486 | L52: =L47 -> 7.4505806e-09 | M52: =M47 -> 0 | N52: ='Proforma L+H'!M217 -> 0 | O52: ='Proforma L+H'!N217 -> 0 | P52: ='Proforma L+H'!O217 -> 0 | Q52: ='Proforma L+H'!P217 -> 0 | R52: ='Proforma L+H'!Q217 -> 0
B53: Preferred returns | F53: =F52 -> -11500000 | G53: =G52 -> 0 | H53: =H52 -> 0 | I53: =I52 -> 0 | J53: =J52 -> 43977766 | L53: =L52 -> 7.4505806e-09 | M53: 27400000 | N53: =N52 -> 0 | O53: =O52 -> 0 | P53: =P52 -> 0 | Q53: =Q52 -> 0 | R53: =R52 -> 0 | T53: =SUM(F53:S53) -> 59877766
B54: IRR Check - preferred returns | F54: =XIRR(F53:R53,F45:R45) -> #NUM! | T54: =U76 -> 0
B55: Remaining Cash Flow for Split | F55: =F52-F53 -> 0 | G55: =G52-G53 -> 0 | H55: =H52-H53 -> 0 | I55: =I52-I53 -> 0 | J55: =J52-J53 -> 0 | K55: =K52-K53 -> 65842486 | L55: =L52-L53 -> 0 | M55: =M52-M53 -> -27400000 | ... R55: =R52-R53 -> 0
B56: =T79 -> 0 | C56: =U79 -> 0 | F56: =F$55*$C56 -> 0 | G56: =G$55*$C56 -> 0 | H56: =H$55*$C56 -> 0 | I56: =I$55*$C56 -> 0 | J56: =J$55*$C56 -> 0 | K56: =K$55*$C56 -> 0 | L56: =L$55*$C56 -> 0 | M56: =M$55*$C56 -> 0 | ... R56: =R$55*$C56 -> 0 | T56: =SUM(F56:S56) -> 0
B57: =T80 -> 0 | C57: =U80 -> 0 | F57: =F$55*$C57 -> 0 | G57: =G$55*$C57 -> 0 | H57: =H$55*$C57 -> 0 | I57: =I$55*$C57 -> 0 | J57: =J$55*$C57 -> 0 | K57: =K$55*$C57 -> 0 | L57: =L$55*$C57 -> 0 | M57: =M$55*$C57 -> 0 | ... R57: =R$55*$C57 -> 0 | T57: =SUM(F57:S57) -> 0
B59: CM Common Members SHARE
B60: Net Levered Before Tax Cash Flow | F60: =-#REF! -> #REF! | G60: =-#REF! -> #REF! | H60: =-#REF! -> #REF! | I60: =I57 -> 0 | J60: =J57 -> 0 | K60: =K57 -> 0 | L60: =L57 -> 0 | M60: =M57 -> 0 | N60: =N57 -> 0 | O60: =O57 -> 0 | P60: =P57 -> 0 | ... R60: =R57 -> 0
B61: Preferred returns | F61: =F60 -> #REF! | G61: =G60 -> #REF!
B62: IRR Check - preferred returns | F62: =XIRR(F61:R61,F45:R45) -> #REF! | T62: 0.1
B63: Remaining Cash Flow for Split | F63: =F60-F61 -> #REF! | G63: =G60-G61 -> #REF! | H63: =H60-H61 -> #REF! | I63: =I60-I61 -> 0 | J63: =J60-J61 -> 0 | K63: =K60-K61 -> 0 | L63: =L60-L61 -> 0 | M63: =M60-M61 -> 0 | ... R63: =R60-R61 -> 0
B64: CM SPONSOR SHARE | C64: 0 | F64: =F$63*$C64 -> #REF! | G64: =G$63*$C64 -> #REF! | H64: =H$63*$C64 -> #REF! | I64: =I$63*$C64 -> 0 | J64: =J$63*$C64 -> 0 | K64: =K$63*$C64 -> 0 | L64: =L$63*$C64 -> 0 | M64: =M$63*$C64 -> 0 | ... R64: =R$63*$C64 -> 0
B65: CM Common Members MANAGER SHARE | C65: =1-C64 -> 1 | F65: =F$63*$C65 -> #REF! | G65: =G$63*$C65 -> #REF! | H65: =H$63*$C65 -> #REF! | I65: =I$63*$C65 -> 0 | J65: =J$63*$C65 -> 0 | K65: =K$63*$C65 -> 0 | L65: =L$63*$C65 -> 0 | M65: =M$63*$C65 -> 0 | ... R65: =R$63*$C65 -> 0 | T65: =SUM(D65:S65) -> #REF!
V66: CM Share Returns | W66: PM Share Returns | AA66: NiCK | AB66: MTN O | AC66: DeREUS | AD66: TOTAL
B67: Proposed Sponsor Split
B68: Market rate Overhead & Fees Paid to Working Sponsors (e.g. Design Fees, Sales Commision, Asset Management, Common Members Fees, etc.)
B69: Cost of Contributed Capital (e.g. Cash Multiple for Pursuit Dollars, 10% Pref for Equity, etc.)
B70: Equal split of Sponsor Distribution (e.g. 3 ways, 4 ways or 5 ways depending on head count of Sponsor Principals)
T71: NICK | U71: =AA75 -> 0 | V71: =$T$57*U71 -> 0 | W71: =(5000000/$D$24)*$T$56+5000000 -> 5000000 | Y71: PURSUIT/ENT. | Z71: 0.33333 | AA71: =1/3 -> 0.33333333 | AB71: =1/3 -> 0.33333333 | AC71: =1/3 -> 0.33333333 | AD71: =SUM(AA71:AC71) -> 1

Sheet Proforma A+H
B1: CLARENDON - AMENITY + HOTEL DEVELOPMENT: PROFORMA
B2: Operations Proforma
G3: 0 | H3: =G3+1 -> 1 | I3: =H3+1 -> 2 | J3: =I3+1 -> 3 | K3: =J3+1 -> 4 | L3: =K3+1 -> 5 | M3: =L3+1 -> 6 | N3: =M3+1 -> 7 | O3: =N3+1 -> 8 | ... R3: =Q3+1 -> 11 | S3: 12
F4: Year Beginning | G4: ='Proforma L+H'!E4 -> 45658 | H4: ='Proforma L+H'!F4 -> 46023 | I4: ='Proforma L+H'!G4 -> 46388 | J4: ='Proforma L+H'!H4 -> 46753 | K4: ='Proforma L+H'!I4 -> 47119 | L4: ='Proforma L+H'!J4 -> 47484 | M4: ='Proforma L+H'!K4 -> 47849 | N4: ='Proforma L+H'!L4 -> 48214 | ... S4: ='Proforma L+H'!Q4 -> 50041 | T4: TOTALS
B5: Buildout schedule | C5: SQFT | U5: Price/ Unit
B6: =Assumptions!F26 -> Lodge Rooms | C6: =Assumptions!F28 -> 500 | I6: =Assumptions!$F27*0.5 -> 10 | J6: =Assumptions!$F27*0.5 -> 10 | T6: =SUM(H6:S6) -> 20 | V6: =T6*C6 -> 10000
B7: =Assumptions!G26 -> Villa/Cabin | C7: =Assumptions!G28 -> 750 | I7: 8 | J7: 8 | K7: 8 | T7: =SUM(H7:S7) -> 24 | V7: =T7*C7 -> 18000
B8: =Assumptions!H26 -> Cottages | C8: =Assumptions!H28 -> 1250 | J8: 12 | K8: 12 | T8: =SUM(H8:S8) -> 24 | V8: =T8*C8 -> 30000
B9: =Assumptions!I26 -> Auton. Tents | C9: =Assumptions!I28 -> 625 | H9: =Assumptions!I27 -> 12 | T9: =SUM(H9:S9) -> 12 | V9: =T9*C9 -> 7500
T10: =SUM(H10:S10) -> 0 | V10: =T10*C10 -> 0
T11: =SUM(H11:S11) -> 0 | V11: =T11*C11 -> 0
B12: Total starts | H12: =SUM(H6:H11) -> 12 | I12: =SUM(I6:I11) -> 18 | J12: =SUM(J6:J11) -> 30 | K12: =SUM(K6:K11) -> 20 | L12: =SUM(L6:L11) -> 0 | M12: =SUM(M6:M11) -> 0 | N12: =SUM(N6:N11) -> 0 | O12: =SUM(O6:O11) -> 0 | ... T12: =SUM(T6:T11) -> 80
B13: Total Leaseable/Sellable SQFT | C13: =SUMPRODUCT(C6:C11,T6:T11) -> 65500 | V13: =T184/C13 -> 2479.8586 | W13: =T184/80 -> 2030384.3
B15: Sales Schedule
B16: =B6 -> Lodge Rooms | C16: =T16 -> 0 | H16: =ROUND(G6*Assumptions!$F33,0) -> 0 | I16: =ROUND(H6*Assumptions!$F33,0) -> 0 | J16: =ROUND(I6*Assumptions!$F33,0) -> 0 | K16: =ROUND(J6*Assumptions!$F33,0) -> 0 | L16: =ROUND(K6*Assumptions!$F33,0) -> 0 | M16: =ROUND(L6*Assumptions!$F33,0) -> 0 | N16: =ROUND(M6*Assumptions!$F33,0) -> 0 | O16: =ROUND(N6*Assumptions!$F33,0) -> 0 | ... S16: =ROUND(R6*Assumptions!$F33,0) -> 0 | T16: =SUM(H16:S16) -> 0
B17: =B7 -> Villa/Cabin | C17: =T17 -> 21 | H17: =ROUNDDOWN(G7*Assumptions!$G$33,0) -> 0 | I17: =ROUNDDOWN(H7*Assumptions!$G$33,0) -> 0 | J17: =ROUND(I7*Assumptions!$G33,0) -> 7 | K17: =ROUND(J7*Assumptions!$G33,0) -> 7 | L17: =ROUND(K7*Assumptions!$G33,0) -> 7 | M17: =ROUND(L7*Assumptions!$G33,0) -> 0 | N17: =ROUND(M7*Assumptions!$G33,0) -> 0 | O17: =ROUND(N7*Assumptions!$G33,0) -> 0 | P17: =ROUND(O7*Assumptions!$G33,0) -> 0 | Q17: =ROUND(P7*Assumptions!$G33,0) -> 0 | ... S17: =ROUND(R7*Assumptions!$G33,0) -> 0 | T17: =SUM(H17:S17) -> 21
B18: =B8 -> Cottages | C18: =T18 -> 24 | H18: =ROUND(G8*Assumptions!$H33,0) -> 0 | I18: =ROUND(H8*Assumptions!$H33,0) -> 0 | J18: =ROUND(I8*Assumptions!$H33,0) -> 0 | K18: =ROUND(J8*Assumptions!$H33,0) -> 12 | L18: =ROUND(K8*Assumptions!$H33,0) -> 12 | M18: =ROUND(L8*Assumptions!$H33,0) -> 0 | N18: =ROUND(M8*Assumptions!$H33,0) -> 0 | O18: =ROUND(N8*Assumptions!$H33,0) -> 0 | ... S18: =ROUND(R8*Assumptions!$H33,0) -> 0 | T18: =SUM(H18:S18) -> 24
B19: =B9 -> Auton. Tents | C19: =T19 -> 0 | H19: =ROUND(G9*Assumptions!$I35,0) -> 0 | I19: =ROUND(H9*Assumptions!$I35,0) -> 0 | J19: =ROUND(I9*Assumptions!$I35,0) -> 0 | K19: =ROUND(J9*Assumptions!$I35,0) -> 0 | L19: =ROUND(K9*Assumptions!$I35,0) -> 0 | M19: =ROUND(L9*Assumptions!$I35,0) -> 0 | N19: =ROUND(M9*Assumptions!$I35,0) -> 0 | O19: =ROUND(N9*Assumptions!$I35,0) -> 0 | ... S19: =ROUND(R9*Assumptions!$I35,0) -> 0 | T19: =SUM(H19:S19) -> 0
H20: =ROUNDDOWN(G10*Assumptions!$F$33,0) -> 0 | I20: =ROUNDDOWN(H10*Assumptions!$F$33,0) -> 0 | J20: =ROUNDDOWN(I10*Assumptions!$F$33,0) -> 0 | K20: =ROUNDDOWN(J10*Assumptions!$F$33,0) -> 0 | L20: =ROUNDDOWN(K10*Assumptions!$F$33,0) -> 0 | M20: =ROUNDDOWN(L10*Assumptions!$F$33,0) -> 0 | N20: =ROUNDDOWN(M10*Assumptions!$F$33,0) -> 0 | O20: =ROUNDDOWN(N10*Assumptions!$F$33,0) -> 0 | ... R20: =ROUNDDOWN(Q10*Assumptions!$F$33,0) -> 0 | S20: =R8 -> 0 | T20: =SUM(H20:S20) -> 0
