Workbook
Name _off3: #REF!
Name _off4: #REF!
Name _off5: #REF!
Name _off6: #REF!
Name _ret1: #REF!
Name _ret2: #REF!
Name _ret3: #REF!
Name _ret4: #REF!
Name _ret5: #REF!
Name _ret6: #REF!
Name _sa1: #REF!
Name _sa2: #REF!
Name _sa3: #REF!
Name _sa4: #REF!
Name _sa5: #REF!
Name _sa6: #REF!
Name ArgusInput: #REF!
Name ArgusInput.New: #REF!
Name Budget.AnalystReport.Rows: #REF!
Name Budget.BudgetPeriods.Columns: #REF!
Name Budget.ColumnHeadings.Row: #REF!
Name Budget.HideColumns.Row: #REF!
Name Budget.HideRows.Column: #REF!
Name Budget.RowOrderBy.Column: #REF!
Name Budget.RowOrderByDescription.Column: #REF!
Name Budget.Total.Column: #REF!
Name Budget.WBCol.Column: #REF!
Name Budget.WBStatus.Column: #REF!
Name Case_A: #REF!
Name CAT_Com: #REF!
Name Choices_Wrapper: #N/A
Name Choices_Wrapper5: #N/A
Name cnsld2: #REF!
Name cnsld3: #REF!
Name cnsld4: #REF!
Name cost1: #REF!
Name CostInflation: #REF!
Name Cur_QTD_Total_Revenue: #REF!
Name Date_Acquisition: #REF!
Name Date_AmortStart1: #REF!
Name Date_AmortStart2: #REF!
Name Date_CostsPricing: #REF!
Name Date_PreDevEnd: #REF!
Name Date_Refi: #REF!
Name Date_Sale: #REF!
Name Date_SaleParcel: #REF!
Name Date_Stabilization: #REF!
Name Description: #REF!
Name DevFeeTarget: #REF!
Name EntryCapRt: #REF!
Name ExitCapRt: #REF!
Name FileVersion: #REF!
Name FinFeeTarget: #REF!
Name Hello: #N/A
Name Hello5: #N/A
Name hotl1: #REF!
Name hotl2: #REF!
Name hotl3: #REF!
Name hotl4: #REF!
Name hotl5: #REF!

Sheet Assumptions
B1: CLARENDON - LAND+HOME, AMENITY+HOTEL DEVELOPMENT - ASSUMPTIONS
B2: OVERALL ASSUMPTIONS
B4: General | E4: Debt Financing | F4: LAND + HOME | G4: AMENITY + HOTEL | I4: Sub-Debt/ Equity Financing | K4: LAND + HOME | L4: AMENITY + HOTEL | N4: Land & Infrastructure
B5: Development Start Date | C5: 45473 | E5: Origination Year | F5: 2024 | G5: 2026 | I5: Pref Accrual Rate | K5: 0.1 | L5: 0.1 | P5: Acres | Q5: Value
B6: Development Start Year | C6: 2024 | E6: Original Term (Years) | F6: 2 | G6: 3 | I6: EB-5 Interest Rate | K6: 0.11 | L6: 0.11 | N6: Total Land | P6: =P7+P8 -> 319 | Q6: =Q7+Q8 -> 22000000
E7: Underwritten LTC | F7: 0.8118774 | G7: 0.75 | I7: EB-5 Origination Fee | K7: 0.01 | L7: =K7 -> 0.01 | N7: RESI | P7: 240 | Q7: 15000000
B8: Repayment Waterfall | E8: Interest Rate | F8: 0.12 | G8: =F8 -> 0.12 | I8: EB-5 Exit Fee | K8: 0.01 | L8: =K8 -> 0.01 | N8: AMENITY + HOTEL | P8: 79 | Q8: 7000000
B9: Loan | E9: Debt Placement & Origination Fee | F9: =0.0294+0.005+0.0056 -> 0.04 | G9: =F9 -> 0.04 | I9: Bridge Loan Placement Fee | K9: 0.02 | L9: N/A | N9: Infrastructure Cost | Q9: 15000000
B10: Preferred Return | E10: 1 Year Extension Fee | F10: =0.005*4 -> 0.02 | I10: Bridge Loan Interest Rate | K10: 0.15 | L10: N/A
B11: Capital Return | E11: Financing Cost Gross-up | F11: 0.2 | G11: 0.275 | I11: GP Promote Split | K11: 0 | L11: 0
F12: ='Proforma Land+Home'!V148-'Proforma Land+Home'!U148 -> -3349077.3 | G12: =IFERROR('Proforma A+H'!W188-'Proforma A+H'!X188,"")
B14: LAND + HOME ASSUMPTIONS
B16: Build / Sale Cost | E16: Unit Mix | J16: Unit Sales
B17: Vertical Construction Cost psft | C17: =850*C18 -> 850 | F17: Avg Size | G17: PPSF | H17: Escalation | J17: Sales Price Scalar | M17: 1
B18: Vertical Construction Costs Scalar | C18: 1 | E18: Homesites | F18: 3500 | G18: 1750 | H18: 0.1 | J18: Net Profit % | M18: 0.2
B19: Cost of Sale - RE Fees | C19: 0.045 | E19: Village | F19: 4500 | G19: 1650 | H19: 0.075 | J19: Phantom Tax Rate | M19: 0.3
B20: Real Estate Taxes (Annual) / mils | C20: =10000/39 -> 256.41026 | E20: Cottages | F20: 2500 | G20: 1850 | H20: 0.075
B23: AMENITY + HOTEL ASSUMPTIONS
B25: Hotel Details | E25: Hotel Guest Rooms | K25: Build Cost
B26: Start Date | C26: 46053 | F26: Lodge Rooms | G26: Villa/Cabin | H26: Cottages | I26: Auton. Tents | K26: Vertical Construction Costs Scalar | N26: ='Returns A+H'!L14 -> 1
B27: Member Dues / year / unit | C27: 15000 | E27: Guest Rooms | F27: 20 | G27: 24 | H27: 24 | I27: 12 | K27: Real Estate Taxes (Annual) / mils | N27: ='Proforma Resi'!C269 -> 256
B28: Loan Interest Rate | C28: 0.03 | E28: SQFT | F28: 500 | G28: 750 | H28: 1250 | I28: 625
B29: Loan Origination Fees | C29: 0 | E29: Sales Price / SF | F29: 0 | G29: 2250 | H29: 2000 | I29: 0
B30: Disposition Year | C30: ='Returns A+H'!L15 -> 7 | E30: Average Daily Rate | F30: 1100 | G30: 1300 | H30: 3000 | I30: 750
B31: Terminal Cap Rate | C31: 0.065 | E31: Average Sales Price | F31: =F28*F29 -> 0 | G31: =G28*G29 -> 1687500 | H31: =H28*H29 -> 2500000 | I31: =I28*I29 -> 0
B32: Selling Costs | C32: 0.05 | E32: Sales Price Escalation | F32: 0.05 | G32: 0.05 | H32: 0.05 | I32: 0.05
B33: Hold Period | C33: 132 | E33: % Rooms for Sale | F33: 0 | G33: 0.5 | H33: 1 | I33: 0
B34: Hotel Room Rent Growth Rate | C34: 0.03
B35: Hotel Days | C35: 365
B36: Hotel Rooms Operating Cost | C36: =35%-F33*15% -> 0.35
B37: Condo Owner Revenue Split | C37: 0.5
F38: 1 | G38: 2 | H38: 3 | I38: 4 | J38: 5 | K38: 6 | L38: 7 | M38: 8 | N38: 9 | O38: 10 | P38: 11 | Q38: 12
B39: Bar Details | F39: 44562 | G39: =F39+31 -> 44593 | H39: =G39+31 -> 44624 | I39: =H39+31 -> 44655 | J39: =I39+31 -> 44686 | K39: =J39+31 -> 44717 | L39: =K39+31 -> 44748 | M39: =L39+31 -> 44779 | N39: =M39+31 -> 44810 | ... Q39: =P39+31 -> 44903 | R39: Avg
B40: Start Date | C40: 46753 | E40: Seasonal Occupancy - Hotel | F40: 0.75 | G40: 0.75 | H40: 0.65 | I40: 0.25 | J40: 0.15 | K40: 0.45 | L40: 0.65 | M40: 0.55 | N40: 0.45 | O40: 0.1 | P40: 0.1 | Q40: 0.55 | R40: =AVERAGE(F40:Q40) -> 0.45
B41: Available room/nights | C41: =(F27+G27)*C35 -> 16060 | E41: Conference Center Occupancy | F41: 0.25 | G41: 0.25 | H41: 0.25 | I41: 0.5 | J41: 0.75 | K41: 1 | L41: 1 | M41: 1 | N41: 0.75 | O41: 0.5 | P41: 0.25 | Q41: 0.25 | R41: =AVERAGE(F41:Q41) -> 0.5625
B42: Paid Room Nights | C42: =C41*R40 -> 7227 | E42: Adj. Conf Center Occupancy | F42: =IF(OR(F38<MONTH($C$63),F38>$C$64),0,F41) -> 0.25 | G42: =IF(OR(G38<MONTH($C$63),G38>$C$64),0,G41) -> 0.25 | H42: =IF(OR(H38<MONTH($C$63),H38>$C$64),0,H41) -> 0.25 | I42: =IF(OR(I38<MONTH($C$63),I38>$C$64),0,I41) -> 0.5 | J42: =IF(OR(J38<MONTH($C$63),J38>$C$64),0,J41) -> 0.75 | K42: =IF(OR(K38<MONTH($C$63),K38>$C$64),0,K41) -> 1 | L42: =IF(OR(L38<MONTH($C$63),L38>$C$64),0,L41) -> 1 | M42: =IF(OR(M38<MONTH($C$63),M38>$C$64),0,M41) -> 1 | ... Q42: =IF(OR(Q38<MONTH($C$63),Q38>$C$64),0,Q41) -> 0.25 | R42: =AVERAGE(F42:Q42) -> 0.5625
B43: Bar Revenue (% of Room Rev) | C43: 0.2
B44: Bar COS (% of Bar Rev) | C44: 0.75 | F44: 0 | G44: =F44+1 -> 1 | H44: =G44+1 -> 2 | I44: =H44+1 -> 3 | J44: =I44+1 -> 4 | K44: =J44+1 -> 5 | L44: =K44+1 -> 6 | M44: =L44+1 -> 7 | N44: =M44+1 -> 8 | O44: =N44+1 -> 9
F45: =YEAR(C5)+1 -> 2025 | G45: =F45+1 -> 2026 | H45: =G45+1 -> 2027 | I45: =H45+1 -> 2028 | J45: =I45+1 -> 2029 | K45: =J45+1 -> 2030 | L45: =K45+1 -> 2031 | M45: =L45+1 -> 2032 | N45: =M45+1 -> 2033 | O45: =N45+1 -> 2034 | P45: Total Rooms | Q45: Condos
B46: Spa / Wellness Center Details | E46: Conf Center Rental Rates | F46: =Assumptions!$C$60 -> 25000 | G46: =F46*(1+$C$61) -> 25750 | H46: =G46*(1+$C$61) -> 26522.5 | I46: =H46*(1+$C$61) -> 27318.175 | J46: =I46*(1+$C$61) -> 28137.72 | K46: =J46*(1+$C$61) -> 28981.852 | L46: =K46*(1+$C$61) -> 29851.307 | M46: =L46*(1+$C$61) -> 30746.847 | N46: =M46*(1+$C$61) -> 31669.252 | O46: =N46*(1+$C$61) -> 32619.33
B47: Start Date | C47: 46753 | E47: Avg Daily Hotel Rates - Lodge Rooms | F47: =Assumptions!$F$30 -> 1100 | G47: =F47*(1+$C$34) -> 1133 | H47: =G47*(1+$C$34) -> 1166.99 | I47: =H47*(1+$C$34) -> 1201.9997 | J47: =I47*(1+$C$34) -> 1238.0597 | K47: =J47*(1+$C$34) -> 1275.2015 | L47: =K47*(1+$C$34) -> 1313.4575 | M47: =L47*(1+$C$34) -> 1352.8613 | N47: =M47*(1+$C$34) -> 1393.4471 | O47: =N47*(1+$C$34) -> 1435.2505 | P47: =F27 -> 20 | Q47: =P47*F33 -> 0
B48: Available room/nights | C48: =(F27+G27)*C35 -> 16060 | E48: Avg Daily Hotel Rates - Villa/ Cabin | F48: =Assumptions!$G$30 -> 1300 | G48: =F48*(1+$C$34) -> 1339 | H48: =G48*(1+$C$34) -> 1379.17 | I48: =H48*(1+$C$34) -> 1420.5451 | J48: =I48*(1+$C$34) -> 1463.1615 | K48: =J48*(1+$C$34) -> 1507.0563 | L48: =K48*(1+$C$34) -> 1552.268 | M48: =L48*(1+$C$34) -> 1598.836 | N48: =M48*(1+$C$34) -> 1646.8011 | O48: =N48*(1+$C$34) -> 1696.2051 | P48: =G27 -> 24 | Q48: =P48*G33 -> 12
B49: Paid Room Nights | C49: =C48*R40 -> 7227 | E49: Avg Daily Hotel Rates - Cottages | F49: =Assumptions!$H$30 -> 3000 | G49: =F49*(1+$C$34) -> 3090 | H49: =G49*(1+$C$34) -> 3182.7 | I49: =H49*(1+$C$34) -> 3278.181 | J49: =I49*(1+$C$34) -> 3376.5264 | K49: =J49*(1+$C$34) -> 3477.8222 | L49: =K49*(1+$C$34) -> 3582.1569 | M49: =L49*(1+$C$34) -> 3689.6216 | N49: =M49*(1+$C$34) -> 3800.3102 | O49: =N49*(1+$C$34) -> 3914.3196 | P49: =H27 -> 24 | Q49: =P49*H33 -> 24
B50: Spa / Wellness Center Revenue (% of Room Rev) | C50: 0.05 | E50: Avg Daily Hotel Rates - Auton. Tents | F50: =I30 -> 750 | G50: =F50*(1+$C$34) -> 772.5 | H50: =G50*(1+$C$34) -> 795.675 | I50: =H50*(1+$C$34) -> 819.54525 | J50: =I50*(1+$C$34) -> 844.13161 | K50: =J50*(1+$C$34) -> 869.45556 | L50: =K50*(1+$C$34) -> 895.53922 | M50: =L50*(1+$C$34) -> 922.4054 | N50: =M50*(1+$C$34) -> 950.07756 | O50: =N50*(1+$C$34) -> 978.57989 | P50: =I27 -> 12 | Q50: =P50*I33 -> 0
E51: Avg Daily Hotel Rates - Total | F51: =SUMPRODUCT(F47:F50,$P$47:$P$50,F56:F59) -> 0 | G51: =SUMPRODUCT(G47:G50,$P$47:$P$50,G56:G59) -> 0 | H51: =SUMPRODUCT(H47:H50,$P$47:$P$50,H56:H59) -> 9548.1 | I51: =SUMPRODUCT(I47:I50,$P$47:$P$50,I56:I59) -> 18357.814 | J51: =SUMPRODUCT(J47:J50,$P$47:$P$50,J56:J59) -> 72707.869 | K51: =SUMPRODUCT(K47:K50,$P$47:$P$50,K56:K59) -> 104798.38 | L51: =SUMPRODUCT(L47:L50,$P$47:$P$50,L56:L59) -> 138748.88 | M51: =SUMPRODUCT(M47:M50,$P$47:$P$50,M56:M59) -> 165049.07 | ... O51: =SUMPRODUCT(O47:O50,$P$47:$P$50,O56:O59) -> 175100.56 | P51: =SUM(P47:P50) -> 80 | Q51: =SUM(Q47:Q50) -> 36
B52: Spa / Wellness Center COS (% Spa Revenue) | C52: 0.25 | E52: Avg Daily Rates - Villa/ Cabin Condo | F52: =F48*$P48*F57 -> 0 | G52: =G48*$P48*G57 -> 0 | H52: =H48*$P48*H57 -> 0 | I52: =I48*$P48*I57 -> 8523.2706 | J52: =J48*$P48*J57 -> 17557.937 | K52: =K48*$P48*K57 -> 27127.013 | L52: =L48*$P48*L57 -> 37254.432 | M52: =M48*$P48*M57 -> 38372.065 | ... O52: =O48*$P48*O57 -> 40708.923
E53: Avg Daily Rates - Cottages Condo | F53: =F49*$P49*F58 -> 0 | G53: =G49*$P49*G58 -> 0 | H53: =H49*$P49*H58 -> 0 | I53: =I49*$P49*I58 -> 0 | J53: =J49*$P49*J58 -> 20259.159 | K53: =K49*$P49*K58 -> 41733.867 | L53: =L49*$P49*L58 -> 64478.824 | M53: =M49*$P49*M58 -> 88550.918 | ... O53: =O49*$P49*O58 -> 93943.669
B54: Restaurant / Event Center
B55: Start Date | C55: 46753 | E55: Availability
B56: Available room/nights | C56: =(F27+G27)*C35 -> 16060 | E56: Lodge Rooms | F56: 0 | G56: {=SUM('Proforma A+H'!$G6:G6/'Proforma A+H'!$T6)} -> 0 | H56: {=SUM('Proforma A+H'!$G6:H6/'Proforma A+H'!$T6)} -> 0 | I56: 0 | J56: {=SUM('Proforma A+H'!$G6:J6/'Proforma A+H'!$T6)} -> 1 | K56: {=SUM('Proforma A+H'!$G6:K6/'Proforma A+H'!$T6)} -> 1 | L56: {=SUM('Proforma A+H'!$G6:L6/'Proforma A+H'!$T6)} -> 1 | M56: {=SUM('Proforma A+H'!$G6:M6/'Proforma A+H'!$T6)} -> 1 | N56: {=SUM('Proforma A+H'!$G6:N6/'Proforma A+H'!$T6)} -> 1 | O56: {=SUM('Proforma A+H'!$G6:O6/'Proforma A+H'!$T6)} -> 1
B57: Paid Room Nights | C57: =C56*R40 -> 7227 | E57: Villa/Cabin | F57: 0 | G57: {=SUM('Proforma A+H'!$G7:G7/'Proforma A+H'!$T7)} -> 0 | H57: {=SUM('Proforma A+H'!$G7:H7/'Proforma A+H'!$T7)} -> 0 | I57: {=SUM('Proforma A+H'!$G7:I7/'Proforma A+H'!$T7)} -> 0.25 | J57: {=SUM('Proforma A+H'!$G7:J7/'Proforma A+H'!$T7)} -> 0.5 | K57: {=SUM('Proforma A+H'!$G7:K7/'Proforma A+H'!$T7)} -> 0.75 | L57: {=SUM('Proforma A+H'!$G7:L7/'Proforma A+H'!$T7)} -> 1 | M57: {=SUM('Proforma A+H'!$G7:M7/'Proforma A+H'!$T7)} -> 1 | N57: {=SUM('Proforma A+H'!$G7:N7/'Proforma A+H'!$T7)} -> 1 | O57: {=SUM('Proforma A+H'!$G7:O7/'Proforma A+H'!$T7)} -> 1
B58: F&B Revenue (% Rooms Revenue) | C58: 0.27 | E58: Cottages | F58: 0 | G58: {=SUM('Proforma A+H'!$G8:G8/'Proforma A+H'!$T8)} -> 0 | H58: {=SUM('Proforma A+H'!$G8:H8/'Proforma A+H'!$T8)} -> 0 | I58: {=SUM('Proforma A+H'!$G8:I8/'Proforma A+H'!$T8)} -> 0 | J58: {=SUM('Proforma A+H'!$G8:J8/'Proforma A+H'!$T8)} -> 0.25 | K58: {=SUM('Proforma A+H'!$G8:K8/'Proforma A+H'!$T8)} -> 0.5 | L58: {=SUM('Proforma A+H'!$G8:L8/'Proforma A+H'!$T8)} -> 0.75 | M58: {=SUM('Proforma A+H'!$G8:M8/'Proforma A+H'!$T8)} -> 1 | N58: {=SUM('Proforma A+H'!$G8:N8/'Proforma A+H'!$T8)} -> 1 | O58: {=SUM('Proforma A+H'!$G8:O8/'Proforma A+H'!$T8)} -> 1
B59: F&B COS (% F&B Revenue) | C59: 0.9 | E59: Auton. Tents | F59: 0 | G59: {=SUM('Proforma A+H'!$G9:G9/'Proforma A+H'!$T9)} -> 0 | H59: {=SUM('Proforma A+H'!$G9:H9/'Proforma A+H'!$T9)} -> 1 | I59: {=SUM('Proforma A+H'!$G9:I9/'Proforma A+H'!$T9)} -> 1 | J59: {=SUM('Proforma A+H'!$G9:J9/'Proforma A+H'!$T9)} -> 1 | K59: {=SUM('Proforma A+H'!$G9:K9/'Proforma A+H'!$T9)} -> 1 | L59: {=SUM('Proforma A+H'!$G9:L9/'Proforma A+H'!$T9)} -> 1 | M59: {=SUM('Proforma A+H'!$G9:M9/'Proforma A+H'!$T9)} -> 1 | N59: {=SUM('Proforma A+H'!$G9:N9/'Proforma A+H'!$T9)} -> 1 | O59: {=SUM('Proforma A+H'!$G9:O9/'Proforma A+H'!$T9)} -> 1
B60: Event Center Rental Rates | C60: 25000 | E60: Total Rooms | F60: =SUMPRODUCT(F56:F59,$P47:$P50) -> 0 | G60: =SUMPRODUCT(G56:G59,$P47:$P50) -> 0 | H60: =SUMPRODUCT(H56:H59,$P47:$P50) -> 12 | I60: =SUMPRODUCT(I56:I59,$P47:$P50) -> 18 | J60: =SUMPRODUCT(J56:J59,$P47:$P50) -> 50 | K60: =SUMPRODUCT(K56:K59,$P47:$P50) -> 62 | L60: =SUMPRODUCT(L56:L59,$P47:$P50) -> 74 | M60: =SUMPRODUCT(M56:M59,$P47:$P50) -> 80 | ... O60: =SUMPRODUCT(O56:O59,$P47:$P50) -> 80
B61: Event Center Rent Growth Rate | C61: 0.03
B62: Daily/ Weekend Rental Schedule | C62: 1
B63: Event Rental Start | C63: 47119
B64: Event Rental Finish | C64: 47483
B65: Event Rental Days | C65: {=IF(C62=1,SUMPRODUCT(--(WEEKDAY(ROW(INDIRECT(C63&":"&C64)),2)>5)),C64-C63)} -> 104
B66: Months | C66: =(YEAR(C64)-YEAR(C63))*12+(MONTH(C64)-MONTH(C63)+1) -> 12
B67: F&B Commission | C67: 0.1
B68: Events COS | C68: 40000
B70: Minor Operating Departments
B71: MOD Revenue (% Room Revenue) | C71: 0 | E71: BMR to handle all recreation ops…consider adding a commission for booking
B72: MOD COS (% MOD Revenue) | C72: 0
B74: Expenses
B75: Admin & General Ops (% of GOI) | C75: 0.16
B76: Sales & Marketing (% of Room Revenue) | C76: 0.06
B77: POMEC (% of Room Revenue) | C77: 0.06
B78: Energy (% of Room Revenue) | C78: 0.04
NJ89: 0
B103: 1 | C103: Weekend
B104: 0 | C104: Daily

Sheet Exhibits
B4: CLARENDON - OVERALL DEVELOPMENT: PROFORMA | H4: =B4 -> CLARENDON - OVERALL DEVELOPMENT: PROFORMA
B5: PROFORMA - SOURCES & USES SUMMARY | H5: PROFORMA - SOURCES & USES PRE-REVENUE
B6: SOURCES | C6: $ | D6: $/SF | E6: Per Home | F6: % Total | H6: =B6 -> SOURCES | I6: $ | J6: $/SF | K6: Per Home | L6: % Total
B7: =B39 -> SPONSOR - EQUITY CAPITAL | C7: =C39+C70 -> 400000 | F7: =C7/$C$17 -> #VALUE! | H7: =B7 -> SPONSOR - EQUITY CAPITAL | I7: =C7 -> 400000 | L7: =I7/$I$17 -> #VALUE!
B8: =B40 -> LP - EQUITY CAPITAL | C8: =C40+C71 -> 15000000 | F8: =C8/$C$17 -> #VALUE! | H8: =B8 -> LP - EQUITY CAPITAL | I8: =C8 -> 15000000 | L8: =I8/$I$17 -> #VALUE!
B9: =B41 -> SELLER CARRYBACK | C9: =C41+C71 -> 0 | F9: =C9/$C$17 -> #VALUE! | H9: =B9 -> SELLER CARRYBACK | I9: =C9 -> 0 | L9: =I9/$I$17 -> #VALUE!
B10: =B42 -> EB5 - MEZZ DEBT | C10: =C42+C72 -> #VALUE! | F10: =C10/$C$17 -> #VALUE! | H10: =B10 -> EB5 - MEZZ DEBT | I10: =C10 -> #VALUE! | L10: =I10/$I$17 -> #VALUE!
B11: =B43 -> DEV LOAN | C11: =C43+C73 -> #VALUE! | F11: =C11/$C$17 -> #VALUE! | H11: =B11 -> DEV LOAN | I11: ='Proforma Land+Home'!E220+'Proforma Land+Home'!F220 -> 50115929 | L11: =I11/$I$17 -> #VALUE!
B12: =B44 -> LAND SALE TO AMENITY | C12: =C44 -> 0 | F12: =C12/$C$17 -> #VALUE! | H12: =B12 -> LAND SALE TO AMENITY | I12: =C12 -> 0 | L12: =I12/$I$17 -> #VALUE!
B13: =B45 -> PRESALE REVENUES | C13: =C45 -> 67709709 | F13: =C13/$C$17 -> #VALUE! | L13: =I13/$I$17 -> #VALUE!
B14: =B46 -> UNIT SALES | C14: =C46+C75 -> 3.7390114e+08 | F14: =C14/$C$17 -> #VALUE! | L14: =I14/$I$17 -> #VALUE!
B15: =B74 -> TOTAL NET OPERATING INCOME (NOI) | C15: =C74 -> 28604665 | F15: =C15/$C$17 -> #VALUE! | L15: =I15/$I$17 -> #VALUE!
B16: =B76 -> HOTEL SALE PROCEEDS / DISPOSITION | C16: =C76 -> 1.4914314e+08 | F16: =C16/$C$17 -> #VALUE! | L16: =I16/$I$17 -> #VALUE!
B17: TOTAL SOURCES | C17: =SUM(C7:C16) -> #VALUE! | F17: =C17/$C$17 -> #VALUE! | H17: =B17 -> TOTAL SOURCES | I17: =SUM(I7:I16) -> #VALUE! | L17: =I17/$I$17 -> #VALUE!
B19: USES | C19: $ | D19: $/SF | E19: Per Home | F19: % Total | H19: =B19 -> USES | I19: $ | J19: $/SF | K19: Per Home | L19: % Total
B20: =B50 -> LAND & PROJECT ACQUISITION | C20: =C50+C80 -> #VALUE! | F20: =C20/$C$31 -> #VALUE! | H20: =B20 -> LAND & PROJECT ACQUISITION | I20: =I50+I80 -> #VALUE! | L20: =I20/$I$31 -> #VALUE!
B21: =B51 -> HARD COSTS - SITE, RESTORATION & INFRASTRUCTURE | C21: =C51+C82 -> 20739104 | F21: =C21/$C$31 -> #VALUE! | H21: =B21 -> HARD COSTS - SITE, RESTORATION & INFRASTRUCTURE | I21: =I51+I82 -> 13964533 | L21: =I21/$I$31 -> #VALUE!
B22: =B81 -> TOTAL VERTICAL CONSTRUCTION COSTS | C22: =C52+C81 -> 2.5321538e+08 | F22: =C22/$C$31 -> #VALUE! | H22: =B22 -> TOTAL VERTICAL CONSTRUCTION COSTS | I22: =I52+I81 -> 1.1676776e+08 | L22: =I22/$I$31 -> #VALUE!
B23: =B53 -> SOFT COSTS PROFESSIONALS - FINAL ENTITLEMENTS & SITE INFRA. | C23: =C53+C83 -> 12354530 | F23: =C23/$C$31 -> #VALUE! | H23: =B23 -> SOFT COSTS PROFESSIONALS - FINAL ENTITLEMENTS & SITE INFRA. | I23: =I53+I83 -> 9906180.6 | L23: =I23/$I$31 -> #VALUE!
B24: =B54 -> SOFT COSTS PROFESSIONALS - HOMES | C24: =C54 -> 6121864.1 | F24: =C24/$C$31 -> #VALUE! | H24: =B24 -> SOFT COSTS PROFESSIONALS - HOMES | I24: =I54 -> 2091708.1 | L24: =I24/$I$31 -> #VALUE!
B25: =B55 -> SOFT COSTS - SALES | C25: =C55+C84 -> 14113850 | F25: =C25/$C$31 -> #VALUE! | H25: =B25 -> SOFT COSTS - SALES | I25: =I55+I84 -> 1577500 | L25: =I25/$I$31 -> #VALUE!
B26: =B56 -> SOFT COSTS - TAXES AND INSURANCE | C26: =C56+C85 -> 1584893.3 | F26: =C26/$C$31 -> #VALUE! | H26: =B26 -> SOFT COSTS - TAXES AND INSURANCE | I26: =I56+I85 -> 767702.48 | L26: =I26/$I$31 -> #VALUE!
B27: =B57 -> SOFT COSTS - MUNICIPALITY FEES | C27: =C57+C86 -> 2286123.4 | F27: =C27/$C$31 -> #VALUE! | H27: =B27 -> SOFT COSTS - MUNICIPALITY FEES | I27: =I57+I86 -> 806661.07 | L27: =I27/$I$31 -> #VALUE!
B28: =B58 -> DEVELOPMENT FEES | C28: =C58+C87 -> 18496362 | F28: =C28/$C$31 -> #VALUE! | H28: =B28 -> DEVELOPMENT FEES | I28: =I58+I87 -> 5150109.4 | L28: =I28/$I$31 -> #VALUE!
B29: =B59 -> FINANCING COSTS & REPAYMENT | C29: =C59+C88 -> #VALUE! | F29: =C29/$C$31 -> #VALUE! | H29: =B29 -> FINANCING COSTS & REPAYMENT | I29: =I59+I88 -> #VALUE! | L29: =I29/$I$31 -> #VALUE!
B30: =B60 -> DISTRIBUTIONS | C30: =C60+C89 -> #VALUE! | F30: =C30/$C$31 -> #VALUE! | H30: WORKING CAPITAL | I30: =I31-SUM(I20:I29) -> #VALUE! | L30: =I30/$I$31 -> #VALUE!
B31: TOTAL USES | C31: =SUM(C20:C30) -> #VALUE! | F31: =C31/$C$31 -> #VALUE! | H31: =B31 -> TOTAL USES | I31: =I17 -> #VALUE! | L31: =I31/$I$31 -> #VALUE!
F32: =C32/$C$31 -> #VALUE!
B36: CLARENDON - RESI DEVELOPMENT: PROFORMA | H36: =B36 -> CLARENDON - RESI DEVELOPMENT: PROFORMA
B37: PROFORMA - SOURCES & USES SUMMARY | D37: ='Proforma Land+Home'!$D$18 -> 158750 | E37: ='Proforma Land+Home'!$R$17 -> 45 | H37: PROFORMA - SOURCES & USES PRE-REVENUE (Year 0-1)
B38: SOURCES | C38: $ | D38: $/SF | E38: Per Home | F38: % Total | H38: =B38 -> SOURCES | I38: $ | J38: $/SF | K38: Per Home | L38: % Total
B39: ='Proforma Land+Home'!B216 -> SPONSOR - EQUITY CAPITAL | C39: ='Proforma Land+Home'!R216 -> 400000 | D39: =C39/'Proforma Land+Home'!$D$18 -> 2.519685 | E39: =C39/'Proforma Land+Home'!$R$17 -> 8888.8889 | F39: =C39/$C$47 -> 0.00091959703 | H39: =B39 -> SPONSOR - EQUITY CAPITAL | I39: =C39 -> 400000 | J39: =I39/$D$37 -> 2.519685 | K39: =I39/$E$37 -> 8888.8889 | L39: =I39/$I$47 -> 0.0048154039
B40: ='Proforma Land+Home'!B217 -> LP - EQUITY CAPITAL | C40: ='Proforma Land+Home'!R217 -> 15000000 | D40: =C40/'Proforma Land+Home'!$D$18 -> 94.488189 | E40: =C40/'Proforma Land+Home'!$R$17 -> 333333.33 | F40: =C40/$C$47 -> 0.034484889 | H40: =B40 -> LP - EQUITY CAPITAL | I40: =C40 -> 15000000 | J40: =I40/$D$37 -> 94.488189 | K40: =I40/$E$37 -> 333333.33 | L40: =I40/$I$47 -> 0.18057765
B41: ='Proforma Land+Home'!B218 -> SELLER CARRYBACK | C41: ='Proforma Land+Home'!R218 -> 0 | D41: =C41/'Proforma Land+Home'!$D$18 -> 0 | E41: =C41/'Proforma Land+Home'!$R$17 -> 0 | F41: =C41/$C$47 -> 0 | H41: =B41 -> SELLER CARRYBACK | I41: =C41 -> 0 | J41: =I41/$D$37 -> 0 | K41: =I41/$E$37 -> 0 | L41: =I41/$I$47 -> 0
B42: ='Proforma Land+Home'!B219 -> EB5 - MEZZ DEBT | C42: ='Proforma Land+Home'!R219 -> 0 | D42: =C42/'Proforma Land+Home'!$D$18 -> 0 | E42: =C42/'Proforma Land+Home'!$R$17 -> 0 | F42: =C42/$C$47 -> 0 | H42: =B42 -> EB5 - MEZZ DEBT | I42: =SUM('Proforma Land+Home'!E219:F219) -> 0 | J42: =I42/$D$37 -> 0 | K42: =I42/$E$37 -> 0 | L42: =I42/$I$47 -> 0
B43: ='Proforma Land+Home'!B220 -> DEV LOAN | C43: ='Proforma Land+Home'!R220 -> 67666761 | D43: =C43/'Proforma Land+Home'!$D$18 -> 426.24731 | E43: =C43/'Proforma Land+Home'!$R$17 -> 1503705.8 | F43: =C43/$C$47 -> 0.15556538 | H43: =B43 -> DEV LOAN | I43: =C43 -> 67666761 | J43: =I43/$D$37 -> 426.24731 | K43: =I43/$E$37 -> 1503705.8 | L43: =I43/$I$47 -> 0.81460695
B44: ='Proforma Land+Home'!B221 -> LAND SALE TO AMENITY | C44: ='Proforma Land+Home'!R221 -> 0 | D44: =C44/'Proforma Land+Home'!$D$18 -> 0 | E44: =C44/'Proforma Land+Home'!$R$17 -> 0 | F44: =C44/$C$47 -> 0 | H44: =B44 -> LAND SALE TO AMENITY | I44: =C44 -> 0 | J44: =I44/$D$37 -> 0 | K44: =I44/$E$37 -> 0 | L44: =I44/$I$47 -> 0
B45: ='Proforma Land+Home'!B222 -> PRESALE REVENUES | C45: ='Proforma Land+Home'!R222 -> 67709709 | D45: =C45/'Proforma Land+Home'!$D$18 -> 426.51785 | E45: =C45/'Proforma Land+Home'!$R$17 -> 1504660.2 | F45: =C45/$C$47 -> 0.15566412
B46: ='Proforma Land+Home'!B223 -> UNIT SALES | C46: ='Proforma Land+Home'!R223 -> 2.8419666e+08 | D46: =C46/'Proforma Land+Home'!$D$18 -> 1790.2152 | E46: =C46/'Proforma Land+Home'!$R$17 -> 6315481.4 | F46: =C46/$C$47 -> 0.65336601
B47: ='Proforma Land+Home'!B224 -> TOTAL SOURCES | C47: ='Proforma Land+Home'!R224 -> 4.3497313e+08 | D47: =C47/'Proforma Land+Home'!$D$18 -> 2739.9882 | E47: =C47/'Proforma Land+Home'!$R$17 -> 9666069.6 | F47: =E47/$E$47 -> 1 | H47: =B47 -> TOTAL SOURCES | I47: =SUM(I39:I46) -> 83066761 | J47: =I47/$D$37 -> 523.25518 | K47: =I47/$E$37 -> 1845928 | L47: =I47/$I$47 -> 1
B49: USES | C49: $ | D49: $/SF | E49: Per Home | F49: % Total | H49: =B49 -> USES | I49: $ | J49: $/SF | K49: Per Home | L49: % Total
B50: ='Proforma Land+Home'!B227 -> LAND & PROJECT ACQUISITION | C50: ='Proforma Land+Home'!R227 -> 18977750 | D50: =C50/'Proforma Land+Home'!$D$18 -> 119.54488 | E50: =C50/'Proforma Land+Home'!$R$17 -> 421727.78 | F50: =E50/$E$61 -> 0.043629706 | H50: ='Proforma Land+Home'!B227 -> LAND & PROJECT ACQUISITION | I50: =SUM('Proforma Land+Home'!E227:F227) -> 18977750 | J50: =I50/$D$37 -> 119.54488 | K50: =I50/$E$37 -> 421727.78 | L50: =I50/$I$61 -> 0.22846383
B51: ='Proforma Land+Home'!B228 -> HARD COSTS - SITE, RESTORATION & INFRASTRUCTURE | C51: ='Proforma Land+Home'!R228 -> 8702853.8 | D51: =C51/'Proforma Land+Home'!$D$18 -> 54.821126 | E51: =C51/'Proforma Land+Home'!$R$17 -> 193396.75 | F51: =E51/$E$61 -> 0.020007796 | H51: ='Proforma Land+Home'!B228 -> HARD COSTS - SITE, RESTORATION & INFRASTRUCTURE | I51: =SUM('Proforma Land+Home'!E228:F228) -> 5898595.6 | J51: =I51/$D$37 -> 37.156508 | K51: =I51/$E$37 -> 131079.9 | L51: =I51/$I$61 -> 0.0710103
B52: ='Proforma Land+Home'!B229 -> HARD COSTS - HOMES | C52: ='Proforma Land+Home'!R229 -> 1.6473103e+08 | D52: =C52/'Proforma Land+Home'!$D$18 -> 1037.6758 | E52: =C52/'Proforma Land+Home'!$R$17 -> 3660689.5 | F52: =E52/$E$61 -> 0.37871541 | H52: ='Proforma Land+Home'!B229 -> HARD COSTS - HOMES | I52: =SUM('Proforma Land+Home'!E229:F229) -> 44335000 | J52: =I52/$D$37 -> 279.27559 | K52: =I52/$E$37 -> 985222.22 | L52: =I52/$I$61 -> 0.53372733
B53: ='Proforma Land+Home'!B230 -> SOFT COSTS PROFESSIONALS - FINAL ENTITLEMENTS & SITE INFRA. | C53: ='Proforma Land+Home'!R230 -> 3773315.6 | D53: =C53/'Proforma Land+Home'!$D$18 -> 23.768917 | E53: =C53/'Proforma Land+Home'!$R$17 -> 83851.458 | F53: =E53/$E$61 -> 0.0086748246 | H53: ='Proforma Land+Home'!B230 -> SOFT COSTS PROFESSIONALS - FINAL ENTITLEMENTS & SITE INFRA. | I53: =SUM('Proforma Land+Home'!E230:F230) -> 2485268 | J53: =I53/$D$37 -> 15.655231 | K53: =I53/$E$37 -> 55228.177 | L53: =I53/$I$61 -> 0.029918922
B54: ='Proforma Land+Home'!B231 -> SOFT COSTS PROFESSIONALS - HOMES | C54: ='Proforma Land+Home'!R231 -> 6121864.1 | D54: =C54/'Proforma Land+Home'!$D$18 -> 38.562923 | E54: =C54/'Proforma Land+Home'!$R$17 -> 136041.42 | F54: =E54/$E$61 -> 0.01407412 | H54: ='Proforma Land+Home'!B231 -> SOFT COSTS PROFESSIONALS - HOMES | I54: =SUM('Proforma Land+Home'!E231:F231) -> 2091708.1 | J54: =I54/$D$37 -> 13.176114 | K54: =I54/$E$37 -> 46482.403 | L54: =I54/$I$61 -> 0.025181048
B55: ='Proforma Land+Home'!B232 -> SOFT COSTS - SALES | C55: ='Proforma Land+Home'!R232 -> 13613850 | D55: =C55/'Proforma Land+Home'!$D$18 -> 85.756534 | E55: =C55/'Proforma Land+Home'!$R$17 -> 302529.99 | F55: =E55/$E$61 -> 0.03129814 | H55: ='Proforma Land+Home'!B232 -> SOFT COSTS - SALES | I55: =SUM('Proforma Land+Home'!E232:F232) -> 1477500 | J55: =I55/$D$37 -> 9.3070866 | K55: =I55/$E$37 -> 32833.333 | L55: =I55/$I$61 -> 0.017786898
B56: ='Proforma Land+Home'!B233 -> SOFT COSTS - TAXES AND INSURANCE | C56: ='Proforma Land+Home'!R233 -> 993629.94 | D56: =C56/'Proforma Land+Home'!$D$18 -> 6.2590862 | E56: =C56/'Proforma Land+Home'!$R$17 -> 22080.665 | F56: =E56/$E$61 -> 0.0022843479 | H56: ='Proforma Land+Home'!B233 -> SOFT COSTS - TAXES AND INSURANCE | I56: =SUM('Proforma Land+Home'!E233:F233) -> 298079.65 | J56: =I56/$D$37 -> 1.8776671 | K56: =I56/$E$37 -> 6623.9922 | L56: =I56/$I$61 -> 0.0035884347
B57: ='Proforma Land+Home'!B234 -> SOFT COSTS - MUNICIPALITY FEES | C57: ='Proforma Land+Home'!R234 -> 2064912.5 | D57: =C57/'Proforma Land+Home'!$D$18 -> 13.007323 | E57: =C57/'Proforma Land+Home'!$R$17 -> 45886.944 | F57: =E57/$E$61 -> 0.0047472185 | H57: ='Proforma Land+Home'!B234 -> SOFT COSTS - MUNICIPALITY FEES | I57: =SUM('Proforma Land+Home'!E234:F234) -> 625579.17 | J57: =I57/$D$37 -> 3.9406562 | K57: =I57/$E$37 -> 13901.759 | L57: =I57/$I$61 -> 0.0075310408
B58: ='Proforma Land+Home'!B235 -> DEVELOPMENT FEES | C58: ='Proforma Land+Home'!R235 -> 15183933 | D58: =C58/'Proforma Land+Home'!$D$18 -> 95.646823 | E58: =C58/'Proforma Land+Home'!$R$17 -> 337420.74 | F58: =E58/$E$61 -> 0.03490775 | H58: ='Proforma Land+Home'!B235 -> DEVELOPMENT FEES | I58: =SUM('Proforma Land+Home'!E235:F235) -> 2490000 | J58: =I58/$D$37 -> 15.685039 | K58: =I58/$E$37 -> 55333.333 | L58: =I58/$I$61 -> 0.029975889
B59: ='Proforma Land+Home'!B236 -> FINANCING COSTS & REPAYMENT | C59: ='Proforma Land+Home'!R236 -> 96554041 | D59: =C59/'Proforma Land+Home'!$D$18 -> 608.21443 | E59: =C59/'Proforma Land+Home'!$R$17 -> 2145645.3 | F59: =E59/$E$61 -> 0.22197702 | H59: ='Proforma Land+Home'!B236 -> FINANCING COSTS & REPAYMENT | I59: =SUM('Proforma Land+Home'!E236:F236) -> 11336448 | J59: =I59/$D$37 -> 71.410697 | K59: =I59/$E$37 -> 251921.07 | L59: =I59/$I$61 -> 0.13647394
B60: ='Proforma Land+Home'!B237 -> DISTRIBUTIONS | C60: ='Proforma Land+Home'!R237 -> 1.0425595e+08 | D60: =C60/'Proforma Land+Home'!$D$18 -> 656.73042 | E60: =C60/'Proforma Land+Home'!$R$17 -> 2316799 | F60: =E60/$E$61 -> 0.23968366 | H60: WORKING CAPITAL | I60: =I61-SUM(I50:I59) -> -6949168.1 | J60: =I60/$D$37 -> -43.774287 | K60: =I60/$E$37 -> -154425.96 | L60: =I60/$I$61 -> -0.083657628
B61: TOTAL USES | C61: ='Proforma Land+Home'!R238 -> 4.3497313e+08 | D61: =C61/'Proforma Land+Home'!$D$18 -> 2739.9882 | E61: =C61/'Proforma Land+Home'!$R$17 -> 9666069.6 | F61: =E61/$E$61 -> 1 | H61: ='Proforma Land+Home'!B238 -> TOTAL USES | I61: =I47 -> 83066761 | J61: =I61/$D$37 -> 523.25518 | K61: =I61/$E$37 -> 1845928 | L61: =I61/$I$61 -> 1
B66: ='Proforma A+H'!B1 -> CLARENDON - AMENITY + HOTEL DEVELOPMENT: PROFORMA | H66: ='Proforma A+H'!B1 -> CLARENDON - AMENITY + HOTEL DEVELOPMENT: PROFORMA
B67: PROFORMA - SOURCES & USES SUMMARY | H67: PROFORMA - SOURCES & USES PRE-REVENUE (Year 0-3)
B68: =B38 -> SOURCES | C68: $ | D68: $/SF | F68: % Total | H68: =H38 -> SOURCES | I68: $ | J68: $/SF | L68: % Total
B69: ='Proforma A+H'!B257 -> LAND EQUITY IN 80 ACRES | C69: ='Proforma A+H'!T257 -> 0 | F69: =C69/$C$77 -> #VALUE! | H69: =B69 -> LAND EQUITY IN 80 ACRES | I69: =C69 -> 0 | L69: =I69/$I$77 -> #VALUE!
B70: ='Proforma A+H'!B258 -> MTN ORIGINS - PURSUIT CAPITAL | C70: ='Proforma A+H'!T258 -> 0 | F70: =C70/$C$77 -> #VALUE! | H70: =B70 -> MTN ORIGINS - PURSUIT CAPITAL | I70: =C70 -> 0 | L70: =I70/$I$77 -> #VALUE!
B71: ='Proforma A+H'!B259 -> LP - EQUITY CAPITAL | C71: ='Proforma A+H'!T259 -> 0 | F71: =C71/$C$77 -> #VALUE! | H71: =B71 -> LP - EQUITY CAPITAL | I71: =C71 -> 0 | L71: =I71/$I$77 -> #VALUE!
B72: ='Proforma A+H'!B260 -> EB5 - MEZZ DEBT | C72: ='Proforma A+H'!T260 -> #VALUE! | F72: =C72/$C$77 -> #VALUE! | H72: =B72 -> EB5 - MEZZ DEBT | I72: =C72 -> #VALUE! | L72: =I72/$I$77 -> #VALUE!
B73: ='Proforma A+H'!B261 -> DEV LOAN | C73: ='Proforma A+H'!T261 -> #VALUE! | F73: =C73/$C$77 -> #VALUE! | H73: =B73 -> DEV LOAN | I73: =C73+'Proforma A+H'!J262 -> #VALUE! | L73: =I73/$I$77 -> #VALUE!
B74: ='Proforma A+H'!B262 -> TOTAL NET OPERATING INCOME (NOI) | C74: ='Proforma A+H'!T262 -> 28604665 | F74: =C74/$C$77 -> #VALUE! | I74: ='Proforma A+H'!Z262 -> 0 | L74: =I74/$I$77 -> #VALUE!
B75: ='Proforma A+H'!B263 -> TOTAL UNIT SALES | C75: ='Proforma A+H'!T263 -> 89704477 | F75: =C75/$C$77 -> #VALUE! | I75: ='Proforma A+H'!Z263 -> 0 | L75: =I75/$I$77 -> #VALUE!
B76: ='Proforma A+H'!B264 -> HOTEL SALE PROCEEDS / DISPOSITION | C76: ='Proforma A+H'!T264 -> 1.4914314e+08 | F76: =C76/$C$77 -> #VALUE! | I76: ='Proforma A+H'!Z264 -> 0 | L76: =I76/$I$77 -> #VALUE!
B77: ='Proforma A+H'!B266 -> TOTAL SOURCES | C77: ='Proforma A+H'!T266 -> #VALUE! | F77: =C77/$C$77 -> #VALUE! | H77: =B77 -> TOTAL SOURCES | I77: =SUM(I69:I76) -> #VALUE! | L77: =I77/$I$77 -> #VALUE!
B79: =B49 -> USES | C79: $ | D79: $/SF | F79: % Total | H79: =H49 -> USES | I79: $ | J79: $/SF | L79: % Total
B80: ='Proforma A+H'!B269 -> LAND ACQUISITION COSTS | C80: ='Proforma A+H'!T269 -> #VALUE! | F80: =C80/$C$90 -> #VALUE! | H80: =B80 -> LAND ACQUISITION COSTS | I80: =SUM('Proforma A+H'!G269:J269) -> #VALUE! | L80: =I80/$I$90 -> #VALUE!
B81: ='Proforma A+H'!B270 -> TOTAL VERTICAL CONSTRUCTION COSTS | C81: ='Proforma A+H'!T270 -> 88484355 | F81: =C81/$C$90 -> #VALUE! | H81: =B81 -> TOTAL VERTICAL CONSTRUCTION COSTS | I81: =SUM('Proforma A+H'!G270:J270) -> 72432759 | L81: =I81/$I$90 -> #VALUE!
B82: ='Proforma A+H'!B271 -> HARD COSTS - SITE | C82: ='Proforma A+H'!T271 -> 12036250 | F82: =C82/$C$90 -> #VALUE! | H82: =B82 -> HARD COSTS - SITE | I82: =SUM('Proforma A+H'!G271:J271) -> 8065937.5 | L82: =I82/$I$90 -> #VALUE!
B83: ='Proforma A+H'!B272 -> SOFT COSTS - PROFESSIONALS | C83: ='Proforma A+H'!T272 -> 8581214.1 | F83: =C83/$C$90 -> #VALUE! | H83: =B83 -> SOFT COSTS - PROFESSIONALS | I83: =SUM('Proforma A+H'!G272:J272) -> 7420912.7 | L83: =I83/$I$90 -> #VALUE!
B84: ='Proforma A+H'!B273 -> SOFT COSTS - SALES | C84: ='Proforma A+H'!T273 -> 500000 | F84: =C84/$C$90 -> #VALUE! | H84: =B84 -> SOFT COSTS - SALES | I84: =SUM('Proforma A+H'!G273:J273) -> 100000 | L84: =I84/$I$90 -> #VALUE!
B85: ='Proforma A+H'!B274 -> SOFT COSTS - TAXES AND INSURANCE | C85: ='Proforma A+H'!T274 -> 591263.33 | F85: =C85/$C$90 -> #VALUE! | H85: =B85 -> SOFT COSTS - TAXES AND INSURANCE | I85: =SUM('Proforma A+H'!G274:J274) -> 469622.83 | L85: =I85/$I$90 -> #VALUE!
B86: ='Proforma A+H'!B275 -> SOFT COSTS - MUNICIPALITY FEES | C86: ='Proforma A+H'!T275 -> 221210.89 | F86: =C86/$C$90 -> #VALUE! | H86: =B86 -> SOFT COSTS - MUNICIPALITY FEES | I86: =SUM('Proforma A+H'!G275:J275) -> 181081.9 | L86: =I86/$I$90 -> #VALUE!
B87: ='Proforma A+H'!B276 -> DEVELOPMENT FEES | C87: ='Proforma A+H'!T276 -> 3312428.8 | F87: =C87/$C$90 -> #VALUE! | H87: =B87 -> DEVELOPMENT FEES | I87: =SUM('Proforma A+H'!G276:J276) -> 2660109.4 | L87: =I87/$I$90 -> #VALUE!
B88: ='Proforma A+H'!B277 -> FINANCING COSTS & REPAYMENT | C88: ='Proforma A+H'!T277 -> #VALUE! | F88: =C88/$C$90 -> #VALUE! | H88: =B88 -> FINANCING COSTS & REPAYMENT | I88: =SUM('Proforma A+H'!G277:J277) -> #VALUE! | L88: =I88/$I$90 -> #VALUE!
B89: ='Proforma A+H'!B278 -> DISTRIBUTIONS | C89: ='Proforma A+H'!T278 -> #VALUE! | F89: =C89/$C$90 -> #VALUE! | H89: WORKING CAPITAL | I89: =I90-SUM(I80:I88) -> #VALUE! | L89: =I89/$I$90 -> #VALUE!
B90: ='Proforma A+H'!B280 -> TOTAL USES | C90: ='Proforma A+H'!T280 -> #VALUE! | F90: =C90/$C$90 -> #VALUE! | H90: =B90 -> TOTAL USES | I90: =I77 -> #VALUE! | L90: =I90/$I$90 -> #VALUE!

Sheet COMB CASH FLOWS
B4: COMBINED MONTHLY CASH FLOWS - UNDER DEVELOPMENT

Sheet Combined Returns
B1: CLARENDON - LAND, HOME, AMENITY DEVELOPMENT
B2: Returns Analysis
B4: PROJECT FINANCING ANALYSIS | F4: BUSINESS CASE ANALYSIS
B5: TOTAL PROJECT CAPITAL NEEDS: | D5: ='Returns Land+Home'!D5 -> 83066761 | F5: TOTAL PROJECT REVENUE (less brokers fees): | H5: ='Returns Land+Home'!H5 -> 3.3911752e+08
B6: TOTAL PROJECT VALUE (PV of FINAL BUILD OUT): | D6: ='Returns Land+Home'!D6 -> 279912500 | F6: - TOTAL PROJECT COST: | H6: ='Returns Land+Home'!H6 -> 2.5078657e+08
B7: STARTING SPEC DEVELOPMENT VALUE: | D7: ='Returns Land+Home'!D7 -> 30975000 | F7: = NET PROFIT | H7: ='Returns Land+Home'!H7 -> 88330954
B8: EQUITY to SPEC DEV VALUE (ETV): | D8: ='Returns Land+Home'!D8 -> 0.49717514 | F8: NET PROFIT %: | H8: ='Returns Land+Home'!H8 -> 0.26047299
B9: LOAN to COST (LTC): | D9: ='Returns Land+Home'!D9 -> 0.81460695 | F9: RETURN on EQUITY/CAPTIAL (ROE): | H9: ='Returns Land+Home'!H9 -> 5.7357762
B10: LOAN to VALUE (LTV): | D10: ='Returns Land+Home'!D10 -> 0.11019829
B12: PROJECT RETURNS ANALYSIS
B13: PROJECT NET CASH FLOWS: | D13: ='Returns Land+Home'!D13 -> 88855954
B14: EQUITY MULTIPLE: | D14: ='Returns Land+Home'!D14 -> 6.7698671
B15: MODELED ROI: | D15: ='Returns Land+Home'!D15 -> 5.7698671
B16: PROJECT IRR : | D16: ='Returns Land+Home'!D16 -> 0.53538527
F18: ='Proforma Land+Home'!E3 -> Year 0 | G18: ='Proforma Land+Home'!F3 -> Year 1 | H18: ='Proforma Land+Home'!G3 -> Year 2 | I18: ='Proforma Land+Home'!H3 -> Year 3 | J18: ='Proforma Land+Home'!I3 -> Year 4 | K18: ='Proforma Land+Home'!J3 -> Year 5 | L18: ='Proforma Land+Home'!K3 -> Year 6 | M18: ='Proforma Land+Home'!L3 -> Year 7 | ... R18: ='Proforma Land+Home'!Q3 -> Year 12
F19: ='Proforma Land+Home'!E4 -> 2025 | G19: ='Proforma Land+Home'!F4 -> 2026 | H19: ='Proforma Land+Home'!G4 -> 2027 | I19: ='Proforma Land+Home'!H4 -> 2028 | J19: ='Proforma Land+Home'!I4 -> 2029 | K19: ='Proforma Land+Home'!J4 -> 2030 | L19: ='Proforma Land+Home'!K4 -> 2031 | M19: ='Proforma Land+Home'!L4 -> 2032 | ... R19: ='Proforma Land+Home'!Q4 -> 2037
B20: SUMMARY OF RETURNS | F20: ='Proforma Land+Home'!E5 -> 45658 | G20: ='Proforma Land+Home'!F5 -> 46023 | H20: ='Proforma Land+Home'!G5 -> 46388 | I20: ='Proforma Land+Home'!H5 -> 46753 | J20: ='Proforma Land+Home'!I5 -> 47119 | K20: ='Proforma Land+Home'!J5 -> 47484 | L20: ='Proforma Land+Home'!K5 -> 47849 | M20: ='Proforma Land+Home'!L5 -> 48214 | ... R20: ='Proforma Land+Home'!Q5 -> 50040
B21: Wondership LP Returns
B22: Capital Return | D22: =SUM(F22:R22) -> 20940638 | F22: ='Returns Land+Home'!F22+'Returns A+H'!F22 -> 0 | G22: ='Returns Land+Home'!G22+'Returns A+H'!G22 -> 0 | H22: ='Returns Land+Home'!H22+'Returns A+H'!H22 -> 1968762.1 | I22: ='Returns Land+Home'!I22+'Returns A+H'!I22 -> 6074217.7 | J22: ='Returns Land+Home'!J22+'Returns A+H'!J22 -> 12897658 | K22: ='Returns Land+Home'!K22+'Returns A+H'!K22 -> 0 | L22: ='Returns Land+Home'!L22+'Returns A+H'!L22 -> 0 | M22: ='Returns Land+Home'!M22+'Returns A+H'!M22 -> 0 | ... R22: ='Returns Land+Home'!R22+'Returns A+H'!R22 -> 0
B23: Profit Split | D23: =SUM(F23:R23) -> #VALUE! | F23: ='Returns Land+Home'!F23+'Returns A+H'!F23 -> 0 | G23: ='Returns Land+Home'!G23+'Returns A+H'!G23 -> 0 | H23: ='Returns Land+Home'!H23+'Returns A+H'!H23 -> 0 | I23: ='Returns Land+Home'!I23+'Returns A+H'!I23 -> 0 | J23: ='Returns Land+Home'!J23+'Returns A+H'!J23 -> 22249737 | K23: ='Returns Land+Home'!K23+'Returns A+H'!K23 -> 2681101.7 | L23: ='Returns Land+Home'!L23+'Returns A+H'!L23 -> 19243076 | M23: ='Returns Land+Home'!M23+'Returns A+H'!M23 -> #VALUE! | ... R23: ='Returns Land+Home'!R23+'Returns A+H'!R23 -> 0
B24: Total Distributions | D24: =SUM(F24:R24) -> #VALUE! | F24: =F22+F23 -> 0 | G24: =G22+G23 -> 0 | H24: =H22+H23 -> 1968762.1 | I24: =I22+I23 -> 6074217.7 | J24: =J22+J23 -> 35147395 | K24: =K22+K23 -> 2681101.7 | L24: =L22+L23 -> 19243076 | M24: =M22+M23 -> #VALUE! | ... R24: =R22+R23 -> 0
B25: Total Contributions | D25: =SUM(F25:R25) -> 15000000 | F25: ='Returns Land+Home'!F25+'Returns A+H'!F25 -> 15000000 | G25: ='Returns Land+Home'!G25+'Returns A+H'!G25 -> 0 | H25: ='Returns Land+Home'!H25+'Returns A+H'!H25 -> 0
B26: Net Profit / Cash Flows | D26: =SUM(F26:R26) -> #VALUE! | F26: =F24-F25 -> -15000000 | G26: =G24-G25 -> 0 | H26: =H24-H25 -> 1968762.1 | I26: =I24-I25 -> 6074217.7 | J26: =J24-J25 -> 35147395 | K26: =K24-K25 -> 2681101.7 | L26: =L24-L25 -> 19243076 | M26: =M24-M25 -> #VALUE! | ... R26: =R24-R25 -> 0
B27: IRR | F27: =XIRR(G26:R26,G20:R20) -> #VALUE!
B28: Equity Multiple | F28: =SUMIF(F26:R26,">0")/-SUMIF(F26:R26,"<0") -> 4.3409702
B29: Cumulative (Equity) Cash Position | F29: =F26+E29 -> -15000000 | G29: =G26+F29 -> -15000000 | H29: =H26+G29 -> -13031238 | I29: =I26+H29 -> -6957020.3 | J29: =J26+I29 -> 28190375 | K29: =K26+J29 -> 30871476 | L29: =L26+K29 -> 50114552 | M29: =M26+L29 -> #VALUE! | ... R29: =R26+Q29 -> #VALUE!
B31: MO LP Returns
B32: Capital Return + Pref | F32: ='Returns Land+Home'!F32+'Returns A+H'!F32 -> 0 | G32: ='Returns Land+Home'!G32+'Returns A+H'!G32 -> 0 | H32: ='Returns Land+Home'!H32+'Returns A+H'!H32 -> 52500.322 | I32: ='Returns Land+Home'!I32+'Returns A+H'!I32 -> 161979.14 | J32: ='Returns Land+Home'!J32+'Returns A+H'!J32 -> #VALUE! | K32: ='Returns Land+Home'!K32+'Returns A+H'!K32 -> #VALUE! | L32: ='Returns Land+Home'!L32+'Returns A+H'!L32 -> #VALUE! | M32: ='Returns Land+Home'!M32+'Returns A+H'!M32 -> #VALUE! | ... R32: ='Returns Land+Home'!R32+'Returns A+H'!R32 -> 0
B33: Profit Split | F33: ='Returns Land+Home'!F33+'Returns A+H'!F33 -> 0 | G33: ='Returns Land+Home'!G33+'Returns A+H'!G33 -> 0 | H33: ='Returns Land+Home'!H33+'Returns A+H'!H33 -> 0 | I33: ='Returns Land+Home'!I33+'Returns A+H'!I33 -> 0 | J33: ='Returns Land+Home'!J33+'Returns A+H'!J33 -> #VALUE! | K33: ='Returns Land+Home'!K33+'Returns A+H'!K33 -> #VALUE! | L33: ='Returns Land+Home'!L33+'Returns A+H'!L33 -> #VALUE! | M33: ='Returns Land+Home'!M33+'Returns A+H'!M33 -> #VALUE! | ... R33: ='Returns Land+Home'!R33+'Returns A+H'!R33 -> 0
B34: Total Distributions | D34: =SUM(F34:R34) -> #VALUE! | F34: =SUM(F32:F33) -> 0 | G34: =SUM(G32:G33) -> 0 | H34: =SUM(H32:H33) -> 52500.322 | I34: =SUM(I32:I33) -> 161979.14 | J34: =SUM(J32:J33) -> #VALUE! | K34: =SUM(K32:K33) -> #VALUE! | L34: =SUM(L32:L33) -> #VALUE! | M34: =SUM(M32:M33) -> #VALUE! | ... R34: =SUM(R32:R33) -> 0
B35: Total Contributions | D35: =SUM(F35:R35) -> 400000 | F35: ='Returns Land+Home'!F35+'Returns A+H'!F35 -> 400000 | G35: ='Returns Land+Home'!G35+'Returns A+H'!G35 -> 0 | H35: ='Returns Land+Home'!H35+'Returns A+H'!H35 -> 0
B36: Net Profit / Cash Flows | D36: =SUM(F36:R36) -> #VALUE! | F36: =F34-F35 -> -400000 | G36: =G34-G35 -> 0 | H36: =H34-H35 -> 52500.322 | I36: =I34-I35 -> 161979.14 | J36: =J34-J35 -> #VALUE! | K36: =K34-K35 -> #VALUE! | L36: =L34-L35 -> #VALUE! | M36: =M34-M35 -> #VALUE! | ... R36: =R34-R35 -> 0
B37: IRR | F37: =XIRR(F36:R36,F20:R20) -> #VALUE!
B38: Equity Multiple | F38: =SUMIF(F36:R36,">0")/-SUMIF(F36:R36,"<0") -> 0.53619865
B39: Cumulative (Equity) Cash Position | F39: =F36+E39 -> -400000 | G39: =G36+F39 -> -400000 | H39: =H36+G39 -> -347499.68 | I39: =I36+H39 -> -185520.54 | J39: =J36+I39 -> #VALUE! | K39: =K36+J39 -> #VALUE! | L39: =L36+K39 -> #VALUE! | M39: =M36+L39 -> #VALUE! | ... R39: =R36+Q39 -> #VALUE!
B41: MO/Wondership JV GP Returns
B42: Total Distributions | D42: =SUM(F42:R42) -> #VALUE! | F42: ='Returns Land+Home'!F42+'Returns A+H'!F42 -> 0 | G42: ='Returns Land+Home'!G42+'Returns A+H'!G42 -> 0 | H42: ='Returns Land+Home'!H42+'Returns A+H'!H42 -> 0 | I42: ='Returns Land+Home'!I42+'Returns A+H'!I42 -> 0 | J42: ='Returns Land+Home'!J42+'Returns A+H'!J42 -> 14896191 | K42: ='Returns Land+Home'!K42+'Returns A+H'!K42 -> 2752597.8 | L42: ='Returns Land+Home'!L42+'Returns A+H'!L42 -> 19756225 | M42: ='Returns Land+Home'!M42+'Returns A+H'!M42 -> #VALUE! | ... R42: ='Returns Land+Home'!R42+'Returns A+H'!R42 -> 0
B43: ='Proforma Land+Home'!B138 -> Developer Overhead | D43: =SUM(F43:R43) -> #REF! | F43: ='Returns Land+Home'!#REF!+'Returns A+H'!F43 -> #REF! | G43: ='Returns Land+Home'!#REF!+'Returns A+H'!G43 -> #REF! | H43: ='Returns Land+Home'!#REF!+'Returns A+H'!H43 -> #REF! | I43: ='Returns Land+Home'!#REF!+'Returns A+H'!I43 -> #REF! | J43: ='Returns Land+Home'!#REF!+'Returns A+H'!J43 -> #REF! | K43: ='Returns Land+Home'!#REF!+'Returns A+H'!K43 -> #REF! | L43: ='Returns Land+Home'!#REF!+'Returns A+H'!L43 -> #REF! | M43: ='Returns Land+Home'!#REF!+'Returns A+H'!M43 -> #REF! | ... R43: ='Returns Land+Home'!#REF!+'Returns A+H'!R43 -> #REF!
B44: ='Proforma Land+Home'!B139 -> Disposition Fees | D44: =SUM(F44:R44) -> #REF! | F44: ='Returns Land+Home'!#REF! -> #REF! | G44: ='Returns Land+Home'!#REF! -> #REF! | H44: ='Returns Land+Home'!#REF! -> #REF! | I44: ='Returns Land+Home'!#REF! -> #REF! | J44: ='Returns Land+Home'!#REF! -> #REF! | K44: ='Returns Land+Home'!#REF! -> #REF! | L44: ='Returns Land+Home'!#REF! -> #REF! | M44: ='Returns Land+Home'!#REF! -> #REF! | ... R44: ='Returns Land+Home'!#REF! -> #REF!
B45: Net Profit / Cash Flows | D45: =SUM(F45:R45) -> #REF! | F45: =SUM(F42:F44) -> #REF! | G45: =SUM(G42:G44) -> #REF! | H45: =SUM(H42:H44) -> #REF! | I45: =SUM(I42:I44) -> #REF! | J45: =SUM(J42:J44) -> #REF! | K45: =SUM(K42:K44) -> #REF! | L45: =SUM(L42:L44) -> #REF! | M45: =SUM(M42:M44) -> #VALUE! | ... R45: =SUM(R42:R44) -> #REF!
B46: Wondership Portion | C46: =Assumptions!K11 -> 0 | D46: =SUM(F46:R46) -> #REF! | F46: =F45*$C$46 -> #REF! | G46: =G45*$C$46 -> #REF! | H46: =H45*$C$46 -> #REF! | I46: =I45*$C$46 -> #REF! | J46: =J45*$C$46 -> #REF! | K46: =K45*$C$46 -> #REF! | L46: =L45*$C$46 -> #REF! | M46: =M45*$C$46 -> #VALUE! | ... R46: =R45*$C$46 -> #REF!
B47: MO Portion | C47: =1-C46 -> 1 | D47: =SUM(F47:R47) -> #REF! | F47: =F45*$C$47 -> #REF! | G47: =G45*$C$47 -> #REF! | H47: =H45*$C$47 -> #REF! | I47: =I45*$C$47 -> #REF! | J47: =J45*$C$47 -> #REF! | K47: =K45*$C$47 -> #REF! | L47: =L45*$C$47 -> #REF! | M47: =M45*$C$47 -> #VALUE! | ... R47: =R45*$C$47 -> #REF!
B49: Net Cash Flow For Distributions - TOTAL PROJECT RETURNS
B50: Net Levered Before Tax Cash Flow | D50: =SUM(F50:R50) -> #VALUE! | F50: ='Returns Land+Home'!F48+'Returns A+H'!F50 -> -15400000 | G50: ='Returns Land+Home'!G48+'Returns A+H'!G50 -> 0 | H50: ='Returns Land+Home'!H48+'Returns A+H'!H50 -> #VALUE! | I50: ='Returns Land+Home'!I48+'Returns A+H'!I50 -> #VALUE! | J50: ='Returns Land+Home'!J48+'Returns A+H'!J50 -> #VALUE! | K50: ='Returns Land+Home'!K48+'Returns A+H'!K50 -> #VALUE! | L50: ='Returns Land+Home'!L48+'Returns A+H'!L50 -> #VALUE! | M50: ='Returns Land+Home'!M48+'Returns A+H'!M50 -> #VALUE! | ... R50: ='Returns Land+Home'!R48+'Returns A+H'!R50 -> 0
B51: Levered IRR | F51: =XIRR(F50:R50,F20:R20) -> #VALUE!
B52: Equity Multiple | F52: =SUMIF(F50:R50,">0")/-SUMIF(F50:R50,"<0") -> 0
B54: Return of PM EQUITY & Hurdle 1 (Preferred Return)
B55: Net Levered Before Tax Cash Flow | F55: =F50 -> -15400000 | G55: =G50 -> 0 | H55: =H50 -> #VALUE! | I55: =I50 -> #VALUE! | J55: =J50 -> #VALUE! | K55: =K50 -> #VALUE! | L55: =L50 -> #VALUE! | M55: =M50 -> #VALUE! | N55: ='Proforma Land+Home'!M204 -> 0 | O55: ='Proforma Land+Home'!N204 -> 0 | P55: ='Proforma Land+Home'!O204 -> 0 | Q55: ='Proforma Land+Home'!P204 -> 0 | R55: ='Proforma Land+Home'!Q204 -> 0
B56: Preferred returns | F56: =F55 -> -15400000 | G56: =G55 -> 0 | H56: =H55 -> #VALUE! | I56: =I55 -> #VALUE! | J56: =J55 -> #VALUE! | L56: =L55 -> #VALUE! | M56: 27400000 | N56: =N55 -> 0 | O56: =O55 -> 0 | P56: =P55 -> 0 | Q56: =Q55 -> 0 | R56: =R55 -> 0 | T56: =SUM(F56:S56) -> #VALUE!
B57: IRR Check - preferred returns | F57: =XIRR(F56:R56,F48:R48) -> #VALUE! | T57: =U79 -> 0
B58: Remaining Cash Flow for Split | F58: =F55-F56 -> 0 | G58: =G55-G56 -> 0 | H58: =H55-H56 -> #VALUE! | I58: =I55-I56 -> #VALUE! | J58: =J55-J56 -> #VALUE! | K58: =K55-K56 -> #VALUE! | L58: =L55-L56 -> #VALUE! | M58: =M55-M56 -> #VALUE! | ... R58: =R55-R56 -> 0
B59: =T82 -> 0 | C59: =U82 -> 0 | F59: =F$58*$C59 -> 0 | G59: =G$58*$C59 -> 0 | H59: =H$58*$C59 -> #VALUE! | I59: =I$58*$C59 -> #VALUE! | J59: =J$58*$C59 -> #VALUE! | K59: =K$58*$C59 -> #VALUE! | L59: =L$58*$C59 -> #VALUE! | M59: =M$58*$C59 -> #VALUE! | ... R59: =R$58*$C59 -> 0 | T59: =SUM(F59:S59) -> #VALUE!
B60: =T83 -> 0 | C60: =U83 -> 0 | F60: =F$58*$C60 -> 0 | G60: =G$58*$C60 -> 0 | H60: =H$58*$C60 -> #VALUE! | I60: =I$58*$C60 -> #VALUE! | J60: =J$58*$C60 -> #VALUE! | K60: =K$58*$C60 -> #VALUE! | L60: =L$58*$C60 -> #VALUE! | M60: =M$58*$C60 -> #VALUE! | ... R60: =R$58*$C60 -> 0 | T60: =SUM(F60:S60) -> #VALUE!
B62: CM Common Members SHARE
B63: Net Levered Before Tax Cash Flow | F63: =-#REF! -> #REF! | G63: =-#REF! -> #REF! | H63: =-#REF! -> #REF! | I63: =I60 -> #VALUE! | J63: =J60 -> #VALUE! | K63: =K60 -> #VALUE! | L63: =L60 -> #VALUE! | M63: =M60 -> #VALUE! | N63: =N60 -> 0 | O63: =O60 -> 0 | P63: =P60 -> 0 | ... R63: =R60 -> 0
B64: Preferred returns | F64: =F63 -> #REF! | G64: =G63 -> #REF!
B65: IRR Check - preferred returns | F65: =XIRR(F64:R64,F48:R48) -> #REF! | T65: 0.1
B66: Remaining Cash Flow for Split | F66: =F63-F64 -> #REF! | G66: =G63-G64 -> #REF! | H66: =H63-H64 -> #REF! | I66: =I63-I64 -> #VALUE! | J66: =J63-J64 -> #VALUE! | K66: =K63-K64 -> #VALUE! | L66: =L63-L64 -> #VALUE! | M66: =M63-M64 -> #VALUE! | ... R66: =R63-R64 -> 0
B67: CM SPONSOR SHARE | C67: 0 | F67: =F$66*$C67 -> #REF! | G67: =G$66*$C67 -> #REF! | H67: =H$66*$C67 -> #REF! | I67: =I$66*$C67 -> #VALUE! | J67: =J$66*$C67 -> #VALUE! | K67: =K$66*$C67 -> #VALUE! | L67: =L$66*$C67 -> #VALUE! | M67: =M$66*$C67 -> #VALUE! | ... R67: =R$66*$C67 -> 0
B68: CM Common Members MANAGER SHARE | C68: =1-C67 -> 1 | F68: =F$66*$C68 -> #REF! | G68: =G$66*$C68 -> #REF! | H68: =H$66*$C68 -> #REF! | I68: =I$66*$C68 -> #VALUE! | J68: =J$66*$C68 -> #VALUE! | K68: =K$66*$C68 -> #VALUE! | L68: =L$66*$C68 -> #VALUE! | M68: =M$66*$C68 -> #VALUE! | ... R68: =R$66*$C68 -> 0 | T68: =SUM(D68:S68) -> #REF!
V69: CM Share Returns | W69: PM Share Returns | AA69: NiCK | AB69: MTN O | AC69: DeREUS | AD69: TOTAL
B70: Proposed Sponsor Split
B71: Market rate Overhead & Fees Paid to Working Sponsors (e.g. Design Fees, Sales Commision, Asset Management, Common Members Fees, etc.)
B72: Cost of Contributed Capital (e.g. Cash Multiple for Pursuit Dollars, 10% Pref for Equity, etc.)
B73: Equal split of Sponsor Distribution (e.g. 3 ways, 4 ways or 5 ways depending on head count of Sponsor Principals)
T74: NICK | U74: =AA78 -> 0 | V74: =$T$60*U74 -> #VALUE! | W74: =(5000000/$D$25)*$T$59+5000000 -> #VALUE! | Y74: PURSUIT/ENT. | Z74: 0.33333 | AA74: =1/3 -> 0.33333333 | AB74: =1/3 -> 0.33333333 | AC74: =1/3 -> 0.33333333 | AD74: =SUM(AA74:AC74) -> 1

Sheet Proforma Resi
B1: BRUNDAGE - RESI DEVELOPMENT: PROFORMA | AB1: AMU Fee | AC1: =+IF(AC2<0,-$C$193*AC2,0) -> 0 | AD1: =+IF(AD2<0,-$C$193*AD2,0) -> #REF! | AE1: =+IF(AE2<0,-$C$193*AE2,0) -> #REF! | AF1: =+IF(AF2<0,-$C$193*AF2,0) -> #REF! | AG1: =+IF(AG2<0,-$C$193*AG2,0) -> #REF! | AH1: =+IF(AH2<0,-$C$193*AH2,0) -> #REF! | AI1: =+IF(AI2<0,-$C$193*AI2,0) -> #REF! | AJ1: =+IF(AJ2<0,-$C$193*AJ2,0) -> #REF!
B2: Build & Sales Proforma | AB2: Cumulative PM (Equity) Cash Position | AC2: =+'Returns Resi'!F30 -> 0 | AD2: =+'Returns Resi'!G40 -> #REF! | AE2: =+'Returns Resi'!H40 -> #REF! | AF2: =+'Returns Resi'!I40 -> #REF! | AG2: =+'Returns Resi'!J40 -> #REF! | AH2: =+'Returns Resi'!K40 -> #REF! | AI2: =+'Returns Resi'!L40 -> #REF! | AJ2: =+'Returns Resi'!M40 -> #REF!
E3: 0 | F3: =E3+1 -> 1 | G3: =F3+1 -> 2 | H3: =G3+1 -> 3 | I3: =H3+1 -> 4 | J3: =I3+1 -> 5 | K3: =J3+1 -> 6 | L3: =K3+1 -> 7 | M3: =L3+1 -> 8 | ... Q3: =P3+1 -> 12 | AC3: Year 0 | AD3: Year 1 | AE3: Year 2 | AF3: Year 3 | AG3: Year 4 | AH3: Year 5 | AI3: Year 6 | AJ3: Year 7
E4: =Assumptions!C6 -> 2024 | F4: =E4+1 -> 2025 | G4: =F4+1 -> 2026 | H4: =G4+1 -> 2027 | I4: =H4+1 -> 2028 | J4: =I4+1 -> 2029 | K4: =J4+1 -> 2030 | L4: =K4+1 -> 2031 | M4: =L4+1 -> 2032 | ... Q4: =P4+1 -> 2036 | R4: TOTALS
C5: Average. Sqft of Lots | D5: Average Unit Size (sf) | E5: 44927 | F5: =E5+365 -> 45292 | G5: =F5+366 -> 45658 | H5: =G5+365 -> 46023 | I5: =H5+365 -> 46388 | J5: =I5+365 -> 46753 | K5: =J5+366 -> 47119 | L5: =K5+365 -> 47484 | M5: =L5+365 -> 47849 | N5: =M5+365 -> 48214 | O5: =N5+365 -> 48579 | P5: =O5+366 -> 48945 | Q5: =P5+365 -> 49310 | S5: Basis per Lot+Unit
A6: Map | B6: Buildout schedule | D6: Unit Size
B7: ='Proforma Resi'!E265 -> Phase 1: Downhill SFR | C7: 10000 | D7: ='Proforma Resi'!G265 -> 2650 | F7: 1 | G7: 1 | H7: 5 | I7: 3 | R7: =SUM(F7:Q7) -> 10 | S7: =D7*F23 -> 3776250 | T7: =R7*S7 -> 37762500 | V7: =SUMPRODUCT(D7,R7) -> 26500
B8: ='Proforma Resi'!E266 -> Phase 1: Uphill SFR | C8: 10000 | D8: ='Proforma Resi'!G266 -> 2405 | F8: 1 | G8: 2 | R8: =SUM(F8:Q8) -> 3 | S8: =D8*F24 -> 3487250 | T8: =R8*S8 -> 10461750 | V8: =SUMPRODUCT(D8,R8) -> 7215
B9: ='Proforma Resi'!E267 -> Phase 1: Uphill/Downhill Duplex | C9: 5000 | D9: ='Proforma Resi'!G267 -> 1783 | F9: 2 | G9: 8 | H9: 4 | I9: 8 | R9: =SUM(F9:Q9) -> 22 | S9: =D9*F25 -> 2451625 | T9: =R9*S9 -> 53935750 | V9: =SUMPRODUCT(D9,R9) -> 39226
B10: ='Proforma Resi'!E268 -> Phase 1: Multi-unit | C10: 5000 | D10: ='Proforma Resi'!G268 -> 1350 | G10: 4 | H10: 4 | R10: =SUM(F10:Q10) -> 8 | S10: =D10*F26 -> 1957500 | T10: =R10*S10 -> 15660000 | V10: =SUMPRODUCT(D10,R10) -> 10800
B11: Total starts | F11: =SUM(F7:F10) -> 4 | G11: =SUM(G7:G10) -> 15 | H11: =SUM(H7:H10) -> 13 | I11: =SUM(I7:I10) -> 11 | J11: =SUM(J7:J10) -> 0 | K11: =SUM(K7:K10) -> 0 | L11: =SUM(L7:L10) -> 0 | M11: =SUM(M7:M10) -> 0 | ... R11: =SUM(R7:R10) -> 43 | S11: TOTAL HOMES | T11: =SUM(T7:T10) -> 117820000 | V11: =SUMPRODUCT(D7:D10,R7:R10) -> 83741 | W11: /sf | X11: =SUM(T7:T10)/V11 -> 1406.9572 | Y11: /sf | Z11: /sf
B12: Total Sellable SQFT | C12: =SUMPRODUCT(C7:C10,R7:R10) -> 280000 | D12: =SUMPRODUCT(D7:D10,R7:R10) -> 83741 | T12: =T11/R11 -> 2740000 | U12: Average
B13: Total Sellable ACRES | C13: =C12/43560 -> 6.4279155
B15: Sales Schedule
B16: =B7 -> Phase 1: Downhill SFR | C16: =R7 -> 10 | F16: 0 | G16: =F7 -> 1 | H16: =G7 -> 1 | I16: =H7 -> 5 | J16: =I7 -> 3 | K16: =J7 -> 0 | L16: =K7 -> 0 | M16: =L7 -> 0 | N16: =M7 -> 0 | ... Q16: =P7 -> 0 | R16: =SUM(F16:Q16) -> 10 | AC16: =+_xlfn.XLOOKUP($T16,$D$23:$D$26,O$23:O$26) -> 2541.4559 | AD16: =+_xlfn.XLOOKUP($T16,$D$23:$D$26,P$23:P$26) -> 2732.0651 | AE16: =+_xlfn.XLOOKUP($T16,$D$23:$D$26,Q$23:Q$26) -> 2936.97
B17: =B8 -> Phase 1: Uphill SFR | C17: =R8 -> 3 | F17: 0 | G17: =F8 -> 1 | H17: =G8 -> 2 | I17: =H8 -> 0 | J17: =I8 -> 0 | K17: =J8 -> 0 | L17: =K8 -> 0 | M17: =L8 -> 0 | N17: =M8 -> 0 | ... Q17: =P8 -> 0 | R17: =SUM(F17:Q17) -> 3 | AC17: =+AC16 -> 2541.4559 | AD17: =+AD16 -> 2732.0651 | AE17: =+AE16 -> 2936.97
B18: =B9 -> Phase 1: Uphill/Downhill Duplex | C18: =R9 -> 22 | F18: 0 | G18: =F9 -> 2 | H18: =G9 -> 8 | I18: =H9 -> 4 | J18: =I9 -> 8 | K18: =J9 -> 0 | L18: =K9 -> 0 | M18: =L9 -> 0 | N18: =M9 -> 0 | ... Q18: =P9 -> 0 | R18: =SUM(F18:Q18) -> 22 | AC18: =+_xlfn.XLOOKUP($T18,$D$23:$D$26,O$23:O$26) -> 2541.4559 | AD18: =+_xlfn.XLOOKUP($T18,$D$23:$D$26,P$23:P$26) -> 2732.0651 | AE18: =+_xlfn.XLOOKUP($T18,$D$23:$D$26,Q$23:Q$26) -> 2936.97
B19: =B10 -> Phase 1: Multi-unit | C19: =R10 -> 8 | F19: 0 | G19: =F10 -> 0 | H19: =G10 -> 4 | I19: =H10 -> 4 | J19: =I10 -> 0 | K19: =J10 -> 0 | L19: =K10 -> 0 | M19: =L10 -> 0 | N19: =M10 -> 0 | ... Q19: =P10 -> 0 | R19: =SUM(F19:Q19) -> 8 | AC19: =+AC18 -> 2541.4559 | AD19: =+AD18 -> 2732.0651 | AE19: =+AE18 -> 2936.97
B20: Total sales | C20: =SUM(C16:C19) -> 43 | F20: =SUM(F16:F19) -> 0 | G20: =SUM(G16:G19) -> 4 | H20: =SUM(H16:H19) -> 15 | I20: =SUM(I16:I19) -> 13 | J20: =SUM(J16:J19) -> 11 | K20: =SUM(K16:K19) -> 0 | L20: =SUM(L16:L19) -> 0 | M20: =SUM(M16:M19) -> 0 | ... R20: =SUM(R16:R19) -> 43
B22: Sales Price Escalation
B23: Phase 1: Large SFR | C23: 0.075 | F23: ='Proforma Resi'!H265 -> 1425 | G23: ='Proforma Resi'!H265 -> 1425 | H23: =G23*(1+$C23) -> 1531.875 | I23: =H23*(1+$C23) -> 1646.7656 | J23: =I23*(1+$C23) -> 1770.273 | K23: =J23*(1+$C23) -> 1903.0435 | L23: =K23*(1+$C23) -> 2045.7718 | M23: =L23*(1+$C23) -> 2199.2047 | N23: =M23*(1+$C$23) -> 2364.145 | O23: =N23*(1+$C$23) -> 2541.4559 | P23: =O23*(1+$C$23) -> 2732.0651 | Q23: =P23*(1+$C$23) -> 2936.97
B24: Phase 1: Small SFR | C24: 0.075 | F24: ='Proforma Resi'!H266 -> 1450 | G24: 1450 | H24: =G24*(1+$C24) -> 1558.75 | I24: =H24*(1+$C24) -> 1675.6562 | J24: =I24*(1+$C24) -> 1801.3305 | K24: =J24*(1+$C24) -> 1936.4303 | L24: =K24*(1+$C24) -> 2081.6625 | M24: =L24*(1+$C24) -> 2237.7872 | N24: =M24*(1+$C$24) -> 2405.6213 | O24: =N24*(1+$C$24) -> 2586.0428 | P24: =O24*(1+$C$24) -> 2779.9961 | Q24: =P24*(1+$C$24) -> 2988.4958
B25: Phase 1: Small Duplex | C25: 0.075 | F25: ='Proforma Resi'!H267 -> 1375 | G25: 1375 | H25: =G25*(1+$C25) -> 1478.125 | I25: =H25*(1+$C25) -> 1588.9844 | J25: =I25*(1+$C25) -> 1708.1582 | K25: =J25*(1+$C25) -> 1836.2701 | L25: =K25*(1+$C25) -> 1973.9903 | M25: =L25*(1+$C25) -> 2122.0396 | N25: =M25*(1+$C$25) -> 2281.1926 | O25: =N25*(1+$C$25) -> 2452.282 | P25: =O25*(1+$C$25) -> 2636.2032 | Q25: =P25*(1+$C$25) -> 2833.9184
B26: Phase 1: Multi-unit | C26: 0.075 | F26: ='Proforma Resi'!H268 -> 1450 | G26: ='Proforma Resi'!H268 -> 1450 | H26: ='Proforma Resi'!H268 -> 1450 | I26: ='Proforma Resi'!H268 -> 1450 | J26: =I26*(1+$C26) -> 1558.75 | K26: =J26*(1+$C26) -> 1675.6562 | L26: =K26*(1+$C26) -> 1801.3305 | M26: =L26*(1+$C26) -> 1936.4303 | N26: =M26*(1+$C$26) -> 2081.6625 | O26: =N26*(1+$C$26) -> 2237.7872 | P26: =O26*(1+$C$26) -> 2405.6213 | Q26: =P26*(1+$C$26) -> 2586.0428
B27: Average Sales $ per Unit | G27: =IFERROR(SUM(F42+G44)/G20,"") -> 3041687.5 | H27: =IFERROR(SUM(G42+H44)/H20,"") -> 2698068.8 | I27: =IFERROR(SUM(H42+I44)/I20,"") -> 3152483.2 | J27: =IFERROR(SUM(I42+J44)/J20,"") -> 3494439.9 | K27: =IFERROR(SUM(J42+K44)/K20,"") | L27: =IFERROR(SUM(K42+L44)/L20,"") | M27: =IFERROR(SUM(L42+M44)/M20,"") | N27: =IFERROR(SUM(M42+N44)/N20,"") | ... Q27: =IFERROR(SUM(P42+Q44)/Q20,"")
B28: SOURCES | T28: Loan / Equity Financing | W28: Project Financing Metrics
B29: CM - PURSUIT CAPITAL | E29: 75000 | L29: 0 | R29: =SUM(E29:Q29) -> 75000 | T29: Year 0-2 Dev Cost | U29: =SUM(E197:G197) -> #REF! | V29: Actual | W29: VALUE OF SPEC DEV | Y29: =SUMPRODUCT(D7:D10,F7:F10,F23:F26) -> 12166750
B30: PM1 - EQUITY CONTRIBUTION (LAND) | F30: $11.7M in LAND CONTRIBUTION SHOWN ON BALANCE SHEET OF DEV LLC | T30: Financing Cost Gross-Up | U30: =U29*(1+Assumptions!#REF!) -> #REF! | V30: =U29+SUMIF(E3:Q3,"<="&Assumptions!G6,'Proforma Resi'!E201:Q201)+R202 -> #REF! | W30: ETV | Y30: =(R32)/Y29 -> #REF!
B31: PM2 - EQUITY (CASH) | F31: =U34-SUM(E29:F29) -> #REF! | L31: 0 | R31: =SUM(E31:Q31) -> #REF! | T31: Year 0-2 Unit Sales | U31: =SUM(E44:G44) -> 12166750 | W31: LTV | Y31: =R35/(Y29+R64+F72+G72) -> #REF!
B32: EQUITY / PROJECT ACQUISITION + ENTITLEMENT | E32: =SUM(E29:E31) -> 75000 | F32: =SUM(F29:F31) -> #REF! | G32: =SUM(G29:G31) -> 0 | H32: =SUM(H29:H31) -> 0 | I32: =SUM(I29:I31) -> 0 | J32: =SUM(J29:J31) -> 0 | K32: =SUM(K29:K31) -> 0 | L32: =SUM(L29:L31) -> 0 | ... R32: =SUM(R29:R31) -> #REF! | T32: LTC | U32: =Assumptions!F7 -> 0.8118774 | W32: LTC Total (INCL LAND VALUE) | Y32: =(R35/(R58+R32+R35)) -> #REF!
T33: Loan Amount | U33: =U30*U32 -> #REF! | V33: Actual
B34: Development Loan | C34: =U33 -> #REF! | E34: 0 | F34: =MAX(F197-F32-F44-E230,0) -> #REF! | G34: =MAX(G197-G32-G44-F230,0) -> #REF! | H34: =MAX(H197-H32-H44-G230,0) -> #REF! | I34: =MAX(I197-I32-I44-H230,0) -> #REF! | J34: =MAX(J197-J32-J44-I230,0) -> #REF! | K34: =MAX(K197-K32-K44-J230,0) -> #REF! | L34: =MAX(L197-L32-L44-K230,0) -> #REF! | M34: =MAX(M197-M32-M44-L230,0) -> #REF! | O34: =MAX(O197-O32-O44-N230,0) -> #REF! | P34: =MAX(P197-P32-P44-O230,0) -> #REF! | Q34: =MAX(Q197-Q32-Q44-P230,0) -> #REF! | R34: =SUM(E34:Q34) -> #REF! | T34: Initial Equity | U34: =U30-U33-C56*0.89 -> #REF! | V34: =U34+C56 -> #REF!
B35: DEBT | E35: =SUM(E34:E34) -> 0 | F35: =SUM(F34:F34) -> #REF! | G35: =SUM(G34:G34) -> #REF! | H35: =SUM(H34:H34) -> #REF! | I35: =SUM(I34:I34) -> #REF! | J35: =SUM(J34:J34) -> #REF! | K35: =SUM(K34:K34) -> #REF! | L35: =SUM(L34:L34) -> #REF! | ... Q35: =SUM(Q34:Q34) -> #REF! | R35: =SUM(E35:Q35) -> #REF!
B37: Construction Start Draw
B38: Foundation Complete Draw
B39: Structure Complete Draw
B40: MEP 4-way Draw
B41: Finishes Start Draw
B42: PRESALE REVENUES | C42: =SUM(C37:C41) -> 0 | E42: =SUM(E37:E41) -> 0 | F42: =SUM(F37:F41) -> 0 | G42: =SUM(G37:G41) -> 0 | H42: =SUM(H37:H41) -> 0 | I42: =SUM(I37:I41) -> 0 | J42: =SUM(J37:J41) -> 0 | K42: =SUM(K37:K41) -> 0 | L42: =SUM(L37:L41) -> 0 | ... P42: =SUM(P37:P41) -> 0 | R42: =SUM(E42:Q42) -> 0 | T42: TOTAL HOME SALES
B43: INFRASTRUCTURE REPAYMENT FROM HOTEL PROFORMA | H43: ='Proforma A+H'!#REF! -> #REF!
B44: UNIT SALES | F44: =(1-$C$42)*SUMPRODUCT(F$16:F$19,$D$7:$D$10,F$23:F$26) -> 0 | G44: =+(1-$C$42)*SUMPRODUCT(G$16:G$19,$D$7:$D$10,G$23:G$26) -> 12166750 | H44: =(1-$C$42)*SUMPRODUCT(H$16:H$19,$D$7:$D$10,H$23:H$26) -> 40471031 | I44: =(1-$C$42)*SUMPRODUCT(I$16:I$19,$D$7:$D$10,I$23:I$26) -> 40982281 | J44: =(1-$C$42)*SUMPRODUCT(J$16:J$19,$D$7:$D$10,J$23:J$26) -> 38438839 | K44: =(1-$C$42)*SUMPRODUCT(K$16:K$19,$D$7:$D$10,K$23:K$26) -> 0 | L44: =(1-$C$42)*SUMPRODUCT(L$16:L$19,$D$7:$D$10,L$23:L$26) -> 0 | M44: =(1-$C$42)*SUMPRODUCT(M$16:M$19,$D$7:$D$10,M$23:M$26) -> 0 | N44: =(1-$C$42)*SUMPRODUCT(N$16:N$19,$D$7:$D$10,N$23:N$26) -> 0 | O44: =(1-$C$42)*SUMPRODUCT(O$16:O$19,$D$7:$D$10,O$23:O$26) -> 0 | ... Q44: =(1-$C$42)*SUMPRODUCT(Q$16:Q$19,$D$7:$D$10,Q$23:Q$26) -> 0 | R44: =SUM(E44:Q44) -> 1.320589e+08
B45: TOTAL SOURCES | E45: =E32+E35+E42+E43+E44 -> 75000 | F45: =F32+F35+F42+F43+F44 -> #REF! | G45: =G32+G35+G42+G43+G44 -> #REF! | H45: =H32+H35+H42+H43+H44 -> #REF! | I45: =I32+I35+I42+I43+I44 -> #REF! | J45: =J32+J35+J42+J43+J44 -> #REF! | K45: =K32+K35+K42+K43+K44 -> #REF! | L45: =L32+L35+L42+L43+L44 -> #REF! | M45: =M32+M35+M42+M43+M44 -> #REF! | N45: =N32+N35+N42+N44 -> 0 | O45: =O32+O35+O42+O44 -> #REF! | P45: =P32+P35+P42+P44 -> #REF! | Q45: =Q32+Q35+Q42+Q44 -> #REF! | R45: =SUM(E45:Q45) -> #REF! | T45: TOTAL SALES | U45: =T46/R11 -> 3071137.2 | V45: Ave. Unit $
T46: =(R42)+R44 -> 1.320589e+08 | U46: =T46/D12 -> 1576.9922 | V46: Ave. $/SF
B47: USES
A48: 01a | B48: LAND & PROJECT ACQUISITION
B49: Asset Acquisition Fee | C49: 0.02 | F49: =C49*C56 -> 300000 | R49: =SUM(E49:L49) -> 300000 | T49: =R49/T46 -> 0.0022717136
B50: Land Downpayment | C50: 0.2 | F50: =Assumptions!Q7*C50 -> 3000000 | R50: =SUM(E50:L50) -> 3000000
B52: Unit Sales Net Profit | C52: ='Proforma Resi'!M267 -> 0.2 | F52: =(F42+F44)*$C$52 -> 0 | G52: =(G42+G44)*$C$52 -> 2433350 | H52: =(H42+H44)*$C$52 -> 8094206.2 | I52: =(I42+I44)*$C$52 -> 8196456.2 | J52: =(J42+J44)*$C$52 -> 7687767.9 | K52: =(K42+K44)*$C$52 -> 0 | L52: =(L42+L44)*$C$52 -> 0 | M52: =(M42+M44)*$C$52 -> 0 | ... Q52: =(Q42+Q44)*$C$52 -> 0 | R52: =SUM(E52:L52) -> 26411780
B53: LESS Phantom Tax | C53: ='Proforma Resi'!M268 -> 0.3 | F53: =F52*$C$53 -> 0 | G53: =G52*$C$53 -> 730005 | H53: =H52*$C$53 -> 2428261.9 | I53: =I52*$C$53 -> 2458936.9 | J53: =J52*$C$53 -> 2306330.4 | K53: =K52*$C$53 -> 0 | L53: =L52*$C$53 -> 0 | M53: =M52*$C$53 -> 0 | ... Q53: =Q52*$C$53 -> 0 | R53: =SUM(E53:L53) -> 7923534.1
B54: Land Repayment | C54: 500000 | D54: Min pmt | G54: =MIN(MAX(G52-G53,$C$54),F56) -> 1703345 | H54: =MIN(MAX(H52-H53,$C$54),G56) -> 5665944.4 | I54: =MIN(MAX(I52-I53,$C$54),H56) -> 4630710.6 | J54: =MIN(MAX(J52-J53,$C$54),I56) -> 0 | K54: =MIN(MAX(K52-K53,$C$54),J56) -> 0 | L54: =MIN(MAX(L52-L53,$C$54),K56) -> 0 | M54: =MIN(MAX(M52-M53,$C$54),L56) -> 0 | N54: =MIN(MAX(N52-N53,$C$54),M56) -> 0 | ... Q54: =MIN(MAX(Q52-Q53,$C$54),P56) -> 0 | R54: =SUM(E54:L54) -> 12000000 | T54: =(R50+R54)/T46 -> 0.11358568 | U54: =Assumptions!Q7 -> 15000000 | V54: Total Land Acquisition
B56: Ending Land Balance | C56: =Assumptions!Q7 -> 15000000 | D56: Land value | F56: =C56-F50 -> 12000000 | G56: =F56-G54 -> 10296655 | H56: =G56-H54 -> 4630710.6 | I56: =H56-I54 -> 0 | J56: =I56-J54 -> 0 | K56: =J56-K54 -> 0 | L56: =K56-L54 -> 0 | M56: =L56-M54 -> 0 | N56: =M56-N54 -> 0 | ... Q56: =P56-Q54 -> 0
B57: Interest Cost | C57: =Assumptions!#REF! -> #REF! | F57: =F56*C57/2 -> #REF! | G57: =F56*$C$57 -> #REF! | H57: =G56*$C$57 -> #REF! | I57: =H56*$C$57 -> #REF! | J57: =I56*$C$57 -> #REF! | K57: =J56*$C$57 -> #REF! | L57: =K56*$C$57 -> #REF! | M57: =L56*$C$57 -> #REF! | N57: =M56*$C$57 -> #REF! | ... Q57: =P56*$C$57 -> #REF! | R57: =SUM(E57:Q57) -> #REF! | T57: =R57/T46 -> #REF!
B58: LAND & PROJECT ACQUISITION | E58: =SUM(E54:E57) -> 0 | F58: =F49+F50+F54+F57 -> #REF! | G58: =G49+G50+G54+G57 -> #REF! | H58: =H49+H50+H54+H57 -> #REF! | I58: =I49+I50+I54+I57 -> #REF! | J58: =J49+J50+J54+J57 -> #REF! | K58: =K49+K50+K54+K57 -> #REF! | L58: =L49+L50+L54+L57 -> #REF! | M58: =M49+M50+M54+M57 -> #REF! | ... Q58: =Q49+Q50+Q54+Q57 -> #REF! | R58: =SUM(E58:Q58) -> #REF! | T58: =+T54+T49+T57 -> #REF!
A60: 02a | B60: HARD COSTS - SITE INFRASTRUCTURE RESORT
B61: Infrastructure per Lot - SFR | C61: =F61/SUM(R7:R8) -> 451765.61 | F61: =(Assumptions!Q9*($T$7/SUM($T$7:$T$8))*Assumptions!P6/Assumptions!P6)/2 -> 5872952.9 | G61: =(Assumptions!Q9*($T$7/SUM($T$7:$T$8))*Assumptions!P6/Assumptions!P6)/2 -> 5872952.9 | H61: INCLUDES: Advanced Waste Water Treatment Plant, Water Main to Parcels, Sewer Main to Parcels, Goose Lake Rd Paving, New Well, Skiway Bridge, Skiway, Misc. | R61: =SUM(E61:P61) -> 11745906
B62: Infrastructure per Lot - Duplex/ Multi-unit | C62: =F62/SUM(R9:R10) -> 54234.903 | F62: =(Assumptions!Q9*($T$8/SUM($T$7:$T$8))*Assumptions!P6/Assumptions!P6)/2 -> 1627047.1 | G62: =(Assumptions!Q9*($T$8/SUM($T$7:$T$8))*Assumptions!P6/Assumptions!P6)/2 -> 1627047.1 | R62: =SUM(E62:P62) -> 3254094.2
B63: Developer Construction Contingency | C63: 0 | E63: =SUM(E61:E62)*$C$63 -> 0 | F63: =SUM(F61:F62)*$C$63 -> 0 | G63: =SUM(G61:G62)*$C$63 -> 0 | H63: =SUM(H61:H62)*$C$63 -> 0 | N63: =SUM(N61:N62)*$C$63 -> 0 | O63: =SUM(O61:O62)*$C$63 -> 0 | P63: =SUM(P61:P62)*$C$63 -> 0 | Q63: =SUM(Q61:Q62)*$C$63 -> 0 | R63: =SUM(E63:Q63) -> 0
B64: =B60 -> HARD COSTS - SITE INFRASTRUCTURE RESORT | E64: =SUM(E61:E63) -> 0 | F64: =SUM(F61:F63) -> 7500000 | G64: =SUM(G61:G63) -> 7500000 | H64: =SUM(H61:H63) -> 0 | I64: =SUM(I61:I63) -> 0 | J64: =SUM(J61:J63) -> 0 | K64: =SUM(K61:K63) -> 0 | L64: =SUM(L61:L63) -> 0 | ... P64: =SUM(P61:P63) -> 0 | R64: =SUM(E64:Q64) -> 15000000 | T64: =R64/$R$11 -> 348837.21 | U64: $/Lot
T65: =(R64-H43)/$T$46 -> #REF! | U65: of Sales
A66: 02a | B66: HARD COSTS - SITE INFRASTRUCTURE INTERNAL ROADS
B67: Infrastructure per Lot - SFR | C67: 85000 | F67: =+(F7+F8)*$C67 -> 170000 | G67: =+(G7+G8)*$C67 -> 255000 | H67: =+(H7+H8)*$C67 -> 425000 | I67: =+(I7+I8)*$C67 -> 255000 | J67: =+(J7+J8)*$C67 -> 0 | K67: =+(K7+K8)*$C67 -> 0 | L67: =+(L7+L8)*$C67 -> 0 | R67: =SUM(E67:P67) -> 1105000
B68: Infrastructure per Lot - Duplex | C68: 65000 | F68: =F9*$C68 -> 130000 | G68: =G9*$C68 -> 520000 | H68: =H9*$C68 -> 260000 | I68: =I9*$C68 -> 520000 | J68: =J9*$C68 -> 0 | K68: =K9*$C68 -> 0 | L68: =L9*$C68 -> 0 | R68: =SUM(E68:P68) -> 1430000
B69: Infrastructure per Lot - Multi-unit | C69: 25000 | F69: =F10*$C69 -> 0 | G69: =G10*$C69 -> 100000 | H69: =H10*$C69 -> 100000 | I69: =I10*$C69 -> 0 | J69: =J10*$C69 -> 0 | K69: =K10*$C69 -> 0 | L69: =L10*$C69 -> 0 | M69: =M10*$C69 -> 0 | ... P69: =P10*$C69 -> 0 | R69: =SUM(E69:P69) -> 200000
B70: Ski Tunnel | C70: 750000 | G70: =C70 -> 750000 | R70: =SUM(E70:P70) -> 750000
B71: Developer Construction Contingency | C71: 0.05 | E71: =SUM(E67:E68)*$C$71 -> 0 | F71: =SUM(F67:F68)*$C$71 -> 15000 | G71: =SUM(G67:G68)*$C$71 -> 38750 | H71: =SUM(H67:H68)*$C$71 -> 34250 | I71: =SUM(I67:I68)*$C$71 -> 38750 | J71: =SUM(J67:J68)*$C$71 -> 0 | K71: =SUM(K67:K68)*$C$71 -> 0 | L71: =SUM(L67:L68)*$C$71 -> 0 | M71: 0 | N71: 0 | O71: 0 | P71: 0 | Q71: 0 | R71: =SUM(E71:Q71) -> 126750
B72: =B66 -> HARD COSTS - SITE INFRASTRUCTURE INTERNAL ROADS | E72: =SUM(E67:E71) -> 0 | F72: =SUM(F67:F71) -> 315000 | G72: =SUM(G67:G71) -> 1663750 | H72: =SUM(H67:H71) -> 819250 | I72: =SUM(I67:I71) -> 813750 | J72: =SUM(J67:J71) -> 0 | K72: =SUM(K67:K71) -> 0 | L72: =SUM(L67:L71) -> 0 | ... P72: =SUM(P67:P71) -> 0 | R72: =SUM(E72:Q72) -> 3611750 | T72: =R72/$R$11 -> 83994.186 | U72: $/unit
T73: =R72/$T$46 -> 0.027349538 | U73: of Sales
A74: 02b | B74: HARD COSTS - HOMES: SFR Large
B75: Infrastructure (Utilities & Driveway) - SFR | C75: 50000 | F75: =((SUM(E$7)*$C75)*0.25)+((SUM(F$7)*$C75)*0.75) -> 37500 | G75: =((SUM(F$7)*$C75)*0.25)+((SUM(G$7)*$C75)*0.75) -> 50000 | H75: =((SUM(G$7)*$C75)*0.25)+((SUM(H$7)*$C75)*0.75) -> 200000 | I75: =((SUM(H$7)*$C75)*0.25)+((SUM(I$7)*$C75)*0.75) -> 175000 | J75: =((SUM(I$7)*$C75)*0.25)+((SUM(J$7)*$C75)*0.75) -> 37500 | K75: =((SUM(J$7)*$C75)*0.25)+((SUM(K$7)*$C75)*0.75) -> 0 | L75: =((SUM(K$7)*$C75)*0.25)+((SUM(L$7)*$C75)*0.75) -> 0 | M75: =((SUM(L$7)*$C75)*0.25)+((SUM(M$7)*$C75)*0.75) -> 0 | ... Q75: =((SUM(P$7)*$C75)*0.25)+((SUM(Q$7)*$C75)*0.75) -> 0 | R75: =SUM(E75:Q75) -> 500000 | T75: =R75/SUM($R$7) -> 50000 | U75: /UNIT | V75: Build Cost $/sf Check
B76: Vertical Construction Costs - SFR | C76: 635 | F76: =(IFERROR(SUMPRODUCT($D$7,E7)*$C76,0)*0.75)+(IFERROR(SUMPRODUCT($D$7,F7)*$C76,0)*0.25) -> 420687.5 | G76: =(IFERROR(SUMPRODUCT($D$7,F7)*$C76,0)*0.75)+(IFERROR(SUMPRODUCT($D$7,G7)*$C76,0)*0.25) -> 1682750 | H76: =(IFERROR(SUMPRODUCT($D$7,G7)*$C76,0)*0.75)+(IFERROR(SUMPRODUCT($D$7,H7)*$C76,0)*0.25) -> 3365500 | I76: =(IFERROR(SUMPRODUCT($D$7,H7)*$C76,0)*0.75)+(IFERROR(SUMPRODUCT($D$7,I7)*$C76,0)*0.25) -> 7572375 | J76: =(IFERROR(SUMPRODUCT($D$7,I7)*$C76,0)*0.75)+(IFERROR(SUMPRODUCT($D$7,J7)*$C76,0)*0.25) -> 3786187.5 | K76: =(IFERROR(SUMPRODUCT($D$7,J7)*$C76,0)*0.75)+(IFERROR(SUMPRODUCT($D$7,K7)*$C76,0)*0.25) -> 0 | L76: =(IFERROR(SUMPRODUCT($D$7,K7)*$C76,0)*0.75)+(IFERROR(SUMPRODUCT($D$7,L7)*$C76,0)*0.25) -> 0 | M76: =(IFERROR(SUMPRODUCT($D$7,L7)*$C76,0)*0.75)+(IFERROR(SUMPRODUCT($D$7,M7)*$C76,0)*0.25) -> 0 | ... Q76: =(IFERROR(SUMPRODUCT($D$7,P7)*$C76,0)*0.75)+(IFERROR(SUMPRODUCT($D$7,Q7)*$C76,0)*0.25) -> 0 | R76: =SUM(E76:Q76) -> 16827500 | T76: =R76/SUM($R$7) -> 1682750 | U76: AVE / UNIT | V76: =(R76)/V7 -> 635
B77: Landscape / Hardscape - SFR | C77: 50000 | F77: =SUM(E7)*$C77 -> 0 | G77: =SUM(F7)*$C77 -> 50000 | H77: =SUM(G7)*$C77 -> 50000 | I77: =SUM(H7)*$C77 -> 250000 | J77: =SUM(I7)*$C77 -> 150000 | K77: =SUM(J7)*$C77 -> 0 | L77: =SUM(K7)*$C77 -> 0 | M77: =SUM(L7)*$C77 -> 0 | ... Q77: =SUM(P7)*$C77 -> 0 | R77: =SUM(E77:Q77) -> 500000 | T77: =R77/SUM($R$7) -> 50000 | U77: /UNIT
B78: Construction Cost Escalation | C78: 0.05 | F78: =SUM(F75:F77,E78)*$C78 -> 22909.375 | G78: =SUM(G75:G77,F78)*$C78 -> 90282.969 | H78: =SUM(H75:H77,G78)*$C78 -> 185289.15 | I78: =SUM(I75:I77,H78)*$C78 -> 409133.21 | J78: =SUM(J75:J77,I78)*$C78 -> 219141.04 | L78: =SUM(L75:L77,K78)*$C78 -> 0 | M78: =SUM(M75:M77,L78)*$C78 -> 0 | R78: =SUM(E78:Q78) -> 926755.73 | T78: =R78/SUM($R$7) -> 92675.573 | U78: AVE / UNIT
B79: Developer Construction Contingency | C79: 0.035 | E79: =SUM(E74:E77)*$C79 -> 0 | F79: =SUM(F74:F78)*$C79 -> 16838.391 | G79: =SUM(G74:G78)*$C79 -> 65556.154 | H79: =SUM(H74:H78)*$C79 -> 133027.62 | I79: =SUM(I74:I78)*$C79 -> 294227.79 | J79: =SUM(J74:J78)*$C79 -> 146749 | K79: =SUM(K74:K78)*$C79 -> 0 | L79: =SUM(L74:L78)*$C79 -> 0 | M79: =SUM(M74:M77)*$C79 -> 0 | N79: =SUM(N74:N77)*$C79 -> 0 | O79: =SUM(O74:O77)*$C79 -> 0 | P79: =SUM(P74:P77)*$C79 -> 0 | Q79: =SUM(Q74:Q77)*$C79 -> 0 | R79: =SUM(E79:Q79) -> 656398.95 | T79: =R79/SUM($R$7) -> 65639.895 | U79: AVE / UNIT | V79: Total Cost $/sf Check
B80: =B74 -> HARD COSTS - HOMES: SFR Large | E80: =SUM(E74:E79) -> 0 | F80: =SUM(F74:F79) -> 497935.27 | G80: =SUM(G74:G79) -> 1938589.1 | H80: =SUM(H74:H79) -> 3933816.8 | I80: =SUM(I74:I79) -> 8700736 | J80: =SUM(J74:J79) -> 4339577.5 | K80: =SUM(K74:K79) -> 0 | L80: =SUM(L74:L79) -> 0 | ... Q80: =SUM(Q74:Q79) -> 0 | R80: =SUM(E80:Q80) -> 19410655 | T80: =R80/SUM($R$7) -> 1941065.5 | U80: AVE / UNIT | V80: =R80/V7 -> 732.47754
T81: {=R80/SUMPRODUCT(D7*F7:Q7*F$23:Q$23)} -> 0.47410556 | U81: of Sales
A82: 02b | B82: HARD COSTS - HOMES: SFR Small
B83: Infrastructure (Utilities & Driveway) - SFR | C83: 50000 | F83: =((SUM(E$8)*$C83)*0.25)+((SUM(F$8)*$C83)*0.75) -> 37500 | G83: =((SUM(F$8)*$C83)*0.25)+((SUM(G$8)*$C83)*0.75) -> 87500 | H83: =((SUM(G$8)*$C83)*0.25)+((SUM(H$8)*$C83)*0.75) -> 25000 | I83: =((SUM(H$8)*$C83)*0.25)+((SUM(I$8)*$C83)*0.75) -> 0 | J83: =((SUM(I$8)*$C83)*0.25)+((SUM(J$8)*$C83)*0.75) -> 0 | K83: =((SUM(J$8)*$C83)*0.25)+((SUM(K$8)*$C83)*0.75) -> 0 | L83: =((SUM(K$8)*$C83)*0.25)+((SUM(L$8)*$C83)*0.75) -> 0 | M83: =((SUM(L$8)*$C83)*0.25)+((SUM(M$8)*$C83)*0.75) -> 0 | ... Q83: =((SUM(P$8)*$C83)*0.25)+((SUM(Q$8)*$C83)*0.75) -> 0 | R83: =SUM(E83:Q83) -> 150000 | T83: =R83/SUM($R$8) -> 50000 | U83: /UNIT | V83: Build Cost $/sf Check
B84: Vertical Construction Costs - SFR | C84: 650 | F84: =(IFERROR((SUMPRODUCT($D$8,E8))*$C84,0)*0.75)+(IFERROR((SUMPRODUCT($D$8,F8))*$C84,0)*0.25) -> 390812.5 | G84: =(IFERROR((SUMPRODUCT($D$8,F8))*$C84,0)*0.75)+(IFERROR((SUMPRODUCT($D$8,G8))*$C84,0)*0.25) -> 1954062.5 | H84: =(IFERROR((SUMPRODUCT($D$8,G8))*$C84,0)*0.75)+(IFERROR((SUMPRODUCT($D$8,H8))*$C84,0)*0.25) -> 2344875 | I84: =(IFERROR((SUMPRODUCT($D$8,H8))*$C84,0)*0.75)+(IFERROR((SUMPRODUCT($D$8,I8))*$C84,0)*0.25) -> 0 | J84: =(IFERROR((SUMPRODUCT($D$8,I8))*$C84,0)*0.75)+(IFERROR((SUMPRODUCT($D$8,J8))*$C84,0)*0.25) -> 0 | K84: =(IFERROR((SUMPRODUCT($D$8,J8))*$C84,0)*0.75)+(IFERROR((SUMPRODUCT($D$8,K8))*$C84,0)*0.25) -> 0 | L84: =(IFERROR((SUMPRODUCT($D$8,K8))*$C84,0)*0.75)+(IFERROR((SUMPRODUCT($D$8,L8))*$C84,0)*0.25) -> 0 | M84: =(IFERROR((SUMPRODUCT($D$8,L8))*$C84,0)*0.75)+(IFERROR((SUMPRODUCT($D$8,M8))*$C84,0)*0.25) -> 0 | ... Q84: =(IFERROR((SUMPRODUCT($D$8,P8))*$C84,0)*0.75)+(IFERROR((SUMPRODUCT($D$8,Q8))*$C84,0)*0.25) -> 0 | R84: =SUM(E84:Q84) -> 4689750 | T84: =R84/SUM($R$8) -> 1563250 | U84: AVE / UNIT | V84: =(R84)/V8 -> 650
B85: Landscape / Hardscape - SFR | C85: 50000 | G85: =SUM(F8*$C85) -> 50000 | H85: =SUM(G8*$C85) -> 100000 | I85: =SUM(H8*$C85) -> 0 | J85: =SUM(I8*$C85) -> 0 | K85: =SUM(J8*$C85) -> 0 | L85: =SUM(K8*$C85) -> 0 | M85: =SUM(L8*$C85) -> 0 | N85: =SUM(M8*$C85) -> 0 | ... Q85: =SUM(P8*$C85) -> 0 | R85: =SUM(E85:Q85) -> 150000 | T85: =R85/SUM($R$8) -> 50000 | U85: /UNIT
B86: Construction Cost Escalation | C86: 0.05 | F86: =SUM(F83:F85,E86)*$C86 -> 21415.625 | G86: =SUM(G83:G85,F86)*$C86 -> 105648.91 | H86: =SUM(H83:H85,G86)*$C86 -> 128776.2 | I86: =SUM(I83:I85,H86)*$C86 -> 6438.8098 | J86: =SUM(J83:J85,I86)*$C86 -> 321.94049 | R86: =SUM(E86:Q86) -> 262601.48 | T86: =R86/SUM($R$8) -> 87533.826 | U86: AVE / UNIT
B87: Developer Construction Contingency | C87: 0.035 | E87: =SUM(E82:E85)*$C87 -> 0 | F87: =SUM(F82:F86)*$C87 -> 15740.484 | G87: =SUM(G82:G86)*$C87 -> 76902.399 | H87: =SUM(H82:H86)*$C87 -> 90952.792 | I87: =SUM(I82:I86)*$C87 -> 225.35834 | J87: =SUM(J82:J86)*$C87 -> 11.267917 | K87: =SUM(K82:K86)*$C87 -> 0 | L87: =SUM(L82:L86)*$C87 -> 0 | M87: =SUM(M82:M85)*$C87 -> 0 | N87: =SUM(N82:N85)*$C87 -> 0 | O87: =SUM(O82:O85)*$C87 -> 0 | P87: =SUM(P82:P85)*$C87 -> 0 | Q87: =SUM(Q82:Q85)*$C87 -> 0 | R87: =SUM(E87:Q87) -> 183832.3 | T87: =R87/SUM($R$8) -> 61277.434 | U87: AVE / UNIT | V87: Total Cost $/sf Check
B88: =B82 -> HARD COSTS - HOMES: SFR Small | E88: =SUM(E82:E87) -> 0 | F88: =SUM(F82:F87) -> 465468.61 | G88: =SUM(G82:G87) -> 2274113.8 | H88: =SUM(H82:H87) -> 2689604 | I88: =SUM(I82:I87) -> 6664.1681 | J88: =SUM(J82:J87) -> 333.20841 | K88: =SUM(K82:K87) -> 0 | L88: =SUM(L82:L87) -> 0 | ... Q88: =SUM(Q82:Q87) -> 0 | R88: =SUM(E88:Q88) -> 5436183.8 | T88: =R88/SUM($R$8) -> 1812061.3 | U88: AVE / UNIT | V88: =R88/V8 -> 753.45583
T89: {=R88/SUMPRODUCT(D8*F8:Q8*F$24:Q$24)} -> 0.51962471 | U89: of Sales
A90: 02b | B90: HARD COSTS - HOMES: Duplex Small
B91: Infrastructure (Utilities & Driveway) - Duplex | C91: 30000 | F91: =((SUM(E$9)*$C91)*0.25)+((SUM(F$9)*$C91)*0.75) -> 45000 | G91: =((SUM(F$9)*$C91)*0.25)+((SUM(G$9)*$C91)*0.75) -> 195000 | H91: =((SUM(G$9)*$C91)*0.25)+((SUM(H$9)*$C91)*0.75) -> 150000 | I91: =((SUM(H$9)*$C91)*0.25)+((SUM(I$9)*$C91)*0.75) -> 210000 | J91: =((SUM(I$9)*$C91)*0.25)+((SUM(J$9)*$C91)*0.75) -> 60000 | K91: =((SUM(J$9)*$C91)*0.25)+((SUM(K$9)*$C91)*0.75) -> 0 | L91: =((SUM(K$9)*$C91)*0.25)+((SUM(L$9)*$C91)*0.75) -> 0 | M91: =((SUM(L$9)*$C91)*0.25)+((SUM(M$9)*$C91)*0.75) -> 0 | ... Q91: =((SUM(P$9)*$C91)*0.25)+((SUM(Q$9)*$C91)*0.75) -> 0 | R91: =SUM(E91:Q91) -> 660000 | T91: =R91/SUM($R$9) -> 30000 | U91: /UNIT | V91: Build Cost $/sf Check
B92: Vertical Construction Costs - Duplex | C92: 615 | F92: =(IFERROR((SUMPRODUCT($D$9,E9))*$C92,0)*0.75)+(IFERROR((SUMPRODUCT($D$9,F9))*$C92,0)*0.25) -> 548272.5 | G92: =(IFERROR((SUMPRODUCT($D$9,F9))*$C92,0)*0.75)+(IFERROR((SUMPRODUCT($D$9,G9))*$C92,0)*0.25) -> 3837907.5 | H92: =(IFERROR((SUMPRODUCT($D$9,G9))*$C92,0)*0.75)+(IFERROR((SUMPRODUCT($D$9,H9))*$C92,0)*0.25) -> 7675815 | I92: =(IFERROR((SUMPRODUCT($D$9,H9))*$C92,0)*0.75)+(IFERROR((SUMPRODUCT($D$9,I9))*$C92,0)*0.25) -> 5482725 | J92: =(IFERROR((SUMPRODUCT($D$9,I9))*$C92,0)*0.75)+(IFERROR((SUMPRODUCT($D$9,J9))*$C92,0)*0.25) -> 6579270 | K92: =(IFERROR((SUMPRODUCT($D$9,J9))*$C92,0)*0.75)+(IFERROR((SUMPRODUCT($D$9,K9))*$C92,0)*0.25) -> 0 | L92: =(IFERROR((SUMPRODUCT($D$9,K9))*$C92,0)*0.75)+(IFERROR((SUMPRODUCT($D$9,L9))*$C92,0)*0.25) -> 0 | M92: =(IFERROR((SUMPRODUCT($D$9,L9))*$C92,0)*0.75)+(IFERROR((SUMPRODUCT($D$9,M9))*$C92,0)*0.25) -> 0 | ... Q92: =(IFERROR((SUMPRODUCT($D$9,P9))*$C92,0)*0.75)+(IFERROR((SUMPRODUCT($D$9,Q9))*$C92,0)*0.25) -> 0 | R92: =SUM(E92:Q92) -> 24123990 | T92: =R92/SUM($R$9) -> 1096545 | U92: AVE / UNIT | V92: =(R92)/V9 -> 615
B93: Landscape / Hardscape - Duplex | C93: 40000 | G93: =+$C$93*F9 -> 80000 | H93: =+$C$93*G9 -> 320000 | I93: =+$C$93*H9 -> 160000 | J93: =+$C$93*I9 -> 320000 | K93: =+$C$93*J9 -> 0 | L93: =+$C$93*K9 -> 0 | M93: =+$C$93*L9 -> 0 | N93: =+$C$93*M9 -> 0 | ... Q93: =+$C$93*P9 -> 0 | R93: =SUM(E93:Q93) -> 880000 | T93: =R93/SUM($R$9) -> 40000 | U93: /UNIT
B94: Construction Cost Escalation | C94: 0.05 | F94: =SUM(F91:F93,E94)*$C94 -> 29663.625 | G94: =SUM(G91:G93,F94)*$C94 -> 207128.56 | H94: =SUM(H91:H93,G94)*$C94 -> 417647.18 | I94: =SUM(I91:I93,H94)*$C94 -> 313518.61 | J94: =SUM(J91:J93,I94)*$C94 -> 363639.43 | R94: =SUM(E94:Q94) -> 1331597.4 | T94: =R94/SUM($R$9) -> 60527.154 | U94: AVE / UNIT
B95: Developer Construction Contingency | C95: 0.035 | E95: =SUM(E90:E93)*$C95 -> 0 | F95: =SUM(F90:F94)*$C95 -> 21802.764 | G95: =SUM(G90:G94)*$C95 -> 151201.26 | H95: =SUM(H90:H94)*$C95 -> 299721.18 | I95: =SUM(I90:I94)*$C95 -> 215818.53 | J95: =SUM(J90:J94)*$C95 -> 256301.83 | K95: =SUM(K90:K94)*$C95 -> 0 | L95: =SUM(L90:L94)*$C95 -> 0 | M95: =SUM(M90:M93)*$C95 -> 0 | N95: =SUM(N90:N93)*$C95 -> 0 | O95: =SUM(O90:O93)*$C95 -> 0 | P95: =SUM(P90:P93)*$C95 -> 0 | Q95: =SUM(Q90:Q93)*$C95 -> 0 | R95: =SUM(E95:Q95) -> 944845.56 | T95: =R95/SUM($R$9) -> 42947.525 | U95: AVE / UNIT | V95: Total Cost $/sf Check
B96: =B90 -> HARD COSTS - HOMES: Duplex Small | E96: =SUM(E90:E95) -> 0 | F96: =SUM(F90:F95) -> 644738.89 | G96: =SUM(G90:G95) -> 4471237.3 | H96: =SUM(H90:H95) -> 8863183.4 | I96: =SUM(I90:I95) -> 6382062.1 | J96: =SUM(J90:J95) -> 7579211.3 | K96: =SUM(K90:K95) -> 0 | L96: =SUM(L90:L95) -> 0 | ... Q96: =SUM(Q90:Q95) -> 0 | R96: =SUM(E96:Q96) -> 27940433 | T96: =R96/SUM($R$9) -> 1270019.7 | U96: AVE / UNIT | V96: =R96/V9 -> 712.29371
T97: {=R96/SUMPRODUCT(D9*F9:Q9*F$25:Q$25)} -> 0.48403905 | U97: of Sales
A98: 02b | B98: HARD COSTS - HOMES: Multi-Unit
B99: Infrastructure (Utilities & Driveway) - Multi-unit | C99: =35000/2 -> 17500 | F99: =((SUM(E$10)*$C99)*0.25)+((SUM(F$10)*$C99)*0.75) -> 0 | G99: =((SUM(F$10)*$C99)*0.25)+((SUM(G$10)*$C99)*0.75) -> 52500 | H99: =((SUM(G$10)*$C99)*0.25)+((SUM(H$10)*$C99)*0.75) -> 70000 | I99: =((SUM(H$10)*$C99)*0.25)+((SUM(I$10)*$C99)*0.75) -> 17500 | J99: =((SUM(I$10)*$C99)*0.25)+((SUM(J$10)*$C99)*0.75) -> 0 | K99: =((SUM(J$10)*$C99)*0.25)+((SUM(K$10)*$C99)*0.75) -> 0 | L99: =((SUM(K$10)*$C99)*0.25)+((SUM(L$10)*$C99)*0.75) -> 0 | M99: =((SUM(L$10)*$C99)*0.25)+((SUM(M$10)*$C99)*0.75) -> 0 | ... Q99: =((SUM(P$10)*$C99)*0.25)+((SUM(Q$10)*$C99)*0.75) -> 0 | R99: =SUM(E99:Q99) -> 140000 | T99: =R99/SUM($R$10) -> 17500 | U99: /UNIT | V99: Build Cost $/sf Check
B100: Underground Parking - per unit $ | C100: 100000 | F100: =$C100*F10 -> 0 | G100: =$C100*G10 -> 400000 | H100: =$C100*H10 -> 400000 | I100: =$C100*I10 -> 0 | J100: =$C100*J10 -> 0 | K100: =$C100*K10 -> 0 | L100: =$C100*L10 -> 0 | M100: =$C100*M10 -> 0 | ... Q100: =$C100*Q10 -> 0 | R100: =SUM(E100:Q100) -> 800000 | T100: =R100/SUM($R$10) -> 100000 | U100: /UNIT
B101: Vertical Construction Costs - Multi-unit | C101: 550 | F101: =(IFERROR((SUMPRODUCT($D$10,E10))*$C101,0)*0.75)+(IFERROR((SUMPRODUCT($D$10,F10))*$C101,0)*0.25) -> 0 | G101: =(IFERROR((SUMPRODUCT($D$10,F10))*$C101,0)*0.75)+(IFERROR((SUMPRODUCT($D$10,G10))*$C101,0)*0.25) -> 742500 | H101: =(IFERROR((SUMPRODUCT($D$10,G10))*$C101,0)*0.75)+(IFERROR((SUMPRODUCT($D$10,H10))*$C101,0)*0.25) -> 2970000 | I101: =(IFERROR((SUMPRODUCT($D$10,H10))*$C101,0)*0.75)+(IFERROR((SUMPRODUCT($D$10,I10))*$C101,0)*0.25) -> 2227500 | J101: =(IFERROR((SUMPRODUCT($D$10,I10))*$C101,0)*0.75)+(IFERROR((SUMPRODUCT($D$10,J10))*$C101,0)*0.25) -> 0 | K101: =(IFERROR((SUMPRODUCT($D$10,J10))*$C101,0)*0.75)+(IFERROR((SUMPRODUCT($D$10,K10))*$C101,0)*0.25) -> 0 | L101: =(IFERROR((SUMPRODUCT($D$10,K10))*$C101,0)*0.75)+(IFERROR((SUMPRODUCT($D$10,L10))*$C101,0)*0.25) -> 0 | M101: =(IFERROR((SUMPRODUCT($D$10,L10))*$C101,0)*0.75)+(IFERROR((SUMPRODUCT($D$10,M10))*$C101,0)*0.25) -> 0 | ... Q101: =(IFERROR((SUMPRODUCT($D$10,P10))*$C101,0)*0.75)+(IFERROR((SUMPRODUCT($D$10,Q10))*$C101,0)*0.25) -> 0 | R101: =SUM(E101:Q101) -> 5940000 | T101: =R101/SUM($R$10) -> 742500 | U101: AVE / UNIT | V101: =(R101)/V10 -> 550
B102: Landscape / Hardscape - Multi-unit | C102: 15000 | G102: =SUM(F10*$C102) -> 0 | H102: =SUM(G10*$C102) -> 60000 | I102: =SUM(H10*$C102) -> 60000 | J102: =SUM(I10*$C102) -> 0 | K102: =SUM(J10*$C102) -> 0 | L102: =SUM(K10*$C102) -> 0 | M102: =SUM(L10*$C102) -> 0 | N102: =SUM(M10*$C102) -> 0 | ... Q102: =SUM(P10*$C102) -> 0 | R102: =SUM(E102:Q102) -> 120000 | T102: =R102/SUM($R$10) -> 15000 | U102: /UNIT
B103: Construction Cost Escalation | C103: 0.05 | G103: =SUM(G99:G102,F103)*$C103 -> 59750 | H103: =SUM(H99:H102,G103)*$C103 -> 177987.5 | I103: =SUM(I99:I102,H103)*$C103 -> 124149.38 | J103: =SUM(J99:J102,I103)*$C103 -> 6207.4688 | R103: =SUM(E103:Q103) -> 368094.34 | T103: =R103/SUM($R$10) -> 46011.793 | U103: AVE / UNIT
B104: Developer Construction Contingency | C104: 0.035 | E104: =SUM(E98:E102)*$C104 -> 0 | F104: =SUM(F98:F103)*$C104 -> 0 | G104: =SUM(G98:G103)*$C104 -> 43916.25 | H104: =SUM(H98:H103)*$C104 -> 128729.56 | I104: =SUM(I98:I103)*$C104 -> 85020.228 | J104: =SUM(J98:J103)*$C104 -> 217.26141 | K104: =SUM(K98:K103)*$C104 -> 0 | L104: =SUM(L98:L103)*$C104 -> 0 | M104: =SUM(M98:M102)*$C104 -> 0 | N104: =SUM(N98:N102)*$C104 -> 0 | O104: =SUM(O98:O102)*$C104 -> 0 | P104: =SUM(P98:P102)*$C104 -> 0 | Q104: =SUM(Q98:Q102)*$C104 -> 0 | R104: =SUM(E104:Q104) -> 257883.3 | T104: =R104/SUM($R$10) -> 32235.413 | U104: AVE / UNIT | V104: Total Cost $/sf Check
B105: =B98 -> HARD COSTS - HOMES: Multi-Unit | E105: =SUM(E98:E104) -> 0 | F105: =SUM(F98:F104) -> 0 | G105: =SUM(G98:G104) -> 1298666.2 | H105: =SUM(H98:H104) -> 3806717.1 | I105: =SUM(I98:I104) -> 2514169.6 | J105: =SUM(J98:J104) -> 6424.7302 | K105: =SUM(K98:K104) -> 0 | L105: =SUM(L98:L104) -> 0 | ... Q105: =SUM(Q98:Q104) -> 0 | R105: =SUM(E105:Q105) -> 7625977.6 | T105: =R105/SUM($R$10) -> 953247.21 | U105: AVE / UNIT | V105: =R105/V10 -> 706.10904
T106: {=R105/SUMPRODUCT(D10*F10:Q10*F$26:Q$26)} -> 0.48697175 | U106: of Sales
...

Sheet Returns Resi
B1: BRUNDAGE - Resi DEVELOPMENT: RETURNS
B2: Returns Analysis
B4: PROJECT FINANCING ANALYSIS | F4: PROJECT RETURNS ANALYSIS
B5: TOTAL PROJECT CAPITAL NEEDS | D5: =SUM('Proforma Resi'!R32,'Proforma Resi'!R35) -> #REF! | F5: TOTAL RETURN | H5: =D54 -> #REF!
B6: TOTAL PROJECT VALUE (PV of FINAL BUILD OUT) | D6: ='Proforma Resi'!T11 -> 117820000 | F6: INVESTED CAPITAL | H6: =D55 -> #REF!
B7: STARTING SPEC DEVELOPMENT VALUE | D7: ='Proforma Resi'!G44+'Proforma Resi'!F42 -> 12166750 | F7: NET PROFIT | H7: =D56 -> #REF!
B8: EQUITY to SPEC DEV VALUE (ETV) | D8: ='Proforma Resi'!Y30 -> #REF! | F8: EQUITY MULTIPLE | H8: =H5/H6 -> #REF!
B9: LOAN to COST (LTC) | D9: ='Proforma Resi'!Y32 -> #REF! | F9: ROI | H9: =H7/H6 -> #REF!
B10: LOAN to VALUE (LTV) | D10: ='Proforma Resi'!Y31 -> #REF! | F10: IRR | H10: =XIRR(F56:N56,F20:N20) -> #REF!
B12: BUSINESS CASE ANALYSIS
B13: TOTAL PROJECT REVENUE (less brokers fees): | D13: =('Proforma Resi'!R44+'Proforma Resi'!R42)-'Proforma Resi'!R172 -> 1.2545596e+08 | J13: Current Assumptions
B14: - TOTAL PROJECT COST | D14: ='Proforma Resi'!R197-'Proforma Resi'!R172+'Proforma Resi'!R202+'Proforma Resi'!R201 -> #REF! | J14: Vertical Const. Costs Scalar | L14: 1
B15: = NET PROFIT | D15: =D13-D14 -> #REF! | J15: Sales Price Scalar | L15: 1
B16: NET PROFIT %: | D16: =D15/D13 -> #REF!
B17: RETURN on EQUITY/CAPTIAL (ROE): | D17: =D15/H6 -> #REF!
F18: ='Proforma Resi'!E3 -> 0 | G18: ='Proforma Resi'!F3 -> 1 | H18: ='Proforma Resi'!G3 -> 2 | I18: ='Proforma Resi'!H3 -> 3 | J18: ='Proforma Resi'!I3 -> 4 | K18: ='Proforma Resi'!J3 -> 5 | L18: ='Proforma Resi'!K3 -> 6 | M18: ='Proforma Resi'!L3 -> 7 | ... R18: ='Proforma Resi'!Q3 -> 12
F19: =Assumptions!C6 -> 2024 | G19: =F19+1 -> 2025 | H19: =G19+1 -> 2026 | I19: =H19+1 -> 2027 | J19: =I19+1 -> 2028 | K19: =J19+1 -> 2029 | L19: =K19+1 -> 2030 | M19: =L19+1 -> 2031 | N19: =M19+1 -> 2032 | ... R19: =Q19+1 -> 2036
B20: SUMMARY OF RETURNS | F20: =DATE(F19,12,31) -> 45657 | G20: =EDATE(F20,12) -> 46022 | H20: =EDATE(G20,12) -> 46387 | I20: =EDATE(H20,12) -> 46752 | J20: =EDATE(I20,12) -> 47118 | K20: =EDATE(J20,12) -> 47483 | L20: =EDATE(K20,12) -> 47848 | M20: =EDATE(L20,12) -> 48213 | N20: =EDATE(M20,12) -> 48579 | ... R20: =EDATE(Q20,12) -> 50040
B21: Preferred Members 1 (PM1) Returns
B22: Land Repayment | D22: =SUM(F22:R22) -> 15000000 | F22: ='Proforma Resi'!E50+'Proforma Resi'!E54 -> 0 | G22: ='Proforma Resi'!F50+'Proforma Resi'!F54 -> 3000000 | H22: ='Proforma Resi'!G50+'Proforma Resi'!G54 -> 1703345 | I22: ='Proforma Resi'!H50+'Proforma Resi'!H54 -> 5665944.4 | J22: ='Proforma Resi'!I50+'Proforma Resi'!I54 -> 4630710.6 | K22: ='Proforma Resi'!J50+'Proforma Resi'!J54 -> 0 | L22: ='Proforma Resi'!K50+'Proforma Resi'!K54 -> 0 | M22: ='Proforma Resi'!L50+'Proforma Resi'!L54 -> 0 | ... R22: ='Proforma Resi'!Q50+'Proforma Resi'!Q54 -> 0
B23: Interest | D23: =SUM(F23:R23) -> #REF! | F23: ='Proforma Resi'!E57 -> 0 | G23: ='Proforma Resi'!F57 -> #REF! | H23: ='Proforma Resi'!G57 -> #REF! | I23: ='Proforma Resi'!H57 -> #REF! | J23: ='Proforma Resi'!I57 -> #REF! | K23: ='Proforma Resi'!J57 -> #REF! | L23: ='Proforma Resi'!K57 -> #REF! | M23: ='Proforma Resi'!L57 -> #REF! | ... R23: ='Proforma Resi'!Q57 -> #REF!
B24: ="Additional Profit Split ("&TEXT(Assumptions!#REF!,"0%")&")" -> #REF! | D24: =SUM(F24:R24) -> #REF! | F24: ='Proforma Resi'!E223 -> 0 | G24: ='Proforma Resi'!F223 -> #REF! | H24: ='Proforma Resi'!G223 -> #REF! | I24: ='Proforma Resi'!H223 -> #REF! | J24: ='Proforma Resi'!I223 -> #REF! | K24: ='Proforma Resi'!J223 -> #REF! | L24: ='Proforma Resi'!K223 -> #REF! | M24: ='Proforma Resi'!L223 -> #REF! | ... R24: ='Proforma Resi'!Q223 -> #REF!
B25: Total PM Distributions | D25: =SUM(F25:R25) -> #REF! | F25: =SUM(F22:F24) -> 0 | G25: =SUM(G22:G24) -> #REF! | H25: =SUM(H22:H24) -> #REF! | I25: =SUM(I22:I24) -> #REF! | J25: =SUM(J22:J24) -> #REF! | K25: =SUM(K22:K24) -> #REF! | L25: =SUM(L22:L24) -> #REF! | M25: =SUM(M22:M24) -> #REF! | ... R25: =SUM(R22:R24) -> #REF!
B26: Total PM Contributions | D26: =SUM(F26:R26) -> 15000000 | G26: ='Proforma Resi'!C56 -> 15000000 | H26: 0 | I26: 0 | J26: 0 | K26: 0 | L26: 0 | M26: 0 | N26: 0 | O26: 0 | P26: 0 | Q26: 0 | R26: 0
B27: PM Net Profit / Cash Flows | D27: =SUM(F27:R27) -> #REF! | F27: =F25-F26 -> 0 | G27: =G25-G26 -> #REF! | H27: =H25-H26 -> #REF! | I27: =I25-I26 -> #REF! | J27: =J25-J26 -> #REF! | K27: =K25-K26 -> #REF! | L27: =L25-L26 -> #REF! | M27: =M25-M26 -> #REF! | ... R27: =R25-R26 -> #REF!
B28: PM IRR | F28: =XIRR(G27:R27,G20:R20) -> #REF!
B29: PM Equity Multiple | F29: =SUMIF(F27:R27,">0")/-SUMIF(F27:R27,"<0") -> #DIV/0!
B30: Cumulative PM (Equity) Cash Position | F30: =F27+E30 -> 0 | G30: =G27+F30 -> #REF! | H30: =H27+G30 -> #REF! | I30: =I27+H30 -> #REF! | J30: =J27+I30 -> #REF! | K30: =K27+J30 -> #REF! | L30: =L27+K30 -> #REF! | M30: =M27+L30 -> #REF! | ... R30: =R27+Q30 -> #REF!
B32: Preferred Members 2 (PM2) Returns
B33: Preferred Returns | D33: =SUM(F33:R33) -> 0 | F33: ='Proforma Resi'!E221 -> 0 | G33: ='Proforma Resi'!F221 -> 0 | H33: ='Proforma Resi'!G221 -> 0 | I33: ='Proforma Resi'!H221 -> 0 | J33: ='Proforma Resi'!I221 -> 0 | K33: ='Proforma Resi'!J221 -> 0 | L33: ='Proforma Resi'!K221 -> 0 | M33: ='Proforma Resi'!L221 -> 0 | ... R33: ='Proforma Resi'!Q221 -> 0
B34: ="Additional Profit Split ("&TEXT(Assumptions!#REF!,"0%")&")" -> #REF! | D34: =SUM(F34:R34) -> #REF! | F34: ='Proforma Resi'!E224 -> 0 | G34: ='Proforma Resi'!F224 -> #REF! | H34: ='Proforma Resi'!G224 -> #REF! | I34: ='Proforma Resi'!H224 -> #REF! | J34: ='Proforma Resi'!I224 -> #REF! | K34: ='Proforma Resi'!J224 -> #REF! | L34: ='Proforma Resi'!K224 -> #REF! | M34: ='Proforma Resi'!L224 -> #REF! | ... R34: ='Proforma Resi'!Q224 -> #REF!
B35: Total PM Distributions | D35: =SUM(F35:R35) -> #REF! | F35: =SUM(F33:F34) -> 0 | G35: =SUM(G33:G34) -> #REF! | H35: =SUM(H33:H34) -> #REF! | I35: =SUM(I33:I34) -> #REF! | J35: =SUM(J33:J34) -> #REF! | K35: =SUM(K33:K34) -> #REF! | L35: =SUM(L33:L34) -> #REF! | M35: =SUM(M33:M34) -> #REF! | ... R35: =SUM(R33:R34) -> #REF!
B36: Total PM Contributions | D36: =SUM(F36:R36) -> #REF! | F36: ='Proforma Resi'!E31 -> 0 | G36: ='Proforma Resi'!F31 -> #REF! | H36: ='Proforma Resi'!G31 -> 0 | I36: ='Proforma Resi'!H31 -> 0 | J36: ='Proforma Resi'!I31 -> 0 | K36: ='Proforma Resi'!J31 -> 0 | L36: ='Proforma Resi'!K31 -> 0 | M36: ='Proforma Resi'!L31 -> 0 | ... R36: ='Proforma Resi'!Q31 -> 0
B37: PM Net Profit / Cash Flows | D37: =SUM(F37:R37) -> #REF! | F37: =F35-F36 -> 0 | G37: =G35-G36 -> #REF! | H37: =H35-H36 -> #REF! | I37: =I35-I36 -> #REF! | J37: =J35-J36 -> #REF! | K37: =K35-K36 -> #REF! | L37: =L35-L36 -> #REF! | M37: =M35-M36 -> #REF! | ... R37: =R35-R36 -> #REF!
B38: PM IRR | F38: =XIRR(G37:R37,G20:R20) -> #REF!
B39: PM Equity Multiple | F39: =SUMIF(F37:R37,">0")/-SUMIF(F37:R37,"<0") -> #DIV/0!
B40: Cumulative PM (Equity) Cash Position | F40: =F37+E40 -> 0 | G40: =G37+F40 -> #REF! | H40: =H37+G40 -> #REF! | I40: =I37+H40 -> #REF! | J40: =J37+I40 -> #REF! | K40: =K37+J40 -> #REF! | L40: =L37+K40 -> #REF! | M40: =M37+L40 -> #REF! | ... R40: =R37+Q40 -> #REF!
B42: Common Members (CM) Returns
B43: ="CM Profit Split ("&TEXT(Assumptions!#REF!,"0%")&")" -> #REF! | D43: =SUM(F43:R43) -> #REF! | F43: ='Proforma Resi'!E225 -> 0 | G43: ='Proforma Resi'!F225 -> #REF! | H43: ='Proforma Resi'!G225 -> #REF! | I43: ='Proforma Resi'!H225 -> #REF! | J43: ='Proforma Resi'!I225 -> #REF! | K43: ='Proforma Resi'!J225 -> #REF! | L43: ='Proforma Resi'!K225 -> #REF! | M43: ='Proforma Resi'!L225 -> #REF! | ... R43: ='Proforma Resi'!Q225 -> #REF!
B44: Total CM Contributions | D44: =SUM(F44:R44) -> 75000 | F44: ='Proforma Resi'!E29 -> 75000 | G44: ='Proforma Resi'!F29 -> 0 | H44: ='Proforma Resi'!G29 -> 0 | I44: ='Proforma Resi'!H29 -> 0 | J44: ='Proforma Resi'!I29 -> 0 | K44: ='Proforma Resi'!J29 -> 0 | L44: ='Proforma Resi'!K29 -> 0 | M44: ='Proforma Resi'!L29 -> 0 | ... R44: ='Proforma Resi'!Q29 -> 0
B45: CM Net Profit/ Cash Flows | D45: =SUM(F45:R45) -> #REF! | F45: =F43-F44 -> -75000 | G45: =G43-G44 -> #REF! | H45: =H43-H44 -> #REF! | I45: =I43-I44 -> #REF! | J45: =J43-J44 -> #REF! | K45: =K43-K44 -> #REF! | L45: =L43-L44 -> #REF! | M45: =M43-M44 -> #REF! | ... R45: =R43-R44 -> #REF!
B46: ='Proforma Resi'!B49 -> Asset Acquisition Fee | F46: ='Proforma Resi'!E49 -> 0 | G46: ='Proforma Resi'!F49 -> 300000 | H46: ='Proforma Resi'!G49 -> 0 | I46: ='Proforma Resi'!H49 -> 0 | J46: ='Proforma Resi'!I49 -> 0 | K46: ='Proforma Resi'!J49 -> 0 | L46: ='Proforma Resi'!K49 -> 0 | M46: ='Proforma Resi'!L49 -> 0 | ... R46: ='Proforma Resi'!Q49 -> 0
B47: ='Proforma Resi'!B191 -> Developer Overhead (% of COSTS less LAND & RE Fees) | D47: =SUM(F47:R47) -> #REF! | F47: ='Proforma Resi'!E191 -> 0 | G47: ='Proforma Resi'!F191 -> #REF! | H47: ='Proforma Resi'!G191 -> #REF! | I47: ='Proforma Resi'!H191 -> #REF! | J47: ='Proforma Resi'!I191 -> #REF! | K47: ='Proforma Resi'!J191 -> #REF! | L47: ='Proforma Resi'!K191 -> 0 | M47: ='Proforma Resi'!L191 -> 0 | ... R47: ='Proforma Resi'!Q191 -> 0
B48: ='Proforma Resi'!B192 -> Disposition Fees | D48: =SUM(F48:R48) -> 2641178 | F48: ='Proforma Resi'!E192 -> 0 | G48: ='Proforma Resi'!F192 -> 0 | H48: ='Proforma Resi'!G192 -> 243335 | I48: ='Proforma Resi'!H192 -> 809420.62 | J48: ='Proforma Resi'!I192 -> 819645.62 | K48: ='Proforma Resi'!J192 -> 768776.79 | L48: ='Proforma Resi'!K192 -> 0 | M48: ='Proforma Resi'!L192 -> 0 | ... R48: ='Proforma Resi'!Q192 -> 0
B49: ='Proforma Resi'!B193 -> Asset Management Fees | D49: =SUM(F49:R49) -> 650404.04 | F49: ='Proforma Resi'!E193 -> 0 | G49: ='Proforma Resi'!F193 -> 168534.63 | H49: ='Proforma Resi'!G193 -> 168534.63 | I49: ='Proforma Resi'!H193 -> 168534.63 | J49: ='Proforma Resi'!I193 -> 129838.88 | K49: ='Proforma Resi'!J193 -> 14961.263 | L49: ='Proforma Resi'!K193 -> 0 | M49: ='Proforma Resi'!L193 -> 0 | ... R49: ='Proforma Resi'!Q193 -> 0
B50: CM Total Cash Flows | D50: =SUM(F50:R50) -> #REF! | F50: =SUM(F45:F49) -> -75000 | G50: =SUM(G45:G49) -> #REF! | H50: =SUM(H45:H49) -> #REF! | I50: =SUM(I45:I49) -> #REF! | J50: =SUM(J45:J49) -> #REF! | K50: =SUM(K45:K49) -> #REF! | L50: =SUM(L45:L49) -> #REF! | M50: =SUM(M45:M49) -> #REF! | ... R50: =SUM(R45:R49) -> #REF!
F52: =F20 -> 45657 | G52: =G20 -> 46022 | H52: =H20 -> 46387 | I52: =I20 -> 46752 | J52: =J20 -> 47118 | K52: =K20 -> 47483 | L52: =L20 -> 47848 | M52: =M20 -> 48213 | ... R52: =R20 -> 50040
B53: Net Cash Flow For Distributions - TOTAL PROJECT RETURNS
B54: Total Return | D54: =SUM(F54:R54) -> #REF! | F54: =F25+F35+F43 -> 0 | G54: =G25+G35+G43 -> #REF! | H54: =H25+H35+H43 -> #REF! | I54: =I25+I35+I43 -> #REF! | J54: =J25+J35+J43 -> #REF! | K54: =K25+K35+K43 -> #REF! | L54: =L25+L35+L43 -> #REF! | M54: =M25+M35+M43 -> #REF! | ... R54: =R25+R35+R43 -> #REF!
B55: Invested Capital | D55: =SUM(F55:R55) -> #REF! | F55: =F26+F36+F44 -> 75000 | G55: =G26+G36+G44 -> #REF! | H55: =H26+H36+H44 -> 0 | I55: =I26+I36+I44 -> 0 | J55: =J26+J36+J44 -> 0 | K55: =K26+K36+K44 -> 0 | L55: =L26+L36+L44 -> 0 | M55: =M26+M36+M44 -> 0 | ... R55: =R26+R36+R44 -> 0
B56: Net Levered Before Tax Cash Flow | D56: =SUM(F56:R56) -> #REF! | F56: =F27+F37+F45 -> -75000 | G56: =G27+G37+G45 -> #REF! | H56: =H27+H37+H45 -> #REF! | I56: =I27+I37+I45 -> #REF! | J56: =J27+J37+J45 -> #REF! | K56: =K27+K37+K45 -> #REF! | L56: =L27+L37+L45 -> #REF! | M56: =M27+M37+M45 -> #REF! | ... R56: =R27+R37+R45 -> #REF!
B57: Check | F57: ='Proforma Resi'!E232-F56 -> 0 | G57: ='Proforma Resi'!F232-G56 -> #REF! | H57: ='Proforma Resi'!G232-H56 -> #REF! | I57: ='Proforma Resi'!H232-I56 -> #REF! | J57: ='Proforma Resi'!I232-J56 -> #REF! | K57: ='Proforma Resi'!J232-K56 -> #REF! | L57: ='Proforma Resi'!K232-L56 -> #REF! | M57: ='Proforma Resi'!L232-M56 -> #REF! | ... R57: ='Proforma Resi'!Q232-R56 -> #REF!
B58: Levered IRR | F58: =XIRR(F56:R56,F52:R52) -> #REF!
B59: Equity Multiple | F59: =SUMIF(F56:R56,">0")/-SUMIF(F56:R56,"<0") -> 0

Sheet Proforma Land+Home
B1: CLARENDON - LAND & HOME DEVELOPMENT | AC1: Year 0 | AD1: Year 1 | AE1: Year 2 | AF1: Year 3 | AG1: Year 4 | AH1: Year 5 | AI1: Year 6 | AJ1: Year 7
B2: Build & Sales Proforma
E3: Year 0 | F3: Year 1 | G3: Year 2 | H3: Year 3 | I3: Year 4 | J3: Year 5 | K3: Year 6 | L3: Year 7 | M3: Year 8 | N3: Year 9 | O3: Year 10 | P3: Year 11 | Q3: Year 12 | Z3: Checks | AA3: =SUM(AA4:AA210) -> #REF!
D4: FY | E4: 2025 | F4: =E4+1 -> 2026 | G4: =F4+1 -> 2027 | H4: =G4+1 -> 2028 | I4: =H4+1 -> 2029 | J4: =I4+1 -> 2030 | K4: =J4+1 -> 2031 | L4: =K4+1 -> 2032 | M4: =L4+1 -> 2033 | ... Q4: =P4+1 -> 2037 | R4: TOTALS
E5: 45658 | F5: =E5+365 -> 46023 | G5: =F5+365 -> 46388 | H5: =G5+365 -> 46753 | I5: =H5+366 -> 47119 | J5: =I5+365 -> 47484 | K5: =J5+365 -> 47849 | L5: =K5+365 -> 48214 | M5: =L5+365 -> 48579 | N5: =M5+365 -> 48944 | O5: =N5+365 -> 49309 | P5: =O5+366 -> 49675 | Q5: =P5+365 -> 50040 | S5: Basis per Lot+Unit
A6: Map | B6: Buildout schedule | D6: Avg Unit Size
A7: A- | B7: Pondside Cabins @ Event Barn (13ea) | D7: 1500 | R7: =SUM(F7:Q7) -> 0 | S7: =D7*$E$34 -> 2775000 | T7: =R7*S7 -> 0 | V7: =#REF!*#REF! -> #REF!
A8: B- | B8: Village Cabins (13ea) | D8: 2000 | R8: =SUM(F8:Q8) -> 0 | S8: =D8*$E$34 -> 3700000 | T8: =R8*S8 -> 0
A9: C- | B9: Village Cottages (13ea) | D9: 2500 | R9: =SUM(F9:Q9) -> 0 | S9: =D9*$E$34 -> 4625000 | T9: =R9*S9 -> 0
A10: D- | B10: Guest Cabins @ Fitness Spa (13ea) | D10: 2500 | R10: =SUM(F10:Q10) -> 0 | S10: =D10*$E$34 -> 4625000 | T10: =R10*S10 -> 0
A11: F- | B11: Jimmy Creek Homes (4ea) | D11: 3500 | E11: 4 | R11: =SUM(E11:Q11) -> 4 | S11: =D11*$E$32 -> 6125000 | T11: =R11*S11 -> 24500000
A12: G- | B12: Bench Homesites (15ea) | D12: 3250 | F12: 8 | G12: 7 | R12: =SUM(E12:Q12) -> 15 | S12: =D12*$E$32 -> 5687500 | T12: =R12*S12 -> 85312500
A13: H- | B13: Forest Homesites (10ea) | D13: 3750 | G13: 5 | H13: 5 | R13: =SUM(E13:Q13) -> 10 | S13: =D13*$E$32 -> 6562500 | T13: =R13*S13 -> 65625000 | U13: Improved Value Before Escalation
A14: J- | B14: Hillside Homesites (10ea) | D14: 3750 | H14: 7 | I14: 3 | R14: =SUM(E14:Q14) -> 10 | S14: =D14*$E$32 -> 6562500 | T14: =R14*S14 -> 65625000
A15: E- | B15: Village Homesites (6ea) | D15: 4500 | R15: =SUM(E15:Q15) -> 0 | S15: =D15*$E$33 -> 7875000 | T15: =R15*S15 -> 0
A16: K- | B16: Deer Creek Homesites (5ea + 1 lot used for Clubhouse) | D16: 3500 | E16: 1 | J16: 5 | R16: =SUM(E16:Q16) -> 6 | S16: =D16*$E$34 -> 6475000 | T16: =R16*S16 -> 38850000
B17: Total starts | E17: =SUM(E7:E16) -> 5 | F17: =SUM(F7:F16) -> 8 | G17: =SUM(G7:G16) -> 12 | H17: =SUM(H7:H16) -> 12 | I17: =SUM(I7:I16) -> 3 | J17: =SUM(J7:J16) -> 5 | K17: =SUM(K7:K16) -> 0 | L17: =SUM(L7:L16) -> 0 | ... R17: =SUM(R7:R16) -> 45 | S17: TOTAL HOMES | T17: =SUM(T7:T16) -> 279912500 | V17: =SUMPRODUCT(D7:D16,R7:R16) -> 158750 | W17: sf | X17: =SUM(T7:T16)/V17 -> 1763.2283 | Y17: /sf | Z17: /sf
B18: Total Sellable SQFT | D18: =SUMPRODUCT(D7:D16,R7:R16) -> 158750 | T18: =T17/R17 -> 6220277.8 | U18: Average | V18: =D18/R17 -> 3527.7778
B20: Sales Schedule | U20: Year 1 | V20: Year 2 | W20: Year 3 | X20: Year 4 | Y20: Year 5 | Z20: Year 6 | AA20: Year 7
B21: =B7 -> Pondside Cabins @ Event Barn (13ea) | C21: =R7 -> 0 | D21: =T21 -> Cottages | G21: =F7 -> 0 | H21: =G7 -> 0 | I21: =H7 -> 0 | J21: =I7 -> 0 | K21: =J7 -> 0 | L21: =K7 -> 0 | M21: =L7 -> 0 | N21: =M7 -> 0 | ... Q21: =P7 -> 0 | R21: =SUM(F21:Q21) -> 0 | T21: Cottages | U21: =+F34 -> 1850 | V21: =+G34 -> 2035 | W21: =+H34 -> 2238.5 | X21: =+I34 -> 2462.35 | Y21: =+J34 -> 2708.585 | Z21: =+K34 -> 2979.4435 | AA21: {=+L34:P34} -> 3277.3879 | AB21: 3605.1266 | AC21: 3965.6393 | AD21: 4362.2032 | AE21: 4798.4236
B22: =B8 -> Village Cabins (13ea) | C22: =R8 -> 0 | D22: =T22 -> Cottages | G22: =F8 -> 0 | H22: =G8 -> 0 | I22: =H8 -> 0 | J22: =I8 -> 0 | K22: =J8 -> 0 | L22: =K8 -> 0 | M22: =L8 -> 0 | N22: =M8 -> 0 | ... Q22: =P8 -> 0 | R22: =SUM(F22:Q22) -> 0 | T22: Cottages | U22: =+U21 -> 1850 | V22: =+V21 -> 2035 | W22: =+W21 -> 2238.5 | X22: =+X21 -> 2462.35 | Y22: =+Y21 -> 2708.585 | Z22: =+Z21 -> 2979.4435 | AA22: =+AA21 -> 3277.3879
B23: =B9 -> Village Cottages (13ea) | C23: =R9 -> 0 | D23: =T23 -> Cottages | G23: =F9 -> 0 | H23: =G9 -> 0 | I23: =H9 -> 0 | J23: =I9 -> 0 | K23: =J9 -> 0 | L23: =K9 -> 0 | M23: =L9 -> 0 | N23: =M9 -> 0 | ... Q23: =P9 -> 0 | R23: =SUM(F23:Q23) -> 0 | T23: Cottages | U23: =+U22 -> 1850 | V23: =+V22 -> 2035 | W23: =+W22 -> 2238.5 | X23: =+X22 -> 2462.35 | Y23: =+Y22 -> 2708.585 | Z23: =+Z22 -> 2979.4435 | AA23: =+AA22 -> 3277.3879
B24: =B10 -> Guest Cabins @ Fitness Spa (13ea) | C24: =R10 -> 0 | D24: =T24 -> Cottages | G24: =F10 -> 0 | H24: =G10 -> 0 | I24: =H10 -> 0 | J24: =I10 -> 0 | K24: =J10 -> 0 | L24: =K10 -> 0 | M24: =L10 -> 0 | N24: =M10 -> 0 | ... Q24: =P10 -> 0 | R24: =SUM(F24:Q24) -> 0 | T24: Cottages | U24: =+U23 -> 1850 | V24: =+V23 -> 2035 | W24: =+W23 -> 2238.5 | X24: =+X23 -> 2462.35 | Y24: =+Y23 -> 2708.585 | Z24: =+Z23 -> 2979.4435 | AA24: =+AA23 -> 3277.3879
B25: =B11 -> Jimmy Creek Homes (4ea) | C25: =R11 -> 4 | D25: =T25 -> Village | F25: =E11 -> 4 | G25: =F11 -> 0 | H25: =G11 -> 0 | I25: =H11 -> 0 | J25: =I11 -> 0 | K25: =J11 -> 0 | L25: =K11 -> 0 | M25: =L15 -> 0 | N25: =M15 -> 0 | O25: =N15 -> 0 | P25: =O15 -> 0 | Q25: =P15 -> 0 | R25: =SUM(F25:Q25) -> 4 | T25: Village | U25: =+F32 -> 1750 | V25: =+G33 -> 1881.25 | W25: =+H33 -> 2022.3438 | X25: =+I33 -> 2174.0195 | Y25: =+J33 -> 2337.071 | Z25: =+K33 -> 2512.3513 | AA25: =+L33 -> 2700.7777
B26: =B12 -> Bench Homesites (15ea) | C26: =R12 -> 15 | D26: =T26 -> Homesites | F26: =E12 -> 0 | G26: =F12 -> 8 | H26: =G12 -> 7 | I26: =H12 -> 0 | J26: =I12 -> 0 | K26: =J12 -> 0 | L26: =K12 -> 0 | M26: =L11 -> 0 | N26: =M11 -> 0 | O26: =N11 -> 0 | P26: =O11 -> 0 | Q26: =P11 -> 0 | R26: =SUM(F26:Q26) -> 15 | T26: Homesites | U26: =+F32 -> 1750 | V26: =+G32 -> 1925 | W26: =+H32 -> 2117.5 | X26: =+I32 -> 2329.25 | Y26: =+J32 -> 2562.175 | Z26: =+K32 -> 2818.3925 | AA26: =+L32 -> 3100.2318
B27: =B13 -> Forest Homesites (10ea) | C27: =R13 -> 10 | D27: =T27 -> Homesites | F27: =E13 -> 0 | G27: =F13 -> 0 | H27: =G13 -> 5 | I27: =H13 -> 5 | J27: =I13 -> 0 | K27: =J13 -> 0 | L27: =K13 -> 0 | M27: =L12 -> 0 | N27: =M12 -> 0 | O27: =N12 -> 0 | P27: =O12 -> 0 | Q27: =P12 -> 0 | R27: =SUM(F27:Q27) -> 10 | T27: Homesites | U27: =+U26 -> 1750 | V27: =+V26 -> 1925 | W27: =+W26 -> 2117.5 | X27: =+X26 -> 2329.25 | Y27: =+Y26 -> 2562.175 | Z27: =+Z26 -> 2818.3925 | AA27: =+AA26 -> 3100.2318
B28: =B14 -> Hillside Homesites (10ea) | C28: =R14 -> 10 | D28: =T28 -> Homesites | F28: =E14 -> 0 | G28: =F14 -> 0 | H28: =G14 -> 0 | I28: =H14 -> 7 | J28: =I14 -> 3 | K28: =J14 -> 0 | L28: =K14 -> 0 | M28: =L14 -> 0 | ... P28: =O14 -> 0 | Q28: =P13 -> 0 | R28: =SUM(F28:Q28) -> 10 | T28: Homesites | U28: =+U27 -> 1750 | V28: =+V27 -> 1925 | W28: =+W27 -> 2117.5 | X28: =+X27 -> 2329.25 | Y28: =+Y27 -> 2562.175 | Z28: =+Z27 -> 2818.3925 | AA28: =+AA27 -> 3100.2318
B29: =B15 -> Village Homesites (6ea) | C29: =R15 -> 0 | D29: =T29 -> Homesites | F29: =E15 -> 0 | G29: =F15 -> 0 | H29: =G15 -> 0 | I29: =H15 -> 0 | J29: =I15 -> 0 | K29: =J15 -> 0 | L29: =K15 -> 0 | M29: =L14 -> 0 | N29: =M14 -> 0 | O29: =N14 -> 0 | P29: =O14 -> 0 | Q29: =P14 -> 0 | R29: =SUM(F29:Q29) -> 0 | T29: Homesites | U29: =+U28 -> 1750 | V29: =+V28 -> 1925 | W29: =+W28 -> 2117.5 | X29: =+X28 -> 2329.25 | Y29: =+Y28 -> 2562.175 | Z29: =+Z28 -> 2818.3925 | AA29: =+AA28 -> 3100.2318
B30: =B16 -> Deer Creek Homesites (5ea + 1 lot used for Clubhouse) | C30: =R16 -> 6 | D30: =T30 -> Cottages | F30: =E16 -> 1 | G30: =F16 -> 0 | H30: =G16 -> 0 | I30: =H16 -> 0 | J30: =I16 -> 0 | K30: =J16 -> 5 | L30: =K16 -> 0 | M30: =L16 -> 0 | ... Q30: =P16 -> 0 | R30: =SUM(F30:Q30) -> 6 | T30: Cottages | U30: =+U24 -> 1850 | V30: =+V24 -> 2035 | W30: =+W24 -> 2238.5 | X30: =+X24 -> 2462.35 | Y30: =+Y24 -> 2708.585 | Z30: =+Z24 -> 2979.4435 | AA30: =+AA24 -> 3277.3879
B31: Total sales | C31: =SUM(C21:C30) -> 45 | F31: =SUM(F21:F30) -> 5 | G31: =SUM(G21:G30) -> 8 | H31: =SUM(H21:H30) -> 12 | I31: =SUM(I21:I30) -> 12 | J31: =SUM(J21:J30) -> 3 | K31: =SUM(K21:K30) -> 5 | L31: =SUM(L21:L30) -> 0 | M31: =SUM(M21:M30) -> 0 | ... R31: =SUM(R21:R30) -> 45 | Z31: Check on Sales & Build out | AA31: =+R17-R31 -> 0
B32: Sales Price Escalation / Residential Sales Sqft Price | C32: =Assumptions!H18 -> 0.1 | D32: Homesites | E32: =Assumptions!G18 -> 1750 | F32: =E32 -> 1750 | G32: =F32*(1+$C$32) -> 1925 | H32: =G32*(1+$C$32) -> 2117.5 | I32: =H32*(1+$C$32) -> 2329.25 | J32: =I32*(1+$C$32) -> 2562.175 | K32: =J32*(1+$C$32) -> 2818.3925 | L32: =K32*(1+$C$32) -> 3100.2318 | M32: =L32*(1+$C$32) -> 3410.2549 | N32: =M32*(1+$C$32) -> 3751.2804 | ... Q32: =P32*(1+$C$32) -> 4992.9542
B33: Sales Price Escalation / Residential Sales Sqft Price | C33: =Assumptions!H19 -> 0.075 | D33: Village | E33: 1750 | F33: =E33 -> 1750 | G33: =F33*(1+$C$33) -> 1881.25 | H33: =G33*(1+$C$33) -> 2022.3438 | I33: =H33*(1+$C$33) -> 2174.0195 | J33: =I33*(1+$C$33) -> 2337.071 | K33: =J33*(1+$C$33) -> 2512.3513 | L33: =K33*(1+$C$33) -> 2700.7777 | M33: =L33*(1+$C$33) -> 2903.336 | N33: =M33*(1+$C$33) -> 3121.0862 | ... Q33: =P33*(1+$C$33) -> 3877.3156
B34: Sales Price Escalation / Residential Sales Sqft Price | C34: 0.1 | D34: Cottages | E34: =Assumptions!G20 -> 1850 | F34: =E34 -> 1850 | G34: =F34*(1+$C$34) -> 2035 | H34: =G34*(1+$C$34) -> 2238.5 | I34: =H34*(1+$C$34) -> 2462.35 | J34: =I34*(1+$C$34) -> 2708.585 | K34: =J34*(1+$C$34) -> 2979.4435 | L34: =K34*(1+$C$34) -> 3277.3879 | M34: =L34*(1+$C$34) -> 3605.1266 | N34: =M34*(1+$C$34) -> 3965.6393 | ... Q34: =P34*(1+$C$34) -> 5278.2659 | U34: Average Res Unit Sales Price
F35: Average Sales $ per Unit | H35: =SUM(G56+H57)/H31 -> 7323020.8 | I35: =SUM(H56+I57)/I31 -> 8734687.5 | J35: =SUM(I56+J57)/J31 -> 9608156.3 | K35: =SUM(J56+K57)/K31 -> 10428052 | T35: =(R56+R57)/R17 -> 7820141.6 | W35: =T35/T18 -> 1.2572013
B36: SOURCES
L37: 0 | R37: =SUM(E37:Q37) -> 0
B38: EQUITY INVESTMENT | L38: 0 | R38: =SUM(E38:Q38) -> 0 | T38: {=SUMPRODUCT(E11:E16*S11:S16)} -> 30975000 | U38: VALUE OF SPEC DEV
B39: SPONSOR - EQUITY CAPITAL | E39: 400000 | R39: =SUM(E39:Q39) -> 400000 | T39: =S39/S41 -> #DIV/0!
B40: LP - EQUITY CAPITAL | E40: 15000000 | R40: =SUM(E40:Q40) -> 15000000 | T40: =S40/S41 -> #DIV/0!
B41: EQUITY INVESTMENT | E41: =SUM(E39:E40) -> 15400000 | F41: =SUM(F39:F40) -> 0 | G41: =SUM(G39:G40) -> 0 | H41: =SUM(H39:H40) -> 0 | I41: =SUM(I39:I40) -> 0 | J41: =SUM(J39:J40) -> 0 | K41: =SUM(K39:K40) -> 0 | L41: =SUM(L39:L40) -> 0 | R41: =SUM(E41:Q41) -> 15400000 | S41: =S39+S40 -> 0 | T41: =(C176+E41)/T38 -> 0.49717514 | U41: ETV | V41: =25000000-E41 -> 9600000 | W41: =25000000-F41 -> 25000000 | Z41: Force to 40mm for total | AA41: =ROUND(40000000-R41,0) -> 24600000
B43: DEBT | C43: =U150 -> 64719113 | T43: =(E48+F48)/(E41+F41+E48+F48) -> 0.76494266 | U43: LTC Year 0+1
B44: SELLER CARRYBACK | R44: =SUM(E44:Q44) -> 0
B45: EB5 - MEZZ DEBT | R45: =SUM(E45:Q45) -> 0
B46: DEV LOAN - DEV COSTS | C46: =U149 -> 0.8118774 | D46: LTC | E46: =MAX(E143+SUM(E153:E154)+SUM(E159:E162)-E41-SUM(E44:E45)-E51-SUM(E56:E57)-D208,0) -> 28150999 | F46: =MAX(F143+SUM(F153:F154)+SUM(F159:F162)-F41-SUM(F44:F45)-F51-SUM(F56:F57)-E208,0) -> 10628481 | R46: =SUM(E46:Q46) -> 38779480 | T46: =(R48)/(R48+R41) -> 0.81460695 | U46: LTC Total
B47: DEV LOAN - FINANCING / RESERVE | E47: =E148+E149 -> 5966884.4 | F47: =F148+F149 -> 5369563.8 | G47: =G148+G149 -> 7558873.3 | H47: =H148+H149 -> 7755405.8 | I47: =I148+I149 -> 2236552.7 | J47: =J148+J149 -> 0 | K47: =K148+K149 -> 0 | L47: =L148+L149 -> 0 | R47: =SUM(E47:Q47) -> 28887280
B48: DEBT | E48: =SUM(E44:E47) -> 34117884 | F48: =SUM(F44:F47) -> 15998045 | G48: =SUM(G44:G47) -> 7558873.3 | H48: =SUM(H44:H47) -> 7755405.8 | I48: =SUM(I44:I47) -> 2236552.7 | J48: =SUM(J44:J47) -> 0 | K48: =SUM(K44:K47) -> 0 | L48: =SUM(L44:L47) -> 0 | M48: =M46 -> 0 | N48: =N46 -> 0 | O48: =O46 -> 0 | P48: =P46 -> 0 | Q48: =Q46 -> 0 | R48: =SUM(E48:Q48) -> 67666761 | T48: =R46/SUM(R51,R56,R57) -> 0.11019829 | U48: LTV
B50: VALUE CREATED POST PUD of 80 ACRES??? | G50: Before, we've put $15M into the Land+Home proforma to "pay ourselves" for the value created for the Resort Lot
B51: LAND SALE TO AMENITY | R51: =SUM(E51:Q51) -> 0
B52: Construction Start Draw + Foundation Complete | C52: 0.2 | G52: =((SUMPRODUCT(H$21:H$30,$D$7:$D$16)*H$32)*$C52) -> 17575250 | H52: =((SUMPRODUCT(I$21:I$30,$D$7:$D$16)*I$32)*$C52) -> 20963250 | I52: =((SUMPRODUCT(J$21:J$30,$D$7:$D$16)*J$32)*$C52) -> 5764893.8 | J52: =((SUMPRODUCT(K$21:K$30,$D$7:$D$16)*K$32)*$C52) -> 9864373.8 | K52: =((SUMPRODUCT(L$21:L$30,$D$7:$D$16)*L$32)*$C52) -> 0 | L52: =((SUMPRODUCT(M$21:M$30,$D$7:$D$16)*M$32)*$C52) -> 0
B53: Structure Complete Draw | C53: 0.15 | G53: =((SUMPRODUCT(H$21:H$30,$D$7:$D$16)*H$32)*$C53) -> 13181438 | H53: =((SUMPRODUCT(I$21:I$30,$D$7:$D$16)*I$32)*$C53) -> 15722438 | I53: =((SUMPRODUCT(J$21:J$30,$D$7:$D$16)*J$32)*$C53) -> 4323670.3 | J53: =((SUMPRODUCT(K$21:K$30,$D$7:$D$16)*K$32)*$C53) -> 7398280.3 | K53: =((SUMPRODUCT(L$21:L$30,$D$7:$D$16)*L$32)*$C53) -> 0 | L53: =((SUMPRODUCT(M$21:M$30,$D$7:$D$16)*M$32)*$C53) -> 0
B54: MEP 4-way + Finishes Start Draw | C54: 0.15 | H54: =((SUMPRODUCT(H$21:H$30,$D$7:$D$16)*H$32)*$C54) -> 13181438 | I54: =((SUMPRODUCT(I$21:I$30,$D$7:$D$16)*I$32)*$C54) -> 15722438 | J54: =((SUMPRODUCT(J$21:J$30,$D$7:$D$16)*J$32)*$C54) -> 4323670.3 | K54: =((SUMPRODUCT(K$21:K$30,$D$7:$D$16)*K$32)*$C54) -> 7398280.3 | L54: =((SUMPRODUCT(L$21:L$30,$D$7:$D$16)*L$32)*$C54) -> 0 | M54: =((SUMPRODUCT(M$21:M$30,$D$7:$D$16)*M$34)*$C54) -> 0 | N54: =((SUMPRODUCT(N$21:N$30,$D$7:$D$16)*N$34)*$C54) -> 0 | O54: =((SUMPRODUCT(O$21:O$30,$D$7:$D$16)*O$34)*$C54) -> 0 | P54: =((SUMPRODUCT(P$21:P$30,$D$7:$D$16)*P$34)*$C54) -> 0 | Q54: =((SUMPRODUCT(Q$21:Q$30,$D$7:$D$16)*Q$34)*$C54) -> 0
B55: Unit Reservations w/ Membership Purchase (50/50) | C55: 0 | E55: =+$C55*SUMPRODUCT(F7:F16,$D$7:$D$16,T$21:T$30) -> 0 | F55: =+$C55*SUMPRODUCT(G7:G16,$D$7:$D$16,U$21:U$30) -> 0 | G55: =+$C55*SUMPRODUCT(H7:H16,$D$7:$D$16,V$21:V$30) -> 0 | H55: =+$C55*SUMPRODUCT(I7:I16,$D$7:$D$16,W$21:W$30) -> 0 | I55: =+$C55*SUMPRODUCT(J7:J16,$D$7:$D$16,X$21:X$30) -> 0 | J55: =+$C55*SUMPRODUCT(K7:K16,$D$7:$D$16,Y$21:Y$30) -> 0 | K55: =+$C55*SUMPRODUCT(L7:L16,$D$7:$D$16,Z$21:Z$30) -> 0 | L55: =+$C55*SUMPRODUCT(M7:M16,$D$7:$D$16,AA$21:AA$30) -> 0 | ... Q55: =+$C55*SUMPRODUCT(R7:R16,$D$7:$D$16,AF$21:AF$30) -> 0
B56: PRESALE REVENUES | C56: =SUM(C52:C55) -> 0.5 | E56: =SUM(E52:E55)/2 -> 0 | F56: =SUM(F52:F55)/2 -> 0 | G56: =SUM(G52:G55)/2 -> 15378344 | H56: =SUM(H52:H55)/2 -> 24933563 | I56: =SUM(I52:I55)/2 -> 12905501 | J56: =SUM(J52:J55)/2 -> 10793162 | K56: =SUM(K52:K55)/2 -> 3699140.2 | L56: =SUM(L52:L55)/2 -> 0 | M56: =SUM(M52:M54) -> 0 | N56: =SUM(N52:N54) -> 0 | O56: =SUM(O52:O54) -> 0 | P56: =SUM(P52:P54) -> 0 | Q56: =SUM(Q52:Q54) -> 0 | R56: =SUM(E56:Q56) -> 67709709 | S56: 71165446 | T56: TOTAL HOME SALES
B57: UNIT SALES | F57: =SUMPRODUCT(E$7:E$15,$D7:$D$15,U$21:U$29)-(E56) -> 24500000 | G57: =SUMPRODUCT(F$7:F$16,$D7:$D$16,V$21:V$30)-(F56) -> 50050000 | H57: =SUMPRODUCT(G$7:G$16,$D7:$D$16,W$21:W$30)-(G56) -> 72497906 | I57: =SUMPRODUCT(H$7:H$16,$D7:$D$16,X$21:X$30)-(H56) -> 79882688 | J57: =SUMPRODUCT(I$7:I$16,$D7:$D$16,Y$21:Y$30)-(I56) -> 15918968 | K57: =SUMPRODUCT(J$7:J$16,$D7:$D$16,Z$21:Z$30)-(J56) -> 41347099 | M57: =SUMPRODUCT(M$21:M$30,$D7:$D$16,AA$21:AA$30)-L56 -> 0 | N57: =SUMPRODUCT(N$21:N$30,$D7:$D$16,AB$21:AB$30)-M56 -> 0 | O57: =SUMPRODUCT(O$21:O$30,$D7:$D$16,AC$21:AC$30)-N56 -> 0 | P57: =SUMPRODUCT(P$21:P$30,$D7:$D$16,AD$21:AD$30)-O56 -> 0 | Q57: =SUMPRODUCT(Q$21:Q$30,$D7:$D$16,AE$21:AE$30)-P56 -> 0 | R57: =SUM(E57:Q57) -> 2.8419666e+08 | S57: 2.7855487e+08 | T57: =R57+(R56) -> 3.5190637e+08 | U57: =T57/R17 -> 7820141.6 | V57: =T57/D18 -> 2216.733 | W57: average $/sf
B58: TOTAL SOURCES | E58: =E41+E48+SUM(E50:E51)+SUM(E56:E57) -> 49517884 | F58: =F41+F48+SUM(F50:F51)+SUM(F56:F57) -> 40498045 | G58: =G41+G48+SUM(G50:G51)+SUM(G56:G57) -> 72987217 | H58: =H41+H48+SUM(H50:H51)+SUM(H56:H57) -> 1.0518687e+08 | I58: =I41+I48+SUM(I50:I51)+SUM(I56:I57) -> 95024741 | J58: =J41+J48+SUM(J50:J51)+SUM(J56:J57) -> 26712130 | K58: =K41+K48+SUM(K50:K51)+SUM(K56:K57) -> 45046239 | L58: =L41+L48+SUM(L50:L51)+SUM(L56:L57) -> 0 | M58: =M41+M48+SUM(M51:M57) -> 0 | N58: =N41+N48+SUM(N51:N57) -> 0 | O58: =O41+O48+SUM(O51:O57) -> 0 | P58: =P41+P48+SUM(P51:P57) -> 0 | Q58: =Q41+Q48+SUM(Q51:Q57) -> 0 | R58: =SUM(E58:Q58) -> 4.3497313e+08 | T58: TOTAL SALES
T59: =(R56)+R57 -> 3.5190637e+08 | U59: =T59/D18 -> 2216.733 | V59: average $/sf
B60: USES | S60: =S65-R65 -> 58661724
B61: LAND & PROJECT ACQUISITION | V61: =E62*0.65 -> 12025000 | W61: 0.65
B62: Project Acquisition | E62: 18500000 | F62: 0 | G62: 0 | H62: 0 | I62: 0 | J62: 0 | K62: 0 | L62: 0 | R62: =SUM(E62:L62) -> 18500000 | V62: =E62*0.85 -> 15725000 | W62: 0.85
B63: Asset Acquisition Fee (based on total project initial value Equity + Debt) | C63: 0.005 | E63: =90000000*$C$63 -> 450000 | G63: 0 | H63: 0 | I63: 0 | J63: 0 | K63: 0 | L63: 0 | R63: =SUM(E63:L63) -> 450000
B64: Closing Costs | C64: 0.0015 | E64: =E62*$C$64 -> 27750 | F64: 0 | G64: 0 | H64: 0 | I64: 0 | J64: 0 | K64: 0 | L64: 0 | M64: =M62*$C$64 -> 0 | N64: =N62*$C$64 -> 0 | O64: =O62*$C$64 -> 0 | P64: =P62*$C$64 -> 0 | Q64: =Q62*$C$64 -> 0 | R64: =SUM(E64:Q64) -> 27750 | V64: 18423158 | W64: 1
B65: LAND & PROJECT ACQUISITION | E65: =SUM(E62:E64) -> 18977750 | F65: =SUM(F62:F64) -> 0 | G65: =SUM(G62:G64) -> 0 | H65: =SUM(H62:H64) -> 0 | I65: =SUM(I62:I64) -> 0 | J65: =SUM(J62:J64) -> 0 | K65: =SUM(K62:K64) -> 0 | L65: =SUM(L62:L64) -> 0 | ... Q65: =SUM(Q62:Q64) -> 0 | R65: =SUM(E65:Q65) -> 18977750 | S65: 77639474 | T65: =R65/R17 -> 421727.78 | U65: $/Lot
B67: HARD COSTS - SITE, RESTORATION & INFRASTRUCTURE
B68: Internal Road: Base + Gravel Finish @ Lower 80 | C68: =235000*1.25 -> 293750 | E68: =$C$68*0.5 -> 146875 | F68: =$C$68*0.5 -> 146875 | G68: 0 | H68: =$C68*I$67 -> 0 | I68: 0 | J68: 0 | K68: 0 | L68: 0 | M68: 0 | N68: 0 | O68: 0 | P68: 0 | R68: =SUM(E68:P68) -> 293750 | T68: =C68-R68 -> 0
B69: Internal Road: Base + Gravel Finish @ 45 Lots | C69: =590000*1.25 -> 737500 | F69: =$C$69/3 -> 245833.33 | G69: =$C$69/3 -> 245833.33 | H69: =$C$69/3 -> 245833.33 | I69: 0 | J69: 0 | K69: 0 | L69: 0 | M69: 0 | N69: 0 | O69: 0 | P69: 0 | R69: =SUM(E69:P69) -> 737500 | T69: =C69-R69 -> 0
B70: Internal Road: Paving @ 45 Lots | C70: =350000*1.25 -> 437500 | E70: =$C70*F$67 -> 0 | F70: =$C$70/3 -> 145833.33 | G70: =$C$70/3 -> 145833.33 | H70: =$C$70/3 -> 145833.33 | I70: 0 | J70: 0 | K70: 0 | L70: 0 | M70: 0 | N70: 0 | O70: 0 | P70: 0 | R70: =SUM(E70:P70) -> 437500 | T70: =C70-R70 -> 0
B71: County/USFS Road: BASE + GRAVEL FINISH @ end of existing | C71: =500000*1.25 -> 625000 | E71: =$C$71/2 -> 312500 | F71: 0 | G71: =$C$71/2 -> 312500 | H71: 0 | I71: 0 | J71: 0 | K71: 0 | L71: 0 | M71: 0 | N71: 0 | O71: 0 | P71: 0 | R71: =SUM(E71:P71) -> 625000 | T71: =C71-R71 -> 0
B72: County/USFS Road: PAVING @ end of existing to back gate | C72: =500000*1.25 -> 625000 | E72: 0 | F72: =$C72/2 -> 312500 | G72: 0 | H72: =$C72/2 -> 312500 | I72: 0 | J72: 0 | K72: 0 | L72: 0 | M72: 0 | N72: 0 | O72: 0 | P72: 0 | R72: =SUM(E72:P72) -> 625000 | T72: =C72-R72 -> 0
B73: Road: Bridges (1) @ Spillway | C73: 150000 | E73: =$C$73 -> 150000 | F73: 0 | G73: 0 | H73: 0 | I73: 0 | J73: 0 | K73: 0 | L73: 0 | M73: 0 | N73: 0 | O73: 0 | P73: 0 | R73: =SUM(E73:P73) -> 150000 | T73: =C73-R73 -> 0
B74: Utilities: County/USFS Power Trench+Line (4.5 miles) | C74: =650000*1.25 -> 812500 | E74: =$C$74 -> 812500 | F74: 0 | G74: 0 | H74: 0 | I74: 0 | J74: 0 | K74: 0 | L74: 0 | M74: 0 | N74: 0 | O74: 0 | P74: 0 | R74: =SUM(E74:P74) -> 812500 | T74: =C74-R74 -> 0
B75: Utilities: Power & Transformers @ 45 Lots (8,500 LF) | C75: =(105000*1.25)+15*4000 -> 191250 | E75: =$C75/3 -> 63750 | F75: =$C75/3 -> 63750 | G75: =$C75/3 -> 63750 | H75: 0 | I75: 0 | J75: 0 | K75: 0 | L75: 0 | M75: 0 | N75: 0 | O75: 0 | P75: 0 | R75: =SUM(E75:P75) -> 191250 | T75: =C75-R75 -> 0
B76: Utilities: Comm. Distrib. @ 45 Lots (8,500 LF) | C76: =(8500*15)*1.25 -> 159375 | E76: =$C76/3 -> 53125 | F76: =$C76/3 -> 53125 | G76: =$C76/3 -> 53125 | H76: 0 | I76: 0 | J76: 0 | K76: 0 | L76: 0 | M76: 0 | N76: 0 | O76: 0 | P76: 0 | R76: =SUM(E76:P76) -> 159375 | T76: =C76-R76 -> 0
B77: Utilities: Water Main @ 45 Lots | C77: =550000*1.25 -> 687500 | E77: =$C77/3 -> 229166.67 | F77: =$C77/3 -> 229166.67 | G77: =$C77/3 -> 229166.67 | H77: 0 | I77: 0 | J77: 0 | K77: 0 | L77: 0 | M77: 0 | N77: 0 | O77: 0 | P77: 0 | R77: =SUM(E77:P77) -> 687500 | T77: =C77-R77 -> 0
B78: Utilities: Water Wells, Pumps & Backup Power Requirements | C78: =1000000*1.25 -> 1250000 | E78: =$C$78/2 -> 625000 | F78: =$C$78/2 -> 625000 | G78: 0 | H78: 0 | I78: 0 | J78: 0 | K78: 0 | L78: 0 | M78: 0 | N78: 0 | O78: 0 | P78: 0 | R78: =SUM(E78:P78) -> 1250000 | T78: =C78-R78 -> 0
B79: Utilities: Lift Station @ 45 Lots (8,500 LF) | C79: =125000*1.25 -> 156250 | E79: =($C79)/3 -> 52083.333 | F79: =($C79)/3 -> 52083.333 | G79: =($C79)/3 -> 52083.333 | H79: 0 | I79: 0 | J79: 0 | K79: 0 | L79: 0 | M79: 0 | N79: 0 | O79: 0 | P79: 0 | R79: =SUM(E79:P79) -> 156250 | T79: =C79-R79 -> 0
B80: Utilities: Sewer Treatment Drainfield Sys (4 EA) | C80: =625000*1.25 -> 781250 | E80: =$C80/4 -> 195312.5 | F80: =$C80/4 -> 195312.5 | G80: =$C80/4 -> 195312.5 | H80: =$C80/4 -> 195312.5 | I80: 0 | J80: 0 | K80: 0 | L80: 0 | M80: 0 | N80: 0 | O80: 0 | P80: 0 | R80: =SUM(E80:P80) -> 781250 | T80: =C80-R80 -> 0
B81: Utilities: Geothermal Infrastructure @ 45 Lots | C81: =175000*1.25 -> 218750 | E81: =$C81/3 -> 72916.667 | F81: =$C81/3 -> 72916.667 | G81: =$C81/3 -> 72916.667 | H81: 0 | I81: 0 | J81: 0 | K81: 0 | L81: 0 | M81: 0 | N81: 0 | O81: 0 | P81: 0 | R81: =SUM(E81:P81) -> 218750 | T81: =C81-R81 -> 0
B82: Landscape: Early Plantings in Public Areas | C82: 750000 | E82: =$C$82/3 -> 250000 | F82: =$C$82/3 -> 250000 | G82: =$C$82/3 -> 250000 | H82: =$C82*I$67 -> 0 | I82: =$C82*I$67 -> 0 | J82: =$C82*J$67 -> 0 | K82: 0 | L82: 0 | M82: 0 | N82: 0 | O82: 0 | P82: 0 | R82: =SUM(E82:P82) -> 750000 | T82: =C82-R82 -> 0
B83: Construction Cost Escalation | C83: 0.05 | E83: =SUM(E67:E82,D83)*$C83 -> 148161.46 | F83: =SUM(F67:F82,E83)*$C83 -> 127027.86 | G83: =SUM(G67:G82,E83:F83)*$C83 -> 94785.508 | H83: =SUM(H67:H82,E83:G83)*$C83 -> 63472.7 | I83: 0 | J83: 0 | K83: 0 | L83: 0 | R83: =SUM(E83:Q83) -> 433447.53
B84: Developer Construction Contingency | C84: 0.05 | E84: =SUM(E68:E82)*$C$84 -> 148161.46 | F84: =SUM(F68:F82)*$C$84 -> 119619.79 | G84: =SUM(G68:G82)*$C$84 -> 81026.042 | H84: =SUM(H68:H82)*$C$84 -> 44973.958 | I84: =SUM(I68:I82)*$C$84 -> 0 | J84: =SUM(J68:J82)*$C$84 -> 0 | K84: =SUM(K68:K82)*$C$84 -> 0 | L84: =SUM(L68:L82)*$C$84 -> 0 | M84: 0 | N84: 0 | O84: 0 | P84: 0 | R84: =SUM(E84:Q84) -> 393781.25
B85: =B67 -> HARD COSTS - SITE, RESTORATION & INFRASTRUCTURE | E85: =SUM(E67:E84) -> 3259552.1 | F85: =SUM(F67:F84) -> 2639043.5 | G85: =SUM(G67:G84) -> 1796332.4 | H85: =SUM(H67:H84) -> 1007925.8 | I85: =SUM(I67:I84) -> 0 | J85: =SUM(J67:J84) -> 0 | K85: =SUM(K67:K84) -> 0 | L85: =SUM(L67:L84) -> 0 | ... P85: =SUM(P67:P84) -> 0 | R85: =SUM(E85:Q85) -> 8702853.8 | S85: 8694686.4 | T85: =R85/$R$17 -> 193396.75 | U85: $/Lot
T86: =R85/$T$59 -> 0.024730595 | U86: of Sales
B87: HARD COSTS - HOMES
B88: Infrastructure (Utilities & Driveway) | C88: 100000 | E88: =((E$17*$C88)*0.25)+((F$17*$C88)*0.75) -> 725000 | F88: =((F$17*$C88)*0.25)+((G$17*$C88)*0.75) -> 1100000 | G88: =((G$17*$C88)*0.25)+((H$17*$C88)*0.75) -> 1200000 | H88: =((H$17*$C88)*0.25)+((I$17*$C88)*0.75) -> 525000 | I88: =((I$17*$C88)*0.25)+((J$17*$C88)*0.75) -> 450000 | J88: =((J$17*$C88)*0.25)+((K$17*$C88)*0.75) -> 125000 | K88: =((K$17*$C88)*0.25)+((L$17*$C88)*0.75) -> 0 | M88: =((L$17*$C88)*0.25)+((M$17*$C88)*0.75) -> 0 | N88: =((M$17*$C88)*0.25)+((N$17*$C88)*0.75) -> 0 | O88: =((N$17*$C88)*0.25)+((O$17*$C88)*0.75) -> 0 | P88: =((O$17*$C88)*0.25)+((P$17*$C88)*0.75) -> 0 | Q88: =((P$17*$C88)*0.25)+((Q$17*$C88)*0.75) -> 0 | R88: =SUM(E88:Q88) -> 4125000 | T88: =R88/$R$17 -> 91666.667 | U88: /LOT | V88: Build Cost $/sf Check
B89: Vertical Construction Costs | C89: =Assumptions!C17 -> 850 | E89: =(((SUMPRODUCT($D$7:$D$16,E7:E16))*$C89)) -> 14875000 | F89: =(((SUMPRODUCT($D$7:$D$16,F7:F16))*$C89)) -> 22100000 | G89: =(((SUMPRODUCT($D$7:$D$16,G7:G16))*$C89)) -> 35275000 | H89: =(((SUMPRODUCT($D$7:$D$16,H7:H16))*$C89)) -> 38250000 | I89: =(((SUMPRODUCT($D$7:$D$16,I7:I16))*$C89)) -> 9562500 | J89: =(((SUMPRODUCT($D$7:$D$16,J7:J16))*$C89)) -> 14875000 | K89: =(((SUMPRODUCT($D$7:$D$16,K7:K16))*$C89)) -> 0 | L89: =(((SUMPRODUCT($D$7:$D$16,L7:L16))*$C89)) -> 0 | M89: =(((SUMPRODUCT($D$7:$D$16,L7:L16))*$C89)*0.5)+(((SUMPRODUCT($D$7:$D$16,M7:M16))*$C89)*0.5) -> 0 | N89: =(((SUMPRODUCT($D$7:$D$16,M7:M16))*$C89)*0.5)+(((SUMPRODUCT($D$7:$D$16,N7:N16))*$C89)*0.5) -> 0 | O89: =(((SUMPRODUCT($D$7:$D$16,N7:N16))*$C89)*0.5)+(((SUMPRODUCT($D$7:$D$16,O7:O16))*$C89)*0.5) -> 0 | P89: =(((SUMPRODUCT($D$7:$D$16,O7:O16))*$C89)*0.5)+(((SUMPRODUCT($D$7:$D$16,P7:P16))*$C89)*0.5) -> 0 | Q89: =(((SUMPRODUCT($D$7:$D$16,P7:P16))*$C89)*0.5)+(((SUMPRODUCT($D$7:$D$16,Q7:Q16))*$C89)*0.5) -> 0 | R89: =SUM(E89:Q89) -> 134937500 | T89: =R89/$R$17 -> 2998611.1 | U89: AVE / HOME | V89: =R89/$V$17 -> 850
B90: Landscape / Hardscape | C90: 150000 | F90: =E$17*$C90 -> 750000 | G90: =F$17*$C90 -> 1200000 | H90: =G$17*$C90 -> 1800000 | I90: =H$17*$C90 -> 1800000 | J90: =I$17*$C90 -> 450000 | K90: =J$17*$C90 -> 750000 | L90: =K$17*$C90 -> 0 | M90: =L$17*$C90 -> 0 | ... Q90: =P$17*$C90 -> 0 | R90: =SUM(F90:Q90) -> 6750000 | T90: =R90/$R$17 -> 150000 | U90: /LOT
B91: Construction Management | C91: 0.035 | E91: =SUM(E88:E90)*$C91 -> 546000 | F91: =SUM(F88:F90)*$C91 -> 838250 | G91: =SUM(G88:G90)*$C91 -> 1318625 | H91: =SUM(H88:H90)*$C91 -> 1420125 | I91: =SUM(I88:I90)*$C91 -> 413437.5 | J91: =SUM(J88:J90)*$C91 -> 540750 | K91: =SUM(K88:K90)*$C91 -> 26250 | L91: =SUM(L88:L90)*$C91 -> 0 | R91: =SUM(E91:Q91) -> 5103437.5 | T91: =R91/$R$17 -> 113409.72 | U91: AVE / HOME
B92: Construction Cost Escalation | C92: 0.05 | E92: =SUM(E88:E90)*$C92 -> 780000 | F92: =SUM(F88:F90,E92)*$C92 -> 1236500 | G92: =SUM(G88:G90,E92:F92)*$C92 -> 1984575 | H92: =SUM(H88:H90,E92:G92)*$C92 -> 2228803.8 | I92: =SUM(I88:I90,E92:H92)*$C92 -> 902118.94 | J92: =SUM(J88:J90,E92:I92)*$C92 -> 1129099.9 | K92: =SUM(K88:K90,E92:J92)*$C92 -> 450554.88 | R92: =SUM(E92:Q92) -> 8711652.5 | T92: =R92/$R$17 -> 193592.28 | U92: AVE / HOME
B93: Developer Construction Contingency | C93: 0.035 | E93: =SUM(E87:E90)*$C93 -> 546000 | F93: =SUM(F87:F90)*$C93 -> 838250 | G93: =SUM(G87:G90)*$C93 -> 1318625 | H93: =SUM(H87:H90)*$C93 -> 1420125 | I93: =SUM(I87:I90)*$C93 -> 413437.5 | J93: =SUM(J87:J90)*$C93 -> 540750 | K93: =SUM(K87:K90)*$C93 -> 26250 | L93: =SUM(L87:L90)*$C93 -> 0 | ... Q93: =SUM(Q87:Q90)*$C93 -> 0 | R93: =SUM(E93:Q93) -> 5103437.5 | T93: =R93/$R$17 -> 113409.72 | U93: AVE / HOME | V93: Total Cost $/sf Check
B94: =B87 -> HARD COSTS - HOMES | E94: =SUM(E87:E93) -> 17472000 | F94: =SUM(F87:F93) -> 26863000 | G94: =SUM(G87:G93) -> 42296825 | H94: =SUM(H87:H93) -> 45644054 | I94: =SUM(I87:I93) -> 13541494 | J94: =SUM(J87:J93) -> 17660600 | K94: =SUM(K87:K93) -> 1253054.9 | L94: =SUM(L87:L93) -> 0 | ... Q94: =SUM(Q87:Q93) -> 0 | R94: =SUM(E94:Q94) -> 1.6473103e+08 | S94: 1.6472096e+08 | T94: =R94/$R$17 -> 3660689.5 | U94: AVE / HOME | V94: =R94/$V$17 -> 1037.6758
T95: =R94/$T$59 -> 0.46811039 | U95: of Sales
B96: SOFT COSTS PROFESSIONALS - FINAL ENTITLEMENTS & SITE INFRA.
B97: Land Planning & PUD App Prep/Revisions (15% of Cost) | C97: =(SUM(C82:C82))*0.15 -> 112500 | E97: =$C$97*0.75 -> 84375 | F97: =$C$97*0.25 -> 28125 | R97: =SUM(E97:Q97) -> 112500 | T97: =C97-R97 -> 0
B98: Future Entitlement Management Overhead | C98: 500000 | E98: =$C98 -> 500000 | F98: =$C98 -> 500000 | G98: =$C98 -> 500000 | H98: =$C98 -> 500000 | R98: =SUM(E98:Q98) -> 2000000
B99: Civil, Surveying & PUD App Prep/Revisions (10% of Infra Cost) | C99: =(SUM(C68:C81))*0.1 -> 712562.5 | E99: =$C$99*0.55 -> 391909.38 | F99: =$C$99*0.2 -> 142512.5 | G99: =$C$99*0.2 -> 142512.5 | H99: =$C$99*0.05 -> 35628.125 | R99: =SUM(E99:Q99) -> 712562.5 | T99: =C99-R99 -> 0
B100: Traffic, Enviro, Economist & Misc. Studies | C100: 300000 | E100: =$C$100 -> 300000 | R100: =SUM(E100:Q100) -> 300000 | T100: =C100-R100 -> 0
B101: Legal / Entitlement | C101: 400000 | E101: =C101*0.75 -> 300000 | F101: =C101*0.25 -> 100000 | R101: =SUM(E101:Q101) -> 400000 | T101: =C101-R101 -> 0
B102: Accounting & CPA costs ($ per year) | C102: 10000 | E102: =$C$102 -> 10000 | F102: =$C$102 -> 10000 | G102: =$C$102 -> 10000 | H102: =$C$102 -> 10000 | I102: =$C$102 -> 10000 | J102: =$C$102 -> 10000 | K102: =$C$102 -> 10000 | R102: =SUM(E102:Q102) -> 70000
B103: Professionals Contingency | C103: 0.05 | E103: =SUM(E96:E102)*$C$103 -> 79314.219 | F103: =SUM(F96:F102)*$C$103 -> 39031.875 | G103: =SUM(G96:G102)*$C$103 -> 32625.625 | H103: =SUM(H96:H102)*$C$103 -> 27281.406 | Q103: =SUM(Q99:Q102)*$C$103 -> 0 | R103: =SUM(E103:Q103) -> 178253.12
B104: =B96 -> SOFT COSTS PROFESSIONALS - FINAL ENTITLEMENTS & SITE INFRA. | E104: =SUM(E96:E103) -> 1665598.6 | F104: =SUM(F96:F103) -> 819669.38 | G104: =SUM(G96:G103) -> 685138.12 | H104: =SUM(H96:H103) -> 572909.53 | I104: =SUM(I96:I103) -> 10000 | J104: =SUM(J96:J103) -> 10000 | K104: =SUM(K96:K103) -> 10000 | L104: =SUM(L96:L103) -> 0 | ... Q104: =SUM(Q96:Q103) -> 0 | R104: =SUM(E104:Q104) -> 3773315.6 | S104: 3237815.6 | T104: =R104/$R$17 -> 83851.458 | U104: $/Lot
...

Sheet Returns Land+Home
B1: ='Proforma Land+Home'!B1 -> CLARENDON - LAND & HOME DEVELOPMENT
B2: Returns Analysis
B4: PROJECT FINANCING ANALYSIS | F4: BUSINESS CASE ANALYSIS
B5: TOTAL PROJECT CAPITAL NEEDS: | D5: ='Proforma Land+Home'!R41+'Proforma Land+Home'!R48 -> 83066761 | F5: TOTAL PROJECT REVENUE (less brokers fees): | H5: =('Proforma Land+Home'!R51+'Proforma Land+Home'!R57+'Proforma Land+Home'!R56)-'Proforma Land+Home'!R121 -> 3.3911752e+08
B6: TOTAL PROJECT VALUE (PV of FINAL BUILD OUT): | D6: ='Proforma Land+Home'!T17 -> 279912500 | F6: - TOTAL PROJECT COST: | H6: ='Proforma Land+Home'!R143-'Proforma Land+Home'!R121+'Proforma Land+Home'!R148+'Proforma Land+Home'!R149+'Proforma Land+Home'!R159+'Proforma Land+Home'!R160+'Proforma Land+Home'!R165 -> 2.5078657e+08
B7: STARTING SPEC DEVELOPMENT VALUE: | D7: ='Proforma Land+Home'!T38 -> 30975000 | F7: = NET PROFIT | H7: =H5-H6 -> 88330954
B8: EQUITY to SPEC DEV VALUE (ETV): | D8: ='Proforma Land+Home'!T41 -> 0.49717514 | F8: NET PROFIT %: | H8: =H7/H5 -> 0.26047299
B9: LOAN to COST (LTC): | D9: ='Proforma Land+Home'!T46 -> 0.81460695 | F9: RETURN on EQUITY/CAPTIAL (ROE): | H9: =H7/'Proforma Land+Home'!E41 -> 5.7357762
B10: LOAN to VALUE (LTV): | D10: ='Proforma Land+Home'!T48 -> 0.11019829
B12: PROJECT RETURNS ANALYSIS
B13: PROJECT NET CASH FLOWS: | D13: =SUM('Proforma Land+Home'!E210:Q210) -> 88855954
B14: EQUITY MULTIPLE: | D14: ='Proforma Land+Home'!R204/-F48 -> 6.7698671
B15: MODELED ROI: | D15: =D13/-F48 -> 5.7698671
B16: PROJECT IRR : | D16: =XIRR('Proforma Land+Home'!E210:Q210,'Proforma Land+Home'!E5:Q5) -> 0.53538527
F18: ='Proforma Land+Home'!E3 -> Year 0 | G18: ='Proforma Land+Home'!F3 -> Year 1 | H18: ='Proforma Land+Home'!G3 -> Year 2 | I18: ='Proforma Land+Home'!H3 -> Year 3 | J18: ='Proforma Land+Home'!I3 -> Year 4 | K18: ='Proforma Land+Home'!J3 -> Year 5 | L18: ='Proforma Land+Home'!K3 -> Year 6 | M18: ='Proforma Land+Home'!L3 -> Year 7 | ... R18: ='Proforma Land+Home'!Q3 -> Year 12
F19: ='Proforma Land+Home'!E4 -> 2025 | G19: ='Proforma Land+Home'!F4 -> 2026 | H19: ='Proforma Land+Home'!G4 -> 2027 | I19: ='Proforma Land+Home'!H4 -> 2028 | J19: ='Proforma Land+Home'!I4 -> 2029 | K19: ='Proforma Land+Home'!J4 -> 2030 | L19: ='Proforma Land+Home'!K4 -> 2031 | M19: ='Proforma Land+Home'!L4 -> 2032 | ... R19: ='Proforma Land+Home'!Q4 -> 2037
B20: SUMMARY OF RETURNS | F20: ='Proforma Land+Home'!E5 -> 45658 | G20: ='Proforma Land+Home'!F5 -> 46023 | H20: ='Proforma Land+Home'!G5 -> 46388 | I20: ='Proforma Land+Home'!H5 -> 46753 | J20: ='Proforma Land+Home'!I5 -> 47119 | K20: ='Proforma Land+Home'!J5 -> 47484 | L20: ='Proforma Land+Home'!K5 -> 47849 | M20: ='Proforma Land+Home'!L5 -> 48214 | ... R20: ='Proforma Land+Home'!Q5 -> 50040
B21: Equity LP Returns
B22: Capital Return | D22: =SUM(F22:R22) -> 20940638 | F22: ='Proforma Land+Home'!E175 -> 0 | G22: ='Proforma Land+Home'!F175 -> 0 | H22: ='Proforma Land+Home'!G175 -> 1968762.1 | I22: ='Proforma Land+Home'!H175 -> 6074217.7 | J22: ='Proforma Land+Home'!I175 -> 12897658 | K22: ='Proforma Land+Home'!J175 -> 0 | L22: ='Proforma Land+Home'!K175 -> 0 | M22: ='Proforma Land+Home'!L175 -> 0 | ... R22: ='Proforma Land+Home'!Q175 -> 0
B23: Profit Split | D23: =SUM(F23:R23) -> 44173914 | F23: ='Proforma Land+Home'!E201-F22 -> 0 | G23: ='Proforma Land+Home'!F201-G22 -> 0 | H23: ='Proforma Land+Home'!G201-H22 -> 0 | I23: ='Proforma Land+Home'!H201-I22 -> 0 | J23: ='Proforma Land+Home'!I201-J22 -> 22249737 | K23: ='Proforma Land+Home'!J201-K22 -> 2681101.7 | L23: ='Proforma Land+Home'!K201-L22 -> 19243076 | M23: ='Proforma Land+Home'!L201-M22 -> 0 | ... R23: ='Proforma Land+Home'!Q201-R22 -> 0
B24: Total Distributions | D24: =SUM(F24:R24) -> 65114552 | F24: =F22+F23 -> 0 | G24: =G22+G23 -> 0 | H24: =H22+H23 -> 1968762.1 | I24: =I22+I23 -> 6074217.7 | J24: =J22+J23 -> 35147395 | K24: =K22+K23 -> 2681101.7 | L24: =L22+L23 -> 19243076 | M24: =M22+M23 -> 0 | ... R24: =R22+R23 -> 0
B25: Total Contributions | D25: =SUM(F25:R25) -> 15000000 | F25: =-'Proforma Land+Home'!E177 -> 15000000 | G25: =-'Proforma Land+Home'!F177 -> 0
B26: Net Profit / Cash Flows | D26: =SUM(F26:R26) -> 50114552 | F26: =F24-F25 -> -15000000 | G26: =G24-G25 -> 0 | H26: =H24-H25 -> 1968762.1 | I26: =I24-I25 -> 6074217.7 | J26: =J24-J25 -> 35147395 | K26: =K24-K25 -> 2681101.7 | L26: =L24-L25 -> 19243076 | M26: =M24-M25 -> 0 | ... R26: =R24-R25 -> 0
B27: IRR | F27: =XIRR(F26:R26,F20:R20) -> 0.40926964
B28: Equity Multiple | F28: =SUMIF(F26:R26,">0")/-SUMIF(F26:R26,"<0") -> 4.3409702
B29: Cumulative (Equity) Cash Position | F29: =F26+E29 -> -15000000 | G29: =G26+F29 -> -15000000 | H29: =H26+G29 -> -13031238 | I29: =I26+H29 -> -6957020.3 | J29: =J26+I29 -> 28190375 | K29: =K26+J29 -> 30871476 | L29: =L26+K29 -> 50114552 | M29: =M26+L29 -> 50114552 | ... R29: =R26+Q29 -> 50114552
B31: MO LP Returns
B32: Capital Return + Pref | F32: ='Proforma Land+Home'!E181 -> 0 | G32: ='Proforma Land+Home'!F181 -> 0 | H32: ='Proforma Land+Home'!G181 -> 52500.322 | I32: ='Proforma Land+Home'!H181 -> 161979.14 | J32: ='Proforma Land+Home'!I181 -> 343937.56 | K32: ='Proforma Land+Home'!J181 -> 0 | L32: ='Proforma Land+Home'!K181 -> 0 | M32: ='Proforma Land+Home'!L181 -> 0 | ... R32: ='Proforma Land+Home'!Q181 -> 0
B33: Profit Split | F33: ='Proforma Land+Home'!E202-F32 -> 0 | G33: ='Proforma Land+Home'!F202-G32 -> 0 | H33: ='Proforma Land+Home'!G202-H32 -> 0 | I33: ='Proforma Land+Home'!H202-I32 -> 0 | J33: ='Proforma Land+Home'!I202-J32 -> 593326.31 | K33: ='Proforma Land+Home'!J202-K32 -> 71496.046 | L33: ='Proforma Land+Home'!K202-L32 -> 513148.69 | M33: ='Proforma Land+Home'!L202-M32 -> 0 | ... R33: ='Proforma Land+Home'!Q202-R32 -> 0
B34: Total Distributions | D34: =SUM(F34:R34) -> 1736388.1 | F34: =SUM(F32:F33) -> 0 | G34: =SUM(G32:G33) -> 0 | H34: =SUM(H32:H33) -> 52500.322 | I34: =SUM(I32:I33) -> 161979.14 | J34: =SUM(J32:J33) -> 937263.87 | K34: =SUM(K32:K33) -> 71496.046 | L34: =SUM(L32:L33) -> 513148.69 | M34: =SUM(M32:M33) -> 0 | ... R34: =SUM(R32:R33) -> 0
B35: Total Contributions | D35: =SUM(F35:R35) -> 400000 | F35: =-'Proforma Land+Home'!E183 -> 400000
B36: Net Profit / Cash Flows | D36: =SUM(F36:R36) -> 1336388.1 | F36: =F34-F35 -> -400000 | G36: =G34-G35 -> 0 | H36: =H34-H35 -> 52500.322 | I36: =I34-I35 -> 161979.14 | J36: =J34-J35 -> 937263.87 | K36: =K34-K35 -> 71496.046 | L36: =L34-L35 -> 513148.69 | M36: =M34-M35 -> 0 | ... R36: =R34-R35 -> 0
B37: IRR | F37: =XIRR(F36:R36,F20:R20) -> 0.40926964
B38: Equity Multiple | F38: =SUMIF(F36:R36,">0")/-SUMIF(F36:R36,"<0") -> 4.3409702
B39: Cumulative (Equity) Cash Position | F39: =F36+E39 -> -400000 | G39: =G36+F39 -> -400000 | H39: =H36+G39 -> -347499.68 | I39: =I36+H39 -> -185520.54 | J39: =J36+I39 -> 751743.33 | K39: =K36+J39 -> 823239.37 | L39: =L36+K39 -> 1336388.1 | M39: =M36+L39 -> 1336388.1 | ... R39: =R36+Q39 -> 1336388.1
B41: MO/Equity JV GP Returns
B42: Total Distributions | D42: =SUM(F42:R42) -> 37405013 | F42: ='Proforma Land+Home'!E203 -> 0 | G42: ='Proforma Land+Home'!F203 -> 0 | H42: ='Proforma Land+Home'!G203 -> 0 | I42: ='Proforma Land+Home'!H203 -> 0 | J42: ='Proforma Land+Home'!I203 -> 14896191 | K42: ='Proforma Land+Home'!J203 -> 2752597.8 | L42: ='Proforma Land+Home'!K203 -> 19756225 | M42: ='Proforma Land+Home'!L203 -> 0 | ... R42: ='Proforma Land+Home'!Q203 -> 0
B43: Net Profit / Cash Flows | D43: =SUM(F43:R43) -> 37405013 | F43: =SUM(F42:F42) -> 0 | G43: =SUM(G42:G42) -> 0 | H43: =SUM(H42:H42) -> 0 | I43: =SUM(I42:I42) -> 0 | J43: =SUM(J42:J42) -> 14896191 | K43: =SUM(K42:K42) -> 2752597.8 | L43: =SUM(L42:L42) -> 19756225 | M43: =SUM(M42:M42) -> 0 | ... R43: =SUM(R42:R42) -> 0
B44: Equity Portion | C44: 0 | D44: =SUM(F44:R44) -> 0 | F44: =F43*$C$44 -> 0 | G44: =G43*$C$44 -> 0 | H44: =H43*$C$44 -> 0 | I44: =I43*$C$44 -> 0 | J44: =J43*$C$44 -> 0 | K44: =K43*$C$44 -> 0 | L44: =L43*$C$44 -> 0 | M44: =M43*$C$44 -> 0 | ... R44: =R43*$C$44 -> 0
B45: MO Portion | C45: =1-C44 -> 1 | D45: =SUM(F45:R45) -> 37405013 | F45: =F43*$C$45 -> 0 | G45: =G43*$C$45 -> 0 | H45: =H43*$C$45 -> 0 | I45: =I43*$C$45 -> 0 | J45: =J43*$C$45 -> 14896191 | K45: =K43*$C$45 -> 2752597.8 | L45: =L43*$C$45 -> 19756225 | M45: =M43*$C$45 -> 0 | ... R45: =R43*$C$45 -> 0
B47: Net Cash Flow For Distributions - TOTAL PROJECT RETURNS
B48: Net Levered Before Tax Cash Flow | D48: =SUM(F48:R48) -> 88855954 | F48: ='Proforma Land+Home'!E210 -> -15400000 | G48: ='Proforma Land+Home'!F210 -> 0 | H48: ='Proforma Land+Home'!G210 -> 2021262.4 | I48: ='Proforma Land+Home'!H210 -> 6236196.8 | J48: ='Proforma Land+Home'!I210 -> 50980850 | K48: ='Proforma Land+Home'!J210 -> 5505195.5 | L48: ='Proforma Land+Home'!K210 -> 39512449 | M48: ='Proforma Land+Home'!L210 -> 0 | ... R48: ='Proforma Land+Home'!Q210 -> 0
B49: Levered IRR | F49: =XIRR(F48:R48,F20:R20) -> 0.53538527
B50: Equity Multiple | F50: =SUMIF(F48:R48,">0")/-SUMIF(F48:R48,"<0") -> 6.7698671
B52: Return of PM EQUITY & Hurdle 1 (Preferred Return)
B53: Net Levered Before Tax Cash Flow | F53: =F48 -> -15400000 | G53: =G48 -> 0 | H53: =H48 -> 2021262.4 | I53: =I48 -> 6236196.8 | J53: =J48 -> 50980850 | K53: =K48 -> 5505195.5 | L53: =L48 -> 39512449 | M53: =M48 -> 0 | N53: ='Proforma Land+Home'!M204 -> 0 | O53: ='Proforma Land+Home'!N204 -> 0 | P53: ='Proforma Land+Home'!O204 -> 0 | Q53: ='Proforma Land+Home'!P204 -> 0 | R53: ='Proforma Land+Home'!Q204 -> 0
B54: Preferred returns | F54: =F53 -> -15400000 | G54: =G53 -> 0 | H54: =H53 -> 2021262.4 | I54: =I53 -> 6236196.8 | J54: =J53 -> 50980850 | L54: =L53 -> 39512449 | M54: 27400000 | N54: =N53 -> 0 | O54: =O53 -> 0 | P54: =P53 -> 0 | Q54: =Q53 -> 0 | R54: =R53 -> 0 | T54: =SUM(F54:S54) -> 1.1075076e+08
B55: IRR Check - preferred returns | F55: =XIRR(F54:R54,F46:R46) -> #NUM! | T55: =U77 -> 0
B56: Remaining Cash Flow for Split | F56: =F53-F54 -> 0 | G56: =G53-G54 -> 0 | H56: =H53-H54 -> 0 | I56: =I53-I54 -> 0 | J56: =J53-J54 -> 0 | K56: =K53-K54 -> 5505195.5 | L56: =L53-L54 -> 0 | M56: =M53-M54 -> -27400000 | ... R56: =R53-R54 -> 0
B57: =T80 -> 0 | C57: =U80 -> 0 | F57: =F$56*$C57 -> 0 | G57: =G$56*$C57 -> 0 | H57: =H$56*$C57 -> 0 | I57: =I$56*$C57 -> 0 | J57: =J$56*$C57 -> 0 | K57: =K$56*$C57 -> 0 | L57: =L$56*$C57 -> 0 | M57: =M$56*$C57 -> 0 | ... R57: =R$56*$C57 -> 0 | T57: =SUM(F57:S57) -> 0
B58: =T81 -> 0 | C58: =U81 -> 0 | F58: =F$56*$C58 -> 0 | G58: =G$56*$C58 -> 0 | H58: =H$56*$C58 -> 0 | I58: =I$56*$C58 -> 0 | J58: =J$56*$C58 -> 0 | K58: =K$56*$C58 -> 0 | L58: =L$56*$C58 -> 0 | M58: =M$56*$C58 -> 0 | ... R58: =R$56*$C58 -> 0 | T58: =SUM(F58:S58) -> 0
B60: CM Common Members SHARE
B61: Net Levered Before Tax Cash Flow | F61: =-#REF! -> #REF! | G61: =-#REF! -> #REF! | H61: =-#REF! -> #REF! | I61: =I58 -> 0 | J61: =J58 -> 0 | K61: =K58 -> 0 | L61: =L58 -> 0 | M61: =M58 -> 0 | N61: =N58 -> 0 | O61: =O58 -> 0 | P61: =P58 -> 0 | ... R61: =R58 -> 0
B62: Preferred returns | F62: =F61 -> #REF! | G62: =G61 -> #REF!
B63: IRR Check - preferred returns | F63: =XIRR(F62:R62,F46:R46) -> #REF! | T63: 0.1
B64: Remaining Cash Flow for Split | F64: =F61-F62 -> #REF! | G64: =G61-G62 -> #REF! | H64: =H61-H62 -> #REF! | I64: =I61-I62 -> 0 | J64: =J61-J62 -> 0 | K64: =K61-K62 -> 0 | L64: =L61-L62 -> 0 | M64: =M61-M62 -> 0 | ... R64: =R61-R62 -> 0
B65: CM SPONSOR SHARE | C65: 0 | F65: =F$64*$C65 -> #REF! | G65: =G$64*$C65 -> #REF! | H65: =H$64*$C65 -> #REF! | I65: =I$64*$C65 -> 0 | J65: =J$64*$C65 -> 0 | K65: =K$64*$C65 -> 0 | L65: =L$64*$C65 -> 0 | M65: =M$64*$C65 -> 0 | ... R65: =R$64*$C65 -> 0
B66: CM Common Members MANAGER SHARE | C66: =1-C65 -> 1 | F66: =F$64*$C66 -> #REF! | G66: =G$64*$C66 -> #REF! | H66: =H$64*$C66 -> #REF! | I66: =I$64*$C66 -> 0 | J66: =J$64*$C66 -> 0 | K66: =K$64*$C66 -> 0 | L66: =L$64*$C66 -> 0 | M66: =M$64*$C66 -> 0 | ... R66: =R$64*$C66 -> 0 | T66: =SUM(D66:S66) -> #REF!
V67: CM Share Returns | W67: PM Share Returns | AA67: NiCK | AB67: MTN O | AC67: DeREUS | AD67: TOTAL
B68: Proposed Sponsor Split
B69: Market rate Overhead & Fees Paid to Working Sponsors (e.g. Design Fees, Sales Commision, Asset Management, Common Members Fees, etc.)
B70: Cost of Contributed Capital (e.g. Cash Multiple for Pursuit Dollars, 10% Pref for Equity, etc.)
B71: Equal split of Sponsor Distribution (e.g. 3 ways, 4 ways or 5 ways depending on head count of Sponsor Principals)
T72: NICK | U72: =AA76 -> 0 | V72: =$T$58*U72 -> 0 | W72: =(5000000/$D$25)*$T$57+5000000 -> 5000000 | Y72: PURSUIT/ENT. | Z72: 0.33333 | AA72: =1/3 -> 0.33333333 | AB72: =1/3 -> 0.33333333 | AC72: =1/3 -> 0.33333333 | AD72: =SUM(AA72:AC72) -> 1

Sheet L+H Monthly Cash Flow
A2: CLARENDON - LAND & HOME DEVELOPMENT | B2: TO BE UPDATED AFTER FINALIZING ANNUAL PROFORMA
A3: MONTLY CASH FLOW SCHEDULE
AH4: CHECK
B5: TOTALS | D5: 2024 | P5: 2025 | AB5: 2026 | AG5: TOTALS
D6: MONTH-1 | E6: MONTH-2 | F6: MONTH-3 | G6: MONTH-4 | H6: MONTH-5 | I6: MONTH-6 | J6: MONTH-7 | K6: MONTH-8 | L6: MONTH-9 | M6: MONTH-10 | N6: MONTH-11 | O6: MONTH-12 | P6: MONTH-13 | Q6: MONTH-14 | R6: MONTH-15 | S6: MONTH-16 | T6: MONTH-17 | U6: MONTH-18 | V6: MONTH-19 | W6: MONTH-20 | X6: MONTH-21 | Y6: MONTH-22 | Z6: MONTH-23 | AA6: MONTH-24 | AB6: MONTH-25 | AC6: MONTH-26 | AD6: MONTH-27 | AE6: MONTH-28
D7: 45292 | E7: 45323 | F7: 45352 | G7: 45383 | H7: 45413 | I7: 45444 | J7: 45474 | K7: 45505 | L7: 45536 | M7: 45566 | N7: 45597 | O7: 45627 | P7: 45658 | Q7: 45689 | R7: 45717 | S7: 45748 | T7: 45778 | U7: 45809 | V7: 45839 | W7: 45870 | X7: 45901 | Y7: 45931 | Z7: 45962 | AA7: 45992 | AB7: 46023 | AC7: 46054 | AD7: 46082 | AE7: 46113
A8: SOURCES
A10: EQUITY INVESTMENT | AG10: 0 | AH10: =B10-AG10 -> 0
A11: ='Proforma Land+Home'!B45 -> EB5 - MEZZ DEBT | B11: ='Proforma Land+Home'!$E45 -> 0 | G11: =B11 -> 0 | AG11: =SUM(C11:AE11) -> 0 | AH11: =B11-AG11 -> 0
A12: ='Proforma Land+Home'!B39 -> SPONSOR - EQUITY CAPITAL | B12: ='Proforma Land+Home'!$E39 -> 400000 | D12: ='Proforma Land+Home'!R39 -> 400000 | AG12: =SUM(C12:AE12) -> 400000 | AH12: =B12-AG12 -> 0
A13: Soft Costs to start PUD of 80 Acres | B13: ='Proforma Land+Home'!#REF! -> #REF! | AG13: 0 | AH13: =B13-AG13 -> #REF!
A14: Soft+Hard Costs for Amenity | B14: ='Proforma Land+Home'!#REF! -> #REF! | AG14: 0 | AH14: =B14-AG14 -> #REF!
A15: Project Level Expenses | B15: ='Proforma Land+Home'!#REF! -> #REF! | AG15: 0 | AH15: =B15-AG15 -> #REF!
A16: Home Construction & Design | B16: ='Proforma Land+Home'!#REF! -> #REF! | AG16: 0 | AH16: =B16-AG16 -> #REF!
A17: EQUITY INVESTMENT | B17: =SUM(B10:B16) -> #REF! | D17: =SUM(D10:D16) -> 400000 | E17: =SUM(E10:E16) -> 0 | F17: =SUM(F10:F16) -> 0 | G17: =SUM(G10:G16) -> 0 | H17: =SUM(H10:H16) -> 0 | I17: =SUM(I10:I16) -> 0 | J17: =SUM(J10:J16) -> 0 | K17: =SUM(K10:K16) -> 0 | ... AE17: =SUM(AE10:AE16) -> 0 | AG17: =SUM(AG10:AG16) -> 400000 | AH17: =B17-AG17 -> #REF!
AH18: =B18-AG18 -> 0
A19: DEBT | AH19: =B19-AG19 -> 0
A20: ='Proforma Land+Home'!#REF! -> #REF! | B20: ='Proforma Land+Home'!#REF! -> #REF! | G20: ='Proforma Land+Home'!#REF! -> #REF! | AG20: =SUM(C20:AE20) -> #REF! | AH20: =B20-AG20 -> #REF!
A21: ='Proforma Land+Home'!B46 -> DEV LOAN - DEV COSTS | B21: ='Proforma Land+Home'!E46+'Proforma Land+Home'!F46 -> 38779480 | G21: ='Proforma Land+Home'!$E$46*0.43 -> 12104930 | J21: ='Proforma Land+Home'!$E$46*0.19 -> 5348689.8 | M21: ='Proforma Land+Home'!$E$46*0.19 -> 5348689.8 | P21: ='Proforma Land+Home'!$E$46*0.19 -> 5348689.8 | S21: ='Proforma Land+Home'!$F$46 -> 10628481 | AG21: =SUM(C21:AE21) -> 38779480 | AH21: =B21-AG21 -> 0
A22: DEBT | B22: =SUM(B19:B21) -> #REF! | D22: =SUM(D19:D21) -> 0 | E22: =SUM(E19:E21) -> 0 | F22: =SUM(F19:F21) -> 0 | G22: =SUM(G19:G21) -> #REF! | I22: =SUM(I19:I21) -> 0 | J22: =SUM(J19:J21) -> 5348689.8 | K22: =SUM(K19:K21) -> 0 | L22: =SUM(L19:L21) -> 0 | M22: =SUM(M19:M21) -> 5348689.8 | N22: =SUM(N19:N21) -> 0 | O22: =SUM(O19:O21) -> 0 | P22: =SUM(P19:P21) -> 5348689.8 | ... AE22: =SUM(AE19:AE21) -> 0 | AG22: =SUM(AG19:AG21) -> #REF! | AH22: =B22-AG22 -> #REF!
AH23: =B23-AG23 -> 0
A24: Net Operating Income from Amenity Operations (before tax) | AH24: =B24-AG24 -> 0
A25: Membership Buy In (50% of PRESALE REVENUES) | B25: 0 | AG25: 0 | AH25: =B25-AG25 -> 0
A26: Proceeds from Sale or Recapitalization of Amenity (Entitled Hotel/Resort Site(s) & Operations after 7 years) | AH26: =B26-AG26 -> 0
A27: NET INCOME FROM AMENITY OPERATIONS | N27: =SUM(N23:N26) -> 0 | Q27: =SUM(Q23:Q26) -> 0 | T27: =SUM(T23:T26) -> 0 | AH27: =B27-AG27 -> 0
AH28: =B28-AG28 -> 0
A29: Construction Start Draw + Foundation Complete | B29: 0 | AH29: =B29-AG29 -> 0
A30: Structure Complete Draw | B30: 0 | AH30: =B30-AG30 -> 0
A31: MEP 4-way + Finishes Start Draw | B31: 0 | AH31: =B31-AG31 -> 0
A32: Unit Reservations w/ Membership Purchase (50/50) | B32: 0 | AH32: =B32-AG32 -> 0
A33: PRESALE REVENUES | B33: 0 | AG33: 0 | AH33: =B33-AG33 -> 0
A34: UNIT SALES | AH34: =B34-AG34 -> 0
A35: TOTAL SOURCES | B35: =B17+B22 -> #REF! | D35: =D17+D22+D27+D33+D34 -> 400000 | E35: =E17+E22+E27+E33+E34 -> 0 | F35: =F17+F22+F27+F33+F34 -> 0 | G35: =G17+G22+G27+G33+G34 -> #REF! | H35: =H17+H22+H27+H33+H34 -> 0 | I35: =I17+I22+I27+I33+I34 -> 0 | J35: =J17+J22+J27+J33+J34 -> 5348689.8 | K35: =K17+K22+K27+K33+K34 -> 0 | ... AE35: =AE17+AE22+AE27+AE33+AE34 -> 0 | AG35: =AG17+AG22+AG27+AG33+AG34 -> #REF! | AH35: =B35-AG35 -> #REF!
AH36: =B36-AG36 -> 0
A37: USES | AH37: =B37-AG37 -> 0
A38: LAND & PROJECT ACQUISITION | AH38: =B38-AG38 -> 0
A39: Project Acquisition | B39: ='Proforma Land+Home'!$E62 -> 18500000 | G39: ='Proforma Land+Home'!$E$62 -> 18500000 | AG39: =SUM(C39:AE39) -> 18500000 | AH39: =B39-AG39 -> 0
A40: Asset Acquisition Fee (based on total project value of $60M) | B40: ='Proforma Land+Home'!$E63 -> 450000 | G40: =B40 -> 450000 | AG40: =SUM(C40:AE40) -> 450000 | AH40: =B40-AG40 -> 0
A41: Closing Costs | B41: ='Proforma Land+Home'!$E64 -> 27750 | G41: ='Proforma Land+Home'!$E$64 -> 27750 | AG41: =SUM(C41:AE41) -> 27750 | AH41: =B41-AG41 -> 0
A42: LAND & PROJECT ACQUISITION | B42: =SUM(B38:B41) -> 18977750 | D42: =SUM(D38:D41) -> 0 | E42: =SUM(E38:E41) -> 0 | F42: =SUM(F38:F41) -> 0 | G42: =SUM(G38:G41) -> 18977750 | H42: =SUM(H38:H41) -> 0 | I42: =SUM(I38:I41) -> 0 | J42: =SUM(J38:J41) -> 0 | K42: =SUM(K38:K41) -> 0 | ... AE42: =SUM(AE38:AE41) -> 0 | AG42: =SUM(AG39:AG41) -> 18977750 | AH42: =B42-AG42 -> 0
AH43: =B43-AG43 -> 0
A44: ='Proforma Land+Home'!#REF! -> #REF! | AH44: =B44-AG44 -> 0
A45: Use of Equity to Amenity | B45: ='Proforma Land+Home'!#REF! -> #REF! | J45: =$B45/18 -> #REF! | K45: =$B45/18 -> #REF! | L45: =$B45/18 -> #REF! | M45: =$B45/18 -> #REF! | N45: =$B45/18 -> #REF! | O45: =$B45/18 -> #REF! | P45: =$B45/18 -> #REF! | Q45: =$B45/18 -> #REF! | ... AA45: =$B45/18 -> #REF! | AG45: =SUM(C45:AE45) -> #REF! | AH45: =B45-AG45 -> #REF!
A46: Use of Debt to Amenity | B46: ='Proforma Land+Home'!#REF! -> #REF! | J46: =$B46/18 -> #REF! | K46: =$B46/18 -> #REF! | L46: =$B46/18 -> #REF! | M46: =$B46/18 -> #REF! | N46: =$B46/18 -> #REF! | O46: =$B46/18 -> #REF! | P46: =$B46/18 -> #REF! | Q46: =$B46/18 -> #REF! | ... AA46: =$B46/18 -> #REF! | AG46: =SUM(C46:AE46) -> #REF! | AH46: =B46-AG46 -> #REF!
A47: AMENITY - USE OF DEBT/EQUITY | B47: =SUM(B44:B46) -> #REF! | D47: =SUM(D44:D46) -> 0 | E47: =SUM(E44:E46) -> 0 | F47: =SUM(F44:F46) -> 0 | G47: =SUM(G44:G46) -> 0 | H47: =SUM(H44:H46) -> 0 | I47: =SUM(I44:I46) -> 0 | J47: =SUM(J44:J46) -> #REF! | K47: =SUM(K44:K46) -> #REF! | ... AE47: =SUM(AE44:AE46) -> 0 | AG47: =SUM(AG44:AG46) -> #REF! | AH47: =B47-AG47 -> #REF!
AH48: =B48-AG48 -> 0
A49: HARD COSTS - SITE, RESTORATION & INFRASTRUCTURE | AH49: =B49-AG49 -> 0
A50: Infrastructure | AG50: =SUM(C50:AE50) -> 0 | AH50: =B50-AG50 -> 0
A51: Internal Road: Base + Gravel Finish @ Lower 80 | B51: ='Proforma Land+Home'!$E68 -> 146875 | J51: =$B51/8 -> 18359.375 | K51: =$B51/8 -> 18359.375 | L51: =$B51/8 -> 18359.375 | M51: =$B51/8 -> 18359.375 | V51: =$B51/8 -> 18359.375 | W51: =$B51/8 -> 18359.375 | X51: =$B51/8 -> 18359.375 | Y51: =$B51/8 -> 18359.375 | AG51: =SUM(C51:AE51) -> 146875 | AH51: =B51-AG51 -> 0
A52: Internal Road: Paving @ Lower 80 | B52: ='Proforma A+H'!$E134 -> 0 | J52: =$B52/8 -> 0 | K52: =$B52/8 -> 0 | L52: =$B52/8 -> 0 | M52: =$B52/8 -> 0 | V52: =$B52/8 -> 0 | W52: =$B52/8 -> 0 | X52: =$B52/8 -> 0 | Y52: =$B52/8 -> 0 | AG52: =SUM(C52:AE52) -> 0 | AH52: =B52-AG52 -> 0
A53: Internal Road: Base + Gravel Finish @ 45 Lots | B53: ='Proforma Land+Home'!$E69 -> 0 | J53: =$B53/8 -> 0 | K53: =$B53/8 -> 0 | L53: =$B53/8 -> 0 | M53: =$B53/8 -> 0 | V53: =$B53/8 -> 0 | W53: =$B53/8 -> 0 | X53: =$B53/8 -> 0 | Y53: =$B53/8 -> 0 | AG53: =SUM(C53:AE53) -> 0 | AH53: =B53-AG53 -> 0
A54: Internal Road: Paving @ 45 Lots | B54: ='Proforma Land+Home'!$E70 -> 0 | J54: =$B54/8 -> 0 | K54: =$B54/8 -> 0 | L54: =$B54/8 -> 0 | M54: =$B54/8 -> 0 | V54: =$B54/8 -> 0 | W54: =$B54/8 -> 0 | X54: =$B54/8 -> 0 | Y54: =$B54/8 -> 0 | AG54: =SUM(C54:AE54) -> 0 | AH54: =B54-AG54 -> 0
A55: County/USFS Road: BASE + GRAVEL FINISH @ end of existing | B55: ='Proforma Land+Home'!$E71 -> 312500 | H55: =$B55/8 -> 39062.5 | I55: =$B55/8 -> 39062.5 | J55: =$B55/8 -> 39062.5 | K55: =$B55/8 -> 39062.5 | L55: =$B55/8 -> 39062.5 | M55: =$B55/8 -> 39062.5 | N55: =$B55/8 -> 39062.5 | O55: =$B55/8 -> 39062.5 | AG55: =SUM(C55:AE55) -> 312500 | AH55: =B55-AG55 -> 0
A56: County/USFS Road: PAVING @ end of existing to back gate | B56: ='Proforma Land+Home'!$E72 -> 0 | H56: =$B56/8 -> 0 | I56: =$B56/8 -> 0 | J56: =$B56/8 -> 0 | K56: =$B56/8 -> 0 | L56: =$B56/8 -> 0 | M56: =$B56/8 -> 0 | N56: =$B56/8 -> 0 | O56: =$B56/8 -> 0 | P56: ='Proforma Land+Home'!$E72/8 -> 0 | Q56: ='Proforma Land+Home'!$E72/8 -> 0 | AG56: =SUM(C56:AE56) -> 0 | AH56: =B56-AG56 -> 0
A57: Road: Bridges (1) @ Spillway | B57: ='Proforma Land+Home'!$E73 -> 150000 | J57: ='Proforma Land+Home'!$E73/4 -> 37500 | K57: ='Proforma Land+Home'!$E73/4 -> 37500 | L57: ='Proforma Land+Home'!$E73/4 -> 37500 | M57: ='Proforma Land+Home'!$E73/4 -> 37500 | AG57: =SUM(C57:AE57) -> 150000 | AH57: =B57-AG57 -> 0
A58: Utilities: County/USFS Power Trench+Line (4.5 miles) | B58: ='Proforma Land+Home'!$E74 -> 812500 | J58: ='Proforma Land+Home'!$E74/2 -> 406250 | K58: ='Proforma Land+Home'!$E74/2 -> 406250 | AG58: =SUM(C58:AE58) -> 812500 | AH58: =B58-AG58 -> 0
A59: Utilities: Power & Transformers @ Lower 80 (4,000 LF) | B59: ='Proforma A+H'!$E135 -> 0 | K59: ='Proforma A+H'!$E135/6 -> 0 | L59: ='Proforma A+H'!$E135/6 -> 0 | M59: ='Proforma A+H'!$E135/6 -> 0 | N59: ='Proforma A+H'!$E135/6 -> 0 | O59: ='Proforma A+H'!$E135/6 -> 0 | P59: ='Proforma A+H'!$E135/6 -> 0 | AG59: =SUM(C59:AE59) -> 0 | AH59: =B59-AG59 -> 0
A60: Utilities: Power & Transformers @ 45 Lots (8,500 LF) | B60: ='Proforma Land+Home'!$E75 -> 63750 | K60: =('Proforma Land+Home'!$E75)/6 -> 10625 | L60: =('Proforma Land+Home'!$E75)/6 -> 10625 | M60: =('Proforma Land+Home'!$E75)/6 -> 10625 | N60: =('Proforma Land+Home'!$E75)/6 -> 10625 | O60: =('Proforma Land+Home'!$E75)/6 -> 10625 | P60: =('Proforma Land+Home'!$E75)/6 -> 10625 | AG60: =SUM(C60:AE60) -> 63750 | AH60: =B60-AG60 -> 0
A61: Utilities: Comm. Distrib. @ Lower 80 (4,000 LF) | B61: ='Proforma A+H'!$E136 -> 0 | K61: =('Proforma A+H'!$E136)/6 -> 0 | L61: =('Proforma A+H'!$E136)/6 -> 0 | M61: =('Proforma A+H'!$E136)/6 -> 0 | N61: =('Proforma A+H'!$E136)/6 -> 0 | O61: =('Proforma A+H'!$E136)/6 -> 0 | P61: =('Proforma A+H'!$E136)/6 -> 0 | AG61: =SUM(C61:AE61) -> 0 | AH61: =B61-AG61 -> 0
A62: Utilities: Comm. Distrib. @ 45 Lots (8,500 LF) | B62: ='Proforma Land+Home'!$E76 -> 53125 | K62: =('Proforma Land+Home'!$E76)/6 -> 8854.1667 | L62: =('Proforma Land+Home'!$E76)/6 -> 8854.1667 | M62: =('Proforma Land+Home'!$E76)/6 -> 8854.1667 | N62: =('Proforma Land+Home'!$E76)/6 -> 8854.1667 | O62: =('Proforma Land+Home'!$E76)/6 -> 8854.1667 | P62: =('Proforma Land+Home'!$E76)/6 -> 8854.1667 | AG62: =SUM(C62:AE62) -> 53125 | AH62: =B62-AG62 -> 0
A63: Utilities: Water Main @ Lower 80 | B63: ='Proforma A+H'!$E137 -> 0 | K63: =('Proforma A+H'!$E137)/6 -> 0 | L63: =('Proforma A+H'!$E137)/6 -> 0 | M63: =('Proforma A+H'!$E137)/6 -> 0 | N63: =('Proforma A+H'!$E137)/6 -> 0 | O63: =('Proforma A+H'!$E137)/6 -> 0 | P63: =('Proforma A+H'!$E137)/6 -> 0 | AG63: =SUM(C63:AE63) -> 0 | AH63: =B63-AG63 -> 0
A64: Utilities: Water Main @ 45 Lots | B64: ='Proforma Land+Home'!$E77 -> 229166.67 | K64: =('Proforma Land+Home'!$E77)/6 -> 38194.444 | L64: =('Proforma Land+Home'!$E77)/6 -> 38194.444 | M64: =('Proforma Land+Home'!$E77)/6 -> 38194.444 | N64: =('Proforma Land+Home'!$E77)/6 -> 38194.444 | O64: =('Proforma Land+Home'!$E77)/6 -> 38194.444 | P64: =('Proforma Land+Home'!$E77)/6 -> 38194.444 | AG64: =SUM(C64:AE64) -> 229166.67 | AH64: =B64-AG64 -> 0
A65: Utilities: Water Wells, Pumps & Storage Tank | B65: ='Proforma Land+Home'!$E78 -> 625000 | K65: =('Proforma Land+Home'!$E78)/6 -> 104166.67 | L65: =('Proforma Land+Home'!$E78)/6 -> 104166.67 | M65: =('Proforma Land+Home'!$E78)/6 -> 104166.67 | N65: =('Proforma Land+Home'!$E78)/6 -> 104166.67 | O65: =('Proforma Land+Home'!$E78)/6 -> 104166.67 | P65: =('Proforma Land+Home'!$E78)/6 -> 104166.67 | AG65: =SUM(C65:AE65) -> 625000 | AH65: =B65-AG65 -> 0
A66: Utilities: Sewer Main @ Resort & Meadow Lots (4,000 LF) | B66: ='Proforma A+H'!$E138 -> 0 | K66: =('Proforma A+H'!$E138)/6 -> 0 | L66: =('Proforma A+H'!$E138)/6 -> 0 | M66: =('Proforma A+H'!$E138)/6 -> 0 | N66: =('Proforma A+H'!$E138)/6 -> 0 | O66: =('Proforma A+H'!$E138)/6 -> 0 | P66: =('Proforma A+H'!$E138)/6 -> 0 | AG66: =SUM(C66:AE66) -> 0 | AH66: =B66-AG66 -> 0
A67: Utilities: Sewer Septic Tank & Sys @ Resort | B67: ='Proforma A+H'!$E139 -> 0 | K67: =('Proforma A+H'!$E139)/6 -> 0 | L67: =('Proforma A+H'!$E139)/6 -> 0 | M67: =('Proforma A+H'!$E139)/6 -> 0 | N67: =('Proforma A+H'!$E139)/6 -> 0 | O67: =('Proforma A+H'!$E139)/6 -> 0 | P67: =('Proforma A+H'!$E139)/6 -> 0 | AG67: =SUM(C67:AE67) -> 0 | AH67: =B67-AG67 -> 0
A68: Utilities: Lift Station @ 45 Lots (8,500 LF) | B68: ='Proforma Land+Home'!$E79 -> 52083.333 | K68: =('Proforma Land+Home'!$E79)/6 -> 8680.5556 | L68: =('Proforma Land+Home'!$E79)/6 -> 8680.5556 | M68: =('Proforma Land+Home'!$E79)/6 -> 8680.5556 | N68: =('Proforma Land+Home'!$E79)/6 -> 8680.5556 | O68: =('Proforma Land+Home'!$E79)/6 -> 8680.5556 | P68: =('Proforma Land+Home'!$E79)/6 -> 8680.5556 | AG68: =SUM(C68:AE68) -> 52083.333 | AH68: =B68-AG68 -> 0
A69: Utilities: Sewer Drainfield Dosing Chamber & Piping | B69: ='Proforma A+H'!$E140 -> 0 | K69: =('Proforma A+H'!$E140)/6 -> 0 | L69: =('Proforma A+H'!$E140)/6 -> 0 | M69: =('Proforma A+H'!$E140)/6 -> 0 | N69: =('Proforma A+H'!$E140)/6 -> 0 | O69: =('Proforma A+H'!$E140)/6 -> 0 | P69: =('Proforma A+H'!$E140)/6 -> 0 | AG69: =SUM(C69:AE69) -> 0 | AH69: =B69-AG69 -> 0
A70: Utilities: Sewer Treatment Drainfield Sys (4 EA) | B70: ='Proforma Land+Home'!$E80 -> 195312.5 | K70: =('Proforma Land+Home'!$E80)/6 -> 32552.083 | L70: =('Proforma Land+Home'!$E80)/6 -> 32552.083 | M70: =('Proforma Land+Home'!$E80)/6 -> 32552.083 | N70: =('Proforma Land+Home'!$E80)/6 -> 32552.083 | O70: =('Proforma Land+Home'!$E80)/6 -> 32552.083 | P70: =('Proforma Land+Home'!$E80)/6 -> 32552.083 | AG70: =SUM(C70:AE70) -> 195312.5 | AH70: =B70-AG70 -> 0
A71: Utilities: Geothermal Infrastructure @ Lower 80 | B71: ='Proforma A+H'!$E141 -> 0 | K71: =('Proforma A+H'!$E141)/6 -> 0 | L71: =('Proforma A+H'!$E141)/6 -> 0 | M71: =('Proforma A+H'!$E141)/6 -> 0 | N71: =('Proforma A+H'!$E141)/6 -> 0 | O71: =('Proforma A+H'!$E141)/6 -> 0 | P71: =('Proforma A+H'!$E141)/6 -> 0 | AG71: =SUM(C71:AE71) -> 0 | AH71: =B71-AG71 -> 0
A72: Utilities: Geothermal Infrastructure @ 45 Lots | B72: ='Proforma Land+Home'!$E81 -> 72916.667 | K72: =('Proforma Land+Home'!$E81)/6 -> 12152.778 | L72: =('Proforma Land+Home'!$E81)/6 -> 12152.778 | M72: =('Proforma Land+Home'!$E81)/6 -> 12152.778 | N72: =('Proforma Land+Home'!$E81)/6 -> 12152.778 | O72: =('Proforma Land+Home'!$E81)/6 -> 12152.778 | P72: =('Proforma Land+Home'!$E81)/6 -> 12152.778 | AG72: =SUM(C72:AE72) -> 72916.667 | AH72: =B72-AG72 -> 0
A73: Landscape: Dredge Silt from 3 Ponds | B73: ='Proforma A+H'!$E142 -> 0 | M73: ='Proforma A+H'!$E142/4 -> 0 | N73: ='Proforma A+H'!$E142/4 -> 0 | O73: ='Proforma A+H'!$E142/4 -> 0 | P73: ='Proforma A+H'!$E142/4 -> 0 | AG73: =SUM(C73:AE73) -> 0 | AH73: =B73-AG73 -> 0
A74: Landscape: Dredge, Liner, Ballast & Plant @ Cooling Pond (1) | B74: ='Proforma A+H'!$E143 -> 0 | M74: ='Proforma A+H'!$E143/4 -> 0 | N74: ='Proforma A+H'!$E143/4 -> 0 | O74: ='Proforma A+H'!$E143/4 -> 0 | P74: ='Proforma A+H'!$E143/4 -> 0 | AG74: =SUM(C74:AE74) -> 0 | AH74: =B74-AG74 -> 0
A75: Landscape: Wetlands Improvement | B75: ='Proforma A+H'!$E144 -> 0 | M75: ='Proforma A+H'!$E144/4 -> 0 | N75: ='Proforma A+H'!$E144/4 -> 0 | O75: ='Proforma A+H'!$E144/4 -> 0 | P75: ='Proforma A+H'!$E144/4 -> 0 | AG75: =SUM(C75:AE75) -> 0 | AH75: =B75-AG75 -> 0
A76: Landscape: Early Plantings in Public Areas (was $1.5M) | B76: ='Proforma Land+Home'!$E82 -> 250000 | M76: ='Proforma Land+Home'!$E82/4 -> 62500 | N76: ='Proforma Land+Home'!$E82/4 -> 62500 | O76: ='Proforma Land+Home'!$E82/4 -> 62500 | P76: ='Proforma Land+Home'!$E82/4 -> 62500 | AG76: =SUM(C76:AE76) -> 250000 | AH76: =B76-AG76 -> 0
A77: Landcape: Irrigation in Public Areas ($750k pushed to Phase 2)) | B77: ='Proforma Land+Home'!#REF! -> #REF! | O77: ='Proforma Land+Home'!#REF!/4 -> #REF! | P77: ='Proforma Land+Home'!#REF!/4 -> #REF! | Q77: ='Proforma Land+Home'!#REF!/4 -> #REF! | R77: ='Proforma Land+Home'!#REF!/4 -> #REF! | AG77: =SUM(C77:AE77) -> #REF! | AH77: =B77-AG77 -> #REF!
A78: Construction Cost Escalation | B78: ='Proforma Land+Home'!$E83 -> 148161.46 | H78: =SUM(H$50:H$77)*'Proforma Land+Home'!$C$83 -> 1953.125 | I78: =SUM(I$50:I$77)*'Proforma Land+Home'!$C$83 -> 1953.125 | J78: =SUM(J$50:J$77)*'Proforma Land+Home'!$C$83 -> 25058.594 | K78: =SUM(K$50:K$77)*'Proforma Land+Home'!$C$83 -> 35819.878 | L78: =SUM(L$50:L$77)*'Proforma Land+Home'!$C$83 -> 15507.378 | M78: =SUM(M$50:M$77)*'Proforma Land+Home'!$C$83 -> 18632.378 | N78: =SUM(N$50:N$77)*'Proforma Land+Home'!$C$83 -> 15839.41 | O78: =SUM(O$50:O$77)*'Proforma Land+Home'!$C$83 -> #REF! | ... Y78: =SUM(Y$50:Y$77)*'Proforma Land+Home'!$C$83 -> 917.96875 | AA78: =SUM(AA$50:AA$77)*'Proforma Land+Home'!$C$83 -> 0 | AC78: =SUM(AC$50:AC$77)*'Proforma Land+Home'!$C$83 -> 0 | AD78: =SUM(AD$50:AD$77)*'Proforma Land+Home'!$C$83 -> 0 | AE78: =SUM(AE$50:AE$77)*'Proforma Land+Home'!$C$83 -> 0 | AG78: =SUM(C78:AE78) -> #REF! | AH78: =B78-AG78 -> #REF!
A79: Developer Construction Contingency | B79: ='Proforma Land+Home'!$E84 -> 148161.46 | H79: =SUM(H$50:H$77)*'Proforma Land+Home'!$C$83 -> 1953.125 | I79: =SUM(I$50:I$77)*'Proforma Land+Home'!$C$83 -> 1953.125 | J79: =SUM(J$50:J$77)*'Proforma Land+Home'!$C$83 -> 25058.594 | K79: =SUM(K$50:K$77)*'Proforma Land+Home'!$C$83 -> 35819.878 | L79: =SUM(L$50:L$77)*'Proforma Land+Home'!$C$83 -> 15507.378 | M79: =SUM(M$50:M$77)*'Proforma Land+Home'!$C$83 -> 18632.378 | N79: =SUM(N$50:N$77)*'Proforma Land+Home'!$C$83 -> 15839.41 | O79: =SUM(O$50:O$77)*'Proforma Land+Home'!$C$83 -> #REF! | ... AE79: =SUM(AE$50:AE$77)*'Proforma Land+Home'!$C$83 -> 0 | AG79: =SUM(C79:AE79) -> #REF! | AH79: =B79-AG79 -> #REF!
A80: HARD COSTS - SITE, RESTORATION & INFRASTRUCTURE | B80: =SUM(B50:B79) -> #REF! | D80: =SUM(D50:D79) -> 0 | E80: =SUM(E50:E79) -> 0 | F80: =SUM(F50:F79) -> 0 | G80: =SUM(G50:G79) -> 0 | H80: =SUM(H50:H79) -> 42968.75 | I80: =SUM(I50:I79) -> 42968.75 | J80: =SUM(J50:J79) -> 551289.06 | K80: =SUM(K50:K79) -> 788037.33 | ... AE80: =SUM(AE50:AE79) -> 0 | AG80: =SUM(AG50:AG79) -> #REF! | AH80: =B80-AG80 -> #REF!
AH81: =B81-AG81 -> 0
A82: HARD COSTS - HOMES | B82: =SUM(C82:AE82) -> 0 | AG82: =SUM(C82:AE82) -> 0 | AH82: =B82-AG82 -> 0
A83: Infrastructure (Utilities & Driveway) | B83: ='Proforma Land+Home'!$E88 -> 725000 | J83: ='Proforma Land+Home'!$E88/3 -> 241666.67 | K83: ='Proforma Land+Home'!$E88/3 -> 241666.67 | L83: ='Proforma Land+Home'!$E88/3 -> 241666.67 | AG83: =SUM(C83:AE83) -> 725000 | AH83: =B83-AG83 -> 0
A84: Vertical Construction Costs | B84: ='Proforma Land+Home'!$E89 -> 14875000 | I84: =('Proforma Land+Home'!$E$89)/18 -> 826388.89 | J84: =('Proforma Land+Home'!$E$89)/18 -> 826388.89 | K84: =('Proforma Land+Home'!$E$89)/18 -> 826388.89 | L84: =('Proforma Land+Home'!$E$89)/18 -> 826388.89 | M84: =('Proforma Land+Home'!$E$89)/18 -> 826388.89 | N84: =('Proforma Land+Home'!$E$89)/18 -> 826388.89 | O84: =('Proforma Land+Home'!$E$89)/18 -> 826388.89 | P84: =('Proforma Land+Home'!$E$89)/18 -> 826388.89 | ... Z84: =('Proforma Land+Home'!$E$89)/18 -> 826388.89 | AG84: =SUM(C84:AE84) -> 14875000 | AH84: =B84-AG84 -> 0
A85: Landscape / Hardscape | B85: ='Proforma Land+Home'!$F90 -> 750000 | V85: =$B85/4 -> 187500 | W85: =$B85/4 -> 187500 | X85: =$B85/4 -> 187500 | Y85: =$B85/4 -> 187500 | AG85: =SUM(C85:AE85) -> 750000 | AH85: =B85-AG85 -> 0
A86: Construction Cost Escalation | B86: ='Proforma Land+Home'!$E92 -> 780000 | I86: =SUM(I82:I84)*'Proforma Land+Home'!$C$92 -> 41319.444 | J86: =SUM(J82:J84)*'Proforma Land+Home'!$C$92 -> 53402.778 | K86: =SUM(K82:K84)*'Proforma Land+Home'!$C$92 -> 53402.778 | L86: =SUM(L82:L84)*'Proforma Land+Home'!$C$92 -> 53402.778 | M86: =SUM(M82:M84)*'Proforma Land+Home'!$C$92 -> 41319.444 | N86: =SUM(N82:N84)*'Proforma Land+Home'!$C$92 -> 41319.444 | O86: =SUM(O82:O84)*'Proforma Land+Home'!$C$92 -> 41319.444 | P86: =SUM(P82:P84)*'Proforma Land+Home'!$C$92 -> 41319.444 | ... Z86: =SUM(Z82:Z84)*'Proforma Land+Home'!$C$92 -> 41319.444 | AA86: =SUM(AA82:AA85)*'Proforma Land+Home'!$C$92 -> 0 | AB86: =SUM(AB82:AB85)*'Proforma Land+Home'!$C$92 -> 0 | AC86: =SUM(AC82:AC85)*'Proforma Land+Home'!$C$92 -> 0 | AD86: =SUM(AD82:AD85)*'Proforma Land+Home'!$C$92 -> 0 | AE86: =SUM(AE82:AE85)*'Proforma Land+Home'!$C$92 -> 0 | AG86: =SUM(C86:AE86) -> 780000 | AH86: =B86-AG86 -> 0
A87: Developer Construction Contingency | B87: ='Proforma Land+Home'!$E93 -> 546000 | D87: =SUM(D82:D84)*'Proforma Land+Home'!$C$93 -> 0 | E87: =SUM(E82:E84)*'Proforma Land+Home'!$C$93 -> 0 | F87: =SUM(F82:F84)*'Proforma Land+Home'!$C$93 -> 0 | G87: =SUM(G82:G84)*'Proforma Land+Home'!$C$93 -> 0 | H87: =SUM(H82:H84)*'Proforma Land+Home'!$C$93 -> 0 | I87: =SUM(I82:I84)*'Proforma Land+Home'!$C$93 -> 28923.611 | J87: =SUM(J82:J84)*'Proforma Land+Home'!$C$93 -> 37381.944 | K87: =SUM(K82:K84)*'Proforma Land+Home'!$C$93 -> 37381.944 | ... Z87: =SUM(Z82:Z84)*'Proforma Land+Home'!$C$93 -> 28923.611 | AA87: =SUM(AA82:AA85)*'Proforma Land+Home'!$C$93 -> 0 | AB87: =SUM(AB82:AB85)*'Proforma Land+Home'!$C$93 -> 0 | AC87: =SUM(AC82:AC85)*'Proforma Land+Home'!$C$93 -> 0 | AD87: =SUM(AD82:AD85)*'Proforma Land+Home'!$C$93 -> 0 | AE87: =SUM(AE82:AE85)*'Proforma Land+Home'!$C$93 -> 0 | AG87: =SUM(C87:AE87) -> 546000 | AH87: =B87-AG87 -> 0
A88: HARD COSTS - HOMES | B88: =SUM(B82:B87) -> 17676000 | D88: =SUM(D82:D87) -> 0 | E88: =SUM(E82:E87) -> 0 | F88: =SUM(F82:F87) -> 0 | G88: =SUM(G82:G87) -> 0 | H88: =SUM(H82:H87) -> 0 | I88: =SUM(I82:I87) -> 896631.94 | J88: =SUM(J82:J87) -> 1158840.3 | K88: =SUM(K82:K87) -> 1158840.3 | ... AE88: =SUM(AE82:AE87) -> 0 | AG88: =SUM(AG82:AG87) -> 17676000 | AH88: =B88-AG88 -> 0
AH89: =B89-AG89 -> 0
A90: SOFT COSTS PROFESSIONALS - FINAL ENTITLEMENTS & SITE INFRA. | B90: ='Proforma Land+Home'!$F96 -> 0 | AG90: =SUM(C90:AE90) -> 0 | AH90: =B90-AG90 -> 0
A91: Land Planning & PUD App Prep/Revisions (15% of Cost) | B91: ='Proforma Land+Home'!$E97 -> 84375 | H91: ='Proforma Land+Home'!$E97/18 -> 4687.5 | I91: ='Proforma Land+Home'!$E97/18 -> 4687.5 | J91: ='Proforma Land+Home'!$E97/18 -> 4687.5 | K91: ='Proforma Land+Home'!$E97/18 -> 4687.5 | L91: ='Proforma Land+Home'!$E97/18 -> 4687.5 | M91: ='Proforma Land+Home'!$E97/18 -> 4687.5 | N91: ='Proforma Land+Home'!$E97/18 -> 4687.5 | O91: ='Proforma Land+Home'!$E97/18 -> 4687.5 | ... Y91: ='Proforma Land+Home'!$E97/18 -> 4687.5 | AG91: =SUM(C91:AE91) -> 84375 | AH91: =B91-AG91 -> 0
A92: Civil, Surveying & PUD App Prep/Revisions (10% of Infra Cost) | B92: ='Proforma Land+Home'!$E99 -> 391909.38 | H92: ='Proforma Land+Home'!$E99/18 -> 21772.743 | I92: ='Proforma Land+Home'!$E99/18 -> 21772.743 | J92: ='Proforma Land+Home'!$E99/18 -> 21772.743 | K92: ='Proforma Land+Home'!$E99/18 -> 21772.743 | L92: ='Proforma Land+Home'!$E99/18 -> 21772.743 | M92: ='Proforma Land+Home'!$E99/18 -> 21772.743 | N92: ='Proforma Land+Home'!$E99/18 -> 21772.743 | O92: ='Proforma Land+Home'!$E99/18 -> 21772.743 | ... Y92: ='Proforma Land+Home'!$E99/18 -> 21772.743 | AG92: =SUM(C92:AE92) -> 391909.38 | AH92: =B92-AG92 -> 0
A93: Traffic, Enviro, Economist & Misc. Studies | B93: ='Proforma Land+Home'!$E100 -> 300000 | H93: ='Proforma Land+Home'!$E100/18 -> 16666.667 | I93: ='Proforma Land+Home'!$E100/18 -> 16666.667 | J93: ='Proforma Land+Home'!$E100/18 -> 16666.667 | K93: ='Proforma Land+Home'!$E100/18 -> 16666.667 | L93: ='Proforma Land+Home'!$E100/18 -> 16666.667 | M93: ='Proforma Land+Home'!$E100/18 -> 16666.667 | N93: ='Proforma Land+Home'!$E100/18 -> 16666.667 | O93: ='Proforma Land+Home'!$E100/18 -> 16666.667 | ... Y93: ='Proforma Land+Home'!$E100/18 -> 16666.667 | AG93: =SUM(C93:AE93) -> 300000 | AH93: =B93-AG93 -> 0
A94: Legal / Entitlement | B94: ='Proforma Land+Home'!$E101 -> 300000 | H94: ='Proforma Land+Home'!$E101/18 -> 16666.667 | I94: ='Proforma Land+Home'!$E101/18 -> 16666.667 | J94: ='Proforma Land+Home'!$E101/18 -> 16666.667 | K94: ='Proforma Land+Home'!$E101/18 -> 16666.667 | L94: ='Proforma Land+Home'!$E101/18 -> 16666.667 | M94: ='Proforma Land+Home'!$E101/18 -> 16666.667 | N94: ='Proforma Land+Home'!$E101/18 -> 16666.667 | O94: ='Proforma Land+Home'!$E101/18 -> 16666.667 | ... Y94: ='Proforma Land+Home'!$E101/18 -> 16666.667 | AG94: =SUM(C94:AE94) -> 300000 | AH94: =B94-AG94 -> 0
A95: Accounting & CPA costs ($ per year) | B95: ='Proforma Land+Home'!$E102 -> 10000 | H95: ='Proforma Land+Home'!$E102/18 -> 555.55556 | I95: ='Proforma Land+Home'!$E102/18 -> 555.55556 | J95: ='Proforma Land+Home'!$E102/18 -> 555.55556 | K95: ='Proforma Land+Home'!$E102/18 -> 555.55556 | L95: ='Proforma Land+Home'!$E102/18 -> 555.55556 | M95: ='Proforma Land+Home'!$E102/18 -> 555.55556 | N95: ='Proforma Land+Home'!$E102/18 -> 555.55556 | O95: ='Proforma Land+Home'!$E102/18 -> 555.55556 | ... Y95: ='Proforma Land+Home'!$E102/18 -> 555.55556 | AG95: =SUM(C95:AE95) -> 10000 | AH95: =B95-AG95 -> 0
A96: Professionals Contingency | B96: ='Proforma Land+Home'!$E103 -> 79314.219 | H96: ='Proforma Land+Home'!$E103/18 -> 4406.3455 | I96: ='Proforma Land+Home'!$E103/18 -> 4406.3455 | J96: ='Proforma Land+Home'!$E103/18 -> 4406.3455 | K96: ='Proforma Land+Home'!$E103/18 -> 4406.3455 | L96: ='Proforma Land+Home'!$E103/18 -> 4406.3455 | M96: ='Proforma Land+Home'!$E103/18 -> 4406.3455 | N96: ='Proforma Land+Home'!$E103/18 -> 4406.3455 | O96: ='Proforma Land+Home'!$E103/18 -> 4406.3455 | ... Y96: ='Proforma Land+Home'!$E103/18 -> 4406.3455 | AG96: =SUM(C96:AE96) -> 79314.219 | AH96: =B96-AG96 -> 0
A97: SOFT COSTS PROFESSIONALS - FINAL ENTITLEMENTS & SITE INFRA. | B97: =SUM(B90:B96) -> 1165598.6 | D97: =SUM(D90:D96) -> 0 | E97: =SUM(E90:E96) -> 0 | F97: =SUM(F90:F96) -> 0 | G97: =SUM(G90:G96) -> 0 | H97: =SUM(H90:H96) -> 64755.477 | I97: =SUM(I90:I96) -> 64755.477 | J97: =SUM(J90:J96) -> 64755.477 | K97: =SUM(K90:K96) -> 64755.477 | ... AE97: =SUM(AE90:AE96) -> 0 | AG97: =SUM(AG90:AG96) -> 1165598.6 | AH97: =B97-AG97 -> 0
AH98: =B98-AG98 -> 0
A99: SOFT COSTS PROFESSIONALS - HOMES | B99: ='Proforma Land+Home'!$F106 -> 0 | AG99: =SUM(C99:AE99) -> 0 | AH99: =B99-AG99 -> 0
A100: Planning & Arch Concepts (4 prototype designs, amenities, etc.) | B100: ='Proforma Land+Home'!$E107 -> 500000 | H100: ='Proforma Land+Home'!$E107/18 -> 27777.778 | I100: ='Proforma Land+Home'!$E107/18 -> 27777.778 | J100: ='Proforma Land+Home'!$E107/18 -> 27777.778 | K100: ='Proforma Land+Home'!$E107/18 -> 27777.778 | L100: ='Proforma Land+Home'!$E107/18 -> 27777.778 | M100: ='Proforma Land+Home'!$E107/18 -> 27777.778 | N100: ='Proforma Land+Home'!$E107/18 -> 27777.778 | O100: ='Proforma Land+Home'!$E107/18 -> 27777.778 | ... Y100: ='Proforma Land+Home'!$E107/18 -> 27777.778 | AG100: =SUM(C100:AE100) -> 500000 | AH100: =B100-AG100 -> 0
A101: Civil Engineering (Unit Infra. & Geotech) | B101: ='Proforma Land+Home'!$E108 -> 36250 | H101: ='Proforma Land+Home'!$E108/18 -> 2013.8889 | I101: ='Proforma Land+Home'!$E108/18 -> 2013.8889 | J101: ='Proforma Land+Home'!$E108/18 -> 2013.8889 | K101: ='Proforma Land+Home'!$E108/18 -> 2013.8889 | L101: ='Proforma Land+Home'!$E108/18 -> 2013.8889 | M101: ='Proforma Land+Home'!$E108/18 -> 2013.8889 | N101: ='Proforma Land+Home'!$E108/18 -> 2013.8889 | O101: ='Proforma Land+Home'!$E108/18 -> 2013.8889 | ... Y101: ='Proforma Land+Home'!$E108/18 -> 2013.8889 | AG101: =SUM(C101:AE101) -> 36250 | AH101: =B101-AG101 -> 0
A102: Architectural Design & CDs | B102: ='Proforma Land+Home'!$E109 -> 297500 | H102: ='Proforma Land+Home'!$E109/18 -> 16527.778 | I102: ='Proforma Land+Home'!$E109/18 -> 16527.778 | J102: ='Proforma Land+Home'!$E109/18 -> 16527.778 | K102: ='Proforma Land+Home'!$E109/18 -> 16527.778 | L102: ='Proforma Land+Home'!$E109/18 -> 16527.778 | M102: ='Proforma Land+Home'!$E109/18 -> 16527.778 | N102: ='Proforma Land+Home'!$E109/18 -> 16527.778 | O102: ='Proforma Land+Home'!$E109/18 -> 16527.778 | ... Y102: ='Proforma Land+Home'!$E109/18 -> 16527.778 | AG102: =SUM(C102:AE102) -> 297500 | AH102: =B102-AG102 -> 0
...

Sheet Proforma A+H
B1: CLARENDON - AMENITY + HOTEL DEVELOPMENT: PROFORMA
B2: Operations Proforma
G3: 0 | H3: =G3+1 -> 1 | I3: =H3+1 -> 2 | J3: =I3+1 -> 3 | K3: =J3+1 -> 4 | L3: =K3+1 -> 5 | M3: =L3+1 -> 6 | N3: =M3+1 -> 7 | O3: =N3+1 -> 8 | ... R3: =Q3+1 -> 11 | S3: 12
G4: 2024 | H4: =G4+1 -> 2025 | I4: =H4+1 -> 2026 | J4: =I4+1 -> 2027 | K4: =J4+1 -> 2028 | L4: =K4+1 -> 2029 | M4: =L4+1 -> 2030 | N4: =M4+1 -> 2031 | O4: =N4+1 -> 2032 | ... S4: =R4+1 -> 2036 | T4: TOTALS
B5: Buildout schedule | C5: SQFT | U5: Price/ Unit
B6: =Assumptions!F26 -> Lodge Rooms | C6: =Assumptions!F28 -> 500 | I6: =Assumptions!$F27*0.5 -> 10 | J6: =Assumptions!$F27*0.5 -> 10 | T6: =SUM(H6:S6) -> 20
B7: =Assumptions!G26 -> Villa/Cabin | C7: =Assumptions!G28 -> 750 | I7: =Assumptions!$G27/4 -> 6 | J7: =Assumptions!$G27/4 -> 6 | K7: =Assumptions!$G27/4 -> 6 | L7: =Assumptions!$G27/4 -> 6 | T7: =SUM(H7:S7) -> 24
B8: =Assumptions!H26 -> Cottages | C8: =Assumptions!H28 -> 1250 | J8: =Assumptions!$H27/4 -> 6 | K8: =Assumptions!$H27/4 -> 6 | L8: =Assumptions!$H27/4 -> 6 | M8: =Assumptions!$H27/4 -> 6 | T8: =SUM(H8:S8) -> 24
B9: =Assumptions!I26 -> Auton. Tents | C9: =Assumptions!I28 -> 625 | H9: =Assumptions!I27 -> 12 | T9: =SUM(H9:S9) -> 12
T10: =SUM(H10:S10) -> 0
T11: =SUM(H11:S11) -> 0
B12: Total starts | H12: =SUM(H6:H11) -> 12 | I12: =SUM(I6:I11) -> 16 | J12: =SUM(J6:J11) -> 22 | K12: =SUM(K6:K11) -> 12 | L12: =SUM(L6:L11) -> 12 | M12: =SUM(M6:M11) -> 6 | N12: =SUM(N6:N11) -> 0 | O12: =SUM(O6:O11) -> 0 | ... T12: =SUM(T6:T11) -> 80
B13: Total Leaseable/Sellable SQFT | C13: =SUMPRODUCT(C6:C11,T6:T11) -> 65500
B15: Sales Schedule
B16: =B6 -> Lodge Rooms | C16: =T16 -> 0 | H16: =ROUND(G6*Assumptions!$F33,0) -> 0 | I16: =ROUND(H6*Assumptions!$F33,0) -> 0 | J16: =ROUND(I6*Assumptions!$F33,0) -> 0 | K16: =ROUND(J6*Assumptions!$F33,0) -> 0 | L16: =ROUND(K6*Assumptions!$F33,0) -> 0 | M16: =ROUND(L6*Assumptions!$F33,0) -> 0 | N16: =ROUND(M6*Assumptions!$F33,0) -> 0 | O16: =ROUND(N6*Assumptions!$F33,0) -> 0 | ... S16: =ROUND(R6*Assumptions!$F33,0) -> 0 | T16: =SUM(H16:S16) -> 0
B17: =B7 -> Villa/Cabin | C17: =T17 -> 12 | H17: =ROUNDDOWN(G7*Assumptions!$G$33,0) -> 0 | I17: =ROUNDDOWN(H7*Assumptions!$G$33,0) -> 0 | J17: =ROUND(I7*Assumptions!$G33,0) -> 3 | K17: =ROUND(J7*Assumptions!$G33,0) -> 3 | L17: =ROUND(K7*Assumptions!$G33,0) -> 3 | M17: =ROUND(L7*Assumptions!$G33,0) -> 3 | N17: =ROUND(M7*Assumptions!$G33,0) -> 0 | O17: =ROUND(N7*Assumptions!$G33,0) -> 0 | P17: =ROUND(O7*Assumptions!$G33,0) -> 0 | Q17: =ROUND(P7*Assumptions!$G33,0) -> 0 | ... S17: =ROUND(R7*Assumptions!$G33,0) -> 0 | T17: =SUM(H17:S17) -> 12
B18: =B8 -> Cottages | C18: =T18 -> 24 | H18: =ROUND(G8*Assumptions!$H33,0) -> 0 | I18: =ROUND(H8*Assumptions!$H33,0) -> 0 | J18: =ROUND(I8*Assumptions!$H33,0) -> 0 | K18: =ROUND(J8*Assumptions!$H33,0) -> 6 | L18: =ROUND(K8*Assumptions!$H33,0) -> 6 | M18: =ROUND(L8*Assumptions!$H33,0) -> 6 | N18: =ROUND(M8*Assumptions!$H33,0) -> 6 | O18: =ROUND(N8*Assumptions!$H33,0) -> 0 | ... S18: =ROUND(R8*Assumptions!$H33,0) -> 0 | T18: =SUM(H18:S18) -> 24
B19: =B9 -> Auton. Tents | C19: =T19 -> 0 | H19: =ROUND(G9*Assumptions!$I35,0) -> 0 | I19: =ROUND(H9*Assumptions!$I35,0) -> 0 | J19: =ROUND(I9*Assumptions!$I35,0) -> 0 | K19: =ROUND(J9*Assumptions!$I35,0) -> 0 | L19: =ROUND(K9*Assumptions!$I35,0) -> 0 | M19: =ROUND(L9*Assumptions!$I35,0) -> 0 | N19: =ROUND(M9*Assumptions!$I35,0) -> 0 | O19: =ROUND(N9*Assumptions!$I35,0) -> 0 | ... S19: =ROUND(R9*Assumptions!$I35,0) -> 0 | T19: =SUM(H19:S19) -> 0
H20: =ROUNDDOWN(G10*Assumptions!$F$33,0) -> 0 | I20: =ROUNDDOWN(H10*Assumptions!$F$33,0) -> 0 | J20: =ROUNDDOWN(I10*Assumptions!$F$33,0) -> 0 | K20: =ROUNDDOWN(J10*Assumptions!$F$33,0) -> 0 | L20: =ROUNDDOWN(K10*Assumptions!$F$33,0) -> 0 | M20: =ROUNDDOWN(L10*Assumptions!$F$33,0) -> 0 | N20: =ROUNDDOWN(M10*Assumptions!$F$33,0) -> 0 | O20: =ROUNDDOWN(N10*Assumptions!$F$33,0) -> 0 | ... R20: =ROUNDDOWN(Q10*Assumptions!$F$33,0) -> 0 | S20: =R8 -> 0 | T20: =SUM(H20:S20) -> 0
H21: =ROUNDDOWN(G11*Assumptions!$G$33,0) -> 0 | I21: =ROUNDDOWN(H11*Assumptions!$G$33,0) -> 0 | J21: =ROUNDDOWN(I11*Assumptions!$G$33,0) -> 0 | K21: =ROUNDDOWN(J11*Assumptions!$G$33,0) -> 0 | L21: =ROUNDDOWN(K11*Assumptions!$G$33,0) -> 0 | M21: =ROUNDDOWN(L11*Assumptions!$G$33,0) -> 0 | N21: =ROUNDDOWN(M11*Assumptions!$G$33,0) -> 0 | O21: =ROUNDDOWN(N11*Assumptions!$G$33,0) -> 0 | ... R21: =ROUNDDOWN(Q11*Assumptions!$G$33,0) -> 0 | S21: =R9 -> 0 | T21: =SUM(H21:S21) -> 0
B22: Total sales | C22: =SUM(C16:C21) -> 36 | H22: =SUM(H16:H21) -> 0 | I22: =SUM(I16:I21) -> 0 | J22: =SUM(J16:J21) -> 3 | K22: =SUM(K16:K21) -> 9 | L22: =SUM(L16:L21) -> 9 | M22: =SUM(M16:M21) -> 9 | N22: =SUM(N16:N21) -> 6 | O22: =SUM(O16:O21) -> 0 | ... T22: =SUM(T16:T21) -> 36 | U22: =T22/T12 -> 0.45
B23: Sales Price Escalation / Hotel RECAP Price | H23: =G23 -> 0 | I23: =G23 -> 0 | J23: =I23*(1+$C$24) -> 0 | K23: =J23*(1+$C$24) -> 0 | L23: =K23*(1+$C$24) -> 0 | M23: =L23*(1+$C$24) -> 0 | N23: =M23*(1+$C$24) -> 0 | O23: =N23*(1+$C$24) -> 0 | P23: =O23*(1+$C$24) -> 0 | Q23: =P23*(1+$C$25) -> 0 | R23: =Q23*(1+$C$25) -> 0 | S23: =R23*(1+$C$25) -> 0
B24: Lodge Rooms Sales Price PSF | C24: =Assumptions!F32 -> 0.05 | D24: Lodge Rooms | G24: =Assumptions!F29 -> 0 | J24: =$G24 -> 0 | K24: =J24*(1+$C$24) -> 0 | L24: =K24*(1+$C$24) -> 0
B25: Cabins Sales Price PSF | C25: =Assumptions!G32 -> 0.05 | D25: Cabins | G25: =Assumptions!G29 -> 2250 | J25: =$G25 -> 2250 | K25: =J25*(1+$C$25) -> 2362.5 | L25: =K25*(1+$C$25) -> 2480.625 | M25: =L25*(1+$C$25) -> 2604.6562 | N25: =M25*(1+$C$25) -> 2734.8891 | O25: =N25*(1+$C$25) -> 2871.6335 | P25: =O25*(1+$C$25) -> 3015.2152 | Q25: =P25*(1+$C$25) -> 3165.976 | R25: =Q25*(1+$C$25) -> 3324.2747
B26: Cottages Sales Price PSF | C26: =C25 -> 0.05 | D26: Cottages | G26: =Assumptions!H29 -> 2000 | J26: =$G26 -> 2000 | K26: =J26*(1+$C26) -> 2100 | L26: =K26*(1+$C26) -> 2205 | M26: =L26*(1+$C26) -> 2315.25 | N26: =M26*(1+$C26) -> 2431.0125 | O26: =N26*(1+$C26) -> 2552.5631 | P26: =O26*(1+$C26) -> 2680.1913 | Q26: =P26*(1+$C26) -> 2814.2008 | R26: =Q26*(1+$C26) -> 2954.9109
B27: Auton. Tent Sales Price PSF | C27: =C26 -> 0.05 | D27: Auton. Tents | G27: =Assumptions!I29 -> 0 | H27: =$G27 -> 0 | I27: =$G27 -> 0 | J27: =$G27 -> 0 | K27: =J27*(1+$C27) -> 0 | L27: =K27*(1+$C27) -> 0 | M27: =L27*(1+$C27) -> 0 | N27: =M27*(1+$C27) -> 0 | O27: =N27*(1+$C27) -> 0 | P27: =O27*(1+$C27) -> 0 | Q27: =P27*(1+$C27) -> 0 | R27: =Q27*(1+$C27) -> 0
B29: Average Sales $ per Unit | J29: =J60/J22 -> 1687500 | K29: =K60/K22 -> 2340625 | Q29: =IFERROR(SUM(P52+Q53)/Q22,"") | R29: =IFERROR(SUM(Q52+R53)/R22,"") | S29: =IFERROR(SUM(R52+S53)/S22,"")
B31: SOURCES
B33: FINANCING
B35: EQUITY INVESTMENT | T35: =SUM(G35:R35) -> 0
B36: LAND EQUITY IN 80 ACRES | I36: ='Proforma Land+Home'!G50 -> Before, we've put $15M into the Land+Home proforma to "pay ourselves" for the value created for the Resort Lot | T36: =SUM(G36:R36) -> 0
B37: MTN ORIGINS - PURSUIT CAPITAL | T37: =SUM(G37:R37) -> 0
B38: LP - EQUITY CAPITAL | I38: =-H38-I213 -> 0 | T38: =SUM(G38:R38) -> 0
B39: EQUITY INVESTMENT | G39: =G36+G37+G38 -> 0 | H39: =H36+H37+H38 -> 0 | I39: =I36+I37+I38 -> #VALUE! | J39: =J36+J37+J38 -> 0 | K39: =K36+K37+K38 -> 0 | L39: =L36+L37+L38 -> 0 | M39: =M36+M37+M38 -> 0 | N39: =N36+N37+N38 -> 0 | ... S39: =S36+S37+S38 -> 0 | T39: =SUM(G39:R39) -> #VALUE!
B41: DEBT
B42: EB5 - MEZZ DEBT | H42: =SUM(G183:H183)*(1+C200+C201)*0.955-H39 -> 15103342 | I42: =W191-H42 -> #VALUE! | T42: =SUM(G42:R42) -> #VALUE!
B43: DEV LOAN - DEV COSTS | C43: =W190 -> #VALUE! | H43: =MAX(H183+H200+H201-H39-H42-H53-H60-G248,0) -> 0 | I43: =MAX(I183+I200+I201-I39-I42-I53-I60-H248,0) -> #VALUE! | J43: =MAX(J183+J200+J201-J39-J42-J53-J60-I248,0) -> #VALUE! | K43: =MAX(K183+K200+K201-K39-K42-K53-K60-J248,0) -> #VALUE! | L43: =MAX(L183+L200+L201-L39-L42-L53-L60-K248,0) -> #VALUE! | M43: =MAX(M183+M200+M201-M39-M42-M53-M60-L248,0) -> #VALUE! | T43: =SUM(G43:R43) -> #VALUE!
B44: DEV LOAN - FINANCING / RESERVE | H44: =IF(SUM($G44:G44)+$T43<$C$43,MIN(H187+H188,$C$43-$T$43-SUM($G44:G44)),0) -> #VALUE! | I44: =IF(SUM($G44:H44)+$T43<$C$43,MIN(I187+I188,$C$43-$T$43-SUM($G44:H44)),0) -> #VALUE! | J44: =IF(SUM($G44:I44)+$T43<$C$43,MIN(J187+J188,$C$43-$T$43-SUM($G44:I44)),0) -> #VALUE! | K44: =IF(SUM($G44:J44)+$T43<$C$43,MIN(K187+K188,$C$43-$T$43-SUM($G44:J44)),0) -> #VALUE! | L44: =IF(SUM($G44:K44)+$T43<$C$43,MIN(L187+L188,$C$43-$T$43-SUM($G44:K44)),0) -> #VALUE! | M44: =IF(SUM($G44:L44)+$T43<$C$43,MIN(M187+M188,$C$43-$T$43-SUM($G44:L44)),0) -> #VALUE! | N44: =IF(SUM($G44:M44)+$T43<$C$43,MIN(N187+N188,$C$43-$T$43-SUM($G44:M44)),0) -> #VALUE! | O44: =IF(SUM($G44:N44)+$T43<$C$43,MIN(O187+O188,$C$43-$T$43-SUM($G44:N44)),0) -> #VALUE! | ... R44: =IF(SUM($G44:Q44)+$T43<$C$43,MIN(R187+R188,$C$43-$T$43-SUM($G44:Q44)),0) -> #VALUE! | T44: =SUM(G44:R44) -> #VALUE!
B45: DEBT | G45: =SUM(G42:G44) -> 0 | H45: =SUM(H42:H44) -> #VALUE! | I45: =SUM(I42:I44) -> #VALUE! | J45: =SUM(J42:J44) -> #VALUE! | K45: =SUM(K42:K44) -> #VALUE! | L45: =SUM(L42:L44) -> #VALUE! | M45: =SUM(M42:M44) -> #VALUE! | N45: =SUM(N42:N44) -> #VALUE! | ... T45: =SUM(T42:T44) -> #VALUE!
B47: OPERATING INCOME
B48: ='A+H Monthly CF'!B98 -> Gross Operating Profit | I48: {=INDEX('A+H Annual CF'!$C$63:$Y$63,0,MATCH(I4,'A+H Annual CF'!$C$6:$Y$6,0))} -> 0 | J48: {=INDEX('A+H Annual CF'!$C$63:$Y$63,0,MATCH(J4,'A+H Annual CF'!$C$6:$Y$6,0))} -> 604064.37 | K48: {=INDEX('A+H Annual CF'!$C$63:$Y$63,0,MATCH(K4,'A+H Annual CF'!$C$6:$Y$6,0))} -> 2802414.9 | L48: {=INDEX('A+H Annual CF'!$C$63:$Y$63,0,MATCH(L4,'A+H Annual CF'!$C$6:$Y$6,0))} -> 5638595.4 | M48: {=INDEX('A+H Annual CF'!$C$63:$Y$63,0,MATCH(M4,'A+H Annual CF'!$C$6:$Y$6,0))} -> 6632922.3 | N48: {=INDEX('A+H Annual CF'!$C$63:$Y$63,0,MATCH(N4,'A+H Annual CF'!$C$6:$Y$6,0))} -> 7681803.9 | T48: =SUM(G48:R48) -> 23359801
B49: VACANCY LOSS DURING STABILIZATION Hotel | G49: 0 | H49: 0 | I49: 0 | J49: -0.5 | K49: -0.25 | L49: 0 | M49: 0 | N49: 0
B50: REALIZED NET OPERATING INCOME | G50: =G48*(1+G49) -> 0 | H50: =H48*(1+H49) -> 0 | I50: =I48*(1+I49) -> 0 | J50: =J48*(1+J49) -> 302032.18 | K50: =K48*(1+K49) -> 2101811.1 | L50: =L48*(1+L49) -> 5638595.4 | M50: =M48*(1+M49) -> 6632922.3 | N50: =N48*(1+N49) -> 7681803.9 | T50: =SUM(G50:R50) -> 22357165
B51: NO. OF MEMBERS | H51: 0 | I51: 0 | J51: 2 | K51: 9.5 | L51: 52 | M51: 57.5 | N51: 57.5
B52: OTHER INCOME - Member Dues | C52: 35000 | D52: /year per member | H52: =IF(H3<=Assumptions!$C$30,$C$52*H51,0) -> 0 | I52: =IF(I3<=Assumptions!$C$30,$C$52*I51,0) -> 0 | J52: =IF(J3<=Assumptions!$C$30,$C$52*J51,0) -> 70000 | K52: =IF(K3<=Assumptions!$C$30,$C$52*K51,0) -> 332500 | L52: =IF(L3<=Assumptions!$C$30,$C$52*L51,0) -> 1820000 | M52: =IF(M3<=Assumptions!$C$30,$C$52*M51,0) -> 2012500 | N52: =IF(N3<=Assumptions!$C$30,$C$52*N51,0) -> 2012500 | T52: =SUM(G52:R52) -> 6247500
B53: TOTAL NET OPERATING INCOME (NOI) | G53: =G50+G52 -> 0 | H53: =H50+H52 -> 0 | I53: =I50+I52 -> 0 | J53: =J50+J52 -> 372032.18 | K53: =K50+K52 -> 2434311.1 | L53: =L50+L52 -> 7458595.4 | M53: =M50+M52 -> 8645422.3 | N53: =N50+N52 -> 9694303.9 | ... R53: =R50+R52 -> 0 | T53: =SUM(G53:R53) -> 28604665
B55: UNIT SALES
B56: UNIT SALES - Lodge Rooms | G56: =$C6*G24*G16 -> 0 | H56: =$C6*H24*H16 -> 0 | I56: =$C6*I24*I16 -> 0 | J56: =$C6*J24*J16 -> 0 | K56: =$C6*K24*K16 -> 0 | L56: =$C6*L24*L16 -> 0 | M56: =$C6*M24*M16 -> 0 | N56: =$C6*N24*N16 -> 0 | ... R56: =$C6*R24*R16 -> 0 | T56: =SUM(G56:R56) -> 0
B57: UNIT SALES - Cabins | G57: =$C7*G25*G17 -> 0 | H57: =$C7*H25*H17 -> 0 | I57: =$C7*I25*I17 -> 0 | J57: =$C7*J25*J17 -> 5062500 | K57: =$C7*K25*K17 -> 5315625 | L57: =$C7*L25*L17 -> 5581406.2 | M57: =$C7*M25*M17 -> 5860476.6 | N57: =$C7*N25*N17 -> 0 | ... R57: =$C7*R25*R17 -> 0 | T57: =SUM(G57:R57) -> 21820008
B58: UNIT SALES - Cottages | G58: =$C8*G26*G18 -> 0 | H58: =$C8*H26*H18 -> 0 | I58: =$C8*I26*I18 -> 0 | J58: =$C8*J26*J18 -> 0 | K58: =$C8*K26*K18 -> 15750000 | L58: =$C8*L26*L18 -> 16537500 | M58: =$C8*M26*M18 -> 17364375 | N58: =$C8*N26*N18 -> 18232594 | ... R58: =$C8*R26*R18 -> 0 | T58: =SUM(G58:R58) -> 67884469
B59: UNIT SALES - Auton. Tents | G59: =$C9*G27*G19 -> 0 | H59: =$C9*H27*H19 -> 0 | I59: =$C9*I27*I19 -> 0 | J59: =$C9*J27*J19 -> 0 | K59: =$C9*K27*K19 -> 0 | L59: =$C9*L27*L19 -> 0 | M59: =$C9*M27*M19 -> 0 | N59: =$C9*N27*N19 -> 0 | ... R59: =$C9*R27*R19 -> 0 | T59: =SUM(G59:R59) -> 0
B60: TOTAL UNIT SALES | G60: =SUM(G56:G59) -> 0 | H60: =SUM(H56:H59) -> 0 | I60: =SUM(I56:I59) -> 0 | J60: =SUM(J56:J59) -> 5062500 | K60: =SUM(K56:K59) -> 21065625 | L60: =SUM(L56:L59) -> 22118906 | M60: =SUM(M56:M59) -> 23224852 | N60: =SUM(N56:N59) -> 18232594 | ... R60: =SUM(R56:R59) -> 0 | T60: =SUM(G60:R60) -> 89704477
B62: HOTEL DISPOSITION
B63: SALE VALUE | C63: =Assumptions!C31 -> 0.065 | D63: Terminal Cap Rate | H63: =H53/$C$63 -> 0 | I63: =I53/$C$63 -> 0 | J63: =J53/$C$63 -> 5723572 | K63: =K53/$C$63 -> 37450941 | L63: =L53/$C$63 -> 1.1474762e+08 | M63: =M53/$C$63 -> 1.330065e+08 | N63: =N53/$C$63 -> 1.4914314e+08 | O63: =O53/$C$63 -> 0 | ... R63: =R53/$C$63 -> 0
B65: HOTEL SALE PROCEEDS / DISPOSITION | H65: =IF(H3=Assumptions!$C$30,H63-H64,0) -> 0 | I65: =IF(I3=Assumptions!$C$30,I63-I64,0) -> 0 | J65: =IF(J3=Assumptions!$C$30,J63-J64,0) -> 0 | K65: =IF(K3=Assumptions!$C$30,K63-K64,0) -> 0 | L65: =IF(L3=Assumptions!$C$30,L63-L64,0) -> 0 | M65: =IF(M3=Assumptions!$C$30,M63-M64,0) -> 0 | N65: =IF(N3=Assumptions!$C$30,N63-N64,0) -> 1.4914314e+08 | O65: =IF(O3=Assumptions!$C$30,O63-O64,0) -> 0 | ... R65: =IF(R3=Assumptions!$C$30,R63-R64,0) -> 0 | T65: =SUM(G65:R65) -> 1.4914314e+08 | V65: =T65+T60 -> 2.3884761e+08
B67: TOTAL SOURCES | G67: =G39+G45+G53+G60+G65 -> 0 | H67: =H39+H45+H53+H60+H65 -> #VALUE! | I67: =I39+I45+I53+I60+I65 -> #VALUE! | J67: =J39+J45+J53+J60+J65 -> #VALUE! | K67: =K39+K45+K53+K60+K65 -> #VALUE! | L67: =L39+L45+L53+L60+L65 -> #VALUE! | M67: =M39+M45+M53+M60+M65 -> #VALUE! | N67: =N39+N45+N53+N60+N65 -> #VALUE! | ... R67: =R39+R45+R53+R60+R65 -> #VALUE! | T67: =SUM(G67:R67) -> #VALUE! | V67: =T43/(T43+T39) -> #VALUE! | W67: LTC
B69: USES
B71: LAND & PROJECT ACQUISITION COSTS
B72: Project Acquisition | G72: Incl L+H Profroma | I72: ='Proforma Land+Home'!G50 -> Before, we've put $15M into the Land+Home proforma to "pay ourselves" for the value created for the Resort Lot | T72: =SUM(G72:R72) -> 0 | V72: =T72/V65 -> 0
B73: Asset Acquisition Fee (based on total project initial value Equity + Debt) | E73: 0.02 | G73: Incl L+H Profroma | T73: =SUM(G73:R73) -> 0
B74: Closing Costs | E74: 0.0015 | T74: =SUM(G74:R74) -> 0
B75: LAND ACQUISITION COSTS | H75: =H72+H73 -> 0 | I75: =I72+I73 -> #VALUE! | J75: =J72+J73 -> 0 | K75: =K72+K73 -> 0 | L75: =L72+L73 -> 0 | M75: =M72+M73 -> 0 | N75: =N72+N73 -> 0 | O75: =O72+O73 -> 0 | ... R75: =R72+R73 -> 0 | T75: =SUM(G75:R75) -> #VALUE! | V75: =T75/V65 -> #VALUE! | W75: of TOTAL DISPOSITION
B77: VERTICAL CONSTRUCTION COSTS | C77: Units | D77: Bldg(s) SF | E77: $/SF
B78: Phase 1 - Amenity Build Out
B79: Clubhouse for Residents | C79: 1 | D79: 5000 | E79: 1000 | H79: =$E79*$D79/2 -> 2500000 | I79: =$E79*$D79/2 -> 2500000 | T79: =SUM(I79:R79) -> 2500000
B80: Clubhouse - Deck, Lawn, etc. | C80: 1 | D80: 3000 | E80: 250 | H80: =$E80*$D80/2 -> 375000 | I80: =H80 -> 375000 | T80: =SUM(J80:R80) -> 0
B81: Hot Springs Pools & Decks | C81: 6 | D81: =C81*350 -> 2100 | E81: 500 | H81: =$E81*$D81/2 -> 525000 | I81: =$E81*$D81/2 -> 525000 | T81: =SUM(I81:R81) -> 525000
B82: Hot Springs Changing Hut/Bthrm/Shower | C82: =C81 -> 6 | D82: =C82*300 -> 1800 | E82: 500 | H82: =$E82*$D82/2 -> 450000 | I82: =$E82*$D82/2 -> 450000 | T82: =SUM(I82:R82) -> 450000
B83: Minor Operating Dept. (Sporting Clays, etc.) | C83: 3 | D83: =C83*1450 -> 4350 | E83: 250 | H83: =$E83*$D83/2 -> 543750 | I83: =$E83*$D83/2 -> 543750 | T83: =SUM(I83:R83) -> 543750
B84: Gear/Toy Storage | C84: 1 | D84: 2000 | E84: 250 | H84: =$E84*$D84/2 -> 250000 | I84: =H84 -> 250000 | T84: =SUM(I84:R84) -> 250000
B85: FF&E Budget | D85: =D79+D80+D81+D82+D83+D84 -> 18250 | E85: 50 | I85: =($D85*$E85)*0.5 -> 456250 | J85: =($D85*$E85)*0.5 -> 456250 | T85: =SUM(I85:R85) -> 912500
B86: =B78 -> Phase 1 - Amenity Build Out | D86: =SUM(D79:D84) -> 18250 | G86: =SUM(G79:G85) -> 0 | H86: =SUM(H79:H85) -> 4643750 | I86: =SUM(I79:I85) -> 5100000 | J86: =SUM(J79:J85) -> 456250 | K86: =SUM(K79:K85) -> 0 | L86: =SUM(L79:L85) -> 0 | M86: =SUM(M79:M85) -> 0 | N86: =SUM(N79:N85) -> 0 | ... R86: =SUM(R79:R85) -> 0 | T86: =SUM(G86:R86) -> 10200000 | U86: =T86/D86 -> 558.90411 | V86: /sf
B88: Phase 2 - Amenity Build Out
B89: Event Center | C89: 1 | D89: 8000 | E89: 350 | I89: =$E89*$D89/2 -> 1400000 | J89: =I89 -> 1400000 | T89: =SUM(H89:R89) -> 2800000
B90: Event Center - Deck, Lawn, Amphitheater | C90: 1 | D90: 3000 | E90: 200 | I90: =$E90*$D90/2 -> 300000 | J90: =I90 -> 300000 | T90: =SUM(H90:R90) -> 600000
B91: Hot Springs Pools & Decks | C91: 12 | D91: =C91*350 -> 4200 | E91: 500 | I91: =$E91*$D91/4 -> 525000 | J91: =$E91*$D91/4 -> 525000 | K91: =$E91*$D91/4 -> 525000 | L91: =$E91*$D91/4 -> 525000 | T91: =SUM(I91:R91) -> 2100000
B92: Hot Springs Changing Hut/Bthrm/Shower | C92: =C91 -> 12 | D92: =C92*300 -> 3600 | E92: 500 | I92: =$E92*$D92/4 -> 450000 | J92: =$E92*$D92/4 -> 450000 | K92: =$E92*$D92/4 -> 450000 | L92: =$E92*$D92/4 -> 450000 | T92: =SUM(I92:R92) -> 1800000
B93: Minor Operating Dept. (Adventure Prog., etc.) | C93: 3 | D93: =C93*1450 -> 4350 | E93: 250 | J93: =$E93*$D93/3 -> 362500 | K93: =$E93*$D93/3 -> 362500 | L93: =$E93*$D93/3 -> 362500 | T93: =SUM(J93:R93) -> 1087500
B94: Gear/Toy Storage | C94: 1 | D94: 2000 | E94: 250 | I94: =$E94*$D94/2 -> 250000 | J94: =I94 -> 250000 | T94: =SUM(H94:R94) -> 500000
B95: FF&E Budget | D95: =D89+D90+D91+D92+D93+D94 -> 25150 | E95: 50 | J95: =($D95*$E95)*0.35 -> 440125 | K95: =($D95*$E95)*0.35 -> 440125 | L95: =($D95*$E95)*0.3 -> 377250 | T95: =SUM(H95:R95) -> 1257500
B96: =B88 -> Phase 2 - Amenity Build Out | D96: =SUM(D89:D94) -> 25150 | G96: =SUM(G89:G95) -> 0 | H96: =SUM(H89:H95) -> 0 | I96: =SUM(I89:I95) -> 2925000 | J96: =SUM(J89:J95) -> 3727625 | K96: =SUM(K89:K95) -> 1777625 | L96: =SUM(L89:L95) -> 1714750 | M96: =SUM(M89:M95) -> 0 | N96: =SUM(N89:N95) -> 0 | ... R96: =SUM(R89:R95) -> 0 | T96: =SUM(H96:R96) -> 10145000 | U96: =T96/D96 -> 403.37972 | V96: /sf
B98: Guest Rooms, Cabins, Cottages & Auton. Tents
B99: =B6 -> Lodge Rooms | C99: =Assumptions!F27 -> 20 | D99: =C99*Assumptions!F28 -> 10000 | E99: 750 | I99: =$C6*I6*$E99 -> 3750000 | J99: =$C6*J6*$E99 -> 3750000 | K99: =$C6*K6*$E99 -> 0 | T99: =SUM(H99:R99) -> 7500000
B100: Rooms: Circulation & Exterior Spaces | C100: =C99 -> 20 | D100: =C100*250 -> 5000 | E100: 350 | I100: =D100*E100/2 -> 875000 | J100: =I100 -> 875000 | T100: =SUM(H100:R100) -> 1750000
B101: =B7 -> Villa/Cabin | C101: =Assumptions!G27 -> 24 | D101: =C101*Assumptions!G28 -> 18000 | E101: 950 | I101: =$C7*I7*$E101 -> 4275000 | J101: =$C7*J7*$E101 -> 4275000 | K101: =$C7*K7*$E101 -> 4275000 | T101: =SUM(H101:R101) -> 12825000
B102: =B8 -> Cottages | C102: =Assumptions!H27 -> 24 | D102: =C102*Assumptions!H28 -> 30000 | E102: 850 | H102: =$C8*H8*$E102 -> 0 | I102: =$C8*I8*$E102 -> 0 | J102: =$C8*J8*$E102 -> 6375000 | K102: =$C8*K8*$E102 -> 6375000 | T102: =SUM(H102:R102) -> 12750000
B103: =B9 -> Auton. Tents | C103: =Assumptions!I27 -> 12 | D103: =C103*Assumptions!I28 -> 7500 | E103: 400 | H103: =$C9*H9*$E103 -> 3000000 | I103: =$C9*I9*$E103 -> 0 | J103: =$C9*J9*$E103 -> 0 | K103: =$C9*K9*$E103 -> 0 | T103: =SUM(H103:R103) -> 3000000
B104: ADU Exterior Spaces (decks, patios, etc.) | C104: =C101+C102+C103 -> 60 | D104: =C104*150 -> 9000 | E104: 250 | I104: =D104*E104/2 -> 1125000 | J104: =I104 -> 1125000 | T104: =SUM(H104:R104) -> 2250000
B105: FF&E Budget | D105: =D99+D100+D101+D102+D103+D104 -> 79500 | E105: 75 | H105: =D103*E105 -> 562500 | I105: =(($D105-$D103)*$E105)/2 -> 2700000 | J105: =(($D105-$D103)*$E105)/2 -> 2700000 | T105: =SUM(H105:R105) -> 5962500
B106: Guest Rooms Vertical Construction Costs | D106: =D99+SUM(D101:D103) -> 65500 | G106: =SUM(G99:G105) -> 0 | H106: =SUM(H99:H105) -> 3562500 | I106: =SUM(I99:I105) -> 12725000 | J106: =SUM(J99:J105) -> 19100000 | K106: =SUM(K99:K105) -> 10650000 | L106: =SUM(L99:L105) -> 0 | M106: =SUM(M99:M105) -> 0 | N106: =SUM(N99:N105) -> 0 | ... R106: =SUM(R99:R105) -> 0 | T106: =SUM(H106:R106) -> 46037500 | U106: =T106/D106 -> 702.8626 | V106: /sf
B108: Lodge + Restaurant
B109: Reception + Lobby | D109: =(400+100+100+200+200)*1.2 -> 1200 | E109: 450 | I109: =D109*E109/2 -> 270000 | J109: =I109 -> 270000 | T109: =SUM(H109:R109) -> 540000
B110: Restaurant (Dining Room, Bar) | D110: =(2000+1200)*1.2 -> 3840 | E110: 450 | I110: =D110*E110/2 -> 864000 | J110: =I110 -> 864000 | T110: =SUM(H110:R110) -> 1728000
B111: Back of House (kitchen, offices, etc.) | D111: =(1000+600+200+600+200+200+400)*1.2 -> 3840 | E111: 450 | I111: =D111*E111/2 -> 864000 | J111: =I111 -> 864000 | T111: =SUM(H111:R111) -> 1728000
B112: Outdoor Dining Deck + Fire Pit | D112: =800+500 -> 1300 | E112: 250 | I112: =D112*E112/2 -> 162500 | J112: =I112 -> 162500 | T112: =SUM(H112:R112) -> 325000
B113: FF&E Budget | D113: =D110+D109+D111+D112 -> 10180 | E113: 65 | J113: =D113*E113 -> 661700 | T113: =SUM(H113:R113) -> 661700
B114: Restaurant + Conf Center Vertical Construction Costs | D114: =SUM(D109:D111) -> 8880 | G114: =SUM(G109:G113) -> 0 | H114: =SUM(H109:H113) -> 0 | I114: =SUM(I109:I113) -> 2160500 | J114: =SUM(J109:J113) -> 2822200 | K114: =SUM(K109:K113) -> 0 | L114: =SUM(L109:L113) -> 0 | M114: =SUM(M109:M113) -> 0 | N114: =SUM(N109:N113) -> 0 | ... R114: =SUM(R109:R113) -> 0 | T114: =SUM(H114:R114) -> 4982700 | U114: =T114/D114 -> 561.11486 | V114: /sf
B116: Spa / Wellness Center
B117: Reception / FOH | D117: =(250+250) -> 500 | E117: 350 | I117: =D117*E117/2 -> 87500 | J117: =I117 -> 87500 | T117: =SUM(H117:R117) -> 175000
B118: Treatment Rooms | D118: =480+1500 -> 1980 | E118: 400 | I118: =D118*E118/2 -> 396000 | J118: =I118 -> 396000 | T118: =SUM(H118:R118) -> 792000
...

Sheet A+H Monthly CF
B1: CLARENDON - AMENITY + HOTEL DEVELOPMENT: PROFORMA
B2: 10-Year Monthly Operating Cash Flow
B3: Month Ending
C4: 1 | D4: =C4+1 -> 2 | E4: =D4+1 -> 3 | F4: =E4+1 -> 4 | G4: =F4+1 -> 5 | H4: =G4+1 -> 6 | I4: =H4+1 -> 7 | J4: =I4+1 -> 8 | K4: =J4+1 -> 9 | ... DR4: =DQ4+1 -> 120
B5: =EOMONTH(C5,-1) -> 46022 | C5: =MIN(Assumptions!C26,Assumptions!C40,Assumptions!C47,Assumptions!C55) -> 46053 | D5: =EOMONTH(C5,1) -> 46081 | E5: =EOMONTH(D5,1) -> 46112 | F5: =EOMONTH(E5,1) -> 46142 | G5: =EOMONTH(F5,1) -> 46173 | H5: =EOMONTH(G5,1) -> 46203 | I5: =EOMONTH(H5,1) -> 46234 | J5: =EOMONTH(I5,1) -> 46265 | K5: =EOMONTH(J5,1) -> 46295 | ... DR5: =EOMONTH(DQ5,1) -> 49674
B6: Year | C6: =YEAR(C5) -> 2026 | D6: =YEAR(D5) -> 2026 | E6: =YEAR(E5) -> 2026 | F6: =YEAR(F5) -> 2026 | G6: =YEAR(G5) -> 2026 | H6: =YEAR(H5) -> 2026 | I6: =YEAR(I5) -> 2026 | J6: =YEAR(J5) -> 2026 | ... DR6: =YEAR(DR5) -> 2035
B8: Lodging Revenue | C8: =(C5-B5)*HLOOKUP(C$6,Assumptions!$F$45:$O$54,7,0) -> 0 | D8: =(D5-C5)*HLOOKUP(D$6,Assumptions!$F$45:$O$54,7,0) -> 0 | E8: =(E5-D5)*HLOOKUP(E$6,Assumptions!$F$45:$O$54,7,0) -> 0 | F8: =(F5-E5)*HLOOKUP(F$6,Assumptions!$F$45:$O$54,7,0) -> 0 | G8: =(G5-F5)*HLOOKUP(G$6,Assumptions!$F$45:$O$54,7,0) -> 0 | H8: =(H5-G5)*HLOOKUP(H$6,Assumptions!$F$45:$O$54,7,0) -> 0 | I8: =(I5-H5)*HLOOKUP(I$6,Assumptions!$F$45:$O$54,7,0) -> 0 | J8: =(J5-I5)*HLOOKUP(J$6,Assumptions!$F$45:$O$54,7,0) -> 0 | ... DR8: =(DR5-DQ5)*HLOOKUP(DR$6,Assumptions!$F$45:$O$54,7,0) -> #N/A
B11: Monthly Occupancy | C11: =_xlfn.XLOOKUP(MONTH(C$5),Assumptions!$F$38:$Q$38,Assumptions!$F$40:$Q$40) -> 0.75 | D11: =_xlfn.XLOOKUP(MONTH(D$5),Assumptions!$F$38:$Q$38,Assumptions!$F$40:$Q$40) -> 0.75 | E11: =_xlfn.XLOOKUP(MONTH(E$5),Assumptions!$F$38:$Q$38,Assumptions!$F$40:$Q$40) -> 0.65 | F11: =_xlfn.XLOOKUP(MONTH(F$5),Assumptions!$F$38:$Q$38,Assumptions!$F$40:$Q$40) -> 0.25 | G11: =_xlfn.XLOOKUP(MONTH(G$5),Assumptions!$F$38:$Q$38,Assumptions!$F$40:$Q$40) -> 0.15 | H11: =_xlfn.XLOOKUP(MONTH(H$5),Assumptions!$F$38:$Q$38,Assumptions!$F$40:$Q$40) -> 0.45 | I11: =_xlfn.XLOOKUP(MONTH(I$5),Assumptions!$F$38:$Q$38,Assumptions!$F$40:$Q$40) -> 0.65 | J11: =_xlfn.XLOOKUP(MONTH(J$5),Assumptions!$F$38:$Q$38,Assumptions!$F$40:$Q$40) -> 0.55 | ... DR11: =_xlfn.XLOOKUP(MONTH(DR$5),Assumptions!$F$38:$Q$38,Assumptions!$F$40:$Q$40) -> 0.55
B12: Total Room Revenue | C12: =SUM(C8:C10)*C11 -> 0 | D12: =SUM(D8:D10)*D11 -> 0 | E12: =SUM(E8:E10)*E11 -> 0 | F12: =SUM(F8:F10)*F11 -> 0 | G12: =SUM(G8:G10)*G11 -> 0 | H12: =SUM(H8:H10)*H11 -> 0 | I12: =SUM(I8:I10)*I11 -> 0 | J12: =SUM(J8:J10)*J11 -> 0 | ... DR12: =SUM(DR8:DR10)*DR11 -> #N/A
B13: Rooms Cost | C13: =C12*-Assumptions!$C$36 -> 0 | D13: =D12*-Assumptions!$C$36 -> 0 | E13: =E12*-Assumptions!$C$36 -> 0 | F13: =F12*-Assumptions!$C$36 -> 0 | G13: =G12*-Assumptions!$C$36 -> 0 | H13: =H12*-Assumptions!$C$36 -> 0 | I13: =I12*-Assumptions!$C$36 -> 0 | J13: =J12*-Assumptions!$C$36 -> 0 | ... DR13: =DR12*-Assumptions!$C$36 -> #N/A
B14: Hotel Room Gross Operating Profit | C14: =C12+C13 -> 0 | D14: =D12+D13 -> 0 | E14: =E12+E13 -> 0 | F14: =F12+F13 -> 0 | G14: =G12+G13 -> 0 | H14: =H12+H13 -> 0 | I14: =I12+I13 -> 0 | J14: =J12+J13 -> 0 | ... DR14: =DR12+DR13 -> #N/A
B15: Condo Owner Revenue Share - Villa/ Cabin | C15: =-(C5-B5)*HLOOKUP(C$6,Assumptions!$F$45:$O$54,8,0)*MAX(C11-(1-Assumptions!$G$33),0)*Assumptions!$C$37 -> 0 | D15: =-(D5-C5)*HLOOKUP(D$6,Assumptions!$F$45:$O$54,8,0)*MAX(D11-(1-Assumptions!$G$33),0)*Assumptions!$C$37 -> 0 | E15: =-(E5-D5)*HLOOKUP(E$6,Assumptions!$F$45:$O$54,8,0)*MAX(E11-(1-Assumptions!$G$33),0)*Assumptions!$C$37 -> 0 | F15: =-(F5-E5)*HLOOKUP(F$6,Assumptions!$F$45:$O$54,8,0)*MAX(F11-(1-Assumptions!$G$33),0)*Assumptions!$C$37 -> 0 | G15: =-(G5-F5)*HLOOKUP(G$6,Assumptions!$F$45:$O$54,8,0)*MAX(G11-(1-Assumptions!$G$33),0)*Assumptions!$C$37 -> 0 | H15: =-(H5-G5)*HLOOKUP(H$6,Assumptions!$F$45:$O$54,8,0)*MAX(H11-(1-Assumptions!$G$33),0)*Assumptions!$C$37 -> 0 | I15: =-(I5-H5)*HLOOKUP(I$6,Assumptions!$F$45:$O$54,8,0)*MAX(I11-(1-Assumptions!$G$33),0)*Assumptions!$C$37 -> 0 | J15: =-(J5-I5)*HLOOKUP(J$6,Assumptions!$F$45:$O$54,8,0)*MAX(J11-(1-Assumptions!$G$33),0)*Assumptions!$C$37 -> 0 | ... DR15: =-(DR5-DQ5)*HLOOKUP(DR$6,Assumptions!$F$45:$O$54,8,0)*MAX(DR11-(1-Assumptions!$G$33),0)*Assumptions!$C$37 -> #N/A
B16: Condo Owner Revenue Share - Cottages | C16: =-(C5-B5)*HLOOKUP(C$6,Assumptions!$F$45:$O$54,9,0)*MAX(C11-(1-Assumptions!$H$33),0)*Assumptions!$C$37 -> 0 | D16: =-(D5-C5)*HLOOKUP(D$6,Assumptions!$F$45:$O$54,9,0)*MAX(D11-(1-Assumptions!$H$33),0)*Assumptions!$C$37 -> 0 | E16: =-(E5-D5)*HLOOKUP(E$6,Assumptions!$F$45:$O$54,9,0)*MAX(E11-(1-Assumptions!$H$33),0)*Assumptions!$C$37 -> 0 | F16: =-(F5-E5)*HLOOKUP(F$6,Assumptions!$F$45:$O$54,9,0)*MAX(F11-(1-Assumptions!$H$33),0)*Assumptions!$C$37 -> 0 | G16: =-(G5-F5)*HLOOKUP(G$6,Assumptions!$F$45:$O$54,9,0)*MAX(G11-(1-Assumptions!$H$33),0)*Assumptions!$C$37 -> 0 | H16: =-(H5-G5)*HLOOKUP(H$6,Assumptions!$F$45:$O$54,9,0)*MAX(H11-(1-Assumptions!$H$33),0)*Assumptions!$C$37 -> 0 | I16: =-(I5-H5)*HLOOKUP(I$6,Assumptions!$F$45:$O$54,9,0)*MAX(I11-(1-Assumptions!$H$33),0)*Assumptions!$C$37 -> 0 | J16: =-(J5-I5)*HLOOKUP(J$6,Assumptions!$F$45:$O$54,9,0)*MAX(J11-(1-Assumptions!$H$33),0)*Assumptions!$C$37 -> 0 | ... DR16: =-(DR5-DQ5)*HLOOKUP(DR$6,Assumptions!$F$45:$O$54,9,0)*MAX(DR11-(1-Assumptions!$H$33),0)*Assumptions!$C$37 -> #N/A
B17: Hotel Room Net Operating Profit | C17: =C14+SUM(C15:C16) -> 0 | D17: =D14+SUM(D15:D16) -> 0 | E17: =E14+SUM(E15:E16) -> 0 | F17: =F14+SUM(F15:F16) -> 0 | G17: =G14+SUM(G15:G16) -> 0 | H17: =H14+SUM(H15:H16) -> 0 | I17: =I14+SUM(I15:I16) -> 0 | J17: =J14+SUM(J15:J16) -> 0 | ... DR17: =DR14+SUM(DR15:DR16) -> #N/A
B19: Bar Revenue | C19: =IF(C5>=Assumptions!$C$40,C12*Assumptions!$C$43,0) -> 0 | D19: =IF(D5>=Assumptions!$C$40,D12*Assumptions!$C$43,0) -> 0 | E19: =IF(E5>=Assumptions!$C$40,E12*Assumptions!$C$43,0) -> 0 | F19: =IF(F5>=Assumptions!$C$40,F12*Assumptions!$C$43,0) -> 0 | G19: =IF(G5>=Assumptions!$C$40,G12*Assumptions!$C$43,0) -> 0 | H19: =IF(H5>=Assumptions!$C$40,H12*Assumptions!$C$43,0) -> 0 | I19: =IF(I5>=Assumptions!$C$40,I12*Assumptions!$C$43,0) -> 0 | J19: =IF(J5>=Assumptions!$C$40,J12*Assumptions!$C$43,0) -> 0 | ... CT19: =IF(CT5>=Assumptions!$C$40,CT12*Assumptions!$C$43,0) -> 579701.86 | CU19: =CU12*Assumptions!$C$43 -> 814217.61 | CV19: =CV12*Assumptions!$C$43 -> 735422.36 | CW19: =CW12*Assumptions!$C$43 -> 705655.26 | CX19: =CX12*Assumptions!$C$43 -> 262650.84 | CY19: =CY12*Assumptions!$C$43 -> 162843.52 | CZ19: =CZ12*Assumptions!$C$43 -> 472771.52 | DA19: =DA12*Assumptions!$C$43 -> 705655.26 | DB19: =DB12*Assumptions!$C$43 -> 597092.91 | ... DR19: =DR12*Assumptions!$C$43 -> #N/A
B20: Food & Beverage COS | C20: =C19*-Assumptions!$C$44 -> 0 | D20: =D19*-Assumptions!$C$44 -> 0 | E20: =E19*-Assumptions!$C$44 -> 0 | F20: =F19*-Assumptions!$C$44 -> 0 | G20: =G19*-Assumptions!$C$44 -> 0 | H20: =H19*-Assumptions!$C$44 -> 0 | I20: =I19*-Assumptions!$C$44 -> 0 | J20: =J19*-Assumptions!$C$44 -> 0 | ... DR20: =DR19*-Assumptions!$C$44 -> #N/A
B21: Bar Food & Beverage Profit | C21: =C20+C19 -> 0 | D21: =D20+D19 -> 0 | E21: =E20+E19 -> 0 | F21: =F20+F19 -> 0 | G21: =G20+G19 -> 0 | H21: =H20+H19 -> 0 | I21: =I20+I19 -> 0 | J21: =J20+J19 -> 0 | ... DR21: =DR20+DR19 -> #N/A
B23: Spa / Wellness Center Revenue | C23: =IF(C5>=Assumptions!$C$47,C12*Assumptions!$C$50,0) -> 0 | D23: =IF(D5>=Assumptions!$C$47,D12*Assumptions!$C$50,0) -> 0 | E23: =IF(E5>=Assumptions!$C$47,E12*Assumptions!$C$50,0) -> 0 | F23: =IF(F5>=Assumptions!$C$47,F12*Assumptions!$C$50,0) -> 0 | G23: =IF(G5>=Assumptions!$C$47,G12*Assumptions!$C$50,0) -> 0 | H23: =IF(H5>=Assumptions!$C$47,H12*Assumptions!$C$50,0) -> 0 | I23: =IF(I5>=Assumptions!$C$47,I12*Assumptions!$C$50,0) -> 0 | J23: =IF(J5>=Assumptions!$C$47,J12*Assumptions!$C$50,0) -> 0 | ... DR23: =IF(DR5>=Assumptions!$C$47,DR12*Assumptions!$C$50,0) -> #N/A
B24: Spa / Wellness Center COS | C24: =-C23*Assumptions!$C$52 -> 0 | D24: =-D23*Assumptions!$C$52 -> 0 | E24: =-E23*Assumptions!$C$52 -> 0 | F24: =-F23*Assumptions!$C$52 -> 0 | G24: =-G23*Assumptions!$C$52 -> 0 | H24: =-H23*Assumptions!$C$52 -> 0 | I24: =-I23*Assumptions!$C$52 -> 0 | J24: =-J23*Assumptions!$C$52 -> 0 | ... DR24: =-DR23*Assumptions!$C$52 -> #N/A
B25: Spa / Wellness Center Profit | C25: =C23+C24 -> 0 | D25: =D23+D24 -> 0 | E25: =E23+E24 -> 0 | F25: =F23+F24 -> 0 | G25: =G23+G24 -> 0 | H25: =H23+H24 -> 0 | I25: =I23+I24 -> 0 | J25: =J23+J24 -> 0 | ... DR25: =DR23+DR24 -> #N/A
B27: Max Event Center Revenue | C27: =IF(C5>=Assumptions!$C$55,Assumptions!$C$65/Assumptions!$C$66*(_xlfn.XLOOKUP(C$6,Assumptions!$E$45:$O$45,Assumptions!$E$46:$O$46)),0) -> 0 | D27: =IF(D5>=Assumptions!$C$55,Assumptions!$C$65/Assumptions!$C$66*(_xlfn.XLOOKUP(D$6,Assumptions!$E$45:$O$45,Assumptions!$E$46:$O$46)),0) -> 0 | E27: =IF(E5>=Assumptions!$C$55,Assumptions!$C$65/Assumptions!$C$66*(_xlfn.XLOOKUP(E$6,Assumptions!$E$45:$O$45,Assumptions!$E$46:$O$46)),0) -> 0 | F27: =IF(F5>=Assumptions!$C$55,Assumptions!$C$65/Assumptions!$C$66*(_xlfn.XLOOKUP(F$6,Assumptions!$E$45:$O$45,Assumptions!$E$46:$O$46)),0) -> 0 | G27: =IF(G5>=Assumptions!$C$55,Assumptions!$C$65/Assumptions!$C$66*(_xlfn.XLOOKUP(G$6,Assumptions!$E$45:$O$45,Assumptions!$E$46:$O$46)),0) -> 0 | H27: =IF(H5>=Assumptions!$C$55,Assumptions!$C$65/Assumptions!$C$66*(_xlfn.XLOOKUP(H$6,Assumptions!$E$45:$O$45,Assumptions!$E$46:$O$46)),0) -> 0 | I27: =IF(I5>=Assumptions!$C$55,Assumptions!$C$65/Assumptions!$C$66*(_xlfn.XLOOKUP(I$6,Assumptions!$E$45:$O$45,Assumptions!$E$46:$O$46)),0) -> 0 | J27: =IF(J5>=Assumptions!$C$55,Assumptions!$C$65/Assumptions!$C$66*(_xlfn.XLOOKUP(J$6,Assumptions!$E$45:$O$45,Assumptions!$E$46:$O$46)),0) -> 0 | ... DR27: =IF(DR5>=Assumptions!$C$55,Assumptions!$C$65/Assumptions!$C$66*(_xlfn.XLOOKUP(DR$6,Assumptions!$E$45:$O$45,Assumptions!$E$46:$O$46)),0) -> #N/A
B28: Monthly Occupancy | C28: =_xlfn.XLOOKUP(MONTH(C$5),Assumptions!$F$38:$Q$38,Assumptions!$F$42:$Q$42) -> 0.25 | D28: =_xlfn.XLOOKUP(MONTH(D$5),Assumptions!$F$38:$Q$38,Assumptions!$F$42:$Q$42) -> 0.25 | E28: =_xlfn.XLOOKUP(MONTH(E$5),Assumptions!$F$38:$Q$38,Assumptions!$F$42:$Q$42) -> 0.25 | F28: =_xlfn.XLOOKUP(MONTH(F$5),Assumptions!$F$38:$Q$38,Assumptions!$F$42:$Q$42) -> 0.5 | G28: =_xlfn.XLOOKUP(MONTH(G$5),Assumptions!$F$38:$Q$38,Assumptions!$F$42:$Q$42) -> 0.75 | H28: =_xlfn.XLOOKUP(MONTH(H$5),Assumptions!$F$38:$Q$38,Assumptions!$F$42:$Q$42) -> 1 | I28: =_xlfn.XLOOKUP(MONTH(I$5),Assumptions!$F$38:$Q$38,Assumptions!$F$42:$Q$42) -> 1 | J28: =_xlfn.XLOOKUP(MONTH(J$5),Assumptions!$F$38:$Q$38,Assumptions!$F$42:$Q$42) -> 1 | ... DR28: =_xlfn.XLOOKUP(MONTH(DR$5),Assumptions!$F$38:$Q$38,Assumptions!$F$42:$Q$42) -> 0.25
B29: Occ. Adj. Conf Center Revenue | C29: =C27*C28 -> 0 | D29: =D27*D28 -> 0 | E29: =E27*E28 -> 0 | F29: =F27*F28 -> 0 | G29: =G27*G28 -> 0 | H29: =H27*H28 -> 0 | I29: =I27*I28 -> 0 | J29: =J27*J28 -> 0 | ... DR29: =DR27*DR28 -> #N/A
B30: Food & Beverage Commission | C30: =C29*Assumptions!$C$67 -> 0 | D30: =D29*Assumptions!$C$67 -> 0 | E30: =E29*Assumptions!$C$67 -> 0 | F30: =F29*Assumptions!$C$67 -> 0 | G30: =G29*Assumptions!$C$67 -> 0 | H30: =H29*Assumptions!$C$67 -> 0 | I30: =I29*Assumptions!$C$67 -> 0 | J30: =J29*Assumptions!$C$67 -> 0 | ... DR30: =DR29*Assumptions!$C$67 -> #N/A
B31: Events COS | C31: =IF(C29=0,0,-Assumptions!$C$68/Assumptions!$C$66) -> 0 | D31: =IF(D29=0,0,-Assumptions!$C$68/Assumptions!$C$66) -> 0 | E31: =IF(E29=0,0,-Assumptions!$C$68/Assumptions!$C$66) -> 0 | F31: =IF(F29=0,0,-Assumptions!$C$68/Assumptions!$C$66) -> 0 | G31: =IF(G29=0,0,-Assumptions!$C$68/Assumptions!$C$66) -> 0 | H31: =IF(H29=0,0,-Assumptions!$C$68/Assumptions!$C$66) -> 0 | I31: =IF(I29=0,0,-Assumptions!$C$68/Assumptions!$C$66) -> 0 | J31: =IF(J29=0,0,-Assumptions!$C$68/Assumptions!$C$66) -> 0 | ... DR31: =IF(DR29=0,0,-Assumptions!$C$68/Assumptions!$C$66) -> #N/A
B32: Events Profit | C32: =C31+C30+C27*C28 -> 0 | D32: =D31+D30+D27*D28 -> 0 | E32: =E31+E30+E27*E28 -> 0 | F32: =F31+F30+F27*F28 -> 0 | G32: =G31+G30+G27*G28 -> 0 | H32: =H31+H30+H27*H28 -> 0 | I32: =I31+I30+I27*I28 -> 0 | J32: =J31+J30+J27*J28 -> 0 | ... DR32: =DR31+DR30+DR27*DR28 -> #N/A
B34: Food & Beverage Revenue | C34: =IF(C5>=Assumptions!$C$55,C12*Assumptions!$C$58,0) -> 0 | D34: =IF(D5>=Assumptions!$C$55,D12*Assumptions!$C$58,0) -> 0 | E34: =IF(E5>=Assumptions!$C$55,E12*Assumptions!$C$58,0) -> 0 | F34: =IF(F5>=Assumptions!$C$55,F12*Assumptions!$C$58,0) -> 0 | G34: =IF(G5>=Assumptions!$C$55,G12*Assumptions!$C$58,0) -> 0 | H34: =IF(H5>=Assumptions!$C$55,H12*Assumptions!$C$58,0) -> 0 | I34: =IF(I5>=Assumptions!$C$55,I12*Assumptions!$C$58,0) -> 0 | J34: =IF(J5>=Assumptions!$C$55,J12*Assumptions!$C$58,0) -> 0 | ... DR34: =IF(DR5>=Assumptions!$C$55,DR12*Assumptions!$C$58,0) -> #N/A
B35: Food & Beverage COS | C35: =-C34*Assumptions!$C$59 -> 0 | D35: =-D34*Assumptions!$C$59 -> 0 | E35: =-E34*Assumptions!$C$59 -> 0 | F35: =-F34*Assumptions!$C$59 -> 0 | G35: =-G34*Assumptions!$C$59 -> 0 | H35: =-H34*Assumptions!$C$59 -> 0 | I35: =-I34*Assumptions!$C$59 -> 0 | J35: =-J34*Assumptions!$C$59 -> 0 | ... DR35: =-DR34*Assumptions!$C$59 -> #N/A
B36: Food & Beverage Profit | C36: =C35+C34 -> 0 | D36: =D35+D34 -> 0 | E36: =E35+E34 -> 0 | F36: =F35+F34 -> 0 | G36: =G35+G34 -> 0 | H36: =H35+H34 -> 0 | I36: =I35+I34 -> 0 | J36: =J35+J34 -> 0 | ... DR36: =DR35+DR34 -> #N/A
B38: Minor Operating Departments | C38: =C12*Assumptions!$C$71 -> 0 | D38: =D12*Assumptions!$C$71 -> 0 | E38: =E12*Assumptions!$C$71 -> 0 | F38: =F12*Assumptions!$C$71 -> 0 | G38: =G12*Assumptions!$C$71 -> 0 | H38: =H12*Assumptions!$C$71 -> 0 | I38: =I12*Assumptions!$C$71 -> 0 | J38: =J12*Assumptions!$C$71 -> 0 | ... DR38: =DR12*Assumptions!$C$71 -> #N/A
B39: MOD COS | C39: =C38*-Assumptions!$C$72 -> 0 | D39: =D38*-Assumptions!$C$72 -> 0 | E39: =E38*-Assumptions!$C$72 -> 0 | F39: =F38*-Assumptions!$C$72 -> 0 | G39: =G38*-Assumptions!$C$72 -> 0 | H39: =H38*-Assumptions!$C$72 -> 0 | I39: =I38*-Assumptions!$C$72 -> 0 | J39: =J38*-Assumptions!$C$72 -> 0 | ... DR39: =DR38*-Assumptions!$C$72 -> #N/A
B40: Minor Operating Departments Profit | C40: =C39+C38 -> 0 | D40: =D39+D38 -> 0 | E40: =E39+E38 -> 0 | F40: =F39+F38 -> 0 | G40: =G39+G38 -> 0 | H40: =H39+H38 -> 0 | I40: =I39+I38 -> 0 | J40: =J39+J38 -> 0 | ... DR40: =DR39+DR38 -> #N/A
