Workbook
Name c_AcresTotal.Res: SUM(#REF!)
Name c_AcresTotal.Res: SUM(tbl_Parcels[Acres])
Name c_UnitTotal.Res: SUM(#REF!)
Name c_UnitTotal.Res: SUM(tbl_Parcels[Low])
Name cv_CFD.CumeDebtSrvc.Annual: mCFD!$BD$373:$BD$402
Name dvl_DevCostCat: DATA!$AR$10:$AZ$10
Name dvl_Rates.Conting: _xlfn.UNIQUE(_xlfn._xlws.FILTER(iGeneral!$F$41:$F$45,iGeneral!$F$41:$F$45<>0))
Name i_CFD.AV.Inflation: i.Finance!$O$26
Name i_CFD.CommeAssesRatio: i.Finance!$O$25
Name i_CFD.FullCashRatio: i.Finance!$O$23
Name i_CFD.LimValRatio: i.Finance!$O$22
Name i_CFD.ObliRate: i.Finance!$O$61
Name i_CFD.ResiAssesRatio: i.Finance!$O$24
Name i_CFD.SA.COI: i.Finance!$O$54
Name i_CFD.SA.IntRate: i.Finance!$O$51
Name i_CFD.SA.Max: i.Finance!$O$49
Name i_CFD.SA.ResFund: i.Finance!$O$53
Name i_CFD.SA.TermYrs: i.Finance!$O$50
Name i_CFD.SA.UnderFee: i.Finance!$O$55
Name i_CFD.SA.YrsCapInt: i.Finance!$O$52
Name i_CFD.TaxRoll1: i.Finance!$O$17
Name i_CFD.TaxRoll2: i.Finance!$O$18
Name i_CFD.TaxRoll3: i.Finance!$O$19
Name i_Cost.Closing: iGeneral!$F$33
Name i_Cost.Commissions: iGeneral!$F$35
Name i_Cost.Legal: iGeneral!$F$36
Name i_Cost.Other: iGeneral!$F$37
Name i_Cost.Subd: iGeneral!$F$51
Name i_Date.Start: iGeneral!$F$13
Name i_Fee.Dispo: iGeneral!$F$34
Name i_HomeSale.MonthsOffset: i.Finance!$O$12
Name i_HousePrice: iGeneral!$F$50
Name i_HousePrice.Start: i.Finance!$O$11
Name i_Name.Project: iGeneral!$F$10
Name i_Price.FinLot: iGeneral!$F$52
Name i_rate.Hurdle1.MO: (1+i_Rate.Hurdle1)^(1/12)-1
Name i_rate.Hurdle2.MO: (1+i_Rate.Hurdle2)^(1/12)-1
Name i_rate.Hurdle3.MO: (1+i_Rate.Hurdle3)^(1/12)-1
Name i_rate.Pref.MO: (1+i_Rate.Pref)^(1/12)-1
Name i_Velocity.HomeSales: i.Finance!$O$13
Name lst_LotProducts: Table4[Product]
Name lst_LotProducts: Table4[Product]
Name lst_LUcodes: Dashboard!#REF!
Name lst_LUcodes: iMPC!$D$10:$D$14
Name lst_ProductDUA: Table4[DUA]
Name lst_ProductDUA: Table4[DUA]

Sheet Dashboard
C3: Project Name | G3: =iGeneral!F10 -> Villages at Tortolita
N4: Navigation here?
C8: Start Date | I8: =i_Date.Start -> 44562
C9: Project Acres: Gross | I9: =SUM(tbl_Parcels[Acres]) -> 1320
C11: Project Economics
D13: Land Acqusition Price: | I13: =iGeneral!#REF! -> #REF!
D14: Project Entitlements:

Sheet iGeneral
C3: =i_Name.Project -> Villages at Tortolita
D4: =F11 -> Marana, AZ Northeast of Marana Road and I-10
C8: Project Identification
C9: ID | D9: Name
C10: 1 | D10: Project Name | F10: Villages at Tortolita
C11: 2 | D11: Location | F11: Marana, AZ Northeast of Marana Road and I-10
C13: Analysis Start Date | F13: 44562 | H13: Growth rates can start at different times
C15: Land Planning Heirarchy - Largest to Smallest
C16: ID | D16: Type | F16: Code | H16: Notes
C17: 1 | D17: Plan Area | F17: PA
C18: 2 | D18: Development Phase | F18: DP | H18: Each PA has at lease 1 DP
C19: 3 | D19: Sale Phase | F19: SP | H19: Each DP has at least 1 SP
C20: 4 | D20: Parcel | F20: P | H20: Each SP has at least 1 P
C21: 5
C23: Growth Rates
C24: ID | D24: Name | E24: Rate | F24: Starts | H24: Notes
C25: 1 | D25: Price | E25: 0.02 | F25: 1 | H25: Growth rates can start at different times
C26: 2 | D26: Cost | E26: 0.01 | F26: 2
C27: 3
C28: 4
C29: 5
C31: Transaction Costs
C32: ID | D32: Transaction Costs | F32: Factor | G32: % of | H32: Notes
C33: 1 | D33: Closing Costs | F33: 0.005 | G33: Residual
C34: 2 | D34: Disposition Fee | F34: 0.03 | G34: Gross
C35: 3 | D35: Commissions | F35: 0.025 | G35: Residual
C36: 4 | D36: Legal / Transaction | F36: 0.005 | G36: Residual
C37: 5 | D37: Other | F37: 0.005 | G37: Residual
C39: Misc Factors
C40: ID | D40: Type | F40: Factor | H40: Notes
C41: 1 | D41: Contingency - Low | F41: 0.05 | H41: Factors are global
C42: 2 | D42: Contingency - Mid | F42: 0.1
C43: 3 | D43: Contingency - Hi | F43: 0.2
C44: 4 | D44: Maximum DUs | F44: 5000
C45: 5
C48: Starting Market Pricing / Costs
C49: ID | D49: Item | F49: Amount | G49: Unit
C50: 1 | D50: Starting House Price | F50: 300000 | G50: $ / Unit
C51: 2 | D51: Subdivision Development Cost | F51: 1300 | G51: $ / FF
C52: 3 | D52: Finished Residential Lot Price | F52: 2000 | G52: $ / FF
C53: 4 | D53: Commercial Land Value | F53: 8 | G53: $ / SF
C54: 5 | D54: Industrial Land Value | F54: 3 | G54: $ / SF

Sheet iLandAcquisition
D7: Land Acquisition
O8: =IF(P10>0,#REF!+1,"")
K9: Price
D10: ID | E10: Seller | F10: Installments | H10: Land Conveyed | I10: Date | J10: Payment | K10: $/Acre | L10: $/SF | M10: Notes | Q10: Year | R10: Acres | S10: Price | T10: $/Ac | U10: $/SF
D11: 1 | E11: Joe Shmoe | F11: 1 | G11: 3 | H11: 150 | I11: 44896 | J11: 2500000 | K11: =IFERROR(J11/H11,0) -> 16666.667 | L11: =K11/43560 -> 0.38261402 | Q11: 2022 | R11: 150 | S11: 1000000 | T11: 6666.6667 | U11: 0.15304561
D12: 2 | F12: 2 | G12: 3 | H12: 500 | I12: 45291 | J12: 5000000 | K12: =IFERROR(J12/H12,0) -> 10000 | L12: =K12/43560 -> 0.22956841 | Q12: 2023 | R12: 500 | S12: 5000000 | T12: 10000 | U12: 0.22956841
D13: 3 | F13: 3 | G13: 3 | H13: 750 | I13: 45657 | J13: 6000000 | K13: =IFERROR(J13/H13,0) -> 8000 | L13: =K13/43560 -> 0.18365473 | Q13: 2024 | R13: 750 | S13: 750000 | T13: 1000 | U13: 0.022956841
D14: 4 | K14: =IFERROR(J14/H14,0) -> 0 | L14: =K14/43560 -> 0 | Q14: 2025 | R14: 250 | S14: 2500000 | T14: 10000 | U14: 0.22956841
D15: 5 | E15: Dave Smith | F15: 1 | G15: 1 | H15: 250 | I15: 46146 | J15: 2500000 | K15: =IFERROR(J15/H15,0) -> 10000 | L15: =K15/43560 -> 0.22956841 | Q15: Grand Total | R15: 1650 | S15: 9250000 | T15: 5606.0606 | U15: 0.12869744
D16: 6 | K16: =IFERROR(J16/H16,0) -> 0 | L16: =K16/43560 -> 0
D17: 7 | K17: =IFERROR(J17/H17,0) -> 0 | L17: =K17/43560 -> 0
D18: 8 | K18: =IFERROR(J18/H18,0) -> 0 | L18: =K18/43560 -> 0
D19: 9 | K19: =IFERROR(J19/H19,0) -> 0 | L19: =K19/43560 -> 0
D20: 10 | K20: =IFERROR(J20/H20,0) -> 0 | L20: =K20/43560 -> 0
E21: Total | H21: =SUM(H11:H20) -> 1650 | J21: =SUM(J11:J20) -> 16000000 | K21: =J21/H21 -> 9696.9697 | L21: =K21/43560 -> 0.22261179

Sheet iMPC
C7: Land Use Definitions | L7: Parcel Table - Village 1 | U7: Plan Area and Parcel Summary
H8: Density Range (DUA) | Q8: Potential DUs | X8: Potential DUs | AA8: Acres by Land Use
C9: ID | D9: Code | E9: Use | H9: From | I9: To | L9: ID | M9: Village | N9: Parcel | O9: Acres | P9: Use | Q9: Low | R9: High | U9: Plan Areas | V9: Parcels | W9: Acres | X9: Low | Y9: Hi | AA9: {=TRANSPOSE(lst_LUcodes)} -> MLDR | AB9: MDR | AC9: MHDR | AD9: MU | AE9: 0
C10: 1 | D10: MLDR | E10: Medium Low Residential | H10: 1 | I10: 2.9 | L10: 1 | M10: 1 | N10: =CONCATENATE(tbl_Parcels[[#This Row],[Village]],".",L10) -> 1.1 | O10: 31.73 | P10: MLDR | Q10: =INT(tbl_Parcels[[#This Row],[Acres]]*_xlfn.XLOOKUP(tbl_Parcels[[#This Row],[Use]],lst_LUcodes,$H$10:$H$14)) -> 31 | R10: =INT(tbl_Parcels[[#This Row],[Acres]]*_xlfn.XLOOKUP(tbl_Parcels[[#This Row],[Use]],lst_LUcodes,$I$10:$I$14)) -> 92 | U10: {=_xlfn.UNIQUE(tbl_Parcels[Village])} -> 1 | V10: =COUNTIF(tbl_Parcels[Village],U10) -> 15 | W10: =SUMIF(tbl_Parcels[Village],$U10,tbl_Parcels[Acres]) -> 379.51 | X10: =SUMIFS(tbl_Parcels[Low],tbl_Parcels[Village],$U10) -> 856 | Y10: =SUMIF(tbl_Parcels[Village],$U10,tbl_Parcels[High]) -> 1825 | AA10: =SUMIFS(tbl_Parcels[Acres],tbl_Parcels[Use],AA$9,tbl_Parcels[Village],$U10) -> 136.74 | AB10: =SUMIFS(tbl_Parcels[Acres],tbl_Parcels[Use],AB$9,tbl_Parcels[Village],$U10) -> 242.77 | AC10: =SUMIFS(tbl_Parcels[Acres],tbl_Parcels[Use],AC$9,tbl_Parcels[Village],$U10) -> 0 | AD10: =SUMIFS(tbl_Parcels[Acres],tbl_Parcels[Use],AD$9,tbl_Parcels[Village],$U10) -> 0 | AE10: =SUMIFS(tbl_Parcels[Acres],tbl_Parcels[Use],AE$9,tbl_Parcels[Village],$U10) -> 0
C11: 2 | D11: MDR | E11: Medium Density Residential | H11: 3 | I11: 5.9 | L11: 2 | M11: 1 | N11: =CONCATENATE(tbl_Parcels[[#This Row],[Village]],".",L11) -> 1.2 | O11: 20.83 | P11: MLDR | Q11: =INT(tbl_Parcels[[#This Row],[Acres]]*_xlfn.XLOOKUP(tbl_Parcels[[#This Row],[Use]],lst_LUcodes,$H$10:$H$14)) -> 20 | R11: =INT(tbl_Parcels[[#This Row],[Acres]]*_xlfn.XLOOKUP(tbl_Parcels[[#This Row],[Use]],lst_LUcodes,$I$10:$I$14)) -> 60 | U11: 2 | V11: =COUNTIF(tbl_Parcels[Village],U11) -> 7 | W11: =SUMIF(tbl_Parcels[Village],$U11,tbl_Parcels[Acres]) -> 223.3 | X11: =SUMIFS(tbl_Parcels[Low],tbl_Parcels[Village],$U11) -> 356 | Y11: =SUMIF(tbl_Parcels[Village],$U11,tbl_Parcels[High]) -> 712 | AA11: =SUMIFS(tbl_Parcels[Acres],tbl_Parcels[Use],AA$9,tbl_Parcels[Village],$U11) -> 0 | AB11: =SUMIFS(tbl_Parcels[Acres],tbl_Parcels[Use],AB$9,tbl_Parcels[Village],$U11) -> 0 | AC11: =SUMIFS(tbl_Parcels[Acres],tbl_Parcels[Use],AC$9,tbl_Parcels[Village],$U11) -> 59.41 | AD11: =SUMIFS(tbl_Parcels[Acres],tbl_Parcels[Use],AD$9,tbl_Parcels[Village],$U11) -> 163.89 | AE11: =SUMIFS(tbl_Parcels[Acres],tbl_Parcels[Use],AE$9,tbl_Parcels[Village],$U11) -> 0
C12: 3 | D12: MHDR | E12: Medium Hi Residential | H12: 6 | I12: 12 | L12: 3 | M12: 1 | N12: =CONCATENATE(tbl_Parcels[[#This Row],[Village]],".",L12) -> 1.3 | O12: 18.85 | P12: MDR | Q12: =INT(tbl_Parcels[[#This Row],[Acres]]*_xlfn.XLOOKUP(tbl_Parcels[[#This Row],[Use]],lst_LUcodes,$H$10:$H$14)) -> 56 | R12: =INT(tbl_Parcels[[#This Row],[Acres]]*_xlfn.XLOOKUP(tbl_Parcels[[#This Row],[Use]],lst_LUcodes,$I$10:$I$14)) -> 111 | U12: 3 | V12: =COUNTIF(tbl_Parcels[Village],U12) -> 12 | W12: =SUMIF(tbl_Parcels[Village],$U12,tbl_Parcels[Acres]) -> 328.16 | X12: =SUMIFS(tbl_Parcels[Low],tbl_Parcels[Village],$U12) -> 677 | Y12: =SUMIF(tbl_Parcels[Village],$U12,tbl_Parcels[High]) -> 1477 | AA12: =SUMIFS(tbl_Parcels[Acres],tbl_Parcels[Use],AA$9,tbl_Parcels[Village],$U12) -> 150.63 | AB12: =SUMIFS(tbl_Parcels[Acres],tbl_Parcels[Use],AB$9,tbl_Parcels[Village],$U12) -> 177.53 | AC12: =SUMIFS(tbl_Parcels[Acres],tbl_Parcels[Use],AC$9,tbl_Parcels[Village],$U12) -> 0 | AD12: =SUMIFS(tbl_Parcels[Acres],tbl_Parcels[Use],AD$9,tbl_Parcels[Village],$U12) -> 0 | AE12: =SUMIFS(tbl_Parcels[Acres],tbl_Parcels[Use],AE$9,tbl_Parcels[Village],$U12) -> 0
C13: 4 | D13: MU | E13: Mixed Use | L13: 4 | M13: 1 | N13: =CONCATENATE(tbl_Parcels[[#This Row],[Village]],".",L13) -> 1.4 | O13: 27.82 | P13: MDR | Q13: =INT(tbl_Parcels[[#This Row],[Acres]]*_xlfn.XLOOKUP(tbl_Parcels[[#This Row],[Use]],lst_LUcodes,$H$10:$H$14)) -> 83 | R13: =INT(tbl_Parcels[[#This Row],[Acres]]*_xlfn.XLOOKUP(tbl_Parcels[[#This Row],[Use]],lst_LUcodes,$I$10:$I$14)) -> 164 | U13: 4 | V13: =COUNTIF(tbl_Parcels[Village],U13) -> 14 | W13: =SUMIF(tbl_Parcels[Village],$U13,tbl_Parcels[Acres]) -> 389.03 | X13: =SUMIFS(tbl_Parcels[Low],tbl_Parcels[Village],$U13) -> 794 | Y13: =SUMIF(tbl_Parcels[Village],$U13,tbl_Parcels[High]) -> 1638 | AA13: =SUMIFS(tbl_Parcels[Acres],tbl_Parcels[Use],AA$9,tbl_Parcels[Village],$U13) -> 75.64 | AB13: =SUMIFS(tbl_Parcels[Acres],tbl_Parcels[Use],AB$9,tbl_Parcels[Village],$U13) -> 241.44 | AC13: =SUMIFS(tbl_Parcels[Acres],tbl_Parcels[Use],AC$9,tbl_Parcels[Village],$U13) -> 0 | AD13: =SUMIFS(tbl_Parcels[Acres],tbl_Parcels[Use],AD$9,tbl_Parcels[Village],$U13) -> 71.95 | AE13: =SUMIFS(tbl_Parcels[Acres],tbl_Parcels[Use],AE$9,tbl_Parcels[Village],$U13) -> 0
C14: 5 | L14: 5 | M14: 1 | N14: =CONCATENATE(tbl_Parcels[[#This Row],[Village]],".",L14) -> 1.5 | O14: 27.77 | P14: MLDR | Q14: =INT(tbl_Parcels[[#This Row],[Acres]]*_xlfn.XLOOKUP(tbl_Parcels[[#This Row],[Use]],lst_LUcodes,$H$10:$H$14)) -> 27 | R14: =INT(tbl_Parcels[[#This Row],[Acres]]*_xlfn.XLOOKUP(tbl_Parcels[[#This Row],[Use]],lst_LUcodes,$I$10:$I$14)) -> 80 | U14: Total | V14: =SUM(V10:V13) -> 48 | W14: =SUM(W10:W13) -> 1320 | X14: =SUM(X10:X13) -> 2683 | Y14: =SUM(Y10:Y13) -> 5652 | AA14: =SUM(AA10:AA13) -> 363.01 | AB14: =SUM(AB10:AB13) -> 661.74 | AC14: =SUM(AC10:AC13) -> 59.41 | AD14: =SUM(AD10:AD13) -> 235.84 | AE14: =SUM(AE10:AE13) -> 0
C15: 6 | L15: 6 | M15: 1 | N15: =CONCATENATE(tbl_Parcels[[#This Row],[Village]],".",L15) -> 1.6 | O15: 25.8 | P15: MDR | Q15: =INT(tbl_Parcels[[#This Row],[Acres]]*_xlfn.XLOOKUP(tbl_Parcels[[#This Row],[Use]],lst_LUcodes,$H$10:$H$14)) -> 77 | R15: =INT(tbl_Parcels[[#This Row],[Acres]]*_xlfn.XLOOKUP(tbl_Parcels[[#This Row],[Use]],lst_LUcodes,$I$10:$I$14)) -> 152
A16: =IF(tbl_Parcels[[#This Row],[Village]]=#REF!,A15+1,1) -> #REF! | C16: 7 | L16: 7 | M16: 1 | N16: =CONCATENATE(tbl_Parcels[[#This Row],[Village]],".",L16) -> 1.7 | O16: 19.53 | P16: MDR | Q16: =INT(tbl_Parcels[[#This Row],[Acres]]*_xlfn.XLOOKUP(tbl_Parcels[[#This Row],[Use]],lst_LUcodes,$H$10:$H$14)) -> 58 | R16: =INT(tbl_Parcels[[#This Row],[Acres]]*_xlfn.XLOOKUP(tbl_Parcels[[#This Row],[Use]],lst_LUcodes,$I$10:$I$14)) -> 115
A17: =IF(tbl_Parcels[[#This Row],[Village]]=#REF!,A16+1,1) -> #REF! | C17: 8 | L17: 8 | M17: 1 | N17: =CONCATENATE(tbl_Parcels[[#This Row],[Village]],".",L17) -> 1.8 | O17: 30.58 | P17: MDR | Q17: =INT(tbl_Parcels[[#This Row],[Acres]]*_xlfn.XLOOKUP(tbl_Parcels[[#This Row],[Use]],lst_LUcodes,$H$10:$H$14)) -> 91 | R17: =INT(tbl_Parcels[[#This Row],[Acres]]*_xlfn.XLOOKUP(tbl_Parcels[[#This Row],[Use]],lst_LUcodes,$I$10:$I$14)) -> 180
C18: 9 | L18: 9 | M18: 1 | N18: =CONCATENATE(tbl_Parcels[[#This Row],[Village]],".",L18) -> 1.9 | O18: 21.71 | P18: MDR | Q18: =INT(tbl_Parcels[[#This Row],[Acres]]*_xlfn.XLOOKUP(tbl_Parcels[[#This Row],[Use]],lst_LUcodes,$H$10:$H$14)) -> 65 | R18: =INT(tbl_Parcels[[#This Row],[Acres]]*_xlfn.XLOOKUP(tbl_Parcels[[#This Row],[Use]],lst_LUcodes,$I$10:$I$14)) -> 128
A19: =IF(tbl_Parcels[[#This Row],[Village]]=#REF!,#REF!+1,1) -> #REF! | C19: 10 | L19: 10 | M19: 1 | N19: =CONCATENATE(tbl_Parcels[[#This Row],[Village]],".",L19) -> 1.10 | O19: 22.39 | P19: MDR | Q19: =INT(tbl_Parcels[[#This Row],[Acres]]*_xlfn.XLOOKUP(tbl_Parcels[[#This Row],[Use]],lst_LUcodes,$H$10:$H$14)) -> 67 | R19: =INT(tbl_Parcels[[#This Row],[Acres]]*_xlfn.XLOOKUP(tbl_Parcels[[#This Row],[Use]],lst_LUcodes,$I$10:$I$14)) -> 132
A20: =IF(tbl_Parcels[[#This Row],[Village]]=M9,A19+1,1) -> 1 | L20: 11 | M20: 1 | N20: =CONCATENATE(tbl_Parcels[[#This Row],[Village]],".",L20) -> 1.11 | O20: 29.51 | P20: MLDR | Q20: =INT(tbl_Parcels[[#This Row],[Acres]]*_xlfn.XLOOKUP(tbl_Parcels[[#This Row],[Use]],lst_LUcodes,$H$10:$H$14)) -> 29 | R20: =INT(tbl_Parcels[[#This Row],[Acres]]*_xlfn.XLOOKUP(tbl_Parcels[[#This Row],[Use]],lst_LUcodes,$I$10:$I$14)) -> 85
A21: =IF(tbl_Parcels[[#This Row],[Village]]=M10,A20+1,1) -> 2 | L21: 12 | M21: 1 | N21: =CONCATENATE(tbl_Parcels[[#This Row],[Village]],".",L21) -> 1.12 | O21: 26.9 | P21: MLDR | Q21: =INT(tbl_Parcels[[#This Row],[Acres]]*_xlfn.XLOOKUP(tbl_Parcels[[#This Row],[Use]],lst_LUcodes,$H$10:$H$14)) -> 26 | R21: =INT(tbl_Parcels[[#This Row],[Acres]]*_xlfn.XLOOKUP(tbl_Parcels[[#This Row],[Use]],lst_LUcodes,$I$10:$I$14)) -> 78
A22: =IF(tbl_Parcels[[#This Row],[Village]]=M11,A21+1,1) -> 3 | L22: 13 | M22: 1 | N22: =CONCATENATE(tbl_Parcels[[#This Row],[Village]],".",L22) -> 1.13 | O22: 20.29 | P22: MDR | Q22: =INT(tbl_Parcels[[#This Row],[Acres]]*_xlfn.XLOOKUP(tbl_Parcels[[#This Row],[Use]],lst_LUcodes,$H$10:$H$14)) -> 60 | R22: =INT(tbl_Parcels[[#This Row],[Acres]]*_xlfn.XLOOKUP(tbl_Parcels[[#This Row],[Use]],lst_LUcodes,$I$10:$I$14)) -> 119
A23: =IF(tbl_Parcels[[#This Row],[Village]]=M12,A22+1,1) -> 4 | L23: 14 | M23: 1 | N23: =CONCATENATE(tbl_Parcels[[#This Row],[Village]],".",L23) -> 1.14 | O23: 21.53 | P23: MDR | Q23: =INT(tbl_Parcels[[#This Row],[Acres]]*_xlfn.XLOOKUP(tbl_Parcels[[#This Row],[Use]],lst_LUcodes,$H$10:$H$14)) -> 64 | R23: =INT(tbl_Parcels[[#This Row],[Acres]]*_xlfn.XLOOKUP(tbl_Parcels[[#This Row],[Use]],lst_LUcodes,$I$10:$I$14)) -> 127
A24: =IF(tbl_Parcels[[#This Row],[Village]]=M13,A23+1,1) -> 5 | L24: 15 | M24: 1 | N24: =CONCATENATE(tbl_Parcels[[#This Row],[Village]],".",L24) -> 1.15 | O24: 34.27 | P24: MDR | Q24: =INT(tbl_Parcels[[#This Row],[Acres]]*_xlfn.XLOOKUP(tbl_Parcels[[#This Row],[Use]],lst_LUcodes,$H$10:$H$14)) -> 102 | R24: =INT(tbl_Parcels[[#This Row],[Acres]]*_xlfn.XLOOKUP(tbl_Parcels[[#This Row],[Use]],lst_LUcodes,$I$10:$I$14)) -> 202
A25: =IF(tbl_Parcels[[#This Row],[Village]]=M14,A24+1,1) -> 1 | L25: 16 | M25: 2 | N25: =CONCATENATE(tbl_Parcels[[#This Row],[Village]],".",L25) -> 2.16 | O25: 31.85 | P25: MHDR | Q25: =INT(tbl_Parcels[[#This Row],[Acres]]*_xlfn.XLOOKUP(tbl_Parcels[[#This Row],[Use]],lst_LUcodes,$H$10:$H$14)) -> 191 | R25: =INT(tbl_Parcels[[#This Row],[Acres]]*_xlfn.XLOOKUP(tbl_Parcels[[#This Row],[Use]],lst_LUcodes,$I$10:$I$14)) -> 382
A26: =IF(tbl_Parcels[[#This Row],[Village]]=M15,A25+1,1) -> 1 | L26: 17 | M26: 2 | N26: =CONCATENATE(tbl_Parcels[[#This Row],[Village]],".",L26) -> 2.17 | O26: 31.04 | P26: MU | Q26: =INT(tbl_Parcels[[#This Row],[Acres]]*_xlfn.XLOOKUP(tbl_Parcels[[#This Row],[Use]],lst_LUcodes,$H$10:$H$14)) -> 0 | R26: =INT(tbl_Parcels[[#This Row],[Acres]]*_xlfn.XLOOKUP(tbl_Parcels[[#This Row],[Use]],lst_LUcodes,$I$10:$I$14)) -> 0
A27: =IF(tbl_Parcels[[#This Row],[Village]]=M16,A26+1,1) -> 1 | L27: 18 | M27: 2 | N27: =CONCATENATE(tbl_Parcels[[#This Row],[Village]],".",L27) -> 2.18 | O27: 27.56 | P27: MHDR | Q27: =INT(tbl_Parcels[[#This Row],[Acres]]*_xlfn.XLOOKUP(tbl_Parcels[[#This Row],[Use]],lst_LUcodes,$H$10:$H$14)) -> 165 | R27: =INT(tbl_Parcels[[#This Row],[Acres]]*_xlfn.XLOOKUP(tbl_Parcels[[#This Row],[Use]],lst_LUcodes,$I$10:$I$14)) -> 330
A28: =IF(tbl_Parcels[[#This Row],[Village]]=M17,A27+1,1) -> 1 | L28: 19 | M28: 2 | N28: =CONCATENATE(tbl_Parcels[[#This Row],[Village]],".",L28) -> 2.19 | O28: 21.86 | P28: MU | Q28: =INT(tbl_Parcels[[#This Row],[Acres]]*_xlfn.XLOOKUP(tbl_Parcels[[#This Row],[Use]],lst_LUcodes,$H$10:$H$14)) -> 0 | R28: =INT(tbl_Parcels[[#This Row],[Acres]]*_xlfn.XLOOKUP(tbl_Parcels[[#This Row],[Use]],lst_LUcodes,$I$10:$I$14)) -> 0
A29: =IF(tbl_Parcels[[#This Row],[Village]]=M18,A28+1,1) -> 1 | L29: 20 | M29: 2 | N29: =CONCATENATE(tbl_Parcels[[#This Row],[Village]],".",L29) -> 2.20 | O29: 35.51 | P29: MU | Q29: =INT(tbl_Parcels[[#This Row],[Acres]]*_xlfn.XLOOKUP(tbl_Parcels[[#This Row],[Use]],lst_LUcodes,$H$10:$H$14)) -> 0 | R29: =INT(tbl_Parcels[[#This Row],[Acres]]*_xlfn.XLOOKUP(tbl_Parcels[[#This Row],[Use]],lst_LUcodes,$I$10:$I$14)) -> 0
A30: =IF(tbl_Parcels[[#This Row],[Village]]=M19,A29+1,1) -> 1 | L30: 21 | M30: 2 | N30: =CONCATENATE(tbl_Parcels[[#This Row],[Village]],".",L30) -> 2.21 | O30: 43.89 | P30: MU | Q30: =INT(tbl_Parcels[[#This Row],[Acres]]*_xlfn.XLOOKUP(tbl_Parcels[[#This Row],[Use]],lst_LUcodes,$H$10:$H$14)) -> 0 | R30: =INT(tbl_Parcels[[#This Row],[Acres]]*_xlfn.XLOOKUP(tbl_Parcels[[#This Row],[Use]],lst_LUcodes,$I$10:$I$14)) -> 0
A31: =IF(tbl_Parcels[[#This Row],[Village]]=M20,A30+1,1) -> 1 | L31: 22 | M31: 2 | N31: =CONCATENATE(tbl_Parcels[[#This Row],[Village]],".",L31) -> 2.22 | O31: 31.59 | P31: MU | Q31: =INT(tbl_Parcels[[#This Row],[Acres]]*_xlfn.XLOOKUP(tbl_Parcels[[#This Row],[Use]],lst_LUcodes,$H$10:$H$14)) -> 0 | R31: =INT(tbl_Parcels[[#This Row],[Acres]]*_xlfn.XLOOKUP(tbl_Parcels[[#This Row],[Use]],lst_LUcodes,$I$10:$I$14)) -> 0
... A57: =IF(tbl_Parcels[[#This Row],[Village]]=M46,A56+1,1) -> 4 | L57: 48 | M57: 4 | N57: =CONCATENATE(tbl_Parcels[[#This Row],[Village]],".",L57) -> 4.48 | O57: 14.47 | P57: MU | Q57: =INT(tbl_Parcels[[#This Row],[Acres]]*_xlfn.XLOOKUP(tbl_Parcels[[#This Row],[Use]],lst_LUcodes,$H$10:$H$14)) -> 0 | R57: =INT(tbl_Parcels[[#This Row],[Acres]]*_xlfn.XLOOKUP(tbl_Parcels[[#This Row],[Use]],lst_LUcodes,$I$10:$I$14)) -> 0
A58: =IF(tbl_Parcels[[#This Row],[Village]]=M47,A57+1,1) -> #VALUE!
A59: =IF(tbl_Parcels[[#This Row],[Village]]=M48,A58+1,1) -> #VALUE!
A60: =IF(tbl_Parcels[[#This Row],[Village]]=M49,A59+1,1) -> #VALUE!
A61: =IF(tbl_Parcels[[#This Row],[Village]]=M50,A60+1,1) -> #VALUE!
A62: =IF(tbl_Parcels[[#This Row],[Village]]=M51,A61+1,1) -> #VALUE!
A63: =IF(tbl_Parcels[[#This Row],[Village]]=M52,A62+1,1) -> #VALUE!
A64: =IF(tbl_Parcels[[#This Row],[Village]]=M53,A63+1,1) -> #VALUE!
A65: =IF(tbl_Parcels[[#This Row],[Village]]=M54,A64+1,1) -> #VALUE!
A66: 47
A67: 48

Sheet iV1
C4: 1 | F4: Parcel Land Use & Lot Product | N4: 1 | P4: Development Phasing | Y4: =C4 -> 1 | AA4: Sale Schedule
N5: Village 4 | P5: 1 | Q5: =P5+1 -> 2 | R5: =Q5+1 -> 3 | S5: =R5+1 -> 4 | X5: Lag to Development Completion
J6: Dev | AB6: Front | AC6: Development | AE6: Sale | AF6: Retail | AG6: Subdivision | AH6: Gross Parcel | AI6: Sale | AJ6: =AF6 -> Retail
C7: ID | D7: Parcel# | E7: Use | F7: Acres | G7: DUA | H7: Product | I7: Units | J7: Phase | N7: Start Month | P7: 6 | Q7: 30 | X7: # | Y7: Parcel | Z7: Lots | AA7: Product | AB7: Feet | AC7: Phase | AD7: Compl | AE7: Date | AF7: Price | AG7: Improvement | AH7: Revenue | AI7: Cost | AJ7: NET
C8: 1 | D8: {=_xlfn._xlws.FILTER(tbl_Parcels[Parcel],tbl_Parcels[Village]=C4,0)} -> 1.1 | E8: =IFERROR(_xlfn.XLOOKUP(D8,tbl_Parcels[Parcel],tbl_Parcels[Use]),0) -> MLDR | F8: =IFERROR(_xlfn.XLOOKUP(D8,tbl_Parcels[Parcel],tbl_Parcels[Acres]),0) -> 31.73 | G8: =LOOKUP('iV1'!$H8,Table4[Product],Table4[DUA]) -> 3.4485 | H8: 60x120 | I8: =IFERROR(INT(LOOKUP('iV1'!$H8,lst_LotProducts,lst_ProductDUA)*'iV1'!$F8),0) -> 109 | J8: 1 | N8: Months to Complete | P8: 12 | Q8: 8 | X8: 1 | Y8: {=_xlfn.UNIQUE(_xlfn._xlws.FILTER(D8:D32,D8:D32<>0))} -> 1.1 | Z8: =IFERROR(LOOKUP(Y8,$D$8:$D$32,$I$8:$I$32),0) -> 109 | AA8: =IFERROR(_xlfn.XLOOKUP($Y8,$D$8:$D$32,$H$8:$H$32),0) -> 60x120 | AB8: =IFERROR(Z8*LOOKUP(AA8,Table4[Product],Table4[Width]),0) -> 6540 | AC8: =IFERROR(_xlfn.XLOOKUP($Y8,$D$8:$D$32,$J$8:$J$32),0) -> 1 | AD8: =IFERROR(_xlfn.XLOOKUP(LOOKUP(AC8,$P$5:$S$5,$P$9:$S$9)+1,DATA!$E$11:$E$370,DATA!$F$11:$F$370),"") -> 45078 | AE8: 45108 | AF8: =IFERROR($AB8*(iGeneral!$F$52*LOOKUP($AE8,DATA!$F$11:$F$370,DATA!$L$11:$L$370)),0) -> 13478009 | AG8: =-IFERROR($AB8*(i_Cost.Subd*LOOKUP($AE8,DATA!$F$11:$F$370,DATA!$L$11:$L$370)),0) -> -8760705.7 | AH8: =AF8+AG8 -> 4717303.1
C9: 2 | D9: 1.2 | E9: =IFERROR(_xlfn.XLOOKUP(D9,tbl_Parcels[Parcel],tbl_Parcels[Use]),0) -> MLDR | F9: =IFERROR(_xlfn.XLOOKUP(D9,tbl_Parcels[Parcel],tbl_Parcels[Acres]),0) -> 20.83 | G9: =LOOKUP('iV1'!$H9,Table4[Product],Table4[DUA]) -> 3.31056 | H9: 60x125 | I9: =IFERROR(INT(LOOKUP('iV1'!$H9,lst_LotProducts,lst_ProductDUA)*'iV1'!$F9),0) -> 68 | J9: 1 | N9: Thru Month | P9: =P7+P8-1 -> 17 | Q9: =Q7+Q8-1 -> 37 | X9: =X8+1 -> 2 | Y9: 1.2 | Z9: =IFERROR(LOOKUP(Y9,$D$8:$D$32,$I$8:$I$32),0) -> 147 | AA9: =IFERROR(_xlfn.XLOOKUP($Y9,$D$8:$D$32,$H$8:$H$32),0) -> 60x125 | AB9: =IFERROR(Z9*LOOKUP(AA9,Table4[Product],Table4[Width]),0) -> 8820 | AC9: =IFERROR(_xlfn.XLOOKUP($Y9,$D$8:$D$32,$J$8:$J$32),0) -> 1 | AD9: =IFERROR(_xlfn.XLOOKUP(LOOKUP(AC9,$P$5:$S$5,$P$9:$S$9)+1,DATA!$E$11:$E$370,DATA!$F$11:$F$370),"") -> 45078 | AE9: 45108 | AF9: =IFERROR($AB9*(iGeneral!$F$52*LOOKUP($AE9,DATA!$F$11:$F$370,DATA!$L$11:$L$370)),0) -> 18176764 | AG9: =-IFERROR($AB9*(i_Cost.Subd*LOOKUP($AE9,DATA!$F$11:$F$370,DATA!$L$11:$L$370)),0) -> -11814897 | AH9: =AF9+AG9 -> 6361867.4
C10: 3 | D10: 1.3 | E10: =IFERROR(_xlfn.XLOOKUP(D10,tbl_Parcels[Parcel],tbl_Parcels[Use]),0) -> MDR | F10: =IFERROR(_xlfn.XLOOKUP(D10,tbl_Parcels[Parcel],tbl_Parcels[Acres]),0) -> 18.85 | G10: =LOOKUP('iV1'!$H10,Table4[Product],Table4[DUA]) -> 5.016 | H10: 45x110 | I10: =IFERROR(INT(LOOKUP('iV1'!$H10,lst_LotProducts,lst_ProductDUA)*'iV1'!$F10),0) -> 94 | J10: 1 | T10: Total | X10: =X9+1 -> 3 | Y10: 1.3 | Z10: =IFERROR(LOOKUP(Y10,$D$8:$D$32,$I$8:$I$32),0) -> 147 | AA10: =IFERROR(_xlfn.XLOOKUP($Y10,$D$8:$D$32,$H$8:$H$32),0) -> 45x110 | AB10: =IFERROR(Z10*LOOKUP(AA10,Table4[Product],Table4[Width]),0) -> 6615 | AC10: =IFERROR(_xlfn.XLOOKUP($Y10,$D$8:$D$32,$J$8:$J$32),0) -> 1 | AD10: =IFERROR(_xlfn.XLOOKUP(LOOKUP(AC10,$P$5:$S$5,$P$9:$S$9)+1,DATA!$E$11:$E$370,DATA!$F$11:$F$370),"") -> 45078 | AE10: 45108 | AF10: =IFERROR($AB10*(iGeneral!$F$52*LOOKUP($AE10,DATA!$F$11:$F$370,DATA!$L$11:$L$370)),0) -> 13632573 | AG10: =-IFERROR($AB10*(i_Cost.Subd*LOOKUP($AE10,DATA!$F$11:$F$370,DATA!$L$11:$L$370)),0) -> -8861172.5 | AH10: =AF10+AG10 -> 4771400.6
C11: 4 | D11: 1.4 | E11: =IFERROR(_xlfn.XLOOKUP(D11,tbl_Parcels[Parcel],tbl_Parcels[Use]),0) -> MDR | F11: =IFERROR(_xlfn.XLOOKUP(D11,tbl_Parcels[Parcel],tbl_Parcels[Acres]),0) -> 27.82 | G11: =LOOKUP('iV1'!$H11,Table4[Product],Table4[DUA]) -> 5.016 | H11: 45x110 | I11: =IFERROR(INT(LOOKUP('iV1'!$H11,lst_LotProducts,lst_ProductDUA)*'iV1'!$F11),0) -> 139 | J11: 1 | N11: Acqusition | O11: a | P11: 0 | Q11: 0 | T11: =P11+Q11+R11+S11 -> 0 | V11: insert summary | X11: =X10+1 -> 4 | Y11: 1.4 | Z11: =IFERROR(LOOKUP(Y11,$D$8:$D$32,$I$8:$I$32),0) -> 147 | AA11: =IFERROR(_xlfn.XLOOKUP($Y11,$D$8:$D$32,$H$8:$H$32),0) -> 45x110 | AB11: =IFERROR(Z11*LOOKUP(AA11,Table4[Product],Table4[Width]),0) -> 6615 | AC11: =IFERROR(_xlfn.XLOOKUP($Y11,$D$8:$D$32,$J$8:$J$32),0) -> 1 | AD11: =IFERROR(_xlfn.XLOOKUP(LOOKUP(AC11,$P$5:$S$5,$P$9:$S$9)+1,DATA!$E$11:$E$370,DATA!$F$11:$F$370),"") -> 45078 | AE11: 45231 | AF11: =IFERROR($AB11*(iGeneral!$F$52*LOOKUP($AE11,DATA!$F$11:$F$370,DATA!$L$11:$L$370)),0) -> 13723684 | AG11: =-IFERROR($AB11*(i_Cost.Subd*LOOKUP($AE11,DATA!$F$11:$F$370,DATA!$L$11:$L$370)),0) -> -8920394.8 | AH11: =AF11+AG11 -> 4803289.5
C12: 5 | D12: 1.5 | E12: =IFERROR(_xlfn.XLOOKUP(D12,tbl_Parcels[Parcel],tbl_Parcels[Use]),0) -> MLDR | F12: =IFERROR(_xlfn.XLOOKUP(D12,tbl_Parcels[Parcel],tbl_Parcels[Acres]),0) -> 27.77 | G12: =LOOKUP('iV1'!$H12,Table4[Product],Table4[DUA]) -> 3.31056 | H12: 60x125 | I12: =IFERROR(INT(LOOKUP('iV1'!$H12,lst_LotProducts,lst_ProductDUA)*'iV1'!$F12),0) -> 91 | J12: 1 | L12: insert summary | N12: Entitlements | P12: 500000 | Q12: 100000 | T12: =P12+Q12+R12+S12 -> 600000 | V12: or charts here | X12: =X11+1 -> 5 | Y12: 1.5 | Z12: =IFERROR(LOOKUP(Y12,$D$8:$D$32,$I$8:$I$32),0) -> 147 | AA12: =IFERROR(_xlfn.XLOOKUP($Y12,$D$8:$D$32,$H$8:$H$32),0) -> 60x125 | AB12: =IFERROR(Z12*LOOKUP(AA12,Table4[Product],Table4[Width]),0) -> 8820 | AC12: =IFERROR(_xlfn.XLOOKUP($Y12,$D$8:$D$32,$J$8:$J$32),0) -> 1 | AD12: =IFERROR(_xlfn.XLOOKUP(LOOKUP(AC12,$P$5:$S$5,$P$9:$S$9)+1,DATA!$E$11:$E$370,DATA!$F$11:$F$370),"") -> 45078 | AE12: 45231 | AF12: =IFERROR($AB12*(iGeneral!$F$52*LOOKUP($AE12,DATA!$F$11:$F$370,DATA!$L$11:$L$370)),0) -> 18298246 | AG12: =-IFERROR($AB12*(i_Cost.Subd*LOOKUP($AE12,DATA!$F$11:$F$370,DATA!$L$11:$L$370)),0) -> -11893860 | AH12: =AF12+AG12 -> 6404386
C13: 6 | D13: 1.6 | E13: =IFERROR(_xlfn.XLOOKUP(D13,tbl_Parcels[Parcel],tbl_Parcels[Use]),0) -> MDR | F13: =IFERROR(_xlfn.XLOOKUP(D13,tbl_Parcels[Parcel],tbl_Parcels[Acres]),0) -> 25.8 | G13: =LOOKUP('iV1'!$H13,Table4[Product],Table4[DUA]) -> 3.972672 | H13: 50x125 | I13: =IFERROR(INT(LOOKUP('iV1'!$H13,lst_LotProducts,lst_ProductDUA)*'iV1'!$F13),0) -> 102 | J13: 1 | L13: or charts here | N13: Engineering | P13: 2500000 | Q13: 500000 | T13: =P13+Q13+R13+S13 -> 3000000 | X13: =X12+1 -> 6 | Y13: 1.6 | Z13: =IFERROR(LOOKUP(Y13,$D$8:$D$32,$I$8:$I$32),0) -> 147 | AA13: =IFERROR(_xlfn.XLOOKUP($Y13,$D$8:$D$32,$H$8:$H$32),0) -> 50x125 | AB13: =IFERROR(Z13*LOOKUP(AA13,Table4[Product],Table4[Width]),0) -> 7350 | AC13: =IFERROR(_xlfn.XLOOKUP($Y13,$D$8:$D$32,$J$8:$J$32),0) -> 1 | AD13: =IFERROR(_xlfn.XLOOKUP(LOOKUP(AC13,$P$5:$S$5,$P$9:$S$9)+1,DATA!$E$11:$E$370,DATA!$F$11:$F$370),"") -> 45078 | AE13: 45231 | AF13: =IFERROR($AB13*(iGeneral!$F$52*LOOKUP($AE13,DATA!$F$11:$F$370,DATA!$L$11:$L$370)),0) -> 15248538 | AG13: =-IFERROR($AB13*(i_Cost.Subd*LOOKUP($AE13,DATA!$F$11:$F$370,DATA!$L$11:$L$370)),0) -> -9911549.8 | AH13: =AF13+AG13 -> 5336988.3
C14: 7 | D14: 1.7 | E14: =IFERROR(_xlfn.XLOOKUP(D14,tbl_Parcels[Parcel],tbl_Parcels[Use]),0) -> MDR | F14: =IFERROR(_xlfn.XLOOKUP(D14,tbl_Parcels[Parcel],tbl_Parcels[Acres]),0) -> 19.53 | G14: =LOOKUP('iV1'!$H14,Table4[Product],Table4[DUA]) -> 4.598 | H14: 45x120 | I14: =IFERROR(INT(LOOKUP('iV1'!$H14,lst_LotProducts,lst_ProductDUA)*'iV1'!$F14),0) -> 89 | J14: 1 | N14: Development > Offsite | P14: 2500000 | Q14: 0 | T14: =P14+Q14+R14+S14 -> 2500000 | X14: =X13+1 -> 7 | Y14: 1.7 | Z14: =IFERROR(LOOKUP(Y14,$D$8:$D$32,$I$8:$I$32),0) -> 147 | AA14: =IFERROR(_xlfn.XLOOKUP($Y14,$D$8:$D$32,$H$8:$H$32),0) -> 45x120 | AB14: =IFERROR(Z14*LOOKUP(AA14,Table4[Product],Table4[Width]),0) -> 6615 | AC14: =IFERROR(_xlfn.XLOOKUP($Y14,$D$8:$D$32,$J$8:$J$32),0) -> 1 | AD14: =IFERROR(_xlfn.XLOOKUP(LOOKUP(AC14,$P$5:$S$5,$P$9:$S$9)+1,DATA!$E$11:$E$370,DATA!$F$11:$F$370),"") -> 45078 | AE14: 45231 | AF14: =IFERROR($AB14*(iGeneral!$F$52*LOOKUP($AE14,DATA!$F$11:$F$370,DATA!$L$11:$L$370)),0) -> 13723684 | AG14: =-IFERROR($AB14*(i_Cost.Subd*LOOKUP($AE14,DATA!$F$11:$F$370,DATA!$L$11:$L$370)),0) -> -8920394.8 | AH14: =AF14+AG14 -> 4803289.5
C15: 8 | D15: 1.8 | E15: =IFERROR(_xlfn.XLOOKUP(D15,tbl_Parcels[Parcel],tbl_Parcels[Use]),0) -> MDR | F15: =IFERROR(_xlfn.XLOOKUP(D15,tbl_Parcels[Parcel],tbl_Parcels[Acres]),0) -> 30.58 | G15: =LOOKUP('iV1'!$H15,Table4[Product],Table4[DUA]) -> 4.797913 | H15: 45x115 | I15: =IFERROR(INT(LOOKUP('iV1'!$H15,lst_LotProducts,lst_ProductDUA)*'iV1'!$F15),0) -> 146 | J15: 1 | N15: Development > OnSite | P15: 5000000 | Q15: 3000000 | T15: =P15+Q15+R15+S15 -> 8000000 | X15: =X14+1 -> 8 | Y15: 1.8 | Z15: =IFERROR(LOOKUP(Y15,$D$8:$D$32,$I$8:$I$32),0) -> 147 | AA15: =IFERROR(_xlfn.XLOOKUP($Y15,$D$8:$D$32,$H$8:$H$32),0) -> 45x115 | AB15: =IFERROR(Z15*LOOKUP(AA15,Table4[Product],Table4[Width]),0) -> 6615 | AC15: =IFERROR(_xlfn.XLOOKUP($Y15,$D$8:$D$32,$J$8:$J$32),0) -> 1 | AD15: =IFERROR(_xlfn.XLOOKUP(LOOKUP(AC15,$P$5:$S$5,$P$9:$S$9)+1,DATA!$E$11:$E$370,DATA!$F$11:$F$370),"") -> 45078 | AE15: 45231 | AF15: =IFERROR($AB15*(iGeneral!$F$52*LOOKUP($AE15,DATA!$F$11:$F$370,DATA!$L$11:$L$370)),0) -> 13723684 | AG15: =-IFERROR($AB15*(i_Cost.Subd*LOOKUP($AE15,DATA!$F$11:$F$370,DATA!$L$11:$L$370)),0) -> -8920394.8 | AH15: =AF15+AG15 -> 4803289.5
C16: 9 | D16: 1.9 | E16: =IFERROR(_xlfn.XLOOKUP(D16,tbl_Parcels[Parcel],tbl_Parcels[Use]),0) -> MDR | F16: =IFERROR(_xlfn.XLOOKUP(D16,tbl_Parcels[Parcel],tbl_Parcels[Acres]),0) -> 21.71 | G16: =LOOKUP('iV1'!$H16,Table4[Product],Table4[DUA]) -> 4.5144 | H16: 50x110 | I16: =IFERROR(INT(LOOKUP('iV1'!$H16,lst_LotProducts,lst_ProductDUA)*'iV1'!$F16),0) -> 98 | J16: 2 | N16: Development > Subdivision | P16: 0 | Q16: 15000000 | T16: =P16+Q16+R16+S16 -> 15000000 | X16: =X15+1 -> 9 | Y16: 1.9 | Z16: =IFERROR(LOOKUP(Y16,$D$8:$D$32,$I$8:$I$32),0) -> 147 | AA16: =IFERROR(_xlfn.XLOOKUP($Y16,$D$8:$D$32,$H$8:$H$32),0) -> 50x110 | AB16: =IFERROR(Z16*LOOKUP(AA16,Table4[Product],Table4[Width]),0) -> 7350 | AC16: =IFERROR(_xlfn.XLOOKUP($Y16,$D$8:$D$32,$J$8:$J$32),0) -> 2 | AD16: =IFERROR(_xlfn.XLOOKUP(LOOKUP(AC16,$P$5:$S$5,$P$9:$S$9)+1,DATA!$E$11:$E$370,DATA!$F$11:$F$370),"") -> 45689 | AE16: 45717 | AF16: =IFERROR($AB16*(iGeneral!$F$52*LOOKUP($AE16,DATA!$F$11:$F$370,DATA!$L$11:$L$370)),0) -> 15660288 | AG16: =-IFERROR($AB16*(i_Cost.Subd*LOOKUP($AE16,DATA!$F$11:$F$370,DATA!$L$11:$L$370)),0) -> -10179187 | AH16: =AF16+AG16 -> 5481100.9
C17: 10 | D17: 1.10 | E17: =IFERROR(_xlfn.XLOOKUP(D17,tbl_Parcels[Parcel],tbl_Parcels[Use]),0) -> MDR | F17: =IFERROR(_xlfn.XLOOKUP(D17,tbl_Parcels[Parcel],tbl_Parcels[Acres]),0) -> 22.39 | G17: =LOOKUP('iV1'!$H17,Table4[Product],Table4[DUA]) -> 4.797913 | H17: 45x115 | I17: =IFERROR(INT(LOOKUP('iV1'!$H17,lst_LotProducts,lst_ProductDUA)*'iV1'!$F17),0) -> 107 | J17: 2 | N17: Development > Other | P17: 2500000 | Q17: 1000000 | T17: =P17+Q17+R17+S17 -> 3500000 | X17: =X16+1 -> 10 | Y17: 1.10 | Z17: =IFERROR(LOOKUP(Y17,$D$8:$D$32,$I$8:$I$32),0) -> 109 | AA17: =IFERROR(_xlfn.XLOOKUP($Y17,$D$8:$D$32,$H$8:$H$32),0) -> 45x115 | AB17: =IFERROR(Z17*LOOKUP(AA17,Table4[Product],Table4[Width]),0) -> 4905 | AC17: =IFERROR(_xlfn.XLOOKUP($Y17,$D$8:$D$32,$J$8:$J$32),0) -> 2 | AD17: =IFERROR(_xlfn.XLOOKUP(LOOKUP(AC17,$P$5:$S$5,$P$9:$S$9)+1,DATA!$E$11:$E$370,DATA!$F$11:$F$370),"") -> 45689 | AE17: 45717 | AF17: =IFERROR($AB17*(iGeneral!$F$52*LOOKUP($AE17,DATA!$F$11:$F$370,DATA!$L$11:$L$370)),0) -> 10450846 | AG17: =-IFERROR($AB17*(i_Cost.Subd*LOOKUP($AE17,DATA!$F$11:$F$370,DATA!$L$11:$L$370)),0) -> -6793049.6 | AH17: =AF17+AG17 -> 3657795.9
C18: 11 | D18: 1.11 | E18: =IFERROR(_xlfn.XLOOKUP(D18,tbl_Parcels[Parcel],tbl_Parcels[Use]),0) -> MLDR | F18: =IFERROR(_xlfn.XLOOKUP(D18,tbl_Parcels[Parcel],tbl_Parcels[Acres]),0) -> 29.51 | G18: =LOOKUP('iV1'!$H18,Table4[Product],Table4[DUA]) -> 2.7284835 | H18: 70x130 | I18: =IFERROR(INT(LOOKUP('iV1'!$H18,lst_LotProducts,lst_ProductDUA)*'iV1'!$F18),0) -> 80 | J18: 2 | N18: Other | P18: 0 | Q18: 0 | R18: 0 | S18: 0 | T18: =P18+Q18+R18+S18 -> 0 | X18: =X17+1 -> 11 | Y18: 1.11 | Z18: =IFERROR(LOOKUP(Y18,$D$8:$D$32,$I$8:$I$32),0) -> 109 | AA18: =IFERROR(_xlfn.XLOOKUP($Y18,$D$8:$D$32,$H$8:$H$32),0) -> 70x130 | AB18: =IFERROR(Z18*LOOKUP(AA18,Table4[Product],Table4[Width]),0) -> 7630 | AC18: =IFERROR(_xlfn.XLOOKUP($Y18,$D$8:$D$32,$J$8:$J$32),0) -> 2 | AD18: =IFERROR(_xlfn.XLOOKUP(LOOKUP(AC18,$P$5:$S$5,$P$9:$S$9)+1,DATA!$E$11:$E$370,DATA!$F$11:$F$370),"") -> 45689 | AE18: 45717 | AF18: =IFERROR($AB18*(iGeneral!$F$52*LOOKUP($AE18,DATA!$F$11:$F$370,DATA!$L$11:$L$370)),0) -> 16256871 | AG18: =-IFERROR($AB18*(i_Cost.Subd*LOOKUP($AE18,DATA!$F$11:$F$370,DATA!$L$11:$L$370)),0) -> -10566966 | AH18: =AF18+AG18 -> 5689904.8
C19: 12 | D19: 1.12 | E19: =IFERROR(_xlfn.XLOOKUP(D19,tbl_Parcels[Parcel],tbl_Parcels[Use]),0) -> MLDR | F19: =IFERROR(_xlfn.XLOOKUP(D19,tbl_Parcels[Parcel],tbl_Parcels[Acres]),0) -> 26.9 | G19: =LOOKUP('iV1'!$H19,Table4[Product],Table4[DUA]) -> 3.1832308 | H19: 65x120 | I19: =IFERROR(INT(LOOKUP('iV1'!$H19,lst_LotProducts,lst_ProductDUA)*'iV1'!$F19),0) -> 85 | J19: 2 | P19: 0 | Q19: 0 | R19: 0 | S19: 0 | T19: =P19+Q19+R19+S19 -> 0 | X19: =X18+1 -> 12 | Y19: 1.12 | Z19: =IFERROR(LOOKUP(Y19,$D$8:$D$32,$I$8:$I$32),0) -> 109 | AA19: =IFERROR(_xlfn.XLOOKUP($Y19,$D$8:$D$32,$H$8:$H$32),0) -> 65x120 | AB19: =IFERROR(Z19*LOOKUP(AA19,Table4[Product],Table4[Width]),0) -> 7085 | AC19: =IFERROR(_xlfn.XLOOKUP($Y19,$D$8:$D$32,$J$8:$J$32),0) -> 2 | AD19: =IFERROR(_xlfn.XLOOKUP(LOOKUP(AC19,$P$5:$S$5,$P$9:$S$9)+1,DATA!$E$11:$E$370,DATA!$F$11:$F$370),"") -> 45689 | AE19: 45717 | AF19: =IFERROR($AB19*(iGeneral!$F$52*LOOKUP($AE19,DATA!$F$11:$F$370,DATA!$L$11:$L$370)),0) -> 15095666 | AG19: =-IFERROR($AB19*(i_Cost.Subd*LOOKUP($AE19,DATA!$F$11:$F$370,DATA!$L$11:$L$370)),0) -> -9812182.8 | AH19: =AF19+AG19 -> 5283483
C20: 13 | D20: 1.13 | E20: =IFERROR(_xlfn.XLOOKUP(D20,tbl_Parcels[Parcel],tbl_Parcels[Use]),0) -> MDR | F20: =IFERROR(_xlfn.XLOOKUP(D20,tbl_Parcels[Parcel],tbl_Parcels[Acres]),0) -> 20.29 | G20: =LOOKUP('iV1'!$H20,Table4[Product],Table4[DUA]) -> 4.797913 | H20: 45x115 | I20: =IFERROR(INT(LOOKUP('iV1'!$H20,lst_LotProducts,lst_ProductDUA)*'iV1'!$F20),0) -> 97 | J20: 2 | P20: 0 | Q20: 0 | R20: 0 | S20: 0 | T20: =P20+Q20+R20+S20 -> 0 | X20: =X19+1 -> 13 | Y20: 1.13 | Z20: =IFERROR(LOOKUP(Y20,$D$8:$D$32,$I$8:$I$32),0) -> 97 | AA20: =IFERROR(_xlfn.XLOOKUP($Y20,$D$8:$D$32,$H$8:$H$32),0) -> 45x115 | AB20: =IFERROR(Z20*LOOKUP(AA20,Table4[Product],Table4[Width]),0) -> 4365 | AC20: =IFERROR(_xlfn.XLOOKUP($Y20,$D$8:$D$32,$J$8:$J$32),0) -> 2 | AD20: =IFERROR(_xlfn.XLOOKUP(LOOKUP(AC20,$P$5:$S$5,$P$9:$S$9)+1,DATA!$E$11:$E$370,DATA!$F$11:$F$370),"") -> 45689 | AE20: 45992 | AF20: =IFERROR($AB20*(iGeneral!$F$52*LOOKUP($AE20,DATA!$F$11:$F$370,DATA!$L$11:$L$370)),0) -> 9440731.8 | AG20: =-IFERROR($AB20*(i_Cost.Subd*LOOKUP($AE20,DATA!$F$11:$F$370,DATA!$L$11:$L$370)),0) -> -6136475.7 | AH20: =AF20+AG20 -> 3304256.1
C21: 14 | D21: 1.14 | E21: =IFERROR(_xlfn.XLOOKUP(D21,tbl_Parcels[Parcel],tbl_Parcels[Use]),0) -> MDR | F21: =IFERROR(_xlfn.XLOOKUP(D21,tbl_Parcels[Parcel],tbl_Parcels[Acres]),0) -> 21.53 | G21: =LOOKUP('iV1'!$H21,Table4[Product],Table4[DUA]) -> 5.016 | H21: 45x110 | I21: =IFERROR(INT(LOOKUP('iV1'!$H21,lst_LotProducts,lst_ProductDUA)*'iV1'!$F21),0) -> 107 | J21: 2 | P21: 0 | Q21: 0 | R21: 0 | S21: 0 | T21: =P21+Q21+R21+S21 -> 0 | X21: =X20+1 -> 14 | Y21: 1.14 | Z21: =IFERROR(LOOKUP(Y21,$D$8:$D$32,$I$8:$I$32),0) -> 107 | AA21: =IFERROR(_xlfn.XLOOKUP($Y21,$D$8:$D$32,$H$8:$H$32),0) -> 45x110 | AB21: =IFERROR(Z21*LOOKUP(AA21,Table4[Product],Table4[Width]),0) -> 4815 | AC21: =IFERROR(_xlfn.XLOOKUP($Y21,$D$8:$D$32,$J$8:$J$32),0) -> 2 | AD21: =IFERROR(_xlfn.XLOOKUP(LOOKUP(AC21,$P$5:$S$5,$P$9:$S$9)+1,DATA!$E$11:$E$370,DATA!$F$11:$F$370),"") -> 45689 | AE21: =AE20 -> 45992 | AF21: =IFERROR($AB21*(iGeneral!$F$52*LOOKUP($AE21,DATA!$F$11:$F$370,DATA!$L$11:$L$370)),0) -> 10414003 | AG21: =-IFERROR($AB21*(i_Cost.Subd*LOOKUP($AE21,DATA!$F$11:$F$370,DATA!$L$11:$L$370)),0) -> -6769102 | AH21: =AF21+AG21 -> 3644901.1
C22: 15 | D22: 1.15 | E22: =IFERROR(_xlfn.XLOOKUP(D22,tbl_Parcels[Parcel],tbl_Parcels[Use]),0) -> MDR | F22: =IFERROR(_xlfn.XLOOKUP(D22,tbl_Parcels[Parcel],tbl_Parcels[Acres]),0) -> 34.27 | G22: =IFERROR(LOOKUP('iV1'!$H22,Table4[Product],Table4[DUA]),0) -> 4.3181217 | H22: 50x115 | I22: =IFERROR(INT(LOOKUP('iV1'!$H22,lst_LotProducts,lst_ProductDUA)*'iV1'!$F22),0) -> 147 | J22: 2 | P22: 0 | Q22: 0 | R22: 0 | S22: 0 | T22: =P22+Q22+R22+S22 -> 0 | X22: =X21+1 -> 15 | Y22: 1.15 | Z22: =IFERROR(LOOKUP(Y22,$D$8:$D$32,$I$8:$I$32),0) -> 147 | AA22: =IFERROR(_xlfn.XLOOKUP($Y22,$D$8:$D$32,$H$8:$H$32),0) -> 50x115 | AB22: =IFERROR(Z22*LOOKUP(AA22,Table4[Product],Table4[Width]),0) -> 7350 | AC22: =IFERROR(_xlfn.XLOOKUP($Y22,$D$8:$D$32,$J$8:$J$32),0) -> 2 | AD22: =IFERROR(_xlfn.XLOOKUP(LOOKUP(AC22,$P$5:$S$5,$P$9:$S$9)+1,DATA!$E$11:$E$370,DATA!$F$11:$F$370),"") -> 45689 | AE22: =AE21 -> 45992 | AF22: =IFERROR($AB22*(iGeneral!$F$52*LOOKUP($AE22,DATA!$F$11:$F$370,DATA!$L$11:$L$370)),0) -> 15896765 | AG22: =-IFERROR($AB22*(i_Cost.Subd*LOOKUP($AE22,DATA!$F$11:$F$370,DATA!$L$11:$L$370)),0) -> -10332897 | AH22: =AF22+AG22 -> 5563867.7
C23: 16 | E23: =IFERROR(_xlfn.XLOOKUP(D23,tbl_Parcels[Parcel],tbl_Parcels[Use]),0) -> 0 | F23: =IFERROR(_xlfn.XLOOKUP(D23,tbl_Parcels[Parcel],tbl_Parcels[Acres]),0) -> 0 | G23: =IFERROR(LOOKUP('iV1'!$H23,Table4[Product],Table4[DUA]),0) -> 0 | I23: =IFERROR(INT(LOOKUP('iV1'!$H23,lst_LotProducts,lst_ProductDUA)*'iV1'!$F23),0) -> 0 | P23: 0 | Q23: 0 | R23: 0 | S23: 0 | T23: =P23+Q23+R23+S23 -> 0 | X23: =X22+1 -> 16 | Z23: =IFERROR(LOOKUP(Y23,$D$8:$D$32,$I$8:$I$32),0) -> 0 | AA23: =IFERROR(_xlfn.XLOOKUP($Y23,$D$8:$D$32,$H$8:$H$32),0) -> 0 | AB23: =IFERROR(Z23*LOOKUP(AA23,Table4[Product],Table4[Width]),0) -> 0 | AC23: =IFERROR(_xlfn.XLOOKUP($Y23,$D$8:$D$32,$J$8:$J$32),0) -> 0 | AD23: =IFERROR(_xlfn.XLOOKUP(LOOKUP(AC23,$P$5:$S$5,$P$9:$S$9)+1,DATA!$E$11:$E$370,DATA!$F$11:$F$370),"") | AF23: =IFERROR($AB23*(iGeneral!$F$52*LOOKUP($AE23,DATA!$F$11:$F$370,DATA!$L$11:$L$370)),0) -> 0 | AG23: =-IFERROR($AB23*(i_Cost.Subd*LOOKUP($AE23,DATA!$F$11:$F$370,DATA!$L$11:$L$370)),0) -> 0 | AH23: =AF23+AG23 -> 0
C24: 17 | E24: =IFERROR(_xlfn.XLOOKUP(D24,tbl_Parcels[Parcel],tbl_Parcels[Use]),0) -> 0 | F24: =IFERROR(_xlfn.XLOOKUP(D24,tbl_Parcels[Parcel],tbl_Parcels[Acres]),0) -> 0 | G24: =IFERROR(LOOKUP('iV1'!$H24,Table4[Product],Table4[DUA]),0) -> 0 | I24: =IFERROR(INT(LOOKUP('iV1'!$H24,lst_LotProducts,lst_ProductDUA)*'iV1'!$F24),0) -> 0 | P24: 0 | Q24: 0 | R24: 0 | S24: 0 | T24: =P24+Q24+R24+S24 -> 0 | X24: =X23+1 -> 17 | Z24: =IFERROR(LOOKUP(Y24,$D$8:$D$32,$I$8:$I$32),0) -> 0 | AA24: =IFERROR(_xlfn.XLOOKUP($Y24,$D$8:$D$32,$H$8:$H$32),0) -> 0 | AB24: =IFERROR(Z24*LOOKUP(AA24,Table4[Product],Table4[Width]),0) -> 0 | AC24: =IFERROR(_xlfn.XLOOKUP($Y24,$D$8:$D$32,$J$8:$J$32),0) -> 0 | AD24: =IFERROR(_xlfn.XLOOKUP(LOOKUP(AC24,$P$5:$S$5,$P$9:$S$9)+1,DATA!$E$11:$E$370,DATA!$F$11:$F$370),"") | AF24: =IFERROR($AB24*(iGeneral!$F$52*LOOKUP($AE24,DATA!$F$11:$F$370,DATA!$L$11:$L$370)),0) -> 0 | AG24: =-IFERROR($AB24*(i_Cost.Subd*LOOKUP($AE24,DATA!$F$11:$F$370,DATA!$L$11:$L$370)),0) -> 0 | AH24: =AF24+AG24 -> 0
C25: 18 | E25: =IFERROR(_xlfn.XLOOKUP(D25,tbl_Parcels[Parcel],tbl_Parcels[Use]),0) -> 0 | F25: =IFERROR(_xlfn.XLOOKUP(D25,tbl_Parcels[Parcel],tbl_Parcels[Acres]),0) -> 0 | G25: =IFERROR(LOOKUP('iV1'!$H25,Table4[Product],Table4[DUA]),0) -> 0 | I25: =IFERROR(INT(LOOKUP('iV1'!$H25,lst_LotProducts,lst_ProductDUA)*'iV1'!$F25),0) -> 0 | P25: 0 | Q25: 0 | R25: 0 | S25: 0 | T25: =P25+Q25+R25+S25 -> 0 | X25: =X24+1 -> 18 | Z25: =IFERROR(LOOKUP(Y25,$D$8:$D$32,$I$8:$I$32),0) -> 0 | AA25: =IFERROR(_xlfn.XLOOKUP($Y25,$D$8:$D$32,$H$8:$H$32),0) -> 0 | AB25: =IFERROR(Z25*LOOKUP(AA25,Table4[Product],Table4[Width]),0) -> 0 | AC25: =IFERROR(_xlfn.XLOOKUP($Y25,$D$8:$D$32,$J$8:$J$32),0) -> 0 | AD25: =IFERROR(_xlfn.XLOOKUP(LOOKUP(AC25,$P$5:$S$5,$P$9:$S$9)+1,DATA!$E$11:$E$370,DATA!$F$11:$F$370),"") | AF25: =IFERROR($AB25*(iGeneral!$F$52*LOOKUP($AE25,DATA!$F$11:$F$370,DATA!$L$11:$L$370)),0) -> 0 | AG25: =-IFERROR($AB25*(i_Cost.Subd*LOOKUP($AE25,DATA!$F$11:$F$370,DATA!$L$11:$L$370)),0) -> 0 | AH25: =AF25+AG25 -> 0
C26: 19 | E26: =IFERROR(_xlfn.XLOOKUP(D26,tbl_Parcels[Parcel],tbl_Parcels[Use]),0) -> 0 | F26: =IFERROR(_xlfn.XLOOKUP(D26,tbl_Parcels[Parcel],tbl_Parcels[Acres]),0) -> 0 | G26: =IFERROR(LOOKUP('iV1'!$H26,Table4[Product],Table4[DUA]),0) -> 0 | I26: =IFERROR(INT(LOOKUP('iV1'!$H26,lst_LotProducts,lst_ProductDUA)*'iV1'!$F26),0) -> 0 | P26: 0 | Q26: 0 | R26: 0 | S26: 0 | T26: =P26+Q26+R26+S26 -> 0 | X26: =X25+1 -> 19 | Z26: =IFERROR(LOOKUP(Y26,$D$8:$D$32,$I$8:$I$32),0) -> 0 | AA26: =IFERROR(_xlfn.XLOOKUP($Y26,$D$8:$D$32,$H$8:$H$32),0) -> 0 | AB26: =IFERROR(Z26*LOOKUP(AA26,Table4[Product],Table4[Width]),0) -> 0 | AC26: =IFERROR(_xlfn.XLOOKUP($Y26,$D$8:$D$32,$J$8:$J$32),0) -> 0 | AD26: =IFERROR(_xlfn.XLOOKUP(LOOKUP(AC26,$P$5:$S$5,$P$9:$S$9)+1,DATA!$E$11:$E$370,DATA!$F$11:$F$370),"") | AF26: =IFERROR($AB26*(iGeneral!$F$52*LOOKUP($AE26,DATA!$F$11:$F$370,DATA!$L$11:$L$370)),0) -> 0 | AG26: =-IFERROR($AB26*(i_Cost.Subd*LOOKUP($AE26,DATA!$F$11:$F$370,DATA!$L$11:$L$370)),0) -> 0 | AH26: =AF26+AG26 -> 0
C27: 20 | E27: =IFERROR(_xlfn.XLOOKUP(D27,tbl_Parcels[Parcel],tbl_Parcels[Use]),0) -> 0 | F27: =IFERROR(_xlfn.XLOOKUP(D27,tbl_Parcels[Parcel],tbl_Parcels[Acres]),0) -> 0 | G27: =IFERROR(LOOKUP('iV1'!$H27,Table4[Product],Table4[DUA]),0) -> 0 | I27: =IFERROR(INT(LOOKUP('iV1'!$H27,lst_LotProducts,lst_ProductDUA)*'iV1'!$F27),0) -> 0 | P27: 0 | Q27: 0 | R27: 0 | S27: 0 | T27: =P27+Q27+R27+S27 -> 0 | X27: =X26+1 -> 20 | Z27: =IFERROR(LOOKUP(Y27,$D$8:$D$32,$I$8:$I$32),0) -> 0 | AA27: =IFERROR(_xlfn.XLOOKUP($Y27,$D$8:$D$32,$H$8:$H$32),0) -> 0 | AB27: =IFERROR(Z27*LOOKUP(AA27,Table4[Product],Table4[Width]),0) -> 0 | AC27: =IFERROR(_xlfn.XLOOKUP($Y27,$D$8:$D$32,$J$8:$J$32),0) -> 0 | AD27: =IFERROR(_xlfn.XLOOKUP(LOOKUP(AC27,$P$5:$S$5,$P$9:$S$9)+1,DATA!$E$11:$E$370,DATA!$F$11:$F$370),"") | AF27: =IFERROR($AB27*(iGeneral!$F$52*LOOKUP($AE27,DATA!$F$11:$F$370,DATA!$L$11:$L$370)),0) -> 0 | AG27: =-IFERROR($AB27*(i_Cost.Subd*LOOKUP($AE27,DATA!$F$11:$F$370,DATA!$L$11:$L$370)),0) -> 0 | AH27: =AF27+AG27 -> 0
C28: 21 | E28: =IFERROR(_xlfn.XLOOKUP(D28,tbl_Parcels[Parcel],tbl_Parcels[Use]),0) -> 0 | F28: =IFERROR(_xlfn.XLOOKUP(D28,tbl_Parcels[Parcel],tbl_Parcels[Acres]),0) -> 0 | G28: =IFERROR(LOOKUP('iV1'!$H28,Table4[Product],Table4[DUA]),0) -> 0 | I28: =IFERROR(INT(LOOKUP('iV1'!$H28,lst_LotProducts,lst_ProductDUA)*'iV1'!$F28),0) -> 0 | P28: 0 | Q28: 0 | R28: 0 | S28: 0 | T28: =P28+Q28+R28+S28 -> 0 | X28: =X27+1 -> 21 | Z28: =IFERROR(LOOKUP(Y28,$D$8:$D$32,$I$8:$I$32),0) -> 0 | AA28: =IFERROR(_xlfn.XLOOKUP($Y28,$D$8:$D$32,$H$8:$H$32),0) -> 0 | AB28: =IFERROR(Z28*LOOKUP(AA28,Table4[Product],Table4[Width]),0) -> 0 | AC28: =IFERROR(_xlfn.XLOOKUP($Y28,$D$8:$D$32,$J$8:$J$32),0) -> 0 | AD28: =IFERROR(_xlfn.XLOOKUP(LOOKUP(AC28,$P$5:$S$5,$P$9:$S$9)+1,DATA!$E$11:$E$370,DATA!$F$11:$F$370),"") | AF28: =IFERROR($AB28*(iGeneral!$F$52*LOOKUP($AE28,DATA!$F$11:$F$370,DATA!$L$11:$L$370)),0) -> 0 | AG28: =-IFERROR($AB28*(i_Cost.Subd*LOOKUP($AE28,DATA!$F$11:$F$370,DATA!$L$11:$L$370)),0) -> 0 | AH28: =AF28+AG28 -> 0
C29: 22 | E29: =IFERROR(_xlfn.XLOOKUP(D29,tbl_Parcels[Parcel],tbl_Parcels[Use]),0) -> 0 | F29: =IFERROR(_xlfn.XLOOKUP(D29,tbl_Parcels[Parcel],tbl_Parcels[Acres]),0) -> 0 | G29: =IFERROR(LOOKUP('iV1'!$H29,Table4[Product],Table4[DUA]),0) -> 0 | I29: =IFERROR(INT(LOOKUP('iV1'!$H29,lst_LotProducts,lst_ProductDUA)*'iV1'!$F29),0) -> 0 | P29: 0 | Q29: 0 | R29: 0 | S29: 0 | T29: =P29+Q29+R29+S29 -> 0 | X29: =X28+1 -> 22 | Z29: =IFERROR(LOOKUP(Y29,$D$8:$D$32,$I$8:$I$32),0) -> 0 | AA29: =IFERROR(_xlfn.XLOOKUP($Y29,$D$8:$D$32,$H$8:$H$32),0) -> 0 | AB29: =IFERROR(Z29*LOOKUP(AA29,Table4[Product],Table4[Width]),0) -> 0 | AC29: =IFERROR(_xlfn.XLOOKUP($Y29,$D$8:$D$32,$J$8:$J$32),0) -> 0 | AD29: =IFERROR(_xlfn.XLOOKUP(LOOKUP(AC29,$P$5:$S$5,$P$9:$S$9)+1,DATA!$E$11:$E$370,DATA!$F$11:$F$370),"") | AF29: =IFERROR($AB29*(iGeneral!$F$52*LOOKUP($AE29,DATA!$F$11:$F$370,DATA!$L$11:$L$370)),0) -> 0 | AG29: =-IFERROR($AB29*(i_Cost.Subd*LOOKUP($AE29,DATA!$F$11:$F$370,DATA!$L$11:$L$370)),0) -> 0 | AH29: =AF29+AG29 -> 0
C30: 23 | E30: =IFERROR(_xlfn.XLOOKUP(D30,tbl_Parcels[Parcel],tbl_Parcels[Use]),0) -> 0 | F30: =IFERROR(_xlfn.XLOOKUP(D30,tbl_Parcels[Parcel],tbl_Parcels[Acres]),0) -> 0 | G30: =IFERROR(LOOKUP('iV1'!$H30,Table4[Product],Table4[DUA]),0) -> 0 | I30: =IFERROR(INT(LOOKUP('iV1'!$H30,lst_LotProducts,lst_ProductDUA)*'iV1'!$F30),0) -> 0 | P30: 0 | Q30: 0 | R30: 0 | S30: 0 | T30: =P30+Q30+R30+S30 -> 0 | X30: =X29+1 -> 23 | Z30: =IFERROR(LOOKUP(Y30,$D$8:$D$32,$I$8:$I$32),0) -> 0 | AA30: =IFERROR(_xlfn.XLOOKUP($Y30,$D$8:$D$32,$H$8:$H$32),0) -> 0 | AB30: =IFERROR(Z30*LOOKUP(AA30,Table4[Product],Table4[Width]),0) -> 0 | AC30: =IFERROR(_xlfn.XLOOKUP($Y30,$D$8:$D$32,$J$8:$J$32),0) -> 0 | AD30: =IFERROR(_xlfn.XLOOKUP(LOOKUP(AC30,$P$5:$S$5,$P$9:$S$9)+1,DATA!$E$11:$E$370,DATA!$F$11:$F$370),"") | AF30: =IFERROR($AB30*(iGeneral!$F$52*LOOKUP($AE30,DATA!$F$11:$F$370,DATA!$L$11:$L$370)),0) -> 0 | AG30: =-IFERROR($AB30*(i_Cost.Subd*LOOKUP($AE30,DATA!$F$11:$F$370,DATA!$L$11:$L$370)),0) -> 0 | AH30: =AF30+AG30 -> 0
C31: 24 | E31: =IFERROR(_xlfn.XLOOKUP(D31,tbl_Parcels[Parcel],tbl_Parcels[Use]),0) -> 0 | F31: =IFERROR(_xlfn.XLOOKUP(D31,tbl_Parcels[Parcel],tbl_Parcels[Acres]),0) -> 0 | G31: =IFERROR(LOOKUP('iV1'!$H31,Table4[Product],Table4[DUA]),0) -> 0 | I31: =IFERROR(INT(LOOKUP('iV1'!$H31,lst_LotProducts,lst_ProductDUA)*'iV1'!$F31),0) -> 0 | P31: 0 | Q31: 0 | R31: 0 | S31: 0 | T31: =P31+Q31+R31+S31 -> 0 | X31: =X30+1 -> 24 | Z31: =IFERROR(LOOKUP(Y31,$D$8:$D$32,$I$8:$I$32),0) -> 0 | AA31: =IFERROR(_xlfn.XLOOKUP($Y31,$D$8:$D$32,$H$8:$H$32),0) -> 0 | AB31: =IFERROR(Z31*LOOKUP(AA31,Table4[Product],Table4[Width]),0) -> 0 | AC31: =IFERROR(_xlfn.XLOOKUP($Y31,$D$8:$D$32,$J$8:$J$32),0) -> 0 | AD31: =IFERROR(_xlfn.XLOOKUP(LOOKUP(AC31,$P$5:$S$5,$P$9:$S$9)+1,DATA!$E$11:$E$370,DATA!$F$11:$F$370),"") | AF31: =IFERROR($AB31*(iGeneral!$F$52*LOOKUP($AE31,DATA!$F$11:$F$370,DATA!$L$11:$L$370)),0) -> 0 | AG31: =-IFERROR($AB31*(i_Cost.Subd*LOOKUP($AE31,DATA!$F$11:$F$370,DATA!$L$11:$L$370)),0) -> 0 | AH31: =AF31+AG31 -> 0
C32: 25 | E32: =IFERROR(_xlfn.XLOOKUP(D32,tbl_Parcels[Parcel],tbl_Parcels[Use]),0) -> 0 | F32: =IFERROR(_xlfn.XLOOKUP(D32,tbl_Parcels[Parcel],tbl_Parcels[Acres]),0) -> 0 | G32: =IFERROR(LOOKUP('iV1'!$H32,Table4[Product],Table4[DUA]),0) -> 0 | I32: =IFERROR(INT(LOOKUP('iV1'!$H32,lst_LotProducts,lst_ProductDUA)*'iV1'!$F32),0) -> 0 | P32: 0 | Q32: 0 | R32: 0 | S32: 0 | T32: =P32+Q32+R32+S32 -> 0 | X32: =X31+1 -> 25 | Z32: =IFERROR(LOOKUP(Y32,$D$8:$D$32,$I$8:$I$32),0) -> 0 | AA32: =IFERROR(_xlfn.XLOOKUP($Y32,$D$8:$D$32,$H$8:$H$32),0) -> 0 | AB32: =IFERROR(Z32*LOOKUP(AA32,Table4[Product],Table4[Width]),0) -> 0 | AC32: =IFERROR(_xlfn.XLOOKUP($Y32,$D$8:$D$32,$J$8:$J$32),0) -> 0 | AD32: =IFERROR(_xlfn.XLOOKUP(LOOKUP(AC32,$P$5:$S$5,$P$9:$S$9)+1,DATA!$E$11:$E$370,DATA!$F$11:$F$370),"") | AF32: =IFERROR($AB32*(iGeneral!$F$52*LOOKUP($AE32,DATA!$F$11:$F$370,DATA!$L$11:$L$370)),0) -> 0 | AG32: =-IFERROR($AB32*(i_Cost.Subd*LOOKUP($AE32,DATA!$F$11:$F$370,DATA!$L$11:$L$370)),0) -> 0 | AH32: =AF32+AG32 -> 0
N33: Total | P33: =SUM(P11:P32) -> 13000000 | Q33: =SUM(Q11:Q32) -> 19600000 | R33: =SUM(R11:R32) -> 0 | S33: =SUM(S11:S32) -> 0 | T33: =P33+Q33+R33+S33 -> 32600000

Sheet V2
C4: 2 | F4: ='iV1'!F4 -> Parcel Land Use & Lot Product | O4: =C4 -> 2 | Q4: Development Phasing | Z4: =O4 -> 2 | AB4: Sale Schedule
O5: =O4 -> 2 | Q5: 1 | R5: =Q5+1 -> 2 | S5: =R5+1 -> 3 | T5: =S5+1 -> 4 | Y5: Lag to Development Completion | AC5: 1
J6: Phasing | AD6: Sale | AE6: Proceeds | AF6: Sale | AG6: =AE6 -> Proceeds
C7: ID | D7: Parcel# | E7: Use | F7: Acres | G7: DUA | H7: Product | I7: Units | J7: Develop | K7: Sale | O7: Start Month | Q7: 6 | R7: 18 | S7: 36 | T7: 60 | Y7: # | Z7: Parcel | AA7: Lots | AB7: Product | AC7: Acres | AD7: Phase | AE7: GROSS | AF7: Cost | AG7: NET
C8: 1 | D8: {=_xlfn._xlws.FILTER(tbl_Parcels[Parcel],tbl_Parcels[Village]=C4,0)} -> 2.16 | E8: =IFERROR(_xlfn.XLOOKUP(D8,tbl_Parcels[Parcel],tbl_Parcels[Use]),0) -> MHDR | F8: =IFERROR(LOOKUP(D8,tbl_Parcels[Parcel],tbl_Parcels[Acres]),0) -> 31.85 | G8: =IFERROR(LOOKUP('V2'!$H8,Table4[Product],Table4[DUA]),0) -> 3.4485 | H8: 60x120 | I8: =IFERROR(INT(LOOKUP('V2'!$H8,lst_LotProducts,lst_ProductDUA)*'V2'!$F8),0) -> 109 | J8: 1 | O8: Months to Complete | Q8: 12 | R8: 8 | S8: 10 | T8: 6 | Y8: 1 | Z8: {=_xlfn.UNIQUE(_xlfn._xlws.FILTER(D8:D32,D8:D32<>0))} -> 2.16 | AA8: =IFERROR(LOOKUP(Z8,$D$8:$D$32,$I$8:$I$32),0) -> 109 | AB8: =IFERROR(_xlfn.XLOOKUP($Z8,$D$8:$D$32,$H$8:$H$32),0) -> 60x120 | AC8: =IFERROR(_xlfn.XLOOKUP($Z8,$D$6:$D$30,$F$6:$F$30),0) -> 31.85 | AD8: 1
C9: 2 | D9: 2.17 | E9: =IFERROR(_xlfn.XLOOKUP(D9,tbl_Parcels[Parcel],tbl_Parcels[Use]),0) -> MU | F9: =IFERROR(LOOKUP(D9,tbl_Parcels[Parcel],tbl_Parcels[Acres]),0) -> 31.04 | G9: =IFERROR(LOOKUP('V2'!$H9,Table4[Product],Table4[DUA]),0) -> 3.31056 | H9: 60x125 | I9: =IFERROR(INT(LOOKUP('V2'!$H9,lst_LotProducts,lst_ProductDUA)*'V2'!$F9),0) -> 102 | J9: 1 | U9: Total | Y9: =Y8+1 -> 2 | Z9: 2.17 | AA9: =IFERROR(LOOKUP(Z9,$D$8:$D$32,$I$8:$I$32),0) -> 102 | AB9: =IFERROR(_xlfn.XLOOKUP($Z9,$D$8:$D$32,$H$8:$H$32),0) -> 60x125 | AC9: =IFERROR(_xlfn.XLOOKUP($Z9,$D$6:$D$30,$F$6:$F$30),0) -> 31.04 | AD9: 1
C10: 3 | D10: 2.18 | E10: =IFERROR(_xlfn.XLOOKUP(D10,tbl_Parcels[Parcel],tbl_Parcels[Use]),0) -> MHDR | F10: =IFERROR(LOOKUP(D10,tbl_Parcels[Parcel],tbl_Parcels[Acres]),0) -> 27.56 | G10: =IFERROR(LOOKUP('V2'!$H10,Table4[Product],Table4[DUA]),0) -> 5.016 | H10: 45x110 | I10: =IFERROR(INT(LOOKUP('V2'!$H10,lst_LotProducts,lst_ProductDUA)*'V2'!$F10),0) -> 138 | J10: 1 | O10: Acqusition | P10: a | Q10: 0 | R10: 0 | S10: 0 | T10: 0 | U10: =Q10+R10+S10+T10 -> 0 | Y10: =Y9+1 -> 3 | Z10: 2.18 | AA10: =IFERROR(LOOKUP(Z10,$D$8:$D$32,$I$8:$I$32),0) -> 138 | AB10: =IFERROR(_xlfn.XLOOKUP($Z10,$D$8:$D$32,$H$8:$H$32),0) -> 45x110 | AC10: =IFERROR(_xlfn.XLOOKUP($Z10,$D$6:$D$30,$F$6:$F$30),0) -> 27.56 | AD10: 1
C11: 4 | D11: 2.19 | E11: =IFERROR(_xlfn.XLOOKUP(D11,tbl_Parcels[Parcel],tbl_Parcels[Use]),0) -> MU | F11: =IFERROR(LOOKUP(D11,tbl_Parcels[Parcel],tbl_Parcels[Acres]),0) -> 21.86 | G11: =IFERROR(LOOKUP('V2'!$H11,Table4[Product],Table4[DUA]),0) -> 5.016 | H11: 45x110 | I11: =IFERROR(INT(LOOKUP('V2'!$H11,lst_LotProducts,lst_ProductDUA)*'V2'!$F11),0) -> 109 | J11: 1 | M11: insert summary | O11: Entitlements | Q11: 5000000 | R11: 2500000 | S11: 1500000 | T11: 3000000 | U11: =Q11+R11+S11+T11 -> 12000000 | W11: insert summary | Y11: =Y10+1 -> 4 | Z11: 2.19 | AA11: =IFERROR(LOOKUP(Z11,$D$8:$D$32,$I$8:$I$32),0) -> 109 | AB11: =IFERROR(_xlfn.XLOOKUP($Z11,$D$8:$D$32,$H$8:$H$32),0) -> 45x110 | AC11: =IFERROR(_xlfn.XLOOKUP($Z11,$D$6:$D$30,$F$6:$F$30),0) -> 21.86 | AD11: 1
C12: 5 | D12: 2.20 | E12: =IFERROR(_xlfn.XLOOKUP(D12,tbl_Parcels[Parcel],tbl_Parcels[Use]),0) -> MU | F12: =IFERROR(LOOKUP(D12,tbl_Parcels[Parcel],tbl_Parcels[Acres]),0) -> 35.51 | G12: =IFERROR(LOOKUP('V2'!$H12,Table4[Product],Table4[DUA]),0) -> 3.31056 | H12: 60x125 | I12: =IFERROR(INT(LOOKUP('V2'!$H12,lst_LotProducts,lst_ProductDUA)*'V2'!$F12),0) -> 117 | J12: 1 | M12: or charts here | O12: Engineering | Q12: 0 | R12: 0 | S12: 0 | T12: 0 | U12: =Q12+R12+S12+T12 -> 0 | W12: or charts here | Y12: =Y11+1 -> 5 | Z12: 2.20 | AA12: =IFERROR(LOOKUP(Z12,$D$8:$D$32,$I$8:$I$32),0) -> 117 | AB12: =IFERROR(_xlfn.XLOOKUP($Z12,$D$8:$D$32,$H$8:$H$32),0) -> 60x125 | AC12: =IFERROR(_xlfn.XLOOKUP($Z12,$D$6:$D$30,$F$6:$F$30),0) -> 35.51 | AD12: 1
C13: 6 | D13: 2.21 | E13: =IFERROR(_xlfn.XLOOKUP(D13,tbl_Parcels[Parcel],tbl_Parcels[Use]),0) -> MU | F13: =IFERROR(LOOKUP(D13,tbl_Parcels[Parcel],tbl_Parcels[Acres]),0) -> 43.89 | G13: =IFERROR(LOOKUP('V2'!$H13,Table4[Product],Table4[DUA]),0) -> 3.972672 | H13: 50x125 | I13: =IFERROR(INT(LOOKUP('V2'!$H13,lst_LotProducts,lst_ProductDUA)*'V2'!$F13),0) -> 174 | J13: 1 | O13: Development > Offsite | Q13: 0 | R13: 0 | S13: 0 | T13: 0 | U13: =Q13+R13+S13+T13 -> 0 | Y13: =Y12+1 -> 6 | Z13: 2.21 | AA13: =IFERROR(LOOKUP(Z13,$D$8:$D$32,$I$8:$I$32),0) -> 174 | AB13: =IFERROR(_xlfn.XLOOKUP($Z13,$D$8:$D$32,$H$8:$H$32),0) -> 50x125 | AC13: =IFERROR(_xlfn.XLOOKUP($Z13,$D$6:$D$30,$F$6:$F$30),0) -> 43.89 | AD13: 1
C14: 7 | D14: 2.22 | E14: =IFERROR(_xlfn.XLOOKUP(D14,tbl_Parcels[Parcel],tbl_Parcels[Use]),0) -> MU | F14: =IFERROR(LOOKUP(D14,tbl_Parcels[Parcel],tbl_Parcels[Acres]),0) -> 31.59 | G14: =IFERROR(LOOKUP('V2'!$H14,Table4[Product],Table4[DUA]),0) -> 4.598 | H14: 45x120 | I14: =IFERROR(INT(LOOKUP('V2'!$H14,lst_LotProducts,lst_ProductDUA)*'V2'!$F14),0) -> 145 | J14: 1 | O14: Development > OnSite | Q14: 0 | R14: 0 | S14: 0 | T14: 0 | U14: =Q14+R14+S14+T14 -> 0 | Y14: =Y13+1 -> 7 | Z14: 2.22 | AA14: =IFERROR(LOOKUP(Z14,$D$8:$D$32,$I$8:$I$32),0) -> 145 | AB14: =IFERROR(_xlfn.XLOOKUP($Z14,$D$8:$D$32,$H$8:$H$32),0) -> 45x120 | AC14: =IFERROR(_xlfn.XLOOKUP($Z14,$D$6:$D$30,$F$6:$F$30),0) -> 31.59 | AD14: 1
C15: 8 | E15: =IFERROR(_xlfn.XLOOKUP(D15,tbl_Parcels[Parcel],tbl_Parcels[Use]),0) -> 0 | F15: =IFERROR(LOOKUP(D15,tbl_Parcels[Parcel],tbl_Parcels[Acres]),0) -> 0 | G15: =IFERROR(LOOKUP('V2'!$H15,Table4[Product],Table4[DUA]),0) -> 0 | I15: =IFERROR(INT(LOOKUP('V2'!$H15,lst_LotProducts,lst_ProductDUA)*'V2'!$F15),0) -> 0 | J15: 1 | O15: Development > Subdivision | Q15: 0 | R15: 0 | S15: 0 | T15: 0 | U15: =Q15+R15+S15+T15 -> 0 | Y15: =Y14+1 -> 8 | AA15: =IFERROR(LOOKUP(Z15,$D$8:$D$32,$I$8:$I$32),0) -> 0 | AB15: =IFERROR(_xlfn.XLOOKUP($Z15,$D$8:$D$32,$H$8:$H$32),0) -> 0 | AC15: =IFERROR(_xlfn.XLOOKUP($Z15,$D$6:$D$30,$F$6:$F$30),0) -> 0 | AD15: 2
C16: 9 | E16: =IFERROR(_xlfn.XLOOKUP(D16,tbl_Parcels[Parcel],tbl_Parcels[Use]),0) -> 0 | F16: =IFERROR(LOOKUP(D16,tbl_Parcels[Parcel],tbl_Parcels[Acres]),0) -> 0 | G16: =IFERROR(LOOKUP('V2'!$H16,Table4[Product],Table4[DUA]),0) -> 0 | I16: =IFERROR(INT(LOOKUP('V2'!$H16,lst_LotProducts,lst_ProductDUA)*'V2'!$F16),0) -> 0 | J16: 2 | O16: Development > Other | Q16: 0 | R16: 0 | S16: 0 | T16: 0 | U16: =Q16+R16+S16+T16 -> 0 | Y16: =Y15+1 -> 9 | AA16: =IFERROR(LOOKUP(Z16,$D$8:$D$32,$I$8:$I$32),0) -> 0 | AB16: =IFERROR(_xlfn.XLOOKUP($Z16,$D$8:$D$32,$H$8:$H$32),0) -> 0 | AC16: =IFERROR(_xlfn.XLOOKUP($Z16,$D$6:$D$30,$F$6:$F$30),0) -> 0 | AD16: 2
C17: 10 | E17: =IFERROR(_xlfn.XLOOKUP(D17,tbl_Parcels[Parcel],tbl_Parcels[Use]),0) -> 0 | F17: =IFERROR(LOOKUP(D17,tbl_Parcels[Parcel],tbl_Parcels[Acres]),0) -> 0 | G17: =IFERROR(LOOKUP('V2'!$H17,Table4[Product],Table4[DUA]),0) -> 0 | I17: =IFERROR(INT(LOOKUP('V2'!$H17,lst_LotProducts,lst_ProductDUA)*'V2'!$F17),0) -> 0 | J17: 2 | O17: Other | Q17: 0 | R17: 0 | S17: 0 | T17: 0 | U17: =Q17+R17+S17+T17 -> 0 | Y17: =Y16+1 -> 10 | AA17: =IFERROR(LOOKUP(Z17,$D$8:$D$32,$I$8:$I$32),0) -> 0 | AB17: =IFERROR(_xlfn.XLOOKUP($Z17,$D$8:$D$32,$H$8:$H$32),0) -> 0 | AC17: =IFERROR(_xlfn.XLOOKUP($Z17,$D$6:$D$30,$F$6:$F$30),0) -> 0 | AD17: 2
C18: 11 | E18: =IFERROR(_xlfn.XLOOKUP(D18,tbl_Parcels[Parcel],tbl_Parcels[Use]),0) -> 0 | F18: =IFERROR(LOOKUP(D18,tbl_Parcels[Parcel],tbl_Parcels[Acres]),0) -> 0 | G18: =IFERROR(LOOKUP('V2'!$H18,Table4[Product],Table4[DUA]),0) -> 0 | I18: =IFERROR(INT(LOOKUP('V2'!$H18,lst_LotProducts,lst_ProductDUA)*'V2'!$F18),0) -> 0 | J18: 2 | Q18: 0 | R18: 0 | S18: 0 | T18: 0 | U18: =Q18+R18+S18+T18 -> 0 | Y18: =Y17+1 -> 11 | AA18: =IFERROR(LOOKUP(Z18,$D$8:$D$32,$I$8:$I$32),0) -> 0 | AB18: =IFERROR(_xlfn.XLOOKUP($Z18,$D$8:$D$32,$H$8:$H$32),0) -> 0 | AC18: =IFERROR(_xlfn.XLOOKUP($Z18,$D$6:$D$30,$F$6:$F$30),0) -> 0 | AD18: 2
C19: 12 | E19: =IFERROR(_xlfn.XLOOKUP(D19,tbl_Parcels[Parcel],tbl_Parcels[Use]),0) -> 0 | F19: =IFERROR(LOOKUP(D19,tbl_Parcels[Parcel],tbl_Parcels[Acres]),0) -> 0 | G19: =IFERROR(LOOKUP('V2'!$H19,Table4[Product],Table4[DUA]),0) -> 0 | I19: =IFERROR(INT(LOOKUP('V2'!$H19,lst_LotProducts,lst_ProductDUA)*'V2'!$F19),0) -> 0 | J19: 2 | Q19: 0 | R19: 0 | S19: 0 | T19: 0 | U19: =Q19+R19+S19+T19 -> 0 | Y19: =Y18+1 -> 12 | AA19: =IFERROR(LOOKUP(Z19,$D$8:$D$32,$I$8:$I$32),0) -> 0 | AB19: =IFERROR(_xlfn.XLOOKUP($Z19,$D$8:$D$32,$H$8:$H$32),0) -> 0 | AC19: =IFERROR(_xlfn.XLOOKUP($Z19,$D$6:$D$30,$F$6:$F$30),0) -> 0 | AD19: 2
C20: 13 | E20: =IFERROR(_xlfn.XLOOKUP(D20,tbl_Parcels[Parcel],tbl_Parcels[Use]),0) -> 0 | F20: =IFERROR(LOOKUP(D20,tbl_Parcels[Parcel],tbl_Parcels[Acres]),0) -> 0 | G20: =IFERROR(LOOKUP('V2'!$H20,Table4[Product],Table4[DUA]),0) -> 0 | I20: =IFERROR(INT(LOOKUP('V2'!$H20,lst_LotProducts,lst_ProductDUA)*'V2'!$F20),0) -> 0 | J20: 2 | Q20: 0 | R20: 0 | S20: 0 | T20: 0 | U20: =Q20+R20+S20+T20 -> 0 | Y20: =Y19+1 -> 13 | AA20: =IFERROR(LOOKUP(Z20,$D$8:$D$32,$I$8:$I$32),0) -> 0 | AB20: =IFERROR(_xlfn.XLOOKUP($Z20,$D$8:$D$32,$H$8:$H$32),0) -> 0 | AC20: =IFERROR(_xlfn.XLOOKUP($Z20,$D$6:$D$30,$F$6:$F$30),0) -> 0 | AD20: 2
C21: 14 | E21: =IFERROR(_xlfn.XLOOKUP(D21,tbl_Parcels[Parcel],tbl_Parcels[Use]),0) -> 0 | F21: =IFERROR(LOOKUP(D21,tbl_Parcels[Parcel],tbl_Parcels[Acres]),0) -> 0 | G21: =IFERROR(LOOKUP('V2'!$H21,Table4[Product],Table4[DUA]),0) -> 0 | I21: =IFERROR(INT(LOOKUP('V2'!$H21,lst_LotProducts,lst_ProductDUA)*'V2'!$F21),0) -> 0 | J21: 2 | Q21: 0 | R21: 0 | S21: 0 | T21: 0 | U21: =Q21+R21+S21+T21 -> 0 | Y21: =Y20+1 -> 14 | AA21: =IFERROR(LOOKUP(Z21,$D$8:$D$32,$I$8:$I$32),0) -> 0 | AB21: =IFERROR(_xlfn.XLOOKUP($Z21,$D$8:$D$32,$H$8:$H$32),0) -> 0 | AC21: =IFERROR(_xlfn.XLOOKUP($Z21,$D$6:$D$30,$F$6:$F$30),0) -> 0 | AD21: 2
C22: 15 | E22: =IFERROR(_xlfn.XLOOKUP(D22,tbl_Parcels[Parcel],tbl_Parcels[Use]),0) -> 0 | F22: =IFERROR(LOOKUP(D22,tbl_Parcels[Parcel],tbl_Parcels[Acres]),0) -> 0 | G22: =IFERROR(LOOKUP('V2'!$H22,Table4[Product],Table4[DUA]),0) -> 0 | I22: =IFERROR(INT(LOOKUP('V2'!$H22,lst_LotProducts,lst_ProductDUA)*'V2'!$F22),0) -> 0 | Q22: 0 | R22: 0 | S22: 0 | T22: 0 | U22: =Q22+R22+S22+T22 -> 0 | Y22: =Y21+1 -> 15 | AA22: =IFERROR(LOOKUP(Z22,$D$8:$D$32,$I$8:$I$32),0) -> 0 | AB22: =IFERROR(_xlfn.XLOOKUP($Z22,$D$8:$D$32,$H$8:$H$32),0) -> 0 | AC22: =IFERROR(_xlfn.XLOOKUP($Z22,$D$6:$D$30,$F$6:$F$30),0) -> 0 | AD22: 2
C23: 16 | E23: =IFERROR(_xlfn.XLOOKUP(D23,tbl_Parcels[Parcel],tbl_Parcels[Use]),0) -> 0 | F23: =IFERROR(LOOKUP(D23,tbl_Parcels[Parcel],tbl_Parcels[Acres]),0) -> 0 | G23: =IFERROR(LOOKUP('V2'!$H23,Table4[Product],Table4[DUA]),0) -> 0 | I23: =IFERROR(INT(LOOKUP('V2'!$H23,lst_LotProducts,lst_ProductDUA)*'V2'!$F23),0) -> 0 | Q23: 0 | R23: 0 | S23: 0 | T23: 0 | U23: =Q23+R23+S23+T23 -> 0 | Y23: =Y22+1 -> 16 | AA23: =IFERROR(LOOKUP(Z23,$D$8:$D$32,$I$8:$I$32),0) -> 0 | AB23: =IFERROR(_xlfn.XLOOKUP($Z23,$D$8:$D$32,$H$8:$H$32),0) -> 0 | AC23: =IFERROR(_xlfn.XLOOKUP($Z23,$D$6:$D$30,$F$6:$F$30),0) -> 0
C24: 17 | E24: =IFERROR(_xlfn.XLOOKUP(D24,tbl_Parcels[Parcel],tbl_Parcels[Use]),0) -> 0 | F24: =IFERROR(LOOKUP(D24,tbl_Parcels[Parcel],tbl_Parcels[Acres]),0) -> 0 | G24: =IFERROR(LOOKUP('V2'!$H24,Table4[Product],Table4[DUA]),0) -> 0 | I24: =IFERROR(INT(LOOKUP('V2'!$H24,lst_LotProducts,lst_ProductDUA)*'V2'!$F24),0) -> 0 | Q24: 0 | R24: 0 | S24: 0 | T24: 0 | U24: =Q24+R24+S24+T24 -> 0 | Y24: =Y23+1 -> 17 | AA24: =IFERROR(LOOKUP(Z24,$D$8:$D$32,$I$8:$I$32),0) -> 0 | AB24: =IFERROR(_xlfn.XLOOKUP($Z24,$D$8:$D$32,$H$8:$H$32),0) -> 0 | AC24: =IFERROR(_xlfn.XLOOKUP($Z24,$D$6:$D$30,$F$6:$F$30),0) -> 0
C25: 18 | E25: =IFERROR(_xlfn.XLOOKUP(D25,tbl_Parcels[Parcel],tbl_Parcels[Use]),0) -> 0 | F25: =IFERROR(LOOKUP(D25,tbl_Parcels[Parcel],tbl_Parcels[Acres]),0) -> 0 | G25: =IFERROR(LOOKUP('V2'!$H25,Table4[Product],Table4[DUA]),0) -> 0 | I25: =IFERROR(INT(LOOKUP('V2'!$H25,lst_LotProducts,lst_ProductDUA)*'V2'!$F25),0) -> 0 | Q25: 0 | R25: 0 | S25: 0 | T25: 0 | U25: =Q25+R25+S25+T25 -> 0 | Y25: =Y24+1 -> 18 | AA25: =IFERROR(LOOKUP(Z25,$D$8:$D$32,$I$8:$I$32),0) -> 0 | AB25: =IFERROR(_xlfn.XLOOKUP($Z25,$D$8:$D$32,$H$8:$H$32),0) -> 0 | AC25: =IFERROR(_xlfn.XLOOKUP($Z25,$D$6:$D$30,$F$6:$F$30),0) -> 0
C26: 19 | E26: =IFERROR(_xlfn.XLOOKUP(D26,tbl_Parcels[Parcel],tbl_Parcels[Use]),0) -> 0 | F26: =IFERROR(LOOKUP(D26,tbl_Parcels[Parcel],tbl_Parcels[Acres]),0) -> 0 | G26: =IFERROR(LOOKUP('V2'!$H26,Table4[Product],Table4[DUA]),0) -> 0 | I26: =IFERROR(INT(LOOKUP('V2'!$H26,lst_LotProducts,lst_ProductDUA)*'V2'!$F26),0) -> 0 | Q26: 0 | R26: 0 | S26: 0 | T26: 0 | U26: =Q26+R26+S26+T26 -> 0 | Y26: =Y25+1 -> 19 | AA26: =IFERROR(LOOKUP(Z26,$D$8:$D$32,$I$8:$I$32),0) -> 0 | AB26: =IFERROR(_xlfn.XLOOKUP($Z26,$D$8:$D$32,$H$8:$H$32),0) -> 0 | AC26: =IFERROR(_xlfn.XLOOKUP($Z26,$D$6:$D$30,$F$6:$F$30),0) -> 0
C27: 20 | E27: =IFERROR(_xlfn.XLOOKUP(D27,tbl_Parcels[Parcel],tbl_Parcels[Use]),0) -> 0 | F27: =IFERROR(LOOKUP(D27,tbl_Parcels[Parcel],tbl_Parcels[Acres]),0) -> 0 | G27: =IFERROR(LOOKUP('V2'!$H27,Table4[Product],Table4[DUA]),0) -> 0 | I27: =IFERROR(INT(LOOKUP('V2'!$H27,lst_LotProducts,lst_ProductDUA)*'V2'!$F27),0) -> 0 | Q27: 0 | R27: 0 | S27: 0 | T27: 0 | U27: =Q27+R27+S27+T27 -> 0 | Y27: =Y26+1 -> 20 | AA27: =IFERROR(LOOKUP(Z27,$D$8:$D$32,$I$8:$I$32),0) -> 0 | AB27: =IFERROR(_xlfn.XLOOKUP($Z27,$D$8:$D$32,$H$8:$H$32),0) -> 0 | AC27: =IFERROR(_xlfn.XLOOKUP($Z27,$D$6:$D$30,$F$6:$F$30),0) -> 0
C28: 21 | E28: =IFERROR(_xlfn.XLOOKUP(D28,tbl_Parcels[Parcel],tbl_Parcels[Use]),0) -> 0 | F28: =IFERROR(LOOKUP(D28,tbl_Parcels[Parcel],tbl_Parcels[Acres]),0) -> 0 | G28: =IFERROR(LOOKUP('V2'!$H28,Table4[Product],Table4[DUA]),0) -> 0 | I28: =IFERROR(INT(LOOKUP('V2'!$H28,lst_LotProducts,lst_ProductDUA)*'V2'!$F28),0) -> 0 | Q28: 0 | R28: 0 | S28: 0 | T28: 0 | U28: =Q28+R28+S28+T28 -> 0 | Y28: =Y27+1 -> 21 | AA28: =IFERROR(LOOKUP(Z28,$D$8:$D$32,$I$8:$I$32),0) -> 0 | AB28: =IFERROR(_xlfn.XLOOKUP($Z28,$D$8:$D$32,$H$8:$H$32),0) -> 0 | AC28: =IFERROR(_xlfn.XLOOKUP($Z28,$D$6:$D$30,$F$6:$F$30),0) -> 0
C29: 22 | E29: =IFERROR(_xlfn.XLOOKUP(D29,tbl_Parcels[Parcel],tbl_Parcels[Use]),0) -> 0 | F29: =IFERROR(LOOKUP(D29,tbl_Parcels[Parcel],tbl_Parcels[Acres]),0) -> 0 | G29: =IFERROR(LOOKUP('V2'!$H29,Table4[Product],Table4[DUA]),0) -> 0 | I29: =IFERROR(INT(LOOKUP('V2'!$H29,lst_LotProducts,lst_ProductDUA)*'V2'!$F29),0) -> 0 | Q29: 0 | R29: 0 | S29: 0 | T29: 0 | U29: =Q29+R29+S29+T29 -> 0 | Y29: =Y28+1 -> 22 | AA29: =IFERROR(LOOKUP(Z29,$D$8:$D$32,$I$8:$I$32),0) -> 0 | AB29: =IFERROR(_xlfn.XLOOKUP($Z29,$D$8:$D$32,$H$8:$H$32),0) -> 0 | AC29: =IFERROR(_xlfn.XLOOKUP($Z29,$D$6:$D$30,$F$6:$F$30),0) -> 0
C30: 23 | E30: =IFERROR(_xlfn.XLOOKUP(D30,tbl_Parcels[Parcel],tbl_Parcels[Use]),0) -> 0 | F30: =IFERROR(LOOKUP(D30,tbl_Parcels[Parcel],tbl_Parcels[Acres]),0) -> 0 | G30: =IFERROR(LOOKUP('V2'!$H30,Table4[Product],Table4[DUA]),0) -> 0 | I30: =IFERROR(INT(LOOKUP('V2'!$H30,lst_LotProducts,lst_ProductDUA)*'V2'!$F30),0) -> 0 | Q30: 0 | R30: 0 | S30: 0 | T30: 0 | U30: =Q30+R30+S30+T30 -> 0 | Y30: =Y29+1 -> 23 | AA30: =IFERROR(LOOKUP(Z30,$D$8:$D$32,$I$8:$I$32),0) -> 0 | AB30: =IFERROR(_xlfn.XLOOKUP($Z30,$D$8:$D$32,$H$8:$H$32),0) -> 0 | AC30: =IFERROR(_xlfn.XLOOKUP($Z30,$D$6:$D$30,$F$6:$F$30),0) -> 0
C31: 24 | E31: =IFERROR(_xlfn.XLOOKUP(D31,tbl_Parcels[Parcel],tbl_Parcels[Use]),0) -> 0 | F31: =IFERROR(LOOKUP(D31,tbl_Parcels[Parcel],tbl_Parcels[Acres]),0) -> 0 | G31: =IFERROR(LOOKUP('V2'!$H31,Table4[Product],Table4[DUA]),0) -> 0 | I31: =IFERROR(INT(LOOKUP('V2'!$H31,lst_LotProducts,lst_ProductDUA)*'V2'!$F31),0) -> 0 | Q31: 0 | R31: 0 | S31: 0 | T31: 0 | U31: =Q31+R31+S31+T31 -> 0 | Y31: =Y30+1 -> 24 | AA31: =IFERROR(LOOKUP(Z31,$D$8:$D$32,$I$8:$I$32),0) -> 0 | AB31: =IFERROR(_xlfn.XLOOKUP($Z31,$D$8:$D$32,$H$8:$H$32),0) -> 0 | AC31: =IFERROR(_xlfn.XLOOKUP($Z31,$D$6:$D$30,$F$6:$F$30),0) -> 0
C32: 25 | E32: =IFERROR(_xlfn.XLOOKUP(D32,tbl_Parcels[Parcel],tbl_Parcels[Use]),0) -> 0 | F32: =IFERROR(LOOKUP(D32,tbl_Parcels[Parcel],tbl_Parcels[Acres]),0) -> 0 | G32: =IFERROR(LOOKUP('V2'!$H32,Table4[Product],Table4[DUA]),0) -> 0 | I32: =IFERROR(INT(LOOKUP('V2'!$H32,lst_LotProducts,lst_ProductDUA)*'V2'!$F32),0) -> 0 | P32: Total | Q32: =SUM(Q10:Q31) -> 5000000 | R32: =SUM(R10:R31) -> 2500000 | S32: =SUM(S10:S31) -> 1500000 | T32: =SUM(T10:T31) -> 3000000 | U32: =Q32+R32+S32+T32 -> 12000000 | Y32: =Y31+1 -> 25 | AA32: =IFERROR(LOOKUP(Z32,$D$8:$D$32,$I$8:$I$32),0) -> 0 | AB32: =IFERROR(_xlfn.XLOOKUP($Z32,$D$8:$D$32,$H$8:$H$32),0) -> 0 | AC32: =IFERROR(_xlfn.XLOOKUP($Z32,$D$6:$D$30,$F$6:$F$30),0) -> 0

Sheet V3
C4: 3 | F4: ='iV1'!F4 -> Parcel Land Use & Lot Product | O4: =C4 -> 3 | Q4: Development Phasing | Y4: =O4 -> 3 | AB4: Sale Schedule
Q5: 1 | R5: =Q5+1 -> 2 | S5: =R5+1 -> 3 | T5: =S5+1 -> 4 | Y5: Lag to Development Completion | AC5: 1
J6: Phasing | AD6: Sale | AE6: Proceeds | AF6: Sale | AG6: =AE6 -> Proceeds
C7: ID | D7: Parcel# | E7: Use | F7: Acres | G7: DUA | H7: Product | I7: Units | J7: Develop | K7: Sale | O7: Start Month | Q7: 6 | R7: 18 | S7: 36 | T7: 60 | Y7: # | Z7: Parcel | AA7: Lots | AB7: Product | AC7: Acres | AD7: Phase | AE7: GROSS | AF7: Cost | AG7: NET
C8: 1 | D8: {=_xlfn._xlws.FILTER(tbl_Parcels[Parcel],tbl_Parcels[Village]=C4,0)} -> 3.23 | E8: =IFERROR(_xlfn.XLOOKUP(D8,tbl_Parcels[Parcel],tbl_Parcels[Use]),0) -> MLDR | F8: =IFERROR(LOOKUP(D8,tbl_Parcels[Parcel],tbl_Parcels[Acres]),0) -> 22.45 | G8: =IFERROR(LOOKUP('V3'!$H8,Table4[Product],Table4[DUA]),0) -> 3.4485 | H8: 60x120 | I8: =IFERROR(INT(LOOKUP('V3'!$H8,lst_LotProducts,lst_ProductDUA)*'V3'!$F8),0) -> 77 | J8: 1 | O8: Months to Complete | Q8: 12 | R8: 8 | S8: 10 | T8: 6 | Y8: 1 | Z8: {=_xlfn.UNIQUE(_xlfn._xlws.FILTER(D8:D32,D8:D32<>0))} -> 3.23 | AA8: =IFERROR(LOOKUP(Z8,$D$8:$D$32,$I$8:$I$32),0) -> 77 | AB8: =IFERROR(_xlfn.XLOOKUP($Z8,$D$8:$D$32,$H$8:$H$32),0) -> 60x120 | AC8: =IFERROR(_xlfn.XLOOKUP($Z8,$D$6:$D$30,$F$6:$F$30),0) -> 22.45 | AD8: 1
C9: 2 | D9: 3.24 | E9: =IFERROR(_xlfn.XLOOKUP(D9,tbl_Parcels[Parcel],tbl_Parcels[Use]),0) -> MLDR | F9: =IFERROR(LOOKUP(D9,tbl_Parcels[Parcel],tbl_Parcels[Acres]),0) -> 37.51 | G9: =IFERROR(LOOKUP('V3'!$H9,Table4[Product],Table4[DUA]),0) -> 3.31056 | H9: 60x125 | I9: =IFERROR(INT(LOOKUP('V3'!$H9,lst_LotProducts,lst_ProductDUA)*'V3'!$F9),0) -> 124 | J9: 1 | U9: Total | Y9: =Y8+1 -> 2 | Z9: 3.24 | AA9: =IFERROR(LOOKUP(Z9,$D$8:$D$32,$I$8:$I$32),0) -> 124 | AB9: =IFERROR(_xlfn.XLOOKUP($Z9,$D$8:$D$32,$H$8:$H$32),0) -> 60x125 | AC9: =IFERROR(_xlfn.XLOOKUP($Z9,$D$6:$D$30,$F$6:$F$30),0) -> 37.51 | AD9: 1
C10: 3 | D10: 3.25 | E10: =IFERROR(_xlfn.XLOOKUP(D10,tbl_Parcels[Parcel],tbl_Parcels[Use]),0) -> MLDR | F10: =IFERROR(LOOKUP(D10,tbl_Parcels[Parcel],tbl_Parcels[Acres]),0) -> 28.33 | G10: =IFERROR(LOOKUP('V3'!$H10,Table4[Product],Table4[DUA]),0) -> 5.016 | H10: 45x110 | I10: =IFERROR(INT(LOOKUP('V3'!$H10,lst_LotProducts,lst_ProductDUA)*'V3'!$F10),0) -> 142 | J10: 1 | O10: Acqusition | P10: a | Q10: 0 | R10: 0 | S10: 0 | T10: 0 | U10: =Q10+R10+S10+T10 -> 0 | Y10: =Y9+1 -> 3 | Z10: 3.25 | AA10: =IFERROR(LOOKUP(Z10,$D$8:$D$32,$I$8:$I$32),0) -> 142 | AB10: =IFERROR(_xlfn.XLOOKUP($Z10,$D$8:$D$32,$H$8:$H$32),0) -> 45x110 | AC10: =IFERROR(_xlfn.XLOOKUP($Z10,$D$6:$D$30,$F$6:$F$30),0) -> 28.33 | AD10: 1
C11: 4 | D11: 3.26 | E11: =IFERROR(_xlfn.XLOOKUP(D11,tbl_Parcels[Parcel],tbl_Parcels[Use]),0) -> MDR | F11: =IFERROR(LOOKUP(D11,tbl_Parcels[Parcel],tbl_Parcels[Acres]),0) -> 15.04 | G11: =IFERROR(LOOKUP('V3'!$H11,Table4[Product],Table4[DUA]),0) -> 5.016 | H11: 45x110 | I11: =IFERROR(INT(LOOKUP('V3'!$H11,lst_LotProducts,lst_ProductDUA)*'V3'!$F11),0) -> 75 | J11: 1 | M11: insert summary | O11: Entitlements | Q11: 5000000 | R11: 2500000 | S11: 1500000 | T11: 3000000 | U11: =Q11+R11+S11+T11 -> 12000000 | W11: insert summary | Y11: =Y10+1 -> 4 | Z11: 3.26 | AA11: =IFERROR(LOOKUP(Z11,$D$8:$D$32,$I$8:$I$32),0) -> 75 | AB11: =IFERROR(_xlfn.XLOOKUP($Z11,$D$8:$D$32,$H$8:$H$32),0) -> 45x110 | AC11: =IFERROR(_xlfn.XLOOKUP($Z11,$D$6:$D$30,$F$6:$F$30),0) -> 15.04 | AD11: 1
C12: 5 | D12: 3.27 | E12: =IFERROR(_xlfn.XLOOKUP(D12,tbl_Parcels[Parcel],tbl_Parcels[Use]),0) -> MDR | F12: =IFERROR(LOOKUP(D12,tbl_Parcels[Parcel],tbl_Parcels[Acres]),0) -> 24.04 | G12: =IFERROR(LOOKUP('V3'!$H12,Table4[Product],Table4[DUA]),0) -> 3.31056 | H12: 60x125 | I12: =IFERROR(INT(LOOKUP('V3'!$H12,lst_LotProducts,lst_ProductDUA)*'V3'!$F12),0) -> 79 | J12: 1 | M12: or charts here | O12: Engineering | Q12: 0 | R12: 0 | S12: 0 | T12: 0 | U12: =Q12+R12+S12+T12 -> 0 | W12: or charts here | Y12: =Y11+1 -> 5 | Z12: 3.27 | AA12: =IFERROR(LOOKUP(Z12,$D$8:$D$32,$I$8:$I$32),0) -> 79 | AB12: =IFERROR(_xlfn.XLOOKUP($Z12,$D$8:$D$32,$H$8:$H$32),0) -> 60x125 | AC12: =IFERROR(_xlfn.XLOOKUP($Z12,$D$6:$D$30,$F$6:$F$30),0) -> 24.04 | AD12: 1
C13: 6 | D13: 3.28 | E13: =IFERROR(_xlfn.XLOOKUP(D13,tbl_Parcels[Parcel],tbl_Parcels[Use]),0) -> MDR | F13: =IFERROR(LOOKUP(D13,tbl_Parcels[Parcel],tbl_Parcels[Acres]),0) -> 44.64 | G13: =IFERROR(LOOKUP('V3'!$H13,Table4[Product],Table4[DUA]),0) -> 3.972672 | H13: 50x125 | I13: =IFERROR(INT(LOOKUP('V3'!$H13,lst_LotProducts,lst_ProductDUA)*'V3'!$F13),0) -> 177 | J13: 1 | O13: Development > Offsite | Q13: 0 | R13: 0 | S13: 0 | T13: 0 | U13: =Q13+R13+S13+T13 -> 0 | Y13: =Y12+1 -> 6 | Z13: 3.28 | AA13: =IFERROR(LOOKUP(Z13,$D$8:$D$32,$I$8:$I$32),0) -> 177 | AB13: =IFERROR(_xlfn.XLOOKUP($Z13,$D$8:$D$32,$H$8:$H$32),0) -> 50x125 | AC13: =IFERROR(_xlfn.XLOOKUP($Z13,$D$6:$D$30,$F$6:$F$30),0) -> 44.64 | AD13: 1
C14: 7 | D14: 3.29 | E14: =IFERROR(_xlfn.XLOOKUP(D14,tbl_Parcels[Parcel],tbl_Parcels[Use]),0) -> MDR | F14: =IFERROR(LOOKUP(D14,tbl_Parcels[Parcel],tbl_Parcels[Acres]),0) -> 18.55 | G14: =IFERROR(LOOKUP('V3'!$H14,Table4[Product],Table4[DUA]),0) -> 4.598 | H14: 45x120 | I14: =IFERROR(INT(LOOKUP('V3'!$H14,lst_LotProducts,lst_ProductDUA)*'V3'!$F14),0) -> 85 | J14: 1 | O14: Development > OnSite | Q14: 0 | R14: 0 | S14: 0 | T14: 0 | U14: =Q14+R14+S14+T14 -> 0 | Y14: =Y13+1 -> 7 | Z14: 3.29 | AA14: =IFERROR(LOOKUP(Z14,$D$8:$D$32,$I$8:$I$32),0) -> 85 | AB14: =IFERROR(_xlfn.XLOOKUP($Z14,$D$8:$D$32,$H$8:$H$32),0) -> 45x120 | AC14: =IFERROR(_xlfn.XLOOKUP($Z14,$D$6:$D$30,$F$6:$F$30),0) -> 18.55 | AD14: 1
C15: 8 | D15: 3.30 | E15: =IFERROR(_xlfn.XLOOKUP(D15,tbl_Parcels[Parcel],tbl_Parcels[Use]),0) -> MDR | F15: =IFERROR(LOOKUP(D15,tbl_Parcels[Parcel],tbl_Parcels[Acres]),0) -> 25.21 | G15: =IFERROR(LOOKUP('V3'!$H15,Table4[Product],Table4[DUA]),0) -> 0 | I15: =IFERROR(INT(LOOKUP('V3'!$H15,lst_LotProducts,lst_ProductDUA)*'V3'!$F15),0) -> 0 | J15: 1 | O15: Development > Subdivision | Q15: 0 | R15: 0 | S15: 0 | T15: 0 | U15: =Q15+R15+S15+T15 -> 0 | Y15: =Y14+1 -> 8 | Z15: 3.30 | AA15: =IFERROR(LOOKUP(Z15,$D$8:$D$32,$I$8:$I$32),0) -> 0 | AB15: =IFERROR(_xlfn.XLOOKUP($Z15,$D$8:$D$32,$H$8:$H$32),0) -> 0 | AC15: =IFERROR(_xlfn.XLOOKUP($Z15,$D$6:$D$30,$F$6:$F$30),0) -> 25.21 | AD15: 2
C16: 9 | D16: 3.31 | E16: =IFERROR(_xlfn.XLOOKUP(D16,tbl_Parcels[Parcel],tbl_Parcels[Use]),0) -> MLDR | F16: =IFERROR(LOOKUP(D16,tbl_Parcels[Parcel],tbl_Parcels[Acres]),0) -> 32.4 | G16: =IFERROR(LOOKUP('V3'!$H16,Table4[Product],Table4[DUA]),0) -> 0 | I16: =IFERROR(INT(LOOKUP('V3'!$H16,lst_LotProducts,lst_ProductDUA)*'V3'!$F16),0) -> 0 | J16: 2 | O16: Development > Other | Q16: 0 | R16: 0 | S16: 0 | T16: 0 | U16: =Q16+R16+S16+T16 -> 0 | Y16: =Y15+1 -> 9 | Z16: 3.31 | AA16: =IFERROR(LOOKUP(Z16,$D$8:$D$32,$I$8:$I$32),0) -> 0 | AB16: =IFERROR(_xlfn.XLOOKUP($Z16,$D$8:$D$32,$H$8:$H$32),0) -> 0 | AC16: =IFERROR(_xlfn.XLOOKUP($Z16,$D$6:$D$30,$F$6:$F$30),0) -> 32.4 | AD16: 2
C17: 10 | D17: 3.32 | E17: =IFERROR(_xlfn.XLOOKUP(D17,tbl_Parcels[Parcel],tbl_Parcels[Use]),0) -> MLDR | F17: =IFERROR(LOOKUP(D17,tbl_Parcels[Parcel],tbl_Parcels[Acres]),0) -> 29.94 | G17: =IFERROR(LOOKUP('V3'!$H17,Table4[Product],Table4[DUA]),0) -> 0 | I17: =IFERROR(INT(LOOKUP('V3'!$H17,lst_LotProducts,lst_ProductDUA)*'V3'!$F17),0) -> 0 | J17: 2 | O17: Other | Q17: 0 | R17: 0 | S17: 0 | T17: 0 | U17: =Q17+R17+S17+T17 -> 0 | Y17: =Y16+1 -> 10 | Z17: 3.32 | AA17: =IFERROR(LOOKUP(Z17,$D$8:$D$32,$I$8:$I$32),0) -> 0 | AB17: =IFERROR(_xlfn.XLOOKUP($Z17,$D$8:$D$32,$H$8:$H$32),0) -> 0 | AC17: =IFERROR(_xlfn.XLOOKUP($Z17,$D$6:$D$30,$F$6:$F$30),0) -> 29.94 | AD17: 2
C18: 11 | D18: 3.33 | E18: =IFERROR(_xlfn.XLOOKUP(D18,tbl_Parcels[Parcel],tbl_Parcels[Use]),0) -> MDR | F18: =IFERROR(LOOKUP(D18,tbl_Parcels[Parcel],tbl_Parcels[Acres]),0) -> 29.31 | G18: =IFERROR(LOOKUP('V3'!$H18,Table4[Product],Table4[DUA]),0) -> 0 | I18: =IFERROR(INT(LOOKUP('V3'!$H18,lst_LotProducts,lst_ProductDUA)*'V3'!$F18),0) -> 0 | J18: 2 | Q18: 0 | R18: 0 | S18: 0 | T18: 0 | U18: =Q18+R18+S18+T18 -> 0 | Y18: =Y17+1 -> 11 | Z18: 3.33 | AA18: =IFERROR(LOOKUP(Z18,$D$8:$D$32,$I$8:$I$32),0) -> 0 | AB18: =IFERROR(_xlfn.XLOOKUP($Z18,$D$8:$D$32,$H$8:$H$32),0) -> 0 | AC18: =IFERROR(_xlfn.XLOOKUP($Z18,$D$6:$D$30,$F$6:$F$30),0) -> 29.31 | AD18: 2
C19: 12 | D19: 3.34 | E19: =IFERROR(_xlfn.XLOOKUP(D19,tbl_Parcels[Parcel],tbl_Parcels[Use]),0) -> MDR | F19: =IFERROR(LOOKUP(D19,tbl_Parcels[Parcel],tbl_Parcels[Acres]),0) -> 20.74 | G19: =IFERROR(LOOKUP('V3'!$H19,Table4[Product],Table4[DUA]),0) -> 0 | I19: =IFERROR(INT(LOOKUP('V3'!$H19,lst_LotProducts,lst_ProductDUA)*'V3'!$F19),0) -> 0 | J19: 2 | Q19: 0 | R19: 0 | S19: 0 | T19: 0 | U19: =Q19+R19+S19+T19 -> 0 | Y19: =Y18+1 -> 12 | Z19: 3.34 | AA19: =IFERROR(LOOKUP(Z19,$D$8:$D$32,$I$8:$I$32),0) -> 0 | AB19: =IFERROR(_xlfn.XLOOKUP($Z19,$D$8:$D$32,$H$8:$H$32),0) -> 0 | AC19: =IFERROR(_xlfn.XLOOKUP($Z19,$D$6:$D$30,$F$6:$F$30),0) -> 20.74 | AD19: 2
C20: 13 | E20: =IFERROR(_xlfn.XLOOKUP(D20,tbl_Parcels[Parcel],tbl_Parcels[Use]),0) -> 0 | F20: =IFERROR(LOOKUP(D20,tbl_Parcels[Parcel],tbl_Parcels[Acres]),0) -> 0 | G20: =IFERROR(LOOKUP('V3'!$H20,Table4[Product],Table4[DUA]),0) -> 0 | I20: =IFERROR(INT(LOOKUP('V3'!$H20,lst_LotProducts,lst_ProductDUA)*'V3'!$F20),0) -> 0 | J20: 2 | Q20: 0 | R20: 0 | S20: 0 | T20: 0 | U20: =Q20+R20+S20+T20 -> 0 | Y20: =Y19+1 -> 13 | AA20: =IFERROR(LOOKUP(Z20,$D$8:$D$32,$I$8:$I$32),0) -> 0 | AB20: =IFERROR(_xlfn.XLOOKUP($Z20,$D$8:$D$32,$H$8:$H$32),0) -> 0 | AC20: =IFERROR(_xlfn.XLOOKUP($Z20,$D$6:$D$30,$F$6:$F$30),0) -> 0 | AD20: 2
C21: 14 | E21: =IFERROR(_xlfn.XLOOKUP(D21,tbl_Parcels[Parcel],tbl_Parcels[Use]),0) -> 0 | F21: =IFERROR(LOOKUP(D21,tbl_Parcels[Parcel],tbl_Parcels[Acres]),0) -> 0 | G21: =IFERROR(LOOKUP('V3'!$H21,Table4[Product],Table4[DUA]),0) -> 0 | I21: =IFERROR(INT(LOOKUP('V3'!$H21,lst_LotProducts,lst_ProductDUA)*'V3'!$F21),0) -> 0 | J21: 2 | Q21: 0 | R21: 0 | S21: 0 | T21: 0 | U21: =Q21+R21+S21+T21 -> 0 | Y21: =Y20+1 -> 14 | AA21: =IFERROR(LOOKUP(Z21,$D$8:$D$32,$I$8:$I$32),0) -> 0 | AB21: =IFERROR(_xlfn.XLOOKUP($Z21,$D$8:$D$32,$H$8:$H$32),0) -> 0 | AC21: =IFERROR(_xlfn.XLOOKUP($Z21,$D$6:$D$30,$F$6:$F$30),0) -> 0 | AD21: 2
C22: 15 | E22: =IFERROR(_xlfn.XLOOKUP(D22,tbl_Parcels[Parcel],tbl_Parcels[Use]),0) -> 0 | F22: =IFERROR(LOOKUP(D22,tbl_Parcels[Parcel],tbl_Parcels[Acres]),0) -> 0 | G22: =IFERROR(LOOKUP('V3'!$H22,Table4[Product],Table4[DUA]),0) -> 0 | I22: =IFERROR(INT(LOOKUP('V3'!$H22,lst_LotProducts,lst_ProductDUA)*'V3'!$F22),0) -> 0 | Q22: 0 | R22: 0 | S22: 0 | T22: 0 | U22: =Q22+R22+S22+T22 -> 0 | Y22: =Y21+1 -> 15 | AA22: =IFERROR(LOOKUP(Z22,$D$8:$D$32,$I$8:$I$32),0) -> 0 | AB22: =IFERROR(_xlfn.XLOOKUP($Z22,$D$8:$D$32,$H$8:$H$32),0) -> 0 | AC22: =IFERROR(_xlfn.XLOOKUP($Z22,$D$6:$D$30,$F$6:$F$30),0) -> 0 | AD22: 2
C23: 16 | E23: =IFERROR(_xlfn.XLOOKUP(D23,tbl_Parcels[Parcel],tbl_Parcels[Use]),0) -> 0 | F23: =IFERROR(LOOKUP(D23,tbl_Parcels[Parcel],tbl_Parcels[Acres]),0) -> 0 | G23: =IFERROR(LOOKUP('V3'!$H23,Table4[Product],Table4[DUA]),0) -> 0 | I23: =IFERROR(INT(LOOKUP('V3'!$H23,lst_LotProducts,lst_ProductDUA)*'V3'!$F23),0) -> 0 | Q23: 0 | R23: 0 | S23: 0 | T23: 0 | U23: =Q23+R23+S23+T23 -> 0 | Y23: =Y22+1 -> 16 | AA23: =IFERROR(LOOKUP(Z23,$D$8:$D$32,$I$8:$I$32),0) -> 0 | AB23: =IFERROR(_xlfn.XLOOKUP($Z23,$D$8:$D$32,$H$8:$H$32),0) -> 0 | AC23: =IFERROR(_xlfn.XLOOKUP($Z23,$D$6:$D$30,$F$6:$F$30),0) -> 0
C24: 17 | E24: =IFERROR(_xlfn.XLOOKUP(D24,tbl_Parcels[Parcel],tbl_Parcels[Use]),0) -> 0 | F24: =IFERROR(LOOKUP(D24,tbl_Parcels[Parcel],tbl_Parcels[Acres]),0) -> 0 | G24: =IFERROR(LOOKUP('V3'!$H24,Table4[Product],Table4[DUA]),0) -> 0 | I24: =IFERROR(INT(LOOKUP('V3'!$H24,lst_LotProducts,lst_ProductDUA)*'V3'!$F24),0) -> 0 | Q24: 0 | R24: 0 | S24: 0 | T24: 0 | U24: =Q24+R24+S24+T24 -> 0 | Y24: =Y23+1 -> 17 | AA24: =IFERROR(LOOKUP(Z24,$D$8:$D$32,$I$8:$I$32),0) -> 0 | AB24: =IFERROR(_xlfn.XLOOKUP($Z24,$D$8:$D$32,$H$8:$H$32),0) -> 0 | AC24: =IFERROR(_xlfn.XLOOKUP($Z24,$D$6:$D$30,$F$6:$F$30),0) -> 0
C25: 18 | E25: =IFERROR(_xlfn.XLOOKUP(D25,tbl_Parcels[Parcel],tbl_Parcels[Use]),0) -> 0 | F25: =IFERROR(LOOKUP(D25,tbl_Parcels[Parcel],tbl_Parcels[Acres]),0) -> 0 | G25: =IFERROR(LOOKUP('V3'!$H25,Table4[Product],Table4[DUA]),0) -> 0 | I25: =IFERROR(INT(LOOKUP('V3'!$H25,lst_LotProducts,lst_ProductDUA)*'V3'!$F25),0) -> 0 | Q25: 0 | R25: 0 | S25: 0 | T25: 0 | U25: =Q25+R25+S25+T25 -> 0 | Y25: =Y24+1 -> 18 | AA25: =IFERROR(LOOKUP(Z25,$D$8:$D$32,$I$8:$I$32),0) -> 0 | AB25: =IFERROR(_xlfn.XLOOKUP($Z25,$D$8:$D$32,$H$8:$H$32),0) -> 0 | AC25: =IFERROR(_xlfn.XLOOKUP($Z25,$D$6:$D$30,$F$6:$F$30),0) -> 0
C26: 19 | E26: =IFERROR(_xlfn.XLOOKUP(D26,tbl_Parcels[Parcel],tbl_Parcels[Use]),0) -> 0 | F26: =IFERROR(LOOKUP(D26,tbl_Parcels[Parcel],tbl_Parcels[Acres]),0) -> 0 | G26: =IFERROR(LOOKUP('V3'!$H26,Table4[Product],Table4[DUA]),0) -> 0 | I26: =IFERROR(INT(LOOKUP('V3'!$H26,lst_LotProducts,lst_ProductDUA)*'V3'!$F26),0) -> 0 | Q26: 0 | R26: 0 | S26: 0 | T26: 0 | U26: =Q26+R26+S26+T26 -> 0 | Y26: =Y25+1 -> 19 | AA26: =IFERROR(LOOKUP(Z26,$D$8:$D$32,$I$8:$I$32),0) -> 0 | AB26: =IFERROR(_xlfn.XLOOKUP($Z26,$D$8:$D$32,$H$8:$H$32),0) -> 0 | AC26: =IFERROR(_xlfn.XLOOKUP($Z26,$D$6:$D$30,$F$6:$F$30),0) -> 0
C27: 20 | E27: =IFERROR(_xlfn.XLOOKUP(D27,tbl_Parcels[Parcel],tbl_Parcels[Use]),0) -> 0 | F27: =IFERROR(LOOKUP(D27,tbl_Parcels[Parcel],tbl_Parcels[Acres]),0) -> 0 | G27: =IFERROR(LOOKUP('V3'!$H27,Table4[Product],Table4[DUA]),0) -> 0 | I27: =IFERROR(INT(LOOKUP('V3'!$H27,lst_LotProducts,lst_ProductDUA)*'V3'!$F27),0) -> 0 | Q27: 0 | R27: 0 | S27: 0 | T27: 0 | U27: =Q27+R27+S27+T27 -> 0 | Y27: =Y26+1 -> 20 | AA27: =IFERROR(LOOKUP(Z27,$D$8:$D$32,$I$8:$I$32),0) -> 0 | AB27: =IFERROR(_xlfn.XLOOKUP($Z27,$D$8:$D$32,$H$8:$H$32),0) -> 0 | AC27: =IFERROR(_xlfn.XLOOKUP($Z27,$D$6:$D$30,$F$6:$F$30),0) -> 0
C28: 21 | E28: =IFERROR(_xlfn.XLOOKUP(D28,tbl_Parcels[Parcel],tbl_Parcels[Use]),0) -> 0 | F28: =IFERROR(LOOKUP(D28,tbl_Parcels[Parcel],tbl_Parcels[Acres]),0) -> 0 | G28: =IFERROR(LOOKUP('V3'!$H28,Table4[Product],Table4[DUA]),0) -> 0 | I28: =IFERROR(INT(LOOKUP('V3'!$H28,lst_LotProducts,lst_ProductDUA)*'V3'!$F28),0) -> 0 | Q28: 0 | R28: 0 | S28: 0 | T28: 0 | U28: =Q28+R28+S28+T28 -> 0 | Y28: =Y27+1 -> 21 | AA28: =IFERROR(LOOKUP(Z28,$D$8:$D$32,$I$8:$I$32),0) -> 0 | AB28: =IFERROR(_xlfn.XLOOKUP($Z28,$D$8:$D$32,$H$8:$H$32),0) -> 0 | AC28: =IFERROR(_xlfn.XLOOKUP($Z28,$D$6:$D$30,$F$6:$F$30),0) -> 0
C29: 22 | E29: =IFERROR(_xlfn.XLOOKUP(D29,tbl_Parcels[Parcel],tbl_Parcels[Use]),0) -> 0 | F29: =IFERROR(LOOKUP(D29,tbl_Parcels[Parcel],tbl_Parcels[Acres]),0) -> 0 | G29: =IFERROR(LOOKUP('V3'!$H29,Table4[Product],Table4[DUA]),0) -> 0 | I29: =IFERROR(INT(LOOKUP('V3'!$H29,lst_LotProducts,lst_ProductDUA)*'V3'!$F29),0) -> 0 | Q29: 0 | R29: 0 | S29: 0 | T29: 0 | U29: =Q29+R29+S29+T29 -> 0 | Y29: =Y28+1 -> 22 | AA29: =IFERROR(LOOKUP(Z29,$D$8:$D$32,$I$8:$I$32),0) -> 0 | AB29: =IFERROR(_xlfn.XLOOKUP($Z29,$D$8:$D$32,$H$8:$H$32),0) -> 0 | AC29: =IFERROR(_xlfn.XLOOKUP($Z29,$D$6:$D$30,$F$6:$F$30),0) -> 0
C30: 23 | E30: =IFERROR(_xlfn.XLOOKUP(D30,tbl_Parcels[Parcel],tbl_Parcels[Use]),0) -> 0 | F30: =IFERROR(LOOKUP(D30,tbl_Parcels[Parcel],tbl_Parcels[Acres]),0) -> 0 | G30: =IFERROR(LOOKUP('V3'!$H30,Table4[Product],Table4[DUA]),0) -> 0 | I30: =IFERROR(INT(LOOKUP('V3'!$H30,lst_LotProducts,lst_ProductDUA)*'V3'!$F30),0) -> 0 | Q30: 0 | R30: 0 | S30: 0 | T30: 0 | U30: =Q30+R30+S30+T30 -> 0 | Y30: =Y29+1 -> 23 | AA30: =IFERROR(LOOKUP(Z30,$D$8:$D$32,$I$8:$I$32),0) -> 0 | AB30: =IFERROR(_xlfn.XLOOKUP($Z30,$D$8:$D$32,$H$8:$H$32),0) -> 0 | AC30: =IFERROR(_xlfn.XLOOKUP($Z30,$D$6:$D$30,$F$6:$F$30),0) -> 0
C31: 24 | E31: =IFERROR(_xlfn.XLOOKUP(D31,tbl_Parcels[Parcel],tbl_Parcels[Use]),0) -> 0 | F31: =IFERROR(LOOKUP(D31,tbl_Parcels[Parcel],tbl_Parcels[Acres]),0) -> 0 | G31: =IFERROR(LOOKUP('V3'!$H31,Table4[Product],Table4[DUA]),0) -> 0 | I31: =IFERROR(INT(LOOKUP('V3'!$H31,lst_LotProducts,lst_ProductDUA)*'V3'!$F31),0) -> 0 | Q31: 0 | R31: 0 | S31: 0 | T31: 0 | U31: =Q31+R31+S31+T31 -> 0 | Y31: =Y30+1 -> 24 | AA31: =IFERROR(LOOKUP(Z31,$D$8:$D$32,$I$8:$I$32),0) -> 0 | AB31: =IFERROR(_xlfn.XLOOKUP($Z31,$D$8:$D$32,$H$8:$H$32),0) -> 0 | AC31: =IFERROR(_xlfn.XLOOKUP($Z31,$D$6:$D$30,$F$6:$F$30),0) -> 0
C32: 25 | E32: =IFERROR(_xlfn.XLOOKUP(D32,tbl_Parcels[Parcel],tbl_Parcels[Use]),0) -> 0 | F32: =IFERROR(LOOKUP(D32,tbl_Parcels[Parcel],tbl_Parcels[Acres]),0) -> 0 | G32: =IFERROR(LOOKUP('V3'!$H32,Table4[Product],Table4[DUA]),0) -> 0 | I32: =IFERROR(INT(LOOKUP('V3'!$H32,lst_LotProducts,lst_ProductDUA)*'V3'!$F32),0) -> 0 | P32: Total | Q32: =SUM(Q10:Q31) -> 5000000 | R32: =SUM(R10:R31) -> 2500000 | S32: =SUM(S10:S31) -> 1500000 | T32: =SUM(T10:T31) -> 3000000 | U32: =Q32+R32+S32+T32 -> 12000000 | Y32: =Y31+1 -> 25 | AA32: =IFERROR(LOOKUP(Z32,$D$8:$D$32,$I$8:$I$32),0) -> 0 | AB32: =IFERROR(_xlfn.XLOOKUP($Z32,$D$8:$D$32,$H$8:$H$32),0) -> 0 | AC32: =IFERROR(_xlfn.XLOOKUP($Z32,$D$6:$D$30,$F$6:$F$30),0) -> 0

Sheet V4
C4: 4 | F4: ='iV1'!F4 -> Parcel Land Use & Lot Product | O4: =C4 -> 4 | Q4: Development Phasing | Y4: =O4 -> 4 | AB4: Sale Schedule | AC4: Sale Schedule
Q5: 1 | R5: =Q5+1 -> 2 | S5: =R5+1 -> 3 | T5: =S5+1 -> 4 | Y5: Lag to Development Completion | AC5: 1
J6: Phasing | O6: Start Month | Q6: 6 | R6: 18 | S6: 36 | T6: 60 | AD6: Sale | AE6: Proceeds | AF6: Sale | AG6: =AE6 -> Proceeds
C7: ID | D7: Parcel# | E7: Use | F7: Acres | G7: DUA | H7: Product | I7: Units | J7: Develop | K7: Sale | O7: Months to Complete | Q7: 12 | R7: 8 | S7: 10 | T7: 6 | Y7: # | Z7: Parcel | AA7: Lots | AB7: Product | AC7: Acres | AD7: Phase | AE7: GROSS | AF7: Cost | AG7: NET
C8: 1 | D8: {=_xlfn._xlws.FILTER(tbl_Parcels[Parcel],tbl_Parcels[Village]=C4,0)} -> 4.35 | E8: =IFERROR(_xlfn.XLOOKUP(D8,tbl_Parcels[Parcel],tbl_Parcels[Use]),0) -> MU | F8: =IFERROR(LOOKUP(D8,tbl_Parcels[Parcel],tbl_Parcels[Acres]),0) -> 14.85 | G8: =IFERROR(LOOKUP('V4'!$H8,Table4[Product],Table4[DUA]),0) -> 3.4485 | H8: 60x120 | I8: =IFERROR(INT(LOOKUP('V4'!$H8,lst_LotProducts,lst_ProductDUA)*'V4'!$F8),0) -> 51 | J8: 1 | O8: Thru Month | Q8: =Q6+Q7-1 -> 17 | R8: =R6+R7-1 -> 25 | S8: =S6+S7-1 -> 45 | T8: =T6+T7-1 -> 65 | Y8: 1 | Z8: {=_xlfn.UNIQUE(_xlfn._xlws.FILTER(D8:D32,D8:D32<>0))} -> 4.35 | AA8: =IFERROR(LOOKUP(Z8,$D$8:$D$32,$I$8:$I$32),0) -> 51 | AB8: =IFERROR(_xlfn.XLOOKUP($Z8,$D$8:$D$32,$H$8:$H$32),0) -> 60x120 | AC8: =IFERROR(_xlfn.XLOOKUP($Z8,$D$6:$D$30,$F$6:$F$30),0) -> 14.85 | AD8: 1
C9: 2 | D9: 4.36 | E9: =IFERROR(_xlfn.XLOOKUP(D9,tbl_Parcels[Parcel],tbl_Parcels[Use]),0) -> MDR | F9: =IFERROR(LOOKUP(D9,tbl_Parcels[Parcel],tbl_Parcels[Acres]),0) -> 30.25 | G9: =IFERROR(LOOKUP('V4'!$H9,Table4[Product],Table4[DUA]),0) -> 3.31056 | H9: 60x125 | I9: =IFERROR(INT(LOOKUP('V4'!$H9,lst_LotProducts,lst_ProductDUA)*'V4'!$F9),0) -> 100 | J9: 1 | U9: Total | Y9: =Y8+1 -> 2 | Z9: 4.36 | AA9: =IFERROR(LOOKUP(Z9,$D$8:$D$32,$I$8:$I$32),0) -> 100 | AB9: =IFERROR(_xlfn.XLOOKUP($Z9,$D$8:$D$32,$H$8:$H$32),0) -> 60x125 | AC9: =IFERROR(_xlfn.XLOOKUP($Z9,$D$6:$D$30,$F$6:$F$30),0) -> 30.25 | AD9: 1
C10: 3 | D10: 4.37 | E10: =IFERROR(_xlfn.XLOOKUP(D10,tbl_Parcels[Parcel],tbl_Parcels[Use]),0) -> MLDR | F10: =IFERROR(LOOKUP(D10,tbl_Parcels[Parcel],tbl_Parcels[Acres]),0) -> 27.96 | G10: =IFERROR(LOOKUP('V4'!$H10,Table4[Product],Table4[DUA]),0) -> 5.016 | H10: 45x110 | I10: =IFERROR(INT(LOOKUP('V4'!$H10,lst_LotProducts,lst_ProductDUA)*'V4'!$F10),0) -> 140 | J10: 1 | O10: Acqusition | P10: a | Q10: 0 | R10: 0 | S10: 0 | T10: 0 | U10: =Q10+R10+S10+T10 -> 0 | Y10: =Y9+1 -> 3 | Z10: 4.37 | AA10: =IFERROR(LOOKUP(Z10,$D$8:$D$32,$I$8:$I$32),0) -> 140 | AB10: =IFERROR(_xlfn.XLOOKUP($Z10,$D$8:$D$32,$H$8:$H$32),0) -> 45x110 | AC10: =IFERROR(_xlfn.XLOOKUP($Z10,$D$6:$D$30,$F$6:$F$30),0) -> 27.96 | AD10: 1
C11: 4 | D11: 4.38 | E11: =IFERROR(_xlfn.XLOOKUP(D11,tbl_Parcels[Parcel],tbl_Parcels[Use]),0) -> MU | F11: =IFERROR(LOOKUP(D11,tbl_Parcels[Parcel],tbl_Parcels[Acres]),0) -> 36.72 | G11: =IFERROR(LOOKUP('V4'!$H11,Table4[Product],Table4[DUA]),0) -> 5.016 | H11: 45x110 | I11: =IFERROR(INT(LOOKUP('V4'!$H11,lst_LotProducts,lst_ProductDUA)*'V4'!$F11),0) -> 184 | J11: 1 | M11: insert summary | O11: Entitlements | Q11: 500000 | R11: 100000 | S11: 50000 | T11: 50000 | U11: =Q11+R11+S11+T11 -> 700000 | W11: insert summary | Y11: =Y10+1 -> 4 | Z11: 4.38 | AA11: =IFERROR(LOOKUP(Z11,$D$8:$D$32,$I$8:$I$32),0) -> 184 | AB11: =IFERROR(_xlfn.XLOOKUP($Z11,$D$8:$D$32,$H$8:$H$32),0) -> 45x110 | AC11: =IFERROR(_xlfn.XLOOKUP($Z11,$D$6:$D$30,$F$6:$F$30),0) -> 36.72 | AD11: 1
C12: 5 | D12: 4.39 | E12: =IFERROR(_xlfn.XLOOKUP(D12,tbl_Parcels[Parcel],tbl_Parcels[Use]),0) -> MDR | F12: =IFERROR(LOOKUP(D12,tbl_Parcels[Parcel],tbl_Parcels[Acres]),0) -> 28.29 | G12: =IFERROR(LOOKUP('V4'!$H12,Table4[Product],Table4[DUA]),0) -> 3.31056 | H12: 60x125 | I12: =IFERROR(INT(LOOKUP('V4'!$H12,lst_LotProducts,lst_ProductDUA)*'V4'!$F12),0) -> 93 | J12: 1 | M12: or charts here | O12: Engineering | Q12: 2500000 | R12: 500000 | S12: 100000 | T12: 100000 | U12: =Q12+R12+S12+T12 -> 3200000 | W12: or charts here | Y12: =Y11+1 -> 5 | Z12: 4.39 | AA12: =IFERROR(LOOKUP(Z12,$D$8:$D$32,$I$8:$I$32),0) -> 93 | AB12: =IFERROR(_xlfn.XLOOKUP($Z12,$D$8:$D$32,$H$8:$H$32),0) -> 60x125 | AC12: =IFERROR(_xlfn.XLOOKUP($Z12,$D$6:$D$30,$F$6:$F$30),0) -> 28.29 | AD12: 1
C13: 6 | D13: 4.40 | E13: =IFERROR(_xlfn.XLOOKUP(D13,tbl_Parcels[Parcel],tbl_Parcels[Use]),0) -> MDR | F13: =IFERROR(LOOKUP(D13,tbl_Parcels[Parcel],tbl_Parcels[Acres]),0) -> 49.27 | G13: =IFERROR(LOOKUP('V4'!$H13,Table4[Product],Table4[DUA]),0) -> 3.972672 | H13: 50x125 | I13: =IFERROR(INT(LOOKUP('V4'!$H13,lst_LotProducts,lst_ProductDUA)*'V4'!$F13),0) -> 195 | J13: 1 | O13: Development > Offsite | Q13: 2500000 | R13: 0 | S13: 0 | T13: 0 | U13: =Q13+R13+S13+T13 -> 2500000 | Y13: =Y12+1 -> 6 | Z13: 4.40 | AA13: =IFERROR(LOOKUP(Z13,$D$8:$D$32,$I$8:$I$32),0) -> 195 | AB13: =IFERROR(_xlfn.XLOOKUP($Z13,$D$8:$D$32,$H$8:$H$32),0) -> 50x125 | AC13: =IFERROR(_xlfn.XLOOKUP($Z13,$D$6:$D$30,$F$6:$F$30),0) -> 49.27 | AD13: 2
C14: 7 | D14: 4.41 | E14: =IFERROR(_xlfn.XLOOKUP(D14,tbl_Parcels[Parcel],tbl_Parcels[Use]),0) -> MDR | F14: =IFERROR(LOOKUP(D14,tbl_Parcels[Parcel],tbl_Parcels[Acres]),0) -> 34.13 | G14: =IFERROR(LOOKUP('V4'!$H14,Table4[Product],Table4[DUA]),0) -> 4.598 | H14: 45x120 | I14: =IFERROR(INT(LOOKUP('V4'!$H14,lst_LotProducts,lst_ProductDUA)*'V4'!$F14),0) -> 156 | J14: 1 | O14: Development > OnSite | Q14: 5000000 | R14: 3000000 | S14: 3000000 | T14: 3000000 | U14: =Q14+R14+S14+T14 -> 14000000 | Y14: =Y13+1 -> 7 | Z14: 4.41 | AA14: =IFERROR(LOOKUP(Z14,$D$8:$D$32,$I$8:$I$32),0) -> 156 | AB14: =IFERROR(_xlfn.XLOOKUP($Z14,$D$8:$D$32,$H$8:$H$32),0) -> 45x120 | AC14: =IFERROR(_xlfn.XLOOKUP($Z14,$D$6:$D$30,$F$6:$F$30),0) -> 34.13 | AD14: 2
C15: 8 | D15: 4.42 | E15: =IFERROR(_xlfn.XLOOKUP(D15,tbl_Parcels[Parcel],tbl_Parcels[Use]),0) -> MU | F15: =IFERROR(LOOKUP(D15,tbl_Parcels[Parcel],tbl_Parcels[Acres]),0) -> 5.91 | G15: =IFERROR(LOOKUP('V4'!$H15,Table4[Product],Table4[DUA]),0) -> 0 | I15: =IFERROR(INT(LOOKUP('V4'!$H15,lst_LotProducts,lst_ProductDUA)*'V4'!$F15),0) -> 0 | J15: 1 | O15: Development > Subdivision | Q15: 15000000 | R15: 15000000 | S15: 12000000 | T15: 5000000 | U15: =Q15+R15+S15+T15 -> 47000000 | Y15: =Y14+1 -> 8 | Z15: 4.42 | AA15: =IFERROR(LOOKUP(Z15,$D$8:$D$32,$I$8:$I$32),0) -> 0 | AB15: =IFERROR(_xlfn.XLOOKUP($Z15,$D$8:$D$32,$H$8:$H$32),0) -> 0 | AC15: =IFERROR(_xlfn.XLOOKUP($Z15,$D$6:$D$30,$F$6:$F$30),0) -> 5.91 | AD15: 2
C16: 9 | D16: 4.43 | E16: =IFERROR(_xlfn.XLOOKUP(D16,tbl_Parcels[Parcel],tbl_Parcels[Use]),0) -> MDR | F16: =IFERROR(LOOKUP(D16,tbl_Parcels[Parcel],tbl_Parcels[Acres]),0) -> 33.72 | G16: =IFERROR(LOOKUP('V4'!$H16,Table4[Product],Table4[DUA]),0) -> 0 | I16: =IFERROR(INT(LOOKUP('V4'!$H16,lst_LotProducts,lst_ProductDUA)*'V4'!$F16),0) -> 0 | J16: 2 | O16: Development > Other | Q16: 2500000 | R16: 1000000 | S16: 500000 | T16: 500000 | U16: =Q16+R16+S16+T16 -> 4500000 | Y16: =Y15+1 -> 9 | Z16: 4.43 | AA16: =IFERROR(LOOKUP(Z16,$D$8:$D$32,$I$8:$I$32),0) -> 0 | AB16: =IFERROR(_xlfn.XLOOKUP($Z16,$D$8:$D$32,$H$8:$H$32),0) -> 0 | AC16: =IFERROR(_xlfn.XLOOKUP($Z16,$D$6:$D$30,$F$6:$F$30),0) -> 33.72 | AD16: 2
C17: 10 | D17: 4.44 | E17: =IFERROR(_xlfn.XLOOKUP(D17,tbl_Parcels[Parcel],tbl_Parcels[Use]),0) -> MDR | F17: =IFERROR(LOOKUP(D17,tbl_Parcels[Parcel],tbl_Parcels[Acres]),0) -> 41.4 | G17: =IFERROR(LOOKUP('V4'!$H17,Table4[Product],Table4[DUA]),0) -> 0 | I17: =IFERROR(INT(LOOKUP('V4'!$H17,lst_LotProducts,lst_ProductDUA)*'V4'!$F17),0) -> 0 | J17: 2 | O17: Other | Q17: 0 | R17: 0 | S17: 0 | T17: 0 | U17: =Q17+R17+S17+T17 -> 0 | Y17: =Y16+1 -> 10 | Z17: 4.44 | AA17: =IFERROR(LOOKUP(Z17,$D$8:$D$32,$I$8:$I$32),0) -> 0 | AB17: =IFERROR(_xlfn.XLOOKUP($Z17,$D$8:$D$32,$H$8:$H$32),0) -> 0 | AC17: =IFERROR(_xlfn.XLOOKUP($Z17,$D$6:$D$30,$F$6:$F$30),0) -> 41.4 | AD17: 3
C18: 11 | D18: 4.45 | E18: =IFERROR(_xlfn.XLOOKUP(D18,tbl_Parcels[Parcel],tbl_Parcels[Use]),0) -> MLDR | F18: =IFERROR(LOOKUP(D18,tbl_Parcels[Parcel],tbl_Parcels[Acres]),0) -> 26.71 | G18: =IFERROR(LOOKUP('V4'!$H18,Table4[Product],Table4[DUA]),0) -> 0 | I18: =IFERROR(INT(LOOKUP('V4'!$H18,lst_LotProducts,lst_ProductDUA)*'V4'!$F18),0) -> 0 | J18: 2 | Q18: 0 | R18: 0 | S18: 0 | T18: 0 | U18: =Q18+R18+S18+T18 -> 0 | Y18: =Y17+1 -> 11 | Z18: 4.45 | AA18: =IFERROR(LOOKUP(Z18,$D$8:$D$32,$I$8:$I$32),0) -> 0 | AB18: =IFERROR(_xlfn.XLOOKUP($Z18,$D$8:$D$32,$H$8:$H$32),0) -> 0 | AC18: =IFERROR(_xlfn.XLOOKUP($Z18,$D$6:$D$30,$F$6:$F$30),0) -> 26.71 | AD18: 3
C19: 12 | D19: 4.46 | E19: =IFERROR(_xlfn.XLOOKUP(D19,tbl_Parcels[Parcel],tbl_Parcels[Use]),0) -> MLDR | F19: =IFERROR(LOOKUP(D19,tbl_Parcels[Parcel],tbl_Parcels[Acres]),0) -> 20.97 | G19: =IFERROR(LOOKUP('V4'!$H19,Table4[Product],Table4[DUA]),0) -> 0 | I19: =IFERROR(INT(LOOKUP('V4'!$H19,lst_LotProducts,lst_ProductDUA)*'V4'!$F19),0) -> 0 | J19: 2 | Q19: 0 | R19: 0 | S19: 0 | T19: 0 | U19: =Q19+R19+S19+T19 -> 0 | Y19: =Y18+1 -> 12 | Z19: 4.46 | AA19: =IFERROR(LOOKUP(Z19,$D$8:$D$32,$I$8:$I$32),0) -> 0 | AB19: =IFERROR(_xlfn.XLOOKUP($Z19,$D$8:$D$32,$H$8:$H$32),0) -> 0 | AC19: =IFERROR(_xlfn.XLOOKUP($Z19,$D$6:$D$30,$F$6:$F$30),0) -> 20.97 | AD19: 3
C20: 13 | D20: 4.47 | E20: =IFERROR(_xlfn.XLOOKUP(D20,tbl_Parcels[Parcel],tbl_Parcels[Use]),0) -> MDR | F20: =IFERROR(LOOKUP(D20,tbl_Parcels[Parcel],tbl_Parcels[Acres]),0) -> 24.38 | G20: =IFERROR(LOOKUP('V4'!$H20,Table4[Product],Table4[DUA]),0) -> 0 | I20: =IFERROR(INT(LOOKUP('V4'!$H20,lst_LotProducts,lst_ProductDUA)*'V4'!$F20),0) -> 0 | J20: 2 | Q20: 0 | R20: 0 | S20: 0 | T20: 0 | U20: =Q20+R20+S20+T20 -> 0 | Y20: =Y19+1 -> 13 | Z20: 4.47 | AA20: =IFERROR(LOOKUP(Z20,$D$8:$D$32,$I$8:$I$32),0) -> 0 | AB20: =IFERROR(_xlfn.XLOOKUP($Z20,$D$8:$D$32,$H$8:$H$32),0) -> 0 | AC20: =IFERROR(_xlfn.XLOOKUP($Z20,$D$6:$D$30,$F$6:$F$30),0) -> 24.38 | AD20: 4
C21: 14 | D21: 4.48 | E21: =IFERROR(_xlfn.XLOOKUP(D21,tbl_Parcels[Parcel],tbl_Parcels[Use]),0) -> MU | F21: =IFERROR(LOOKUP(D21,tbl_Parcels[Parcel],tbl_Parcels[Acres]),0) -> 14.47 | G21: =IFERROR(LOOKUP('V4'!$H21,Table4[Product],Table4[DUA]),0) -> 0 | I21: =IFERROR(INT(LOOKUP('V4'!$H21,lst_LotProducts,lst_ProductDUA)*'V4'!$F21),0) -> 0 | J21: 2 | Q21: 0 | R21: 0 | S21: 0 | T21: 0 | U21: =Q21+R21+S21+T21 -> 0 | Y21: =Y20+1 -> 14 | Z21: 4.48 | AA21: =IFERROR(LOOKUP(Z21,$D$8:$D$32,$I$8:$I$32),0) -> 0 | AB21: =IFERROR(_xlfn.XLOOKUP($Z21,$D$8:$D$32,$H$8:$H$32),0) -> 0 | AC21: =IFERROR(_xlfn.XLOOKUP($Z21,$D$6:$D$30,$F$6:$F$30),0) -> 14.47 | AD21: 4
C22: 15 | E22: =IFERROR(_xlfn.XLOOKUP(D22,tbl_Parcels[Parcel],tbl_Parcels[Use]),0) -> 0 | F22: =IFERROR(LOOKUP(D22,tbl_Parcels[Parcel],tbl_Parcels[Acres]),0) -> 0 | G22: =IFERROR(LOOKUP('V4'!$H22,Table4[Product],Table4[DUA]),0) -> 0 | I22: =IFERROR(INT(LOOKUP('V4'!$H22,lst_LotProducts,lst_ProductDUA)*'V4'!$F22),0) -> 0 | Q22: 0 | R22: 0 | S22: 0 | T22: 0 | U22: =Q22+R22+S22+T22 -> 0 | Y22: =Y21+1 -> 15 | AA22: =IFERROR(LOOKUP(Z22,$D$8:$D$32,$I$8:$I$32),0) -> 0 | AB22: =IFERROR(_xlfn.XLOOKUP($Z22,$D$8:$D$32,$H$8:$H$32),0) -> 0 | AC22: =IFERROR(_xlfn.XLOOKUP($Z22,$D$6:$D$30,$F$6:$F$30),0) -> 0
C23: 16 | E23: =IFERROR(_xlfn.XLOOKUP(D23,tbl_Parcels[Parcel],tbl_Parcels[Use]),0) -> 0 | F23: =IFERROR(LOOKUP(D23,tbl_Parcels[Parcel],tbl_Parcels[Acres]),0) -> 0 | G23: =IFERROR(LOOKUP('V4'!$H23,Table4[Product],Table4[DUA]),0) -> 0 | I23: =IFERROR(INT(LOOKUP('V4'!$H23,lst_LotProducts,lst_ProductDUA)*'V4'!$F23),0) -> 0 | Q23: 0 | R23: 0 | S23: 0 | T23: 0 | U23: =Q23+R23+S23+T23 -> 0 | Y23: =Y22+1 -> 16 | AA23: =IFERROR(LOOKUP(Z23,$D$8:$D$32,$I$8:$I$32),0) -> 0 | AB23: =IFERROR(_xlfn.XLOOKUP($Z23,$D$8:$D$32,$H$8:$H$32),0) -> 0 | AC23: =IFERROR(_xlfn.XLOOKUP($Z23,$D$6:$D$30,$F$6:$F$30),0) -> 0
C24: 17 | E24: =IFERROR(_xlfn.XLOOKUP(D24,tbl_Parcels[Parcel],tbl_Parcels[Use]),0) -> 0 | F24: =IFERROR(LOOKUP(D24,tbl_Parcels[Parcel],tbl_Parcels[Acres]),0) -> 0 | G24: =IFERROR(LOOKUP('V4'!$H24,Table4[Product],Table4[DUA]),0) -> 0 | I24: =IFERROR(INT(LOOKUP('V4'!$H24,lst_LotProducts,lst_ProductDUA)*'V4'!$F24),0) -> 0 | Q24: 0 | R24: 0 | S24: 0 | T24: 0 | U24: =Q24+R24+S24+T24 -> 0 | Y24: =Y23+1 -> 17 | AA24: =IFERROR(LOOKUP(Z24,$D$8:$D$32,$I$8:$I$32),0) -> 0 | AB24: =IFERROR(_xlfn.XLOOKUP($Z24,$D$8:$D$32,$H$8:$H$32),0) -> 0 | AC24: =IFERROR(_xlfn.XLOOKUP($Z24,$D$6:$D$30,$F$6:$F$30),0) -> 0
C25: 18 | E25: =IFERROR(_xlfn.XLOOKUP(D25,tbl_Parcels[Parcel],tbl_Parcels[Use]),0) -> 0 | F25: =IFERROR(LOOKUP(D25,tbl_Parcels[Parcel],tbl_Parcels[Acres]),0) -> 0 | G25: =IFERROR(LOOKUP('V4'!$H25,Table4[Product],Table4[DUA]),0) -> 0 | I25: =IFERROR(INT(LOOKUP('V4'!$H25,lst_LotProducts,lst_ProductDUA)*'V4'!$F25),0) -> 0 | Q25: 0 | R25: 0 | S25: 0 | T25: 0 | U25: =Q25+R25+S25+T25 -> 0 | Y25: =Y24+1 -> 18 | AA25: =IFERROR(LOOKUP(Z25,$D$8:$D$32,$I$8:$I$32),0) -> 0 | AB25: =IFERROR(_xlfn.XLOOKUP($Z25,$D$8:$D$32,$H$8:$H$32),0) -> 0 | AC25: =IFERROR(_xlfn.XLOOKUP($Z25,$D$6:$D$30,$F$6:$F$30),0) -> 0
C26: 19 | E26: =IFERROR(_xlfn.XLOOKUP(D26,tbl_Parcels[Parcel],tbl_Parcels[Use]),0) -> 0 | F26: =IFERROR(LOOKUP(D26,tbl_Parcels[Parcel],tbl_Parcels[Acres]),0) -> 0 | G26: =IFERROR(LOOKUP('V4'!$H26,Table4[Product],Table4[DUA]),0) -> 0 | I26: =IFERROR(INT(LOOKUP('V4'!$H26,lst_LotProducts,lst_ProductDUA)*'V4'!$F26),0) -> 0 | Q26: 0 | R26: 0 | S26: 0 | T26: 0 | U26: =Q26+R26+S26+T26 -> 0 | Y26: =Y25+1 -> 19 | AA26: =IFERROR(LOOKUP(Z26,$D$8:$D$32,$I$8:$I$32),0) -> 0 | AB26: =IFERROR(_xlfn.XLOOKUP($Z26,$D$8:$D$32,$H$8:$H$32),0) -> 0 | AC26: =IFERROR(_xlfn.XLOOKUP($Z26,$D$6:$D$30,$F$6:$F$30),0) -> 0
C27: 20 | E27: =IFERROR(_xlfn.XLOOKUP(D27,tbl_Parcels[Parcel],tbl_Parcels[Use]),0) -> 0 | F27: =IFERROR(LOOKUP(D27,tbl_Parcels[Parcel],tbl_Parcels[Acres]),0) -> 0 | G27: =IFERROR(LOOKUP('V4'!$H27,Table4[Product],Table4[DUA]),0) -> 0 | I27: =IFERROR(INT(LOOKUP('V4'!$H27,lst_LotProducts,lst_ProductDUA)*'V4'!$F27),0) -> 0 | Q27: 0 | R27: 0 | S27: 0 | T27: 0 | U27: =Q27+R27+S27+T27 -> 0 | Y27: =Y26+1 -> 20 | AA27: =IFERROR(LOOKUP(Z27,$D$8:$D$32,$I$8:$I$32),0) -> 0 | AB27: =IFERROR(_xlfn.XLOOKUP($Z27,$D$8:$D$32,$H$8:$H$32),0) -> 0 | AC27: =IFERROR(_xlfn.XLOOKUP($Z27,$D$6:$D$30,$F$6:$F$30),0) -> 0
C28: 21 | E28: =IFERROR(_xlfn.XLOOKUP(D28,tbl_Parcels[Parcel],tbl_Parcels[Use]),0) -> 0 | F28: =IFERROR(LOOKUP(D28,tbl_Parcels[Parcel],tbl_Parcels[Acres]),0) -> 0 | G28: =IFERROR(LOOKUP('V4'!$H28,Table4[Product],Table4[DUA]),0) -> 0 | I28: =IFERROR(INT(LOOKUP('V4'!$H28,lst_LotProducts,lst_ProductDUA)*'V4'!$F28),0) -> 0 | Q28: 0 | R28: 0 | S28: 0 | T28: 0 | U28: =Q28+R28+S28+T28 -> 0 | Y28: =Y27+1 -> 21 | AA28: =IFERROR(LOOKUP(Z28,$D$8:$D$32,$I$8:$I$32),0) -> 0 | AB28: =IFERROR(_xlfn.XLOOKUP($Z28,$D$8:$D$32,$H$8:$H$32),0) -> 0 | AC28: =IFERROR(_xlfn.XLOOKUP($Z28,$D$6:$D$30,$F$6:$F$30),0) -> 0
C29: 22 | E29: =IFERROR(_xlfn.XLOOKUP(D29,tbl_Parcels[Parcel],tbl_Parcels[Use]),0) -> 0 | F29: =IFERROR(LOOKUP(D29,tbl_Parcels[Parcel],tbl_Parcels[Acres]),0) -> 0 | G29: =IFERROR(LOOKUP('V4'!$H29,Table4[Product],Table4[DUA]),0) -> 0 | I29: =IFERROR(INT(LOOKUP('V4'!$H29,lst_LotProducts,lst_ProductDUA)*'V4'!$F29),0) -> 0 | Q29: 0 | R29: 0 | S29: 0 | T29: 0 | U29: =Q29+R29+S29+T29 -> 0 | Y29: =Y28+1 -> 22 | AA29: =IFERROR(LOOKUP(Z29,$D$8:$D$32,$I$8:$I$32),0) -> 0 | AB29: =IFERROR(_xlfn.XLOOKUP($Z29,$D$8:$D$32,$H$8:$H$32),0) -> 0 | AC29: =IFERROR(_xlfn.XLOOKUP($Z29,$D$6:$D$30,$F$6:$F$30),0) -> 0
C30: 23 | E30: =IFERROR(_xlfn.XLOOKUP(D30,tbl_Parcels[Parcel],tbl_Parcels[Use]),0) -> 0 | F30: =IFERROR(LOOKUP(D30,tbl_Parcels[Parcel],tbl_Parcels[Acres]),0) -> 0 | G30: =IFERROR(LOOKUP('V4'!$H30,Table4[Product],Table4[DUA]),0) -> 0 | I30: =IFERROR(INT(LOOKUP('V4'!$H30,lst_LotProducts,lst_ProductDUA)*'V4'!$F30),0) -> 0 | Q30: 0 | R30: 0 | S30: 0 | T30: 0 | U30: =Q30+R30+S30+T30 -> 0 | Y30: =Y29+1 -> 23 | AA30: =IFERROR(LOOKUP(Z30,$D$8:$D$32,$I$8:$I$32),0) -> 0 | AB30: =IFERROR(_xlfn.XLOOKUP($Z30,$D$8:$D$32,$H$8:$H$32),0) -> 0 | AC30: =IFERROR(_xlfn.XLOOKUP($Z30,$D$6:$D$30,$F$6:$F$30),0) -> 0
C31: 24 | E31: =IFERROR(_xlfn.XLOOKUP(D31,tbl_Parcels[Parcel],tbl_Parcels[Use]),0) -> 0 | F31: =IFERROR(LOOKUP(D31,tbl_Parcels[Parcel],tbl_Parcels[Acres]),0) -> 0 | G31: =IFERROR(LOOKUP('V4'!$H31,Table4[Product],Table4[DUA]),0) -> 0 | I31: =IFERROR(INT(LOOKUP('V4'!$H31,lst_LotProducts,lst_ProductDUA)*'V4'!$F31),0) -> 0 | Q31: 0 | R31: 0 | S31: 0 | T31: 0 | U31: =Q31+R31+S31+T31 -> 0 | Y31: =Y30+1 -> 24 | AA31: =IFERROR(LOOKUP(Z31,$D$8:$D$32,$I$8:$I$32),0) -> 0 | AB31: =IFERROR(_xlfn.XLOOKUP($Z31,$D$8:$D$32,$H$8:$H$32),0) -> 0 | AC31: =IFERROR(_xlfn.XLOOKUP($Z31,$D$6:$D$30,$F$6:$F$30),0) -> 0
C32: 25 | E32: =IFERROR(_xlfn.XLOOKUP(D32,tbl_Parcels[Parcel],tbl_Parcels[Use]),0) -> 0 | F32: =IFERROR(LOOKUP(D32,tbl_Parcels[Parcel],tbl_Parcels[Acres]),0) -> 0 | G32: =IFERROR(LOOKUP('V4'!$H32,Table4[Product],Table4[DUA]),0) -> 0 | I32: =IFERROR(INT(LOOKUP('V4'!$H32,lst_LotProducts,lst_ProductDUA)*'V4'!$F32),0) -> 0 | P32: Total | Q32: =SUM(Q10:Q31) -> 28000000 | R32: =SUM(R10:R31) -> 19600000 | S32: =SUM(S10:S31) -> 15650000 | T32: =SUM(T10:T31) -> 8650000 | U32: =Q32+R32+S32+T32 -> 71900000 | Z32: Total | AA32: =SUM(AA8:AA31) -> 919 | AC32: =SUM(AC8:AC31) -> 389.03 | AD32: =SUM(AD10:AD31) -> 28 | AE32: =AA32+AB32+AC32+AD32 -> 1336.03
Z35: {=_xlfn.UNIQUE(_xlfn._xlws.FILTER(AD9:AD33,AD9:AD33<>0))} -> 1
Z36: 2
Z37: 3
Z38: 4
Z39: 28

Sheet Budget
Q2: Hide these helpers
D3: # | E3: Plan Area | F3: Dev Phase | G3: Cost Center | H3: Category | I3: Description | J3: Budget | K3: Reimb | L3: Inflate | M3: Contin | N3: Start Mo | O3: For | P3: Budget Inflated | Q3: End Mo | R3: Start Date | S3: End Date
A4: =IF($L4="y",1,0) -> 1 | B4: =IF($L4="y",1,0) -> 1 | D4: =IF(ISBLANK(H4),"",COUNTA(G$4:$G4)) -> 1 | E4: 1 | G4: Acquisition | H4: Diligence | J4: 25000 | L4: y | M4: n | N4: 1 | O4: 4 | Q4: =IF(J4=0,0,IF(N4+O4-1,N4+O4-1)) -> 4 | R4: {=IF(N4=0,"",EDATE(i_Date.Start,N4-1))} -> 44562 | S4: =IF(O4=0,"",EOMONTH(EDATE(R4,O4),0)) -> 44712
A5: =IF($L5="y",1,0) -> 0 | B5: =IF($L5="y",1,0) -> 0 | D5: =IF(ISBLANK(H5),"",COUNTA(G$4:$G5)) -> 2 | E5: 1 | G5: Entitlements | H5: PrePlat [Block] | J5: 25000 | N5: 1 | O5: 6 | Q5: =IF(J5=0,0,IF(N5+O5-1,N5+O5-1)) -> 6 | R5: {=IF(N5=0,"",EDATE(i_Date.Start,N5-1))} -> 44562 | S5: =IF(O5=0,"",EOMONTH(EDATE(R5,O5),0)) -> 44773
A6: =IF($L6="y",1,0) -> 0 | B6: =IF($L6="y",1,0) -> 0 | D6: =IF(ISBLANK(H6),"",COUNTA(G$4:$G6)) -> 3 | E6: 1 | G6: Entitlements | H6: PrePlat [Subd] | J6: 50000 | N6: 1 | O6: 15 | Q6: =IF(J6=0,0,IF(N6+O6-1,N6+O6-1)) -> 15 | R6: {=IF(N6=0,"",EDATE(i_Date.Start,N6-1))} -> 44562 | S6: =IF(O6=0,"",EOMONTH(EDATE(R6,O6),0)) -> 45046
A7: =IF($L7="y",1,0) -> 0 | B7: =IF($L7="y",1,0) -> 0 | D7: =IF(ISBLANK(H7),"",COUNTA(G$4:$G7)) -> 4 | E7: 1 | G7: Engineering | H7: Other | I7: Offsites | J7: 200000 | N7: 1 | O7: 4 | Q7: =IF(J7=0,0,IF(N7+O7-1,N7+O7-1)) -> 4 | R7: {=IF(N7=0,"",EDATE(i_Date.Start,N7-1))} -> 44562 | S7: =IF(O7=0,"",EOMONTH(EDATE(R7,O7),0)) -> 44712
A8: =IF($L8="y",1,0) -> 0 | B8: =IF($L8="y",1,0) -> 0 | D8: =IF(ISBLANK(H8),"",COUNTA(G$4:$G8)) -> 5 | G8: Engineering | H8: Project | J8: 750000 | Q8: =IF(J8=0,0,IF(N8+O8-1,N8+O8-1)) -> -1 | R8: {=IF(N8=0,"",EDATE(i_Date.Start,N8-1))} | S8: =IF(O8=0,"",EOMONTH(EDATE(R8,O8),0))
A9: =IF($L9="y",1,0) -> 0 | B9: =IF($L9="y",1,0) -> 0 | D9: =IF(ISBLANK(H9),"",COUNTA(G$4:$G9)) -> 6 | E9: 1 | G9: Engineering | H9: Subdivisions | N9: 1 | O9: 18 | Q9: =IF(J9=0,0,IF(N9+O9-1,N9+O9-1)) -> 0 | R9: {=IF(N9=0,"",EDATE(i_Date.Start,N9-1))} -> 44562 | S9: =IF(O9=0,"",EOMONTH(EDATE(R9,O9),0)) -> 45138
A10: =IF($L10="y",1,0) -> 0 | B10: =IF($L10="y",1,0) -> 0 | D10: =IF(ISBLANK(H10),"",COUNTA(G$4:$G10)) -> 7 | E10: 1 | G10: Offsites | H10: Other | I10: All | N10: 1 | O10: 18 | Q10: =IF(J10=0,0,IF(N10+O10-1,N10+O10-1)) -> 0 | R10: {=IF(N10=0,"",EDATE(i_Date.Start,N10-1))} -> 44562 | S10: =IF(O10=0,"",EOMONTH(EDATE(R10,O10),0)) -> 45138
A11: =IF($L11="y",1,0) -> 0 | B11: =IF($L11="y",1,0) -> 0 | D11: =IF(ISBLANK(H11),"",COUNTA(G$4:$G11)) -> 8 | E11: 1 | G11: Onsites | H11: Other | I11: All | N11: 19 | O11: 54 | Q11: =IF(J11=0,0,IF(N11+O11-1,N11+O11-1)) -> 0 | R11: {=IF(N11=0,"",EDATE(i_Date.Start,N11-1))} -> 45108 | S11: =IF(O11=0,"",EOMONTH(EDATE(R11,O11),0)) -> 46783
A12: =IF($L12="y",1,0) -> 0 | B12: =IF($L12="y",1,0) -> 0 | D12: =IF(ISBLANK(H12),"",COUNTA(G$4:$G12)) -> 9 | E12: 1 | G12: Exactions | H12: Other | I12: Legal bribes | N12: 1 | O12: 18 | Q12: =IF(J12=0,0,IF(N12+O12-1,N12+O12-1)) -> 0 | R12: {=IF(N12=0,"",EDATE(i_Date.Start,N12-1))} -> 44562 | S12: =IF(O12=0,"",EOMONTH(EDATE(R12,O12),0)) -> 45138
A13: =IF($L13="y",1,0) -> 0 | B13: =IF($L13="y",1,0) -> 0 | D13: =IF(ISBLANK(H13),"",COUNTA(G$4:$G13)) | E13: 1 | N13: 19 | O13: 54 | Q13: =IF(J13=0,0,IF(N13+O13-1,N13+O13-1)) -> 0 | R13: {=IF(N13=0,"",EDATE(i_Date.Start,N13-1))} -> 45108 | S13: =IF(O13=0,"",EOMONTH(EDATE(R13,O13),0)) -> 46783
A14: =IF($L14="y",1,0) -> 0 | B14: =IF($L14="y",1,0) -> 0 | D14: =IF(ISBLANK(H14),"",COUNTA(G$4:$G14)) | Q14: =IF(J14=0,0,IF(N14+O14-1,N14+O14-1)) -> 0 | R14: {=IF(N14=0,"",EDATE(i_Date.Start,N14-1))} | S14: =IF(O14=0,"",EOMONTH(EDATE(R14,O14),0))
A15: =IF($L15="y",1,0) -> 0 | B15: =IF($L15="y",1,0) -> 0 | D15: =IF(ISBLANK(H15),"",COUNTA(G$4:$G15)) | E15: 1 | N15: 1 | O15: 2 | Q15: =IF(J15=0,0,IF(N15+O15-1,N15+O15-1)) -> 0 | R15: {=IF(N15=0,"",EDATE(i_Date.Start,N15-1))} -> 44562 | S15: =IF(O15=0,"",EOMONTH(EDATE(R15,O15),0)) -> 44651
A16: =IF($L16="y",1,0) -> 0 | B16: =IF($L16="y",1,0) -> 0 | D16: =IF(ISBLANK(H16),"",COUNTA(G$4:$G16)) | E16: 1 | N16: 1 | O16: 2 | Q16: =IF(J16=0,0,IF(N16+O16-1,N16+O16-1)) -> 0 | R16: {=IF(N16=0,"",EDATE(i_Date.Start,N16-1))} -> 44562 | S16: =IF(O16=0,"",EOMONTH(EDATE(R16,O16),0)) -> 44651
A17: =IF($L17="y",1,0) -> 0 | B17: =IF($L17="y",1,0) -> 0 | D17: =IF(ISBLANK(H17),"",COUNTA(G$4:$G17)) | E17: 1 | N17: 1 | O17: 2 | Q17: =IF(J17=0,0,IF(N17+O17-1,N17+O17-1)) -> 0 | R17: {=IF(N17=0,"",EDATE(i_Date.Start,N17-1))} -> 44562 | S17: =IF(O17=0,"",EOMONTH(EDATE(R17,O17),0)) -> 44651
A18: =IF($L18="y",1,0) -> 0 | B18: =IF($L18="y",1,0) -> 0 | D18: =IF(ISBLANK(H18),"",COUNTA(G$4:$G18)) | E18: 1 | N18: 1 | O18: 2 | Q18: =IF(J18=0,0,IF(N18+O18-1,N18+O18-1)) -> 0 | R18: {=IF(N18=0,"",EDATE(i_Date.Start,N18-1))} -> 44562 | S18: =IF(O18=0,"",EOMONTH(EDATE(R18,O18),0)) -> 44651
A19: =IF($L19="y",1,0) -> 0 | B19: =IF($L19="y",1,0) -> 0 | D19: =IF(ISBLANK(H19),"",COUNTA(G$4:$G19)) | N19: 1 | O19: 2 | Q19: =IF(J19=0,0,IF(N19+O19-1,N19+O19-1)) -> 0 | R19: {=IF(N19=0,"",EDATE(i_Date.Start,N19-1))} -> 44562 | S19: =IF(O19=0,"",EOMONTH(EDATE(R19,O19),0)) -> 44651
A20: =IF($L20="y",1,0) -> 0 | B20: =IF($L20="y",1,0) -> 0 | D20: =IF(ISBLANK(H20),"",COUNTA(G$4:$G20)) | E20: 1 | N20: 1 | O20: 2 | Q20: =IF(J20=0,0,IF(N20+O20-1,N20+O20-1)) -> 0 | R20: {=IF(N20=0,"",EDATE(i_Date.Start,N20-1))} -> 44562 | S20: =IF(O20=0,"",EOMONTH(EDATE(R20,O20),0)) -> 44651
A21: =IF($L21="y",1,0) -> 0 | B21: =IF($L21="y",1,0) -> 0 | D21: =IF(ISBLANK(H21),"",COUNTA(G$4:$G21)) | E21: 1 | N21: 1 | O21: 2 | Q21: =IF(J21=0,0,IF(N21+O21-1,N21+O21-1)) -> 0 | R21: {=IF(N21=0,"",EDATE(i_Date.Start,N21-1))} -> 44562 | S21: =IF(O21=0,"",EOMONTH(EDATE(R21,O21),0)) -> 44651
A22: =IF($L22="y",1,0) -> 0 | B22: =IF($L22="y",1,0) -> 0 | D22: =IF(ISBLANK(H22),"",COUNTA(G$4:$G22)) | E22: 1 | N22: 1 | O22: 2 | Q22: =IF(J22=0,0,IF(N22+O22-1,N22+O22-1)) -> 0 | R22: {=IF(N22=0,"",EDATE(i_Date.Start,N22-1))} -> 44562 | S22: =IF(O22=0,"",EOMONTH(EDATE(R22,O22),0)) -> 44651
A23: =IF($L23="y",1,0) -> 0 | B23: =IF($L23="y",1,0) -> 0 | D23: =IF(ISBLANK(H23),"",COUNTA(G$4:$G23)) | E23: 1 | N23: 1 | O23: 2 | Q23: =IF(J23=0,0,IF(N23+O23-1,N23+O23-1)) -> 0 | R23: {=IF(N23=0,"",EDATE(i_Date.Start,N23-1))} -> 44562 | S23: =IF(O23=0,"",EOMONTH(EDATE(R23,O23),0)) -> 44651
D24: =IF(ISBLANK(H24),"",COUNTA(G$4:$G24)) | E24: 2 | N24: 1 | O24: 2 | Q24: =IF(J24=0,0,IF(N24+O24-1,N24+O24-1)) -> 0 | R24: {=IF(N24=0,"",EDATE(i_Date.Start,N24-1))} -> 44562 | S24: =IF(O24=0,"",EOMONTH(EDATE(R24,O24),0)) -> 44651
D25: =IF(ISBLANK(H25),"",COUNTA(G$4:$G25)) | E25: 3 | N25: 1 | O25: 2 | Q25: =IF(J25=0,0,IF(N25+O25-1,N25+O25-1)) -> 0 | R25: {=IF(N25=0,"",EDATE(i_Date.Start,N25-1))} -> 44562 | S25: =IF(O25=0,"",EOMONTH(EDATE(R25,O25),0)) -> 44651
D26: =IF(ISBLANK(H26),"",COUNTA(G$4:$G26)) | E26: 4 | N26: 1 | O26: 2 | Q26: =IF(J26=0,0,IF(N26+O26-1,N26+O26-1)) -> 0 | R26: {=IF(N26=0,"",EDATE(i_Date.Start,N26-1))} -> 44562 | S26: =IF(O26=0,"",EOMONTH(EDATE(R26,O26),0)) -> 44651
D27: =IF(ISBLANK(H27),"",COUNTA(G$4:$G27)) | E27: 5 | N27: 1 | O27: 2 | Q27: =IF(J27=0,0,IF(N27+O27-1,N27+O27-1)) -> 0 | R27: {=IF(N27=0,"",EDATE(i_Date.Start,N27-1))} -> 44562 | S27: =IF(O27=0,"",EOMONTH(EDATE(R27,O27),0)) -> 44651
D28: =IF(ISBLANK(H28),"",COUNTA(G$4:$G28)) | E28: 6 | N28: 1 | O28: 2 | Q28: =IF(J28=0,0,IF(N28+O28-1,N28+O28-1)) -> 0 | R28: {=IF(N28=0,"",EDATE(i_Date.Start,N28-1))} -> 44562 | S28: =IF(O28=0,"",EOMONTH(EDATE(R28,O28),0)) -> 44651
D29: =IF(ISBLANK(H29),"",COUNTA(G$4:$G29)) | E29: 7 | N29: 1 | O29: 2 | Q29: =IF(J29=0,0,IF(N29+O29-1,N29+O29-1)) -> 0 | R29: {=IF(N29=0,"",EDATE(i_Date.Start,N29-1))} -> 44562 | S29: =IF(O29=0,"",EOMONTH(EDATE(R29,O29),0)) -> 44651
D30: =IF(ISBLANK(H30),"",COUNTA(G$4:$G30)) | E30: 8 | N30: 1 | O30: 2 | Q30: =IF(J30=0,0,IF(N30+O30-1,N30+O30-1)) -> 0 | R30: {=IF(N30=0,"",EDATE(i_Date.Start,N30-1))} -> 44562 | S30: =IF(O30=0,"",EOMONTH(EDATE(R30,O30),0)) -> 44651
D31: =IF(ISBLANK(H31),"",COUNTA(G$4:$G31)) | E31: 9 | N31: 1 | O31: 2 | Q31: =IF(J31=0,0,IF(N31+O31-1,N31+O31-1)) -> 0 | R31: {=IF(N31=0,"",EDATE(i_Date.Start,N31-1))} -> 44562 | S31: =IF(O31=0,"",EOMONTH(EDATE(R31,O31),0)) -> 44651
D32: =IF(ISBLANK(H32),"",COUNTA(G$4:$G32)) | E32: 10 | N32: 1 | O32: 2 | Q32: =IF(J32=0,0,IF(N32+O32-1,N32+O32-1)) -> 0 | R32: {=IF(N32=0,"",EDATE(i_Date.Start,N32-1))} -> 44562 | S32: =IF(O32=0,"",EOMONTH(EDATE(R32,O32),0)) -> 44651

Sheet CALCS
P4: ='iV1'!C4 -> 1 | R4: ='iV1'!P4 -> Development Phasing | V4: =P4 -> 1 | X4: Parcel Sales | Z4: Total
P5: ='iV1'!P5 -> 1 | Q5: ='iV1'!Q5 -> 2 | R5: ='iV1'!R5 -> 3 | S5: ='iV1'!S5 -> 4 | T5: Total | V5: {=TRANSPOSE(_xlfn.UNIQUE(_xlfn._xlws.FILTER('iV1'!AE8:AE32,'iV1'!AE8:AE32<>0)))} -> 45108 | W5: 45231 | X5: 45717 | Y5: 45992
P6: ='iV1'!P7 -> 6 | Q6: ='iV1'!Q7 -> 30 | R6: ='iV1'!R7 -> 0 | S6: ='iV1'!S7 -> 0 | T6: =MIN(P6:S6) -> 0 | V6: ='iV1'!V7 -> 0 | W6: ='iV1'!W7 -> 0
C7: Periocity | J7: Rates (5 max) | P7: ='iV1'!P8 -> 12 | Q7: ='iV1'!Q8 -> 8 | R7: ='iV1'!R8 -> 0 | S7: ='iV1'!S8 -> 0 | T7: =T8-T6+1 -> 38 | V7: ='iV1'!V8 -> 0 | W7: ='iV1'!W8 -> 0
J8: =DATA!L8 -> Price | K8: =DATA!M8 -> Cost | L8: =DATA!N8 -> 0 | M8: =DATA!O8 -> 0 | N8: =DATA!P8 -> 0 | P8: =P6+P7-1 -> 17 | Q8: =Q6+Q7-1 -> 37 | R8: =R6+R7-1 -> -1 | S8: =S6+S7-1 -> -1 | T8: {=_xlfn.XLOOKUP(LOOKUP(2,1/(T12:T371<>0),T12:T371),T12:T371,C12:C371)} -> 37 | V8: =V6+V7-1 -> -1 | W8: =W6+W7-1 -> -1
J9: =IFERROR(_xlfn.XLOOKUP(J$8,iGeneral!$D$25:$D$29,iGeneral!$F$25:$F$29),"") -> 1 | K9: =IFERROR(_xlfn.XLOOKUP(K$8,iGeneral!$D$25:$D$29,iGeneral!$F$25:$F$29),"") -> 2 | L9: =IFERROR(_xlfn.XLOOKUP(L$8,iGeneral!$D$25:$D$29,iGeneral!$F$25:$F$29),"") | M9: =IFERROR(_xlfn.XLOOKUP(M$8,iGeneral!$D$25:$D$29,iGeneral!$F$25:$F$29),"") | N9: =IFERROR(_xlfn.XLOOKUP(N$8,iGeneral!$D$25:$D$29,iGeneral!$F$25:$F$29),"") | P9: ='iV1'!P33 -> 13000000 | Q9: ='iV1'!Q33 -> 19600000 | R9: ='iV1'!R33 -> 0 | S9: ='iV1'!S33 -> 0 | T9: ='iV1'!T33 -> 32600000 | V9: ='iV1'!V32 -> 0 | W9: ='iV1'!W32 -> 0 | X9: ='iV1'!X32 -> 25 | Y9: ='iV1'!Y32 -> 0 | Z9: ='iV1'!Z32 -> 0
C10: Mo | D10: Date | E10: Qtr | F10: Qtr-Yr | G10: Yr | H10: Date-Yr | J10: =IFERROR(_xlfn.XLOOKUP(J$8,iGeneral!$D$25:$D$29,iGeneral!$E$25:$E$29),0) -> 0.02 | K10: =IFERROR(_xlfn.XLOOKUP(K$8,iGeneral!$D$25:$D$29,iGeneral!$E$25:$E$29),0) -> 0.01 | L10: =IFERROR(_xlfn.XLOOKUP(L$8,iGeneral!$D$25:$D$29,iGeneral!$E$25:$E$29),0) -> 0 | M10: =IFERROR(_xlfn.XLOOKUP(M$8,iGeneral!$D$25:$D$29,iGeneral!$E$25:$E$29),0) -> 0 | N10: =IFERROR(_xlfn.XLOOKUP(N$8,iGeneral!$D$25:$D$29,iGeneral!$E$25:$E$29),0) -> 0 | P10: =SUM(P11:P243) -> 13009035 | Q10: =SUM(Q11:Q243) -> 19937604 | R10: =SUM(R11:R243) -> 0 | S10: =SUM(S11:S243) -> 0 | T10: =SUM(T11:T243) -> 32946640 | V10: =SUM(V11:V243) -> 0 | W10: =SUM(W11:W243) -> 0 | X10: =SUM(X11:X243) -> 0 | Y10: =SUM(Y11:Y243) -> 0 | Z10: =SUM(Z11:Z243) -> 0
C11: 1 | D11: =i_Date.Start -> 44562 | E11: =INT(INT(C11+2)/3) -> 1 | F11: ="Q"&INT((MONTH(D11)/4)+1)&"-"&RIGHT(YEAR(D11),2) -> Q1-22 | G11: =MIN(INT(YEARFRAC(D$11,D23)),30) -> 1 | H11: =YEAR(D11) -> 2022 | J11: =DATA!L11 -> 1 | K11: =DATA!M11 -> 1 | L11: =DATA!N11 -> 1 | M11: =DATA!O11 -> 1 | N11: =DATA!P11 -> 1 | P11: =IF(AND($C11>=P$6,$C11<=P$6+P$7-1),P$9/P$7*$K11,0) -> 0 | Q11: =IF(AND($C11>=Q$6,$C11<=Q$6+Q$7-1),Q$9/Q$7*$K11,0) -> 0 | R11: =IF(AND($C11>=R$6,$C11<=R$6+R$7-1),R$9/R$7*$K11,0) -> 0 | S11: =IF(AND($C11>=S$6,$C11<=S$6+S$7-1),S$9/S$7*$K11,0) -> 0 | T11: =SUM(P11:S11) -> 0 | V11: =IF(AND($C11>=V$6,$C11<=V$6+V$7-1),V$9/V$7*$K11,0) -> 0 | W11: =IF(AND($C11>=W$6,$C11<=W$6+W$7-1),W$9/W$7*$K11,0) -> 0 | X11: =IF(AND($C11>=X$6,$C11<=X$6+X$7-1),X$9/X$7*$K11,0) -> 0 | Y11: =IF(AND($C11>=Y$6,$C11<=Y$6+Y$7-1),Y$9/Y$7*$K11,0) -> 0 | Z11: =SUM(V11:Y11) -> 0
C12: =C11+1 -> 2 | D12: =EOMONTH(D11,0)+1 -> 44593 | E12: =INT(INT(C12+2)/3) -> 1 | F12: ="Q"&INT((MONTH(D12)/4)+1)&"-"&RIGHT(YEAR(D12),2) -> Q1-22 | G12: =MIN(INT(YEARFRAC(D$11,D24)),30) -> 1 | H12: =YEAR(D12) -> 2022 | J12: =DATA!L12 -> 1.0016667 | K12: =DATA!M12 -> 1 | L12: =DATA!N12 -> 1 | M12: =DATA!O12 -> 1 | N12: =DATA!P12 -> 1 | P12: =IF(AND($C12>=P$6,$C12<=P$6+P$7-1),P$9/P$7*$K12,0) -> 0 | Q12: =IF(AND($C12>=Q$6,$C12<=Q$6+Q$7-1),Q$9/Q$7*$K12,0) -> 0 | R12: =IF(AND($C12>=R$6,$C12<=R$6+R$7-1),R$9/R$7*$K12,0) -> 0 | S12: =IF(AND($C12>=S$6,$C12<=S$6+S$7-1),S$9/S$7*$K12,0) -> 0 | T12: =SUM(P12:S12) -> 0 | V12: =IF(AND($C12>=V$6,$C12<=V$6+V$7-1),V$9/V$7*$K12,0) -> 0 | W12: =IF(AND($C12>=W$6,$C12<=W$6+W$7-1),W$9/W$7*$K12,0) -> 0 | X12: =IF(AND($C12>=X$6,$C12<=X$6+X$7-1),X$9/X$7*$K12,0) -> 0 | Y12: =IF(AND($C12>=Y$6,$C12<=Y$6+Y$7-1),Y$9/Y$7*$K12,0) -> 0 | Z12: =SUM(V12:Y12) -> 0
C13: =C12+1 -> 3 | D13: =EOMONTH(D12,0)+1 -> 44621 | E13: =INT(INT(C13+2)/3) -> 1 | F13: ="Q"&INT((MONTH(D13)/4)+1)&"-"&RIGHT(YEAR(D13),2) -> Q1-22 | G13: =MIN(INT(YEARFRAC(D$11,D25)),30) -> 1 | H13: =YEAR(D13) -> 2022 | J13: =DATA!L13 -> 1.0033361 | K13: =DATA!M13 -> 1 | L13: =DATA!N13 -> 1 | M13: =DATA!O13 -> 1 | N13: =DATA!P13 -> 1 | P13: =IF(AND($C13>=P$6,$C13<=P$6+P$7-1),P$9/P$7*$K13,0) -> 0 | Q13: =IF(AND($C13>=Q$6,$C13<=Q$6+Q$7-1),Q$9/Q$7*$K13,0) -> 0 | R13: =IF(AND($C13>=R$6,$C13<=R$6+R$7-1),R$9/R$7*$K13,0) -> 0 | S13: =IF(AND($C13>=S$6,$C13<=S$6+S$7-1),S$9/S$7*$K13,0) -> 0 | T13: =SUM(P13:S13) -> 0 | V13: =IF(AND($C13>=V$6,$C13<=V$6+V$7-1),V$9/V$7*$K13,0) -> 0 | W13: =IF(AND($C13>=W$6,$C13<=W$6+W$7-1),W$9/W$7*$K13,0) -> 0 | X13: =IF(AND($C13>=X$6,$C13<=X$6+X$7-1),X$9/X$7*$K13,0) -> 0 | Y13: =IF(AND($C13>=Y$6,$C13<=Y$6+Y$7-1),Y$9/Y$7*$K13,0) -> 0 | Z13: =SUM(V13:Y13) -> 0
C14: =C13+1 -> 4 | D14: =EOMONTH(D13,0)+1 -> 44652 | E14: =INT(INT(C14+2)/3) -> 2 | F14: ="Q"&INT((MONTH(D14)/4)+1)&"-"&RIGHT(YEAR(D14),2) -> Q2-22 | G14: =MIN(INT(YEARFRAC(D$11,D26)),30) -> 1 | H14: =YEAR(D14) -> 2022 | J14: =DATA!L14 -> 1.0050083 | K14: =DATA!M14 -> 1 | L14: =DATA!N14 -> 1 | M14: =DATA!O14 -> 1 | N14: =DATA!P14 -> 1 | P14: =IF(AND($C14>=P$6,$C14<=P$6+P$7-1),P$9/P$7*$K14,0) -> 0 | Q14: =IF(AND($C14>=Q$6,$C14<=Q$6+Q$7-1),Q$9/Q$7*$K14,0) -> 0 | R14: =IF(AND($C14>=R$6,$C14<=R$6+R$7-1),R$9/R$7*$K14,0) -> 0 | S14: =IF(AND($C14>=S$6,$C14<=S$6+S$7-1),S$9/S$7*$K14,0) -> 0 | T14: =SUM(P14:S14) -> 0 | V14: =IF(AND($C14>=V$6,$C14<=V$6+V$7-1),V$9/V$7*$K14,0) -> 0 | W14: =IF(AND($C14>=W$6,$C14<=W$6+W$7-1),W$9/W$7*$K14,0) -> 0 | X14: =IF(AND($C14>=X$6,$C14<=X$6+X$7-1),X$9/X$7*$K14,0) -> 0 | Y14: =IF(AND($C14>=Y$6,$C14<=Y$6+Y$7-1),Y$9/Y$7*$K14,0) -> 0 | Z14: =SUM(V14:Y14) -> 0
C15: =C14+1 -> 5 | D15: =EOMONTH(D14,0)+1 -> 44682 | E15: =INT(INT(C15+2)/3) -> 2 | F15: ="Q"&INT((MONTH(D15)/4)+1)&"-"&RIGHT(YEAR(D15),2) -> Q2-22 | G15: =MIN(INT(YEARFRAC(D$11,D27)),30) -> 1 | H15: =YEAR(D15) -> 2022 | J15: =DATA!L15 -> 1.0066834 | K15: =DATA!M15 -> 1 | L15: =DATA!N15 -> 1 | M15: =DATA!O15 -> 1 | N15: =DATA!P15 -> 1 | P15: =IF(AND($C15>=P$6,$C15<=P$6+P$7-1),P$9/P$7*$K15,0) -> 0 | Q15: =IF(AND($C15>=Q$6,$C15<=Q$6+Q$7-1),Q$9/Q$7*$K15,0) -> 0 | R15: =IF(AND($C15>=R$6,$C15<=R$6+R$7-1),R$9/R$7*$K15,0) -> 0 | S15: =IF(AND($C15>=S$6,$C15<=S$6+S$7-1),S$9/S$7*$K15,0) -> 0 | T15: =SUM(P15:S15) -> 0 | V15: =IF(AND($C15>=V$6,$C15<=V$6+V$7-1),V$9/V$7*$K15,0) -> 0 | W15: =IF(AND($C15>=W$6,$C15<=W$6+W$7-1),W$9/W$7*$K15,0) -> 0 | X15: =IF(AND($C15>=X$6,$C15<=X$6+X$7-1),X$9/X$7*$K15,0) -> 0 | Y15: =IF(AND($C15>=Y$6,$C15<=Y$6+Y$7-1),Y$9/Y$7*$K15,0) -> 0 | Z15: =SUM(V15:Y15) -> 0
C16: =C15+1 -> 6 | D16: =EOMONTH(D15,0)+1 -> 44713 | E16: =INT(INT(C16+2)/3) -> 2 | F16: ="Q"&INT((MONTH(D16)/4)+1)&"-"&RIGHT(YEAR(D16),2) -> Q2-22 | G16: =MIN(INT(YEARFRAC(D$11,D28)),30) -> 1 | H16: =YEAR(D16) -> 2022 | J16: =DATA!L16 -> 1.0083612 | K16: =DATA!M16 -> 1 | L16: =DATA!N16 -> 1 | M16: =DATA!O16 -> 1 | N16: =DATA!P16 -> 1 | P16: =IF(AND($C16>=P$6,$C16<=P$6+P$7-1),P$9/P$7*$K16,0) -> 1083333.3 | Q16: =IF(AND($C16>=Q$6,$C16<=Q$6+Q$7-1),Q$9/Q$7*$K16,0) -> 0 | R16: =IF(AND($C16>=R$6,$C16<=R$6+R$7-1),R$9/R$7*$K16,0) -> 0 | S16: =IF(AND($C16>=S$6,$C16<=S$6+S$7-1),S$9/S$7*$K16,0) -> 0 | T16: =SUM(P16:S16) -> 1083333.3 | V16: =IF(AND($C16>=V$6,$C16<=V$6+V$7-1),V$9/V$7*$K16,0) -> 0 | W16: =IF(AND($C16>=W$6,$C16<=W$6+W$7-1),W$9/W$7*$K16,0) -> 0 | X16: =IF(AND($C16>=X$6,$C16<=X$6+X$7-1),X$9/X$7*$K16,0) -> 0 | Y16: =IF(AND($C16>=Y$6,$C16<=Y$6+Y$7-1),Y$9/Y$7*$K16,0) -> 0 | Z16: =SUM(V16:Y16) -> 0
C17: =C16+1 -> 7 | D17: =EOMONTH(D16,0)+1 -> 44743 | E17: =INT(INT(C17+2)/3) -> 3 | F17: ="Q"&INT((MONTH(D17)/4)+1)&"-"&RIGHT(YEAR(D17),2) -> Q2-22 | G17: =MIN(INT(YEARFRAC(D$11,D29)),30) -> 1 | H17: =YEAR(D17) -> 2022 | J17: =DATA!L17 -> 1.0100418 | K17: =DATA!M17 -> 1 | L17: =DATA!N17 -> 1 | M17: =DATA!O17 -> 1 | N17: =DATA!P17 -> 1 | P17: =IF(AND($C17>=P$6,$C17<=P$6+P$7-1),P$9/P$7*$K17,0) -> 1083333.3 | Q17: =IF(AND($C17>=Q$6,$C17<=Q$6+Q$7-1),Q$9/Q$7*$K17,0) -> 0 | R17: =IF(AND($C17>=R$6,$C17<=R$6+R$7-1),R$9/R$7*$K17,0) -> 0 | S17: =IF(AND($C17>=S$6,$C17<=S$6+S$7-1),S$9/S$7*$K17,0) -> 0 | T17: =SUM(P17:S17) -> 1083333.3 | V17: =IF(AND($C17>=V$6,$C17<=V$6+V$7-1),V$9/V$7*$K17,0) -> 0 | W17: =IF(AND($C17>=W$6,$C17<=W$6+W$7-1),W$9/W$7*$K17,0) -> 0 | X17: =IF(AND($C17>=X$6,$C17<=X$6+X$7-1),X$9/X$7*$K17,0) -> 0 | Y17: =IF(AND($C17>=Y$6,$C17<=Y$6+Y$7-1),Y$9/Y$7*$K17,0) -> 0 | Z17: =SUM(V17:Y17) -> 0
C18: =C17+1 -> 8 | D18: =EOMONTH(D17,0)+1 -> 44774 | E18: =INT(INT(C18+2)/3) -> 3 | F18: ="Q"&INT((MONTH(D18)/4)+1)&"-"&RIGHT(YEAR(D18),2) -> Q3-22 | G18: =MIN(INT(YEARFRAC(D$11,D30)),30) -> 1 | H18: =YEAR(D18) -> 2022 | J18: =DATA!L18 -> 1.0117252 | K18: =DATA!M18 -> 1 | L18: =DATA!N18 -> 1 | M18: =DATA!O18 -> 1 | N18: =DATA!P18 -> 1 | P18: =IF(AND($C18>=P$6,$C18<=P$6+P$7-1),P$9/P$7*$K18,0) -> 1083333.3 | Q18: =IF(AND($C18>=Q$6,$C18<=Q$6+Q$7-1),Q$9/Q$7*$K18,0) -> 0 | R18: =IF(AND($C18>=R$6,$C18<=R$6+R$7-1),R$9/R$7*$K18,0) -> 0 | S18: =IF(AND($C18>=S$6,$C18<=S$6+S$7-1),S$9/S$7*$K18,0) -> 0 | T18: =SUM(P18:S18) -> 1083333.3 | V18: =IF(AND($C18>=V$6,$C18<=V$6+V$7-1),V$9/V$7*$K18,0) -> 0 | W18: =IF(AND($C18>=W$6,$C18<=W$6+W$7-1),W$9/W$7*$K18,0) -> 0 | X18: =IF(AND($C18>=X$6,$C18<=X$6+X$7-1),X$9/X$7*$K18,0) -> 0 | Y18: =IF(AND($C18>=Y$6,$C18<=Y$6+Y$7-1),Y$9/Y$7*$K18,0) -> 0 | Z18: =SUM(V18:Y18) -> 0
C19: =C18+1 -> 9 | D19: =EOMONTH(D18,0)+1 -> 44805 | E19: =INT(INT(C19+2)/3) -> 3 | F19: ="Q"&INT((MONTH(D19)/4)+1)&"-"&RIGHT(YEAR(D19),2) -> Q3-22 | G19: =MIN(INT(YEARFRAC(D$11,D31)),30) -> 1 | H19: =YEAR(D19) -> 2022 | J19: =DATA!L19 -> 1.0134114 | K19: =DATA!M19 -> 1 | L19: =DATA!N19 -> 1 | M19: =DATA!O19 -> 1 | N19: =DATA!P19 -> 1 | P19: =IF(AND($C19>=P$6,$C19<=P$6+P$7-1),P$9/P$7*$K19,0) -> 1083333.3 | Q19: =IF(AND($C19>=Q$6,$C19<=Q$6+Q$7-1),Q$9/Q$7*$K19,0) -> 0 | R19: =IF(AND($C19>=R$6,$C19<=R$6+R$7-1),R$9/R$7*$K19,0) -> 0 | S19: =IF(AND($C19>=S$6,$C19<=S$6+S$7-1),S$9/S$7*$K19,0) -> 0 | T19: =SUM(P19:S19) -> 1083333.3 | V19: =IF(AND($C19>=V$6,$C19<=V$6+V$7-1),V$9/V$7*$K19,0) -> 0 | W19: =IF(AND($C19>=W$6,$C19<=W$6+W$7-1),W$9/W$7*$K19,0) -> 0 | X19: =IF(AND($C19>=X$6,$C19<=X$6+X$7-1),X$9/X$7*$K19,0) -> 0 | Y19: =IF(AND($C19>=Y$6,$C19<=Y$6+Y$7-1),Y$9/Y$7*$K19,0) -> 0 | Z19: =SUM(V19:Y19) -> 0
C20: =C19+1 -> 10 | D20: =EOMONTH(D19,0)+1 -> 44835 | E20: =INT(INT(C20+2)/3) -> 4 | F20: ="Q"&INT((MONTH(D20)/4)+1)&"-"&RIGHT(YEAR(D20),2) -> Q3-22 | G20: =MIN(INT(YEARFRAC(D$11,D32)),30) -> 1 | H20: =YEAR(D20) -> 2022 | J20: =DATA!L20 -> 1.0151004 | K20: =DATA!M20 -> 1 | L20: =DATA!N20 -> 1 | M20: =DATA!O20 -> 1 | N20: =DATA!P20 -> 1 | P20: =IF(AND($C20>=P$6,$C20<=P$6+P$7-1),P$9/P$7*$K20,0) -> 1083333.3 | Q20: =IF(AND($C20>=Q$6,$C20<=Q$6+Q$7-1),Q$9/Q$7*$K20,0) -> 0 | R20: =IF(AND($C20>=R$6,$C20<=R$6+R$7-1),R$9/R$7*$K20,0) -> 0 | S20: =IF(AND($C20>=S$6,$C20<=S$6+S$7-1),S$9/S$7*$K20,0) -> 0 | T20: =SUM(P20:S20) -> 1083333.3 | V20: =IF(AND($C20>=V$6,$C20<=V$6+V$7-1),V$9/V$7*$K20,0) -> 0 | W20: =IF(AND($C20>=W$6,$C20<=W$6+W$7-1),W$9/W$7*$K20,0) -> 0 | X20: =IF(AND($C20>=X$6,$C20<=X$6+X$7-1),X$9/X$7*$K20,0) -> 0 | Y20: =IF(AND($C20>=Y$6,$C20<=Y$6+Y$7-1),Y$9/Y$7*$K20,0) -> 0 | Z20: =SUM(V20:Y20) -> 0
C21: =C20+1 -> 11 | D21: =EOMONTH(D20,0)+1 -> 44866 | E21: =INT(INT(C21+2)/3) -> 4 | F21: ="Q"&INT((MONTH(D21)/4)+1)&"-"&RIGHT(YEAR(D21),2) -> Q3-22 | G21: =MIN(INT(YEARFRAC(D$11,D33)),30) -> 1 | H21: =YEAR(D21) -> 2022 | J21: =DATA!L21 -> 1.0167922 | K21: =DATA!M21 -> 1 | L21: =DATA!N21 -> 1 | M21: =DATA!O21 -> 1 | N21: =DATA!P21 -> 1 | P21: =IF(AND($C21>=P$6,$C21<=P$6+P$7-1),P$9/P$7*$K21,0) -> 1083333.3 | Q21: =IF(AND($C21>=Q$6,$C21<=Q$6+Q$7-1),Q$9/Q$7*$K21,0) -> 0 | R21: =IF(AND($C21>=R$6,$C21<=R$6+R$7-1),R$9/R$7*$K21,0) -> 0 | S21: =IF(AND($C21>=S$6,$C21<=S$6+S$7-1),S$9/S$7*$K21,0) -> 0 | T21: =SUM(P21:S21) -> 1083333.3 | V21: =IF(AND($C21>=V$6,$C21<=V$6+V$7-1),V$9/V$7*$K21,0) -> 0 | W21: =IF(AND($C21>=W$6,$C21<=W$6+W$7-1),W$9/W$7*$K21,0) -> 0 | X21: =IF(AND($C21>=X$6,$C21<=X$6+X$7-1),X$9/X$7*$K21,0) -> 0 | Y21: =IF(AND($C21>=Y$6,$C21<=Y$6+Y$7-1),Y$9/Y$7*$K21,0) -> 0 | Z21: =SUM(V21:Y21) -> 0
C22: =C21+1 -> 12 | D22: =EOMONTH(D21,0)+1 -> 44896 | E22: =INT(INT(C22+2)/3) -> 4 | F22: ="Q"&INT((MONTH(D22)/4)+1)&"-"&RIGHT(YEAR(D22),2) -> Q4-22 | G22: =MIN(INT(YEARFRAC(D$11,D34)),30) -> 1 | H22: =YEAR(D22) -> 2022 | J22: =DATA!L22 -> 1.0184869 | K22: =DATA!M22 -> 1 | L22: =DATA!N22 -> 1 | M22: =DATA!O22 -> 1 | N22: =DATA!P22 -> 1 | P22: =IF(AND($C22>=P$6,$C22<=P$6+P$7-1),P$9/P$7*$K22,0) -> 1083333.3 | Q22: =IF(AND($C22>=Q$6,$C22<=Q$6+Q$7-1),Q$9/Q$7*$K22,0) -> 0 | R22: =IF(AND($C22>=R$6,$C22<=R$6+R$7-1),R$9/R$7*$K22,0) -> 0 | S22: =IF(AND($C22>=S$6,$C22<=S$6+S$7-1),S$9/S$7*$K22,0) -> 0 | T22: =SUM(P22:S22) -> 1083333.3 | V22: =IF(AND($C22>=V$6,$C22<=V$6+V$7-1),V$9/V$7*$K22,0) -> 0 | W22: =IF(AND($C22>=W$6,$C22<=W$6+W$7-1),W$9/W$7*$K22,0) -> 0 | X22: =IF(AND($C22>=X$6,$C22<=X$6+X$7-1),X$9/X$7*$K22,0) -> 0 | Y22: =IF(AND($C22>=Y$6,$C22<=Y$6+Y$7-1),Y$9/Y$7*$K22,0) -> 0 | Z22: =SUM(V22:Y22) -> 0
C23: =C22+1 -> 13 | D23: =EOMONTH(D22,0)+1 -> 44927 | E23: =INT(INT(C23+2)/3) -> 5 | F23: ="Q"&INT((MONTH(D23)/4)+1)&"-"&RIGHT(YEAR(D23),2) -> Q1-23 | G23: =MIN(INT(YEARFRAC(D$11,D35)),30) -> 2 | H23: =YEAR(D23) -> 2023 | J23: =DATA!L23 -> 1.0201844 | K23: =DATA!M23 -> 1 | L23: =DATA!N23 -> 1 | M23: =DATA!O23 -> 1 | N23: =DATA!P23 -> 1 | P23: =IF(AND($C23>=P$6,$C23<=P$6+P$7-1),P$9/P$7*$K23,0) -> 1083333.3 | Q23: =IF(AND($C23>=Q$6,$C23<=Q$6+Q$7-1),Q$9/Q$7*$K23,0) -> 0 | R23: =IF(AND($C23>=R$6,$C23<=R$6+R$7-1),R$9/R$7*$K23,0) -> 0 | S23: =IF(AND($C23>=S$6,$C23<=S$6+S$7-1),S$9/S$7*$K23,0) -> 0 | T23: =SUM(P23:S23) -> 1083333.3 | V23: =IF(AND($C23>=V$6,$C23<=V$6+V$7-1),V$9/V$7*$K23,0) -> 0 | W23: =IF(AND($C23>=W$6,$C23<=W$6+W$7-1),W$9/W$7*$K23,0) -> 0 | X23: =IF(AND($C23>=X$6,$C23<=X$6+X$7-1),X$9/X$7*$K23,0) -> 0 | Y23: =IF(AND($C23>=Y$6,$C23<=Y$6+Y$7-1),Y$9/Y$7*$K23,0) -> 0 | Z23: =SUM(V23:Y23) -> 0
... C369: =C368+1 -> 359 | D369: =EOMONTH(D368,0)+1 -> 55458 | E369: =INT(INT(C369+2)/3) -> 120 | F369: ="Q"&INT((MONTH(D369)/4)+1)&"-"&RIGHT(YEAR(D369),2) -> Q3-51 | G369: =MIN(INT(YEARFRAC(D$11,D381)),30) -> 30 | H369: =YEAR(D369) -> 2051 | J369: =DATA!L369 -> 1.8151534 | K369: =DATA!M369 -> 1.3340418 | L369: =DATA!N369 -> 1 | M369: =DATA!O369 -> 1 | N369: =DATA!P369 -> 1 | P369: =IF(AND($C369>=P$6,$C369<=P$6+P$7-1),P$9/P$7*$K369,0) -> 0 | Q369: =IF(AND($C369>=Q$6,$C369<=Q$6+Q$7-1),Q$9/Q$7*$K369,0) -> 0 | R369: =IF(AND($C369>=R$6,$C369<=R$6+R$7-1),R$9/R$7*$K369,0) -> 0 | S369: =IF(AND($C369>=S$6,$C369<=S$6+S$7-1),S$9/S$7*$K369,0) -> 0 | T369: =SUM(P369:S369) -> 0 | V369: =IF(AND($C369>=V$6,$C369<=V$6+V$7-1),V$9/V$7*$K369,0) -> 0 | W369: =IF(AND($C369>=W$6,$C369<=W$6+W$7-1),W$9/W$7*$K369,0) -> 0 | X369: =IF(AND($C369>=X$6,$C369<=X$6+X$7-1),X$9/X$7*$K369,0) -> 0 | Y369: =IF(AND($C369>=Y$6,$C369<=Y$6+Y$7-1),Y$9/Y$7*$K369,0) -> 0 | Z369: =SUM(V369:Y369) -> 0
C370: =C369+1 -> 360 | D370: =EOMONTH(D369,0)+1 -> 55488 | E370: =INT(INT(C370+2)/3) -> 120 | F370: ="Q"&INT((MONTH(D370)/4)+1)&"-"&RIGHT(YEAR(D370),2) -> Q4-51 | G370: =MIN(INT(YEARFRAC(D$11,D382)),30) -> 30 | H370: =YEAR(D370) -> 2051 | J370: =DATA!L370 -> 1.8181787 | K370: =DATA!M370 -> 1.3351535 | L370: =DATA!N370 -> 1 | M370: =DATA!O370 -> 1 | N370: =DATA!P370 -> 1 | O370: =DATA!Q370 -> 0 | P370: =IF(AND($C370>=P$6,$C370<=P$6+P$7-1),P$9/P$7*$K370,0) -> 0 | Q370: =IF(AND($C370>=Q$6,$C370<=Q$6+Q$7-1),Q$9/Q$7*$K370,0) -> 0 | R370: =IF(AND($C370>=R$6,$C370<=R$6+R$7-1),R$9/R$7*$K370,0) -> 0 | S370: =IF(AND($C370>=S$6,$C370<=S$6+S$7-1),S$9/S$7*$K370,0) -> 0 | T370: =SUM(P370:S370) -> 0 | U370: =DATA!W370 -> 0 | V370: =IF(AND($C370>=V$6,$C370<=V$6+V$7-1),V$9/V$7*$K370,0) -> 0 | W370: =IF(AND($C370>=W$6,$C370<=W$6+W$7-1),W$9/W$7*$K370,0) -> 0 | X370: =IF(AND($C370>=X$6,$C370<=X$6+X$7-1),X$9/X$7*$K370,0) -> 0 | Y370: =IF(AND($C370>=Y$6,$C370<=Y$6+Y$7-1),Y$9/Y$7*$K370,0) -> 0 | Z370: =SUM(V370:Y370) -> 0 | AA370: =DATA!AC370 -> 0 | AB370: =DATA!AD370 -> 0 | AC370: =DATA!AE370 -> 0 | AD370: =DATA!AF370 -> 0 | AE370: =DATA!AG370 -> 0
G373: 31

Sheet DATA
E3: Lookup Lists & Data Validation
E7: Periocity | L7: Rates (5 max) | R7: Lot Products | Y7: Lot Product Validation | AQ7: Budget Validation | BF7: Misc Factors
L8: {=TRANSPOSE(iGeneral!D25:D29)} -> Price | M8: Cost | N8: 0 | O8: 0 | P8: 0 | BG8: Contingency
C9: NAVIGATION | L9: =IFERROR(_xlfn.XLOOKUP(L$8,iGeneral!$D$25:$D$29,iGeneral!$F$25:$F$29),"") -> 1 | M9: =IFERROR(_xlfn.XLOOKUP(M$8,iGeneral!$D$25:$D$29,iGeneral!$F$25:$F$29),"") -> 2 | N9: =IFERROR(_xlfn.XLOOKUP(N$8,iGeneral!$D$25:$D$29,iGeneral!$F$25:$F$29),"") | O9: =IFERROR(_xlfn.XLOOKUP(O$8,iGeneral!$D$25:$D$29,iGeneral!$F$25:$F$29),"") | P9: =IFERROR(_xlfn.XLOOKUP(P$8,iGeneral!$D$25:$D$29,iGeneral!$F$25:$F$29),"") | S9: Use | T9: Lot | U9: Lot | V9: Lot | W9: 0.57 | Y9: Use | Z9: Lot | AV9: ` | BG9: Rates
C10: {=TRANSPOSE(_xlfn.UNIQUE(_xlfn._xlws.FILTER(E7:BX7,E7:BX7<>0)))} -> Periocity | E10: Mo | F10: Date | G10: Qtr | H10: Qtr-Yr | I10: Yr | J10: Date-Yr | L10: =IFERROR(_xlfn.XLOOKUP(L$8,iGeneral!$D$25:$D$29,iGeneral!$E$25:$E$29),0) -> 0.02 | M10: =IFERROR(_xlfn.XLOOKUP(M$8,iGeneral!$D$25:$D$29,iGeneral!$E$25:$E$29),0) -> 0.01 | N10: =IFERROR(_xlfn.XLOOKUP(N$8,iGeneral!$D$25:$D$29,iGeneral!$E$25:$E$29),0) -> 0 | O10: =IFERROR(_xlfn.XLOOKUP(O$8,iGeneral!$D$25:$D$29,iGeneral!$E$25:$E$29),0) -> 0 | P10: =IFERROR(_xlfn.XLOOKUP(P$8,iGeneral!$D$25:$D$29,iGeneral!$E$25:$E$29),0) -> 0 | R10: Product | S10: Code | T10: Width | U10: Depth | V10: Area | W10: DUA | Y10: Code | Z10: Products | AQ10: Cost Center | AR10: Category | AT10: =AQ10 -> Cost Center | AU10: Category | BG10: {=_xlfn.UNIQUE(_xlfn._xlws.FILTER(iGeneral!$F$41:$F$45,iGeneral!$F$41:$F$45<>0))} -> 0.05
C11: Rates (5 max) | E11: 1 | F11: =i_Date.Start -> 44562 | G11: =INT(INT(E11+2)/3) -> 1 | H11: ="Q"&INT((MONTH(F11)/4)+1)&"-"&RIGHT(YEAR(F11),2) -> Q1-22 | I11: =MIN(INT(YEARFRAC(F$11,F23)),30) -> 1 | J11: =YEAR(F11) -> 2022 | L11: 1 | M11: 1 | N11: 1 | O11: =N11 -> 1 | P11: =O11 -> 1 | R11: =CONCATENATE(T11,"x",U11) -> 40x90 | S11: MHDR | T11: 40 | U11: 90 | V11: =T11*U11 -> 3600 | W11: =43560/(Table4[[#This Row],[Area]])*W$9 -> 6.897 | Y11: {=_xlfn.UNIQUE(Table4[Code])} -> MHDR | Z11: {=IFERROR(TRANSPOSE(_xlfn._xlws.SORT(_xlfn._xlws.FILTER($R$11:$R$45,$S$11:$S$45=iMPC!P10))),0)} -> 60x115 | AA11: 60x120 | AB11: 60x125 | AC11: 60x130 | AD11: 65x120 | AE11: 65x125 | AF11: 70x125 | AG11: 70x130 | AH11: 70x135 | AI11: 80x125 | AJ11: 80x130 | AK11: 80x135 | AL11: 80x140 | AM11: 90x130 | AN11: 90x135 | AO11: 90x140 | AQ11: Acquisition | AR11: Deposits | AT11: {=_xlfn.UNIQUE(AQ11:AQ72)} -> Acquisition | AU11: {=IFERROR(TRANSPOSE(_xlfn._xlws.SORT(_xlfn._xlws.FILTER($AR$11:$AR$72,$AQ$11:$AQ$72=Budget!G4))),0)} -> Closing | AV11: Deposits | AW11: Diligence | AX11: Legal | AY11: Option Payments | AZ11: Other | BG11: 0.1
C12: Lot Products | E12: =E11+1 -> 2 | F12: =EOMONTH(F11,0)+1 -> 44593 | G12: =INT(INT(E12+2)/3) -> 1 | H12: ="Q"&INT((MONTH(F12)/4)+1)&"-"&RIGHT(YEAR(F12),2) -> Q1-22 | I12: =MIN(INT(YEARFRAC(F$11,F24)),30) -> 1 | J12: =YEAR(F12) -> 2022 | L12: =IF(I13<iGeneral!F$25,1,L11*(1+L$10/12)) -> 1.0016667 | M12: =IF(I11<iGeneral!F$26,1,M11*(1+M$10/12)) -> 1 | N12: =IF(I11<iGeneral!F$27,1,N11*(1+N$10/12)) -> 1 | O12: =IFERROR(IF(I11<iGeneral!F$28,1,O11*(1+O$10/12)),1) -> 1 | P12: =IFERROR(IF(DATA!$I12<iGeneral!F$29,1,P11*(1+P$10/12)),1) -> 1 | R12: =CONCATENATE(T12,"x",U12) -> 40x100 | S12: MHDR | T12: 40 | U12: 100 | V12: =T12*U12 -> 4000 | W12: =43560/(Table4[[#This Row],[Area]])*W$9 -> 6.2073 | Y12: MDR | Z12: {=IFERROR(TRANSPOSE(_xlfn._xlws.SORT(_xlfn._xlws.FILTER($R$11:$R$45,$S$11:$S$45=iMPC!P11))),0)} -> 60x115 | AA12: 60x120 | AB12: 60x125 | AC12: 60x130 | AD12: 65x120 | AE12: 65x125 | AF12: 70x125 | AG12: 70x130 | AH12: 70x135 | AI12: 80x125 | AJ12: 80x130 | AK12: 80x135 | AL12: 80x140 | AM12: 90x130 | AN12: 90x135 | AO12: 90x140 | AQ12: Acquisition | AR12: Option Payments | AT12: Entitlements | AU12: {=IFERROR(TRANSPOSE(_xlfn._xlws.SORT(_xlfn._xlws.FILTER($AR$11:$AR$72,$AQ$11:$AQ$72=Budget!G5))),0)} -> Dev Agmt | AV12: PrePlat [Block] | AW12: PrePlat [Subd] | AX12: Zoning | BG12: 0.2
C13: Lot Product Validation | E13: =E12+1 -> 3 | F13: =EOMONTH(F12,0)+1 -> 44621 | G13: =INT(INT(E13+2)/3) -> 1 | H13: ="Q"&INT((MONTH(F13)/4)+1)&"-"&RIGHT(YEAR(F13),2) -> Q1-22 | I13: =MIN(INT(YEARFRAC(F$11,F25)),30) -> 1 | J13: =YEAR(F13) -> 2022 | L13: =IF(I14<iGeneral!F$25,1,L12*(1+L$10/12)) -> 1.0033361 | M13: =IF(I12<iGeneral!F$26,1,M12*(1+M$10/12)) -> 1 | N13: =IF(I12<iGeneral!F$27,1,N12*(1+N$10/12)) -> 1 | O13: =IFERROR(IF(I12<iGeneral!F$28,1,O12*(1+O$10/12)),1) -> 1 | P13: =IFERROR(IF(DATA!$I13<iGeneral!F$29,1,P12*(1+P$10/12)),1) -> 1 | R13: =CONCATENATE(T13,"x",U13) -> 40x105 | S13: MHDR | T13: 40 | U13: 105 | V13: =T13*U13 -> 4200 | W13: =43560/(Table4[[#This Row],[Area]])*W$9 -> 5.9117143 | Y13: MLDR | Z13: {=IFERROR(TRANSPOSE(_xlfn._xlws.SORT(_xlfn._xlws.FILTER($R$11:$R$45,$S$11:$S$45=iMPC!P12))),0)} -> 40x110 | AA13: 40x115 | AB13: 45x105 | AC13: 45x110 | AD13: 45x115 | AE13: 45x120 | AF13: 50x110 | AG13: 50x115 | AH13: 50x120 | AI13: 50x125 | AJ13: 55x115 | AK13: 55x120 | AL13: 55x125 | AM13: 55x130 | AQ13: Acquisition | AR13: Diligence | AT13: Engineering | AU13: {=IFERROR(TRANSPOSE(_xlfn._xlws.SORT(_xlfn._xlws.FILTER($AR$11:$AR$72,$AQ$11:$AQ$72=Budget!G6))),0)} -> Dev Agmt | AV13: PrePlat [Block] | AW13: PrePlat [Subd] | AX13: Zoning | BG13: 5000
C14: Budget Validation | E14: =E13+1 -> 4 | F14: =EOMONTH(F13,0)+1 -> 44652 | G14: =INT(INT(E14+2)/3) -> 2 | H14: ="Q"&INT((MONTH(F14)/4)+1)&"-"&RIGHT(YEAR(F14),2) -> Q2-22 | I14: =MIN(INT(YEARFRAC(F$11,F26)),30) -> 1 | J14: =YEAR(F14) -> 2022 | L14: =IF(I15<iGeneral!F$25,1,L13*(1+L$10/12)) -> 1.0050083 | M14: =IF(I13<iGeneral!F$26,1,M13*(1+M$10/12)) -> 1 | N14: =IF(I13<iGeneral!F$27,1,N13*(1+N$10/12)) -> 1 | O14: =IFERROR(IF(I13<iGeneral!F$28,1,O13*(1+O$10/12)),1) -> 1 | P14: =IFERROR(IF(DATA!$I14<iGeneral!F$29,1,P13*(1+P$10/12)),1) -> 1 | R14: =CONCATENATE(T14,"x",U14) -> 40x110 | S14: MDR | T14: 40 | U14: 110 | V14: =T14*U14 -> 4400 | W14: =43560/(Table4[[#This Row],[Area]])*W$9 -> 5.643 | Y14: MU | Z14: {=IFERROR(TRANSPOSE(_xlfn._xlws.SORT(_xlfn._xlws.FILTER($R$11:$R$45,$S$11:$S$45=iMPC!P13))),0)} -> 40x110 | AA14: 40x115 | AB14: 45x105 | AC14: 45x110 | AD14: 45x115 | AE14: 45x120 | AF14: 50x110 | AG14: 50x115 | AH14: 50x120 | AI14: 50x125 | AJ14: 55x115 | AK14: 55x120 | AL14: 55x125 | AM14: 55x130 | AQ14: Acquisition | AR14: Legal | AT14: Offsites | AU14: {=IFERROR(TRANSPOSE(_xlfn._xlws.SORT(_xlfn._xlws.FILTER($AR$11:$AR$72,$AQ$11:$AQ$72=Budget!G7))),0)} -> Other | AV14: Project | AW14: Subdivisions
C15: Misc Factors | E15: =E14+1 -> 5 | F15: =EOMONTH(F14,0)+1 -> 44682 | G15: =INT(INT(E15+2)/3) -> 2 | H15: ="Q"&INT((MONTH(F15)/4)+1)&"-"&RIGHT(YEAR(F15),2) -> Q2-22 | I15: =MIN(INT(YEARFRAC(F$11,F27)),30) -> 1 | J15: =YEAR(F15) -> 2022 | L15: =IF(I16<iGeneral!F$25,1,L14*(1+L$10/12)) -> 1.0066834 | M15: =IF(I14<iGeneral!F$26,1,M14*(1+M$10/12)) -> 1 | N15: =IF(I14<iGeneral!F$27,1,N14*(1+N$10/12)) -> 1 | O15: =IFERROR(IF(I14<iGeneral!F$28,1,O14*(1+O$10/12)),1) -> 1 | P15: =IFERROR(IF(DATA!$I15<iGeneral!F$29,1,P14*(1+P$10/12)),1) -> 1 | R15: =CONCATENATE(T15,"x",U15) -> 40x115 | S15: MDR | T15: 40 | U15: 115 | V15: =T15*U15 -> 4600 | W15: =43560/(Table4[[#This Row],[Area]])*W$9 -> 5.3976522 | Y15: i | Z15: {=IFERROR(TRANSPOSE(_xlfn._xlws.SORT(_xlfn._xlws.FILTER($R$11:$R$45,$S$11:$S$45=iMPC!P14))),0)} -> 60x115 | AA15: 60x120 | AB15: 60x125 | AC15: 60x130 | AD15: 65x120 | AE15: 65x125 | AF15: 70x125 | AG15: 70x130 | AH15: 70x135 | AI15: 80x125 | AJ15: 80x130 | AK15: 80x135 | AL15: 80x140 | AM15: 90x130 | AN15: 90x135 | AO15: 90x140 | AQ15: Acquisition | AR15: Closing | AT15: Onsites | AU15: {=IFERROR(TRANSPOSE(_xlfn._xlws.SORT(_xlfn._xlws.FILTER($AR$11:$AR$72,$AQ$11:$AQ$72=Budget!G8))),0)} -> Other | AV15: Project | AW15: Subdivisions
E16: =E15+1 -> 6 | F16: =EOMONTH(F15,0)+1 -> 44713 | G16: =INT(INT(E16+2)/3) -> 2 | H16: ="Q"&INT((MONTH(F16)/4)+1)&"-"&RIGHT(YEAR(F16),2) -> Q2-22 | I16: =MIN(INT(YEARFRAC(F$11,F28)),30) -> 1 | J16: =YEAR(F16) -> 2022 | L16: =IF(I17<iGeneral!F$25,1,L15*(1+L$10/12)) -> 1.0083612 | M16: =IF(I15<iGeneral!F$26,1,M15*(1+M$10/12)) -> 1 | N16: =IF(I15<iGeneral!F$27,1,N15*(1+N$10/12)) -> 1 | O16: =IFERROR(IF(I15<iGeneral!F$28,1,O15*(1+O$10/12)),1) -> 1 | P16: =IFERROR(IF(DATA!$I16<iGeneral!F$29,1,P15*(1+P$10/12)),1) -> 1 | R16: =CONCATENATE(T16,"x",U16) -> 45x105 | S16: MDR | T16: 45 | U16: 105 | V16: =T16*U16 -> 4725 | W16: =43560/(Table4[[#This Row],[Area]])*W$9 -> 5.2548571 | Z16: {=IFERROR(TRANSPOSE(_xlfn._xlws.SORT(_xlfn._xlws.FILTER($R$11:$R$45,$S$11:$S$45=iMPC!P15))),0)} -> 40x110 | AA16: 40x115 | AB16: 45x105 | AC16: 45x110 | AD16: 45x115 | AE16: 45x120 | AF16: 50x110 | AG16: 50x115 | AH16: 50x120 | AI16: 50x125 | AJ16: 55x115 | AK16: 55x120 | AL16: 55x125 | AM16: 55x130 | AQ16: Acquisition | AR16: Other | AT16: Exactions | AU16: {=IFERROR(TRANSPOSE(_xlfn._xlws.SORT(_xlfn._xlws.FILTER($AR$11:$AR$72,$AQ$11:$AQ$72=Budget!G9))),0)} -> Other | AV16: Project | AW16: Subdivisions
E17: =E16+1 -> 7 | F17: =EOMONTH(F16,0)+1 -> 44743 | G17: =INT(INT(E17+2)/3) -> 3 | H17: ="Q"&INT((MONTH(F17)/4)+1)&"-"&RIGHT(YEAR(F17),2) -> Q2-22 | I17: =MIN(INT(YEARFRAC(F$11,F29)),30) -> 1 | J17: =YEAR(F17) -> 2022 | L17: =IF(I18<iGeneral!F$25,1,L16*(1+L$10/12)) -> 1.0100418 | M17: =IF(I16<iGeneral!F$26,1,M16*(1+M$10/12)) -> 1 | N17: =IF(I16<iGeneral!F$27,1,N16*(1+N$10/12)) -> 1 | O17: =IFERROR(IF(I16<iGeneral!F$28,1,O16*(1+O$10/12)),1) -> 1 | P17: =IFERROR(IF(DATA!$I17<iGeneral!F$29,1,P16*(1+P$10/12)),1) -> 1 | R17: =CONCATENATE(T17,"x",U17) -> 45x110 | S17: MDR | T17: 45 | U17: =U16+5 -> 110 | V17: =T17*U17 -> 4950 | W17: =43560/(Table4[[#This Row],[Area]])*W$9 -> 5.016 | Z17: {=IFERROR(TRANSPOSE(_xlfn._xlws.SORT(_xlfn._xlws.FILTER($R$11:$R$45,$S$11:$S$45=iMPC!P16))),0)} -> 40x110 | AA17: 40x115 | AB17: 45x105 | AC17: 45x110 | AD17: 45x115 | AE17: 45x120 | AF17: 50x110 | AG17: 50x115 | AH17: 50x120 | AI17: 50x125 | AJ17: 55x115 | AK17: 55x120 | AL17: 55x125 | AM17: 55x130 | AQ17: Entitlements | AR17: Zoning | AT17: Operation | AU17: {=IFERROR(TRANSPOSE(_xlfn._xlws.SORT(_xlfn._xlws.FILTER($AR$11:$AR$72,$AQ$11:$AQ$72=Budget!G10))),0)} -> Amenities | AV17: Concrete | AW17: Drainage | AX17: Dry Utilities | AY17: Earthwork | AZ17: Landscaping | BA17: Other | BB17: Paving | BC17: Permits | BD17: Removals / Aband | BE17: Storm Drain | BF17: Survey | BG17: Testing | BH17: Walls / Monmt | BI17: Wastewater | BJ17: Water
E18: =E17+1 -> 8 | F18: =EOMONTH(F17,0)+1 -> 44774 | G18: =INT(INT(E18+2)/3) -> 3 | H18: ="Q"&INT((MONTH(F18)/4)+1)&"-"&RIGHT(YEAR(F18),2) -> Q3-22 | I18: =MIN(INT(YEARFRAC(F$11,F30)),30) -> 1 | J18: =YEAR(F18) -> 2022 | L18: =IF(I19<iGeneral!F$25,1,L17*(1+L$10/12)) -> 1.0117252 | M18: =IF(I17<iGeneral!F$26,1,M17*(1+M$10/12)) -> 1 | N18: =IF(I17<iGeneral!F$27,1,N17*(1+N$10/12)) -> 1 | O18: =IFERROR(IF(I17<iGeneral!F$28,1,O17*(1+O$10/12)),1) -> 1 | P18: =IFERROR(IF(DATA!$I18<iGeneral!F$29,1,P17*(1+P$10/12)),1) -> 1 | R18: =CONCATENATE(T18,"x",U18) -> 45x115 | S18: MDR | T18: 45 | U18: =U17+5 -> 115 | V18: =T18*U18 -> 5175 | W18: =43560/(Table4[[#This Row],[Area]])*W$9 -> 4.797913 | Z18: {=IFERROR(TRANSPOSE(_xlfn._xlws.SORT(_xlfn._xlws.FILTER($R$11:$R$45,$S$11:$S$45=iMPC!P17))),0)} -> 40x110 | AA18: 40x115 | AB18: 45x105 | AC18: 45x110 | AD18: 45x115 | AE18: 45x120 | AF18: 50x110 | AG18: 50x115 | AH18: 50x120 | AI18: 50x125 | AJ18: 55x115 | AK18: 55x120 | AL18: 55x125 | AM18: 55x130 | AQ18: Entitlements | AR18: Dev Agmt | AT18: Ownership | AU18: {=IFERROR(TRANSPOSE(_xlfn._xlws.SORT(_xlfn._xlws.FILTER($AR$11:$AR$72,$AQ$11:$AQ$72=Budget!G11))),0)} -> Amenities | AV18: Concrete | AW18: Drainage | AX18: Dry Utilities | AY18: Earthwork | AZ18: Landscaping | BA18: Other | BB18: Paving | BC18: Permits | BD18: Removals / Aband | BE18: Storm Drain | BF18: Survey | BG18: Testing | BH18: Walls / Monmt | BI18: Wastewater | BJ18: Water
E19: =E18+1 -> 9 | F19: =EOMONTH(F18,0)+1 -> 44805 | G19: =INT(INT(E19+2)/3) -> 3 | H19: ="Q"&INT((MONTH(F19)/4)+1)&"-"&RIGHT(YEAR(F19),2) -> Q3-22 | I19: =MIN(INT(YEARFRAC(F$11,F31)),30) -> 1 | J19: =YEAR(F19) -> 2022 | L19: =IF(I20<iGeneral!F$25,1,L18*(1+L$10/12)) -> 1.0134114 | M19: =IF(I18<iGeneral!F$26,1,M18*(1+M$10/12)) -> 1 | N19: =IF(I18<iGeneral!F$27,1,N18*(1+N$10/12)) -> 1 | O19: =IFERROR(IF(I18<iGeneral!F$28,1,O18*(1+O$10/12)),1) -> 1 | P19: =IFERROR(IF(DATA!$I19<iGeneral!F$29,1,P18*(1+P$10/12)),1) -> 1 | R19: =CONCATENATE(T19,"x",U19) -> 45x120 | S19: MDR | T19: 45 | U19: =U18+5 -> 120 | V19: =T19*U19 -> 5400 | W19: =43560/(Table4[[#This Row],[Area]])*W$9 -> 4.598 | Z19: {=IFERROR(TRANSPOSE(_xlfn._xlws.SORT(_xlfn._xlws.FILTER($R$11:$R$45,$S$11:$S$45=iMPC!P18))),0)} -> 40x110 | AA19: 40x115 | AB19: 45x105 | AC19: 45x110 | AD19: 45x115 | AE19: 45x120 | AF19: 50x110 | AG19: 50x115 | AH19: 50x120 | AI19: 50x125 | AJ19: 55x115 | AK19: 55x120 | AL19: 55x125 | AM19: 55x130 | AQ19: Entitlements | AR19: PrePlat [Block] | AU19: {=IFERROR(TRANSPOSE(_xlfn._xlws.SORT(_xlfn._xlws.FILTER($AR$11:$AR$72,$AQ$11:$AQ$72=Budget!G12))),0)} -> Offsite | AV19: Onsite | AW19: Other
E20: =E19+1 -> 10 | F20: =EOMONTH(F19,0)+1 -> 44835 | G20: =INT(INT(E20+2)/3) -> 4 | H20: ="Q"&INT((MONTH(F20)/4)+1)&"-"&RIGHT(YEAR(F20),2) -> Q3-22 | I20: =MIN(INT(YEARFRAC(F$11,F32)),30) -> 1 | J20: =YEAR(F20) -> 2022 | L20: =IF(I21<iGeneral!F$25,1,L19*(1+L$10/12)) -> 1.0151004 | M20: =IF(I19<iGeneral!F$26,1,M19*(1+M$10/12)) -> 1 | N20: =IF(I19<iGeneral!F$27,1,N19*(1+N$10/12)) -> 1 | O20: =IFERROR(IF(I19<iGeneral!F$28,1,O19*(1+O$10/12)),1) -> 1 | P20: =IFERROR(IF(DATA!$I20<iGeneral!F$29,1,P19*(1+P$10/12)),1) -> 1 | R20: =CONCATENATE(T20,"x",U20) -> 50x110 | S20: MDR | T20: 50 | U20: 110 | V20: =T20*U20 -> 5500 | W20: =43560/(Table4[[#This Row],[Area]])*W$9 -> 4.5144 | Z20: {=IFERROR(TRANSPOSE(_xlfn._xlws.SORT(_xlfn._xlws.FILTER($R$11:$R$45,$S$11:$S$45=iMPC!P19))),0)} -> 40x110 | AA20: 40x115 | AB20: 45x105 | AC20: 45x110 | AD20: 45x115 | AE20: 45x120 | AF20: 50x110 | AG20: 50x115 | AH20: 50x120 | AI20: 50x125 | AJ20: 55x115 | AK20: 55x120 | AL20: 55x125 | AM20: 55x130 | AQ20: Entitlements | AR20: PrePlat [Subd] | AU20: {=IFERROR(TRANSPOSE(_xlfn._xlws.SORT(_xlfn._xlws.FILTER($AR$11:$AR$72,$AQ$11:$AQ$72=Budget!G13))),0)} -> 0
E21: =E20+1 -> 11 | F21: =EOMONTH(F20,0)+1 -> 44866 | G21: =INT(INT(E21+2)/3) -> 4 | H21: ="Q"&INT((MONTH(F21)/4)+1)&"-"&RIGHT(YEAR(F21),2) -> Q3-22 | I21: =MIN(INT(YEARFRAC(F$11,F33)),30) -> 1 | J21: =YEAR(F21) -> 2022 | L21: =IF(I22<iGeneral!F$25,1,L20*(1+L$10/12)) -> 1.0167922 | M21: =IF(I20<iGeneral!F$26,1,M20*(1+M$10/12)) -> 1 | N21: =IF(I20<iGeneral!F$27,1,N20*(1+N$10/12)) -> 1 | O21: =IFERROR(IF(I20<iGeneral!F$28,1,O20*(1+O$10/12)),1) -> 1 | P21: =IFERROR(IF(DATA!$I21<iGeneral!F$29,1,P20*(1+P$10/12)),1) -> 1 | R21: =CONCATENATE(T21,"x",U21) -> 50x115 | S21: MDR | T21: 50 | U21: =U20+5 -> 115 | V21: =T21*U21 -> 5750 | W21: =43560/(Table4[[#This Row],[Area]])*W$9 -> 4.3181217 | Z21: {=IFERROR(TRANSPOSE(_xlfn._xlws.SORT(_xlfn._xlws.FILTER($R$11:$R$45,$S$11:$S$45=iMPC!P20))),0)} -> 60x115 | AA21: 60x120 | AB21: 60x125 | AC21: 60x130 | AD21: 65x120 | AE21: 65x125 | AF21: 70x125 | AG21: 70x130 | AH21: 70x135 | AI21: 80x125 | AJ21: 80x130 | AK21: 80x135 | AL21: 80x140 | AM21: 90x130 | AN21: 90x135 | AO21: 90x140 | AQ21: Engineering | AR21: Project | AU21: {=IFERROR(TRANSPOSE(_xlfn._xlws.SORT(_xlfn._xlws.FILTER($AR$11:$AR$72,$AQ$11:$AQ$72=Budget!G14))),0)} -> 0
E22: =E21+1 -> 12 | F22: =EOMONTH(F21,0)+1 -> 44896 | G22: =INT(INT(E22+2)/3) -> 4 | H22: ="Q"&INT((MONTH(F22)/4)+1)&"-"&RIGHT(YEAR(F22),2) -> Q4-22 | I22: =MIN(INT(YEARFRAC(F$11,F34)),30) -> 1 | J22: =YEAR(F22) -> 2022 | L22: =IF(I23<iGeneral!F$25,1,L21*(1+L$10/12)) -> 1.0184869 | M22: =IF(I21<iGeneral!F$26,1,M21*(1+M$10/12)) -> 1 | N22: =IF(I21<iGeneral!F$27,1,N21*(1+N$10/12)) -> 1 | O22: =IFERROR(IF(I21<iGeneral!F$28,1,O21*(1+O$10/12)),1) -> 1 | P22: =IFERROR(IF(DATA!$I22<iGeneral!F$29,1,P21*(1+P$10/12)),1) -> 1 | R22: =CONCATENATE(T22,"x",U22) -> 50x120 | S22: MDR | T22: 50 | U22: =U21+5 -> 120 | V22: =T22*U22 -> 6000 | W22: =43560/(Table4[[#This Row],[Area]])*W$9 -> 4.1382 | Z22: {=IFERROR(TRANSPOSE(_xlfn._xlws.SORT(_xlfn._xlws.FILTER($R$11:$R$45,$S$11:$S$45=iMPC!P21))),0)} -> 60x115 | AA22: 60x120 | AB22: 60x125 | AC22: 60x130 | AD22: 65x120 | AE22: 65x125 | AF22: 70x125 | AG22: 70x130 | AH22: 70x135 | AI22: 80x125 | AJ22: 80x130 | AK22: 80x135 | AL22: 80x140 | AM22: 90x130 | AN22: 90x135 | AO22: 90x140 | AQ22: Engineering | AR22: Subdivisions | AU22: {=IFERROR(TRANSPOSE(_xlfn._xlws.SORT(_xlfn._xlws.FILTER($AR$11:$AR$72,$AQ$11:$AQ$72=Budget!G15))),0)} -> 0
E23: =E22+1 -> 13 | F23: =EOMONTH(F22,0)+1 -> 44927 | G23: =INT(INT(E23+2)/3) -> 5 | H23: ="Q"&INT((MONTH(F23)/4)+1)&"-"&RIGHT(YEAR(F23),2) -> Q1-23 | I23: =MIN(INT(YEARFRAC(F$11,F35)),30) -> 2 | J23: =YEAR(F23) -> 2023 | L23: =IF(I24<iGeneral!F$25,1,L22*(1+L$10/12)) -> 1.0201844 | M23: =IF(I22<iGeneral!F$26,1,M22*(1+M$10/12)) -> 1 | N23: =IF(I22<iGeneral!F$27,1,N22*(1+N$10/12)) -> 1 | O23: =IFERROR(IF(I22<iGeneral!F$28,1,O22*(1+O$10/12)),1) -> 1 | P23: =IFERROR(IF(DATA!$I23<iGeneral!F$29,1,P22*(1+P$10/12)),1) -> 1 | R23: =CONCATENATE(T23,"x",U23) -> 50x125 | S23: MDR | T23: 50 | U23: =U22+5 -> 125 | V23: =T23*U23 -> 6250 | W23: =43560/(Table4[[#This Row],[Area]])*W$9 -> 3.972672 | Z23: {=IFERROR(TRANSPOSE(_xlfn._xlws.SORT(_xlfn._xlws.FILTER($R$11:$R$45,$S$11:$S$45=iMPC!P22))),0)} -> 40x110 | AA23: 40x115 | AB23: 45x105 | AC23: 45x110 | AD23: 45x115 | AE23: 45x120 | AF23: 50x110 | AG23: 50x115 | AH23: 50x120 | AI23: 50x125 | AJ23: 55x115 | AK23: 55x120 | AL23: 55x125 | AM23: 55x130 | AQ23: Engineering | AR23: Other | AU23: {=IFERROR(TRANSPOSE(_xlfn._xlws.SORT(_xlfn._xlws.FILTER($AR$11:$AR$72,$AQ$11:$AQ$72=Budget!G16))),0)} -> 0
E24: =E23+1 -> 14 | F24: =EOMONTH(F23,0)+1 -> 44958 | G24: =INT(INT(E24+2)/3) -> 5 | H24: ="Q"&INT((MONTH(F24)/4)+1)&"-"&RIGHT(YEAR(F24),2) -> Q1-23 | I24: =MIN(INT(YEARFRAC(F$11,F36)),30) -> 2 | J24: =YEAR(F24) -> 2023 | L24: =IF(I25<iGeneral!F$25,1,L23*(1+L$10/12)) -> 1.0218847 | M24: =IF(I23<iGeneral!F$26,1,M23*(1+M$10/12)) -> 1.0008333 | N24: =IF(I23<iGeneral!F$27,1,N23*(1+N$10/12)) -> 1 | O24: =IFERROR(IF(I23<iGeneral!F$28,1,O23*(1+O$10/12)),1) -> 1 | P24: =IFERROR(IF(DATA!$I24<iGeneral!F$29,1,P23*(1+P$10/12)),1) -> 1 | R24: =CONCATENATE(T24,"x",U24) -> 55x115 | S24: MDR | T24: 55 | U24: 115 | V24: =T24*U24 -> 6325 | W24: =43560/(Table4[[#This Row],[Area]])*W$9 -> 3.9255652 | Z24: {=IFERROR(TRANSPOSE(_xlfn._xlws.SORT(_xlfn._xlws.FILTER($R$11:$R$45,$S$11:$S$45=iMPC!P23))),0)} -> 40x110 | AA24: 40x115 | AB24: 45x105 | AC24: 45x110 | AD24: 45x115 | AE24: 45x120 | AF24: 50x110 | AG24: 50x115 | AH24: 50x120 | AI24: 50x125 | AJ24: 55x115 | AK24: 55x120 | AL24: 55x125 | AM24: 55x130 | AQ24: Offsites | AR24: Survey | AU24: {=IFERROR(TRANSPOSE(_xlfn._xlws.SORT(_xlfn._xlws.FILTER($AR$11:$AR$72,$AQ$11:$AQ$72=Budget!G17))),0)} -> 0
E25: =E24+1 -> 15 | F25: =EOMONTH(F24,0)+1 -> 44986 | G25: =INT(INT(E25+2)/3) -> 5 | H25: ="Q"&INT((MONTH(F25)/4)+1)&"-"&RIGHT(YEAR(F25),2) -> Q1-23 | I25: =MIN(INT(YEARFRAC(F$11,F37)),30) -> 2 | J25: =YEAR(F25) -> 2023 | L25: =IF(I26<iGeneral!F$25,1,L24*(1+L$10/12)) -> 1.0235878 | M25: =IF(I24<iGeneral!F$26,1,M24*(1+M$10/12)) -> 1.0016674 | N25: =IF(I24<iGeneral!F$27,1,N24*(1+N$10/12)) -> 1 | O25: =IFERROR(IF(I24<iGeneral!F$28,1,O24*(1+O$10/12)),1) -> 1 | P25: =IFERROR(IF(DATA!$I25<iGeneral!F$29,1,P24*(1+P$10/12)),1) -> 1 | R25: =CONCATENATE(T25,"x",U25) -> 55x120 | S25: MDR | T25: 55 | U25: =U24+5 -> 120 | V25: =T25*U25 -> 6600 | W25: =43560/(Table4[[#This Row],[Area]])*W$9 -> 3.762 | Z25: {=IFERROR(TRANSPOSE(_xlfn._xlws.SORT(_xlfn._xlws.FILTER($R$11:$R$45,$S$11:$S$45=iMPC!P24))),0)} -> 40x110 | AA25: 40x115 | AB25: 45x105 | AC25: 45x110 | AD25: 45x115 | AE25: 45x120 | AF25: 50x110 | AG25: 50x115 | AH25: 50x120 | AI25: 50x125 | AJ25: 55x115 | AK25: 55x120 | AL25: 55x125 | AM25: 55x130 | AQ25: Offsites | AR25: Testing | AU25: {=IFERROR(TRANSPOSE(_xlfn._xlws.SORT(_xlfn._xlws.FILTER($AR$11:$AR$72,$AQ$11:$AQ$72=Budget!G18))),0)} -> 0
E26: =E25+1 -> 16 | F26: =EOMONTH(F25,0)+1 -> 45017 | G26: =INT(INT(E26+2)/3) -> 6 | H26: ="Q"&INT((MONTH(F26)/4)+1)&"-"&RIGHT(YEAR(F26),2) -> Q2-23 | I26: =MIN(INT(YEARFRAC(F$11,F38)),30) -> 2 | J26: =YEAR(F26) -> 2023 | L26: =IF(I27<iGeneral!F$25,1,L25*(1+L$10/12)) -> 1.0252938 | M26: =IF(I25<iGeneral!F$26,1,M25*(1+M$10/12)) -> 1.0025021 | N26: =IF(I25<iGeneral!F$27,1,N25*(1+N$10/12)) -> 1 | O26: =IFERROR(IF(I25<iGeneral!F$28,1,O25*(1+O$10/12)),1) -> 1 | P26: =IFERROR(IF(DATA!$I26<iGeneral!F$29,1,P25*(1+P$10/12)),1) -> 1 | R26: =CONCATENATE(T26,"x",U26) -> 55x125 | S26: MDR | T26: 55 | U26: =U25+5 -> 125 | V26: =T26*U26 -> 6875 | W26: =43560/(Table4[[#This Row],[Area]])*W$9 -> 3.61152 | Z26: {=IFERROR(TRANSPOSE(_xlfn._xlws.SORT(_xlfn._xlws.FILTER($R$11:$R$45,$S$11:$S$45=iMPC!P25))),0)} -> 40x100 | AA26: 40x105 | AB26: 40x90 | AQ26: Offsites | AR26: Removals / Aband | AU26: {=IFERROR(TRANSPOSE(_xlfn._xlws.SORT(_xlfn._xlws.FILTER($AR$11:$AR$72,$AQ$11:$AQ$72=Budget!G19))),0)} -> 0
E27: =E26+1 -> 17 | F27: =EOMONTH(F26,0)+1 -> 45047 | G27: =INT(INT(E27+2)/3) -> 6 | H27: ="Q"&INT((MONTH(F27)/4)+1)&"-"&RIGHT(YEAR(F27),2) -> Q2-23 | I27: =MIN(INT(YEARFRAC(F$11,F39)),30) -> 2 | J27: =YEAR(F27) -> 2023 | L27: =IF(I28<iGeneral!F$25,1,L26*(1+L$10/12)) -> 1.0270026 | M27: =IF(I26<iGeneral!F$26,1,M26*(1+M$10/12)) -> 1.0033375 | N27: =IF(I26<iGeneral!F$27,1,N26*(1+N$10/12)) -> 1 | O27: =IFERROR(IF(I26<iGeneral!F$28,1,O26*(1+O$10/12)),1) -> 1 | P27: =IFERROR(IF(DATA!$I27<iGeneral!F$29,1,P26*(1+P$10/12)),1) -> 1 | R27: =CONCATENATE(T27,"x",U27) -> 55x130 | S27: MDR | T27: 55 | U27: =U26+5 -> 130 | V27: =T27*U27 -> 7150 | W27: =43560/(Table4[[#This Row],[Area]])*W$9 -> 3.4726154 | Z27: {=IFERROR(TRANSPOSE(_xlfn._xlws.SORT(_xlfn._xlws.FILTER($R$11:$R$45,$S$11:$S$45=iMPC!P26))),0)} -> x | AQ27: Offsites | AR27: Permits | AU27: {=IFERROR(TRANSPOSE(_xlfn._xlws.SORT(_xlfn._xlws.FILTER($AR$11:$AR$72,$AQ$11:$AQ$72=Budget!G20))),0)} -> 0
E28: =E27+1 -> 18 | F28: =EOMONTH(F27,0)+1 -> 45078 | G28: =INT(INT(E28+2)/3) -> 6 | H28: ="Q"&INT((MONTH(F28)/4)+1)&"-"&RIGHT(YEAR(F28),2) -> Q2-23 | I28: =MIN(INT(YEARFRAC(F$11,F40)),30) -> 2 | J28: =YEAR(F28) -> 2023 | L28: =IF(I29<iGeneral!F$25,1,L27*(1+L$10/12)) -> 1.0287143 | M28: =IF(I27<iGeneral!F$26,1,M27*(1+M$10/12)) -> 1.0041736 | N28: =IF(I27<iGeneral!F$27,1,N27*(1+N$10/12)) -> 1 | O28: =IFERROR(IF(I27<iGeneral!F$28,1,O27*(1+O$10/12)),1) -> 1 | P28: =IFERROR(IF(DATA!$I28<iGeneral!F$29,1,P27*(1+P$10/12)),1) -> 1 | R28: =CONCATENATE(T28,"x",U28) -> 60x115 | S28: MLDR | T28: 60 | U28: 115 | V28: =T28*U28 -> 6900 | W28: =43560/(Table4[[#This Row],[Area]])*W$9 -> 3.5984348 | Z28: {=IFERROR(TRANSPOSE(_xlfn._xlws.SORT(_xlfn._xlws.FILTER($R$11:$R$45,$S$11:$S$45=iMPC!P27))),0)} -> 40x100 | AA28: 40x105 | AB28: 40x90 | AQ28: Offsites | AR28: Earthwork | AU28: {=IFERROR(TRANSPOSE(_xlfn._xlws.SORT(_xlfn._xlws.FILTER($AR$11:$AR$72,$AQ$11:$AQ$72=Budget!G21))),0)} -> 0
E29: =E28+1 -> 19 | F29: =EOMONTH(F28,0)+1 -> 45108 | G29: =INT(INT(E29+2)/3) -> 7 | H29: ="Q"&INT((MONTH(F29)/4)+1)&"-"&RIGHT(YEAR(F29),2) -> Q2-23 | I29: =MIN(INT(YEARFRAC(F$11,F41)),30) -> 2 | J29: =YEAR(F29) -> 2023 | L29: =IF(I30<iGeneral!F$25,1,L28*(1+L$10/12)) -> 1.0304288 | M29: =IF(I28<iGeneral!F$26,1,M28*(1+M$10/12)) -> 1.0050104 | N29: =IF(I28<iGeneral!F$27,1,N28*(1+N$10/12)) -> 1 | O29: =IFERROR(IF(I28<iGeneral!F$28,1,O28*(1+O$10/12)),1) -> 1 | P29: =IFERROR(IF(DATA!$I29<iGeneral!F$29,1,P28*(1+P$10/12)),1) -> 1 | R29: =CONCATENATE(T29,"x",U29) -> 60x120 | S29: MLDR | T29: 60 | U29: 120 | V29: =T29*U29 -> 7200 | W29: =43560/(Table4[[#This Row],[Area]])*W$9 -> 3.4485 | Z29: {=IFERROR(TRANSPOSE(_xlfn._xlws.SORT(_xlfn._xlws.FILTER($R$11:$R$45,$S$11:$S$45=iMPC!P28))),0)} -> x | AQ29: Offsites | AR29: Wastewater | AU29: {=IFERROR(TRANSPOSE(_xlfn._xlws.SORT(_xlfn._xlws.FILTER($AR$11:$AR$72,$AQ$11:$AQ$72=Budget!G22))),0)} -> 0
E30: =E29+1 -> 20 | F30: =EOMONTH(F29,0)+1 -> 45139 | G30: =INT(INT(E30+2)/3) -> 7 | H30: ="Q"&INT((MONTH(F30)/4)+1)&"-"&RIGHT(YEAR(F30),2) -> Q3-23 | I30: =MIN(INT(YEARFRAC(F$11,F42)),30) -> 2 | J30: =YEAR(F30) -> 2023 | L30: =IF(I31<iGeneral!F$25,1,L29*(1+L$10/12)) -> 1.0321462 | M30: =IF(I29<iGeneral!F$26,1,M29*(1+M$10/12)) -> 1.0058479 | N30: =IF(I29<iGeneral!F$27,1,N29*(1+N$10/12)) -> 1 | O30: =IFERROR(IF(I29<iGeneral!F$28,1,O29*(1+O$10/12)),1) -> 1 | P30: =IFERROR(IF(DATA!$I30<iGeneral!F$29,1,P29*(1+P$10/12)),1) -> 1 | R30: =CONCATENATE(T30,"x",U30) -> 60x125 | S30: MLDR | T30: 60 | U30: 125 | V30: =T30*U30 -> 7500 | W30: =43560/(Table4[[#This Row],[Area]])*W$9 -> 3.31056 | Z30: {=IFERROR(TRANSPOSE(_xlfn._xlws.SORT(_xlfn._xlws.FILTER($R$11:$R$45,$S$11:$S$45=iMPC!P29))),0)} -> x | AQ30: Offsites | AR30: Water | AU30: {=IFERROR(TRANSPOSE(_xlfn._xlws.SORT(_xlfn._xlws.FILTER($AR$11:$AR$72,$AQ$11:$AQ$72=Budget!G23))),0)} -> 0
E31: =E30+1 -> 21 | F31: =EOMONTH(F30,0)+1 -> 45170 | G31: =INT(INT(E31+2)/3) -> 7 | H31: ="Q"&INT((MONTH(F31)/4)+1)&"-"&RIGHT(YEAR(F31),2) -> Q3-23 | I31: =MIN(INT(YEARFRAC(F$11,F43)),30) -> 2 | J31: =YEAR(F31) -> 2023 | L31: =IF(I32<iGeneral!F$25,1,L30*(1+L$10/12)) -> 1.0338664 | M31: =IF(I30<iGeneral!F$26,1,M30*(1+M$10/12)) -> 1.0066861 | N31: =IF(I30<iGeneral!F$27,1,N30*(1+N$10/12)) -> 1 | O31: =IFERROR(IF(I30<iGeneral!F$28,1,O30*(1+O$10/12)),1) -> 1 | P31: =IFERROR(IF(DATA!$I31<iGeneral!F$29,1,P30*(1+P$10/12)),1) -> 1 | R31: =CONCATENATE(T31,"x",U31) -> 60x130 | S31: MLDR | T31: 60 | U31: 130 | V31: =T31*U31 -> 7800 | W31: =43560/(Table4[[#This Row],[Area]])*W$9 -> 3.1832308 | Z31: {=IFERROR(TRANSPOSE(_xlfn._xlws.SORT(_xlfn._xlws.FILTER($R$11:$R$45,$S$11:$S$45=iMPC!P30))),0)} -> x | AQ31: Offsites | AR31: Storm Drain | AU31: {=IFERROR(TRANSPOSE(_xlfn._xlws.SORT(_xlfn._xlws.FILTER($AR$11:$AR$72,$AQ$11:$AQ$72=Budget!G24))),0)} -> 0
E32: =E31+1 -> 22 | F32: =EOMONTH(F31,0)+1 -> 45200 | G32: =INT(INT(E32+2)/3) -> 8 | H32: ="Q"&INT((MONTH(F32)/4)+1)&"-"&RIGHT(YEAR(F32),2) -> Q3-23 | I32: =MIN(INT(YEARFRAC(F$11,F44)),30) -> 2 | J32: =YEAR(F32) -> 2023 | L32: =IF(I33<iGeneral!F$25,1,L31*(1+L$10/12)) -> 1.0355895 | M32: =IF(I31<iGeneral!F$26,1,M31*(1+M$10/12)) -> 1.007525 | N32: =IF(I31<iGeneral!F$27,1,N31*(1+N$10/12)) -> 1 | O32: =IFERROR(IF(I31<iGeneral!F$28,1,O31*(1+O$10/12)),1) -> 1 | P32: =IFERROR(IF(DATA!$I32<iGeneral!F$29,1,P31*(1+P$10/12)),1) -> 1 | R32: =CONCATENATE(T32,"x",U32) -> 65x120 | S32: MLDR | T32: 65 | U32: 120 | V32: =T32*U32 -> 7800 | W32: =43560/(Table4[[#This Row],[Area]])*W$9 -> 3.1832308 | Z32: {=IFERROR(TRANSPOSE(_xlfn._xlws.SORT(_xlfn._xlws.FILTER($R$11:$R$45,$S$11:$S$45=iMPC!P31))),0)} -> x | AQ32: Offsites | AR32: Concrete | AU32: {=IFERROR(TRANSPOSE(_xlfn._xlws.SORT(_xlfn._xlws.FILTER($AR$11:$AR$72,$AQ$11:$AQ$72=Budget!G25))),0)} -> 0
E33: =E32+1 -> 23 | F33: =EOMONTH(F32,0)+1 -> 45231 | G33: =INT(INT(E33+2)/3) -> 8 | H33: ="Q"&INT((MONTH(F33)/4)+1)&"-"&RIGHT(YEAR(F33),2) -> Q3-23 | I33: =MIN(INT(YEARFRAC(F$11,F45)),30) -> 2 | J33: =YEAR(F33) -> 2023 | L33: =IF(I34<iGeneral!F$25,1,L32*(1+L$10/12)) -> 1.0373155 | M33: =IF(I32<iGeneral!F$26,1,M32*(1+M$10/12)) -> 1.0083647 | N33: =IF(I32<iGeneral!F$27,1,N32*(1+N$10/12)) -> 1 | O33: =IFERROR(IF(I32<iGeneral!F$28,1,O32*(1+O$10/12)),1) -> 1 | P33: =IFERROR(IF(DATA!$I33<iGeneral!F$29,1,P32*(1+P$10/12)),1) -> 1 | R33: =CONCATENATE(T33,"x",U33) -> 65x125 | S33: MLDR | T33: 65 | U33: 125 | V33: =T33*U33 -> 8125 | W33: =43560/(Table4[[#This Row],[Area]])*W$9 -> 3.0559015 | Z33: {=IFERROR(TRANSPOSE(_xlfn._xlws.SORT(_xlfn._xlws.FILTER($R$11:$R$45,$S$11:$S$45=iMPC!P32))),0)} -> 60x115 | AA33: 60x120 | AB33: 60x125 | AC33: 60x130 | AD33: 65x120 | AE33: 65x125 | AF33: 70x125 | AG33: 70x130 | AH33: 70x135 | AI33: 80x125 | AJ33: 80x130 | AK33: 80x135 | AL33: 80x140 | AM33: 90x130 | AN33: 90x135 | AO33: 90x140 | AQ33: Offsites | AR33: Amenities | AU33: {=IFERROR(TRANSPOSE(_xlfn._xlws.SORT(_xlfn._xlws.FILTER($AR$11:$AR$72,$AQ$11:$AQ$72=Budget!G26))),0)} -> 0
E34: =E33+1 -> 24 | F34: =EOMONTH(F33,0)+1 -> 45261 | G34: =INT(INT(E34+2)/3) -> 8 | H34: ="Q"&INT((MONTH(F34)/4)+1)&"-"&RIGHT(YEAR(F34),2) -> Q4-23 | I34: =MIN(INT(YEARFRAC(F$11,F46)),30) -> 2 | J34: =YEAR(F34) -> 2023 | L34: =IF(I35<iGeneral!F$25,1,L33*(1+L$10/12)) -> 1.0390444 | M34: =IF(I33<iGeneral!F$26,1,M33*(1+M$10/12)) -> 1.009205 | N34: =IF(I33<iGeneral!F$27,1,N33*(1+N$10/12)) -> 1 | O34: =IFERROR(IF(I33<iGeneral!F$28,1,O33*(1+O$10/12)),1) -> 1 | P34: =IFERROR(IF(DATA!$I34<iGeneral!F$29,1,P33*(1+P$10/12)),1) -> 1 | R34: =CONCATENATE(T34,"x",U34) -> 70x125 | S34: MLDR | T34: 70 | U34: 125 | V34: =T34*U34 -> 8750 | W34: =43560/(Table4[[#This Row],[Area]])*W$9 -> 2.8376229 | Z34: {=IFERROR(TRANSPOSE(_xlfn._xlws.SORT(_xlfn._xlws.FILTER($R$11:$R$45,$S$11:$S$45=iMPC!P33))),0)} -> 60x115 | AA34: 60x120 | AB34: 60x125 | AC34: 60x130 | AD34: 65x120 | AE34: 65x125 | AF34: 70x125 | AG34: 70x130 | AH34: 70x135 | AI34: 80x125 | AJ34: 80x130 | AK34: 80x135 | AL34: 80x140 | AM34: 90x130 | AN34: 90x135 | AO34: 90x140 | AQ34: Offsites | AR34: Drainage | AU34: {=IFERROR(TRANSPOSE(_xlfn._xlws.SORT(_xlfn._xlws.FILTER($AR$11:$AR$72,$AQ$11:$AQ$72=Budget!G27))),0)} -> 0
E35: =E34+1 -> 25 | F35: =EOMONTH(F34,0)+1 -> 45292 | G35: =INT(INT(E35+2)/3) -> 9 | H35: ="Q"&INT((MONTH(F35)/4)+1)&"-"&RIGHT(YEAR(F35),2) -> Q1-24 | I35: =MIN(INT(YEARFRAC(F$11,F47)),30) -> 3 | J35: =YEAR(F35) -> 2024 | L35: =IF(I36<iGeneral!F$25,1,L34*(1+L$10/12)) -> 1.0407761 | M35: =IF(I34<iGeneral!F$26,1,M34*(1+M$10/12)) -> 1.010046 | N35: =IF(I34<iGeneral!F$27,1,N34*(1+N$10/12)) -> 1 | O35: =IFERROR(IF(I34<iGeneral!F$28,1,O34*(1+O$10/12)),1) -> 1 | P35: =IFERROR(IF(DATA!$I35<iGeneral!F$29,1,P34*(1+P$10/12)),1) -> 1 | R35: =CONCATENATE(T35,"x",U35) -> 70x130 | S35: MLDR | T35: 70 | U35: 130 | V35: =T35*U35 -> 9100 | W35: =43560/(Table4[[#This Row],[Area]])*W$9 -> 2.7284835 | Z35: {=IFERROR(TRANSPOSE(_xlfn._xlws.SORT(_xlfn._xlws.FILTER($R$11:$R$45,$S$11:$S$45=iMPC!P34))),0)} -> 60x115 | AA35: 60x120 | AB35: 60x125 | AC35: 60x130 | AD35: 65x120 | AE35: 65x125 | AF35: 70x125 | AG35: 70x130 | AH35: 70x135 | AI35: 80x125 | AJ35: 80x130 | AK35: 80x135 | AL35: 80x140 | AM35: 90x130 | AN35: 90x135 | AO35: 90x140 | AQ35: Offsites | AR35: Dry Utilities | AU35: {=IFERROR(TRANSPOSE(_xlfn._xlws.SORT(_xlfn._xlws.FILTER($AR$11:$AR$72,$AQ$11:$AQ$72=Budget!G28))),0)} -> 0
E36: =E35+1 -> 26 | F36: =EOMONTH(F35,0)+1 -> 45323 | G36: =INT(INT(E36+2)/3) -> 9 | H36: ="Q"&INT((MONTH(F36)/4)+1)&"-"&RIGHT(YEAR(F36),2) -> Q1-24 | I36: =MIN(INT(YEARFRAC(F$11,F48)),30) -> 3 | J36: =YEAR(F36) -> 2024 | L36: =IF(I37<iGeneral!F$25,1,L35*(1+L$10/12)) -> 1.0425107 | M36: =IF(I35<iGeneral!F$26,1,M35*(1+M$10/12)) -> 1.0108877 | N36: =IF(I35<iGeneral!F$27,1,N35*(1+N$10/12)) -> 1 | O36: =IFERROR(IF(I35<iGeneral!F$28,1,O35*(1+O$10/12)),1) -> 1 | P36: =IFERROR(IF(DATA!$I36<iGeneral!F$29,1,P35*(1+P$10/12)),1) -> 1 | R36: =CONCATENATE(T36,"x",U36) -> 70x135 | S36: MLDR | T36: 70 | U36: 135 | V36: =T36*U36 -> 9450 | W36: =43560/(Table4[[#This Row],[Area]])*W$9 -> 2.6274286 | Z36: {=IFERROR(TRANSPOSE(_xlfn._xlws.SORT(_xlfn._xlws.FILTER($R$11:$R$45,$S$11:$S$45=iMPC!P35))),0)} -> 40x110 | AA36: 40x115 | AB36: 45x105 | AC36: 45x110 | AD36: 45x115 | AE36: 45x120 | AF36: 50x110 | AG36: 50x115 | AH36: 50x120 | AI36: 50x125 | AJ36: 55x115 | AK36: 55x120 | AL36: 55x125 | AM36: 55x130 | AQ36: Offsites | AR36: Paving | AU36: {=IFERROR(TRANSPOSE(_xlfn._xlws.SORT(_xlfn._xlws.FILTER($AR$11:$AR$72,$AQ$11:$AQ$72=Budget!G29))),0)} -> 0
E37: =E36+1 -> 27 | F37: =EOMONTH(F36,0)+1 -> 45352 | G37: =INT(INT(E37+2)/3) -> 9 | H37: ="Q"&INT((MONTH(F37)/4)+1)&"-"&RIGHT(YEAR(F37),2) -> Q1-24 | I37: =MIN(INT(YEARFRAC(F$11,F49)),30) -> 3 | J37: =YEAR(F37) -> 2024 | L37: =IF(I38<iGeneral!F$25,1,L36*(1+L$10/12)) -> 1.0442483 | M37: =IF(I36<iGeneral!F$26,1,M36*(1+M$10/12)) -> 1.0117301 | N37: =IF(I36<iGeneral!F$27,1,N36*(1+N$10/12)) -> 1 | O37: =IFERROR(IF(I36<iGeneral!F$28,1,O36*(1+O$10/12)),1) -> 1 | P37: =IFERROR(IF(DATA!$I37<iGeneral!F$29,1,P36*(1+P$10/12)),1) -> 1 | R37: =CONCATENATE(T37,"x",U37) -> 80x125 | S37: MLDR | T37: 80 | U37: 125 | V37: =T37*U37 -> 10000 | W37: =43560/(Table4[[#This Row],[Area]])*W$9 -> 2.48292 | Z37: {=IFERROR(TRANSPOSE(_xlfn._xlws.SORT(_xlfn._xlws.FILTER($R$11:$R$45,$S$11:$S$45=iMPC!P36))),0)} -> 40x110 | AA37: 40x115 | AB37: 45x105 | AC37: 45x110 | AD37: 45x115 | AE37: 45x120 | AF37: 50x110 | AG37: 50x115 | AH37: 50x120 | AI37: 50x125 | AJ37: 55x115 | AK37: 55x120 | AL37: 55x125 | AM37: 55x130 | AQ37: Offsites | AR37: Landscaping | AU37: {=IFERROR(TRANSPOSE(_xlfn._xlws.SORT(_xlfn._xlws.FILTER($AR$11:$AR$72,$AQ$11:$AQ$72=Budget!G30))),0)} -> 0
E38: =E37+1 -> 28 | F38: =EOMONTH(F37,0)+1 -> 45383 | G38: =INT(INT(E38+2)/3) -> 10 | H38: ="Q"&INT((MONTH(F38)/4)+1)&"-"&RIGHT(YEAR(F38),2) -> Q2-24 | I38: =MIN(INT(YEARFRAC(F$11,F50)),30) -> 3 | J38: =YEAR(F38) -> 2024 | L38: =IF(I39<iGeneral!F$25,1,L37*(1+L$10/12)) -> 1.0459887 | M38: =IF(I37<iGeneral!F$26,1,M37*(1+M$10/12)) -> 1.0125732 | N38: =IF(I37<iGeneral!F$27,1,N37*(1+N$10/12)) -> 1 | O38: =IFERROR(IF(I37<iGeneral!F$28,1,O37*(1+O$10/12)),1) -> 1 | P38: =IFERROR(IF(DATA!$I38<iGeneral!F$29,1,P37*(1+P$10/12)),1) -> 1 | R38: =CONCATENATE(T38,"x",U38) -> 80x130 | S38: MLDR | T38: 80 | U38: 130 | V38: =T38*U38 -> 10400 | W38: =43560/(Table4[[#This Row],[Area]])*W$9 -> 2.3874231 | Z38: {=IFERROR(TRANSPOSE(_xlfn._xlws.SORT(_xlfn._xlws.FILTER($R$11:$R$45,$S$11:$S$45=iMPC!P37))),0)} -> 40x110 | AA38: 40x115 | AB38: 45x105 | AC38: 45x110 | AD38: 45x115 | AE38: 45x120 | AF38: 50x110 | AG38: 50x115 | AH38: 50x120 | AI38: 50x125 | AJ38: 55x115 | AK38: 55x120 | AL38: 55x125 | AM38: 55x130 | AQ38: Offsites | AR38: Walls / Monmt | AU38: {=IFERROR(TRANSPOSE(_xlfn._xlws.SORT(_xlfn._xlws.FILTER($AR$11:$AR$72,$AQ$11:$AQ$72=Budget!G31))),0)} -> 0
E39: =E38+1 -> 29 | F39: =EOMONTH(F38,0)+1 -> 45413 | G39: =INT(INT(E39+2)/3) -> 10 | H39: ="Q"&INT((MONTH(F39)/4)+1)&"-"&RIGHT(YEAR(F39),2) -> Q2-24 | I39: =MIN(INT(YEARFRAC(F$11,F51)),30) -> 3 | J39: =YEAR(F39) -> 2024 | L39: =IF(I40<iGeneral!F$25,1,L38*(1+L$10/12)) -> 1.047732 | M39: =IF(I38<iGeneral!F$26,1,M38*(1+M$10/12)) -> 1.013417 | N39: =IF(I38<iGeneral!F$27,1,N38*(1+N$10/12)) -> 1 | O39: =IFERROR(IF(I38<iGeneral!F$28,1,O38*(1+O$10/12)),1) -> 1 | P39: =IFERROR(IF(DATA!$I39<iGeneral!F$29,1,P38*(1+P$10/12)),1) -> 1 | R39: =CONCATENATE(T39,"x",U39) -> 80x135 | S39: MLDR | T39: 80 | U39: 135 | V39: =T39*U39 -> 10800 | W39: =43560/(Table4[[#This Row],[Area]])*W$9 -> 2.299 | Z39: {=IFERROR(TRANSPOSE(_xlfn._xlws.SORT(_xlfn._xlws.FILTER($R$11:$R$45,$S$11:$S$45=iMPC!P38))),0)} -> 40x110 | AA39: 40x115 | AB39: 45x105 | AC39: 45x110 | AD39: 45x115 | AE39: 45x120 | AF39: 50x110 | AG39: 50x115 | AH39: 50x120 | AI39: 50x125 | AJ39: 55x115 | AK39: 55x120 | AL39: 55x125 | AM39: 55x130 | AQ39: Offsites | AR39: Other | AU39: {=IFERROR(TRANSPOSE(_xlfn._xlws.SORT(_xlfn._xlws.FILTER($AR$11:$AR$72,$AQ$11:$AQ$72=Budget!G32))),0)} -> 0
E40: =E39+1 -> 30 | F40: =EOMONTH(F39,0)+1 -> 45444 | G40: =INT(INT(E40+2)/3) -> 10 | H40: ="Q"&INT((MONTH(F40)/4)+1)&"-"&RIGHT(YEAR(F40),2) -> Q2-24 | I40: =MIN(INT(YEARFRAC(F$11,F52)),30) -> 3 | J40: =YEAR(F40) -> 2024 | L40: =IF(I41<iGeneral!F$25,1,L39*(1+L$10/12)) -> 1.0494782 | M40: =IF(I39<iGeneral!F$26,1,M39*(1+M$10/12)) -> 1.0142615 | N40: =IF(I39<iGeneral!F$27,1,N39*(1+N$10/12)) -> 1 | O40: =IFERROR(IF(I39<iGeneral!F$28,1,O39*(1+O$10/12)),1) -> 1 | P40: =IFERROR(IF(DATA!$I40<iGeneral!F$29,1,P39*(1+P$10/12)),1) -> 1 | R40: =CONCATENATE(T40,"x",U40) -> 80x140 | S40: MLDR | T40: 80 | U40: 140 | V40: =T40*U40 -> 11200 | W40: =43560/(Table4[[#This Row],[Area]])*W$9 -> 2.2168929 | Z40: {=IFERROR(TRANSPOSE(_xlfn._xlws.SORT(_xlfn._xlws.FILTER($R$11:$R$45,$S$11:$S$45=iMPC!P39))),0)} -> 40x110 | AA40: 40x115 | AB40: 45x105 | AC40: 45x110 | AD40: 45x115 | AE40: 45x120 | AF40: 50x110 | AG40: 50x115 | AH40: 50x120 | AI40: 50x125 | AJ40: 55x115 | AK40: 55x120 | AL40: 55x125 | AM40: 55x130 | AQ40: Onsites | AR40: Survey | AU40: {=IFERROR(TRANSPOSE(_xlfn._xlws.SORT(_xlfn._xlws.FILTER($AR$11:$AR$72,$AQ$11:$AQ$72=Budget!G33))),0)} -> 0
E41: =E40+1 -> 31 | F41: =EOMONTH(F40,0)+1 -> 45474 | G41: =INT(INT(E41+2)/3) -> 11 | H41: ="Q"&INT((MONTH(F41)/4)+1)&"-"&RIGHT(YEAR(F41),2) -> Q2-24 | I41: =MIN(INT(YEARFRAC(F$11,F53)),30) -> 3 | J41: =YEAR(F41) -> 2024 | L41: =IF(I42<iGeneral!F$25,1,L40*(1+L$10/12)) -> 1.0512273 | M41: =IF(I40<iGeneral!F$26,1,M40*(1+M$10/12)) -> 1.0151067 | N41: =IF(I40<iGeneral!F$27,1,N40*(1+N$10/12)) -> 1 | O41: =IFERROR(IF(I40<iGeneral!F$28,1,O40*(1+O$10/12)),1) -> 1 | P41: =IFERROR(IF(DATA!$I41<iGeneral!F$29,1,P40*(1+P$10/12)),1) -> 1 | R41: =CONCATENATE(T41,"x",U41) -> 90x130 | S41: MLDR | T41: 90 | U41: 130 | V41: =T41*U41 -> 11700 | W41: =43560/(Table4[[#This Row],[Area]])*W$9 -> 2.1221538 | Z41: {=IFERROR(TRANSPOSE(_xlfn._xlws.SORT(_xlfn._xlws.FILTER($R$11:$R$45,$S$11:$S$45=iMPC!P40))),0)} -> 60x115 | AA41: 60x120 | AB41: 60x125 | AC41: 60x130 | AD41: 65x120 | AE41: 65x125 | AF41: 70x125 | AG41: 70x130 | AH41: 70x135 | AI41: 80x125 | AJ41: 80x130 | AK41: 80x135 | AL41: 80x140 | AM41: 90x130 | AN41: 90x135 | AO41: 90x140 | AQ41: Onsites | AR41: Testing | AU41: {=IFERROR(TRANSPOSE(_xlfn._xlws.SORT(_xlfn._xlws.FILTER($AR$11:$AR$72,$AQ$11:$AQ$72=Budget!G34))),0)} -> 0
E42: =E41+1 -> 32 | F42: =EOMONTH(F41,0)+1 -> 45505 | G42: =INT(INT(E42+2)/3) -> 11 | H42: ="Q"&INT((MONTH(F42)/4)+1)&"-"&RIGHT(YEAR(F42),2) -> Q3-24 | I42: =MIN(INT(YEARFRAC(F$11,F54)),30) -> 3 | J42: =YEAR(F42) -> 2024 | L42: =IF(I43<iGeneral!F$25,1,L41*(1+L$10/12)) -> 1.0529794 | M42: =IF(I41<iGeneral!F$26,1,M41*(1+M$10/12)) -> 1.0159526 | N42: =IF(I41<iGeneral!F$27,1,N41*(1+N$10/12)) -> 1 | O42: =IFERROR(IF(I41<iGeneral!F$28,1,O41*(1+O$10/12)),1) -> 1 | P42: =IFERROR(IF(DATA!$I42<iGeneral!F$29,1,P41*(1+P$10/12)),1) -> 1 | R42: =CONCATENATE(T42,"x",U42) -> 90x135 | S42: MLDR | T42: 90 | U42: 135 | V42: =T42*U42 -> 12150 | W42: =43560/(Table4[[#This Row],[Area]])*W$9 -> 2.0435556 | Z42: {=IFERROR(TRANSPOSE(_xlfn._xlws.SORT(_xlfn._xlws.FILTER($R$11:$R$45,$S$11:$S$45=iMPC!P41))),0)} -> 60x115 | AA42: 60x120 | AB42: 60x125 | AC42: 60x130 | AD42: 65x120 | AE42: 65x125 | AF42: 70x125 | AG42: 70x130 | AH42: 70x135 | AI42: 80x125 | AJ42: 80x130 | AK42: 80x135 | AL42: 80x140 | AM42: 90x130 | AN42: 90x135 | AO42: 90x140 | AQ42: Onsites | AR42: Removals / Aband | AU42: {=IFERROR(TRANSPOSE(_xlfn._xlws.SORT(_xlfn._xlws.FILTER($AR$11:$AR$72,$AQ$11:$AQ$72=Budget!G35))),0)} -> 0
E43: =E42+1 -> 33 | F43: =EOMONTH(F42,0)+1 -> 45536 | G43: =INT(INT(E43+2)/3) -> 11 | H43: ="Q"&INT((MONTH(F43)/4)+1)&"-"&RIGHT(YEAR(F43),2) -> Q3-24 | I43: =MIN(INT(YEARFRAC(F$11,F55)),30) -> 3 | J43: =YEAR(F43) -> 2024 | L43: =IF(I44<iGeneral!F$25,1,L42*(1+L$10/12)) -> 1.0547344 | M43: =IF(I42<iGeneral!F$26,1,M42*(1+M$10/12)) -> 1.0167993 | N43: =IF(I42<iGeneral!F$27,1,N42*(1+N$10/12)) -> 1 | O43: =IFERROR(IF(I42<iGeneral!F$28,1,O42*(1+O$10/12)),1) -> 1 | P43: =IFERROR(IF(DATA!$I43<iGeneral!F$29,1,P42*(1+P$10/12)),1) -> 1 | R43: =CONCATENATE(T43,"x",U43) -> 90x140 | S43: MLDR | T43: 90 | U43: 140 | V43: =T43*U43 -> 12600 | W43: =43560/(Table4[[#This Row],[Area]])*W$9 -> 1.9705714 | Z43: {=IFERROR(TRANSPOSE(_xlfn._xlws.SORT(_xlfn._xlws.FILTER($R$11:$R$45,$S$11:$S$45=iMPC!P42))),0)} -> 40x110 | AA43: 40x115 | AB43: 45x105 | AC43: 45x110 | AD43: 45x115 | AE43: 45x120 | AF43: 50x110 | AG43: 50x115 | AH43: 50x120 | AI43: 50x125 | AJ43: 55x115 | AK43: 55x120 | AL43: 55x125 | AM43: 55x130 | AQ43: Onsites | AR43: Permits | AU43: {=IFERROR(TRANSPOSE(_xlfn._xlws.SORT(_xlfn._xlws.FILTER($AR$11:$AR$72,$AQ$11:$AQ$72=Budget!G36))),0)} -> 0
E44: =E43+1 -> 34 | F44: =EOMONTH(F43,0)+1 -> 45566 | G44: =INT(INT(E44+2)/3) -> 12 | H44: ="Q"&INT((MONTH(F44)/4)+1)&"-"&RIGHT(YEAR(F44),2) -> Q3-24 | I44: =MIN(INT(YEARFRAC(F$11,F56)),30) -> 3 | J44: =YEAR(F44) -> 2024 | L44: =IF(I45<iGeneral!F$25,1,L43*(1+L$10/12)) -> 1.0564922 | M44: =IF(I43<iGeneral!F$26,1,M43*(1+M$10/12)) -> 1.0176466 | N44: =IF(I43<iGeneral!F$27,1,N43*(1+N$10/12)) -> 1 | O44: =IFERROR(IF(I43<iGeneral!F$28,1,O43*(1+O$10/12)),1) -> 1 | P44: =IFERROR(IF(DATA!$I44<iGeneral!F$29,1,P43*(1+P$10/12)),1) -> 1 | R44: =CONCATENATE(T44,"x",U44) -> x | S44: MU | V44: =T44*U44 -> 0 | W44: =43560/(Table4[[#This Row],[Area]])*W$9 -> #DIV/0! | Z44: {=IFERROR(TRANSPOSE(_xlfn._xlws.SORT(_xlfn._xlws.FILTER($R$11:$R$45,$S$11:$S$45=iMPC!P43))),0)} -> 40x110 | AA44: 40x115 | AB44: 45x105 | AC44: 45x110 | AD44: 45x115 | AE44: 45x120 | AF44: 50x110 | AG44: 50x115 | AH44: 50x120 | AI44: 50x125 | AJ44: 55x115 | AK44: 55x120 | AL44: 55x125 | AM44: 55x130 | AQ44: Onsites | AR44: Earthwork
E45: =E44+1 -> 35 | F45: =EOMONTH(F44,0)+1 -> 45597 | G45: =INT(INT(E45+2)/3) -> 12 | H45: ="Q"&INT((MONTH(F45)/4)+1)&"-"&RIGHT(YEAR(F45),2) -> Q3-24 | I45: =MIN(INT(YEARFRAC(F$11,F57)),30) -> 3 | J45: =YEAR(F45) -> 2024 | L45: =IF(I46<iGeneral!F$25,1,L44*(1+L$10/12)) -> 1.0582531 | M45: =IF(I44<iGeneral!F$26,1,M44*(1+M$10/12)) -> 1.0184946 | N45: =IF(I44<iGeneral!F$27,1,N44*(1+N$10/12)) -> 1 | O45: =IFERROR(IF(I44<iGeneral!F$28,1,O44*(1+O$10/12)),1) -> 1 | P45: =IFERROR(IF(DATA!$I45<iGeneral!F$29,1,P44*(1+P$10/12)),1) -> 1 | R45: =CONCATENATE(T45,"x",U45) -> x | S45: i | V45: =T45*U45 -> 0 | W45: =43560/(Table4[[#This Row],[Area]])*W$9 -> #DIV/0! | Z45: {=IFERROR(TRANSPOSE(_xlfn._xlws.SORT(_xlfn._xlws.FILTER($R$11:$R$45,$S$11:$S$45=iMPC!P44))),0)} -> x | AQ45: Onsites | AR45: Wastewater
E46: =E45+1 -> 36 | F46: =EOMONTH(F45,0)+1 -> 45627 | G46: =INT(INT(E46+2)/3) -> 12 | H46: ="Q"&INT((MONTH(F46)/4)+1)&"-"&RIGHT(YEAR(F46),2) -> Q4-24 | I46: =MIN(INT(YEARFRAC(F$11,F58)),30) -> 3 | J46: =YEAR(F46) -> 2024 | L46: =IF(I47<iGeneral!F$25,1,L45*(1+L$10/12)) -> 1.0600168 | M46: =IF(I45<iGeneral!F$26,1,M45*(1+M$10/12)) -> 1.0193434 | N46: =IF(I45<iGeneral!F$27,1,N45*(1+N$10/12)) -> 1 | O46: =IFERROR(IF(I45<iGeneral!F$28,1,O45*(1+O$10/12)),1) -> 1 | P46: =IFERROR(IF(DATA!$I46<iGeneral!F$29,1,P45*(1+P$10/12)),1) -> 1 | Z46: {=IFERROR(TRANSPOSE(_xlfn._xlws.SORT(_xlfn._xlws.FILTER($R$11:$R$45,$S$11:$S$45=iMPC!P45))),0)} -> 40x110 | AA46: 40x115 | AB46: 45x105 | AC46: 45x110 | AD46: 45x115 | AE46: 45x120 | AF46: 50x110 | AG46: 50x115 | AH46: 50x120 | AI46: 50x125 | AJ46: 55x115 | AK46: 55x120 | AL46: 55x125 | AM46: 55x130 | AQ46: Onsites | AR46: Water
E47: =E46+1 -> 37 | F47: =EOMONTH(F46,0)+1 -> 45658 | G47: =INT(INT(E47+2)/3) -> 13 | H47: ="Q"&INT((MONTH(F47)/4)+1)&"-"&RIGHT(YEAR(F47),2) -> Q1-25 | I47: =MIN(INT(YEARFRAC(F$11,F59)),30) -> 4 | J47: =YEAR(F47) -> 2025 | L47: =IF(I48<iGeneral!F$25,1,L46*(1+L$10/12)) -> 1.0617835 | M47: =IF(I46<iGeneral!F$26,1,M46*(1+M$10/12)) -> 1.0201928 | N47: =IF(I46<iGeneral!F$27,1,N46*(1+N$10/12)) -> 1 | O47: =IFERROR(IF(I46<iGeneral!F$28,1,O46*(1+O$10/12)),1) -> 1 | P47: =IFERROR(IF(DATA!$I47<iGeneral!F$29,1,P46*(1+P$10/12)),1) -> 1 | Z47: {=IFERROR(TRANSPOSE(_xlfn._xlws.SORT(_xlfn._xlws.FILTER($R$11:$R$45,$S$11:$S$45=iMPC!P46))),0)} -> 60x115 | AA47: 60x120 | AB47: 60x125 | AC47: 60x130 | AD47: 65x120 | AE47: 65x125 | AF47: 70x125 | AG47: 70x130 | AH47: 70x135 | AI47: 80x125 | AJ47: 80x130 | AK47: 80x135 | AL47: 80x140 | AM47: 90x130 | AN47: 90x135 | AO47: 90x140 | AQ47: Onsites | AR47: Storm Drain
E48: =E47+1 -> 38 | F48: =EOMONTH(F47,0)+1 -> 45689 | G48: =INT(INT(E48+2)/3) -> 13 | H48: ="Q"&INT((MONTH(F48)/4)+1)&"-"&RIGHT(YEAR(F48),2) -> Q1-25 | I48: =MIN(INT(YEARFRAC(F$11,F60)),30) -> 4 | J48: =YEAR(F48) -> 2025 | L48: =IF(I49<iGeneral!F$25,1,L47*(1+L$10/12)) -> 1.0635532 | M48: =IF(I47<iGeneral!F$26,1,M47*(1+M$10/12)) -> 1.021043 | N48: =IF(I47<iGeneral!F$27,1,N47*(1+N$10/12)) -> 1 | O48: =IFERROR(IF(I47<iGeneral!F$28,1,O47*(1+O$10/12)),1) -> 1 | P48: =IFERROR(IF(DATA!$I48<iGeneral!F$29,1,P47*(1+P$10/12)),1) -> 1 | Z48: {=IFERROR(TRANSPOSE(_xlfn._xlws.SORT(_xlfn._xlws.FILTER($R$11:$R$45,$S$11:$S$45=iMPC!P47))),0)} -> x | AQ48: Onsites | AR48: Concrete
E49: =E48+1 -> 39 | F49: =EOMONTH(F48,0)+1 -> 45717 | G49: =INT(INT(E49+2)/3) -> 13 | H49: ="Q"&INT((MONTH(F49)/4)+1)&"-"&RIGHT(YEAR(F49),2) -> Q1-25 | I49: =MIN(INT(YEARFRAC(F$11,F61)),30) -> 4 | J49: =YEAR(F49) -> 2025 | L49: =IF(I50<iGeneral!F$25,1,L48*(1+L$10/12)) -> 1.0653257 | M49: =IF(I48<iGeneral!F$26,1,M48*(1+M$10/12)) -> 1.0218939 | N49: =IF(I48<iGeneral!F$27,1,N48*(1+N$10/12)) -> 1 | O49: =IFERROR(IF(I48<iGeneral!F$28,1,O48*(1+O$10/12)),1) -> 1 | P49: =IFERROR(IF(DATA!$I49<iGeneral!F$29,1,P48*(1+P$10/12)),1) -> 1 | Z49: {=IFERROR(TRANSPOSE(_xlfn._xlws.SORT(_xlfn._xlws.FILTER($R$11:$R$45,$S$11:$S$45=iMPC!P48))),0)} -> 40x110 | AA49: 40x115 | AB49: 45x105 | AC49: 45x110 | AD49: 45x115 | AE49: 45x120 | AF49: 50x110 | AG49: 50x115 | AH49: 50x120 | AI49: 50x125 | AJ49: 55x115 | AK49: 55x120 | AL49: 55x125 | AM49: 55x130 | AQ49: Onsites | AR49: Amenities
E50: =E49+1 -> 40 | F50: =EOMONTH(F49,0)+1 -> 45748 | G50: =INT(INT(E50+2)/3) -> 14 | H50: ="Q"&INT((MONTH(F50)/4)+1)&"-"&RIGHT(YEAR(F50),2) -> Q2-25 | I50: =MIN(INT(YEARFRAC(F$11,F62)),30) -> 4 | J50: =YEAR(F50) -> 2025 | L50: =IF(I51<iGeneral!F$25,1,L49*(1+L$10/12)) -> 1.0671013 | M50: =IF(I49<iGeneral!F$26,1,M49*(1+M$10/12)) -> 1.0227455 | N50: =IF(I49<iGeneral!F$27,1,N49*(1+N$10/12)) -> 1 | O50: =IFERROR(IF(I49<iGeneral!F$28,1,O49*(1+O$10/12)),1) -> 1 | P50: =IFERROR(IF(DATA!$I50<iGeneral!F$29,1,P49*(1+P$10/12)),1) -> 1 | Z50: {=IFERROR(TRANSPOSE(_xlfn._xlws.SORT(_xlfn._xlws.FILTER($R$11:$R$45,$S$11:$S$45=iMPC!P49))),0)} -> 40x110 | AA50: 40x115 | AB50: 45x105 | AC50: 45x110 | AD50: 45x115 | AE50: 45x120 | AF50: 50x110 | AG50: 50x115 | AH50: 50x120 | AI50: 50x125 | AJ50: 55x115 | AK50: 55x120 | AL50: 55x125 | AM50: 55x130 | AQ50: Onsites | AR50: Drainage
E51: =E50+1 -> 41 | F51: =EOMONTH(F50,0)+1 -> 45778 | G51: =INT(INT(E51+2)/3) -> 14 | H51: ="Q"&INT((MONTH(F51)/4)+1)&"-"&RIGHT(YEAR(F51),2) -> Q2-25 | I51: =MIN(INT(YEARFRAC(F$11,F63)),30) -> 4 | J51: =YEAR(F51) -> 2025 | L51: =IF(I52<iGeneral!F$25,1,L50*(1+L$10/12)) -> 1.0688798 | M51: =IF(I50<iGeneral!F$26,1,M50*(1+M$10/12)) -> 1.0235977 | N51: =IF(I50<iGeneral!F$27,1,N50*(1+N$10/12)) -> 1 | O51: =IFERROR(IF(I50<iGeneral!F$28,1,O50*(1+O$10/12)),1) -> 1 | P51: =IFERROR(IF(DATA!$I51<iGeneral!F$29,1,P50*(1+P$10/12)),1) -> 1 | Z51: {=IFERROR(TRANSPOSE(_xlfn._xlws.SORT(_xlfn._xlws.FILTER($R$11:$R$45,$S$11:$S$45=iMPC!P50))),0)} -> 40x110 | AA51: 40x115 | AB51: 45x105 | AC51: 45x110 | AD51: 45x115 | AE51: 45x120 | AF51: 50x110 | AG51: 50x115 | AH51: 50x120 | AI51: 50x125 | AJ51: 55x115 | AK51: 55x120 | AL51: 55x125 | AM51: 55x130 | AQ51: Onsites | AR51: Dry Utilities
E52: =E51+1 -> 42 | F52: =EOMONTH(F51,0)+1 -> 45809 | G52: =INT(INT(E52+2)/3) -> 14 | H52: ="Q"&INT((MONTH(F52)/4)+1)&"-"&RIGHT(YEAR(F52),2) -> Q2-25 | I52: =MIN(INT(YEARFRAC(F$11,F64)),30) -> 4 | J52: =YEAR(F52) -> 2025 | L52: =IF(I53<iGeneral!F$25,1,L51*(1+L$10/12)) -> 1.0706613 | M52: =IF(I51<iGeneral!F$26,1,M51*(1+M$10/12)) -> 1.0244507 | N52: =IF(I51<iGeneral!F$27,1,N51*(1+N$10/12)) -> 1 | O52: =IFERROR(IF(I51<iGeneral!F$28,1,O51*(1+O$10/12)),1) -> 1 | P52: =IFERROR(IF(DATA!$I52<iGeneral!F$29,1,P51*(1+P$10/12)),1) -> 1 | Z52: {=IFERROR(TRANSPOSE(_xlfn._xlws.SORT(_xlfn._xlws.FILTER($R$11:$R$45,$S$11:$S$45=iMPC!P51))),0)} -> x | AQ52: Onsites | AR52: Paving
E53: =E52+1 -> 43 | F53: =EOMONTH(F52,0)+1 -> 45839 | G53: =INT(INT(E53+2)/3) -> 15 | H53: ="Q"&INT((MONTH(F53)/4)+1)&"-"&RIGHT(YEAR(F53),2) -> Q2-25 | I53: =MIN(INT(YEARFRAC(F$11,F65)),30) -> 4 | J53: =YEAR(F53) -> 2025 | L53: =IF(I54<iGeneral!F$25,1,L52*(1+L$10/12)) -> 1.0724457 | M53: =IF(I52<iGeneral!F$26,1,M52*(1+M$10/12)) -> 1.0253044 | N53: =IF(I52<iGeneral!F$27,1,N52*(1+N$10/12)) -> 1 | O53: =IFERROR(IF(I52<iGeneral!F$28,1,O52*(1+O$10/12)),1) -> 1 | P53: =IFERROR(IF(DATA!$I53<iGeneral!F$29,1,P52*(1+P$10/12)),1) -> 1 | Z53: {=IFERROR(TRANSPOSE(_xlfn._xlws.SORT(_xlfn._xlws.FILTER($R$11:$R$45,$S$11:$S$45=iMPC!P52))),0)} -> 40x110 | AA53: 40x115 | AB53: 45x105 | AC53: 45x110 | AD53: 45x115 | AE53: 45x120 | AF53: 50x110 | AG53: 50x115 | AH53: 50x120 | AI53: 50x125 | AJ53: 55x115 | AK53: 55x120 | AL53: 55x125 | AM53: 55x130 | AQ53: Onsites | AR53: Landscaping
E54: =E53+1 -> 44 | F54: =EOMONTH(F53,0)+1 -> 45870 | G54: =INT(INT(E54+2)/3) -> 15 | H54: ="Q"&INT((MONTH(F54)/4)+1)&"-"&RIGHT(YEAR(F54),2) -> Q3-25 | I54: =MIN(INT(YEARFRAC(F$11,F66)),30) -> 4 | J54: =YEAR(F54) -> 2025 | L54: =IF(I55<iGeneral!F$25,1,L53*(1+L$10/12)) -> 1.0742331 | M54: =IF(I53<iGeneral!F$26,1,M53*(1+M$10/12)) -> 1.0261589 | N54: =IF(I53<iGeneral!F$27,1,N53*(1+N$10/12)) -> 1 | O54: =IFERROR(IF(I53<iGeneral!F$28,1,O53*(1+O$10/12)),1) -> 1 | P54: =IFERROR(IF(DATA!$I54<iGeneral!F$29,1,P53*(1+P$10/12)),1) -> 1 | Z54: {=IFERROR(TRANSPOSE(_xlfn._xlws.SORT(_xlfn._xlws.FILTER($R$11:$R$45,$S$11:$S$45=iMPC!P53))),0)} -> 40x110 | AA54: 40x115 | AB54: 45x105 | AC54: 45x110 | AD54: 45x115 | AE54: 45x120 | AF54: 50x110 | AG54: 50x115 | AH54: 50x120 | AI54: 50x125 | AJ54: 55x115 | AK54: 55x120 | AL54: 55x125 | AM54: 55x130 | AQ54: Onsites | AR54: Walls / Monmt
E55: =E54+1 -> 45 | F55: =EOMONTH(F54,0)+1 -> 45901 | G55: =INT(INT(E55+2)/3) -> 15 | H55: ="Q"&INT((MONTH(F55)/4)+1)&"-"&RIGHT(YEAR(F55),2) -> Q3-25 | I55: =MIN(INT(YEARFRAC(F$11,F67)),30) -> 4 | J55: =YEAR(F55) -> 2025 | L55: =IF(I56<iGeneral!F$25,1,L54*(1+L$10/12)) -> 1.0760235 | M55: =IF(I54<iGeneral!F$26,1,M54*(1+M$10/12)) -> 1.027014 | N55: =IF(I54<iGeneral!F$27,1,N54*(1+N$10/12)) -> 1 | O55: =IFERROR(IF(I54<iGeneral!F$28,1,O54*(1+O$10/12)),1) -> 1 | P55: =IFERROR(IF(DATA!$I55<iGeneral!F$29,1,P54*(1+P$10/12)),1) -> 1 | Z55: {=IFERROR(TRANSPOSE(_xlfn._xlws.SORT(_xlfn._xlws.FILTER($R$11:$R$45,$S$11:$S$45=iMPC!P54))),0)} -> 60x115 | AA55: 60x120 | AB55: 60x125 | AC55: 60x130 | AD55: 65x120 | AE55: 65x125 | AF55: 70x125 | AG55: 70x130 | AH55: 70x135 | AI55: 80x125 | AJ55: 80x130 | AK55: 80x135 | AL55: 80x140 | AM55: 90x130 | AN55: 90x135 | AO55: 90x140 | AQ55: Onsites | AR55: Other
E56: =E55+1 -> 46 | F56: =EOMONTH(F55,0)+1 -> 45931 | G56: =INT(INT(E56+2)/3) -> 16 | H56: ="Q"&INT((MONTH(F56)/4)+1)&"-"&RIGHT(YEAR(F56),2) -> Q3-25 | I56: =MIN(INT(YEARFRAC(F$11,F68)),30) -> 4 | J56: =YEAR(F56) -> 2025 | L56: =IF(I57<iGeneral!F$25,1,L55*(1+L$10/12)) -> 1.0778169 | M56: =IF(I55<iGeneral!F$26,1,M55*(1+M$10/12)) -> 1.0278698 | N56: =IF(I55<iGeneral!F$27,1,N55*(1+N$10/12)) -> 1 | O56: =IFERROR(IF(I55<iGeneral!F$28,1,O55*(1+O$10/12)),1) -> 1 | P56: =IFERROR(IF(DATA!$I56<iGeneral!F$29,1,P55*(1+P$10/12)),1) -> 1 | Z56: {=IFERROR(TRANSPOSE(_xlfn._xlws.SORT(_xlfn._xlws.FILTER($R$11:$R$45,$S$11:$S$45=iMPC!P55))),0)} -> 60x115 | AA56: 60x120 | AB56: 60x125 | AC56: 60x130 | AD56: 65x120 | AE56: 65x125 | AF56: 70x125 | AG56: 70x130 | AH56: 70x135 | AI56: 80x125 | AJ56: 80x130 | AK56: 80x135 | AL56: 80x140 | AM56: 90x130 | AN56: 90x135 | AO56: 90x140 | AQ56: Exactions | AR56: Offsite
E57: =E56+1 -> 47 | F57: =EOMONTH(F56,0)+1 -> 45962 | G57: =INT(INT(E57+2)/3) -> 16 | H57: ="Q"&INT((MONTH(F57)/4)+1)&"-"&RIGHT(YEAR(F57),2) -> Q3-25 | I57: =MIN(INT(YEARFRAC(F$11,F69)),30) -> 4 | J57: =YEAR(F57) -> 2025 | L57: =IF(I58<iGeneral!F$25,1,L56*(1+L$10/12)) -> 1.0796132 | M57: =IF(I56<iGeneral!F$26,1,M56*(1+M$10/12)) -> 1.0287264 | N57: =IF(I56<iGeneral!F$27,1,N56*(1+N$10/12)) -> 1 | O57: =IFERROR(IF(I56<iGeneral!F$28,1,O56*(1+O$10/12)),1) -> 1 | P57: =IFERROR(IF(DATA!$I57<iGeneral!F$29,1,P56*(1+P$10/12)),1) -> 1 | Z57: {=IFERROR(TRANSPOSE(_xlfn._xlws.SORT(_xlfn._xlws.FILTER($R$11:$R$45,$S$11:$S$45=iMPC!P56))),0)} -> 40x110 | AA57: 40x115 | AB57: 45x105 | AC57: 45x110 | AD57: 45x115 | AE57: 45x120 | AF57: 50x110 | AG57: 50x115 | AH57: 50x120 | AI57: 50x125 | AJ57: 55x115 | AK57: 55x120 | AL57: 55x125 | AM57: 55x130 | AQ57: Exactions | AR57: Onsite
E58: =E57+1 -> 48 | F58: =EOMONTH(F57,0)+1 -> 45992 | G58: =INT(INT(E58+2)/3) -> 16 | H58: ="Q"&INT((MONTH(F58)/4)+1)&"-"&RIGHT(YEAR(F58),2) -> Q4-25 | I58: =MIN(INT(YEARFRAC(F$11,F70)),30) -> 4 | J58: =YEAR(F58) -> 2025 | L58: =IF(I59<iGeneral!F$25,1,L57*(1+L$10/12)) -> 1.0814126 | M58: =IF(I57<iGeneral!F$26,1,M57*(1+M$10/12)) -> 1.0295837 | N58: =IF(I57<iGeneral!F$27,1,N57*(1+N$10/12)) -> 1 | O58: =IFERROR(IF(I57<iGeneral!F$28,1,O57*(1+O$10/12)),1) -> 1 | P58: =IFERROR(IF(DATA!$I58<iGeneral!F$29,1,P57*(1+P$10/12)),1) -> 1 | Z58: {=IFERROR(TRANSPOSE(_xlfn._xlws.SORT(_xlfn._xlws.FILTER($R$11:$R$45,$S$11:$S$45=iMPC!P57))),0)} -> x | AQ58: Exactions | AR58: Other
E59: =E58+1 -> 49 | F59: =EOMONTH(F58,0)+1 -> 46023 | G59: =INT(INT(E59+2)/3) -> 17 | H59: ="Q"&INT((MONTH(F59)/4)+1)&"-"&RIGHT(YEAR(F59),2) -> Q1-26 | I59: =MIN(INT(YEARFRAC(F$11,F71)),30) -> 5 | J59: =YEAR(F59) -> 2026 | L59: =IF(I60<iGeneral!F$25,1,L58*(1+L$10/12)) -> 1.0832149 | M59: =IF(I58<iGeneral!F$26,1,M58*(1+M$10/12)) -> 1.0304417 | N59: =IF(I58<iGeneral!F$27,1,N58*(1+N$10/12)) -> 1 | O59: =IFERROR(IF(I58<iGeneral!F$28,1,O58*(1+O$10/12)),1) -> 1 | P59: =IFERROR(IF(DATA!$I59<iGeneral!F$29,1,P58*(1+P$10/12)),1) -> 1 | Z59: {=IFERROR(TRANSPOSE(_xlfn._xlws.SORT(_xlfn._xlws.FILTER($R$11:$R$45,$S$11:$S$45=iMPC!#REF!))),0)} -> 0 | AQ59: Operation | AR59: G&A
E60: =E59+1 -> 50 | F60: =EOMONTH(F59,0)+1 -> 46054 | G60: =INT(INT(E60+2)/3) -> 17 | H60: ="Q"&INT((MONTH(F60)/4)+1)&"-"&RIGHT(YEAR(F60),2) -> Q1-26 | I60: =MIN(INT(YEARFRAC(F$11,F72)),30) -> 5 | J60: =YEAR(F60) -> 2026 | L60: =IF(I61<iGeneral!F$25,1,L59*(1+L$10/12)) -> 1.0850203 | M60: =IF(I59<iGeneral!F$26,1,M59*(1+M$10/12)) -> 1.0313004 | N60: =IF(I59<iGeneral!F$27,1,N59*(1+N$10/12)) -> 1 | O60: =IFERROR(IF(I59<iGeneral!F$28,1,O59*(1+O$10/12)),1) -> 1 | P60: =IFERROR(IF(DATA!$I60<iGeneral!F$29,1,P59*(1+P$10/12)),1) -> 1 | Z60: {=IFERROR(TRANSPOSE(_xlfn._xlws.SORT(_xlfn._xlws.FILTER($R$11:$R$45,$S$11:$S$45=iMPC!#REF!))),0)} -> 0 | AQ60: Operation | AR60: Management
E61: =E60+1 -> 51 | F61: =EOMONTH(F60,0)+1 -> 46082 | G61: =INT(INT(E61+2)/3) -> 17 | H61: ="Q"&INT((MONTH(F61)/4)+1)&"-"&RIGHT(YEAR(F61),2) -> Q1-26 | I61: =MIN(INT(YEARFRAC(F$11,F73)),30) -> 5 | J61: =YEAR(F61) -> 2026 | L61: =IF(I62<iGeneral!F$25,1,L60*(1+L$10/12)) -> 1.0868287 | M61: =IF(I60<iGeneral!F$26,1,M60*(1+M$10/12)) -> 1.0321598 | N61: =IF(I60<iGeneral!F$27,1,N60*(1+N$10/12)) -> 1 | O61: =IFERROR(IF(I60<iGeneral!F$28,1,O60*(1+O$10/12)),1) -> 1 | P61: =IFERROR(IF(DATA!$I61<iGeneral!F$29,1,P60*(1+P$10/12)),1) -> 1 | Z61: {=IFERROR(TRANSPOSE(_xlfn._xlws.SORT(_xlfn._xlws.FILTER($R$11:$R$45,$S$11:$S$45=iMPC!#REF!))),0)} -> 0 | AQ61: Operation | AR61: HOA
E62: =E61+1 -> 52 | F62: =EOMONTH(F61,0)+1 -> 46113 | G62: =INT(INT(E62+2)/3) -> 18 | H62: ="Q"&INT((MONTH(F62)/4)+1)&"-"&RIGHT(YEAR(F62),2) -> Q2-26 | I62: =MIN(INT(YEARFRAC(F$11,F74)),30) -> 5 | J62: =YEAR(F62) -> 2026 | L62: =IF(I63<iGeneral!F$25,1,L61*(1+L$10/12)) -> 1.08864 | M62: =IF(I61<iGeneral!F$26,1,M61*(1+M$10/12)) -> 1.0330199 | N62: =IF(I61<iGeneral!F$27,1,N61*(1+N$10/12)) -> 1 | O62: =IFERROR(IF(I61<iGeneral!F$28,1,O61*(1+O$10/12)),1) -> 1 | P62: =IFERROR(IF(DATA!$I62<iGeneral!F$29,1,P61*(1+P$10/12)),1) -> 1 | Z62: {=IFERROR(TRANSPOSE(_xlfn._xlws.SORT(_xlfn._xlws.FILTER($R$11:$R$45,$S$11:$S$45=iMPC!#REF!))),0)} -> 0 | AQ62: Operation | AR62: Legal
E63: =E62+1 -> 53 | F63: =EOMONTH(F62,0)+1 -> 46143 | G63: =INT(INT(E63+2)/3) -> 18 | H63: ="Q"&INT((MONTH(F63)/4)+1)&"-"&RIGHT(YEAR(F63),2) -> Q2-26 | I63: =MIN(INT(YEARFRAC(F$11,F75)),30) -> 5 | J63: =YEAR(F63) -> 2026 | L63: =IF(I64<iGeneral!F$25,1,L62*(1+L$10/12)) -> 1.0904544 | M63: =IF(I62<iGeneral!F$26,1,M62*(1+M$10/12)) -> 1.0338808 | N63: =IF(I62<iGeneral!F$27,1,N62*(1+N$10/12)) -> 1 | O63: =IFERROR(IF(I62<iGeneral!F$28,1,O62*(1+O$10/12)),1) -> 1 | P63: =IFERROR(IF(DATA!$I63<iGeneral!F$29,1,P62*(1+P$10/12)),1) -> 1 | Z63: {=IFERROR(TRANSPOSE(_xlfn._xlws.SORT(_xlfn._xlws.FILTER($R$11:$R$45,$S$11:$S$45=iMPC!#REF!))),0)} -> 0 | AQ63: Operation | AR63: Accounting
E64: =E63+1 -> 54 | F64: =EOMONTH(F63,0)+1 -> 46174 | G64: =INT(INT(E64+2)/3) -> 18 | H64: ="Q"&INT((MONTH(F64)/4)+1)&"-"&RIGHT(YEAR(F64),2) -> Q2-26 | I64: =MIN(INT(YEARFRAC(F$11,F76)),30) -> 5 | J64: =YEAR(F64) -> 2026 | L64: =IF(I65<iGeneral!F$25,1,L63*(1+L$10/12)) -> 1.0922719 | M64: =IF(I63<iGeneral!F$26,1,M63*(1+M$10/12)) -> 1.0347423 | N64: =IF(I63<iGeneral!F$27,1,N63*(1+N$10/12)) -> 1 | O64: =IFERROR(IF(I63<iGeneral!F$28,1,O63*(1+O$10/12)),1) -> 1 | P64: =IFERROR(IF(DATA!$I64<iGeneral!F$29,1,P63*(1+P$10/12)),1) -> 1 | Z64: {=IFERROR(TRANSPOSE(_xlfn._xlws.SORT(_xlfn._xlws.FILTER($R$11:$R$45,$S$11:$S$45=iMPC!#REF!))),0)} -> 0 | AQ64: Operation | AR64: Marketing
E65: =E64+1 -> 55 | F65: =EOMONTH(F64,0)+1 -> 46204 | G65: =INT(INT(E65+2)/3) -> 19 | H65: ="Q"&INT((MONTH(F65)/4)+1)&"-"&RIGHT(YEAR(F65),2) -> Q2-26 | I65: =MIN(INT(YEARFRAC(F$11,F77)),30) -> 5 | J65: =YEAR(F65) -> 2026 | L65: =IF(I66<iGeneral!F$25,1,L64*(1+L$10/12)) -> 1.0940923 | M65: =IF(I64<iGeneral!F$26,1,M64*(1+M$10/12)) -> 1.0356046 | N65: =IF(I64<iGeneral!F$27,1,N64*(1+N$10/12)) -> 1 | O65: =IFERROR(IF(I64<iGeneral!F$28,1,O64*(1+O$10/12)),1) -> 1 | P65: =IFERROR(IF(DATA!$I65<iGeneral!F$29,1,P64*(1+P$10/12)),1) -> 1 | Z65: {=IFERROR(TRANSPOSE(_xlfn._xlws.SORT(_xlfn._xlws.FILTER($R$11:$R$45,$S$11:$S$45=iMPC!#REF!))),0)} -> 0 | AQ65: Operation | AR65: Other
E66: =E65+1 -> 56 | F66: =EOMONTH(F65,0)+1 -> 46235 | G66: =INT(INT(E66+2)/3) -> 19 | H66: ="Q"&INT((MONTH(F66)/4)+1)&"-"&RIGHT(YEAR(F66),2) -> Q3-26 | I66: =MIN(INT(YEARFRAC(F$11,F78)),30) -> 5 | J66: =YEAR(F66) -> 2026 | L66: =IF(I67<iGeneral!F$25,1,L65*(1+L$10/12)) -> 1.0959158 | M66: =IF(I65<iGeneral!F$26,1,M65*(1+M$10/12)) -> 1.0364676 | N66: =IF(I65<iGeneral!F$27,1,N65*(1+N$10/12)) -> 1 | O66: =IFERROR(IF(I65<iGeneral!F$28,1,O65*(1+O$10/12)),1) -> 1 | P66: =IFERROR(IF(DATA!$I66<iGeneral!F$29,1,P65*(1+P$10/12)),1) -> 1 | Z66: {=IFERROR(TRANSPOSE(_xlfn._xlws.SORT(_xlfn._xlws.FILTER($R$11:$R$45,$S$11:$S$45=iMPC!#REF!))),0)} -> 0 | AQ66: Ownership | AR66: G&A
E67: =E66+1 -> 57 | F67: =EOMONTH(F66,0)+1 -> 46266 | G67: =INT(INT(E67+2)/3) -> 19 | H67: ="Q"&INT((MONTH(F67)/4)+1)&"-"&RIGHT(YEAR(F67),2) -> Q3-26 | I67: =MIN(INT(YEARFRAC(F$11,F79)),30) -> 5 | J67: =YEAR(F67) -> 2026 | L67: =IF(I68<iGeneral!F$25,1,L66*(1+L$10/12)) -> 1.0977423 | M67: =IF(I66<iGeneral!F$26,1,M66*(1+M$10/12)) -> 1.0373313 | N67: =IF(I66<iGeneral!F$27,1,N66*(1+N$10/12)) -> 1 | O67: =IFERROR(IF(I66<iGeneral!F$28,1,O66*(1+O$10/12)),1) -> 1 | P67: =IFERROR(IF(DATA!$I67<iGeneral!F$29,1,P66*(1+P$10/12)),1) -> 1 | Z67: {=IFERROR(TRANSPOSE(_xlfn._xlws.SORT(_xlfn._xlws.FILTER($R$11:$R$45,$S$11:$S$45=iMPC!#REF!))),0)} -> 0 | AQ67: Ownership | AR67: Management
E68: =E67+1 -> 58 | F68: =EOMONTH(F67,0)+1 -> 46296 | G68: =INT(INT(E68+2)/3) -> 20 | H68: ="Q"&INT((MONTH(F68)/4)+1)&"-"&RIGHT(YEAR(F68),2) -> Q3-26 | I68: =MIN(INT(YEARFRAC(F$11,F80)),30) -> 5 | J68: =YEAR(F68) -> 2026 | L68: =IF(I69<iGeneral!F$25,1,L67*(1+L$10/12)) -> 1.0995719 | M68: =IF(I67<iGeneral!F$26,1,M67*(1+M$10/12)) -> 1.0381958 | N68: =IF(I67<iGeneral!F$27,1,N67*(1+N$10/12)) -> 1 | O68: =IFERROR(IF(I67<iGeneral!F$28,1,O67*(1+O$10/12)),1) -> 1 | P68: =IFERROR(IF(DATA!$I68<iGeneral!F$29,1,P67*(1+P$10/12)),1) -> 1 | Z68: {=IFERROR(TRANSPOSE(_xlfn._xlws.SORT(_xlfn._xlws.FILTER($R$11:$R$45,$S$11:$S$45=iMPC!#REF!))),0)} -> 0 | AQ68: Ownership | AR68: HOA
E69: =E68+1 -> 59 | F69: =EOMONTH(F68,0)+1 -> 46327 | G69: =INT(INT(E69+2)/3) -> 20 | H69: ="Q"&INT((MONTH(F69)/4)+1)&"-"&RIGHT(YEAR(F69),2) -> Q3-26 | I69: =MIN(INT(YEARFRAC(F$11,F81)),30) -> 5 | J69: =YEAR(F69) -> 2026 | L69: =IF(I70<iGeneral!F$25,1,L68*(1+L$10/12)) -> 1.1014045 | M69: =IF(I68<iGeneral!F$26,1,M68*(1+M$10/12)) -> 1.0390609 | N69: =IF(I68<iGeneral!F$27,1,N68*(1+N$10/12)) -> 1 | O69: =IFERROR(IF(I68<iGeneral!F$28,1,O68*(1+O$10/12)),1) -> 1 | P69: =IFERROR(IF(DATA!$I69<iGeneral!F$29,1,P68*(1+P$10/12)),1) -> 1 | Z69: {=IFERROR(TRANSPOSE(_xlfn._xlws.SORT(_xlfn._xlws.FILTER($R$11:$R$45,$S$11:$S$45=iMPC!#REF!))),0)} -> 0 | AQ69: Ownership | AR69: Legal
E70: =E69+1 -> 60 | F70: =EOMONTH(F69,0)+1 -> 46357 | G70: =INT(INT(E70+2)/3) -> 20 | H70: ="Q"&INT((MONTH(F70)/4)+1)&"-"&RIGHT(YEAR(F70),2) -> Q4-26 | I70: =MIN(INT(YEARFRAC(F$11,F82)),30) -> 5 | J70: =YEAR(F70) -> 2026 | L70: =IF(I71<iGeneral!F$25,1,L69*(1+L$10/12)) -> 1.1032402 | M70: =IF(I69<iGeneral!F$26,1,M69*(1+M$10/12)) -> 1.0399268 | N70: =IF(I69<iGeneral!F$27,1,N69*(1+N$10/12)) -> 1 | O70: =IFERROR(IF(I69<iGeneral!F$28,1,O69*(1+O$10/12)),1) -> 1 | P70: =IFERROR(IF(DATA!$I70<iGeneral!F$29,1,P69*(1+P$10/12)),1) -> 1 | Z70: {=IFERROR(TRANSPOSE(_xlfn._xlws.SORT(_xlfn._xlws.FILTER($R$11:$R$45,$S$11:$S$45=iMPC!#REF!))),0)} -> 0 | AQ70: Ownership | AR70: Accounting
... E72: =E71+1 -> 62 | F72: =EOMONTH(F71,0)+1 -> 46419 | G72: =INT(INT(E72+2)/3) -> 21 | H72: ="Q"&INT((MONTH(F72)/4)+1)&"-"&RIGHT(YEAR(F72),2) -> Q1-27 | I72: =MIN(INT(YEARFRAC(F$11,F84)),30) -> 6 | J72: =YEAR(F72) -> 2027 | L72: =IF(I73<iGeneral!F$25,1,L71*(1+L$10/12)) -> 1.1069207 | M72: =IF(I71<iGeneral!F$26,1,M71*(1+M$10/12)) -> 1.0416608 | N72: =IF(I71<iGeneral!F$27,1,N71*(1+N$10/12)) -> 1 | O72: =IFERROR(IF(I71<iGeneral!F$28,1,O71*(1+O$10/12)),1) -> 1 | P72: =IFERROR(IF(DATA!$I72<iGeneral!F$29,1,P71*(1+P$10/12)),1) -> 1 | Z72: {=IFERROR(TRANSPOSE(_xlfn._xlws.SORT(_xlfn._xlws.FILTER($R$11:$R$45,$S$11:$S$45=iMPC!#REF!))),0)} -> 0 | AQ72: Ownership | AR72: Other
E73: =E72+1 -> 63 | F73: =EOMONTH(F72,0)+1 -> 46447 | G73: =INT(INT(E73+2)/3) -> 21 | H73: ="Q"&INT((MONTH(F73)/4)+1)&"-"&RIGHT(YEAR(F73),2) -> Q1-27 | I73: =MIN(INT(YEARFRAC(F$11,F85)),30) -> 6 | J73: =YEAR(F73) -> 2027 | L73: =IF(I74<iGeneral!F$25,1,L72*(1+L$10/12)) -> 1.1087656 | M73: =IF(I72<iGeneral!F$26,1,M72*(1+M$10/12)) -> 1.0425288 | N73: =IF(I72<iGeneral!F$27,1,N72*(1+N$10/12)) -> 1 | O73: =IFERROR(IF(I72<iGeneral!F$28,1,O72*(1+O$10/12)),1) -> 1 | P73: =IFERROR(IF(DATA!$I73<iGeneral!F$29,1,P72*(1+P$10/12)),1) -> 1 | Z73: {=IFERROR(TRANSPOSE(_xlfn._xlws.SORT(_xlfn._xlws.FILTER($R$11:$R$45,$S$11:$S$45=iMPC!#REF!))),0)} -> 0
E74: =E73+1 -> 64 | F74: =EOMONTH(F73,0)+1 -> 46478 | G74: =INT(INT(E74+2)/3) -> 22 | H74: ="Q"&INT((MONTH(F74)/4)+1)&"-"&RIGHT(YEAR(F74),2) -> Q2-27 | I74: =MIN(INT(YEARFRAC(F$11,F86)),30) -> 6 | J74: =YEAR(F74) -> 2027 | L74: =IF(I75<iGeneral!F$25,1,L73*(1+L$10/12)) -> 1.1106135 | M74: =IF(I73<iGeneral!F$26,1,M73*(1+M$10/12)) -> 1.0433976 | N74: =IF(I73<iGeneral!F$27,1,N73*(1+N$10/12)) -> 1 | O74: =IFERROR(IF(I73<iGeneral!F$28,1,O73*(1+O$10/12)),1) -> 1 | P74: =IFERROR(IF(DATA!$I74<iGeneral!F$29,1,P73*(1+P$10/12)),1) -> 1 | Z74: {=IFERROR(TRANSPOSE(_xlfn._xlws.SORT(_xlfn._xlws.FILTER($R$11:$R$45,$S$11:$S$45=iMPC!#REF!))),0)} -> 0
E75: =E74+1 -> 65 | F75: =EOMONTH(F74,0)+1 -> 46508 | G75: =INT(INT(E75+2)/3) -> 22 | H75: ="Q"&INT((MONTH(F75)/4)+1)&"-"&RIGHT(YEAR(F75),2) -> Q2-27 | I75: =MIN(INT(YEARFRAC(F$11,F87)),30) -> 6 | J75: =YEAR(F75) -> 2027 | L75: =IF(I76<iGeneral!F$25,1,L74*(1+L$10/12)) -> 1.1124646 | M75: =IF(I74<iGeneral!F$26,1,M74*(1+M$10/12)) -> 1.0442671 | N75: =IF(I74<iGeneral!F$27,1,N74*(1+N$10/12)) -> 1 | O75: =IFERROR(IF(I74<iGeneral!F$28,1,O74*(1+O$10/12)),1) -> 1 | P75: =IFERROR(IF(DATA!$I75<iGeneral!F$29,1,P74*(1+P$10/12)),1) -> 1 | Z75: {=IFERROR(TRANSPOSE(_xlfn._xlws.SORT(_xlfn._xlws.FILTER($R$11:$R$45,$S$11:$S$45=iMPC!#REF!))),0)} -> 0
E76: =E75+1 -> 66 | F76: =EOMONTH(F75,0)+1 -> 46539 | G76: =INT(INT(E76+2)/3) -> 22 | H76: ="Q"&INT((MONTH(F76)/4)+1)&"-"&RIGHT(YEAR(F76),2) -> Q2-27 | I76: =MIN(INT(YEARFRAC(F$11,F88)),30) -> 6 | J76: =YEAR(F76) -> 2027 | L76: =IF(I77<iGeneral!F$25,1,L75*(1+L$10/12)) -> 1.1143187 | M76: =IF(I75<iGeneral!F$26,1,M75*(1+M$10/12)) -> 1.0451373 | N76: =IF(I75<iGeneral!F$27,1,N75*(1+N$10/12)) -> 1 | O76: =IFERROR(IF(I75<iGeneral!F$28,1,O75*(1+O$10/12)),1) -> 1 | P76: =IFERROR(IF(DATA!$I76<iGeneral!F$29,1,P75*(1+P$10/12)),1) -> 1 | Z76: {=IFERROR(TRANSPOSE(_xlfn._xlws.SORT(_xlfn._xlws.FILTER($R$11:$R$45,$S$11:$S$45=iMPC!#REF!))),0)} -> 0
E77: =E76+1 -> 67 | F77: =EOMONTH(F76,0)+1 -> 46569 | G77: =INT(INT(E77+2)/3) -> 23 | H77: ="Q"&INT((MONTH(F77)/4)+1)&"-"&RIGHT(YEAR(F77),2) -> Q2-27 | I77: =MIN(INT(YEARFRAC(F$11,F89)),30) -> 6 | J77: =YEAR(F77) -> 2027 | L77: =IF(I78<iGeneral!F$25,1,L76*(1+L$10/12)) -> 1.1161759 | M77: =IF(I76<iGeneral!F$26,1,M76*(1+M$10/12)) -> 1.0460083 | N77: =IF(I76<iGeneral!F$27,1,N76*(1+N$10/12)) -> 1 | O77: =IFERROR(IF(I76<iGeneral!F$28,1,O76*(1+O$10/12)),1) -> 1 | P77: =IFERROR(IF(DATA!$I77<iGeneral!F$29,1,P76*(1+P$10/12)),1) -> 1 | Z77: {=IFERROR(TRANSPOSE(_xlfn._xlws.SORT(_xlfn._xlws.FILTER($R$11:$R$45,$S$11:$S$45=iMPC!#REF!))),0)} -> 0
E78: =E77+1 -> 68 | F78: =EOMONTH(F77,0)+1 -> 46600 | G78: =INT(INT(E78+2)/3) -> 23 | H78: ="Q"&INT((MONTH(F78)/4)+1)&"-"&RIGHT(YEAR(F78),2) -> Q3-27 | I78: =MIN(INT(YEARFRAC(F$11,F90)),30) -> 6 | J78: =YEAR(F78) -> 2027 | L78: =IF(I79<iGeneral!F$25,1,L77*(1+L$10/12)) -> 1.1180362 | M78: =IF(I77<iGeneral!F$26,1,M77*(1+M$10/12)) -> 1.0468799 | N78: =IF(I77<iGeneral!F$27,1,N77*(1+N$10/12)) -> 1 | O78: =IFERROR(IF(I77<iGeneral!F$28,1,O77*(1+O$10/12)),1) -> 1 | P78: =IFERROR(IF(DATA!$I78<iGeneral!F$29,1,P77*(1+P$10/12)),1) -> 1 | Z78: {=IFERROR(TRANSPOSE(_xlfn._xlws.SORT(_xlfn._xlws.FILTER($R$11:$R$45,$S$11:$S$45=iMPC!#REF!))),0)} -> 0
E79: =E78+1 -> 69 | F79: =EOMONTH(F78,0)+1 -> 46631 | G79: =INT(INT(E79+2)/3) -> 23 | H79: ="Q"&INT((MONTH(F79)/4)+1)&"-"&RIGHT(YEAR(F79),2) -> Q3-27 | I79: =MIN(INT(YEARFRAC(F$11,F91)),30) -> 6 | J79: =YEAR(F79) -> 2027 | L79: =IF(I80<iGeneral!F$25,1,L78*(1+L$10/12)) -> 1.1198995 | M79: =IF(I78<iGeneral!F$26,1,M78*(1+M$10/12)) -> 1.0477523 | N79: =IF(I78<iGeneral!F$27,1,N78*(1+N$10/12)) -> 1 | O79: =IFERROR(IF(I78<iGeneral!F$28,1,O78*(1+O$10/12)),1) -> 1 | P79: =IFERROR(IF(DATA!$I79<iGeneral!F$29,1,P78*(1+P$10/12)),1) -> 1 | Z79: {=IFERROR(TRANSPOSE(_xlfn._xlws.SORT(_xlfn._xlws.FILTER($R$11:$R$45,$S$11:$S$45=iMPC!#REF!))),0)} -> 0
E80: =E79+1 -> 70 | F80: =EOMONTH(F79,0)+1 -> 46661 | G80: =INT(INT(E80+2)/3) -> 24 | H80: ="Q"&INT((MONTH(F80)/4)+1)&"-"&RIGHT(YEAR(F80),2) -> Q3-27 | I80: =MIN(INT(YEARFRAC(F$11,F92)),30) -> 6 | J80: =YEAR(F80) -> 2027 | L80: =IF(I81<iGeneral!F$25,1,L79*(1+L$10/12)) -> 1.121766 | M80: =IF(I79<iGeneral!F$26,1,M79*(1+M$10/12)) -> 1.0486255 | N80: =IF(I79<iGeneral!F$27,1,N79*(1+N$10/12)) -> 1 | O80: =IFERROR(IF(I79<iGeneral!F$28,1,O79*(1+O$10/12)),1) -> 1 | P80: =IFERROR(IF(DATA!$I80<iGeneral!F$29,1,P79*(1+P$10/12)),1) -> 1 | Z80: {=IFERROR(TRANSPOSE(_xlfn._xlws.SORT(_xlfn._xlws.FILTER($R$11:$R$45,$S$11:$S$45=iMPC!#REF!))),0)} -> 0
E81: =E80+1 -> 71 | F81: =EOMONTH(F80,0)+1 -> 46692 | G81: =INT(INT(E81+2)/3) -> 24 | H81: ="Q"&INT((MONTH(F81)/4)+1)&"-"&RIGHT(YEAR(F81),2) -> Q3-27 | I81: =MIN(INT(YEARFRAC(F$11,F93)),30) -> 6 | J81: =YEAR(F81) -> 2027 | L81: =IF(I82<iGeneral!F$25,1,L80*(1+L$10/12)) -> 1.1236357 | M81: =IF(I80<iGeneral!F$26,1,M80*(1+M$10/12)) -> 1.0494993 | N81: =IF(I80<iGeneral!F$27,1,N80*(1+N$10/12)) -> 1 | O81: =IFERROR(IF(I80<iGeneral!F$28,1,O80*(1+O$10/12)),1) -> 1 | P81: =IFERROR(IF(DATA!$I81<iGeneral!F$29,1,P80*(1+P$10/12)),1) -> 1 | Z81: {=IFERROR(TRANSPOSE(_xlfn._xlws.SORT(_xlfn._xlws.FILTER($R$11:$R$45,$S$11:$S$45=iMPC!#REF!))),0)} -> 0
E82: =E81+1 -> 72 | F82: =EOMONTH(F81,0)+1 -> 46722 | G82: =INT(INT(E82+2)/3) -> 24 | H82: ="Q"&INT((MONTH(F82)/4)+1)&"-"&RIGHT(YEAR(F82),2) -> Q4-27 | I82: =MIN(INT(YEARFRAC(F$11,F94)),30) -> 6 | J82: =YEAR(F82) -> 2027 | L82: =IF(I83<iGeneral!F$25,1,L81*(1+L$10/12)) -> 1.1255084 | M82: =IF(I81<iGeneral!F$26,1,M81*(1+M$10/12)) -> 1.0503739 | N82: =IF(I81<iGeneral!F$27,1,N81*(1+N$10/12)) -> 1 | O82: =IFERROR(IF(I81<iGeneral!F$28,1,O81*(1+O$10/12)),1) -> 1 | P82: =IFERROR(IF(DATA!$I82<iGeneral!F$29,1,P81*(1+P$10/12)),1) -> 1 | Z82: {=IFERROR(TRANSPOSE(_xlfn._xlws.SORT(_xlfn._xlws.FILTER($R$11:$R$45,$S$11:$S$45=iMPC!#REF!))),0)} -> 0
E83: =E82+1 -> 73 | F83: =EOMONTH(F82,0)+1 -> 46753 | G83: =INT(INT(E83+2)/3) -> 25 | H83: ="Q"&INT((MONTH(F83)/4)+1)&"-"&RIGHT(YEAR(F83),2) -> Q1-28 | I83: =MIN(INT(YEARFRAC(F$11,F95)),30) -> 7 | J83: =YEAR(F83) -> 2028 | L83: =IF(I84<iGeneral!F$25,1,L82*(1+L$10/12)) -> 1.1273842 | M83: =IF(I82<iGeneral!F$26,1,M82*(1+M$10/12)) -> 1.0512492 | N83: =IF(I82<iGeneral!F$27,1,N82*(1+N$10/12)) -> 1 | O83: =IFERROR(IF(I82<iGeneral!F$28,1,O82*(1+O$10/12)),1) -> 1 | P83: =IFERROR(IF(DATA!$I83<iGeneral!F$29,1,P82*(1+P$10/12)),1) -> 1 | Z83: {=IFERROR(TRANSPOSE(_xlfn._xlws.SORT(_xlfn._xlws.FILTER($R$11:$R$45,$S$11:$S$45=iMPC!#REF!))),0)} -> 0
E84: =E83+1 -> 74 | F84: =EOMONTH(F83,0)+1 -> 46784 | G84: =INT(INT(E84+2)/3) -> 25 | H84: ="Q"&INT((MONTH(F84)/4)+1)&"-"&RIGHT(YEAR(F84),2) -> Q1-28 | I84: =MIN(INT(YEARFRAC(F$11,F96)),30) -> 7 | J84: =YEAR(F84) -> 2028 | L84: =IF(I85<iGeneral!F$25,1,L83*(1+L$10/12)) -> 1.1292632 | M84: =IF(I83<iGeneral!F$26,1,M83*(1+M$10/12)) -> 1.0521252 | N84: =IF(I83<iGeneral!F$27,1,N83*(1+N$10/12)) -> 1 | O84: =IFERROR(IF(I83<iGeneral!F$28,1,O83*(1+O$10/12)),1) -> 1 | P84: =IFERROR(IF(DATA!$I84<iGeneral!F$29,1,P83*(1+P$10/12)),1) -> 1 | Z84: {=IFERROR(TRANSPOSE(_xlfn._xlws.SORT(_xlfn._xlws.FILTER($R$11:$R$45,$S$11:$S$45=iMPC!#REF!))),0)} -> 0
... E96: =E95+1 -> 86 | F96: =EOMONTH(F95,0)+1 -> 47150 | G96: =INT(INT(E96+2)/3) -> 29 | H96: ="Q"&INT((MONTH(F96)/4)+1)&"-"&RIGHT(YEAR(F96),2) -> Q1-29 | I96: =MIN(INT(YEARFRAC(F$11,F108)),30) -> 8 | J96: =YEAR(F96) -> 2029 | L96: =IF(I97<iGeneral!F$25,1,L95*(1+L$10/12)) -> 1.1520567 | M96: =IF(I95<iGeneral!F$26,1,M95*(1+M$10/12)) -> 1.0626949 | N96: =IF(I95<iGeneral!F$27,1,N95*(1+N$10/12)) -> 1 | O96: =IFERROR(IF(I95<iGeneral!F$28,1,O95*(1+O$10/12)),1) -> 1 | P96: =IFERROR(IF(DATA!$I96<iGeneral!F$29,1,P95*(1+P$10/12)),1) -> 1 | Z96: {=IFERROR(TRANSPOSE(_xlfn._xlws.SORT(_xlfn._xlws.FILTER($R$11:$R$45,$S$11:$S$45=iMPC!#REF!))),0)} -> 0
E97: =E96+1 -> 87 | F97: =EOMONTH(F96,0)+1 -> 47178 | G97: =INT(INT(E97+2)/3) -> 29 | H97: ="Q"&INT((MONTH(F97)/4)+1)&"-"&RIGHT(YEAR(F97),2) -> Q1-29 | I97: =MIN(INT(YEARFRAC(F$11,F109)),30) -> 8 | J97: =YEAR(F97) -> 2029 | L97: =IF(I98<iGeneral!F$25,1,L96*(1+L$10/12)) -> 1.1539768 | M97: =IF(I96<iGeneral!F$26,1,M96*(1+M$10/12)) -> 1.0635804 | N97: =IF(I96<iGeneral!F$27,1,N96*(1+N$10/12)) -> 1 | O97: =IFERROR(IF(I96<iGeneral!F$28,1,O96*(1+O$10/12)),1) -> 1 | P97: =IFERROR(IF(DATA!$I97<iGeneral!F$29,1,P96*(1+P$10/12)),1) -> 1
E98: =E97+1 -> 88 | F98: =EOMONTH(F97,0)+1 -> 47209 | G98: =INT(INT(E98+2)/3) -> 30 | H98: ="Q"&INT((MONTH(F98)/4)+1)&"-"&RIGHT(YEAR(F98),2) -> Q2-29 | I98: =MIN(INT(YEARFRAC(F$11,F110)),30) -> 8 | J98: =YEAR(F98) -> 2029 | L98: =IF(I99<iGeneral!F$25,1,L97*(1+L$10/12)) -> 1.1559 | M98: =IF(I97<iGeneral!F$26,1,M97*(1+M$10/12)) -> 1.0644668 | N98: =IF(I97<iGeneral!F$27,1,N97*(1+N$10/12)) -> 1 | O98: =IFERROR(IF(I97<iGeneral!F$28,1,O97*(1+O$10/12)),1) -> 1 | P98: =IFERROR(IF(DATA!$I98<iGeneral!F$29,1,P97*(1+P$10/12)),1) -> 1
E99: =E98+1 -> 89 | F99: =EOMONTH(F98,0)+1 -> 47239 | G99: =INT(INT(E99+2)/3) -> 30 | H99: ="Q"&INT((MONTH(F99)/4)+1)&"-"&RIGHT(YEAR(F99),2) -> Q2-29 | I99: =MIN(INT(YEARFRAC(F$11,F111)),30) -> 8 | J99: =YEAR(F99) -> 2029 | L99: =IF(I100<iGeneral!F$25,1,L98*(1+L$10/12)) -> 1.1578265 | M99: =IF(I98<iGeneral!F$26,1,M98*(1+M$10/12)) -> 1.0653538 | N99: =IF(I98<iGeneral!F$27,1,N98*(1+N$10/12)) -> 1 | O99: =IFERROR(IF(I98<iGeneral!F$28,1,O98*(1+O$10/12)),1) -> 1 | P99: =IFERROR(IF(DATA!$I99<iGeneral!F$29,1,P98*(1+P$10/12)),1) -> 1
E100: =E99+1 -> 90 | F100: =EOMONTH(F99,0)+1 -> 47270 | G100: =INT(INT(E100+2)/3) -> 30 | H100: ="Q"&INT((MONTH(F100)/4)+1)&"-"&RIGHT(YEAR(F100),2) -> Q2-29 | I100: =MIN(INT(YEARFRAC(F$11,F112)),30) -> 8 | J100: =YEAR(F100) -> 2029 | L100: =IF(I101<iGeneral!F$25,1,L99*(1+L$10/12)) -> 1.1597563 | M100: =IF(I99<iGeneral!F$26,1,M99*(1+M$10/12)) -> 1.0662416 | N100: =IF(I99<iGeneral!F$27,1,N99*(1+N$10/12)) -> 1 | O100: =IFERROR(IF(I99<iGeneral!F$28,1,O99*(1+O$10/12)),1) -> 1 | P100: =IFERROR(IF(DATA!$I100<iGeneral!F$29,1,P99*(1+P$10/12)),1) -> 1
E101: =E100+1 -> 91 | F101: =EOMONTH(F100,0)+1 -> 47300 | G101: =INT(INT(E101+2)/3) -> 31 | H101: ="Q"&INT((MONTH(F101)/4)+1)&"-"&RIGHT(YEAR(F101),2) -> Q2-29 | I101: =MIN(INT(YEARFRAC(F$11,F113)),30) -> 8 | J101: =YEAR(F101) -> 2029 | L101: =IF(I102<iGeneral!F$25,1,L100*(1+L$10/12)) -> 1.1616892 | M101: =IF(I100<iGeneral!F$26,1,M100*(1+M$10/12)) -> 1.0671301 | N101: =IF(I100<iGeneral!F$27,1,N100*(1+N$10/12)) -> 1 | O101: =IFERROR(IF(I100<iGeneral!F$28,1,O100*(1+O$10/12)),1) -> 1 | P101: =IFERROR(IF(DATA!$I101<iGeneral!F$29,1,P100*(1+P$10/12)),1) -> 1
E102: =E101+1 -> 92 | F102: =EOMONTH(F101,0)+1 -> 47331 | G102: =INT(INT(E102+2)/3) -> 31 | H102: ="Q"&INT((MONTH(F102)/4)+1)&"-"&RIGHT(YEAR(F102),2) -> Q3-29 | I102: =MIN(INT(YEARFRAC(F$11,F114)),30) -> 8 | J102: =YEAR(F102) -> 2029 | L102: =IF(I103<iGeneral!F$25,1,L101*(1+L$10/12)) -> 1.1636253 | M102: =IF(I101<iGeneral!F$26,1,M101*(1+M$10/12)) -> 1.0680194 | N102: =IF(I101<iGeneral!F$27,1,N101*(1+N$10/12)) -> 1 | O102: =IFERROR(IF(I101<iGeneral!F$28,1,O101*(1+O$10/12)),1) -> 1 | P102: =IFERROR(IF(DATA!$I102<iGeneral!F$29,1,P101*(1+P$10/12)),1) -> 1
E103: =E102+1 -> 93 | F103: =EOMONTH(F102,0)+1 -> 47362 | G103: =INT(INT(E103+2)/3) -> 31 | H103: ="Q"&INT((MONTH(F103)/4)+1)&"-"&RIGHT(YEAR(F103),2) -> Q3-29 | I103: =MIN(INT(YEARFRAC(F$11,F115)),30) -> 8 | J103: =YEAR(F103) -> 2029 | L103: =IF(I104<iGeneral!F$25,1,L102*(1+L$10/12)) -> 1.1655647 | M103: =IF(I102<iGeneral!F$26,1,M102*(1+M$10/12)) -> 1.0689094 | N103: =IF(I102<iGeneral!F$27,1,N102*(1+N$10/12)) -> 1 | O103: =IFERROR(IF(I102<iGeneral!F$28,1,O102*(1+O$10/12)),1) -> 1 | P103: =IFERROR(IF(DATA!$I103<iGeneral!F$29,1,P102*(1+P$10/12)),1) -> 1
E104: =E103+1 -> 94 | F104: =EOMONTH(F103,0)+1 -> 47392 | G104: =INT(INT(E104+2)/3) -> 32 | H104: ="Q"&INT((MONTH(F104)/4)+1)&"-"&RIGHT(YEAR(F104),2) -> Q3-29 | I104: =MIN(INT(YEARFRAC(F$11,F116)),30) -> 8 | J104: =YEAR(F104) -> 2029 | L104: =IF(I105<iGeneral!F$25,1,L103*(1+L$10/12)) -> 1.1675073 | M104: =IF(I103<iGeneral!F$26,1,M103*(1+M$10/12)) -> 1.0698002 | N104: =IF(I103<iGeneral!F$27,1,N103*(1+N$10/12)) -> 1 | O104: =IFERROR(IF(I103<iGeneral!F$28,1,O103*(1+O$10/12)),1) -> 1 | P104: =IFERROR(IF(DATA!$I104<iGeneral!F$29,1,P103*(1+P$10/12)),1) -> 1
E105: =E104+1 -> 95 | F105: =EOMONTH(F104,0)+1 -> 47423 | G105: =INT(INT(E105+2)/3) -> 32 | H105: ="Q"&INT((MONTH(F105)/4)+1)&"-"&RIGHT(YEAR(F105),2) -> Q3-29 | I105: =MIN(INT(YEARFRAC(F$11,F117)),30) -> 8 | J105: =YEAR(F105) -> 2029 | L105: =IF(I106<iGeneral!F$25,1,L104*(1+L$10/12)) -> 1.1694532 | M105: =IF(I104<iGeneral!F$26,1,M104*(1+M$10/12)) -> 1.0706917 | N105: =IF(I104<iGeneral!F$27,1,N104*(1+N$10/12)) -> 1 | O105: =IFERROR(IF(I104<iGeneral!F$28,1,O104*(1+O$10/12)),1) -> 1 | P105: =IFERROR(IF(DATA!$I105<iGeneral!F$29,1,P104*(1+P$10/12)),1) -> 1
E106: =E105+1 -> 96 | F106: =EOMONTH(F105,0)+1 -> 47453 | G106: =INT(INT(E106+2)/3) -> 32 | H106: ="Q"&INT((MONTH(F106)/4)+1)&"-"&RIGHT(YEAR(F106),2) -> Q4-29 | I106: =MIN(INT(YEARFRAC(F$11,F118)),30) -> 8 | J106: =YEAR(F106) -> 2029 | L106: =IF(I107<iGeneral!F$25,1,L105*(1+L$10/12)) -> 1.1714022 | M106: =IF(I105<iGeneral!F$26,1,M105*(1+M$10/12)) -> 1.0715839 | N106: =IF(I105<iGeneral!F$27,1,N105*(1+N$10/12)) -> 1 | O106: =IFERROR(IF(I105<iGeneral!F$28,1,O105*(1+O$10/12)),1) -> 1 | P106: =IFERROR(IF(DATA!$I106<iGeneral!F$29,1,P105*(1+P$10/12)),1) -> 1
E107: =E106+1 -> 97 | F107: =EOMONTH(F106,0)+1 -> 47484 | G107: =INT(INT(E107+2)/3) -> 33 | H107: ="Q"&INT((MONTH(F107)/4)+1)&"-"&RIGHT(YEAR(F107),2) -> Q1-30 | I107: =MIN(INT(YEARFRAC(F$11,F119)),30) -> 9 | J107: =YEAR(F107) -> 2030 | L107: =IF(I108<iGeneral!F$25,1,L106*(1+L$10/12)) -> 1.1733546 | M107: =IF(I106<iGeneral!F$26,1,M106*(1+M$10/12)) -> 1.0724769 | N107: =IF(I106<iGeneral!F$27,1,N106*(1+N$10/12)) -> 1 | O107: =IFERROR(IF(I106<iGeneral!F$28,1,O106*(1+O$10/12)),1) -> 1 | P107: =IFERROR(IF(DATA!$I107<iGeneral!F$29,1,P106*(1+P$10/12)),1) -> 1
E108: =E107+1 -> 98 | F108: =EOMONTH(F107,0)+1 -> 47515 | G108: =INT(INT(E108+2)/3) -> 33 | H108: ="Q"&INT((MONTH(F108)/4)+1)&"-"&RIGHT(YEAR(F108),2) -> Q1-30 | I108: =MIN(INT(YEARFRAC(F$11,F120)),30) -> 9 | J108: =YEAR(F108) -> 2030 | L108: =IF(I109<iGeneral!F$25,1,L107*(1+L$10/12)) -> 1.1753102 | M108: =IF(I107<iGeneral!F$26,1,M107*(1+M$10/12)) -> 1.0733706 | N108: =IF(I107<iGeneral!F$27,1,N107*(1+N$10/12)) -> 1 | O108: =IFERROR(IF(I107<iGeneral!F$28,1,O107*(1+O$10/12)),1) -> 1 | P108: =IFERROR(IF(DATA!$I108<iGeneral!F$29,1,P107*(1+P$10/12)),1) -> 1
... E369: =E368+1 -> 359 | F369: =EOMONTH(F368,0)+1 -> 55458 | G369: =INT(INT(E369+2)/3) -> 120 | H369: ="Q"&INT((MONTH(F369)/4)+1)&"-"&RIGHT(YEAR(F369),2) -> Q3-51 | I369: =MIN(INT(YEARFRAC(F$11,F381)),30) -> 30 | J369: =YEAR(F369) -> 2051 | L369: =IF(I370<iGeneral!F$25,1,L368*(1+L$10/12)) -> 1.8151534 | M369: =IF(I368<iGeneral!F$26,1,M368*(1+M$10/12)) -> 1.3340418 | N369: =IF(I368<iGeneral!F$27,1,N368*(1+N$10/12)) -> 1 | O369: =IFERROR(IF(I368<iGeneral!F$28,1,O368*(1+O$10/12)),1) -> 1 | P369: =IFERROR(IF(DATA!$I369<iGeneral!F$29,1,P368*(1+P$10/12)),1) -> 1
E370: =E369+1 -> 360 | F370: =EOMONTH(F369,0)+1 -> 55488 | G370: =INT(INT(E370+2)/3) -> 120 | H370: ="Q"&INT((MONTH(F370)/4)+1)&"-"&RIGHT(YEAR(F370),2) -> Q4-51 | I370: =MIN(INT(YEARFRAC(F$11,F382)),30) -> 30 | J370: =YEAR(F370) -> 2051 | L370: =IF(I373<iGeneral!F$25,1,L369*(1+L$10/12)) -> 1.8181787 | M370: =IF(I369<iGeneral!F$26,1,M369*(1+M$10/12)) -> 1.3351535 | N370: =IF(I369<iGeneral!F$27,1,N369*(1+N$10/12)) -> 1 | O370: =IFERROR(IF(I369<iGeneral!F$28,1,O369*(1+O$10/12)),1) -> 1 | P370: =IFERROR(IF(DATA!$I370<iGeneral!F$29,1,P369*(1+P$10/12)),1) -> 1
I373: 31

Sheet i.Finance
D2: Project Name
D3: Villages at Tortolita
